Workbook

Sheet Revenue Drivers
C2: ='Income Statement '!C2 -> H1'21 | D2: ='Income Statement '!D2 -> H2'21 | E2: ='Income Statement '!E2 -> FY'21 | F2: ='Income Statement '!F2 -> H1'22 | G2: ='Income Statement '!G2 -> H2'22 | H2: ='Income Statement '!H2 -> FY'22 | I2: ='Income Statement '!I2 -> H1'23 | J2: ='Income Statement '!J2 -> H2'23 | ... AC2: ='Income Statement '!AC2 -> FY'29E
B3: Net Sales
B4: Organic Sales | H4: 2716 | I4: 742 | K4: 969 | L4: =L7+L10 -> -67 | N4: ='North America'!N4+Europe!N4+'Asia Pacific'!N4+LATAM!N4+Africa!N4 -> 1358.32 | O4: ='North America'!O4+Europe!O4+'Asia Pacific'!O4+LATAM!O4+Africa!O4 -> 871.92 | Q4: ='North America'!Q4+Europe!Q4+'Asia Pacific'!Q4+LATAM!Q4+Africa!Q4 -> 1473.7772 | R4: ='North America'!R4+Europe!R4+'Asia Pacific'!R4+LATAM!R4+Africa!R4 -> 946.0332 | T4: ='North America'!T4+Europe!T4+'Asia Pacific'!T4+LATAM!T4+Africa!T4 -> 1621.1549 | U4: ='North America'!U4+Europe!U4+'Asia Pacific'!U4+LATAM!U4+Africa!U4 -> 1026.446 | W4: ='North America'!W4+Europe!W4+'Asia Pacific'!W4+LATAM!W4+Africa!W4 -> 1783.2704 | X4: ='North America'!X4+Europe!X4+'Asia Pacific'!X4+LATAM!X4+Africa!X4 -> 1113.6939 | Z4: ='North America'!Z4+Europe!Z4+'Asia Pacific'!Z4+LATAM!Z4+Africa!Z4 -> 1961.5975 | AA4: ='North America'!AA4+Europe!AA4+'Asia Pacific'!AA4+LATAM!AA4+Africa!AA4 -> 1208.3579 | AC4: ='North America'!AC4+Europe!AC4+'Asia Pacific'!AC4+LATAM!AC4+Africa!AC4 -> 2157.7572
B5: Organic growth (%) | H5: 0.21 | K5: =K4/H22 -> 0.062710329 | L5: =L8+L11 -> -0.0060251799 | N5: =N4/K22 -> 0.079373576 | O5: =O4/L22 -> 0.07954023 | Q5: =Q4/N22 -> 0.079422296 | R5: =R4/O22 -> 0.079576058 | T5: =T4/Q22 -> 0.07947447 | U5: =U4/R22 -> 0.079609108 | W5: =W4/T22 -> 0.07952196 | X5: =X4/U22 -> 0.079639593 | Z5: =Z4/W22 -> 0.079565182 | AA5: =AA4/X22 -> 0.07966771 | AC5: =AC4/Z22 -> 0.079604515
B7: Volume | I7: 142 | L7: -573 | N7: ='North America'!N7+Europe!N7+'Asia Pacific'!N7+LATAM!N7+Africa!N7 -> 0 | O7: ='North America'!O7+Europe!O7+'Asia Pacific'!O7+LATAM!O7+Africa!O7 -> 0 | Q7: ='North America'!Q7+Europe!Q7+'Asia Pacific'!Q7+LATAM!Q7+Africa!Q7 -> 0 | R7: ='North America'!R7+Europe!R7+'Asia Pacific'!R7+LATAM!R7+Africa!R7 -> 0 | T7: ='North America'!T7+Europe!T7+'Asia Pacific'!T7+LATAM!T7+Africa!T7 -> 0 | U7: ='North America'!U7+Europe!U7+'Asia Pacific'!U7+LATAM!U7+Africa!U7 -> 0 | W7: ='North America'!W7+Europe!W7+'Asia Pacific'!W7+LATAM!W7+Africa!W7 -> 0 | X7: ='North America'!X7+Europe!X7+'Asia Pacific'!X7+LATAM!X7+Africa!X7 -> 0 | Z7: ='North America'!Z7+Europe!Z7+'Asia Pacific'!Z7+LATAM!Z7+Africa!Z7 -> 0 | AA7: ='North America'!AA7+Europe!AA7+'Asia Pacific'!AA7+LATAM!AA7+Africa!AA7 -> 0 | AC7: ='North America'!AC7+Europe!AC7+'Asia Pacific'!AC7+LATAM!AC7+Africa!AC7 -> 0
B8: Volume Growth (%) | K8: =K7/H22 -> 0 | L8: =L7/I22 -> -0.051528777
B10: Price | I10: 600 | L10: 506 | N10: ='North America'!N10+Europe!N10+'Asia Pacific'!N10+LATAM!N10+Africa!N10 -> 0 | O10: ='North America'!O10+Europe!O10+'Asia Pacific'!O10+LATAM!O10+Africa!O10 -> 0 | Q10: ='North America'!Q10+Europe!Q10+'Asia Pacific'!Q10+LATAM!Q10+Africa!Q10 -> 0 | R10: ='North America'!R10+Europe!R10+'Asia Pacific'!R10+LATAM!R10+Africa!R10 -> 0 | T10: ='North America'!T10+Europe!T10+'Asia Pacific'!T10+LATAM!T10+Africa!T10 -> 0 | U10: ='North America'!U10+Europe!U10+'Asia Pacific'!U10+LATAM!U10+Africa!U10 -> 0 | W10: ='North America'!W10+Europe!W10+'Asia Pacific'!W10+LATAM!W10+Africa!W10 -> 0 | X10: ='North America'!X10+Europe!X10+'Asia Pacific'!X10+LATAM!X10+Africa!X10 -> 0 | Z10: ='North America'!Z10+Europe!Z10+'Asia Pacific'!Z10+LATAM!Z10+Africa!Z10 -> 0 | AA10: ='North America'!AA10+Europe!AA10+'Asia Pacific'!AA10+LATAM!AA10+Africa!AA10 -> 0 | AC10: ='North America'!AC10+Europe!AC10+'Asia Pacific'!AC10+LATAM!AC10+Africa!AC10 -> 0
B11: Price (%) | K11: =K10/H22 -> 0 | L11: =L10/I22 -> 0.045503597
B13: FX | H13: -223 | I13: 669 | K13: 817 | L13: -167 | N13: ='North America'!N13+Europe!N13+'Asia Pacific'!N13+LATAM!N13+Africa!N13 -> 0 | O13: ='North America'!O13+Europe!O13+'Asia Pacific'!O13+LATAM!O13+Africa!O13 -> 0 | Q13: ='North America'!Q13+Europe!Q13+'Asia Pacific'!Q13+LATAM!Q13+Africa!Q13 -> 0 | R13: ='North America'!R13+Europe!R13+'Asia Pacific'!R13+LATAM!R13+Africa!R13 -> 0 | T13: ='North America'!T13+Europe!T13+'Asia Pacific'!T13+LATAM!T13+Africa!T13 -> 0 | U13: ='North America'!U13+Europe!U13+'Asia Pacific'!U13+LATAM!U13+Africa!U13 -> 0 | W13: ='North America'!W13+Europe!W13+'Asia Pacific'!W13+LATAM!W13+Africa!W13 -> 0 | X13: ='North America'!X13+Europe!X13+'Asia Pacific'!X13+LATAM!X13+Africa!X13 -> 0 | Z13: ='North America'!Z13+Europe!Z13+'Asia Pacific'!Z13+LATAM!Z13+Africa!Z13 -> 0 | AA13: ='North America'!AA13+Europe!AA13+'Asia Pacific'!AA13+LATAM!AA13+Africa!AA13 -> 0 | AC13: ='North America'!AC13+Europe!AC13+'Asia Pacific'!AC13+LATAM!AC13+Africa!AC13 -> 0
B14: FX Growth (%) | K14: =K13/H22 -> 0.052873414 | L14: =L13/I22 -> -0.015017986
B16: Scope | H16: 75 | I16: -33 | K16: 182 | L16: -51 | N16: ='North America'!N16+Europe!N16+'Asia Pacific'!N16+LATAM!N16+Africa!N16 -> 84.895 | O16: ='North America'!O16+Europe!O16+'Asia Pacific'!O16+LATAM!O16+Africa!O16 -> 54.495 | Q16: ='North America'!Q16+Europe!Q16+'Asia Pacific'!Q16+LATAM!Q16+Africa!Q16 -> 368.4443 | R16: ='North America'!R16+Europe!R16+'Asia Pacific'!R16+LATAM!R16+Africa!R16 -> 59.127075 | T16: ='North America'!T16+Europe!T16+'Asia Pacific'!T16+LATAM!T16+Africa!T16 -> 405.28873 | U16: ='North America'!U16+Europe!U16+'Asia Pacific'!U16+LATAM!U16+Africa!U16 -> 64.152876 | W16: ='North America'!W16+Europe!W16+'Asia Pacific'!W16+LATAM!W16+Africa!W16 -> 445.8176 | X16: ='North America'!X16+Europe!X16+'Asia Pacific'!X16+LATAM!X16+Africa!X16 -> 69.605871 | Z16: ='North America'!Z16+Europe!Z16+'Asia Pacific'!Z16+LATAM!Z16+Africa!Z16 -> 490.39936 | AA16: ='North America'!AA16+Europe!AA16+'Asia Pacific'!AA16+LATAM!AA16+Africa!AA16 -> 75.52237 | AC16: ='North America'!AC16+Europe!AC16+'Asia Pacific'!AC16+LATAM!AC16+Africa!AC16 -> 539.4393
B17: Scope growth (%) | K17: =K16/H22 -> 0.011778411 | L17: =L16/I22 -> -0.0045863309 | N17: =N16/K22 -> 0.0049608485 | O17: =O16/L22 -> 0.0049712644 | Q17: =Q16/N22 -> 0.019855574 | R17: =R16/O22 -> 0.0049735036 | T17: =T16/Q22 -> 0.019868617 | U17: =U16/R22 -> 0.0049755692 | W17: =W16/T22 -> 0.01988049 | X17: =X16/U22 -> 0.0049774745 | Z17: =Z16/W22 -> 0.019891295 | AA17: =AA16/X22 -> 0.0049792319 | AC17: =AC16/Z22 -> 0.019901129
B19: Hyperinflation | H19: 189 | I19: 85 | K19: 175 | L19: 127 | N19: ='North America'!N19+Europe!N19+'Asia Pacific'!N19+LATAM!N19+Africa!N19 -> 0 | O19: ='North America'!O19+Europe!O19+'Asia Pacific'!O19+LATAM!O19+Africa!O19 -> 0 | Q19: ='North America'!Q19+Europe!Q19+'Asia Pacific'!Q19+LATAM!Q19+Africa!Q19 -> 0 | R19: ='North America'!R19+Europe!R19+'Asia Pacific'!R19+LATAM!R19+Africa!R19 -> 0 | T19: ='North America'!T19+Europe!T19+'Asia Pacific'!T19+LATAM!T19+Africa!T19 -> 0 | U19: ='North America'!U19+Europe!U19+'Asia Pacific'!U19+LATAM!U19+Africa!U19 -> 0 | W19: ='North America'!W19+Europe!W19+'Asia Pacific'!W19+LATAM!W19+Africa!W19 -> 0 | X19: ='North America'!X19+Europe!X19+'Asia Pacific'!X19+LATAM!X19+Africa!X19 -> 0 | Z19: ='North America'!Z19+Europe!Z19+'Asia Pacific'!Z19+LATAM!Z19+Africa!Z19 -> 0 | AA19: ='North America'!AA19+Europe!AA19+'Asia Pacific'!AA19+LATAM!AA19+Africa!AA19 -> 0 | AC19: ='North America'!AC19+Europe!AC19+'Asia Pacific'!AC19+LATAM!AC19+Africa!AC19 -> 0
B20: Hyprinflation (%)
H21: -38 | I21: =11120-9420 -> 1700 | K21: =-(15452-14970) -> -482
B22: Total | E22: 12733 | F22: 7957 | H22: =E22+H4+H13+H16+H19+H21 -> 15452 | I22: =F22+I4+I13+I16+I19+I21 -> 11120 | K22: =H22+K4+K13+K16+K19+K21 -> 17113 | L22: =I22+L4+L13+L16+L19+L21 -> 10962 | N22: =K22+N4+N13+N16+N19+N21 -> 18556.215 | O22: =L22+O4+O13+O16+O19+O21 -> 11888.415 | Q22: =N22+Q4+Q13+Q16+Q19+Q21 -> 20398.436 | R22: =O22+R4+R13+R16+R19+R21 -> 12893.575 | T22: =Q22+T4+T13+T16+T19+T21 -> 22424.88 | U22: =R22+U4+U13+U16+U19+U21 -> 13984.174 | W22: =T22+W4+W13+W16+W19+W21 -> 24653.968 | X22: =U22+X4+X13+X16+X19+X21 -> 15167.474 | Z22: =W22+Z4+Z13+Z16+Z19+Z21 -> 27105.965 | AA22: =X22+AA4+AA13+AA16+AA19+AA21 -> 16451.354 | AC22: =Z22+AC4+AC13+AC16+AC19+AC21 -> 29803.161
K23: =K22/H22-1 -> 0.10749418 | L23: =L22/I22-1 -> -0.014208633 | N23: =N22/K22-1 -> 0.084334424 | O23: =O22/L22-1 -> 0.084511494 | Q23: =Q22/N22-1 -> 0.09927787 | R23: =R22/O22-1 -> 0.084549561 | T23: =T22/Q22-1 -> 0.099343087 | U23: =U22/R22-1 -> 0.084584677 | W23: =W22/T22-1 -> 0.099402449 | X23: =X22/U22-1 -> 0.084617067 | Z23: =Z22/W22-1 -> 0.099456477 | AA23: =AA22/X22-1 -> 0.084646942 | AC23: =AC22/Z22-1 -> 0.099505644

Sheet North America
C2: ='Income Statement '!C2 -> H1'21 | D2: ='Income Statement '!D2 -> H2'21 | E2: ='Income Statement '!E2 -> FY'21 | F2: ='Income Statement '!F2 -> H1'22 | G2: ='Income Statement '!G2 -> H2'22 | H2: ='Income Statement '!H2 -> FY'22 | I2: ='Income Statement '!I2 -> H1'23 | J2: ='Income Statement '!J2 -> H2'23 | ... AC2: ='Income Statement '!AC2 -> FY'29E
B3: Net Sales
B4: Organic Sales | H4: 754 | I4: 88 | K4: 11 | L4: -64 | N4: =N5*K22 -> 536.96 | O4: =O5*L22 -> 326.72 | Q4: =Q5*N22 -> 582.6016 | R4: =R5*O22 -> 354.4912 | T4: =T5*Q22 -> 640.86176 | U4: =U5*R22 -> 384.62295 | W4: =W5*T22 -> 704.94794 | X4: =X5*U22 -> 417.3159 | Z4: =Z5*W22 -> 775.44273 | AA4: =AA5*X22 -> 452.78775 | AC4: =AC5*Z22 -> 852.987
B5: Organic growth (%) | I5: 0.03 | K5: =K4/H22 -> 0.0018184824 | L5: =L4/I22 -> -0.015425404 | N5: =N8+N11 -> 0.08 | O5: =O8+O11 -> 0.08 | Q5: =Q8+Q11 -> 0.08 | R5: =R8+R11 -> 0.08 | T5: =T8+T11 -> 0.08 | U5: =U8+U11 -> 0.08 | W5: =W8+W11 -> 0.08 | X5: =X8+X11 -> 0.08 | Z5: =Z8+Z11 -> 0.08 | AA5: =AA8+AA11 -> 0.08 | AC5: =AC8+AC11 -> 0.08
B7: Volume | L7: -124.47
B8: Volume Growth (%) | L8: =L7/I22 -> -0.03 | N8: 0.04 | O8: 0.04 | Q8: 0.04 | R8: 0.04 | T8: 0.04 | U8: 0.04 | W8: 0.04 | X8: 0.04 | Z8: 0.04 | AA8: 0.04 | AC8: 0.04
B10: Price | L10: =L11*I22 -> 41.49
B11: Price (%) | L11: 0.01 | N11: 0.04 | O11: 0.04 | Q11: 0.04 | R11: 0.04 | T11: 0.04 | U11: 0.04 | W11: 0.04 | X11: 0.04 | Z11: 0.04 | AA11: 0.04 | AC11: 0.04
B13: FX | H13: 97 | I13: 452 | K13: 678 | L13: -3 | N13: =N14*K22 -> 0 | O13: =O14*L22 -> 0 | Q13: =Q14*N22 -> 0 | R13: =R14*O22 -> 0 | T13: =T14*Q22 -> 0 | U13: =U14*R22 -> 0 | W13: =W14*T22 -> 0 | X13: =X14*U22 -> 0 | Z13: =Z14*W22 -> 0 | AA13: =AA14*X22 -> 0 | AC13: =AC14*Z22 -> 0
B14: FX Growth (%) | K14: =K13/H22 -> 0.11208464 | L14: =L13/I22 -> -0.0007230658 | N14: 0 | O14: 0 | Q14: 0 | R14: 0 | T14: 0 | U14: 0 | W14: 0 | X14: 0 | Z14: 0 | AA14: 0 | AC14: 0
B16: Scope | H16: 34 | I16: 13 | K16: 20 | L16: 2 | N16: =N17*K22 -> 33.56 | O16: =O17*L22 -> 20.42 | Q16: =Q17*N22 -> 145.6504 | R16: =R17*O22 -> 22.1557 | T16: =T17*Q22 -> 160.21544 | U16: =U17*R22 -> 24.038934 | W16: =W17*T22 -> 176.23698 | X16: =X17*U22 -> 26.082244 | Z16: =Z17*W22 -> 193.86068 | AA16: =AA17*X22 -> 28.299235 | AC16: =AC17*Z22 -> 213.24675
B17: Scope growth (%) | K17: =K16/H22 -> 0.0033063316 | L17: =L16/I22 -> 0.00048204387 | N17: 0.005 | O17: 0.005 | Q17: 0.02 | R17: 0.005 | T17: 0.02 | U17: 0.005 | W17: 0.02 | X17: 0.005 | Z17: 0.02 | AA17: 0.005 | AC17: 0.02
B19: Hyperinflation | K19: 0 | L19: 0
B20: Hyperinflation (%)
H21: -46 | I21: =4149-3517 -> 632 | K21: -46
B22: Total | E22: 5210 | F22: 2964 | H22: =E22+H4+H13+H16+H19+H21 -> 6049 | I22: =F22+I4+I13+I16+I19+I21 -> 4149 | K22: =H22+K4+K13+K16+K19+K21 -> 6712 | L22: =I22+L4+L13+L16+L19+L21 -> 4084 | N22: =N4+N13+N16+K22 -> 7282.52 | O22: =O4+O13+O16+L22 -> 4431.14 | Q22: =Q4+Q13+Q16+N22 -> 8010.772 | R22: =R4+R13+R16+O22 -> 4807.7869 | T22: =T4+T13+T16+Q22 -> 8811.8492 | U22: =U4+U13+U16+R22 -> 5216.4488 | W22: =W4+W13+W16+T22 -> 9693.0341 | X22: =X4+X13+X16+U22 -> 5659.8469 | Z22: =Z4+Z13+Z16+W22 -> 10662.338 | AA22: =AA4+AA13+AA16+X22 -> 6140.9339 | AC22: =AC4+AC13+AC16+Z22 -> 11728.571
K23: =K22/H22-1 -> 0.10960489 | L23: =L22/I22-1 -> -0.015666426 | N23: =N22/K22-1 -> 0.085 | O23: =O22/L22-1 -> 0.085 | Q23: =Q22/N22-1 -> 0.1 | R23: =R22/O22-1 -> 0.085 | T23: =T22/Q22-1 -> 0.1 | U23: =U22/R22-1 -> 0.085 | W23: =W22/T22-1 -> 0.1 | X23: =X22/U22-1 -> 0.085 | Z23: =Z22/W22-1 -> 0.1 | AA23: =AA22/X22-1 -> 0.085 | AC23: =AC22/Z22-1 -> 0.1

Sheet Europe
C2: ='Income Statement '!C2 -> H1'21 | D2: ='Income Statement '!D2 -> H2'21 | E2: ='Income Statement '!E2 -> FY'21 | F2: ='Income Statement '!F2 -> H1'22 | G2: ='Income Statement '!G2 -> H2'22 | H2: ='Income Statement '!H2 -> FY'22 | I2: ='Income Statement '!I2 -> H1'23 | J2: ='Income Statement '!J2 -> H2'23 | ... AC2: ='Income Statement '!AC2 -> FY'29E
B3: Net Sales
B4: Organic Sales | H4: 766 | I4: 164 | K4: 347 | L4: 78 | N4: =N5*K22 -> 285.52 | O4: =O5*L22 -> 205.2 | Q4: =Q5*N22 -> 309.7892 | R4: =R5*O22 -> 222.642 | T4: =T5*Q22 -> 340.76812 | U4: =U5*R22 -> 241.56657 | W4: =W5*T22 -> 374.84493 | X4: =X5*U22 -> 262.09973 | Z4: =Z5*W22 -> 412.32943 | AA4: =AA5*X22 -> 284.37821 | AC4: =AC5*Z22 -> 453.56237
B5: Organic growth (%) | I5: 0.1 | K5: =K4/H22 -> 0.10803238 | L5: =L4/I22 -> 0.033347584 | N5: =N8+N11 -> 0.08 | O5: =O8+O11 -> 0.08 | Q5: =Q8+Q11 -> 0.08 | R5: =R8+R11 -> 0.08 | T5: =T8+T11 -> 0.08 | U5: =U8+U11 -> 0.08 | W5: =W8+W11 -> 0.08 | X5: =X8+X11 -> 0.08 | Z5: =Z8+Z11 -> 0.08 | AA5: =AA8+AA11 -> 0.08 | AC5: =AC8+AC11 -> 0.08
B7: Volume
B8: Volume Growth (%) | L8: -0.04 | N8: 0.04 | O8: 0.04 | Q8: 0.04 | R8: 0.04 | T8: 0.04 | U8: 0.04 | W8: 0.04 | X8: 0.04 | Z8: 0.04 | AA8: 0.04 | AC8: 0.04
B10: Price
B11: Price (%) | L11: 0.07 | N11: 0.04 | O11: 0.04 | Q11: 0.04 | R11: 0.04 | T11: 0.04 | U11: 0.04 | W11: 0.04 | X11: 0.04 | Z11: 0.04 | AA11: 0.04 | AC11: 0.04
B13: FX | H13: -304 | I13: -13 | K13: -41 | L13: 5 | N13: =N14*K22 -> 0 | O13: =O14*L22 -> 0 | Q13: =Q14*N22 -> 0 | R13: =R14*O22 -> 0 | T13: =T14*Q22 -> 0 | U13: =U14*R22 -> 0 | W13: =W14*T22 -> 0 | X13: =X14*U22 -> 0 | Z13: =Z14*W22 -> 0 | AA13: =AA14*X22 -> 0 | AC13: =AC14*Z22 -> 0
B14: FX Growth (%) | K14: =K13/H22 -> -0.012764633 | L14: =L13/I22 -> 0.0021376657 | N14: 0 | O14: 0 | Q14: 0 | R14: 0 | T14: 0 | U14: 0 | W14: 0 | X14: 0 | Z14: 0 | AA14: 0 | AC14: 0
B16: Scope | H16: 23 | I16: -9 | K16: 20 | L16: 20 | N16: =N17*K22 -> 17.845 | O16: =O17*L22 -> 12.825 | Q16: =Q17*N22 -> 77.4473 | R16: =R17*O22 -> 13.915125 | T16: =T17*Q22 -> 85.19203 | U16: =U17*R22 -> 15.097911 | W16: =W17*T22 -> 93.711233 | X16: =X17*U22 -> 16.381233 | Z16: =Z17*W22 -> 103.08236 | AA16: =AA17*X22 -> 17.773638 | AC16: =AC17*Z22 -> 113.39059
B17: Scope growth (%) | K17: =K16/H22 -> 0.0062266501 | L17: =L16/I22 -> 0.0085506627 | N17: 0.005 | O17: 0.005 | Q17: 0.02 | R17: 0.005 | T17: 0.02 | U17: 0.005 | W17: 0.02 | X17: 0.005 | Z17: 0.02 | AA17: 0.005 | AC17: 0.02
B19: Hyperinflation | H19: 189 | I19: 85 | K19: 175 | L19: 123
B20: Hyperinflation (%)
I21: 360 | K21: -144
B22: Total | E22: 2538 | F22: 1752 | H22: 3212 | I22: =F22+I4+I13+I16+I19+I21 -> 2339 | K22: =H22+K4+K13+K16+K19+K21 -> 3569 | L22: =I22+L4+L13+L16+L19+L21 -> 2565 | N22: =N4+N13+N16+K22 -> 3872.365 | O22: =O4+O13+O16+L22 -> 2783.025 | Q22: =Q4+Q13+Q16+N22 -> 4259.6015 | R22: =R4+R13+R16+O22 -> 3019.5821 | T22: =T4+T13+T16+Q22 -> 4685.5616 | U22: =U4+U13+U16+R22 -> 3276.2466 | W22: =W4+W13+W16+T22 -> 5154.1178 | X22: =X4+X13+X16+U22 -> 3554.7276 | Z22: =Z4+Z13+Z16+W22 -> 5669.5296 | AA22: =AA4+AA13+AA16+X22 -> 3856.8794 | AC22: =AC4+AC13+AC16+Z22 -> 6236.4826
K23: =K22/H22-1 -> 0.1111457 | L23: =L22/I22-1 -> 0.096622488 | N23: =N22/K22-1 -> 0.085 | O23: =O22/L22-1 -> 0.085 | Q23: =Q22/N22-1 -> 0.1 | R23: =R22/O22-1 -> 0.085 | T23: =T22/Q22-1 -> 0.1 | U23: =U22/R22-1 -> 0.085 | W23: =W22/T22-1 -> 0.1 | X23: =X22/U22-1 -> 0.085 | Z23: =Z22/W22-1 -> 0.1 | AA23: =AA22/X22-1 -> 0.085 | AC23: =AC22/Z22-1 -> 0.1

Sheet Asia Pacific
C2: ='Income Statement '!C2 -> H1'21 | D2: ='Income Statement '!D2 -> H2'21 | E2: ='Income Statement '!E2 -> FY'21 | F2: ='Income Statement '!F2 -> H1'22 | G2: ='Income Statement '!G2 -> H2'22 | H2: ='Income Statement '!H2 -> FY'22 | I2: ='Income Statement '!I2 -> H1'23 | J2: ='Income Statement '!J2 -> H2'23 | ... AC2: ='Income Statement '!AC2 -> FY'29E
B3: Net Sales
B4: Organic Sales | H4: 402 | I4: 250 | K4: 353 | L4: 125 | N4: =N5*K22 -> 256 | O4: =O5*L22 -> 176.48 | Q4: =Q5*N22 -> 277.76 | R4: =R5*O22 -> 191.4808 | T4: =T5*Q22 -> 305.536 | U4: =U5*R22 -> 207.75667 | W4: =W5*T22 -> 336.0896 | X4: =X5*U22 -> 225.41598 | Z4: =Z5*W22 -> 369.69856 | AA4: =AA5*X22 -> 244.57634 | AC4: =AC5*Z22 -> 406.66842
B5: Organic growth (%) | K5: =K4/H22 -> 0.12887915 | L5: =L4/I22 -> 0.057630244 | N5: =N8+N11 -> 0.08 | O5: =O8+O11 -> 0.08 | Q5: =Q8+Q11 -> 0.08 | R5: =R8+R11 -> 0.08 | T5: =T8+T11 -> 0.08 | U5: =U8+U11 -> 0.08 | W5: =W8+W11 -> 0.08 | X5: =X8+X11 -> 0.08 | Z5: =Z8+Z11 -> 0.08 | AA5: =AA8+AA11 -> 0.08 | AC5: =AC8+AC11 -> 0.08
B7: Volume
B8: Volume Growth (%) | L8: -0.02 | N8: 0.04 | O8: 0.04 | Q8: 0.04 | R8: 0.04 | T8: 0.04 | U8: 0.04 | W8: 0.04 | X8: 0.04 | Z8: 0.04 | AA8: 0.04 | AC8: 0.04
B10: Price
B11: Price (%) | L11: 0.08 | N11: 0.04 | O11: 0.04 | Q11: 0.04 | R11: 0.04 | T11: 0.04 | U11: 0.04 | W11: 0.04 | X11: 0.04 | Z11: 0.04 | AA11: 0.04 | AC11: 0.04
B13: FX | H13: -4 | I13: 89 | K13: 73 | L13: -23 | N13: =N14*K22 -> 0 | O13: =O14*L22 -> 0 | Q13: =Q14*N22 -> 0 | R13: =R14*O22 -> 0 | T13: =T14*Q22 -> 0 | U13: =U14*R22 -> 0 | W13: =W14*T22 -> 0 | X13: =X14*U22 -> 0 | Z13: =Z14*W22 -> 0 | AA13: =AA14*X22 -> 0 | AC13: =AC14*Z22 -> 0
B14: FX Growth (%) | K14: =K13/H22 -> 0.026652063 | L14: =L13/I22 -> -0.010603965 | N14: 0 | O14: 0 | Q14: 0 | R14: 0 | T14: 0 | U14: 0 | W14: 0 | X14: 0 | Z14: 0 | AA14: 0 | AC14: 0
B16: Scope | I16: -33 | K16: 35 | L16: -65 | N16: =N17*K22 -> 16 | O16: =O17*L22 -> 11.03 | Q16: =Q17*N22 -> 69.44 | R16: =R17*O22 -> 11.96755 | T16: =T17*Q22 -> 76.384 | U16: =U17*R22 -> 12.984792 | W16: =W17*T22 -> 84.0224 | X16: =X17*U22 -> 14.088499 | Z16: =Z17*W22 -> 92.42464 | AA16: =AA17*X22 -> 15.286021 | AC16: =AC17*Z22 -> 101.6671
B17: Scope growth (%) | K17: =K16/H22 -> 0.012778386 | L17: =L16/I22 -> -0.029967727 | N17: 0.005 | O17: 0.005 | Q17: 0.02 | R17: 0.005 | T17: 0.02 | U17: 0.005 | W17: 0.02 | X17: 0.005 | Z17: 0.02 | AA17: 0.005 | AC17: 0.02
B19: Hyperinflation
B20: Hyperinflation (%)
H21: =2739-2884 -> -145 | I21: =2169-1837 -> 332
B22: Total | E22: 2486 | F22: 1531 | H22: 2739 | I22: =F22+I4+I13+I16+I19+I21 -> 2169 | K22: =H22+K4+K13+K16+K19+K21 -> 3200 | L22: =I22+L4+L13+L16+L19+L21 -> 2206 | N22: =N4+N13+N16+K22 -> 3472 | O22: =O4+O13+O16+L22 -> 2393.51 | Q22: =Q4+Q13+Q16+N22 -> 3819.2 | R22: =R4+R13+R16+O22 -> 2596.9584 | T22: =T4+T13+T16+Q22 -> 4201.12 | U22: =U4+U13+U16+R22 -> 2817.6998 | W22: =W4+W13+W16+T22 -> 4621.232 | X22: =X4+X13+X16+U22 -> 3057.2043 | Z22: =Z4+Z13+Z16+W22 -> 5083.3552 | AA22: =AA4+AA13+AA16+X22 -> 3317.0667 | AC22: =AC4+AC13+AC16+Z22 -> 5591.6907
K23: =K22/H22-1 -> 0.1683096 | L23: =L22/I22-1 -> 0.017058552 | N23: =N22/K22-1 -> 0.085 | O23: =O22/L22-1 -> 0.085 | Q23: =Q22/N22-1 -> 0.1 | R23: =R22/O22-1 -> 0.085 | T23: =T22/Q22-1 -> 0.1 | U23: =U22/R22-1 -> 0.085 | W23: =W22/T22-1 -> 0.1 | X23: =X22/U22-1 -> 0.085 | Z23: =Z22/W22-1 -> 0.1 | AA23: =AA22/X22-1 -> 0.085 | AC23: =AC22/Z22-1 -> 0.1

Sheet LATAM
C2: ='Income Statement '!C2 -> H1'21 | D2: ='Income Statement '!D2 -> H2'21 | E2: ='Income Statement '!E2 -> FY'21 | F2: ='Income Statement '!F2 -> H1'22 | G2: ='Income Statement '!G2 -> H2'22 | H2: ='Income Statement '!H2 -> FY'22 | I2: ='Income Statement '!I2 -> H1'23 | J2: ='Income Statement '!J2 -> H2'23 | ... AC2: ='Income Statement '!AC2 -> FY'29E
B3: Net Sales
B4: Organic Sales | H4: 308 | I4: 167 | K4: 142 | L4: -310 | N4: =N5*K22 -> 143.92 | O4: =O5*L22 -> 85.52 | Q4: =Q5*N22 -> 156.1532 | R4: =R5*O22 -> 92.7892 | T4: =T5*Q22 -> 171.76852 | U4: =U5*R22 -> 100.67628 | W4: =W5*T22 -> 188.94537 | X4: =X5*U22 -> 109.23377 | Z4: =Z5*W22 -> 207.83991 | AA4: =AA5*X22 -> 118.51864 | AC4: =AC5*Z22 -> 228.6239
B5: Organic growth (%) | K5: =K4/H22 -> 0.094102054 | L5: =L4/I22 -> -0.23864511 | N5: =N8+N11 -> 0.08 | O5: =O8+O11 -> 0.08 | Q5: =Q8+Q11 -> 0.08 | R5: =R8+R11 -> 0.08 | T5: =T8+T11 -> 0.08 | U5: =U8+U11 -> 0.08 | W5: =W8+W11 -> 0.08 | X5: =X8+X11 -> 0.08 | Z5: =Z8+Z11 -> 0.08 | AA5: =AA8+AA11 -> 0.08 | AC5: =AC8+AC11 -> 0.08
B7: Volume
B8: Volume Growth (%) | L8: -0.19 | N8: 0.04 | O8: 0.04 | Q8: 0.04 | R8: 0.04 | T8: 0.04 | U8: 0.04 | W8: 0.04 | X8: 0.04 | Z8: 0.04 | AA8: 0.04 | AC8: 0.04
B10: Price
B11: Price (%) | L11: -0.04 | N11: 0.04 | O11: 0.04 | Q11: 0.04 | R11: 0.04 | T11: 0.04 | U11: 0.04 | W11: 0.04 | X11: 0.04 | Z11: 0.04 | AA11: 0.04 | AC11: 0.04
B13: FX | H13: -35 | I13: 111 | K13: 145 | L13: 80 | N13: =N14*K22 -> 0 | O13: =O14*L22 -> 0 | Q13: =Q14*N22 -> 0 | R13: =R14*O22 -> 0 | T13: =T14*Q22 -> 0 | U13: =U14*R22 -> 0 | W13: =W14*T22 -> 0 | X13: =X14*U22 -> 0 | Z13: =Z14*W22 -> 0 | AA13: =AA14*X22 -> 0 | AC13: =AC14*Z22 -> 0
B14: FX Growth (%) | K14: =K13/H22 -> 0.096090126 | L14: =L13/I22 -> 0.061585835 | N14: 0 | O14: 0 | Q14: 0 | R14: 0 | T14: 0 | U14: 0 | W14: 0 | X14: 0 | Z14: 0 | AA14: 0 | AC14: 0
B16: Scope | H16: 15 | I16: 3 | K16: 3 | L16: 0 | N16: =N17*K22 -> 8.995 | O16: =O17*L22 -> 5.345 | Q16: =Q17*N22 -> 39.0383 | R16: =R17*O22 -> 5.799325 | T16: =T17*Q22 -> 42.94213 | U16: =U17*R22 -> 6.2922676 | W16: =W17*T22 -> 47.236343 | X16: =X17*U22 -> 6.8271104 | Z16: =Z17*W22 -> 51.959977 | AA16: =AA17*X22 -> 7.4074148 | AC16: =AC17*Z22 -> 57.155975
B17: Scope growth (%) | K17: =K16/H22 -> 0.0019880716 | L17: =L16/I22 -> 0 | N17: 0.005 | O17: 0.005 | Q17: 0.02 | R17: 0.005 | T17: 0.02 | U17: 0.005 | W17: 0.02 | X17: 0.005 | Z17: 0.02 | AA17: 0.005 | AC17: 0.02
B19: Hyperinflation
B20: Hyperinflation (%)
H21: =1682-1509 -> 173 | I21: =1299-1100 -> 199
B22: Total | E22: 1394 | F22: 819 | H22: 1509 | I22: =F22+I4+I13+I16+I19+I21 -> 1299 | K22: =H22+K4+K13+K16+K19+K21 -> 1799 | L22: =I22+L4+L13+L16+L19+L21 -> 1069 | N22: =N4+N13+N16+K22 -> 1951.915 | O22: =O4+O13+O16+L22 -> 1159.865 | Q22: =Q4+Q13+Q16+N22 -> 2147.1065 | R22: =R4+R13+R16+O22 -> 1258.4535 | T22: =T4+T13+T16+Q22 -> 2361.8171 | U22: =U4+U13+U16+R22 -> 1365.4221 | W22: =W4+W13+W16+T22 -> 2597.9989 | X22: =X4+X13+X16+U22 -> 1481.483 | Z22: =Z4+Z13+Z16+W22 -> 2857.7988 | AA22: =AA4+AA13+AA16+X22 -> 1607.409 | AC22: =AC4+AC13+AC16+Z22 -> 3143.5786
K23: =K22/H22-1 -> 0.19218025 | L23: =L22/I22-1 -> -0.17705928 | N23: =N22/K22-1 -> 0.085 | O23: =O22/L22-1 -> 0.085 | Q23: =Q22/N22-1 -> 0.1 | R23: =R22/O22-1 -> 0.085 | T23: =T22/Q22-1 -> 0.1 | U23: =U22/R22-1 -> 0.085 | W23: =W22/T22-1 -> 0.1 | X23: =X22/U22-1 -> 0.085 | Z23: =Z22/W22-1 -> 0.1 | AA23: =AA22/X22-1 -> 0.085 | AC23: =AC22/Z22-1 -> 0.1

Sheet Africa
C2: ='Income Statement '!C2 -> H1'21 | D2: ='Income Statement '!D2 -> H2'21 | E2: ='Income Statement '!E2 -> FY'21 | F2: ='Income Statement '!F2 -> H1'22 | G2: ='Income Statement '!G2 -> H2'22 | H2: ='Income Statement '!H2 -> FY'22 | I2: ='Income Statement '!I2 -> H1'23 | J2: ='Income Statement '!J2 -> H2'23 | ... AC2: ='Income Statement '!AC2 -> FY'29E
B3: Net Sales
B4: Organic Sales | H4: 451 | I4: 52 | K4: 83 | L4: 95 | N4: =N5*K22 -> 135.92 | O4: =O5*L22 -> 78 | Q4: =Q5*N22 -> 147.4732 | R4: =R5*O22 -> 84.63 | T4: =T5*Q22 -> 162.22052 | U4: =U5*R22 -> 91.82355 | W4: =W5*T22 -> 178.44257 | X4: =X5*U22 -> 99.628552 | Z4: =Z5*W22 -> 196.28683 | AA4: =AA5*X22 -> 108.09698 | AC4: =AC5*Z22 -> 215.91551
B5: Organic growth (%) | L5: =L4/I22 -> 0.085354897 | N5: =N8+N11 -> 0.08 | O5: =O8+O11 -> 0.08 | Q5: =Q8+Q11 -> 0.08 | R5: =R8+R11 -> 0.08 | T5: =T8+T11 -> 0.08 | U5: =U8+U11 -> 0.08 | W5: =W8+W11 -> 0.08 | X5: =X8+X11 -> 0.08 | Z5: =Z8+Z11 -> 0.08 | AA5: =AA8+AA11 -> 0.08 | AC5: =AC8+AC11 -> 0.08
B7: Volume
B8: Volume Growth (%) | L8: -0.06 | N8: 0.04 | O8: 0.04 | Q8: 0.04 | R8: 0.04 | T8: 0.04 | U8: 0.04 | W8: 0.04 | X8: 0.04 | Z8: 0.04 | AA8: 0.04 | AC8: 0.04
B10: Price
B11: Price (%) | L11: 0.16 | N11: 0.04 | O11: 0.04 | Q11: 0.04 | R11: 0.04 | T11: 0.04 | U11: 0.04 | W11: 0.04 | X11: 0.04 | Z11: 0.04 | AA11: 0.04 | AC11: 0.04
B13: FX | H13: 24 | I13: 30 | K13: -39 | L13: -229 | N13: =N14*K22 -> 0 | O13: =O14*L22 -> 0 | Q13: =Q14*N22 -> 0 | R13: =R14*O22 -> 0 | T13: =T14*Q22 -> 0 | U13: =U14*R22 -> 0 | W13: =W14*T22 -> 0 | X13: =X14*U22 -> 0 | Z13: =Z14*W22 -> 0 | AA13: =AA14*X22 -> 0 | AC13: =AC14*Z22 -> 0
B14: FX Growth (%) | L14: =L13/I22 -> -0.20575022 | N14: 0 | O14: 0 | Q14: 0 | R14: 0 | T14: 0 | U14: 0 | W14: 0 | X14: 0 | Z14: 0 | AA14: 0 | AC14: 0
B16: Scope | H16: 3 | I16: -73 | K16: 104 | L16: -8 | N16: =N17*K22 -> 8.495 | O16: =O17*L22 -> 4.875 | Q16: =Q17*N22 -> 36.8683 | R16: =R17*O22 -> 5.289375 | T16: =T17*Q22 -> 40.55513 | U16: =U17*R22 -> 5.7389719 | W16: =W17*T22 -> 44.610643 | X16: =X17*U22 -> 6.2267845 | Z16: =Z17*W22 -> 49.071707 | AA16: =AA17*X22 -> 6.7560612 | AC16: =AC17*Z22 -> 53.978878
B17: Scope growth (%) | L17: =L16/I22 -> -0.0071877808 | N17: 0.005 | O17: 0.005 | Q17: 0.02 | R17: 0.005 | T17: 0.02 | U17: 0.005 | W17: 0.02 | X17: 0.005 | Z17: 0.02 | AA17: 0.005 | AC17: 0.02
B19: Hyperinflation | L19: 4
B20: Hyperinflation (%)
H21: 26 | I21: =1113-943 -> 170
B22: Total | E22: 1047 | F22: 868 | H22: 1551 | I22: 1113 | K22: =H22+K4+K13+K16+K19 -> 1699 | L22: =I22+L4+L13+L16+L19 -> 975 | N22: =N4+N13+N16+K22 -> 1843.415 | O22: =O4+O13+O16+L22 -> 1057.875 | Q22: =Q4+Q13+Q16+N22 -> 2027.7565 | R22: =R4+R13+R16+O22 -> 1147.7944 | T22: =T4+T13+T16+Q22 -> 2230.5322 | U22: =U4+U13+U16+R22 -> 1245.3569 | W22: =W4+W13+W16+T22 -> 2453.5854 | X22: =X4+X13+X16+U22 -> 1351.2122 | Z22: =Z4+Z13+Z16+W22 -> 2698.9439 | AA22: =AA4+AA13+AA16+X22 -> 1466.0653 | AC22: =AC4+AC13+AC16+Z22 -> 2968.8383
K23: =K22/H22-1 -> 0.095422308 | L23: =L22/I22-1 -> -0.12398922 | N23: =N22/K22-1 -> 0.085 | O23: =O22/L22-1 -> 0.085 | Q23: =Q22/N22-1 -> 0.1 | R23: =R22/O22-1 -> 0.085 | T23: =T22/Q22-1 -> 0.1 | U23: =U22/R22-1 -> 0.085 | W23: =W22/T22-1 -> 0.1 | X23: =X22/U22-1 -> 0.085 | Z23: =Z22/W22-1 -> 0.1 | AA23: =AA22/X22-1 -> 0.085 | AC23: =AC22/Z22-1 -> 0.1

Sheet Corporate
C2: ='Income Statement '!C2 -> H1'21 | D2: ='Income Statement '!D2 -> H2'21 | E2: ='Income Statement '!E2 -> FY'21 | F2: ='Income Statement '!F2 -> H1'22 | G2: ='Income Statement '!G2 -> H2'22 | H2: ='Income Statement '!H2 -> FY'22 | I2: ='Income Statement '!I2 -> H1'23 | J2: ='Income Statement '!J2 -> H2'23 | ... AC2: ='Income Statement '!AC2 -> FY'29E
B3: Net Sales
B4: Organic Sales | K4: 33 | L4: 9
B5: Organic growth (%) | L5: 0.17
B7: FX | K7: 1 | L7: -229
B8: FX Growth (%)
B10: Scope | L10: -8
B11: Scope growth (%)
B13: Hyperinflation | L13: 4
B14: Hyperinflation (%)
B16: Total | H16: 54 | I16: 1113 | K16: =H16+K4+K7+K10+K13 -> 88 | L16: =I16+L4+L7+L10+L13 -> 889

Sheet Income Statement 
C2: H1'21 | D2: H2'21 | E2: FY'21 | F2: H1'22 | G2: H2'22 | H2: FY'22 | I2: H1'23 | J2: H2'23 | K2: FY'23 | L2: H1'24 | M2: H2'24E | N2: FY'24E | O2: H1'25E | P2: H2'25E | Q2: FY'25E | R2: H1'26E | S2: H2'26E | T2: FY'26E | U2: H1'27E | V2: H2'27E | W2: FY'27E | X2: H1'28E | Y2: H2'28E | Z2: FY'28E | AA2: H1'29E | AB2: H2'29E | AC2: FY'29E
B3: Sales | C3: 10436 | D3: =E3-C3 -> 8717 | E3: 19153 | F3: 11753 | G3: =H3-F3 -> 10695 | H3: 22448 | I3: 15611 | J3: =K3-I3 -> 7904 | K3: 23515 | L3: 15181
B4: Excise Duties | C4: 3562 | D4: =E4-C4 -> 2858 | E4: 6420 | F4: 3796 | G4: =H4-F4 -> 3200 | H4: 6996 | I4: 4491 | J4: =K4-I4 -> 1911 | K4: 6402 | L4: 4219
B5: Net Sales | C5: =C3-C4 -> 6874 | D5: =D3-D4 -> 5859 | E5: =E3-E4 -> 12733 | F5: =F3-F4 -> 7957 | G5: =G3-G4 -> 7495 | H5: =H3-H4 -> 15452 | I5: =I3-I4 -> 11120 | J5: =J3-J4 -> 5993 | ... L5: =L3-L4 -> 10962 | M5: =N5-L5 -> 7594.215 | N5: ='Revenue Drivers'!N22 -> 18556.215 | O5: ='Revenue Drivers'!O22 -> 11888.415 | P5: =Q5-O5 -> 8510.0215 | Q5: ='Revenue Drivers'!Q22 -> 20398.436 | R5: ='Revenue Drivers'!R22 -> 12893.575 | S5: =T5-R5 -> 9531.3049 | T5: ='Revenue Drivers'!T22 -> 22424.88 | U5: ='Revenue Drivers'!U22 -> 13984.174 | V5: =W5-U5 -> 10669.794 | W5: ='Revenue Drivers'!W22 -> 24653.968 | X5: ='Revenue Drivers'!X22 -> 15167.474 | Y5: =Z5-X5 -> 11938.491 | Z5: ='Revenue Drivers'!Z22 -> 27105.965 | AA5: ='Revenue Drivers'!AA22 -> 16451.354 | AB5: =AC5-AA5 -> 13351.807 | AC5: ='Revenue Drivers'!AC22 -> 29803.161
B6: Cost of Sales | C6: 2661 | D6: =E6-C6 -> 2377 | E6: 5038 | F6: 2955 | G6: =H6-F6 -> 3018 | H6: 5973 | I6: 4279 | J6: =K6-I6 -> 2620 | K6: 6899 | L6: 4241 | M6: =M5-M7 -> 3181.486 | N6: =L6+M6 -> 7422.486 | O6: =O5-O7 -> 4160.9452 | P6: =P5-P7 -> 2978.5075 | Q6: =O6+P6 -> 7139.4528 | R6: =R5-R7 -> 4512.7513 | S6: =S5-S7 -> 3335.9567 | T6: =R6+S6 -> 7848.7081 | U6: =U5-U7 -> 4894.461 | V6: =V5-V7 -> 3734.4279 | W6: =U6+V6 -> 8628.8889 | X6: =X5-X7 -> 5308.6159 | Y6: =Y5-Y7 -> 4178.4719 | Z6: =X6+Y6 -> 9487.0877 | AA6: =AA5-AA7 -> 5757.974 | AB6: =AB5-AB7 -> 4673.1325 | AC6: =AA6+AB6 -> 10431.107
B7: Gross Profit | C7: =C5-C6 -> 4213 | D7: =D5-D6 -> 3482 | E7: =E5-E6 -> 7695 | F7: =F5-F6 -> 5002 | G7: =G5-G6 -> 4477 | H7: =H5-H6 -> 9479 | I7: =I5-I6 -> 6841 | J7: =J5-J6 -> 3373 | ... L7: =L5-L6 -> 6721 | M7: =N7-L7 -> 4412.729 | N7: =N5*N8 -> 11133.729 | O7: =O5*O8 -> 7727.4698 | P7: =Q7-O7 -> 5531.514 | Q7: =Q5*Q8 -> 13258.984 | R7: =R5*R8 -> 8380.8239 | S7: =T7-R7 -> 6195.3482 | T7: =T5*T8 -> 14576.172 | U7: =U5*U8 -> 9089.7132 | V7: =W7-U7 -> 6935.3661 | W7: =W5*W8 -> 16025.079 | X7: =X5*X8 -> 9858.8581 | Y7: =Z7-X7 -> 7760.0192 | Z7: =Z5*Z8 -> 17618.877 | AA7: =AA5*AA8 -> 10693.38 | AB7: =AC7-AA7 -> 8678.6747 | AC7: =AC5*AC8 -> 19372.055
B8: Gross Profit Margin (%) | C8: =C7/C5 -> 0.61288915 | D8: =D7/D5 -> 0.59429937 | E8: =E7/E5 -> 0.60433519 | F8: =F7/F5 -> 0.62862888 | G8: =G7/G5 -> 0.59733155 | H8: =H7/H5 -> 0.6134481 | I8: =I7/I5 -> 0.61519784 | J8: =J7/J5 -> 0.56282329 | ... M8: =M7/M5 -> 0.58106453 | N8: 0.6 | O8: 0.65 | P8: =P7/P5 -> 0.65 | Q8: 0.65 | R8: 0.65 | S8: =S7/S5 -> 0.65 | T8: 0.65 | U8: 0.65 | V8: =V7/V5 -> 0.65 | W8: 0.65 | X8: 0.65 | Y8: =Y7/Y5 -> 0.65 | Z8: 0.65 | AA8: 0.65 | AB8: =AB7/AB5 -> 0.65 | AC8: 0.65
B9: Marketing | C9: 1085 | D9: =E9-C9 -> 1078 | E9: 2163 | F9: 1351 | G9: =H9-F9 -> 1370 | H9: 2721 | I9: 1861 | J9: =K9-I9 -> 1190 | K9: 3051 | L9: 1952 | M9: =N9-L9 -> 831.43225 | N9: =N10*N5 -> 2783.4322 | O9: =O10*O5 -> 1783.2622 | P9: =Q9-O9 -> 1276.5032 | Q9: =Q10*Q5 -> 3059.7655 | R9: =R10*R5 -> 1934.0363 | S9: =T9-R9 -> 1429.6957 | T9: =T10*T5 -> 3363.732 | U9: =U10*U5 -> 2097.6261 | V9: =W9-U9 -> 1600.4691 | W9: =W10*W5 -> 3698.0952 | X9: =X10*X5 -> 2275.1211 | Y9: =Z9-X9 -> 1790.7737 | Z9: =Z10*Z5 -> 4065.8947 | AA9: =AA10*AA5 -> 2467.7031 | AB9: =AC9-AA9 -> 2002.7711 | AC9: =AC10*AC5 -> 4470.4742
B10: % of sales | C10: =C9/C5 -> 0.15784114 | D10: =D9/D5 -> 0.18399044 | E10: =E9/E5 -> 0.16987356 | F10: =F9/F5 -> 0.16978761 | G10: =G9/G5 -> 0.18278853 | H10: =H9/H5 -> 0.17609371 | I10: =I9/I5 -> 0.16735612 | J10: =J9/J5 -> 0.19856499 | ... M10: =M9/M5 -> 0.10948232 | N10: 0.15 | O10: 0.15 | P10: =P9/P5 -> 0.15 | Q10: 0.15 | R10: 0.15 | S10: =S9/S5 -> 0.15 | T10: 0.15 | U10: 0.15 | V10: =V9/V5 -> 0.15 | W10: 0.15 | X10: 0.15 | Y10: =Y9/Y5 -> 0.15 | Z10: 0.15 | AA10: 0.15 | AB10: =AB9/AB5 -> 0.15 | AC10: 0.15
B11: Other Operating Item | C11: 889 | D11: =E11-C11 -> 1195 | E11: =2531-E13 -> 2084 | F11: 908 | G11: =H11-F11 -> 795 | H11: =2531-H13 -> 1703 | I11: 1249 | J11: =K11-I11 -> 216 | K11: =2531-K13 -> 1465 | L11: 1452 | M11: =N11-L11 -> 106.72206 | N11: =N12*N7 -> 1558.7221 | O11: =O12*O7 -> 850.02167 | P11: =Q11-O11 -> 873.64621 | Q11: =Q12*Q7 -> 1723.6679 | R11: =R12*R7 -> 921.89063 | S11: =T11-R11 -> 973.01174 | T11: =T12*T7 -> 1894.9024 | U11: =U12*U7 -> 999.86845 | V11: =W11-U11 -> 1083.3919 | W11: =W12*W7 -> 2083.2603 | X11: =X12*X7 -> 1084.4744 | Y11: =Z11-X11 -> 1205.9797 | Z11: =Z12*Z7 -> 2290.454 | AA11: =AA12*AA7 -> 1176.2718 | AB11: =AC11-AA11 -> 1342.0953 | AC11: =AC12*AC7 -> 2518.3671
B12: % of sales | C12: =C11/C5 -> 0.1293279 | D12: =D11/D5 -> 0.20395972 | E12: =E11/E5 -> 0.16366921 | F12: =F11/F5 -> 0.11411336 | G12: =G11/G5 -> 0.10607071 | H12: =H11/H5 -> 0.11021227 | I12: =I11/I5 -> 0.11232014 | J12: =J11/J5 -> 0.036042049 | ... L12: =L11/L5 -> 0.13245758 | M12: =M11/M7 -> 0.024185047 | N12: 0.14 | O12: 0.11 | P12: =P11/P7 -> 0.1579398 | Q12: 0.13 | R12: 0.11 | S12: =S11/S7 -> 0.15705522 | T12: 0.13 | U12: 0.11 | V12: =V11/V7 -> 0.15621264 | W12: 0.13 | X12: 0.11 | Y12: =Y11/Y7 -> 0.15540937 | Z12: 0.13 | AA12: 0.11 | AB12: =AB11/AB7 -> 0.15464289 | AC12: 0.13
B13: D&A | C13: 486 | D13: =E13-C13 -> -39 | E13: 447 | F13: 452 | G13: =H13-F13 -> 376 | H13: 828 | I13: 332 | J13: =K13-I13 -> 734 | K13: 1066 | L13: 411 | M13: =N13-L13 -> 418.812 | N13: ='Balance Sheet'!N62 -> 829.812 | O13: ='Balance Sheet'!O62 -> 417.97975 | P13: =Q13-O13 -> 428.79717 | Q13: ='Balance Sheet'!Q62 -> 846.77692 | R13: ='Balance Sheet'!R62 -> 429.9311 | S13: =T13-R13 -> 442.85595 | T13: ='Balance Sheet'!T62 -> 872.78705 | U13: ='Balance Sheet'!U62 -> 446.03341 | V13: =W13-U13 -> 461.08493 | W13: ='Balance Sheet'!W62 -> 907.11835 | X13: ='Balance Sheet'!X62 -> 466.41005 | Y13: =Z13-X13 -> 483.62082 | Z13: ='Balance Sheet'!Z62 -> 950.03088 | AA13: ='Balance Sheet'!AA62 -> 491.2259 | AB13: =AC13-AA13 -> 510.64139 | AC13: ='Balance Sheet'!AC62 -> 1001.8673
B14: Operating Profit | C14: =C7-C9-C11 -> 2239 | D14: =D7-D9-D11 -> 1209 | E14: =E7-E9-E11 -> 3448 | F14: =F7-F9-F11 -> 2743 | G14: =G7-G9-G11 -> 2312 | H14: =H7-H9-H11 -> 5055 | I14: =I7-I9-I11 -> 3731 | J14: =J7-J9-J11 -> 1967 | ... AC14: =AC7-AC9-AC11 -> 12383.214
B15: EBIT Margin (%) | C15: =C14/C5 -> 0.3257201 | D15: =D14/D5 -> 0.20634921 | E15: =E14/E5 -> 0.27079243 | F15: =F14/F5 -> 0.34472791 | G15: =G14/G5 -> 0.30847231 | H15: =H14/H5 -> 0.32714212 | I15: =I14/I5 -> 0.33552158 | J15: =J14/J5 -> 0.32821625 | ... AC15: =AC14/AC5 -> 0.4155
B16: Non-operating items | C16: 5 | D16: =E16-C16 -> 9 | E16: 14 | F16: -31 | G16: =H16-F16 -> 14 | H16: -17 | I16: 19 | J16: =K16-I16 -> 309 | K16: 328 | L16: -60 | N16: =L16+M16 -> -60
B17: Finance Income | C17: 127 | D17: =E17-C17 -> 151 | E17: 278 | F17: 130 | G17: =H17-F17 -> 367 | H17: 497 | I17: 303 | J17: =K17-I17 -> 37 | K17: 340 | L17: 287 | N17: =L17+M17 -> 287
B18: Finance Charges | C18: -327 | D18: =E18-C18 -> -324 | E18: -651 | F18: -310 | G18: =H18-F18 -> -609 | H18: -919 | I18: -648 | J18: =K18-I18 -> -286 | K18: -934 | L18: -718 | M18: =N18-L18 -> -799.04 | N18: =-'Balance Sheet'!N82 -> -1517.04 | O18: =-'Balance Sheet'!O82 -> -819.04 | P18: =Q18-O18 -> -839.04 | Q18: =-'Balance Sheet'!Q82 -> -1658.08 | R18: =-'Balance Sheet'!R82 -> -859.04 | S18: =T18-R18 -> -879.04 | T18: =-'Balance Sheet'!T82 -> -1738.08 | U18: =-'Balance Sheet'!U82 -> -899.04 | V18: =W18-U18 -> -919.04 | W18: =-'Balance Sheet'!W82 -> -1818.08 | X18: =-'Balance Sheet'!X82 -> -939.04 | Y18: =Z18-X18 -> -959.04 | Z18: =-'Balance Sheet'!Z82 -> -1898.08 | AA18: =-'Balance Sheet'!AA82 -> -979.04 | AB18: =AC18-AA18 -> -999.04 | AC18: =-'Balance Sheet'!AC82 -> -1978.08
B19: Share of after tax results of associates and JVs | C19: 154 | D19: =E19-C19 -> 180 | E19: 334 | F19: 190 | G19: =H19-F19 -> 227 | H19: 417 | I19: 202 | J19: =K19-I19 -> 168 | K19: 370 | L19: 253 | N19: =L19+M19 -> 253
B20: Profit Before Taxes | C20: =C14+C16+C17+C18+C19 -> 2198 | D20: =D14+D16+D17+D18+D19 -> 1225 | E20: =E14+E16+E17+E18+E19 -> 3423 | F20: =F14+F16+F17+F18+F19 -> 2722 | G20: =G14+G16+G17+G18+G19 -> 2311 | H20: =H14+H16+H17+H18+H19 -> 5033 | I20: =I14+I16+I17+I18+I19 -> 3607 | J20: =J14+J16+J17+J18+J19 -> 2195 | ... AC20: =AC14+AC16+AC17+AC18+AC19 -> 10405.134
B21: Taxation | C21: 537 | D21: =E21-C21 -> 370 | E21: 907 | F21: 634 | G21: =H21-F21 -> 415 | H21: 1049 | I21: 766 | J21: =K21-I21 -> 204 | K21: 970 | L21: 737 | M21: =N21-L21 -> 413.90694 | N21: =N20*N22 -> 1150.9069 | O21: =O20*O22 -> 855.02917 | P21: =Q21-O21 -> 508.46491 | Q21: =Q20*Q22 -> 1363.4941 | R21: =R20*R22 -> 933.1714 | S21: =T21-R21 -> 582.72014 | T21: =T20*T22 -> 1515.8915 | U21: =U20*U22 -> 1018.6357 | V21: =W21-U21 -> 666.49303 | W21: =W20*W22 -> 1685.1288 | X21: =X20*X22 -> 1112.0445 | Y21: =Z21-X21 -> 760.84517 | Z21: =Z20*Z22 -> 1872.8897 | AA21: =AA20*AA22 -> 1214.0731 | AB21: =AC21-AA21 -> 866.95366 | AC21: =AC20*AC22 -> 2081.0267
B22: Tax Rate (%) | C22: =C21/C20 -> 0.24431301 | D22: =D21/D20 -> 0.30204082 | E22: =E21/E20 -> 0.26497225 | F22: =F21/F20 -> 0.23291697 | G22: =G21/G20 -> 0.17957594 | H22: =H21/H20 -> 0.2084244 | I22: =I21/I20 -> 0.21236485 | J22: =J21/J20 -> 0.092938497 | ... M22: =M21/M20 -> 0.15470064 | N22: 0.2 | O22: 0.2 | P22: =P21/P20 -> 0.2 | Q22: 0.2 | R22: 0.2 | S22: =S21/S20 -> 0.2 | T22: 0.2 | U22: 0.2 | V22: =V21/V20 -> 0.2 | W22: 0.2 | X22: 0.2 | Y22: =Y21/Y20 -> 0.2 | Z22: 0.2 | AA22: 0.2 | AB22: =AB21/AB20 -> 0.2 | AC22: 0.2
B23: Profit | C23: =C20-C21 -> 1661 | D23: =D20-D21 -> 855 | E23: =E20-E21 -> 2516 | F23: =F20-F21 -> 2088 | G23: =G20-G21 -> 1896 | H23: =H20-H21 -> 3984 | I23: =I20-I21 -> 2841 | J23: =J20-J21 -> 1991 | ... AC23: =AC20-AC21 -> 8324.1069
B25: Non-controlling interests | C25: 81 | D25: =E25-C25 -> 58 | E25: 139 | F25: 123 | G25: =H25-F25 -> -34 | H25: 89 | I25: 132 | J25: =K25-I25 -> -100 | K25: 32 | L25: 132 | M25: =L25 -> 132 | N25: =L25+M25 -> 264
B26: Share of parent | C26: =C23-C25 -> 1580 | D26: =D23-D25 -> 797 | E26: =E23-E25 -> 2377 | F26: =F23-F25 -> 1965 | G26: =G23-G25 -> 1930 | H26: =H23-H25 -> 3895 | I26: =I23-I25 -> 2709 | J26: =J23-J25 -> 2091 | ... AC26: =AC23-AC25 -> 8324.1069
B28: Weighted number of shares
B29: Basic Shares | C29: 2336 | D29: =D26/D33*100 -> 2338.985 | E29: 2337 | F29: 2331 | G29: =G26/G33*100 -> 2304.9124 | H29: 2318 | I29: 2274 | J29: =J26/J33*100 -> 2251.1745 | K29: 2264 | L29: 2242 | M29: =L29 -> 2242 | N29: =M29 -> 2242 | O29: =N29 -> 2242 | P29: =O29 -> 2242 | Q29: =P29 -> 2242 | R29: =Q29 -> 2242 | S29: =R29 -> 2242 | T29: =S29 -> 2242 | ... AC29: =AB29 -> 2242
B30: Dilutive effect | C30: 7 | D30: =D31-D29 -> 9.9900119 | E30: 8 | F30: 8 | G30: =G31-G29 -> 6.0048726 | H30: 7 | I30: 7 | J30: =J31-J29 -> 6.9996032 | K30: 7 | L30: 5
B31: Diluted Shares | C31: =C29+C30 -> 2343 | D31: =D26/D34*100 -> 2348.975 | E31: =E29+E30 -> 2345 | F31: =F29+F30 -> 2339 | G31: =G26/G34*100 -> 2310.9173 | H31: =H29+H30 -> 2325 | I31: =I29+I30 -> 2281 | J31: =J26/J34*100 -> 2258.1741 | K31: =K29+K30 -> 2271 | L31: =L29+L30 -> 2247 | M31: =L31 -> 2247 | N31: =M31 -> 2247 | O31: =N31 -> 2247 | P31: =O31 -> 2247 | Q31: =P31 -> 2247 | R31: =Q31 -> 2247 | S31: =R31 -> 2247 | T31: =S31 -> 2247 | ... AC31: =AB31 -> 2247
B33: Basic EPS | C33: =C26/C29*100 -> 67.636986 | D33: =E33-C33 -> 34.07461 | E33: =E26/E29*100 -> 101.7116 | F33: =F26/F29*100 -> 84.298584 | G33: =H33-F33 -> 83.734203 | H33: =H26/H29*100 -> 168.03279 | I33: =I26/I29*100 -> 119.12929 | J33: =K33-I33 -> 92.884847 | K33: =K26/K29*100 -> 212.01413 | L33: =L26/L29*100 -> 98.572703 | M33: =M26/M29*100 -> 94.987857 | N33: =N26/N29*100 -> 193.56056 | O33: =O26/O29*100 -> 152.54758 | P33: =P26/P29*100 -> 90.716308 | Q33: =Q26/Q29*100 -> 243.26388 | R33: =R26/R29*100 -> 166.4891 | ... AC33: =AC26/AC29*100 -> 371.28041
B34: Diluted EPS | C34: =C26/C31*100 -> 67.434913 | D34: =E34-C34 -> 33.929693 | E34: =E26/E31*100 -> 101.36461 | F34: =F26/F31*100 -> 84.010261 | G34: =H34-F34 -> 83.516621 | H34: =H26/H31*100 -> 167.52688 | I34: =I26/I31*100 -> 118.7637 | J34: =K34-I34 -> 92.596934 | K34: =K26/K31*100 -> 211.36063 | L34: =L26/L31*100 -> 98.35336 | M34: =M26/M31*100 -> 94.776491 | N34: =N26/N31*100 -> 193.12985 | O34: =O26/O31*100 -> 152.20813 | P34: =P26/P31*100 -> 90.514447 | Q34: =Q26/Q31*100 -> 242.72258 | R34: =R26/R31*100 -> 166.11863 | ... AC34: =AC26/AC31*100 -> 370.45424
B37: Adjustments

Sheet Cash Flow
C2: ='Balance Sheet'!C2 -> H1'21 | D2: ='Balance Sheet'!D2 -> H2'21 | E2: ='Balance Sheet'!E2 -> FY'21 | F2: ='Balance Sheet'!F2 -> H1'22 | G2: ='Balance Sheet'!G2 -> H2'22 | H2: ='Balance Sheet'!H2 -> FY'22 | I2: ='Balance Sheet'!I2 -> H1'23 | J2: ='Balance Sheet'!J2 -> H2'23 | ... AC2: ='Balance Sheet'!AC2 -> FY'29E
B3: Cash flows from operating activities
B4: Profit from the period | C4: 1661 | D4: =E4-C4 -> 1138 | E4: 2799 | F4: 2088 | G4: =H4-F4 -> 1250 | H4: 3338 | I4: 2841 | J4: =K4-I4 -> 925 | K4: 3766 | L4: 2342 | M4: ='Income Statement '!M23 -> 2261.6278 | N4: ='Income Statement '!N23 -> 4603.6278 | O4: ='Income Statement '!O23 -> 3420.1167 | P4: ='Income Statement '!P23 -> 2033.8596 | Q4: ='Income Statement '!Q23 -> 5453.9763 | R4: ='Income Statement '!R23 -> 3732.6856 | S4: ='Income Statement '!S23 -> 2330.8806 | T4: ='Income Statement '!T23 -> 6063.5662 | ... AC4: ='Income Statement '!AC23 -> 8324.1069
B5: Taxation | C5: 537 | D5: =E5-C5 -> 370 | E5: 907 | F5: 634 | G5: =H5-F5 -> 415 | H5: 1049 | I5: 766 | J5: =K5-I5 -> 204 | K5: 970 | L5: 737 | M5: ='Income Statement '!M21 -> 413.90694 | N5: ='Income Statement '!N21 -> 1150.9069 | O5: ='Income Statement '!O21 -> 855.02917 | P5: ='Income Statement '!P21 -> 508.46491 | Q5: ='Income Statement '!Q21 -> 1363.4941 | R5: ='Income Statement '!R21 -> 933.1714 | S5: ='Income Statement '!S21 -> 582.72014 | T5: ='Income Statement '!T21 -> 1515.8915 | ... AC5: ='Income Statement '!AC21 -> 2081.0267
B6: Share of after tax results of associates and JVs | C6: -154 | D6: =E6-C6 -> -180 | E6: -334 | F6: -190 | G6: =H6-F6 -> -227 | H6: -417 | I6: -202 | J6: =K6-I6 -> -168 | K6: -370 | L6: -253 | M6: =-'Income Statement '!M19 -> 0 | N6: =-'Income Statement '!N19 -> -253 | O6: =-'Income Statement '!O19 -> 0 | P6: =-'Income Statement '!P19 -> 0 | Q6: =-'Income Statement '!Q19 -> 0 | R6: =-'Income Statement '!R19 -> 0 | S6: =-'Income Statement '!S19 -> 0 | T6: =-'Income Statement '!T19 -> 0 | ... AC6: =-'Income Statement '!AC19 -> 0
B7: Net finance charges | C7: 200 | D7: =E7-C7 -> 173 | E7: 373 | F7: 180 | G7: =H7-F7 -> 242 | H7: 422 | I7: 345 | J7: =K7-I7 -> 249 | K7: 594 | L7: 431 | M7: =-'Income Statement '!M18 -> 799.04 | N7: =-'Income Statement '!N18-'Income Statement '!N17 -> 1230.04 | O7: =-'Income Statement '!O18 -> 819.04 | P7: =-'Income Statement '!P18 -> 839.04 | Q7: =-'Income Statement '!Q18 -> 1658.08 | R7: =-'Income Statement '!R18 -> 859.04 | S7: =-'Income Statement '!S18 -> 879.04 | T7: =-'Income Statement '!T18 -> 1738.08 | U7: =-'Income Statement '!U18 -> 899.04 | V7: =-'Income Statement '!V18 -> 919.04 | ... AC7: =-'Income Statement '!AC18 -> 1978.08
B8: Non-operating items | C8: -5 | D8: =E8-C8 -> -9 | E8: -14 | F8: 31 | G8: =H8-F8 -> -14 | H8: 17 | I8: -19 | J8: =K8-I8 -> -309 | K8: -328 | L8: 60 | M8: =-'Income Statement '!M16 -> 0 | N8: =-'Income Statement '!N16 -> 60 | O8: =-'Income Statement '!O16 -> 0 | P8: =-'Income Statement '!P16 -> 0 | Q8: =-'Income Statement '!Q16 -> 0 | R8: =-'Income Statement '!R16 -> 0 | S8: =-'Income Statement '!S16 -> 0 | T8: =-'Income Statement '!T16 -> 0 | ... AC8: =-'Income Statement '!AC16 -> 0
B9: Operating Profit | C9: =SUM(C4:C8) -> 2239 | D9: =SUM(D4:D8) -> 1492 | E9: =SUM(E4:E8) -> 3731 | F9: =SUM(F4:F8) -> 2743 | G9: =SUM(G4:G8) -> 1666 | H9: =SUM(H4:H8) -> 4409 | I9: =SUM(I4:I8) -> 3731 | J9: =SUM(J4:J8) -> 901 | ... AC9: =SUM(AC4:AC8) -> 12383.214
B10: Increase in inventories | C10: -112 | D10: =E10-C10 -> -331 | E10: -443 | F10: -187 | G10: =H10-F10 -> -553 | H10: -740 | I10: -552 | J10: =K10-I10 -> -123 | K10: -675 | L10: -82 | M10: ='Balance Sheet'!L16-'Balance Sheet'!M16 -> -300.0082 | N10: =L10+M10 -> -382.0082 | O10: ='Balance Sheet'!N16-'Balance Sheet'!O16 -> -1259.8418 | P10: ='Balance Sheet'!O16-'Balance Sheet'!P16 -> 1619.7777 | Q10: =O10+P10 -> 359.9359 | R10: ='Balance Sheet'!Q16-'Balance Sheet'!R16 -> -2583.63 | S10: ='Balance Sheet'!R16-'Balance Sheet'!S16 -> 1612.0475 | T10: =R10+S10 -> -971.58257 | U10: ='Balance Sheet'!T16-'Balance Sheet'!U16 -> -2657.8272 | V10: ='Balance Sheet'!U16-'Balance Sheet'!V16 -> 1589.0864 | W10: =U10+V10 -> -1068.7408 | X10: ='Balance Sheet'!W16-'Balance Sheet'!X16 -> -2684.0193 | Y10: ='Balance Sheet'!X16-'Balance Sheet'!Y16 -> 1543.9126 | Z10: =X10+Y10 -> -1140.1067 | AA10: ='Balance Sheet'!Z16-'Balance Sheet'!AA16 -> -2814.7688 | AB10: ='Balance Sheet'!AA16-'Balance Sheet'!AB16 -> 1486.0842 | AC10: =AA10+AB10 -> -1328.6846
B11: Increase in trade and other receivables | C11: -1078 | D11: =E11-C11 -> 632 | E11: -446 | F11: -976 | G11: =H11-F11 -> 598 | H11: -378 | I11: -1191 | J11: =K11-I11 -> 1312 | K11: 121 | L11: -1106 | M11: ='Balance Sheet'!L17-'Balance Sheet'!M17 -> 703.54202 | N11: =L11+M11 -> -402.45798 | O11: ='Balance Sheet'!N17-'Balance Sheet'!O17 -> -1074.334 | P11: ='Balance Sheet'!O17-'Balance Sheet'!P17 -> 703.44632 | Q11: =O11+P11 -> -370.8877 | R11: ='Balance Sheet'!Q17-'Balance Sheet'!R17 -> -1122.0336 | S11: ='Balance Sheet'!R17-'Balance Sheet'!S17 -> 700.08918 | T11: =R11+S11 -> -421.94443 | U11: ='Balance Sheet'!T17-'Balance Sheet'!U17 -> -1154.2564 | V11: ='Balance Sheet'!U17-'Balance Sheet'!V17 -> 690.11752 | W11: =U11+V11 -> -464.13887 | X11: ='Balance Sheet'!W17-'Balance Sheet'!X17 -> -1165.6312 | Y11: ='Balance Sheet'!X17-'Balance Sheet'!Y17 -> 670.4992 | Z11: =X11+Y11 -> -495.13205 | AA11: ='Balance Sheet'!Z17-'Balance Sheet'!AA17 -> -1222.4139 | AB11: ='Balance Sheet'!AA17-'Balance Sheet'!AB17 -> 645.38514 | AC11: =AA11+AB11 -> -577.02875
B12: Increase in trade and other payables | C12: 1161 | D12: =E12-C12 -> 59 | E12: 1220 | F12: 653 | G12: =H12-F12 -> 286 | H12: 939 | I12: 131 | J12: =K12-I12 -> -752 | K12: -621 | L12: 469 | M12: ='Balance Sheet'!M30-'Balance Sheet'!L30 -> -910.86726 | N12: =L12+M12 -> -441.86726 | O12: ='Balance Sheet'!O30-'Balance Sheet'!N30 -> 800.77276 | P12: ='Balance Sheet'!P30-'Balance Sheet'!O30 -> -1020.46 | Q12: =O12+P12 -> -219.6872 | R12: ='Balance Sheet'!R30-'Balance Sheet'!Q30 -> 1627.6869 | S12: ='Balance Sheet'!S30-'Balance Sheet'!R30 -> -1015.5899 | T12: =R12+S12 -> 612.09702 | U12: ='Balance Sheet'!U30-'Balance Sheet'!T30 -> 1674.4311 | V12: ='Balance Sheet'!V30-'Balance Sheet'!U30 -> -1001.1244 | W12: =U12+V12 -> 673.30672 | X12: ='Balance Sheet'!X30-'Balance Sheet'!W30 -> 1690.9322 | Y12: ='Balance Sheet'!Y30-'Balance Sheet'!X30 -> -972.66495 | Z12: =X12+Y12 -> 718.26721 | AA12: ='Balance Sheet'!AA30-'Balance Sheet'!Z30 -> 1773.3044 | AB12: ='Balance Sheet'!AB30-'Balance Sheet'!AA30 -> -936.23305 | AC12: =AA12+AB12 -> 837.07132
B13: Net change in working capital | C13: =C10+C11+C12 -> -29 | D13: =D10+D11+D12 -> 360 | E13: =E10+E11+E12 -> 331 | F13: =F10+F11+F12 -> -510 | G13: =G10+G11+G12 -> 331 | H13: =H10+H11+H12 -> -179 | I13: =I10+I11+I12 -> -1612 | J13: =J10+J11+J12 -> 437 | ... AC13: =AC10+AC11+AC12 -> -1068.6421
B14: D&A | C14: 219 | D14: =E14-C14 -> 228 | E14: 447 | F14: 224 | G14: =H14-F14 -> 604 | H14: 828 | I14: 332 | J14: =K14-I14 -> 734 | K14: 1066 | L14: 411 | M14: ='Income Statement '!M13 -> 418.812 | N14: =L14+M14 -> 829.812 | O14: ='Income Statement '!O13 -> 417.97975 | P14: ='Income Statement '!P13 -> 428.79717 | Q14: =O14+P14 -> 846.77692 | R14: ='Income Statement '!R13 -> 429.9311 | S14: ='Income Statement '!S13 -> 442.85595 | T14: =R14+S14 -> 872.78705 | U14: ='Income Statement '!U13 -> 446.03341 | V14: ='Income Statement '!V13 -> 461.08493 | W14: =U14+V14 -> 907.11835 | X14: ='Income Statement '!X13 -> 466.41005 | Y14: ='Income Statement '!Y13 -> 483.62082 | Z14: =X14+Y14 -> 950.03088 | AA14: ='Income Statement '!AA13 -> 491.2259 | AB14: ='Income Statement '!AB13 -> 510.64139 | AC14: =AA14+AB14 -> 1001.8673
B15: Dividends Received | C15: 82 | D15: =E15-C15 -> 208 | E15: 290 | F15: 1 | G15: =H15-F15 -> 189 | H15: 190 | I15: 5 | J15: =K15-I15 -> 214 | K15: 219 | L15: 5 | N15: =L15+M15 -> 5 | Q15: =O15+P15 -> 0 | T15: =R15+S15 -> 0 | W15: =U15+V15 -> 0 | Z15: =X15+Y15 -> 0 | AC15: =AA15+AB15 -> 0
B16: Post employment payments | C16: -14 | D16: =E16-C16 -> -16 | E16: -30 | F16: -23 | G16: =H16-F16 -> -66 | H16: -89 | I16: -27 | J16: =K16-I16 -> 2 | K16: -25 | L16: -24 | N16: =L16+M16 -> -24 | Q16: =O16+P16 -> 0 | T16: =R16+S16 -> 0 | W16: =U16+V16 -> 0 | Z16: =X16+Y16 -> 0 | AC16: =AA16+AB16 -> 0
B17: Other items | C17: -1 | D17: =E17-C17 -> 89 | E17: 88 | F17: 34 | G17: =H17-F17 -> 19 | H17: 53 | I17: 9 | J17: =K17-I17 -> 53 | K17: 62 | L17: 59 | N17: =L17+M17 -> 59 | Q17: =O17+P17 -> 0 | T17: =R17+S17 -> 0 | W17: =U17+V17 -> 0 | Z17: =X17+Y17 -> 0 | AC17: =AA17+AB17 -> 0
B18: Cash generated from operations | C18: =SUM(C14:C17) -> 286 | D18: =SUM(D14:D17) -> 509 | E18: =SUM(E14:E17) -> 795 | F18: =SUM(F14:F17) -> 236 | G18: =SUM(G14:G17) -> 746 | H18: =SUM(H14:H17) -> 982 | I18: =SUM(I14:I17) -> 319 | J18: =SUM(J14:J17) -> 1003 | ... AC18: =SUM(AC14:AC17) -> 1001.8673
B19: Interest Received | C19: 84 | D19: =E19-C19 -> 5 | E19: 89 | F19: 41 | G19: =H19-F19 -> 69 | H19: 110 | I19: 78 | J19: =K19-I19 -> 53 | K19: 131 | L19: 91 | N19: =L19+M19 -> 91
B20: Interest Paid | C20: -266 | D20: =E20-C20 -> -174 | E20: -440 | F20: -185 | G20: =H20-F20 -> -253 | H20: -438 | I20: -293 | J20: =K20-I20 -> -392 | K20: -685 | L20: -443 | M20: =-M7 -> -799.04 | N20: =L20+M20 -> -1242.04 | O20: =-O7 -> -819.04 | P20: =-P7 -> -839.04 | Q20: =O20+P20 -> -1658.08 | R20: =-R7 -> -859.04 | S20: =-S7 -> -879.04 | T20: =R20+S20 -> -1738.08 | U20: =-U7 -> -899.04 | V20: =-V7 -> -919.04 | W20: =U20+V20 -> -1818.08 | X20: =-X7 -> -939.04 | Y20: =-Y7 -> -959.04 | Z20: =X20+Y20 -> -1898.08 | AA20: =-AA7 -> -979.04 | AB20: =-AB7 -> -999.04 | AC20: =AA20+AB20 -> -1978.08 | AG20: 3654 | AH20: 3935 | AI20: 1472 | AJ20: 1552 | AK20: 3024 | AL20: 4319.1063
B21: Taxation Paid | C21: -316 | D21: =E21-C21 -> -536 | E21: -852 | F21: -378 | G21: =H21-F21 -> -571 | H21: -949 | I21: -751 | J21: =K21-I21 -> -450 | K21: -1201 | L21: -551 | M21: =-M5 -> -413.90694 | N21: =L21+M21 -> -964.90694 | O21: =-O5 -> -855.02917 | P21: =-P5 -> -508.46491 | Q21: =O21+P21 -> -1363.4941 | R21: =-R5 -> -933.1714 | S21: =-S5 -> -582.72014 | T21: =R21+S21 -> -1515.8915 | U21: =-U5 -> -1018.6357 | V21: =-V5 -> -666.49303 | W21: =U21+V21 -> -1685.1288 | X21: =-X5 -> -1112.0445 | Y21: =-Y5 -> -760.84517 | Z21: =X21+Y21 -> -1872.8897 | AA21: =-AA5 -> -1214.0731 | AB21: =-AB5 -> -866.95366 | AC21: =AA21+AB21 -> -2081.0267
B22: Net Cash Flow from Operating Activities | C22: =C9+C13+C18+C19+C20+C21 -> 1998 | D22: =D9+D13+D18+D19+D20+D21 -> 1656 | E22: =E9+E13+E18+E19+E20+E21 -> 3654 | F22: =F9+F13+F18+F19+F20+F21 -> 1947 | G22: =G9+G13+G18+G19+G20+G21 -> 1988 | H22: =H9+H13+H18+H19+H20+H21 -> 3935 | I22: =I9+I13+I18+I19+I20+I21 -> 1472 | J22: =J9+J13+J18+J19+J20+J21 -> 1552 | ... AC22: =AC9+AC13+AC18+AC19+AC20+AC21 -> 8257.3321
B24: Cash Flows from investing activities
B25: Disposal of PP&E | C25: 8 | D25: =E25-C25 -> 5 | E25: 13 | F25: 7 | G25: =H25-F25 -> 10 | H25: 17 | I25: 8 | J25: =K25-I25 -> 5 | K25: 13 | L25: 7 | N25: =L25+M25 -> 7
B26: Capex | C26: -250 | D26: =E26-C26 -> -376 | E26: -626 | F26: -382 | G26: =H26-F26 -> -715 | H26: -1097 | I26: -514 | J26: =K26-I26 -> -666 | K26: -1180 | L26: -582 | M26: =-'Balance Sheet'!M59 -> -402.4934 | N26: =L26+M26 -> -984.49339 | O26: =-'Balance Sheet'!O59 -> -630.086 | P26: =-'Balance Sheet'!P59 -> -451.03114 | Q26: =O26+P26 -> -1081.1171 | R26: =-'Balance Sheet'!R59 -> -683.35949 | S26: =-'Balance Sheet'!S59 -> -505.15916 | T26: =R26+S26 -> -1188.5186 | U26: =-'Balance Sheet'!U59 -> -741.16123 | V26: =-'Balance Sheet'!V59 -> -565.49908 | W26: =U26+V26 -> -1306.6603 | X26: =-'Balance Sheet'!X59 -> -803.87612 | Y26: =-'Balance Sheet'!Y59 -> -632.74002 | Z26: =X26+Y26 -> -1436.6161 | AA26: =-'Balance Sheet'!AA59 -> -871.92178 | AB26: =-'Balance Sheet'!AB59 -> -707.64578 | AC26: =AA26+AB26 -> -1579.5676
B27: Movements in loans and other investments | C27: -3 | D27: =E27-C27 -> -1 | E27: -4 | F27: 3 | G27: =H27-F27 -> -75 | H27: -72 | I27: -2 | J27: =K27-I27 -> -55 | K27: -57 | L27: -109 | N27: =L27+M27 -> -109
B28: Sale of businesses and brands | C28: 5 | D28: =E28-C28 -> 9 | E28: 14 | F28: 2 | G28: =H28-F28 -> 80 | H28: 82 | I28: 111 | J28: =K28-I28 -> 351 | K28: 462 | L28: 18 | N28: =L28+M28 -> 18
B29: Acquisition of subsidiaries | C29: -364 | D29: =E29-C29 -> -86 | E29: -450 | F29: -110 | G29: =H29-F29 -> -96 | H29: -206 | I29: -129 | J29: =K29-I29 -> -213 | K29: -342 | L29: -3 | N29: =L29+M29 -> -3
B30: Investment in associates and JVs | C30: 0 | D30: =E30-C30 -> -38 | E30: -38 | F30: -24 | G30: =H30-F30 -> -41 | H30: -65 | I30: -38 | J30: =K30-I30 -> -55 | K30: -93 | L30: -51 | N30: =L30+M30 -> -51
B31: Net Cashflow from investing activities | C31: =SUM(C25:C30) -> -604 | D31: =SUM(D25:D30) -> -487 | E31: =SUM(E25:E30) -> -1091 | F31: =SUM(F25:F30) -> -504 | G31: =SUM(G25:G30) -> -837 | H31: =SUM(H25:H30) -> -1341 | I31: =SUM(I25:I30) -> -564 | J31: =SUM(J25:J30) -> -633 | ... AC31: =SUM(AC25:AC30) -> -1579.5676
B33: Cash Flows from financing activities
B34: Share buyback | C34: 0 | D34: =E34-C34 -> -109 | E34: -109 | F34: -538 | G34: =H34-F34 -> -1746 | H34: -2284 | I34: -655 | J34: =K34-I34 -> -726 | K34: -1381 | L34: -480 | N34: =L34+M34 -> -480
B35: Net sale of own shares for share schemes | C35: 9 | D35: =E35-C35 -> 40 | E35: 49 | F35: 42 | G35: =H35-F35 -> -24 | H35: 18 | I35: 12 | J35: =K35-I35 -> 17 | K35: 29 | L35: 5 | N35: =L35+M35 -> 5
B36: Purchase of treasury shares in respect of subsidiaries | C36: 0 | D36: =E36-C36 -> 0 | E36: 0 | F36: -13 | G36: =H36-F36 -> -2 | H36: -15 | J36: =K36-I36 -> 0 | K36: 0 | N36: =L36+M36 -> 0
B37: Dividends paid to non-controlling interests | C37: -53 | D37: =E37-C37 -> -24 | E37: -77 | F37: -51 | G37: =H37-F37 -> -30 | H37: -81 | I37: -94 | J37: =K37-I37 -> -3 | K37: -97 | L37: -71 | N37: =L37+M37 -> -71
B38: Proceeds from bonds | C38: 1031 | D38: =E38-C38 -> 0 | E38: 1031 | F38: 0 | G38: =H38-F38 -> 2263 | H38: 2263 | I38: 1989 | J38: =K38-I38 -> 240 | K38: 2229 | L38: 1690 | N38: =L38+M38 -> 1690
B39: Repayment of bonds | C39: -1247 | D39: =E39-C39 -> 0 | E39: -1247 | F39: -769 | G39: =H39-F39 -> -752 | H39: -1521 | I39: -300 | J39: =K39-I39 -> -1040 | K39: -1340 | L39: -1132 | N39: =L39+M39 -> -1132
B40: Purchase of non-controlling interests | C40: -34 | D40: =E40-C40 -> -8 | E40: -42 | F40: 0 | G40: =H40-F40 -> 0 | H40: 0 | J40: =K40-I40 -> -146 | K40: -146 | M40: 132 | N40: =L40+M40 -> 132
B41: Cash inflow from other borrowings | C41: 0 | D41: =E41-C41 -> 34 | E41: 34 | F41: 136 | G41: =H41-F41 -> 367 | H41: 503 | I41: 173 | J41: =K41-I41 -> 260 | K41: 433 | L41: 470 | M41: ='Balance Sheet'!M37-'Balance Sheet'!L37 -> 500 | N41: =L41+M41 -> 970 | O41: ='Balance Sheet'!O37-'Balance Sheet'!N37 -> 500 | P41: ='Balance Sheet'!P37-'Balance Sheet'!O37 -> 500 | Q41: =O41+P41 -> 1000 | R41: ='Balance Sheet'!R37-'Balance Sheet'!Q37 -> 500 | S41: ='Balance Sheet'!S37-'Balance Sheet'!R37 -> 500 | T41: =R41+S41 -> 1000 | U41: ='Balance Sheet'!U37-'Balance Sheet'!T37 -> 500 | V41: ='Balance Sheet'!V37-'Balance Sheet'!U37 -> 500 | W41: =U41+V41 -> 1000 | X41: ='Balance Sheet'!X37-'Balance Sheet'!W37 -> 500 | Y41: ='Balance Sheet'!Y37-'Balance Sheet'!X37 -> 500 | Z41: =X41+Y41 -> 1000 | AA41: ='Balance Sheet'!AA37-'Balance Sheet'!Z37 -> 500 | AB41: ='Balance Sheet'!AB37-'Balance Sheet'!AA37 -> 500 | AC41: =AA41+AB41 -> 1000
B42: Cash outflow from other borrowings | C42: -345 | D42: =E42-C42 -> -442 | E42: -787 | F42: -98 | G42: =H42-F42 -> -326 | H42: -424 | I42: -206 | J42: =K42-I42 -> -168 | K42: -374 | L42: -801 | N42: =L42+M42 -> -801
B43: Equity Dividend Paid | C43: -992 | D43: =E43-C43 -> -654 | E43: -1646 | F43: -1040 | G43: =H43-F43 -> -678 | H43: -1718 | I43: -1194 | J43: =K43-I43 -> -567 | K43: -1761 | L43: -1348 | N43: =L43+M43 -> -1348
B44: Net Cashflow from financing activities | C44: =SUM(C34:C43) -> -1631 | D44: =SUM(D34:D43) -> -1163 | E44: =SUM(E34:E43) -> -2794 | F44: =SUM(F34:F43) -> -2331 | G44: =SUM(G34:G43) -> -928 | H44: =SUM(H34:H43) -> -3259 | I44: =SUM(I34:I43) -> -275 | J44: =SUM(J34:J43) -> -2133 | ... AC44: =SUM(AC34:AC43) -> 1000
B45: Net (decrease)/increase in net cash and cash equivalents | C45: =C22+C31+C44 -> -237 | D45: =D22+D31+D44 -> 6 | E45: =E22+E31+E44 -> -231 | F45: =F22+F31+F44 -> -888 | G45: =G22+G31+G44 -> 223 | H45: =H22+H31+H44 -> -665 | I45: =I22+I31+I44 -> 633 | J45: =J22+J31+J44 -> -1214 | ... AC45: =AC22+AC31+AC44 -> 7677.7645
B46: FX | C46: -237 | D46: =E46-C46 -> -48 | E46: -285 | F46: 14 | G46: =H46-F46 -> 225 | H46: 239 | I46: -25 | J46: =K46-I46 -> -202 | K46: -227 | L46: -45 | N46: =L46+M46 -> -45
B47: Reclassification to assets held for sale | D47: =E47-C47 -> 0 | G47: =H47-F47 -> 0 | I47: -57 | J47: =K47-I47 -> 57 | L47: 0 | N47: =L47+M47 -> 0
B48: Opening Cash | C48: 3153 | D48: =C49 -> 2680 | E48: 3153 | F48: 2637 | G48: =F49 -> 1763 | H48: =E49 -> 2637 | I48: 2675 | J48: =I49 -> 3226 | K48: =H49 -> 2211 | L48: 1768 | M48: =L49-L53 -> 1529 | N48: =L48-L53 -> 1815 | O48: =N49 -> 3931.6129 | P48: =O49 -> 6106.2203 | Q48: =O48 -> 3931.6129 | R48: =Q49 -> 9920.61 | S48: =R49 -> 11821.891 | T48: =R48 -> 9920.61 | U48: =T49 -> 15887.015 | V48: =U49 -> 18028.777 | W48: =U48 -> 15887.015 | X48: =W49 -> 22368.415 | Y48: =X49 -> 24820.408 | Z48: =X48 -> 22368.415 | AA48: =Z49 -> 29456.417 | AB48: =AA49 -> 32168.135 | AC48: =AA48 -> 29456.417
B49: Closing Cash | C49: =C45+C46+C47+C48+1 -> 2680 | D49: =D45+D46+D47+D48 -> 2638 | E49: =E45+E46+E47+E48 -> 2637 | F49: =F45+F46+F47+F48 -> 1763 | G49: =G45+G46+G47+G48 -> 2211 | H49: =H45+H46+H47+H48 -> 2211 | I49: =I45+I46+I47+I48 -> 3226 | J49: =J45+J46+J47+J48 -> 1867 | K49: =K45+K46+K47+K48 -> 1403 | ... AC49: =AC45+AC46+AC47+AC48 -> 37134.181
B51: Net cash and cash equivalents consist of:
B52: Cash and cash equivalents | C52: 2763 | D52: =E52-C52 -> -14 | E52: 2749 | F52: =E54 -> 2637 | G52: =H52-F52 -> -352 | H52: 2285 | I52: 3319 | J52: =K52-I52 -> -1880 | K52: 1439 | L52: 1529
B53: Bank overdrafts | C53: -83 | D53: =E53-C53 -> -29 | E53: -112 | G53: =H53-F53 -> -74 | H53: -74 | I53: -93 | J53: =K53-I53 -> 57 | K53: -36 | L53: -47
B54: Closing Cash | C54: =C52+C53 -> 2680 | D54: =D52+D53 -> -43 | E54: =E52+E53 -> 2637 | F54: =F52+F53 -> 2637 | G54: =G52+G53 -> -426 | H54: =H52+H53 -> 2211 | I54: =I52+I53 -> 3226 | J54: =J52+J53 -> -1823 | ... AC54: =AC52+AC53 -> 0

Sheet Balance Sheet
C2: ='Income Statement '!C2 -> H1'21 | D2: ='Income Statement '!D2 -> H2'21 | E2: ='Income Statement '!E2 -> FY'21 | F2: ='Income Statement '!F2 -> H1'22 | G2: ='Income Statement '!G2 -> H2'22 | H2: ='Income Statement '!H2 -> FY'22 | I2: ='Income Statement '!I2 -> H1'23 | J2: ='Income Statement '!J2 -> H2'23 | ... AC2: ='Income Statement '!AC2 -> FY'29E
B3: Non-current Assets
B4: Intangible Assets | C4: 10877 | D4: =E4 -> 10764 | E4: 10764 | F4: 10921 | G4: =H4 -> 11902 | H4: 11902 | I4: 14556 | J4: =K4 -> 11512 | K4: 11512 | L4: 14496 | M4: =L4 -> 14496 | N4: =M4 -> 14496 | O4: =N4 -> 14496 | P4: =O4 -> 14496 | Q4: =P4 -> 14496 | R4: =Q4 -> 14496 | S4: =R4 -> 14496 | T4: =S4 -> 14496 | ... AC4: =AB4 -> 14496
B5: PP&E | C5: 4757 | D5: =E5 -> 4849 | E5: 4849 | F5: 5091 | G5: =H5 -> 5848 | H5: 5848 | I5: 7168 | J5: =K5 -> 6142 | K5: 6142 | L5: 8212 | M5: =M65 -> 8195.6814 | N5: =N65 -> 8195.6814 | O5: =O65 -> 8407.7876 | P5: =P65 -> 8430.0216 | Q5: =Q65 -> 8430.0216 | R5: =R65 -> 8683.45 | S5: =S65 -> 8745.7532 | T5: =T65 -> 8745.7532 | ... AC5: =AC65 -> 10209.581
B6: Biological Assets | C6: 63 | D6: =E6 -> 66 | E6: 66 | F6: 75 | G6: =H6 -> 94 | H6: 94 | I6: 143 | J6: =K6 -> 156 | K6: 156 | L6: 194 | M6: =L6 -> 194 | N6: =M6 -> 194 | O6: =N6 -> 194 | P6: =O6 -> 194 | Q6: =P6 -> 194 | R6: =Q6 -> 194 | S6: =R6 -> 194 | T6: =S6 -> 194 | ... AC6: =AB6 -> 194
B7: Investments in associates and JVs | C7: 3578 | D7: =E7 -> 3308 | E7: 3308 | F7: 3473 | G7: =H7 -> 3652 | H7: 3652 | I7: 4710 | J7: =K7 -> 3829 | K7: 3829 | L7: 5229 | M7: =L7 -> 5229 | N7: =M7 -> 5229 | O7: =N7 -> 5229 | P7: =O7 -> 5229 | Q7: =P7 -> 5229 | R7: =Q7 -> 5229 | S7: =R7 -> 5229 | T7: =S7 -> 5229 | ... AC7: =AB7 -> 5229
B8: Other investments | C8: 36 | D8: =E8 -> 40 | E8: 40 | F8: 50 | G8: =H8 -> 37 | H8: 37 | I8: 50 | J8: =K8 -> 57 | K8: 57 | L8: 96 | M8: =L8 -> 96 | N8: =M8 -> 96 | O8: =N8 -> 96 | P8: =O8 -> 96 | Q8: =P8 -> 96 | R8: =Q8 -> 96 | S8: =R8 -> 96 | T8: =S8 -> 96 | ... AC8: =AB8 -> 96
B9: Other receivables | C9: 41 | D9: =E9 -> 36 | E9: 36 | F9: 28 | G9: =H9 -> 37 | H9: 37 | I9: 33 | J9: =K9 -> 31 | K9: 31 | L9: 32 | M9: =L9 -> 32 | N9: =M9 -> 32 | O9: =N9 -> 32 | P9: =O9 -> 32 | Q9: =P9 -> 32 | R9: =Q9 -> 32 | S9: =R9 -> 32 | T9: =S9 -> 32 | ... AC9: =AB9 -> 32
B10: Other financial assets | C10: 410 | D10: =E10 -> 327 | E10: 327 | F10: 319 | G10: =H10 -> 345 | H10: 345 | I10: 479 | J10: =K10 -> 394 | K10: 394 | L10: 430 | M10: =L10 -> 430 | N10: =M10 -> 430 | O10: =N10 -> 430 | P10: =O10 -> 430 | Q10: =P10 -> 430 | R10: =Q10 -> 430 | S10: =R10 -> 430 | T10: =S10 -> 430 | ... AC10: =AB10 -> 430
B11: Deferred tax assets | C11: 114 | D11: =E11 -> 100 | E11: 100 | F11: 83 | G11: =H11 -> 114 | H11: 114 | I11: 127 | J11: =K11 -> 141 | K11: 141 | L11: 171 | M11: =L11 -> 171 | N11: =M11 -> 171 | O11: =N11 -> 171 | P11: =O11 -> 171 | Q11: =P11 -> 171 | R11: =Q11 -> 171 | S11: =R11 -> 171 | T11: =S11 -> 171 | ... AC11: =AB11 -> 171
B12: Post Employment Benefit Assets | C12: 1083 | D12: =E12 -> 1018 | E12: 1018 | F12: 1544 | G12: =H12 -> 1553 | H12: 1553 | I12: 1272 | J12: =K12 -> 960 | K12: 960 | L12: 1118 | M12: =L12 -> 1118 | N12: =M12 -> 1118 | O12: =N12 -> 1118 | P12: =O12 -> 1118 | Q12: =P12 -> 1118 | R12: =Q12 -> 1118 | S12: =R12 -> 1118 | T12: =S12 -> 1118 | ... AC12: =AB12 -> 1118
B13: Total Non-Current Assets | C13: =SUM(C4:C12) -> 20959 | D13: =SUM(D4:D12) -> 20508 | E13: =SUM(E4:E12) -> 20508 | F13: =SUM(F4:F12) -> 21584 | G13: =SUM(G4:G12) -> 23582 | H13: =SUM(H4:H12) -> 23582 | I13: =SUM(I4:I12) -> 28538 | J13: =SUM(J4:J12) -> 23222 | ... AC13: =SUM(AC4:AC12) -> 31975.581
B15: Current Assets
B16: Inventories | C16: 5750 | D16: =E16 -> 6045 | E16: 6045 | F16: 6235 | G16: =H16 -> 7094 | H16: 7094 | I16: 9062 | J16: =K16 -> 7661 | K16: 7661 | L16: 9840 | M16: =M70 -> 10140.008 | N16: =N70 -> 10140.008 | O16: =O70 -> 11399.85 | P16: =P70 -> 9780.0723 | Q16: =Q70 -> 9780.0723 | R16: =R70 -> 12363.702 | S16: =S70 -> 10751.655 | T16: =T70 -> 10751.655 | ... AC16: =AC70 -> 14289.187
B17: Trade and other receivables | C17: 3075 | D17: =E17 -> 2385 | E17: 2385 | F17: 3328 | G17: =H17 -> 2933 | H17: 2933 | I17: 4648 | J17: =K17 -> 2720 | K17: 2720 | L17: 4580 | M17: =M71 -> 3876.458 | N17: =N71 -> 3876.458 | O17: =O71 -> 4950.792 | P17: =P71 -> 4247.3457 | Q17: =Q71 -> 4247.3457 | R17: =R71 -> 5369.3793 | S17: =S71 -> 4669.2901 | T17: =T71 -> 4669.2901 | ... AC17: =AC71 -> 6205.5898
B18: Assets held for sales | C18: 0 | D18: =E18 -> 0 | E18: 0 | F18: 16 | G18: =H18 -> 222 | H18: 222 | I18: 220 | J18: =K18 -> 0 | K18: 0 | L18: 0 | M18: =L18 -> 0 | N18: =M18 -> 0 | O18: =N18 -> 0 | P18: =O18 -> 0 | Q18: =P18 -> 0 | R18: =Q18 -> 0 | S18: =R18 -> 0 | T18: =S18 -> 0 | ... AC18: =AB18 -> 0
B19: Corporate tax receivables | C19: 173 | D19: =E19 -> 145 | E19: 145 | F19: 151 | G19: =H19 -> 149 | H19: 149 | I19: 199 | J19: =K19 -> 232 | K19: 232 | L19: 274 | M19: =L19 -> 274 | N19: =M19 -> 274 | O19: =N19 -> 274 | P19: =O19 -> 274 | Q19: =P19 -> 274 | R19: =Q19 -> 274 | S19: =R19 -> 274 | T19: =S19 -> 274 | ... AC19: =AB19 -> 274
B20: Other financial assets | C20: 84 | D20: =E20 -> 121 | E20: 121 | F20: 66 | G20: =H20 -> 251 | H20: 251 | I20: 479 | J20: =K20 -> 347 | K20: 347 | L20: 564 | M20: =L20 -> 564 | N20: =M20 -> 564 | O20: =N20 -> 564 | P20: =O20 -> 564 | Q20: =P20 -> 564 | R20: =Q20 -> 564 | S20: =R20 -> 564 | T20: =S20 -> 564 | ... AC20: =AB20 -> 564
B21: Cash and Cash equivalents | C21: 2763 | D21: =E21 -> 2749 | E21: 2749 | F21: 1780 | G21: =H21 -> 2285 | H21: 2285 | I21: 3319 | J21: =K21 -> 1439 | K21: 1439 | L21: 1529 | M21: ='Cash Flow'!M49 -> 3931.6129 | N21: ='Cash Flow'!N49 -> 3931.6129 | O21: ='Cash Flow'!O49 -> 6106.2203 | P21: ='Cash Flow'!P49 -> 9920.61 | Q21: ='Cash Flow'!Q49 -> 9920.61 | R21: ='Cash Flow'!R49 -> 11821.891 | S21: ='Cash Flow'!S49 -> 15887.015 | T21: ='Cash Flow'!T49 -> 15887.015 | ... AC21: ='Cash Flow'!AC49 -> 37134.181
B22: Total Current Assets | C22: =SUM(C16:C21) -> 11845 | D22: =SUM(D16:D21) -> 11445 | E22: =SUM(E16:E21) -> 11445 | F22: =SUM(F16:F21) -> 11576 | G22: =SUM(G16:G21) -> 12934 | H22: =SUM(H16:H21) -> 12934 | I22: =SUM(I16:I21) -> 17927 | J22: =SUM(J16:J21) -> 12399 | ... AC22: =SUM(AC16:AC21) -> 58466.958
B24: Total Assets | C24: =C13+C22 -> 32804 | D24: =D13+D22 -> 31953 | E24: =E13+E22 -> 31953 | F24: =F13+F22 -> 33160 | G24: =G13+G22 -> 36516 | H24: =H13+H22 -> 36516 | I24: =I13+I22 -> 46465 | J24: =J13+J22 -> 35621 | ... AC24: =AC13+AC22 -> 90442.539
B26: Current Liabilities
B27: Borrowings and bank overdrafts | C27: 1214 | D27: =E27 -> 1862 | E27: 1862 | F27: 1184 | G27: =H27 -> 1522 | H27: 1522 | I27: 2767 | J27: =K27 -> 1701 | K27: 1701 | L27: 2004 | M27: =L27 -> 2004 | N27: =M27 -> 2004 | O27: =N27 -> 2004 | P27: =O27 -> 2004 | Q27: =P27 -> 2004 | R27: =Q27 -> 2004 | S27: =R27 -> 2004 | T27: =S27 -> 2004 | ... AC27: =AB27 -> 2004
B28: Other financial liabilities | C28: 332 | D28: =E28 -> 257 | E28: 257 | F28: 388 | G28: =H28 -> 444 | H28: 444 | I28: 524 | J28: =K28 -> 359 | K28: 359 | L28: 371 | M28: =L28 -> 371 | N28: =M28 -> 371 | O28: =N28 -> 371 | P28: =O28 -> 371 | Q28: =P28 -> 371 | R28: =Q28 -> 371 | S28: =R28 -> 371 | T28: =S28 -> 371 | ... AC28: =AB28 -> 371
B29: Share buyback liability | C29: 0 | D29: =E29 -> 91 | E29: 91 | F29: 184 | G29: =H29 -> 117 | H29: 117 | I29: 259 | J29: =K29 -> 0 | K29: 0 | L29: 497 | M29: =L29 -> 497 | N29: =M29 -> 497 | O29: =N29 -> 497 | P29: =O29 -> 497 | Q29: =P29 -> 497 | R29: =Q29 -> 497 | S29: =R29 -> 497 | T29: =S29 -> 497 | ... AC29: =AB29 -> 497
B30: Trade and other payables | C30: 4624 | D30: =E30 -> 4648 | E30: 4648 | F30: 5327 | G30: =H30 -> 5887 | H30: 5887 | I30: 7332 | J30: =K30 -> 5300 | K30: 5300 | L30: 7292 | M30: =M72 -> 6381.1327 | N30: =N72 -> 6381.1327 | O30: =O72 -> 7181.9055 | P30: =P72 -> 6161.4455 | Q30: =Q72 -> 6161.4455 | R30: =R72 -> 7789.1325 | S30: =S72 -> 6773.5426 | T30: =T72 -> 6773.5426 | ... AC30: =AC72 -> 9002.1878
B31: Liabilities held for sale | C31: 0 | D31: =E31 -> 0 | E31: 0 | F31: 30 | G31: =H31 -> 61 | H31: 61 | I31: 92 | J31: =K31 -> 0 | K31: 0 | L31: 0 | M31: =L31 -> 0 | N31: =M31 -> 0 | O31: =N31 -> 0 | P31: =O31 -> 0 | Q31: =P31 -> 0 | R31: =Q31 -> 0 | S31: =R31 -> 0 | T31: =S31 -> 0 | ... AC31: =AB31 -> 0
B32: Corporate tax payables | C32: 364 | D32: =E32 -> 146 | E32: 146 | F32: 380 | G32: =H32 -> 252 | H32: 252 | I32: 319 | J32: =K32 -> 135 | K32: 135 | L32: 253 | M32: =L32 -> 253 | N32: =M32 -> 253 | O32: =N32 -> 253 | P32: =O32 -> 253 | Q32: =P32 -> 253 | R32: =Q32 -> 253 | S32: =R32 -> 253 | T32: =S32 -> 253 | ... AC32: =AB32 -> 253
B33: Provisions | C33: 176 | D33: =E33 -> 138 | E33: 138 | F33: 111 | G33: =H33 -> 159 | H33: 159 | I33: 135 | J33: =K33 -> 119 | K33: 119 | L33: 213 | M33: =L33 -> 213 | N33: =M33 -> 213 | O33: =N33 -> 213 | P33: =O33 -> 213 | Q33: =P33 -> 213 | R33: =Q33 -> 213 | S33: =R33 -> 213 | T33: =S33 -> 213 | ... AC33: =AB33 -> 213
B34: Total Current Liabilities | C34: =SUM(C27:C33) -> 6710 | D34: =SUM(D27:D33) -> 7142 | E34: =SUM(E27:E33) -> 7142 | F34: =SUM(F27:F33) -> 7604 | G34: =SUM(G27:G33) -> 8442 | H34: =SUM(H27:H33) -> 8442 | I34: =SUM(I27:I33) -> 11428 | J34: =SUM(J27:J33) -> 7614 | ... AC34: =SUM(AC27:AC33) -> 12340.188
B36: Non-Current Liabilities
B37: Borrowings | C37: 14063 | D37: =E37 -> 12865 | E37: 12865 | F37: 12693 | G37: =H37 -> 14498 | H37: 14498 | I37: 18365 | J37: =K37 -> 14801 | K37: 14801 | L37: 19476 | M37: =M81 -> 19976 | N37: =N81 -> 19976 | O37: =O81 -> 20476 | P37: =P81 -> 20976 | Q37: =Q81 -> 20976 | R37: =R81 -> 21476 | S37: =S81 -> 21976 | T37: =T81 -> 21976 | ... AC37: =AC81 -> 24976
B38: Other financial liabilities | C38: 376 | D38: =E38 -> 384 | E38: 384 | F38: 378 | G38: =H38 -> 703 | H38: 703 | I38: 925 | J38: =K38 -> 747 | K38: 747 | L38: 865 | M38: =L38 -> 865 | N38: =M38 -> 865 | O38: =N38 -> 865 | P38: =O38 -> 865 | Q38: =P38 -> 865 | R38: =Q38 -> 865 | S38: =R38 -> 865 | T38: =S38 -> 865 | ... AC38: =AB38 -> 865
B39: Other Payables | C39: 267 | D39: =E39 -> 338 | E39: 338 | F39: 278 | G39: =H39 -> 380 | H39: 380 | I39: 424 | J39: =K39 -> 368 | K39: 368 | L39: 447 | M39: =L39 -> 447 | N39: =M39 -> 447 | O39: =N39 -> 447 | P39: =O39 -> 447 | Q39: =P39 -> 447 | R39: =Q39 -> 447 | S39: =R39 -> 447 | T39: =S39 -> 447 | ... AC39: =AB39 -> 447
B40: Provisions | C40: 295 | D40: =E40 -> 274 | E40: 274 | F40: 278 | G40: =H40 -> 258 | H40: 258 | I40: 319 | J40: =K40 -> 243 | K40: 243 | L40: 313 | M40: =L40 -> 313 | N40: =M40 -> 313 | O40: =N40 -> 313 | P40: =O40 -> 313 | Q40: =P40 -> 313 | R40: =Q40 -> 313 | S40: =R40 -> 313 | T40: =S40 -> 313 | ... AC40: =AB40 -> 313
B41: Deferred tax liabilities | C41: 1900 | D41: =E41 -> 1945 | E41: 1945 | F41: 2112 | G41: =H41 -> 2319 | H41: 2319 | I41: 2708 | J41: =K41 -> 2183 | K41: 2183 | L41: 2839 | M41: =L41 -> 2839 | N41: =M41 -> 2839 | O41: =N41 -> 2839 | P41: =O41 -> 2839 | Q41: =P41 -> 2839 | R41: =Q41 -> 2839 | S41: =R41 -> 2839 | T41: =S41 -> 2839 | ... AC41: =AB41 -> 2839
B42: Post employment benefit liabilities | C42: 815 | D42: =E42 -> 574 | E42: 574 | F42: 486 | G42: =H42 -> 402 | H42: 402 | I42: 457 | J42: =K42 -> 373 | K42: 373 | L42: 471 | M42: =L42 -> 471 | N42: =M42 -> 471 | O42: =N42 -> 471 | P42: =O42 -> 471 | Q42: =P42 -> 471 | R42: =Q42 -> 471 | S42: =R42 -> 471 | T42: =S42 -> 471 | ... AC42: =AB42 -> 471
B43: Total Non-Current Liabilities | C43: =SUM(C37:C42) -> 17716 | D43: =SUM(D37:D42) -> 16380 | E43: =SUM(E37:E42) -> 16380 | F43: =SUM(F37:F42) -> 16225 | G43: =SUM(G37:G42) -> 18560 | H43: =SUM(H37:H42) -> 18560 | I43: =SUM(I37:I42) -> 23198 | J43: =SUM(J37:J42) -> 18715 | ... AC43: =SUM(AC37:AC42) -> 29911
B45: Equity
B46: Share Capital | C46: 742 | D46: =E46 -> 741 | E46: 741 | F46: 737 | G46: =H46 -> 723 | H46: 723 | I46: 863 | J46: =K46 -> 712 | K46: 712 | L46: 893 | M46: =L46 -> 893 | N46: =M46 -> 893 | O46: =N46 -> 893 | P46: =O46 -> 893 | Q46: =P46 -> 893 | R46: =Q46 -> 893 | S46: =R46 -> 893 | T46: =S46 -> 893 | ... AC46: =AB46 -> 893
B47: Share Premium | C47: 1351 | D47: =E47 -> 1351 | E47: 1351 | F47: 1351 | G47: =H47 -> 1351 | H47: 1351 | I47: 1621 | J47: =K47 -> 1351 | K47: 1351 | L47: 1703 | M47: =L47 -> 1703 | N47: =M47 -> 1703 | O47: =N47 -> 1703 | P47: =O47 -> 1703 | Q47: =P47 -> 1703 | R47: =Q47 -> 1703 | S47: =R47 -> 1703 | T47: =S47 -> 1703 | ... AC47: =AB47 -> 1703
B48: Other reserves | C48: 1835 | D48: =E48 -> 1621 | E48: 1621 | F48: 1551 | G48: =H48 -> 2174 | H48: 2174 | I48: 560 | J48: =K48 -> 1861 | K48: 1861 | L48: 502 | M48: =L48 -> 502 | N48: =M48 -> 502 | O48: =N48 -> 502 | P48: =O48 -> 502 | Q48: =P48 -> 502 | R48: =Q48 -> 502 | S48: =R48 -> 502 | T48: =S48 -> 502 | ... AC48: =AB48 -> 502
B49: Retained Earnings | C49: 2890 | D49: =E49 -> 3184 | E49: 3184 | F49: 4019 | G49: =H49 -> 3550 | H49: 3550 | I49: 6722 | J49: =K49 -> 3898 | K49: 3898 | L49: 6693 | M49: =L49+'Income Statement '!M23 -> 8954.6278 | N49: =M49 -> 8954.6278 | O49: =N49+'Income Statement '!O23 -> 12374.744 | P49: =O49+'Income Statement '!P23 -> 14408.604 | Q49: =P49 -> 14408.604 | R49: =Q49+'Income Statement '!R23 -> 18141.29 | S49: =R49+'Income Statement '!S23 -> 20472.17 | T49: =S49 -> 20472.17 | U49: =T49+'Income Statement '!U23 -> 24546.713 | V49: =U49+'Income Statement '!V23 -> 27212.685 | W49: =V49 -> 27212.685 | X49: =W49+'Income Statement '!X23 -> 31660.863 | Y49: =X49+'Income Statement '!Y23 -> 34704.244 | Z49: =Y49 -> 34704.244 | AA49: =Z49+'Income Statement '!AA23 -> 39560.536 | AB49: =AA49+'Income Statement '!AB23 -> 43028.351 | AC49: =AB49 -> 43028.351
B50: Equity attributable to the parent | C50: =SUM(C46:C49) -> 6818 | D50: =SUM(D46:D49) -> 6897 | E50: =SUM(E46:E49) -> 6897 | F50: =SUM(F46:F49) -> 7658 | G50: =SUM(G46:G49) -> 7798 | H50: =SUM(H46:H49) -> 7798 | I50: =SUM(I46:I49) -> 9766 | J50: =SUM(J46:J49) -> 7822 | ... AC50: =SUM(AC46:AC49) -> 46126.351
B51: Non-controlling interests | C51: 1560 | D51: =E51 -> 1534 | E51: 1534 | F51: 1673 | G51: =H51 -> 1716 | H51: 1716 | I51: 2073 | J51: =K51 -> 1470 | K51: 1470 | L51: 1933 | M51: =L51+'Income Statement '!M25 -> 2065 | N51: =M51 -> 2065 | O51: =N51+'Income Statement '!O25 -> 2065 | P51: =O51+'Income Statement '!P25 -> 2065 | Q51: =P51+'Income Statement '!Q25 -> 2065 | R51: =Q51+'Income Statement '!R25 -> 2065 | S51: =R51+'Income Statement '!S25 -> 2065 | T51: =S51+'Income Statement '!T25 -> 2065 | U51: =T51+'Income Statement '!U25 -> 2065 | V51: =U51+'Income Statement '!V25 -> 2065 | ... AC51: =AB51+'Income Statement '!AC25 -> 2065
B52: Total Equity | C52: =C50+C51 -> 8378 | D52: =D50+D51 -> 8431 | E52: =E50+E51 -> 8431 | F52: =F50+F51 -> 9331 | G52: =G50+G51 -> 9514 | H52: =H50+H51 -> 9514 | I52: =I50+I51 -> 11839 | J52: =J50+J51 -> 9292 | ... AC52: =AC50+AC51 -> 48191.351
B54: Check | C54: =C24-C34-C43-C52 -> 0 | D54: =D24-D34-D43-D52 -> 0 | E54: =E24-E34-E43-E52 -> 0 | F54: =F24-F34-F43-F52 -> 0 | G54: =G24-G34-G43-G52 -> 0 | H54: =H24-H34-H43-H52 -> 0 | I54: =I24-I34-I43-I52 -> 0 | J54: =J24-J34-J43-J52 -> 0 | ... AC54: =AC24-AC34-AC43-AC52 -> 0
B56: PP&E
B58: Cost | K58: =9569-K59-K61 -> 8402 | L58: =L65+L62-L59 -> 8041 | M58: =L65 -> 8212 | N58: =L58 -> 8041 | O58: =N65 -> 8195.6814 | P58: =O65 -> 8407.7876 | Q58: =N65 -> 8195.6814 | R58: =Q65 -> 8430.0216 | S58: =R65 -> 8683.45 | T58: =Q65 -> 8430.0216 | U58: =T65 -> 8745.7532 | V58: =U65 -> 9040.881 | W58: =T65 -> 8745.7532 | X58: =W65 -> 9145.2952 | Y58: =X65 -> 9482.7612 | Z58: =W65 -> 9145.2952 | AA58: =Z65 -> 9631.8804 | AB58: =AA65 -> 10012.576 | AC58: =Z65 -> 9631.8804
B59: Capex | C59: =-'Cash Flow'!C26 -> 250 | D59: =-'Cash Flow'!D26 -> 376 | E59: =-'Cash Flow'!E26 -> 626 | F59: =-'Cash Flow'!F26 -> 382 | G59: =-'Cash Flow'!G26 -> 715 | H59: =-'Cash Flow'!H26 -> 1097 | I59: =-'Cash Flow'!I26 -> 514 | J59: =-'Cash Flow'!J26 -> 666 | ... L59: =-'Cash Flow'!L26 -> 582 | M59: =M60*'Income Statement '!M5 -> 402.4934 | N59: =L59+M59 -> 984.49339 | O59: =O60*'Income Statement '!O5 -> 630.086 | P59: =P60*'Income Statement '!P5 -> 451.03114 | Q59: =O59+P59 -> 1081.1171 | R59: =R60*'Income Statement '!R5 -> 683.35949 | S59: =S60*'Income Statement '!S5 -> 505.15916 | T59: =R59+S59 -> 1188.5186 | U59: =U60*'Income Statement '!U5 -> 741.16123 | V59: =V60*'Income Statement '!V5 -> 565.49908 | W59: =U59+V59 -> 1306.6603 | X59: =X60*'Income Statement '!X5 -> 803.87612 | Y59: =Y60*'Income Statement '!Y5 -> 632.74002 | Z59: =X59+Y59 -> 1436.6161 | AA59: =AA60*'Income Statement '!AA5 -> 871.92178 | AB59: =AB60*'Income Statement '!AB5 -> 707.64578 | AC59: =AA59+AB59 -> 1579.5676
L60: =L59/'Income Statement '!L5 -> 0.053092501 | M60: 0.053 | O60: 0.053 | P60: 0.053 | R60: 0.053 | S60: 0.053 | U60: 0.053 | V60: 0.053 | X60: 0.053 | Y60: 0.053 | AA60: 0.053 | AB60: 0.053
B61: Disposal | C61: =-'Cash Flow'!C25 -> -8 | D61: =-'Cash Flow'!D25 -> -5 | E61: =-'Cash Flow'!E25 -> -13 | F61: =-'Cash Flow'!F25 -> -7 | G61: =-'Cash Flow'!G25 -> -10 | H61: =-'Cash Flow'!H25 -> -17 | I61: =-'Cash Flow'!I25 -> -8 | J61: =-'Cash Flow'!J25 -> -5 | ... L61: =-'Cash Flow'!L25 -> -7
B62: Depreciation charge for the year | K62: 1066 | L62: ='Income Statement '!L13 -> 411 | M62: =M63*M58 -> 418.812 | N62: =L62+M62 -> 829.812 | O62: =O63*O58 -> 417.97975 | P62: =P63*P58 -> 428.79717 | Q62: =O62+P62 -> 846.77692 | R62: =R63*R58 -> 429.9311 | S62: =S63*S58 -> 442.85595 | T62: =R62+S62 -> 872.78705 | U62: =U63*U58 -> 446.03341 | V62: =V63*V58 -> 461.08493 | W62: =U62+V62 -> 907.11835 | X62: =X63*X58 -> 466.41005 | Y62: =Y63*Y58 -> 483.62082 | Z62: =X62+Y62 -> 950.03088 | AA62: =AA63*AA58 -> 491.2259 | AB62: =AB63*AB58 -> 510.64139 | AC62: =AA62+AB62 -> 1001.8673
B63: % of sales | L63: =L62/L58 -> 0.051113046 | M63: 0.051 | N63: =N62/N58 -> 0.10319761 | O63: 0.051 | P63: 0.051 | Q63: =Q62/Q58 -> 0.10331989 | R63: 0.051 | S63: 0.051 | T63: =T62/T58 -> 0.10353319 | U63: 0.051 | V63: 0.051 | W63: =W62/W58 -> 0.10372101 | X63: 0.051 | Y63: 0.051 | Z63: =Z62/Z58 -> 0.10388193 | AA63: 0.051 | AB63: 0.051 | AC63: =AC62/AC58 -> 0.10401575
B65: Closing Balance | C65: =C5 -> 4757 | D65: =D5 -> 4849 | E65: =E5 -> 4849 | F65: =F5 -> 5091 | G65: =G5 -> 5848 | H65: =H5 -> 5848 | I65: =I5 -> 7168 | J65: =J5 -> 6142 | ... L65: =L5 -> 8212 | M65: =M58+M59-M62 -> 8195.6814 | N65: =N58+N59-N62 -> 8195.6814 | O65: =O58+O59-O62 -> 8407.7876 | P65: =P58+P59-P62 -> 8430.0216 | Q65: =Q58+Q59-Q62 -> 8430.0216 | R65: =R58+R59-R62 -> 8683.45 | S65: =S58+S59-S62 -> 8745.7532 | T65: =T58+T59-T62 -> 8745.7532 | ... AC65: =AC58+AC59-AC62 -> 10209.581
B68: Working Capital Schedule
C69: =91.25*2 -> 182.5 | D69: =91.25*2 -> 182.5 | E69: 365 | F69: =91.25*2 -> 182.5 | G69: =91.25*2 -> 182.5 | H69: 365 | I69: =91.25*2 -> 182.5 | J69: =91.25*2 -> 182.5 | K69: 365 | L69: 183 | M69: 183 | N69: 366 | O69: =91.25*2 -> 182.5 | P69: =91.25*2 -> 182.5 | Q69: 365 | R69: =91.25*2 -> 182.5 | S69: =91.25*2 -> 182.5 | T69: 365 | U69: =91.25*2 -> 182.5 | V69: =91.25*2 -> 182.5 | W69: 365 | X69: 183 | Y69: 183 | Z69: 366 | AA69: =91.25*2 -> 182.5 | AB69: =91.25*2 -> 182.5 | AC69: 365
B70: Inventories | C70: =C16 -> 5750 | D70: =D16 -> 6045 | E70: =E16 -> 6045 | F70: =F16 -> 6235 | G70: =G16 -> 7094 | H70: =H16 -> 7094 | I70: =I16 -> 9062 | J70: =J16 -> 7661 | ... L70: =L16 -> 9840 | M70: =N70 -> 10140.008 | N70: ='Income Statement '!N6*'Balance Sheet'!N74/'Balance Sheet'!N69 -> 10140.008 | O70: ='Income Statement '!O6*'Balance Sheet'!O74/'Balance Sheet'!O69 -> 11399.85 | P70: =Q70 -> 9780.0723 | Q70: ='Income Statement '!Q6*'Balance Sheet'!Q74/'Balance Sheet'!Q69 -> 9780.0723 | R70: ='Income Statement '!R6*'Balance Sheet'!R74/'Balance Sheet'!R69 -> 12363.702 | S70: =T70 -> 10751.655 | T70: ='Income Statement '!T6*'Balance Sheet'!T74/'Balance Sheet'!T69 -> 10751.655 | U70: ='Income Statement '!U6*'Balance Sheet'!U74/'Balance Sheet'!U69 -> 13409.482 | V70: =W70 -> 11820.396 | W70: ='Income Statement '!W6*'Balance Sheet'!W74/'Balance Sheet'!W69 -> 11820.396 | X70: ='Income Statement '!X6*'Balance Sheet'!X74/'Balance Sheet'!X69 -> 14504.415 | Y70: =Z70 -> 12960.502 | Z70: ='Income Statement '!Z6*'Balance Sheet'!Z74/'Balance Sheet'!Z69 -> 12960.502 | AA70: ='Income Statement '!AA6*'Balance Sheet'!AA74/'Balance Sheet'!AA69 -> 15775.271 | AB70: =AC70 -> 14289.187 | AC70: ='Income Statement '!AC6*'Balance Sheet'!AC74/'Balance Sheet'!AC69 -> 14289.187
B71: Trade Receivables | C71: =C17 -> 3075 | D71: =D17 -> 2385 | E71: =E17 -> 2385 | F71: =F17 -> 3328 | G71: =G17 -> 2933 | H71: =H17 -> 2933 | I71: =I17 -> 4648 | J71: =J17 -> 2720 | ... L71: =L17 -> 4580 | M71: =N71 -> 3876.458 | N71: =N75*'Income Statement '!N5/'Balance Sheet'!N69 -> 3876.458 | O71: =O75*'Income Statement '!O5/'Balance Sheet'!O69 -> 4950.792 | P71: =Q71 -> 4247.3457 | Q71: =Q75*'Income Statement '!Q5/'Balance Sheet'!Q69 -> 4247.3457 | R71: =R75*'Income Statement '!R5/'Balance Sheet'!R69 -> 5369.3793 | S71: =T71 -> 4669.2901 | T71: =T75*'Income Statement '!T5/'Balance Sheet'!T69 -> 4669.2901 | U71: =U75*'Income Statement '!U5/'Balance Sheet'!U69 -> 5823.5465 | V71: =W71 -> 5133.429 | W71: =W75*'Income Statement '!W5/'Balance Sheet'!W69 -> 5133.429 | X71: =X75*'Income Statement '!X5/'Balance Sheet'!X69 -> 6299.0602 | Y71: =Z71 -> 5628.561 | Z71: =Z75*'Income Statement '!Z5/'Balance Sheet'!Z69 -> 5628.561 | AA71: =AA75*'Income Statement '!AA5/'Balance Sheet'!AA69 -> 6850.9749 | AB71: =AC71 -> 6205.5898 | AC71: =AC75*'Income Statement '!AC5/'Balance Sheet'!AC69 -> 6205.5898
B72: Trade Payables | C72: =C30 -> 4624 | D72: =D30 -> 4648 | E72: =E30 -> 4648 | F72: =F30 -> 5327 | G72: =G30 -> 5887 | H72: =H30 -> 5887 | I72: =I30 -> 7332 | J72: =J30 -> 5300 | ... L72: =L30 -> 7292 | M72: =N72 -> 6381.1327 | N72: ='Income Statement '!N6*'Balance Sheet'!N76/'Balance Sheet'!N69 -> 6381.1327 | O72: ='Income Statement '!O6*'Balance Sheet'!O76/'Balance Sheet'!O69 -> 7181.9055 | P72: =Q72 -> 6161.4455 | Q72: ='Income Statement '!Q6*'Balance Sheet'!Q76/'Balance Sheet'!Q69 -> 6161.4455 | R72: ='Income Statement '!R6*'Balance Sheet'!R76/'Balance Sheet'!R69 -> 7789.1325 | S72: =T72 -> 6773.5426 | T72: ='Income Statement '!T6*'Balance Sheet'!T76/'Balance Sheet'!T69 -> 6773.5426 | U72: ='Income Statement '!U6*'Balance Sheet'!U76/'Balance Sheet'!U69 -> 8447.9737 | V72: =W72 -> 7446.8493 | W72: ='Income Statement '!W6*'Balance Sheet'!W76/'Balance Sheet'!W69 -> 7446.8493 | X72: ='Income Statement '!X6*'Balance Sheet'!X76/'Balance Sheet'!X69 -> 9137.7815 | Y72: =Z72 -> 8165.1165 | Z72: ='Income Statement '!Z6*'Balance Sheet'!Z76/'Balance Sheet'!Z69 -> 8165.1165 | AA72: ='Income Statement '!AA6*'Balance Sheet'!AA76/'Balance Sheet'!AA69 -> 9938.4209 | AB72: =AC72 -> 9002.1878 | AC72: ='Income Statement '!AC6*'Balance Sheet'!AC76/'Balance Sheet'!AC69 -> 9002.1878
B74: Inventory days | C74: =C70/'Income Statement '!C6*C69 -> 394.35363 | D74: =D70/'Income Statement '!D6*D69 -> 464.11969 | E74: =E70/'Income Statement '!E6*E69 -> 437.95653 | F74: =F70/'Income Statement '!F6*F69 -> 385.07191 | G74: =G70/'Income Statement '!G6*G69 -> 428.9778 | H74: =H70/'Income Statement '!H6*H69 -> 433.50243 | I74: =I70/'Income Statement '!I6*I69 -> 386.49568 | J74: =J70/'Income Statement '!J6*J69 -> 533.63836 | ... M74: =M70/'Income Statement '!M6*M69 -> 583.25622 | N74: 500 | O74: 500 | P74: =P70/'Income Statement '!P6*P69 -> 599.2475 | Q74: 500 | R74: 500 | S74: =S70/'Income Statement '!S6*S69 -> 588.19019 | T74: 500 | U74: 500 | V74: =V70/'Income Statement '!V6*V69 -> 577.65802 | W74: 500 | X74: 500 | Y74: =Y70/'Income Statement '!Y6*Y69 -> 567.61707 | Z74: 500 | AA74: 500 | AB74: =AB70/'Income Statement '!AB6*AB69 -> 558.0361 | AC74: 500
B75: DoR | C75: =C71/'Income Statement '!C5*'Balance Sheet'!C69 -> 81.639148 | D75: =D71/'Income Statement '!D5*'Balance Sheet'!D69 -> 74.289555 | E75: =E71/'Income Statement '!E5*'Balance Sheet'!E69 -> 68.367627 | F75: =F71/'Income Statement '!F5*'Balance Sheet'!F69 -> 76.330275 | G75: =G71/'Income Statement '!G5*'Balance Sheet'!G69 -> 71.417278 | H75: =H71/'Income Statement '!H5*'Balance Sheet'!H69 -> 69.28197 | I75: =I71/'Income Statement '!I5*'Balance Sheet'!I69 -> 76.282374 | J75: =J71/'Income Statement '!J5*'Balance Sheet'!J69 -> 82.829968 | ... M75: =M71/'Income Statement '!M5*'Balance Sheet'!M69 -> 93.412131 | N75: =L75 -> 76.458675 | O75: 76 | P75: =P71/'Income Statement '!P5*'Balance Sheet'!P69 -> 91.08562 | Q75: 76 | R75: 76 | S75: =S71/'Income Statement '!S5*'Balance Sheet'!S69 -> 89.404909 | T75: 76 | U75: 76 | V75: =V71/'Income Statement '!V5*'Balance Sheet'!V69 -> 87.804019 | W75: 76 | X75: 76 | Y75: =Y71/'Income Statement '!Y5*'Balance Sheet'!Y69 -> 86.277794 | Z75: 76 | AA75: 76 | AB75: =AB71/'Income Statement '!AB5*'Balance Sheet'!AB69 -> 84.821487 | AC75: 76
B76: DP | C76: =C72/'Income Statement '!C6*C69 -> 317.1289 | D76: =D72/'Income Statement '!D6*D69 -> 356.86159 | E76: =E72/'Income Statement '!E6*E69 -> 336.74474 | F76: =F72/'Income Statement '!F6*F69 -> 328.99408 | G76: =G72/'Income Statement '!G6*G69 -> 355.98989 | H76: =H72/'Income Statement '!H6*H69 -> 359.74468 | I76: =I72/'Income Statement '!I6*I69 -> 312.71091 | J76: =J72/'Income Statement '!J6*J69 -> 369.17939 | ... M76: =M72/'Income Statement '!M6*M69 -> 367.04461 | N76: =L76 -> 314.65126 | O76: 315 | P76: =P72/'Income Statement '!P6*P69 -> 377.52593 | Q76: 315 | R76: 315 | S76: =S72/'Income Statement '!S6*S69 -> 370.55982 | T76: 315 | U76: 315 | V76: =V72/'Income Statement '!V6*V69 -> 363.92455 | W76: 315 | X76: 315 | Y76: =Y72/'Income Statement '!Y6*Y69 -> 357.59875 | Z76: 315 | AA76: 315 | AB76: =AB72/'Income Statement '!AB6*AB69 -> 351.56274 | AC76: 315
B78: Debt Schedule
B79: Opening Balance | F79: =C81 -> 14063 | G79: =D81 -> 12865 | H79: =E81 -> 12865 | I79: =F81 -> 12693 | J79: =G81 -> 14498 | K79: =H81 -> 14498 | L79: =K81 -> 14801 | M79: =L81 -> 19476 | N79: =L79 -> 14801 | O79: =N81 -> 19976 | P79: =O81 -> 20476 | Q79: =O79 -> 19976 | R79: =Q81 -> 20976 | S79: =R81 -> 21476 | T79: =R79 -> 20976 | U79: =T81 -> 21976 | V79: =U81 -> 22476 | W79: =U79 -> 21976 | X79: =W81 -> 22976 | Y79: =X81 -> 23476 | Z79: =X79 -> 22976 | AA79: =Z81 -> 23976 | AB79: =AA81 -> 24476 | AC79: =AA79 -> 23976
B80: Repayment/Addition | F80: =F81-F79 -> -1370 | G80: =G81-G79 -> 1633 | H80: =H81-H79 -> 1633 | I80: =I81-I79 -> 5672 | J80: =J81-J79 -> 303 | K80: =K81-K79 -> 303 | L80: =L81-L79 -> 4675 | M80: 500 | N80: =L80+M80 -> 5175 | O80: 500 | P80: 500 | Q80: =O80+P80 -> 1000 | R80: 500 | S80: 500 | T80: =R80+S80 -> 1000 | U80: 500 | V80: 500 | W80: =U80+V80 -> 1000 | X80: 500 | Y80: 500 | Z80: =X80+Y80 -> 1000 | AA80: 500 | AB80: 500 | AC80: =AA80+AB80 -> 1000
B81: =B37 -> Borrowings | C81: =C37 -> 14063 | D81: =D37 -> 12865 | E81: =E37 -> 12865 | F81: =F37 -> 12693 | G81: =G37 -> 14498 | H81: =H37 -> 14498 | I81: =I37 -> 18365 | ... L81: =L37 -> 19476 | M81: =M79+M80 -> 19976 | N81: =N79+N80 -> 19976 | O81: =O79+O80 -> 20476 | P81: =P79+P80 -> 20976 | Q81: =Q79+Q80 -> 20976 | R81: =R79+R80 -> 21476 | S81: =S79+S80 -> 21976 | T81: =T79+T80 -> 21976 | ... AC81: =AC79+AC80 -> 24976
B82: Interest Charge | C82: =-'Income Statement '!C18 -> 327 | D82: =-'Income Statement '!D18 -> 324 | E82: =-'Income Statement '!E18 -> 651 | F82: =-'Income Statement '!F18 -> 310 | G82: =-'Income Statement '!G18 -> 609 | H82: =-'Income Statement '!H18 -> 919 | I82: =-'Income Statement '!I18 -> 648 | J82: =-'Income Statement '!J18 -> 286 | ... L82: =-'Income Statement '!L18 -> 718 | M82: =M81*M83 -> 799.04 | N82: =L82+M82 -> 1517.04 | O82: =O81*O83 -> 819.04 | P82: =P81*P83 -> 839.04 | Q82: =O82+P82 -> 1658.08 | R82: =R81*R83 -> 859.04 | S82: =S81*S83 -> 879.04 | T82: =R82+S82 -> 1738.08 | U82: =U81*U83 -> 899.04 | V82: =V81*V83 -> 919.04 | W82: =U82+V82 -> 1818.08 | X82: =X81*X83 -> 939.04 | Y82: =Y81*Y83 -> 959.04 | Z82: =X82+Y82 -> 1898.08 | AA82: =AA81*AA83 -> 979.04 | AB82: =AB81*AB83 -> 999.04 | AC82: =AA82+AB82 -> 1978.08
C83: =C82/C81 -> 0.023252507 | D83: =D82/D81 -> 0.025184609 | E83: =E82/E81 -> 0.05060241 | F83: =F82/F81 -> 0.02442291 | G83: =G82/G81 -> 0.042005794 | H83: =H82/H81 -> 0.063388054 | I83: =I82/I81 -> 0.035284509 | J83: =J82/J81 -> 0.019323019 | ... L83: =L82/L81 -> 0.036865886 | M83: 0.04 | N83: =N82/N81 -> 0.075943132 | O83: 0.04 | P83: 0.04 | Q83: =Q82/Q81 -> 0.079046529 | R83: 0.04 | S83: 0.04 | T83: =T82/T81 -> 0.079089916 | U83: 0.04 | V83: 0.04 | W83: =W82/W81 -> 0.079129526 | X83: 0.04 | Y83: 0.04 | Z83: =Z82/Z81 -> 0.079165832 | AA83: 0.04 | AB83: 0.04 | AC83: =AC82/AC81 -> 0.079199231
B86: Retained earnings
B87: Opening Balance | F87: =E91 -> 3184 | G87: =F91 -> 4019 | H87: =E91 -> 3184 | I87: =H91 -> 3550 | J87: =I91 -> 6722 | K87: =H91 -> 3550 | L87: =K91 -> 3898 | M87: =L91 -> 6693 | N87: =K91 -> 3898 | O87: =N91 -> 8369.6278 | P87: =O91 -> 11789.744 | Q87: =O87 -> 8369.6278 | R87: =Q91 -> 13823.604 | S87: =R91 -> 17556.29 | T87: =Q91 -> 13823.604 | U87: =T91 -> 19887.17 | V87: =U91 -> 23961.713 | W87: =T91 -> 19887.17 | X87: =W91 -> 26627.685 | Y87: =X91 -> 31075.863 | Z87: =W91 -> 26627.685 | AA87: =Z91 -> 34119.244 | AB87: =AA91 -> 38975.536 | AC87: =Z91 -> 34119.244
B88: Net Income | F88: ='Income Statement '!F23 -> 2088 | G88: ='Income Statement '!G23 -> 1896 | H88: ='Income Statement '!H23 -> 3984 | I88: ='Income Statement '!I23 -> 2841 | J88: ='Income Statement '!J23 -> 1991 | K88: ='Income Statement '!K23 -> 4832 | L88: ='Income Statement '!L23 -> 2342 | M88: ='Income Statement '!M26 -> 2129.6278 | N88: =L88+M88 -> 4471.6278 | O88: ='Income Statement '!O23 -> 3420.1167 | P88: ='Income Statement '!P23 -> 2033.8596 | Q88: =O88+P88 -> 5453.9763 | R88: ='Income Statement '!R23 -> 3732.6856 | S88: ='Income Statement '!S23 -> 2330.8806 | T88: =R88+S88 -> 6063.5662 | U88: ='Income Statement '!U23 -> 4074.5429 | V88: ='Income Statement '!V23 -> 2665.9721 | W88: =U88+V88 -> 6740.515 | X88: ='Income Statement '!X23 -> 4448.1781 | Y88: ='Income Statement '!Y23 -> 3043.3807 | Z88: =X88+Y88 -> 7491.5588 | AA88: ='Income Statement '!AA23 -> 4856.2922 | AB88: ='Income Statement '!AB23 -> 3467.8146 | AC88: =AA88+AB88 -> 8324.1069
B89: Dividends | F89: ='Cash Flow'!F43 -> -1040 | G89: ='[1]Financial Statements'!G188 -> 0 | H89: ='[1]Financial Statements'!H188 -> 0 | I89: ='[1]Financial Statements'!I188 -> 0 | J89: ='[1]Financial Statements'!J188 -> 0 | K89: ='[1]Financial Statements'!K188 -> 0 | L89: ='[1]Financial Statements'!L188 -> 0 | M89: =N89-L89 -> 0 | N89: ='[1]Financial Statements'!N188 -> 0
B90: Adjustments | F90: =-(+F87+F88+F89-F91) -> -213 | G90: =-(+G87+G88+G89-G91) -> -2365 | H90: =-(+H87+H88+H89-H91) -> -3618 | I90: =-(+I87+I88+I89-I91) -> 331 | J90: =-(+J87+J88+J89-J91) -> -4815 | K90: =-(+K87+K88+K89-K91) -> -4484 | L90: =-(+L87+L88+L89-L91) -> 453 | M90: =L90 -> 453
B91: Closing Balance | C91: =C49 -> 2890 | D91: =D49 -> 3184 | E91: =E49 -> 3184 | F91: =F49 -> 4019 | G91: =G49 -> 3550 | H91: =H49 -> 3550 | I91: =I49 -> 6722 | J91: =J49 -> 3898 | ... L91: =L49 -> 6693 | M91: =M87+M88-M90 -> 8369.6278 | N91: =M91 -> 8369.6278 | O91: =O87+O88+O89+O90 -> 11789.744 | P91: =P87+P88+P89+P90 -> 13823.604 | Q91: =Q87+Q88+Q89+Q90 -> 13823.604 | R91: =R87+R88+R89+R90 -> 17556.29 | S91: =S87+S88+S89+S90 -> 19887.17 | T91: =T87+T88+T89+T90 -> 19887.17 | U91: =U87+U88+U89+U90 -> 23961.713 | V91: =V87+V88+V89+V90 -> 26627.685 | ... AC91: =AC87+AC88+AC89+AC90 -> 42443.351

Sheet DCF 
A3: Remy Cointreau
A4: Figures in Euro millions, except share data | C4: 2024E | D4: 2025E | E4: 2026E | F4: 2027E | G4: 2028E
A5: DCF | C5: 0.5 | D5: =+C5+1 -> 1.5 | E5: =+D5+1 -> 2.5 | F5: =+E5+1 -> 3.5 | G5: =+F5+1 -> 4.5
A6: Revenues | C6: ='Income Statement '!N5 -> 18556.215 | D6: ='Income Statement '!Q5 -> 20398.436 | E6: ='Income Statement '!T5 -> 22424.88 | F6: ='Income Statement '!W5 -> 24653.968 | G6: ='Income Statement '!Z5 -> 27105.965
A7: EBIT | C7: ='Income Statement '!N14 -> 6791.5747 | D7: ='Income Statement '!Q14 -> 8475.5504 | E7: ='Income Statement '!T14 -> 9317.5377 | F7: ='Income Statement '!W14 -> 10243.724 | G7: ='Income Statement '!Z14 -> 11262.528
A8: Tax | C8: ='Income Statement '!N22 -> 0.2 | D8: ='Income Statement '!Q22 -> 0.2 | E8: ='Income Statement '!T22 -> 0.2 | F8: ='Income Statement '!W22 -> 0.2 | G8: ='Income Statement '!Z22 -> 0.2
A9: EBIT (1-t) | C9: =+C7*(1-C8) -> 5433.2598 | D9: =+D7*(1-D8) -> 6780.4403 | E9: =+E7*(1-E8) -> 7454.0302 | F9: =+F7*(1-F8) -> 8194.979 | G9: =+G7*(1-G8) -> 9010.0228
A10: D&A | C10: ='Income Statement '!N13 -> 829.812 | D10: ='Income Statement '!Q13 -> 846.77692 | E10: ='Income Statement '!T13 -> 872.78705 | F10: ='Income Statement '!W13 -> 907.11835 | G10: ='Income Statement '!Z13 -> 950.03088
A11: NWC | C11: ='Cash Flow'!N13 -> -1226.3334 | D11: ='Cash Flow'!O13 -> -1533.4031 | E11: ='Cash Flow'!P13 -> 1302.7641 | F11: ='Cash Flow'!Q13 -> -230.639 | G11: ='Cash Flow'!R13 -> -2077.9767
A12: Capital expenditures | C12: ='[1]Financial Statements'!Q103 -> 0 | D12: ='[1]Financial Statements'!T103 -> 0 | E12: ='[1]Financial Statements'!W103 -> 0 | F12: ='[1]Financial Statements'!Z103 -> 0 | G12: ='[1]Financial Statements'!AC103 -> 0
A13: Unlevered free cash flows (UFCF) | C13: =+C9+C10+C11+C12 -> 5036.7383 | D13: =+D9+D10+D11+D12 -> 6093.8141 | E13: =+E9+E10+E11+E12 -> 9629.5813 | F13: =+F9+F10+F11+F12 -> 8871.4584 | G13: =+G9+G10+G11+G12 -> 7882.0769
A14: Discounting factor | C14: =1/(1+$C$30)^C5 -> 0.96225045 | D14: =1/(1+$C$30)^D5 -> 0.89097264 | E14: =1/(1+$C$30)^E5 -> 0.82497466 | F14: =1/(1+$C$30)^F5 -> 0.76386543 | G14: =1/(1+$C$30)^G5 -> 0.70728281
A15: FCFF | C15: =+C14*C13 -> 4846.6037 | D15: =+D14*D13 -> 5429.4217 | E15: =+E14*E13 -> 7944.1606 | F15: =+F14*F13 -> 6776.6004 | G15: =+G14*G13 -> 5574.8575
A16: TV | G16: =+(G13*(1+C33))/(C30-C33) -> 99195.194
A17: Enterprise Value | C17: =+SUM(C15:G15)+G16 -> 129766.84
A18: Net Debt | C18: ='Balance Sheet'!L81-'Balance Sheet'!L21 -> 17947
A19: Minority Interest | C19: ='[1]Financial Statements'!Q23 -> 0.1790509
A20: Equity Value | C20: =+C17+C18+C19 -> 147714.02
A21: No. of shares | C21: ='Income Statement '!L31 -> 2247
A22: Target Price | C22: =+C20/C21 -> 65.738325
A23: CMP | C23: 22.74
A24: Change(%) | C24: =+C22/C23-1 -> 1.8908674
A26: Assumptions | F26: Sensitivity Analysis
A27: Equity Risk Premium | C27: 0.05 | F27: =+C22 -> 65.738325 | G27: 0.085 | H27: 0.095 | I27: 0.105 | J27: 0.115 | K27: 0.125
A28: Risk Free rate | C28: 0.0236 | F28: 0.015 | G28: 65.738325 | H28: 65.738325 | I28: 65.738325 | J28: 65.738325 | K28: 65.738325
A29: Beta | C29: 1.62 | F29: 0.025 | G29: 65.738325 | H29: 65.738325 | I29: 65.738325 | J29: 65.738325 | K29: 65.738325
A30: WACC | C30: 0.08 | F30: 0.035 | G30: 65.738325 | H30: 65.738325 | I30: 65.738325 | J30: 65.738325 | K30: 65.738325
A31: Cost of Equity | C31: =+C28+(C29*C27) -> 0.1046 | F31: 0.045 | G31: 65.738325 | H31: 65.738325 | I31: 65.738325 | J31: 65.738325 | K31: 65.738325
A32: Cost of Debt | C32: =[1]Schedules!Q39 -> 0.034782059 | F32: 0.055 | G32: 65.738325 | H32: 65.738325 | I32: 65.738325 | J32: 65.738325 | K32: 65.738325
A33: Growth rate (%) | C33: 0.0005
