Workbook

Sheet Profit and Loss Statement 
A1: In millions of € | B1: H1'19 | C1: H2'19 | D1: FY'19 | E1: H1'20 | F1: H2'20 | G1: H1'21 | H1: H2'21 | I1: H1'22 | J1: H2'22 | K1: H1'23 | L1: H2'23 | M1: H1'24 | N1: H2'24 | O1: H1'25 | P1: H2'25 | Q1: H1'26 | R1: H2'26 | S1: H1'27 | T1: H2'27 | U1: H1'28 | V1: H2'28 | W1: H1'29 | X1: H2'29 | Y1: H1'30 | Z1: H2'30 | AE1: FY'20 | AF1: FY'21 | AG1: FY'22 | AH1: FY'23 | AI1: FY'24 | AJ1: FY'25 | AK1: FY'26 | AL1: FY'27 | AM1: FY'28 | AN1: FY'29 | AO1: FY'30
A3: Revenue | B3: 13597 | C3: =D3-B3 -> 14924 | D3: 28521 | E3: 11156 | F3: =AE3-E3 -> 12614 | G3: 11970 | H3: =AF3-G3 -> 14613 | I3: 16401 | J3: =AG3-I3 -> 18275 | K3: 17436 | L3: =AH3-K3 -> 18939 | M3: 17823 | P3: =AK3-O3 -> 0 | R3: =AM3-Q3 -> 0 | T3: =AO3-S3 -> 0 | V3: =AQ3-U3 -> 0 | X3: =AS3-W3 -> 0 | Z3: =AU3-Y3 -> 0 | AE3: 23770 | AF3: 26583 | AG3: 34676 | AH3: 36375 | AI3: 35955
A4: Excise tax expense | B4: -2154 | C4: =D4-B4 -> -2398 | D4: -4552 | E4: -1913 | F4: =AE4-E4 -> -2142 | G4: -1960 | H4: =AF4-G4 -> -2682 | I4: -2916 | J4: =AG4-I4 -> -3041 | K4: -2912 | L4: =AH4-K4 -> -3101 | M4: -2999 | P4: =AK4-O4 -> 0 | R4: =AM4-Q4 -> 0 | T4: =AO4-S4 -> 0 | V4: =AQ4-U4 -> 0 | X4: =AS4-W4 -> 0 | Z4: =AU4-Y4 -> 0 | AE4: -4055 | AF4: -4642 | AG4: -5957 | AH4: -6013 | AI4: -6134
A5: Net Revenue | B5: =B3+B4 -> 11443 | C5: =C3+C4 -> 12526 | D5: =D3+D4 -> 23969 | E5: =E3+E4 -> 9243 | F5: =F3+F4 -> 10472 | G5: =G3+G4 -> 10010 | H5: =H3+H4 -> 11931 | I5: =I3+I4 -> 13485 | ... M5: =M3+M4 -> 14824 | N5: =AI5-M5 -> 14997 | O5: =O42 -> 15432.843 | P5: =AJ5-O5 -> 19885.332 | Q5: =Q42 -> 16386.674 | R5: =AK5-Q5 -> 22330.016 | S5: =S42 -> 17678.547 | T5: =AL5-S5 -> 25098.108 | U5: =U42 -> 19330.782 | V5: =AM5-U5 -> 28255.609 | W5: =W42 -> 21384.123 | X5: =AN5-W5 -> 31881.428 | Y5: =Y42 -> 23897.321 | Z5: =AO5-Y5 -> 36070.143 | AF5: =AF3+AF4 -> 21941 | AG5: =AG3+AG4 -> 28719 | AH5: =AH3+AH4 -> 30362 | AI5: =AI3+AI4 -> 29821 | AJ5: =AJ42 -> 35318.175 | AK5: =AK42 -> 38716.689 | AL5: =AL42 -> 42776.655 | AM5: =AM42 -> 47586.391 | AN5: =AN42 -> 53265.551 | AO5: =AO42 -> 59967.464
K6: =K5/I5-1 -> 0.077048572 | L6: =L5/J5-1 -> 0.039648155 | M6: =M5/K5-1 -> 0.020655467 | N6: =N5/L5-1 -> -0.053100139 | O6: =O5/M5-1 -> 0.041071431 | P6: =P5/N5-1 -> 0.32595402 | Q6: =Q5/O5-1 -> 0.061805247 | R6: =R5/P5-1 -> 0.12293902 | ... Z6: =Z5/X5-1 -> 0.13138418
A7: Other Income | B7: 78 | C7: =D7-B7 -> 17 | D7: 95 | E7: 5 | F7: =AE7-E7 -> 51 | G7: 194 | H7: =AF7-G7 -> 1327 | I7: 31 | J7: =AG7-I7 -> 116 | K7: 145 | L7: =AH7-K7 -> 248 | M7: 26 | N7: =N5*N8 -> 14.997 | O7: =O8*O5 -> 308.65686 | P7: =AJ7-O7 -> -213.90973 | Q7: =Q8*Q5 -> 327.73347 | R7: =AK7-Q7 -> -223.86924 | S7: =S8*S5 -> 353.57094 | T7: =AL7-S7 -> -238.81515 | U7: =U8*U5 -> 386.61564 | V7: =AM7-U7 -> -258.9569 | W7: =W8*W5 -> 427.68246 | X7: =AN7-W7 -> -284.78839 | Y7: =Y8*Y5 -> 477.94641 | Z7: =AO7-Y7 -> -317.0733 | AE7: 56 | AF7: 1521 | AG7: 147 | AH7: 393 | AI7: 80 | AJ7: =AJ5*AJ8 -> 94.747125 | AK7: =AK5*AK8 -> 103.86423 | AL7: =AL5*AL8 -> 114.75579 | AM7: =AM5*AM8 -> 127.65874 | AN7: =AN5*AN8 -> 142.89407 | AO7: =AO5*AO8 -> 160.87311
I8: =I7/I5 -> 0.0022988506 | J8: =J7/J5 -> 0.0076145464 | K8: =K7/K5 -> 0.0099834756 | L8: =L7/L5 -> 0.015658543 | M8: =M7/M5 -> 0.0017539126 | N8: 0.001 | O8: 0.02 | P8: =P7/P5 -> -0.010757162 | Q8: =O8 -> 0.02 | R8: =R7/R5 -> -0.010025485 | S8: =Q8 -> 0.02 | T8: =T7/T5 -> -0.009515265 | U8: =S8 -> 0.02 | V8: =V7/V5 -> -0.009164796 | W8: =U8 -> 0.02 | X8: =X7/X5 -> -0.0089327363 | Y8: =W8 -> 0.02 | Z8: =Z7/Z5 -> -0.008790464 | AF8: =AF7/AF5 -> 0.069322273 | AG8: =AG7/AG5 -> 0.0051185626 | AH8: =AH7/AH5 -> 0.012943811 | AI8: =AI7/AI5 -> 0.0026826733 | AJ8: =AI8 -> 0.0026826733 | AK8: =AJ8 -> 0.0026826733 | AL8: =AK8 -> 0.0026826733 | AM8: =AL8 -> 0.0026826733 | AN8: =AM8 -> 0.0026826733 | AO8: =AN8 -> 0.0026826733
A9: Raw Materials, consumables and services | B9: -7064 | C9: =D9-B9 -> -7528 | D9: -14592 | E9: -5967 | F9: =AE9-E9 -> -6483 | G9: -5972 | H9: =AF9-G9 -> -7563 | I9: -8580 | J9: =AG9-I9 -> -10038 | K9: -9704 | L9: =AH9-K9 -> -10373 | M9: -9674 | N9: =-N10*N5 -> -10047.99 | O9: =-O10*O5 -> -10071.325 | P9: =AJ9-O9 -> -12801.815 | Q9: =-Q10*Q5 -> -10693.786 | R9: =AK9-Q9 -> -14380.337 | S9: =-S10*S5 -> -11536.85 | T9: =AL9-S9 -> -16166.632 | U9: =-U10*U5 -> -12615.083 | V9: =AM9-U9 -> -18203.333 | W9: =-W10*W5 -> -13955.073 | X9: =AN9-W9 -> -20541.342 | Y9: =-Y10*Y5 -> -15595.162 | Z9: =AO9-Y9 -> -23241.619 | AE9: -12450 | AF9: -13535 | AG9: -18618 | AH9: -20077 | AI9: -19313 | AJ9: =-AJ10*AJ5 -> -22873.14 | AK9: =-AK10*AK5 -> -25074.123 | AL9: =-AL10*AL5 -> -27703.482 | AM9: =-AM10*AM5 -> -30818.416 | AN9: =-AN10*AN5 -> -34496.415 | AO9: =-AO10*AO5 -> -38836.78
B10: =-B9/B5 -> 0.61732063 | C10: =-C9/C5 -> 0.60098994 | D10: =-D9/D5 -> 0.60878635 | E10: =-E9/E5 -> 0.64556962 | F10: =-F9/F5 -> 0.61907945 | G10: =-G9/G5 -> 0.5966034 | H10: =-H9/H5 -> 0.6338949 | I10: =-I9/I5 -> 0.63626251 | ... M10: =-M9/M5 -> 0.65259039 | N10: 0.67 | O10: =M10 -> 0.65259039 | P10: =-P9/P5 -> 0.64378181 | Q10: =O10 -> 0.65259039 | R10: =-R9/R5 -> 0.64399136 | S10: =Q10 -> 0.65259039 | T10: =-T9/T5 -> 0.64413748 | U10: =S10 -> 0.65259039 | V10: =-V9/V5 -> 0.64423785 | W10: =U10 -> 0.65259039 | X10: =-X9/X5 -> 0.64430431 | Y10: =W10 -> 0.65259039 | Z10: =-Z9/Z5 -> 0.64434506 | AE10: =-AE9/AE5 -> #DIV/0! | AF10: =-AF9/AF5 -> 0.61688164 | AG10: =-AG9/AG5 -> 0.64828163 | AH10: =-AH9/AH5 -> 0.6612542 | AI10: =-AI9/AI5 -> 0.64763086 | AJ10: =AI10 -> 0.64763086 | AK10: =AJ10 -> 0.64763086 | AL10: =AK10 -> 0.64763086 | AM10: =AL10 -> 0.64763086 | AN10: =AM10 -> 0.64763086 | AO10: =AN10 -> 0.64763086
A11: Personnel Expenses | B11: -1898 | C11: =D11-B11 -> -1982 | D11: -3880 | E11: -1716 | F11: =AE11-E11 -> -1953 | G11: -1645 | H11: =AF11-G11 -> -1840 | I11: -1934 | J11: =AG11-I11 -> -2145 | K11: -2110 | L11: =AH11-K11 -> -2243 | M11: -2267 | N11: =-N12*N5 -> -2399.52 | O11: =-O12*O5 -> -2360.1089 | P11: =AJ11-O11 -> -2929.1493 | Q11: =-Q12*Q5 -> -2505.976 | R11: =AK11-Q11 -> -3292.2445 | S11: =-S12*S5 -> -2703.5393 | T11: =AL11-S11 -> -3702.7027 | U11: =-U12*U5 -> -2956.2117 | V11: =AM11-U11 -> -4170.3375 | W11: =-W12*W5 -> -3270.2244 | X11: =AN11-W11 -> -4706.8371 | Y11: =-Y12*Y5 -> -3654.5619 | Z11: =AO11-Y11 -> -5326.1796 | AE11: -3669 | AF11: -3485 | AG11: -4079 | AH11: -4353 | AI11: -4466 | AJ11: =-AJ12*AJ5 -> -5289.2583 | AK11: =-AK12*AK5 -> -5798.2205 | AL11: =-AL12*AL5 -> -6406.242 | AM11: =-AM12*AM5 -> -7126.5492 | AN11: =-AN12*AN5 -> -7977.0615 | AO11: =-AO12*AO5 -> -8980.7415
B12: =-B11/B5 -> 0.16586559 | C12: =-C11/C5 -> 0.15823088 | D12: =-D11/D5 -> 0.16187576 | E12: =-E11/E5 -> 0.18565401 | F12: =-F11/F5 -> 0.18649733 | G12: =-G11/G5 -> 0.16433566 | H12: =-H11/H5 -> 0.1542201 | I12: =-I11/I5 -> 0.14341861 | ... M12: =-M11/M5 -> 0.15292768 | N12: 0.16 | O12: =M12 -> 0.15292768 | P12: =-P11/P5 -> 0.14730201 | Q12: =O12 -> 0.15292768 | R12: =-R11/R5 -> 0.14743583 | S12: =Q12 -> 0.15292768 | T12: =-T11/T5 -> 0.14752916 | U12: =S12 -> 0.15292768 | V12: =-V11/V5 -> 0.14759326 | W12: =U12 -> 0.15292768 | X12: =-X11/X5 -> 0.1476357 | Y12: =W12 -> 0.15292768 | Z12: =-Z11/Z5 -> 0.14766173 | AE12: =-AE11/AE5 -> #DIV/0! | AF12: =-AF11/AF5 -> 0.15883506 | AG12: =-AG11/AG5 -> 0.14203141 | AH12: =-AH11/AH5 -> 0.14337 | AI12: =-AI11/AI5 -> 0.14976024 | AJ12: =AI12 -> 0.14976024 | AK12: =AJ12 -> 0.14976024 | AL12: =AK12 -> 0.14976024 | AM12: =AL12 -> 0.14976024 | AN12: =AM12 -> 0.14976024 | AO12: =AN12 -> 0.14976024
A13: D&A | B13: -911 | C13: =D13-B13 -> -1048 | D13: -1959 | E13: -1480 | F13: =AE13-E13 -> -1394 | G13: -870 | H13: =AF13-G13 -> -1089 | I13: -932 | J13: =AG13-I13 -> -954 | K13: -1244 | L13: =AH13-K13 -> -1852 | M13: -1367 | N13: =AI13-M13 -> -1238 | O13: =-('Balance Sheet'!O58+'Balance Sheet'!O68) -> -1692.54 | P13: =AJ13-O13 -> -1425.72 | Q13: =-('Balance Sheet'!Q58+'Balance Sheet'!Q68) -> -1766.7082 | R13: =AK13-Q13 -> -1514.0154 | S13: =-('Balance Sheet'!S58+'Balance Sheet'!S68) -> -1848.0132 | T13: =AL13-S13 -> -1610.8072 | U13: =-('Balance Sheet'!U58+'Balance Sheet'!U68) -> -1937.8442 | V13: =AM13-U13 -> -1717.7488 | W13: =-('Balance Sheet'!W58+'Balance Sheet'!W68) -> -2037.7756 | X13: =AN13-W13 -> -1836.7148 | Y13: =-('Balance Sheet'!Y58+'Balance Sheet'!Y68) -> -2149.6333 | Z13: =AO13-Y13 -> -1969.8787 | AE13: -2874 | AF13: -1959 | AG13: -1886 | AH13: -3096 | AI13: -2605 | AJ13: =-'Balance Sheet'!AJ58-'Balance Sheet'!AJ68 -> -3118.26 | AK13: =-'Balance Sheet'!AK58-'Balance Sheet'!AK68 -> -3280.7236 | AL13: =-'Balance Sheet'!AL58-'Balance Sheet'!AL68 -> -3458.8204 | AM13: =-'Balance Sheet'!AM58-'Balance Sheet'!AM68 -> -3655.593 | AN13: =-'Balance Sheet'!AN58-'Balance Sheet'!AN68 -> -3874.4904 | AO13: =-'Balance Sheet'!AO58-'Balance Sheet'!AO68 -> -4119.5119
A14: EBIT | B14: =B5+B7+B9+B11+B13 -> 1648 | C14: =C5+C7+C9+C11+C13 -> 1985 | D14: =D5+D7+D9+D11+D13 -> 3633 | E14: =E5+E7+E9+E11+E13 -> 85 | F14: =F5+F7+F9+F11+F13 -> 693 | G14: =G5+G7+G9+G11+G13 -> 1717 | H14: =H5+H7+H9+H11+H13 -> 2766 | I14: =I5+I7+I9+I11+I13 -> 2070 | ... Z14: =Z5+Z7+Z9+Z11+Z13 -> 5215.3931 | AE14: =AE5+AE7+AE9+AE11+AE13 -> -18937 | AF14: =AF5+AF7+AF9+AF11+AF13 -> 4483 | AG14: =AG5+AG7+AG9+AG11+AG13 -> 4283 | AH14: =AH5+AH7+AH9+AH11+AH13 -> 3229 | AI14: =AI5+AI7+AI9+AI11+AI13 -> 3517 | AJ14: =AJ5+AJ7+AJ9+AJ11+AJ13 -> 4132.2638 | AK14: =AK5+AK7+AK9+AK11+AK13 -> 4667.4864 | AL14: =AL5+AL7+AL9+AL11+AL13 -> 5322.8665 | ... AO14: =AO5+AO7+AO9+AO11+AO13 -> 8191.3031
A15: EBITDA | B15: =B14-B13 -> 2559 | C15: =C14-C13 -> 3033 | D15: =D14-D13 -> 5592 | E15: =E14-E13 -> 1565 | F15: =F14-F13 -> 2087 | G15: =G14-G13 -> 2587 | H15: =H14-H13 -> 3855 | I15: =I14-I13 -> 3002 | ... Z15: =Z14-Z13 -> 7185.2718 | AE15: =AE14-AE13 -> -16063 | AF15: =AF14-AF13 -> 6442 | AG15: =AG14-AG13 -> 6169 | AH15: =AH14-AH13 -> 6325 | AI15: =AI14-AI13 -> 6122 | AJ15: =AJ14-AJ13 -> 7250.5238 | AK15: =AK14-AK13 -> 7948.21 | AL15: =AL14-AL13 -> 8781.6869 | ... AO15: =AO14-AO13 -> 12310.815
A16: Interest Income | B16: 28 | C16: =D16-B16 -> 47 | D16: 75 | E16: 32 | F16: =AE16-E16 -> 18 | G16: 24 | H16: =AF16-G16 -> 25 | I16: 29 | J16: =AG16-I16 -> 45 | K16: 46 | L16: =AH16-K16 -> 44 | M16: 47 | N16: =AI16-M16 -> 63 | P16: =AK16-O16 -> 0 | R16: =AM16-Q16 -> 0 | T16: =AO16-S16 -> 0 | V16: =AQ16-U16 -> 0 | X16: =AS16-W16 -> 0 | Z16: =AU16-Y16 -> 0 | AE16: 50 | AF16: 49 | AG16: 74 | AH16: 90 | AI16: 110
A17: Interest Expenses | B17: -255 | C17: =D17-B17 -> -274 | D17: -529 | E17: -239 | F17: =AE17-E17 -> -258 | G17: -226 | H17: =AF17-G17 -> -236 | I17: -214 | J17: =AG17-I17 -> -244 | K17: -295 | L17: =AH17-K17 -> -345 | M17: -342 | N17: =+'Balance Sheet'!N90 -> -377 | O17: =+'Balance Sheet'!O90 -> -364.5 | P17: =+'Balance Sheet'!P90 -> -374.5 | Q17: =+'Balance Sheet'!Q90 -> -374.5 | R17: =+'Balance Sheet'!R90 -> -384.5 | S17: =+'Balance Sheet'!S90 -> -384.5 | T17: =+'Balance Sheet'!T90 -> -394.5 | U17: =+'Balance Sheet'!U90 -> -394.5 | ... Z17: =+'Balance Sheet'!Z90 -> -424.5 | AE17: -497 | AF17: -462 | AG17: -458 | AH17: -640 | AI17: -680 | AJ17: =+'Balance Sheet'!AJ90 -> -739 | AK17: =+'Balance Sheet'!AK90 -> -759 | AL17: =+'Balance Sheet'!AL90 -> -779 | AM17: =+'Balance Sheet'!AM90 -> -799 | AN17: =+'Balance Sheet'!AN90 -> -819 | AO17: =+'Balance Sheet'!AO90 -> -839
A18: Other net finance income/expenses | B18: -25 | C18: =D18-B18 -> -34 | D18: -59 | E18: -58 | F18: =AE18-E18 -> -85 | G18: 24 | H18: =AF18-G18 -> -10 | I18: 37 | J18: =AG18-I18 -> 11 | K18: -186 | L18: =AH18-K18 -> -189 | M18: -142 | N18: =AI18-M18 -> -93 | P18: =AK18-O18 -> 0 | R18: =AM18-Q18 -> 0 | T18: =AO18-S18 -> 0 | V18: =AQ18-U18 -> 0 | X18: =AS18-W18 -> 0 | Z18: =AU18-Y18 -> 0 | AE18: -143 | AF18: 14 | AG18: 48 | AH18: -375 | AI18: -235
A19: Net finance expense | B19: =SUM(B16:B18) -> -252 | C19: =SUM(C16:C18) -> -261 | D19: =SUM(D16:D18) -> -513 | E19: =SUM(E16:E18) -> -265 | F19: =SUM(F16:F18) -> -325 | G19: =SUM(G16:G18) -> -178 | H19: =SUM(H16:H18) -> -221 | I19: =SUM(I16:I18) -> -148 | ... Z19: =SUM(Z16:Z18) -> -424.5 | AE19: =SUM(AE16:AE18) -> -590 | AF19: =SUM(AF16:AF18) -> -399 | AG19: =SUM(AG16:AG18) -> -336 | AH19: =SUM(AH16:AH18) -> -925 | AI19: =SUM(AI16:AI18) -> -805 | AJ19: =SUM(AJ16:AJ18) -> -739 | AK19: =SUM(AK16:AK18) -> -759 | AL19: =SUM(AL16:AL18) -> -779 | ... AO19: =SUM(AO16:AO18) -> -839
A20: Share of profit/(loss) of associates and joint ventures | B20: 80 | C20: =D20-B20 -> 84 | D20: 164 | E20: -41 | F20: =AE20-E20 -> 10 | G20: 70 | H20: =AF20-G20 -> 180 | I20: 80 | J20: =AG20-I20 -> 143 | K20: 100 | L20: =AH20-K20 -> 118 | M20: -766 | N20: =AI20-M20 -> 61 | P20: =AK20-O20 -> 0 | R20: =AM20-Q20 -> 0 | T20: =AO20-S20 -> 0 | V20: =AQ20-U20 -> 0 | X20: =AS20-W20 -> 0 | Z20: =AU20-Y20 -> 0 | AE20: -31 | AF20: 250 | AG20: 223 | AH20: 218 | AI20: -705
A21: PBT | B21: =B14+B19+B20 -> 1476 | C21: =C14+C19+C20 -> 1808 | D21: =D14+D19+D20 -> 3284 | E21: =E14+E19+E20 -> -221 | F21: =F14+F19+F20 -> 378 | G21: =G14+G19+G20 -> 1609 | H21: =H14+H19+H20 -> 2725 | I21: =I14+I19+I20 -> 2002 | ... Z21: =Z14+Z19+Z20 -> 4790.8931 | AE21: =AE14+AE19+AE20 -> -19558 | AF21: =AF14+AF19+AF20 -> 4334 | AG21: =AG14+AG19+AG20 -> 4170 | AH21: =AH14+AH19+AH20 -> 2522 | AI21: =AI14+AI19+AI20 -> 2007 | AJ21: =AJ14+AJ19+AJ20 -> 3393.2638 | AK21: =AK14+AK19+AK20 -> 3908.4864 | AL21: =AL14+AL19+AL20 -> 4543.8665 | ... AO21: =AO14+AO19+AO20 -> 7352.3031
A22: Tax | B22: -438 | C22: =D22-B22 -> -472 | D22: -910 | E22: -51 | F22: =AE22-E22 -> -194 | G22: -440 | H22: =AF22-G22 -> -359 | I22: -547 | J22: =AG22-I22 -> -584 | K22: -89 | L22: =AH22-K22 -> -32 | M22: -387 | N22: =-N23*N21 -> -137.26818 | O22: =-O21*O23 -> -175.42361 | P22: =AJ22-O22 -> -1254.9208 | Q22: =-Q21*Q23 -> -192.28119 | R22: =AK22-Q22 -> -1455.2422 | S22: =-S21*S23 -> -218.29017 | T22: =AL22-S22 -> -1697.0616 | U22: =-U21*U23 -> -253.92626 | V22: =AM22-U22 -> -1986.2632 | W22: =-W21*W23 -> -300.1925 | X22: =AN22-W22 -> -2330.7446 | Y22: =-Y21*Y23 -> -358.59739 | Z22: =AO22-Y22 -> -2740.5797 | AE22: -245 | AF22: -799 | AG22: -1131 | AH22: -121 | AI22: -846 | AJ22: =-AJ23*AJ21 -> -1430.3444 | AK22: =-AK23*AK21 -> -1647.5234 | AL22: =-AL23*AL21 -> -1915.3518 | AM22: =-AM23*AM21 -> -2240.1895 | AN22: =-AN23*AN21 -> -2630.9371 | AO22: =-AO23*AO21 -> -3099.1771
B23: =-B22/B21 -> 0.29674797 | C23: =-C22/C21 -> 0.26106195 | D23: =-D22/D21 -> 0.2771011 | E23: =-E22/E21 -> -0.23076923 | F23: =-F22/F21 -> 0.51322751 | G23: =-G22/G21 -> 0.27346178 | H23: =-H22/H21 -> 0.13174312 | I23: =-I22/I21 -> 0.27322677 | ... M23: =-M22/M21 -> 1.1415929 | N23: 0.14 | O23: 0.14 | P23: =-P22/P21 -> 0.58634637 | Q23: 0.14 | R23: =-R22/R21 -> 0.57404887 | S23: 0.14 | T23: =-T22/T21 -> 0.56859634 | U23: 0.14 | V23: =-V22/V21 -> 0.56738494 | W23: 0.14 | X23: =-X22/X21 -> 0.56885636 | Y23: 0.14 | Z23: =-Z22/Z21 -> 0.57203941 | AE23: =-AE22/AE21 -> -0.012526843 | AF23: =-AF22/AF21 -> 0.18435625 | AG23: =-AG22/AG21 -> 0.27122302 | AH23: =-AH22/AH21 -> 0.047977795 | AI23: =-AI22/AI21 -> 0.42152466 | AJ23: =AI23 -> 0.42152466 | AK23: =AJ23 -> 0.42152466 | AL23: =AK23 -> 0.42152466 | AM23: =AL23 -> 0.42152466 | AN23: =AM23 -> 0.42152466 | AO23: =AN23 -> 0.42152466
A24: PAT | B24: =B21+B22 -> 1038 | C24: =C21+C22 -> 1336 | D24: =D21+D22 -> 2374 | E24: =E21+E22 -> -272 | F24: =F21+F22 -> 184 | G24: =G21+G22 -> 1169 | H24: =H21+H22 -> 2366 | I24: =I21+I22 -> 1455 | ... Z24: =Z21+Z22 -> 2050.3134 | AE24: =AE21+AE22 -> -19803 | AF24: =AF21+AF22 -> 3535 | AG24: =AG21+AG22 -> 3039 | AH24: =AH21+AH22 -> 2401 | AI24: =AI21+AI22 -> 1161 | AJ24: =AJ21+AJ22 -> 1962.9194 | AK24: =AK21+AK22 -> 2260.963 | AL24: =AL21+AL22 -> 2628.5147 | ... AO24: =AO21+AO22 -> 4253.126
A26: Attributable to:
A27: Shareholders | B27: 471 | C27: =D27-B27 -> 616 | D27: 1087 | E27: -297 | F27: =AE27-E27 -> 93 | G27: 1034 | H27: =AF27-G27 -> 2290 | I27: 1265 | J27: =AG27-I27 -> 1417 | K27: 1156 | L27: =AH27-K27 -> 1148 | M27: -95 | N27: =M27/M24*N24 -> 1668.8706 | O27: =N27/N24*O24 -> 2132.7543 | P27: =AJ27-O27 -> -479.23566 | Q27: =Q30 -> 2337.7043 | R27: =AJ27-Q27 -> -684.18566 | S27: =S30 -> 2653.9148 | T27: =AL27-S27 -> -439.71376 | U27: =U30 -> 3087.169 | V27: =AM27-U27 -> -497.4464 | W27: =W30 -> 3649.6618 | X27: =AN27-W27 -> -608.22395 | Y27: =Y30 -> 4359.7332 | Z27: =AO27-Y27 -> -776.99656 | AE27: -204 | AF27: 3324 | AG27: 2682 | AH27: 2304 | AI27: 978 | AJ27: =AI27/AI24*AJ24 -> 1653.5187 | AK27: =AJ27/AJ24*AK24 -> 1904.5838 | AL27: =AK27/AK24*AL24 -> 2214.201 | AM27: =AL27/AL24*AM24 -> 2589.7226 | AN27: =AM27/AM24*AN24 -> 3041.4379 | AO27: =AN27/AN24*AO24 -> 3582.7366
A28: Minority Interests | B28: =465+102 -> 567 | C28: =D28-B28 -> 720 | D28: =1079+208 -> 1287 | E28: 25 | F28: =AE28-E28 -> 91 | G28: 135 | H28: =AF28-G28 -> 76 | I28: 190 | J28: =AG28-I28 -> 167 | K28: 31 | L28: =AH28-K28 -> 66 | M28: 47 | N28: =M28/M24*N24 -> -825.65176 | O28: =N28/N24*O24 -> -1055.1521 | P28: =AJ28-O28 -> 1364.5529 | Q28: =Q31 -> -1156.5485 | R28: =AK28-Q28 -> 1512.9276 | S28: =S31 -> -1312.9894 | T28: =AL28-S28 -> 1727.3031 | U28: =U31 -> -1527.3362 | V28: =AM28-U28 -> 2011.9162 | W28: =W31 -> -1805.6222 | X28: =AN28-W28 -> 2374.7256 | Y28: =Y31 -> -2156.9206 | Z28: =AO28-Y28 -> 2827.31 | AE28: 116 | AF28: 211 | AG28: 357 | AH28: 97 | AI28: 183 | AJ28: =AI28/AI24*AJ24 -> 309.40073 | AK28: =AJ28/AJ24*AK24 -> 356.37918 | AL28: =AK28/AK24*AL24 -> 414.31369 | AM28: =AL28/AL24*AM24 -> 484.58 | AN28: =AM28/AM24*AN24 -> 569.10341 | AO28: =AN28/AN24*AO24 -> 670.38937
N30: =N27/N24 -> 1.9791667 | Q30: =N$30*Q24 -> 2337.7043 | S30: =$N$30*S24 -> 2653.9148 | U30: =$N$30*U24 -> 3087.169 | W30: =$N$30*W24 -> 3649.6618 | Y30: =$N$30*Y24 -> 4359.7332
N31: =N28/N24 -> -0.97916667 | Q31: =N$31*Q24 -> -1156.5485 | S31: =$N$31*S24 -> -1312.9894 | U31: =$N$31*U24 -> -1527.3362 | W31: =$N$31*W24 -> -1805.6222 | Y31: =$N$31*Y24 -> -2156.9206
A32: EPS
A33: Basic | B33: =B27/B37 -> 1.6352454 | C33: =C27/C37 -> 2.1386649 | D33: =D27/D37 -> 3.7739102 | E33: =E27/E37 -> -0.51604855 | F33: =F27/F37 -> 0.16156335 | G33: =G27/G37 -> 1.7959493 | H33: =H27/H37 -> 3.977488 | I33: =I27/I37 -> 2.1977012 | ... Z33: =Z27/Z37 -> -1.3870258 | AE33: =AE27/AE37 -> -0.35439703 | AF33: =AF27/AF37 -> 5.7734367 | AG33: =AG27/AG37 -> 4.6597812 | AH33: =AH27/AH37 -> 4.0891024 | AI33: =AI27/AI37 -> 1.7458395 | AJ33: =AJ27/AJ37 -> 2.9517159 | AK33: =AK27/AK37 -> 3.3998953 | AL33: =AL27/AL37 -> 3.9525967 | ... AO33: =AO27/AO37 -> 6.3955859
A34: Diluted | B34: =B27/B38 -> 1.6352454 | C34: =C27/C38 -> 2.1386649 | D34: =D27/D38 -> 3.7739102 | E34: =E27/E38 -> -0.51604855 | F34: =F27/F38 -> 0.16156335 | G34: =G27/G38 -> 1.79576 | H34: =H27/H38 -> 3.9759057 | I34: =I27/I38 -> 2.1971904 | ... Z34: =Z27/Z38 -> -1.3859124 | AE34: =AE27/AE38 -> -0.35439703 | AF34: =AF27/AF38 -> 5.77114 | AG34: =AG27/AG38 -> 4.6560389 | AH34: =AH27/AH38 -> 4.085254 | AI34: =AI27/AI38 -> 1.7444379 | AJ34: =AJ27/AJ38 -> 2.9493463 | AK34: =AK27/AK38 -> 3.397166 | AL34: =AL27/AL38 -> 3.9494236 | ... AO34: =AO27/AO38 -> 6.3904517
A36: Shares
A37: WASO - Basic | B37: 288.03017 | C37: =D37 -> 288.03017 | D37: 288.03017 | E37: 575.52725 | F37: =AE37 -> 575.6256 | G37: 575.74008 | H37: =AF37 -> 575.74027 | I37: 575.60145 | J37: =AG37 -> 575.5635 | K37: 566.68019 | L37: =AH37 -> 563.44885 | M37: 560.21409 | N37: =AI37 -> 560.18896 | O37: =N37 -> 560.18896 | P37: =AJ37 -> 560.18896 | Q37: =P37 -> 560.18896 | R37: =AK37 -> 560.18896 | S37: =R37 -> 560.18896 | T37: =AL37 -> 560.18896 | U37: =T37 -> 560.18896 | V37: =AM37 -> 560.18896 | W37: =V37 -> 560.18896 | X37: =AN37 -> 560.18896 | Y37: =X37 -> 560.18896 | Z37: =AO37 -> 560.18896 | AE37: 575.6256 | AF37: 575.74027 | AG37: 575.5635 | AH37: 563.44885 | AI37: 560.18896 | AJ37: =AI37 -> 560.18896 | AK37: =AJ37 -> 560.18896 | AL37: =AK37 -> 560.18896 | AM37: =AL37 -> 560.18896 | AN37: =AM37 -> 560.18896 | AO37: =AN37 -> 560.18896
A38: WASO - Diluted | B38: 288.03017 | C38: =D38 -> 288.03017 | D38: 288.03017 | E38: 575.52725 | F38: =AE38 -> 575.6256 | G38: 575.80076 | H38: =AF38 -> 575.96939 | I38: 575.73527 | J38: =AG38 -> 576.02612 | K38: 566.90014 | L38: =AH38 -> 563.97962 | M38: 560.44677 | N38: =AI38 -> 560.63903 | O38: =N38 -> 560.63903 | P38: =O38 -> 560.63903 | Q38: =P38 -> 560.63903 | R38: =Q38 -> 560.63903 | S38: =R38 -> 560.63903 | T38: =S38 -> 560.63903 | U38: =T38 -> 560.63903 | V38: =U38 -> 560.63903 | ... Z38: =Y38 -> 560.63903 | AE38: 575.6256 | AF38: 575.96939 | AG38: 576.02612 | AH38: 563.97962 | AI38: 560.63903 | AJ38: =AI38 -> 560.63903 | AK38: =AJ38 -> 560.63903 | AL38: =AK38 -> 560.63903 | AM38: =AL38 -> 560.63903 | AN38: =AM38 -> 560.63903 | AO38: =AN38 -> 560.63903
A41: eia | AG41: =AG42-AG5 -> -25 | AH41: =AH42-AH5 -> -54 | AI41: =AI42-AI5 -> 2702.624
A42: Net Revenue (beia) | I42: =Total!I17 -> 13485 | J42: =J5 -> 15234 | K42: =Total!K17 -> 14514 | L42: =L5 -> 15838 | M42: =Total!M17 -> 14815 | N42: =N5 -> 14997 | O42: =Total!O17 -> 15432.843 | P42: =P5 -> 19885.332 | Q42: =Total!Q17 -> 16386.674 | R42: =R5 -> 22330.016 | S42: =Total!S17 -> 17678.547 | T42: =T5 -> 25098.108 | U42: =Total!U17 -> 19330.782 | V42: =V5 -> 28255.609 | W42: =Total!W17 -> 21384.123 | X42: =X5 -> 31881.428 | Y42: =Total!Y17 -> 23897.321 | Z42: =Z5 -> 36070.143 | AG42: =Total!AG17 -> 28694 | AH42: =Total!AH17 -> 30308 | AI42: =Total!AI17 -> 32523.624 | AJ42: =Total!AJ17 -> 35318.175 | AK42: =Total!AK17 -> 38716.689 | AL42: =Total!AL17 -> 42776.655 | AM42: =Total!AM17 -> 47586.391 | AN42: =Total!AN17 -> 53265.551 | AO42: =Total!AO17 -> 59967.464

Sheet Balance Sheet
A1: ='Profit and Loss Statement '!A1 -> In millions of € | B1: ='Profit and Loss Statement '!B1 -> H1'19 | C1: ='Profit and Loss Statement '!C1 -> H2'19 | D1: ='Profit and Loss Statement '!D1 -> FY'19 | E1: ='Profit and Loss Statement '!E1 -> H1'20 | F1: ='Profit and Loss Statement '!F1 -> H2'20 | G1: ='Profit and Loss Statement '!G1 -> H1'21 | H1: ='Profit and Loss Statement '!H1 -> H2'21 | ... Z1: ='Profit and Loss Statement '!Z1 -> H2'30 | AE1: ='Profit and Loss Statement '!AE1 -> FY'20 | AF1: ='Profit and Loss Statement '!AF1 -> FY'21 | AG1: ='Profit and Loss Statement '!AG1 -> FY'22 | AH1: ='Profit and Loss Statement '!AH1 -> FY'23 | AI1: ='Profit and Loss Statement '!AI1 -> FY'24 | AJ1: ='Profit and Loss Statement '!AJ1 -> FY'25 | AK1: ='Profit and Loss Statement '!AK1 -> FY'26 | AL1: ='Profit and Loss Statement '!AL1 -> FY'27 | ... AO1: ='Profit and Loss Statement '!AO1 -> FY'30
A3: Intangible Assets | B3: 17569 | C3: =D3 -> 17769 | D3: 17769 | E3: 16461 | F3: =AE3 -> 15767 | G3: 16112 | H3: =AF3 -> 20762 | I3: 21357 | J3: =AG3 -> 21408 | K3: 22653 | L3: =AH3 -> 21781 | M3: 21771 | N3: =AI3 -> 21701 | O3: =O70 -> 21024.328 | P3: =P70 -> 20946.182 | Q3: =Q70 -> 20268.453 | R3: =R70 -> 20211.221 | S3: =S70 -> 19534.796 | T3: =T70 -> 19501.374 | U3: =U70 -> 18828.638 | V3: =V70 -> 18822.513 | ... Z3: =Z70 -> 17586.019 | AE3: 15767 | AF3: 20762 | AG3: 21408 | AH3: 21781 | AI3: 21701 | AJ3: =AJ70 -> 20946.182 | AK3: =AK70 -> 20211.221 | AL3: =AL70 -> 19501.374 | AM3: =AM70 -> 18822.513 | AN3: =AN70 -> 18181.41 | AO3: =AO70 -> 17586.019 | AU3: =P3-Q3 -> 677.72872
A4: PP&E | B4: 12545 | C4: =D4 -> 13269 | D4: 13269 | E4: 11857 | F4: =AE4 -> 11551 | G4: 11668 | H4: =AF4 -> 12401 | I4: 12697 | J4: =AG4 -> 13623 | K4: 14299 | L4: =AH4 -> 14772 | M4: 14463 | N4: =AI4 -> 14677 | O4: =O60 -> 14741.431 | P4: =P60+P61 -> 14785.831 | Q4: =Q60 -> 14843.918 | R4: =R60+R61 -> 14950.236 | S4: =S60 -> 15016.146 | T4: =T60+T61 -> 15195.628 | U4: =U60 -> 15283.675 | V4: =V60+V61 -> 15549.944 | W4: =W60 -> 15675.535 | X4: =X60+X61 -> 16045.145 | Y4: =Y60 -> 16225.65 | Z4: =Z60+Z61 -> 16718.747 | AE4: 11551 | AF4: 12401 | AG4: 13623 | AH4: 14772 | AI4: 14677 | AJ4: =AJ60 -> 14785.831 | AK4: =AK60+$AI$61 -> 14950.236 | AL4: =AL60+$AI$61 -> 15195.628 | AM4: =AM60+$AI$61 -> 15549.944 | AN4: =AN60+$AI$61 -> 16045.145 | AO4: =AO60+$AI$61 -> 16718.747 | AU4: =P4-Q4 -> -58.087698
A6: Investments in associates and JV | B6: 4884 | C6: =D6 -> 4868 | D6: 4868 | E6: 4705 | F6: =AE6 -> 4437 | G6: 5248 | H6: =AF6 -> 4148 | I6: 4412 | J6: =AG6 -> 4296 | K6: 4242 | L6: =AH6 -> 4130 | M6: 3452 | N6: =AI6 -> 3500 | O6: =N6 -> 3500 | P6: =AJ6 -> 3500 | Q6: =P6 -> 3500 | R6: =AK6 -> 3500 | S6: =R6 -> 3500 | T6: =AL6 -> 3500 | U6: =T6 -> 3500 | V6: =AM6 -> 3500 | W6: =V6 -> 3500 | X6: =AN6 -> 3500 | Y6: =X6 -> 3500 | Z6: =AO6 -> 3500 | AE6: 4437 | AF6: 4148 | AG6: 4296 | AH6: 4130 | AI6: 3500 | AJ6: =AI6 -> 3500 | AK6: =AJ6 -> 3500 | AL6: =AK6 -> 3500 | AM6: =AL6 -> 3500 | AN6: =AM6 -> 3500 | AO6: =AN6 -> 3500 | AU6: =P6-Q6 -> 0
A7: Loans and advances to customers | B7: 348 | C7: =D7 -> 277 | D7: 277 | E7: 183 | F7: =AE7 -> 194 | G7: 195 | H7: =AF7 -> 209 | I7: 200 | J7: =AG7 -> 216 | K7: 251 | L7: =AH7 -> 239 | M7: 270 | N7: =AI7 -> 258 | O7: =N7 -> 258 | P7: =AJ7 -> 258 | Q7: =P7 -> 258 | R7: =AK7 -> 258 | S7: =R7 -> 258 | T7: =AL7 -> 258 | U7: =T7 -> 258 | V7: =AM7 -> 258 | W7: =V7 -> 258 | X7: =AN7 -> 258 | Y7: =X7 -> 258 | Z7: =AO7 -> 258 | AE7: 194 | AF7: 209 | AG7: 216 | AH7: 239 | AI7: 258 | AJ7: =AI7 -> 258 | AK7: =AJ7 -> 258 | AL7: =AK7 -> 258 | AM7: =AL7 -> 258 | AN7: =AM7 -> 258 | AO7: =AN7 -> 258 | AU7: =P7-Q7 -> 0
A8: Deferred tax assets | B8: 662 | C8: =D8 -> 647 | D8: 647 | E8: 701 | F8: =AE8 -> 779 | G8: 740 | H8: =AF8 -> 682 | I8: 642 | J8: =AG8 -> 618 | K8: 871 | L8: =AH8 -> 1292 | M8: 1215 | N8: =AI8 -> 1264 | O8: =N8 -> 1264 | P8: =AJ8 -> 1264 | Q8: =P8 -> 1264 | R8: =AK8 -> 1264 | S8: =R8 -> 1264 | T8: =AL8 -> 1264 | U8: =T8 -> 1264 | V8: =AM8 -> 1264 | W8: =V8 -> 1264 | X8: =AN8 -> 1264 | Y8: =X8 -> 1264 | Z8: =AO8 -> 1264 | AE8: 779 | AF8: 682 | AG8: 618 | AH8: 1292 | AI8: 1264 | AJ8: =AI8 -> 1264 | AK8: =AJ8 -> 1264 | AL8: =AK8 -> 1264 | AM8: =AL8 -> 1264 | AN8: =AM8 -> 1264 | AO8: =AN8 -> 1264 | AU8: =P8-Q8 -> 0
A9: Equity instruments | J9: =AG9 -> 145 | K9: 598 | L9: =AH9 -> 562 | M9: 535 | N9: =AI9 -> 465 | O9: =N9 -> 465 | P9: =AJ9 -> 465 | Q9: =P9 -> 465 | R9: =AK9 -> 465 | S9: =R9 -> 465 | T9: =AL9 -> 465 | U9: =T9 -> 465 | V9: =AM9 -> 465 | W9: =V9 -> 465 | X9: =AN9 -> 465 | Y9: =X9 -> 465 | Z9: =AO9 -> 465 | AG9: 145 | AH9: 562 | AI9: 465 | AJ9: =AI9 -> 465 | AK9: =AJ9 -> 465 | AL9: =AK9 -> 465 | AM9: =AL9 -> 465 | AN9: =AM9 -> 465 | AO9: =AN9 -> 465 | AU9: =P9-Q9 -> 0
A10: Other non-current assets | B10: 1401 | C10: =D10 -> 1255 | D10: 1255 | E10: 1115 | F10: =AE10 -> 884 | G10: 1112 | H10: =AF10 -> 1070 | I10: 1276 | J10: =AG10 -> 1085 | K10: 1155 | L10: =AH10 -> 978 | M10: 988 | N10: =AI10 -> 1009 | O10: =N10 -> 1009 | P10: =AJ10 -> 1009 | Q10: =P10 -> 1009 | R10: =AK10 -> 1009 | S10: =R10 -> 1009 | T10: =AL10 -> 1009 | U10: =T10 -> 1009 | V10: =AM10 -> 1009 | W10: =V10 -> 1009 | X10: =AN10 -> 1009 | Y10: =X10 -> 1009 | Z10: =AO10 -> 1009 | AE10: 884 | AF10: 1070 | AG10: 1085 | AH10: 978 | AI10: 1009 | AJ10: =AI10 -> 1009 | AK10: =AJ10 -> 1009 | AL10: =AK10 -> 1009 | AM10: =AL10 -> 1009 | AN10: =AM10 -> 1009 | AO10: =AN10 -> 1009 | AU10: =P10-Q10 -> 0
A11: Total non-current assets | B11: =SUM(B3:B4)+SUM(B6:B10) -> 37409 | C11: =SUM(C3:C4)+SUM(C6:C10) -> 38085 | D11: =SUM(D3:D4)+SUM(D6:D10) -> 38085 | E11: =SUM(E3:E4)+SUM(E6:E10) -> 35022 | F11: =SUM(F3:F4)+SUM(F6:F10) -> 33612 | G11: =SUM(G3:G4)+SUM(G6:G10) -> 35075 | H11: =SUM(H3:H4)+SUM(H6:H10) -> 39272 | I11: =SUM(I3:I4)+SUM(I6:I10) -> 40584 | ... Z11: =SUM(Z3:Z4)+SUM(Z6:Z10) -> 40800.766 | AE11: =SUM(AE3:AE4)+SUM(AE6:AE10) -> 33612 | AF11: =SUM(AF3:AF4)+SUM(AF6:AF10) -> 39272 | AG11: =SUM(AG3:AG4)+SUM(AG6:AG10) -> 41391 | AH11: =SUM(AH3:AH4)+SUM(AH6:AH10) -> 43754 | AI11: =SUM(AI3:AI4)+SUM(AI6:AI10) -> 42874 | AJ11: =SUM(AJ3:AJ4)+SUM(AJ6:AJ10) -> 42228.012 | AK11: =SUM(AK3:AK4)+SUM(AK6:AK10) -> 41657.457 | AL11: =SUM(AL3:AL4)+SUM(AL6:AL10) -> 41193.002 | ... AO11: =SUM(AO3:AO4)+SUM(AO6:AO10) -> 40800.766
A13: Inventories | B13: 2275 | C13: =D13 -> 2213 | D13: 2213 | E13: 2163 | F13: =AE13 -> 1958 | G13: 2345 | H13: =AF13 -> 2438 | I13: 3143 | J13: =AG13 -> 3250 | K13: 4370 | L13: =AH13 -> 3721 | M13: 3859 | N13: =AI13 -> 3572 | O13: =O99 -> 3760.9109 | P13: =AJ13 -> 4328.4016 | Q13: =Q99 -> 3566.8554 | R13: =AK13 -> 4744.9048 | S13: =S99 -> 3756.5143 | T13: =AL13 -> 5242.472 | U13: =U99 -> 4037.7976 | V13: =AM13 -> 5815.9926 | W13: =W99 -> 4413.6596 | X13: =AN13 -> 6527.9335 | Y13: =Y99 -> 4893.1346 | Z13: =AO13 -> 7349.2831 | AE13: 1958 | AF13: 2438 | AG13: 3250 | AH13: 3721 | AI13: 3572 | AJ13: =AJ99 -> 4328.4016 | AK13: =AK99 -> 4744.9048 | AL13: =AL99 -> 5242.472 | AM13: =AM99 -> 5815.9926 | AN13: =AN99 -> 6527.9335 | AO13: =AO99 -> 7349.2831 | AU13: =P13-Q13 -> 761.54626
A14: Trade and other receivables | B14: 4595 | C14: =D14 -> 4123 | D14: 4123 | E14: 3983 | F14: =AE14 -> 2807 | G14: 3911 | H14: =AF14 -> 3662 | I14: 4966 | J14: =AG14 -> 4531 | K14: 5715 | L14: =AH14 -> 5019 | M14: 5385 | N14: =AI14 -> 4588 | O14: =O100 -> 5072.833 | P14: =AJ14 -> 5838.2821 | Q14: =Q100 -> 4811.0849 | R14: =AK14 -> 6400.0746 | S14: =S100 -> 5066.9028 | T14: =AL14 -> 7071.2085 | U14: =U100 -> 5446.3065 | V14: =AM14 -> 7844.7908 | W14: =W100 -> 5953.2806 | X14: =AN14 -> 8805.0788 | Y14: =Y100 -> 6600.0114 | Z14: =AO14 -> 9912.9406 | AE14: 2807 | AF14: 3662 | AG14: 4531 | AH14: 5019 | AI14: 4588 | AJ14: =AJ100 -> 5838.2821 | AK14: =AK100 -> 6400.0746 | AL14: =AL100 -> 7071.2085 | AM14: =AM100 -> 7844.7908 | AN14: =AN100 -> 8805.0788 | AO14: =AO100 -> 9912.9406 | AU14: =P14-Q14 -> 1027.1972
A15: Current tax assets | B15: 65 | C15: =D15 -> 123 | D15: 123 | E15: 204 | F15: =AE15 -> 154 | G15: 105 | H15: =AF15 -> 97 | I15: 107 | J15: =AG15 -> 84 | K15: 180 | L15: =AH15 -> 196 | M15: 166 | N15: =AI15 -> 165 | O15: =N15 -> 165 | P15: =AJ15 -> 165 | Q15: =P15 -> 165 | R15: =AK15 -> 165 | S15: =R15 -> 165 | T15: =AL15 -> 165 | U15: =T15 -> 165 | V15: =AM15 -> 165 | W15: =V15 -> 165 | X15: =AN15 -> 165 | Y15: =X15 -> 165 | Z15: =AO15 -> 165 | AE15: 154 | AF15: 97 | AG15: 84 | AH15: 196 | AI15: 165 | AJ15: =AI15 -> 165 | AK15: =AJ15 -> 165 | AL15: =AK15 -> 165 | AM15: =AL15 -> 165 | AN15: =AM15 -> 165 | AO15: =AN15 -> 165 | AU15: =P15-Q15 -> 0
A16: Derivative assets | B16: 24 | C16: =D16 -> 28 | D16: 28 | E16: 97 | F16: =AE16 -> 77 | G16: 74 | H16: =AF16 -> 96 | I16: 68 | J16: =AG16 -> 70 | K16: 37 | L16: =AH16 -> 58 | M16: 143 | N16: =AI16 -> 169 | O16: =N16 -> 169 | P16: =AJ16 -> 169 | Q16: =P16 -> 169 | R16: =AK16 -> 169 | S16: =R16 -> 169 | T16: =AL16 -> 169 | U16: =T16 -> 169 | V16: =AM16 -> 169 | W16: =V16 -> 169 | X16: =AN16 -> 169 | Y16: =X16 -> 169 | Z16: =AO16 -> 169 | AE16: 77 | AF16: 96 | AG16: 70 | AH16: 58 | AI16: 169 | AJ16: =AI16 -> 169 | AK16: =AJ16 -> 169 | AL16: =AK16 -> 169 | AM16: =AL16 -> 169 | AN16: =AM16 -> 169 | AO16: =AN16 -> 169 | AU16: =P16-Q16 -> 0
A17: Cash and Cash Equivalents | B17: 1751 | C17: =D17 -> 1821 | D17: 1821 | E17: 4266 | F17: =AE17 -> 4000 | G17: 1967 | H17: =AF17 -> 3248 | I17: 2889 | J17: =AG17 -> 2765 | K17: 2168 | L17: =AH17 -> 2377 | M17: 2277 | N17: =AI17 -> 2350 | O17: ='Cash Flow Statement'!O50+N17-'Cash Flow Statement'!N50 -> 4163.2655 | P17: =AJ17 -> 5437.8665 | Q17: ='Cash Flow Statement'!Q50+P17-'Cash Flow Statement'!P50 -> 7347.0375 | R17: =AK17 -> 8846.8426 | S17: ='Cash Flow Statement'!S50+R17-'Cash Flow Statement'!R50 -> 10864.47 | T17: =AL17 -> 12532.345 | U17: ='Cash Flow Statement'!U50+T17-'Cash Flow Statement'!T50 -> 14702.832 | V17: =AM17 -> 16537.852 | W17: ='Cash Flow Statement'!W50+V17-'Cash Flow Statement'!V50 -> 18911.985 | X17: =AN17 -> 20926.696 | Y17: ='Cash Flow Statement'!Y50+X17-'Cash Flow Statement'!X50 -> 23552.303 | Z17: =AO17 -> 25754.359 | AE17: 4000 | AF17: 3248 | AG17: 2765 | AH17: 2377 | AI17: 2350 | AJ17: ='Cash Flow Statement'!AJ50 -> 5437.8665 | AK17: ='Cash Flow Statement'!AK50 -> 8846.8426 | AL17: ='Cash Flow Statement'!AL50 -> 12532.345 | AM17: ='Cash Flow Statement'!AM50 -> 16537.852 | AN17: ='Cash Flow Statement'!AN50 -> 20926.696 | AO17: ='Cash Flow Statement'!AO50 -> 25754.359 | AU17: =P17-Q17 -> -1909.171
A18: Assets classified as held for sale | B18: 108 | C18: =D18 -> 111 | D18: 111 | E18: 61 | F18: =AE18 -> 24 | G18: 17 | H18: =AF18 -> 37 | I18: 550 | J18: =AG18 -> 315 | K18: 374 | L18: =AH18 -> 28 | M18: 40 | N18: =AI18 -> 55 | O18: =N18 -> 55 | P18: =AJ18 -> 55 | Q18: =P18 -> 55 | R18: =AK18 -> 55 | S18: =R18 -> 55 | T18: =AL18 -> 55 | U18: =T18 -> 55 | V18: =AM18 -> 55 | W18: =V18 -> 55 | X18: =AN18 -> 55 | Y18: =X18 -> 55 | Z18: =AO18 -> 55 | AE18: 24 | AF18: 37 | AG18: 315 | AH18: 28 | AI18: 55 | AJ18: =AI18 -> 55 | AK18: =AJ18 -> 55 | AL18: =AK18 -> 55 | AM18: =AL18 -> 55 | AN18: =AM18 -> 55 | AO18: =AN18 -> 55 | AU18: =P18-Q18 -> 0
A19: Other current assets | B19: 0 | C19: =D19 -> 0 | D19: 0 | E19: 0 | F19: =AE19 -> 0 | G19: 0 | H19: =AF19 -> 0 | I19: 42 | J19: =AG19 -> 0 | K19: 0 | L19: =AH19 -> 0 | M19: 0 | N19: =AI19 -> 0 | O19: =N19 -> 0 | P19: =AJ19 -> 0 | Q19: =P19 -> 0 | R19: =AK19 -> 0 | S19: =R19 -> 0 | T19: =AL19 -> 0 | U19: =T19 -> 0 | V19: =AM19 -> 0 | W19: =V19 -> 0 | X19: =AN19 -> 0 | Y19: =X19 -> 0 | Z19: =AO19 -> 0 | AE19: 0 | AF19: 0 | AG19: 0 | AH19: 0 | AI19: =AH19 -> 0 | AJ19: =AI19 -> 0 | AK19: =AJ19 -> 0 | AL19: =AK19 -> 0 | AM19: =AL19 -> 0 | AN19: =AM19 -> 0 | AO19: =AN19 -> 0 | AU19: =P19-Q19 -> 0
A20: Total Current Assets | B20: =SUM(B13:B19) -> 8818 | C20: =SUM(C13:C19) -> 8419 | D20: =SUM(D13:D19) -> 8419 | E20: =SUM(E13:E18) -> 10774 | F20: =SUM(F13:F18) -> 9020 | G20: =SUM(G13:G19) -> 8419 | H20: =SUM(H13:H19) -> 9578 | I20: =SUM(I13:I19) -> 11765 | J20: =SUM(J13:J19) -> 11015 | K20: =SUM(K13:K19) -> 12844 | L20: =SUM(L13:L19) -> 11399 | M20: =SUM(M13:M19) -> 11870 | N20: =SUM(N13:N19) -> 10899 | O20: =SUM(O13:O18) -> 13386.009 | P20: =SUM(P13:P19) -> 15993.55 | Q20: =SUM(Q13:Q18) -> 16113.978 | R20: =SUM(R13:R19) -> 20380.822 | S20: =SUM(S13:S18) -> 20076.888 | T20: =SUM(T13:T19) -> 25235.026 | U20: =SUM(U13:U18) -> 24575.936 | V20: =SUM(V13:V19) -> 30587.635 | W20: =SUM(W13:W18) -> 29667.925 | X20: =SUM(X13:X19) -> 36648.708 | Y20: =SUM(Y13:Y18) -> 35434.449 | Z20: =SUM(Z13:Z19) -> 43405.582 | AE20: =SUM(AE13:AE18) -> 9020 | AF20: =SUM(AF13:AF19) -> 9578 | AG20: =SUM(AG13:AG19) -> 11015 | AH20: =SUM(AH13:AH19) -> 11399 | AI20: =SUM(AI13:AI19) -> 10899 | AJ20: =SUM(AJ13:AJ18) -> 15993.55 | AK20: =SUM(AK13:AK18) -> 20380.822 | AL20: =SUM(AL13:AL18) -> 25235.026 | AM20: =SUM(AM13:AM18) -> 30587.635 | AN20: =SUM(AN13:AN18) -> 36648.708 | AO20: =SUM(AO13:AO18) -> 43405.582
A22: Total Assets | B22: =B11+B20 -> 46227 | C22: =C11+C20 -> 46504 | D22: =D11+D20 -> 46504 | E22: =E11+E20 -> 45796 | F22: =F11+F20 -> 42632 | G22: =G11+G20 -> 43494 | H22: =H11+H20 -> 48850 | I22: =I11+I20 -> 52349 | ... Z22: =Z11+Z20 -> 84206.348 | AE22: =AE11+AE20 -> 42632 | AF22: =AF11+AF20 -> 48850 | AG22: =AG11+AG20 -> 52406 | AH22: =AH11+AH20 -> 55153 | AI22: =AI11+AI20 -> 53773 | AJ22: =AJ11+AJ20 -> 58221.563 | AK22: =AK11+AK20 -> 62038.279 | AL22: =AL11+AL20 -> 66428.028 | ... AO22: =AO11+AO20 -> 84206.348
A24: Share Capital | B24: 461 | C24: =D24 -> 461 | D24: 461 | E24: 922 | F24: =AE24 -> 922 | G24: 922 | H24: =AF24 -> 922 | I24: 922 | J24: =AG24 -> 922 | K24: 922 | L24: =AH24 -> 922 | M24: 922 | N24: =AI24 -> 922 | O24: =N24 -> 922 | P24: =AJ24 -> 922 | Q24: =P24 -> 922 | R24: =AK24 -> 922 | S24: =R24 -> 922 | T24: =AL24 -> 922 | U24: =T24 -> 922 | V24: =AM24 -> 922 | W24: =V24 -> 922 | X24: =AN24 -> 922 | Y24: =X24 -> 922 | Z24: =AO24 -> 922 | AE24: 922 | AF24: 922 | AG24: 922 | AH24: 922 | AI24: 922 | AJ24: =AI24 -> 922 | AK24: =AJ24 -> 922 | AL24: =AK24 -> 922 | AM24: =AL24 -> 922 | AN24: =AM24 -> 922 | AO24: =AN24 -> 922 | AU24: =Q24-P24 -> 0
A25: Share Premium | B25: 1257 | C25: =D25 -> 1257 | D25: 1257 | E25: 2701 | F25: =AE25 -> 2701 | G25: 2701 | H25: =AF25 -> 2701 | I25: 2701 | J25: =AG25 -> 2701 | K25: 2701 | L25: =AH25 -> 2701 | M25: 2701 | N25: =AI25 -> 2701 | O25: =N25 -> 2701 | P25: =AJ25 -> 2701 | Q25: =P25 -> 2701 | R25: =AK25 -> 2701 | S25: =R25 -> 2701 | T25: =AL25 -> 2701 | U25: =T25 -> 2701 | V25: =AM25 -> 2701 | W25: =V25 -> 2701 | X25: =AN25 -> 2701 | Y25: =X25 -> 2701 | Z25: =AO25 -> 2701 | AE25: 2701 | AF25: 2701 | AG25: 2701 | AH25: 2701 | AI25: =AH25 -> 2701 | AJ25: =AI25 -> 2701 | AK25: =AJ25 -> 2701 | AL25: =AK25 -> 2701 | AM25: =AL25 -> 2701 | AN25: =AM25 -> 2701 | AO25: =AN25 -> 2701 | AU25: =Q25-P25 -> 0
A26: Reserves | B26: =-1591-13+2+185+534 -> -883 | C26: =D26 -> -799 | D26: =-1511-8+2+158+560 -> -799 | E26: =-4527+33+1+171+1109-25 -> -3238 | F26: =AE26 -> -3714 | G26: =-4541+27-5+57+1180-23 -> -3305 | H26: =AF26 -> -2808 | I26: =-2935-79-9+56+1094-40 -> -1913 | J26: =AG26 -> -2423 | K26: =-3504-174-6+104+1339-966 -> -3207 | L26: =AH26 -> -2641 | M26: =-3798+99-7+61+1890-966 -> -2721 | N26: =AI26 -> -3248 | O26: =N26 -> -3248 | P26: =AJ26 -> -3248 | Q26: =P26 -> -3248 | R26: =AK26 -> -3248 | S26: =R26 -> -3248 | T26: =AL26 -> -3248 | U26: =T26 -> -3248 | V26: =AM26 -> -3248 | W26: =V26 -> -3248 | X26: =AN26 -> -3248 | Y26: =X26 -> -3248 | Z26: =AO26 -> -3248 | AE26: =-4940+28-2+54+1171-25 -> -3714 | AF26: =-4003+56-8+56+1128-37 -> -2808 | AG26: =-3619-47-9+70+1242-60 -> -2423 | AH26: =-3705-14-7+71+1980-966 -> -2641 | AI26: =-4297+100-8-32+1978-989 -> -3248 | AJ26: =AI26 -> -3248 | AK26: =AJ26 -> -3248 | AL26: =AK26 -> -3248 | AM26: =AL26 -> -3248 | AN26: =AM26 -> -3248 | AO26: =AN26 -> -3248 | AU26: =Q26-P26 -> 0
A27: Retained Earnings | B27: 6689 | C27: =D27 -> 7074 | D27: 7074 | E27: 13208 | F27: =AE27 -> 13483 | G27: 14219 | H27: =AF27 -> 16541 | I27: 17434 | J27: =AG27 -> 18351 | K27: 18898 | L27: =AH27 -> 19074 | M27: 18506 | N27: =AI27 -> 19206 | O27: =N27+'Profit and Loss Statement '!O27 -> 21338.754 | P27: =AJ27 -> 20859.519 | Q27: =P27+'Profit and Loss Statement '!Q27 -> 23197.223 | R27: =AK27 -> 22764.102 | S27: =R27+'Profit and Loss Statement '!S27 -> 25418.017 | T27: =AL27 -> 24978.304 | U27: =T27+'Profit and Loss Statement '!U27 -> 28065.473 | V27: =AM27 -> 27568.026 | W27: =V27+'Profit and Loss Statement '!W27 -> 31217.688 | X27: =AN27 -> 30609.464 | Y27: =X27+'Profit and Loss Statement '!Y27 -> 34969.197 | Z27: =AO27 -> 34192.201 | AE27: 13483 | AF27: 16541 | AG27: 18351 | AH27: 19074 | AI27: 19206 | AJ27: =AI27+'Profit and Loss Statement '!AJ27 -> 20859.519 | AK27: =AJ27+'Profit and Loss Statement '!AK27 -> 22764.102 | AL27: =AK27+'Profit and Loss Statement '!AL27 -> 24978.304 | AM27: =AL27+'Profit and Loss Statement '!AM27 -> 27568.026 | AN27: =AM27+'Profit and Loss Statement '!AN27 -> 30609.464 | AO27: =AN27+'Profit and Loss Statement '!AO27 -> 34192.201 | AU27: =Q27-P27 -> 2337.7043
A28: Minority Interests | B28: =7690+1069 -> 8759 | C28: =D28 -> 9318 | D28: =8154+1164 -> 9318 | E28: 967 | F28: =AE28 -> 1000 | G28: 970 | H28: =AF28 -> 2344 | I28: 2412 | J28: =AG28 -> 2369 | K28: 2749 | L28: =AH28 -> 2733 | M28: 2674 | N28: =AI28 -> 2821 | O28: =N28+'Profit and Loss Statement '!O28 -> 1765.8479 | P28: =AJ28 -> 3130.4007 | Q28: =P28+'Profit and Loss Statement '!Q28 -> 1973.8523 | R28: =AK28 -> 3486.7799 | S28: =R28+'Profit and Loss Statement '!S28 -> 2173.7905 | T28: =AL28 -> 3901.0936 | U28: =T28+'Profit and Loss Statement '!U28 -> 2373.7574 | V28: =AM28 -> 4385.6736 | W28: =V28+'Profit and Loss Statement '!W28 -> 2580.0514 | X28: =AN28 -> 4954.777 | Y28: =X28+'Profit and Loss Statement '!Y28 -> 2797.8564 | Z28: =AO28 -> 5625.1664 | AE28: 1000 | AF28: 2344 | AG28: 2369 | AH28: 2733 | AI28: 2821 | AJ28: =AI28+'Profit and Loss Statement '!AJ28 -> 3130.4007 | AK28: =AJ28+'Profit and Loss Statement '!AK28 -> 3486.7799 | AL28: =AK28+'Profit and Loss Statement '!AL28 -> 3901.0936 | AM28: =AL28+'Profit and Loss Statement '!AM28 -> 4385.6736 | AN28: =AM28+'Profit and Loss Statement '!AN28 -> 4954.777 | AO28: =AN28+'Profit and Loss Statement '!AO28 -> 5625.1664 | AU28: =Q28-P28 -> -1156.5485
A29: Total Equity | B29: =SUM(B24:B28) -> 16283 | C29: =SUM(C24:C28) -> 17311 | D29: =SUM(D24:D28) -> 17311 | E29: =SUM(E24:E28) -> 14560 | F29: =SUM(F24:F28) -> 14392 | G29: =SUM(G24:G28) -> 15507 | H29: =SUM(H24:H28) -> 19700 | I29: =SUM(I24:I28) -> 21556 | ... Z29: =SUM(Z24:Z28) -> 40192.367 | AE29: =SUM(AE24:AE28) -> 14392 | AF29: =SUM(AF24:AF28) -> 19700 | AG29: =SUM(AG24:AG28) -> 21920 | AH29: =SUM(AH24:AH28) -> 22789 | AI29: =SUM(AI24:AI28) -> 22402 | AJ29: =SUM(AJ24:AJ28) -> 24364.919 | AK29: =SUM(AK24:AK28) -> 26625.882 | AL29: =SUM(AL24:AL28) -> 29254.397 | ... AO29: =SUM(AO24:AO28) -> 40192.367
A31: Borrowings | B31: 14112 | C31: =D31 -> 13366 | D31: 13366 | E31: 15564 | F31: =AE31 -> 14616 | G31: 13831 | H31: =AF31 -> 13640 | I31: 13026 | J31: =AG31 -> 12893 | K31: 14441 | L31: =AH31 -> 14046 | M31: 13792 | N31: =AI31 -> 13783 | O31: =O82 -> 14033 | P31: =AJ31 -> 14283 | Q31: =Q82 -> 14533 | R31: =AK31 -> 14783 | S31: =S82 -> 15033 | T31: =AL31 -> 15283 | U31: =U82 -> 15533 | V31: =AM31 -> 15783 | W31: =W82 -> 16033 | X31: =AN31 -> 16283 | Y31: =Y82 -> 16533 | Z31: =AO31 -> 16783 | AE31: 14616 | AF31: 13640 | AG31: 12893 | AH31: 14046 | AI31: 13783 | AJ31: =AJ82 -> 14283 | AK31: =AK82 -> 14783 | AL31: =AL82 -> 15283 | AM31: =AM82 -> 15783 | AN31: =AN82 -> 16283 | AO31: =AO82 -> 16783 | AU31: =Q31-P31 -> 250
A32: Post-retirement obligations | B32: 1101 | C32: =D32 -> 1189 | D32: 1189 | E32: 1206 | F32: =AE32 -> 938 | G32: 832 | H32: =AF32 -> 668 | I32: 555 | J32: =AG32 -> 568 | K32: 533 | L32: =AH32 -> 586 | M32: 628 | N32: =AI32 -> 519 | O32: =N32 -> 519 | P32: =AJ32 -> 519 | Q32: =P32 -> 519 | R32: =AK32 -> 519 | S32: =R32 -> 519 | T32: =AL32 -> 519 | U32: =T32 -> 519 | V32: =AM32 -> 519 | W32: =V32 -> 519 | X32: =AN32 -> 519 | Y32: =X32 -> 519 | Z32: =AO32 -> 519 | AE32: 938 | AF32: 668 | AG32: 568 | AH32: 586 | AI32: 519 | AJ32: =AI32 -> 519 | AK32: =AJ32 -> 519 | AL32: =AK32 -> 519 | AM32: =AL32 -> 519 | AN32: =AM32 -> 519 | AO32: =AN32 -> 519 | AU32: =Q32-P32 -> 0
A33: Provisions | B33: 769 | C33: =D33 -> 756 | D33: 756 | E33: 602 | F33: =AE33 -> 688 | G33: 676 | H33: =AF33 -> 636 | I33: 636 | J33: =AG33 -> 572 | K33: 651 | L33: =AH33 -> 627 | M33: 586 | N33: =AI33 -> 586 | O33: =N33 -> 586 | P33: =AJ33 -> 586 | Q33: =P33 -> 586 | R33: =AK33 -> 586 | S33: =R33 -> 586 | T33: =AL33 -> 586 | U33: =T33 -> 586 | V33: =AM33 -> 586 | W33: =V33 -> 586 | X33: =AN33 -> 586 | Y33: =X33 -> 586 | Z33: =AO33 -> 586 | AE33: 688 | AF33: 636 | AG33: 572 | AH33: 627 | AI33: 586 | AJ33: =AI33 -> 586 | AK33: =AJ33 -> 586 | AL33: =AK33 -> 586 | AM33: =AL33 -> 586 | AN33: =AM33 -> 586 | AO33: =AN33 -> 586 | AU33: =Q33-P33 -> 0
A34: Deffered tax liabilities | B34: 1417 | C34: =D34 -> 1422 | D34: 1422 | E34: 1198 | F34: =AE34 -> 999 | G34: 1073 | H34: =AF34 -> 1971 | I34: 2078 | J34: =AG34 -> 2138 | K34: 2403 | L34: =AH34 -> 2213 | M34: 2105 | N34: =AI34 -> 2155 | O34: =N34 -> 2155 | P34: =AJ34 -> 2155 | Q34: =P34 -> 2155 | R34: =AK34 -> 2155 | S34: =R34 -> 2155 | T34: =AL34 -> 2155 | U34: =T34 -> 2155 | V34: =AM34 -> 2155 | W34: =V34 -> 2155 | X34: =AN34 -> 2155 | Y34: =X34 -> 2155 | Z34: =AO34 -> 2155 | AE34: 999 | AF34: 1971 | AG34: 2138 | AH34: 2213 | AI34: 2155 | AJ34: =AI34 -> 2155 | AK34: =AJ34 -> 2155 | AL34: =AK34 -> 2155 | AM34: =AL34 -> 2155 | AN34: =AM34 -> 2155 | AO34: =AN34 -> 2155 | AU34: =Q34-P34 -> 0
A35: Other non-current liabilities | B35: 172 | C35: =D35 -> 153 | D35: 153 | E35: 108 | F35: =AE35 -> 131 | G35: 136 | H35: =AF35 -> 141 | I35: 179 | J35: =AG35 -> 125 | K35: 75 | L35: =AH35 -> 67 | M35: 81 | N35: =AI35 -> 90 | O35: =N35 -> 90 | P35: =AJ35 -> 90 | Q35: =P35 -> 90 | R35: =AK35 -> 90 | S35: =R35 -> 90 | T35: =AL35 -> 90 | U35: =T35 -> 90 | V35: =AM35 -> 90 | W35: =V35 -> 90 | X35: =AN35 -> 90 | Y35: =X35 -> 90 | Z35: =AO35 -> 90 | AE35: 131 | AF35: 141 | AG35: 125 | AH35: 67 | AI35: 90 | AJ35: =AI35 -> 90 | AK35: =AJ35 -> 90 | AL35: =AK35 -> 90 | AM35: =AL35 -> 90 | AN35: =AM35 -> 90 | AO35: =AN35 -> 90 | AU35: =Q35-P35 -> 0
A36: Total non-current liabilities | B36: =SUM(B31:B35) -> 17571 | C36: =SUM(C31:C35) -> 16886 | D36: =SUM(D31:D35) -> 16886 | E36: =SUM(E31:E35) -> 18678 | F36: =SUM(F31:F35) -> 17372 | G36: =SUM(G31:G35) -> 16548 | H36: =SUM(H31:H35) -> 17056 | I36: =SUM(I31:I35) -> 16474 | ... Z36: =SUM(Z31:Z35) -> 20133 | AE36: =SUM(AE31:AE35) -> 17372 | AF36: =SUM(AF31:AF35) -> 17056 | AG36: =SUM(AG31:AG35) -> 16296 | AH36: =SUM(AH31:AH35) -> 17539 | AI36: =SUM(AI31:AI35) -> 17133 | AJ36: =SUM(AJ31:AJ35) -> 17633 | AK36: =SUM(AK31:AK35) -> 18133 | AL36: =SUM(AL31:AL35) -> 18633 | ... AO36: =SUM(AO31:AO35) -> 20133
A38: Borrowings | B38: 3727 | C38: =D38 -> 3686 | D38: 3686 | E38: 5423 | F38: =AE38 -> 3580 | G38: 3155 | H38: =AF38 -> 3233 | I38: 3556 | J38: =AG38 -> 3484 | K38: 5416 | L38: =AH38 -> 4192 | M38: 4705 | N38: =AI38 -> 3266 | O38: =O83 -> 4192 | P38: =AJ38 -> 4192 | Q38: =Q83 -> 4192 | R38: =AK38 -> 4192 | S38: =S83 -> 4192 | T38: =AL38 -> 4192 | U38: =U83 -> 4192 | V38: =AM38 -> 4192 | W38: =W83 -> 4192 | X38: =AN38 -> 4192 | Y38: =Y83 -> 4192 | Z38: =AO38 -> 4192 | AE38: 3580 | AF38: 3233 | AG38: 3484 | AH38: 4192 | AI38: 3266 | AJ38: =AJ83 -> 4192 | AK38: =AK83 -> 4192 | AL38: =AL83 -> 4192 | AM38: =AM83 -> 4192 | AN38: =AN83 -> 4192 | AO38: =AO83 -> 4192 | AU38: =Q38-P38 -> 0
A39: Trade and other payables | B39: 7595 | C39: =D39 -> 7520 | D39: 7520 | E39: 6115 | F39: =AE39 -> 6107 | G39: 7100 | H39: =AF39 -> 7750 | I39: 9091 | J39: =AG39 -> 9283 | K39: 9744 | L39: =AH39 -> 9432 | M39: 9401 | N39: =AI39 -> 9912 | O39: =O101 -> 9533.1662 | P39: =AJ39 -> 10971.643 | Q39: =Q101 -> 9041.2738 | R39: =AK39 -> 12027.397 | S39: =S101 -> 9522.0218 | T39: =AL39 -> 13288.631 | U39: =U101 -> 10235.019 | V39: =AM39 -> 14742.392 | W39: =W101 -> 11187.755 | X39: =AN39 -> 16547.022 | Y39: =Y101 -> 12403.13 | Z39: =AO39 -> 18628.981 | AE39: 6107 | AF39: 7750 | AG39: 9283 | AH39: 9432 | AI39: 9912 | AJ39: =AJ101 -> 10971.643 | AK39: =AK101 -> 12027.397 | AL39: =AL101 -> 13288.631 | AM39: =AM101 -> 14742.392 | AN39: =AN101 -> 16547.022 | AO39: =AO101 -> 18628.981 | AU39: =Q39-P39 -> -1930.3694
A40: Returnable packaging deposits | B40: 610 | C40: =D40 -> 565 | D40: 565 | E40: 528 | F40: =AE40 -> 454 | G40: 524 | H40: =AF40 -> 476 | I40: 590 | J40: =AG40 -> 545 | K40: 578 | L40: =AH40 -> 531 | M40: 583 | N40: =AI40 -> 525 | O40: =N40 -> 525 | P40: =AJ40 -> 525 | Q40: =P40 -> 525 | R40: =AK40 -> 525 | S40: =R40 -> 525 | T40: =AL40 -> 525 | U40: =T40 -> 525 | V40: =AM40 -> 525 | W40: =V40 -> 525 | X40: =AN40 -> 525 | Y40: =X40 -> 525 | Z40: =AO40 -> 525 | AE40: 454 | AF40: 476 | AG40: 545 | AH40: 531 | AI40: 525 | AJ40: =AI40 -> 525 | AK40: =AJ40 -> 525 | AL40: =AK40 -> 525 | AM40: =AL40 -> 525 | AN40: =AM40 -> 525 | AO40: =AN40 -> 525 | AU40: =Q40-P40 -> 0
A41: Provisions | B41: 134 | C41: =D41 -> 184 | D41: 184 | E41: 176 | F41: =AE41 -> 416 | G41: 336 | H41: =AF41 -> 301 | I41: 257 | J41: =AG41 -> 226 | K41: 174 | L41: =AH41 -> 206 | M41: 201 | N41: =AI41 -> 176 | O41: =N41 -> 176 | P41: =AJ41 -> 176 | Q41: =P41 -> 176 | R41: =AK41 -> 176 | S41: =R41 -> 176 | T41: =AL41 -> 176 | U41: =T41 -> 176 | V41: =AM41 -> 176 | W41: =V41 -> 176 | X41: =AN41 -> 176 | Y41: =X41 -> 176 | Z41: =AO41 -> 176 | AE41: 416 | AF41: 301 | AG41: 226 | AH41: 206 | AI41: 176 | AJ41: =AI41 -> 176 | AK41: =AJ41 -> 176 | AL41: =AK41 -> 176 | AM41: =AL41 -> 176 | AN41: =AM41 -> 176 | AO41: =AN41 -> 176 | AU41: =Q41-P41 -> 0
A42: Current tax liabilities | B42: 248 | C42: =D42 -> 283 | D42: 283 | E42: 259 | F42: =AE42 -> 259 | G42: 262 | H42: =AF42 -> 268 | I42: 344 | J42: =AG42 -> 352 | K42: 322 | L42: =AH42 -> 332 | M42: 346 | N42: =AI42 -> 307 | O42: =N42 -> 307 | P42: =AJ42 -> 307 | Q42: =P42 -> 307 | R42: =AK42 -> 307 | S42: =R42 -> 307 | T42: =AL42 -> 307 | U42: =T42 -> 307 | V42: =AM42 -> 307 | W42: =V42 -> 307 | X42: =AN42 -> 307 | Y42: =X42 -> 307 | Z42: =AO42 -> 307 | AE42: 259 | AF42: 268 | AG42: 352 | AH42: 332 | AI42: 307 | AJ42: =AI42 -> 307 | AK42: =AJ42 -> 307 | AL42: =AK42 -> 307 | AM42: =AL42 -> 307 | AN42: =AM42 -> 307 | AO42: =AN42 -> 307 | AU42: =Q42-P42 -> 0
A43: Derivative liabilities | B43: 59 | C43: =D43 -> 69 | D43: 69 | E43: 57 | F43: =AE43 -> 52 | G43: 62 | H43: =AF43 -> 46 | I43: 158 | J43: =AG43 -> 119 | K43: 251 | L43: =AH43 -> 132 | M43: 54 | N43: =AI43 -> 52 | O43: =N43 -> 52 | P43: =AJ43 -> 52 | Q43: =P43 -> 52 | R43: =AK43 -> 52 | S43: =R43 -> 52 | T43: =AL43 -> 52 | U43: =T43 -> 52 | V43: =AM43 -> 52 | W43: =V43 -> 52 | X43: =AN43 -> 52 | Y43: =X43 -> 52 | Z43: =AO43 -> 52 | AE43: 52 | AF43: 46 | AG43: 119 | AH43: 132 | AI43: 52 | AJ43: =AI43 -> 52 | AK43: =AJ43 -> 52 | AL43: =AK43 -> 52 | AM43: =AL43 -> 52 | AN43: =AM43 -> 52 | AO43: =AN43 -> 52 | AU43: =Q43-P43 -> 0
A44: Liabilities associated with assets classified as held for sale | B44: 0 | C44: =D44 -> 0 | D44: 0 | E44: 0 | F44: =AE44 -> 0 | G44: 0 | H44: =AF44 -> 20 | I44: 323 | J44: =AG44 -> 181 | K44: 262 | L44: =AH44 -> 0 | M44: 0 | N44: =AI44 -> 0 | O44: =N44 -> 0 | P44: =AJ44 -> 0 | Q44: =P44 -> 0 | R44: =AK44 -> 0 | S44: =R44 -> 0 | T44: =AL44 -> 0 | U44: =T44 -> 0 | V44: =AM44 -> 0 | W44: =V44 -> 0 | X44: =AN44 -> 0 | Y44: =X44 -> 0 | Z44: =AO44 -> 0 | AE44: 0 | AF44: 20 | AG44: 181 | AH44: 0 | AI44: =AH44 -> 0 | AJ44: =AI44 -> 0 | AK44: =AJ44 -> 0 | AL44: =AK44 -> 0 | AM44: =AL44 -> 0 | AN44: =AM44 -> 0 | AO44: =AN44 -> 0 | AU44: =Q44-P44 -> 0
A45: Total current liabilities | B45: =SUM(B38:B44) -> 12373 | C45: =SUM(C38:C44) -> 12307 | D45: =SUM(D38:D44) -> 12307 | E45: =SUM(E38:E43) -> 12558 | F45: =SUM(F38:F43) -> 10868 | G45: =SUM(G38:G44) -> 11439 | H45: =SUM(H38:H44) -> 12094 | I45: =SUM(I38:I44) -> 14319 | J45: =SUM(J38:J44) -> 14190 | K45: =SUM(K38:K44) -> 16747 | L45: =SUM(L38:L44) -> 14825 | M45: =SUM(M38:M44) -> 15290 | N45: =SUM(N38:N44) -> 14238 | O45: =SUM(O38:O43) -> 14785.166 | P45: =SUM(P38:P44) -> 16223.643 | Q45: =SUM(Q38:Q43) -> 14293.274 | R45: =SUM(R38:R44) -> 17279.397 | S45: =SUM(S38:S43) -> 14774.022 | T45: =SUM(T38:T44) -> 18540.631 | U45: =SUM(U38:U43) -> 15487.019 | V45: =SUM(V38:V44) -> 19994.392 | W45: =SUM(W38:W43) -> 16439.755 | X45: =SUM(X38:X44) -> 21799.022 | Y45: =SUM(Y38:Y43) -> 17655.13 | Z45: =SUM(Z38:Z44) -> 23880.981 | AE45: =SUM(AE38:AE43) -> 10868 | AF45: =SUM(AF38:AF44) -> 12094 | AG45: =SUM(AG38:AG44) -> 14190 | AH45: =SUM(AH38:AH44) -> 14825 | AI45: =SUM(AI38:AI44) -> 14238 | AJ45: =SUM(AJ38:AJ43) -> 16223.643 | AK45: =SUM(AK38:AK43) -> 17279.397 | AL45: =SUM(AL38:AL43) -> 18540.631 | AM45: =SUM(AM38:AM43) -> 19994.392 | AN45: =SUM(AN38:AN43) -> 21799.022 | AO45: =SUM(AO38:AO43) -> 23880.981
A47: Total Equity and Liabilities | B47: =B29+B36+B45 -> 46227 | C47: =C29+C36+C45 -> 46504 | D47: =D29+D36+D45 -> 46504 | E47: =E29+E36+E45 -> 45796 | F47: =F29+F36+F45 -> 42632 | G47: =G29+G36+G45 -> 43494 | H47: =H29+H36+H45 -> 48850 | I47: =I29+I36+I45 -> 52349 | ... Z47: =Z29+Z36+Z45 -> 84206.348 | AE47: =AE29+AE36+AE45 -> 42632 | AF47: =AF29+AF36+AF45 -> 48850 | AG47: =AG29+AG36+AG45 -> 52406 | AH47: =AH29+AH36+AH45 -> 55153 | AI47: =AI29+AI36+AI45 -> 53773 | AJ47: =AJ29+AJ36+AJ45 -> 58221.563 | AK47: =AK29+AK36+AK45 -> 62038.279 | AL47: =AL29+AL36+AL45 -> 66428.028 | ... AO47: =AO29+AO36+AO45 -> 84206.348
B49: =B22=B47 -> TRUE | C49: =C22=C47 -> TRUE | D49: =D22=D47 -> TRUE | E49: =E22=E47 -> TRUE | F49: =F22=F47 -> TRUE | G49: =G22=G47 -> TRUE | H49: =H22=H47 -> TRUE | I49: =I22=I47 -> TRUE | ... Z49: =Z22=Z47 -> TRUE | AE49: =AE22=AE47 -> TRUE | AF49: =AF22=AF47 -> TRUE | AG49: =AG22=AG47 -> TRUE | AH49: =AH22=AH47 -> TRUE | AI49: =AI22=AI47 -> TRUE | AJ49: =AJ22=AJ47 -> TRUE | AK49: =AK22=AK47 -> TRUE | AL49: =AL22=AL47 -> TRUE | ... AO49: =AO22=AO47 -> TRUE
N51: =N47-N22 -> 0 | O51: =O47-O22 -> 0 | P51: =P47-P22 -> 0 | Q51: =Q47-Q22 -> 0 | R51: =R47-R22 -> 0 | S51: =S47-S22 -> 0 | T51: =T47-T22 -> 0 | U51: =U47-U22 -> 0 | ... Z51: =Z47-Z22 -> 0 | AI51: =AI47-AI22 -> 0 | AJ51: =AJ47-AJ22 -> 0 | AK51: =AK47-AK22 -> 0 | AL51: =AL47-AL22 -> 0 | AM51: =AM47-AM22 -> 0 | AN51: =AN47-AN22 -> 0 | AO51: =AO47-AO22 -> 0
A52: PP&E schedule
A53: Opening Balance | M53: =AI53 -> 28465 | N53: =M53+M54 -> 29686 | O53: =N53+N54+N56 -> 28718 | P53: =O53+O54 -> 29643.971 | Q53: =P53+P54+P56 -> 30837.091 | R53: =Q53+Q54 -> 31820.291 | S53: =R53+R54+R56 -> 33160.092 | T53: =S53+S54 -> 34220.805 | U53: =T53+T54+T56 -> 35726.691 | V53: =U53+U54 -> 36886.538 | W53: =V53+V54+V56 -> 38581.875 | X53: =W53+W54 -> 39864.922 | Y53: =X53+X54+X56 -> 41777.808 | Z53: =Y53+Y54 -> 43211.647 | AG53: 24635 | AH53: 26604 | AI53: 28465 | AJ53: =AI53+AI54+AI56 -> 28718 | AK53: =AJ53+AJ54 -> 30837.091 | AL53: =AK53+AK54 -> 33160.092 | AM53: =AL53+AL54 -> 35726.691 | AN53: =AM53+AM54 -> 38581.875 | AO53: =AN53+AN54 -> 41777.808
A54: Additions during the period | K54: 1378 | M54: 1221 | N54: =AI54-M54 -> 963 | O54: =O55*'Profit and Loss Statement '!O5 -> 925.97057 | P54: =AJ54-O54 -> 1193.1199 | Q54: =Q55*'Profit and Loss Statement '!Q5 -> 983.20041 | R54: =AK54-Q54 -> 1339.8009 | S54: =S55*'Profit and Loss Statement '!S5 -> 1060.7128 | T54: =AL54-S54 -> 1505.8865 | U54: =U55*'Profit and Loss Statement '!U5 -> 1159.8469 | V54: =AM54-U54 -> 1695.3366 | W54: =W55*'Profit and Loss Statement '!W5 -> 1283.0474 | X54: =AN54-W54 -> 1912.8857 | Y54: =Y55*'Profit and Loss Statement '!Y5 -> 1433.8392 | Z54: =AO54-Y54 -> 2164.2086 | AG54: 1791 | AH54: 2434 | AI54: 2184 | AJ54: =AJ55*'Profit and Loss Statement '!AJ5 -> 2119.0905 | AK54: =AK55*'Profit and Loss Statement '!AK5 -> 2323.0014 | AL54: =AL55*'Profit and Loss Statement '!AL5 -> 2566.5993 | AM54: =AM55*'Profit and Loss Statement '!AM5 -> 2855.1835 | AN54: =AN55*'Profit and Loss Statement '!AN5 -> 3195.9331 | AO54: =AO55*'Profit and Loss Statement '!AO5 -> 3598.0478
O55: 0.06 | P55: =AJ55 -> 0.06 | Q55: 0.06 | R55: =AK55 -> 0.06 | S55: 0.06 | T55: =AL55 -> 0.06 | U55: 0.06 | V55: =AM55 -> 0.06 | W55: 0.06 | X55: =AN55 -> 0.06 | Y55: 0.06 | Z55: =AO55 -> 0.06 | AG55: =AG54/'Profit and Loss Statement '!AG5 -> 0.062362896 | AH55: =AH54/'Profit and Loss Statement '!AH5 -> 0.080165997 | AI55: =AI54/'Profit and Loss Statement '!AI5 -> 0.073236981 | AJ55: 0.06 | AK55: 0.06 | AL55: 0.06 | AM55: 0.06 | AN55: 0.06 | AO55: 0.06
A56: Others | N56: =AI56 -> -1931 | AG56: =1969-AG54 -> 178 | AH56: =1861-AH54 -> -573 | AI56: =-40+2322-100-844+214-1299-AI54 -> -1931 | AK56: =AJ56 -> 0 | AL56: =AK56 -> 0 | AM56: =AL56 -> 0 | AN56: =AM56 -> 0 | AO56: =AN56 -> 0
A57: Accumulated Depreciation | M57: =AI57 -> 13130 | N57: =M57+M58 -> 13620 | O57: =N57+N58 -> 15145 | P57: =O57+O58 -> 16006.54 | Q57: =P57+P58 -> 17155.26 | R57: =Q57+Q58 -> 18080.373 | S57: =R57+R58 -> 19313.856 | T57: =S57+S58 -> 20308.659 | U57: =T57+T58 -> 21635.063 | ... Z57: =Y57+Y58 -> 28089.997 | AG57: =13994-AG58 -> 12457 | AH57: =14733-AH58 -> 12837 | AI57: =15145-AI58 -> 13130 | AJ57: =AI57+AI58 -> 15145 | AK57: =AJ57+AJ58 -> 17155.26 | AL57: =AK57+AK58 -> 19313.856 | AM57: =AL57+AL58 -> 21635.063 | AN57: =AM57+AM58 -> 24135.931 | AO57: =AN57+AN58 -> 26836.662
A58: Depreciation expense | B58: =-'Profit and Loss Statement '!B13 -> 911 | C58: =-'Profit and Loss Statement '!C13 -> 1048 | D58: =-'Profit and Loss Statement '!D13 -> 1959 | M58: 490 | N58: =AI58-M58 -> 1525 | O58: =O59*O53 -> 861.54 | P58: =AJ58-O58 -> 1148.72 | Q58: =Q59*Q53 -> 925.11272 | R58: =AK58-Q58 -> 1233.4836 | S58: =S59*S53 -> 994.80276 | T58: =AL58-S58 -> 1326.4037 | U58: =U59*U53 -> 1071.8007 | V58: =AM58-U58 -> 1429.0676 | W58: =W59*W53 -> 1157.4562 | X58: =AN58-W58 -> 1543.275 | Y58: =Y59*Y53 -> 1253.3342 | Z58: =AO58-Y58 -> 1671.1123 | AG58: =AG72 -> 1537 | AH58: =AH72 -> 1896 | AI58: =AI72 -> 2015 | AJ58: =AJ59*AJ53 -> 2010.26 | AK58: =AK59*AK53 -> 2158.5963 | AL58: =AL59*AL53 -> 2321.2064 | AM58: =AM59*AM53 -> 2500.8684 | AN58: =AN59*AN53 -> 2700.7312 | AO58: =AO59*AO53 -> 2924.4465
M59: =M58/M53 -> 0.017214123 | O59: 0.03 | P59: =AJ59 -> 0.07 | Q59: 0.03 | R59: =AK59 -> 0.07 | S59: 0.03 | T59: =AL59 -> 0.07 | U59: 0.03 | V59: =AM59 -> 0.07 | W59: 0.03 | X59: =AN59 -> 0.07 | Y59: 0.03 | Z59: =AO59 -> 0.07 | AG59: =AG58/AG53 -> 0.062390907 | AH59: =AH58/AH53 -> 0.071267479 | AI59: =AI58/AI53 -> 0.070788688 | AJ59: 0.07 | AK59: 0.07 | AL59: 0.07 | AM59: 0.07 | AN59: 0.07 | AO59: 0.07
A60: Net PP&E | M60: 14463 | N60: =N53+N54+N56-N57-N58 -> 13573 | O60: =O53+O54+O56-O57-O58+N61 -> 14741.431 | P60: =P53+P54+P56-P57-P58 -> 13681.831 | Q60: =Q53+Q54+Q56-Q57-Q58+P61 -> 14843.918 | R60: =R53+R54+R56-R57-R58 -> 13846.236 | S60: =S53+S54+S56-S57-S58+R61 -> 15016.146 | T60: =T53+T54+T56-T57-T58 -> 14091.628 | U60: =U53+U54+U56-U57-U58+T61 -> 15283.675 | V60: =V53+V54+V56-V57-V58 -> 14445.944 | W60: =W53+W54+W56-W57-W58+V61 -> 15675.535 | X60: =X53+X54+X56-X57-X58 -> 14941.145 | Y60: =Y53+Y54+Y56-Y57-Y58+X61 -> 16225.65 | Z60: =Z53+Z54+Z56-Z57-Z58 -> 15614.747 | AG60: =AG53+AG54+AG56-AG57-AG58 -> 12610 | AH60: =AH53+AH54+AH56-AH57-AH58 -> 13732 | AI60: =AI53+AI54+AI56-AI57-AI58 -> 13573 | AJ60: =AJ53+AJ54+AJ56-AJ57-AJ58+AI61 -> 14785.831 | AK60: =AK53+AK54+AK56-AK57-AK58 -> 13846.236 | AL60: =AL53+AL54+AL56-AL57-AL58 -> 14091.628 | AM60: =AM53+AM54+AM56-AM57-AM58 -> 14445.944 | AN60: =AN53+AN54+AN56-AN57-AN58 -> 14941.145 | AO60: =AO53+AO54+AO56-AO57-AO58 -> 15614.747
M61: =AI61 -> 1104 | N61: =M61 -> 1104 | P61: =N61 -> 1104 | R61: =P61 -> 1104 | T61: =R61 -> 1104 | V61: =T61 -> 1104 | X61: =V61 -> 1104 | Z61: =X61 -> 1104 | AG61: =AG4-AG60 -> 1013 | AH61: =AH4-AH60 -> 1040 | AI61: =AI4-AI60 -> 1104
A62: Intangible Assets | P62: =AJ62 -> 0 | R62: =AK62 -> 0 | T62: =AL62 -> 0 | V62: =AM62 -> 0 | X62: =AN62 -> 0 | Z62: =AO62 -> 0
A63: Opening Balance | M63: =AI63 -> 27419 | N63: =M63+M64 -> 27500 | O63: =N63+N64 -> 27700 | P63: =AJ63+O64 -> 27854.328 | Q63: =P63+P64 -> 28053.182 | R63: =AK63+Q64 -> 28217.048 | S63: =R63+R64 -> 28440.349 | T63: =AL63+S64 -> 28617.134 | U63: =T63+T64 -> 28868.115 | V63: =AM63+U64 -> 29061.423 | W63: =V63+V64 -> 29343.979 | X63: =AN63+W64 -> 29557.82 | Y63: =X63+X64 -> 29876.635 | Z63: =AO63+Y64 -> 30115.608 | AG63: 25380 | AH63: 26394 | AI63: 27419 | AJ63: =AI63+AI64 -> 27700 | AK63: =AJ63+AJ64 -> 28053.182 | AL63: =AK63+AK64 -> 28440.349 | AM63: =AL63+AL64 -> 28868.115 | AN63: =AM63+AM64 -> 29343.979 | AO63: =AN63+AN64 -> 29876.635
A64: Additions during the period | K64: 90 | M64: 81 | N64: =AI64-M64 -> 200 | O64: =O65*'Profit and Loss Statement '!O5 -> 154.32843 | P64: =AJ64-O64 -> 198.85332 | Q64: =Q65*'Profit and Loss Statement '!Q5 -> 163.86674 | R64: =AK64-Q64 -> 223.30016 | S64: =S65*'Profit and Loss Statement '!S5 -> 176.78547 | T64: =AL64-S64 -> 250.98108 | U64: =U65*'Profit and Loss Statement '!U5 -> 193.30782 | V64: =AM64-U64 -> 282.55609 | W64: =W65*'Profit and Loss Statement '!W5 -> 213.84123 | X64: =AN64-W64 -> 318.81428 | Y64: =Y65*'Profit and Loss Statement '!Y5 -> 238.97321 | Z64: =AO64-Y64 -> 360.70143 | AG64: 220 | AH64: 243 | AI64: 281 | AJ64: =AJ65*'Profit and Loss Statement '!AJ5 -> 353.18175 | AK64: =AK65*'Profit and Loss Statement '!AK5 -> 387.16689 | AL64: =AL65*'Profit and Loss Statement '!AL5 -> 427.76655 | AM64: =AM65*'Profit and Loss Statement '!AM5 -> 475.86391 | AN64: =AN65*'Profit and Loss Statement '!AN5 -> 532.65551 | AO64: =AO65*'Profit and Loss Statement '!AO5 -> 599.67464
O65: 0.01 | P65: =AJ65 -> 0.01 | Q65: 0.01 | R65: =AK65 -> 0.01 | S65: 0.01 | T65: =AL65 -> 0.01 | U65: 0.01 | V65: =AM65 -> 0.01 | W65: 0.01 | X65: =AN65 -> 0.01 | Y65: 0.01 | Z65: =AO65 -> 0.01 | AG65: =AG64/'Profit and Loss Statement '!AG5 -> 0.0076604339 | AH65: =AH64/'Profit and Loss Statement '!AH5 -> 0.0080034253 | AI65: =AI64/'Profit and Loss Statement '!AI5 -> 0.0094228899 | AJ65: 0.01 | AK65: 0.01 | AL65: 0.01 | AM65: 0.01 | AN65: 0.01 | AO65: 0.01
A66: Others | O66: =N66 -> 0 | P66: =AJ66 -> 44 | Q66: =P66 -> 44 | R66: =AK66 -> 44 | S66: =R66 -> 44 | T66: =AL66 -> 44 | U66: =T66 -> 44 | V66: =AM66 -> 44 | W66: =V66 -> 44 | X66: =AN66 -> 44 | Y66: =X66 -> 44 | Z66: =AO66 -> 44 | AG66: =1014-AG64 -> 794 | AH66: =63+1511+241-61-379+52-402-AH64 -> 782 | AI66: =8+281-142+24+154-AI64 -> 44 | AJ66: =AI66 -> 44 | AK66: =AJ66 -> 44 | AL66: =AK66 -> 44 | AM66: =AL66 -> 44 | AN66: =AM66 -> 44 | AO66: =AN66 -> 44
A67: Accumulated | M67: =AI67 -> 5509 | N67: =M67+M68 -> 5729 | O67: =N67+N68 -> 6043 | P67: =O67+O68 -> 6874 | Q67: =P67+P68 -> 7151 | R67: =Q67+Q68 -> 7992.5955 | S67: =R67+R68 -> 8273.1273 | T67: =S67+S68 -> 9126.3377 | U67: =T67+T68 -> 9410.7412 | ... Z67: =Y67+Y68 -> 12635.524 | AG67: =4986-AG68 -> 4730 | AH67: =5638-AH68 -> 4658 | AI67: =6043-AI68 -> 5509 | AJ67: =AI67+AI68 -> 6043 | AK67: =AJ67+AJ68 -> 7151 | AL67: =AK67+AK68 -> 8273.1273 | AM67: =AL67+AL68 -> 9410.7412 | AN67: =AM67+AM68 -> 10565.466 | AO67: =AN67+AN68 -> 11739.225
A68: Amortisation expense | M68: =M63+M64-M67-M70 -> 220 | N68: =AI68-M68 -> 314 | O68: =O69*O63 -> 831 | P68: =AJ68-O68 -> 277 | Q68: =Q69*Q63 -> 841.59545 | R68: =AK68-Q68 -> 280.53182 | S68: =S69*S63 -> 853.21046 | T68: =AL68-S68 -> 284.40349 | U68: =U69*U63 -> 866.04346 | V68: =AM68-U68 -> 288.68115 | W68: =W69*W63 -> 880.31937 | X68: =AN68-W68 -> 293.43979 | Y68: =Y69*Y63 -> 896.29904 | Z68: =AO68-Y68 -> 298.76635 | AG68: =AG73 -> 256 | AH68: =AH73 -> 980 | AI68: =AI73 -> 534 | AJ68: =AJ69*AJ63 -> 1108 | AK68: =AK69*AK63 -> 1122.1273 | AL68: =AL69*AL63 -> 1137.6139 | AM68: =AM69*AM63 -> 1154.7246 | AN68: =AN69*AN63 -> 1173.7592 | AO68: =AO69*AO63 -> 1195.0654
M69: =M68/M63 -> 0.0080236332 | O69: 0.03 | P69: =AJ69 -> 0.04 | Q69: 0.03 | R69: =AK69 -> 0.04 | S69: 0.03 | T69: =AL69 -> 0.04 | U69: 0.03 | V69: =AM69 -> 0.04 | W69: 0.03 | X69: =AN69 -> 0.04 | Y69: 0.03 | Z69: =AO69 -> 0.04 | AG69: =AG68/AG63 -> 0.010086682 | AH69: =AH68/AH63 -> 0.037129651 | AI69: =AI68/AI63 -> 0.019475546 | AJ69: 0.04 | AK69: 0.04 | AL69: 0.04 | AM69: 0.04 | AN69: 0.04 | AO69: 0.04
A70: Closing Balance | M70: 21771 | N70: =N63+N64-N67-N68 -> 21657 | O70: =O63+O64+O66-O67-O68+N71 -> 21024.328 | P70: =AJ70 -> 20946.182 | Q70: =Q63+Q64+Q66-Q67-Q68 -> 20268.453 | R70: =AK70 -> 20211.221 | S70: =S63+S64+S66-S67-S68+R71 -> 19534.796 | T70: =AL70 -> 19501.374 | U70: =U63+U64+U66-U67-U68+T71 -> 18828.638 | V70: =AM70 -> 18822.513 | W70: =W63+W64+W66-W67-W68+V71 -> 18156.035 | X70: =AN70 -> 18181.41 | Y70: =Y63+Y64+Y66-Y67-Y68+X71 -> 17524.084 | Z70: =AO70 -> 17586.019 | AG70: =AG63+AG64+AG66-AG67-AG68 -> 21408 | AH70: =AH63+AH64+AH66-AH67-AH68 -> 21781 | AI70: =AI63+AI64+AI66-AI67-AI68 -> 21701 | AJ70: =AJ63+AJ64+AJ66-AJ67-AJ68 -> 20946.182 | AK70: =AK63+AK64+AK66-AK67-AK68 -> 20211.221 | AL70: =AL63+AL64+AL66-AL67-AL68 -> 19501.374 | AM70: =AM63+AM64+AM66-AM67-AM68 -> 18822.513 | AN70: =AN63+AN64+AN66-AN67-AN68 -> 18181.41 | AO70: =AO63+AO64+AO66-AO67-AO68 -> 17586.019
N71: 44 | P71: 44 | AI71: =AI3-AI70 -> 0 | AJ71: =AJ70-AI70 -> -754.81825
A72: PPE | AG72: 1537 | AH72: 1896 | AI72: 2015
A73: Intangible Assets | AG73: 256 | AH73: 980 | AI73: 534
A74: Assets classified for sale | AG74: 88 | AH74: 220 | AI74: 7
A75: Other | AG75: 5 | AH75: 0 | AI75: 49
AG76: =SUM(AG72:AG75) -> 1886 | AH76: =SUM(AH72:AH75) -> 3096 | AI76: =SUM(AI72:AI75) -> 2605
A81: Debt Schedule
A82: Non-current borrowings | I82: =I31 -> 13026 | J82: =J31 -> 12893 | K82: =K31 -> 14441 | L82: =L31 -> 14046 | M82: =M31 -> 13792 | N82: =AI82 -> 13783 | O82: =N82+250 -> 14033 | P82: =O82+250 -> 14283 | Q82: =P82+250 -> 14533 | R82: =AK82 -> 14783 | S82: =R82+250 -> 15033 | T82: =AL82 -> 15283 | U82: =T82+250 -> 15533 | V82: =AM82 -> 15783 | W82: =V82+250 -> 16033 | X82: =AN82 -> 16283 | Y82: =X82+250 -> 16533 | Z82: =AO82 -> 16783 | AG82: 12893 | AH82: 14046 | AI82: 13783 | AJ82: =AI82+500 -> 14283 | AK82: =AJ82+500 -> 14783 | AL82: =AK82+500 -> 15283 | AM82: =AL82+500 -> 15783 | AN82: =AM82+500 -> 16283 | AO82: =AN82+500 -> 16783
A83: Current borrowings | I83: =I38 -> 3556 | J83: =J38 -> 3484 | K83: =K38 -> 5416 | L83: =L38 -> 4192 | M83: =M38 -> 4705 | N83: =AI83 -> 4192 | O83: =N83 -> 4192 | P83: =AJ83 -> 4192 | Q83: =P83 -> 4192 | R83: =AK83 -> 4192 | S83: =R83 -> 4192 | T83: =AL83 -> 4192 | U83: =T83 -> 4192 | V83: =AM83 -> 4192 | W83: =V83 -> 4192 | X83: =AN83 -> 4192 | Y83: =X83 -> 4192 | Z83: =AO83 -> 4192 | AG83: 3484 | AH83: 4192 | AI83: =AH83 -> 4192 | AJ83: =AI83 -> 4192 | AK83: =AJ83 -> 4192 | AL83: =AK83 -> 4192 | AM83: =AL83 -> 4192 | AN83: =AM83 -> 4192 | AO83: =AN83 -> 4192
A84: Total Borrowings | B84: =SUM(#REF!) -> #REF! | C84: =SUM(#REF!) -> #REF! | D84: =SUM(#REF!) -> #REF! | E84: =SUM(#REF!) -> #REF! | F84: =SUM(#REF!) -> #REF! | G84: =SUM(#REF!) -> #REF! | H84: =SUM(#REF!) -> #REF! | I84: =I82+I83 -> 16582 | J84: =J82+J83 -> 16377 | K84: =K82+K83 -> 19857 | L84: =L82+L83 -> 18238 | M84: =M82+M83 -> 18497 | N84: =N82+N83 -> 17975 | O84: =O82+O83 -> 18225 | P84: =P82+P83 -> 18475 | ... Z84: =Z82+Z83 -> 20975 | AE84: =SUM(#REF!) -> #REF! | AF84: =SUM(#REF!) -> #REF! | AG84: =AG82+AG83 -> 16377 | AH84: =AH82+AH83 -> 18238 | AI84: =AI82+AI83 -> 17975 | AJ84: =AJ82+AJ83 -> 18475 | AK84: =AK82+AK83 -> 18975 | AL84: =AL82+AL83 -> 19475 | AM84: =AM82+AM83 -> 19975 | AN84: =AN82+AN83 -> 20475 | AO84: =AO82+AO83 -> 20975
A85: Market Value of cross-currency interest rate swaps | M85: 12 | AG85: -17 | AH85: -3
A86: Other investments | M86: -58 | AG86: -64 | AH86: -23
A87: Cash and Cash Equivalents | M87: -2277 | N87: ='Cash Flow Statement'!N50 -> 2339.2188 | AG87: -2765 | AH87: -2377 | AI87: =-AI17 -> -2350
A88: Net Debt | B88: =B84+SUM(#REF!) -> #REF! | C88: =C84+SUM(#REF!) -> #REF! | D88: =D84+SUM(#REF!) -> #REF! | E88: =E84+SUM(#REF!) -> #REF! | F88: =F84+SUM(#REF!) -> #REF! | G88: =G84+SUM(#REF!) -> #REF! | H88: =H84+SUM(#REF!) -> #REF! | I88: =I84+I85+I86+I87 -> 16582 | J88: =J84+J85+J86+J87 -> 16377 | K88: =K84+K85+K86+K87 -> 19857 | L88: =L84+L85+L86+L87 -> 18238 | M88: =M84+M85+M86+M87 -> 16174 | N88: =N84+N85+N86-N87 -> 15635.781 | O88: =O84+O85+O86+O87 -> 18225 | P88: =P84+P85+P86+P87 -> 18475 | Q88: =Q84+Q85+Q86+Q87 -> 18725 | R88: =R84+R85+R86+R87 -> 18975 | S88: =S84+S85+S86+S87 -> 19225 | T88: =T84+T85+T86+T87 -> 19475 | U88: =U84+U85+U86+U87 -> 19725 | V88: =V84+V85+V86+V87 -> 19975 | ... Z88: =Z84+Z85+Z86+Z87 -> 20975 | AE88: =AE84+AE85+AE86+AE87 -> #REF! | AF88: =AF84+AF85+AF86+AF87 -> #REF! | AG88: =AG84+AG85+AG86+AG87 -> 13531 | AH88: =AH84+AH85+AH86+AH87 -> 15835 | AI88: =AI84+AI85+AI86+AI87 -> 15625 | AJ88: =AJ84+AJ85+AJ86+AJ87 -> 18475 | AK88: =AK84+AK85+AK86+AK87 -> 18975 | AL88: =AL84+AL85+AL86+AL87 -> 19475 | ... AO88: =AO84+AO85+AO86+AO87 -> 20975
A90: Interest | I90: ='Profit and Loss Statement '!I17 -> -214 | J90: ='Profit and Loss Statement '!J17 -> -244 | K90: ='Profit and Loss Statement '!K17 -> -295 | L90: ='Profit and Loss Statement '!L17 -> -345 | M90: ='Profit and Loss Statement '!M17 -> -342 | N90: =AI90-M90 -> -377 | O90: =-O91*O84 -> -364.5 | P90: =AJ90-O90 -> -374.5 | Q90: =-Q91*Q84 -> -374.5 | R90: =AK90-Q90 -> -384.5 | S90: =-S91*S84 -> -384.5 | T90: =AL90-S90 -> -394.5 | U90: =-U91*U84 -> -394.5 | V90: =AM90-U90 -> -404.5 | W90: =-W91*W84 -> -404.5 | X90: =AN90-W90 -> -414.5 | Y90: =-Y91*Y84 -> -414.5 | Z90: =AO90-Y90 -> -424.5 | AG90: ='Profit and Loss Statement '!AG17 -> -458 | AH90: ='Profit and Loss Statement '!AH17 -> -640 | AI90: =-AI91*AI84 -> -719 | AJ90: =-AJ91*AJ84 -> -739 | AK90: =-AK91*AK84 -> -759 | AL90: =-AL91*AL84 -> -779 | AM90: =-AM91*AM84 -> -799 | AN90: =-AN91*AN84 -> -819 | AO90: =-AO91*AO84 -> -839
A91: Interest charge (%) | I91: =-I90/I84 -> 0.01290556 | J91: =-J90/J84 -> 0.014898944 | K91: =-K90/K84 -> 0.014856222 | L91: =-L90/L84 -> 0.018916548 | M91: =-M90/M84 -> 0.018489485 | N91: =-N90/N84 -> 0.020973574 | O91: 0.02 | P91: =-P90/P84 -> 0.020270636 | Q91: 0.02 | R91: =-R90/R84 -> 0.020263505 | S91: 0.02 | T91: =-T90/T84 -> 0.020256739 | U91: 0.02 | V91: =-V90/V84 -> 0.020250313 | W91: 0.02 | X91: =-X90/X84 -> 0.0202442 | Y91: 0.02 | Z91: =-Z90/Z84 -> 0.020238379 | AG91: =-AG90/AG84 -> 0.02796605 | AH91: =-AH90/AH84 -> 0.035091567 | AI91: 0.04 | AJ91: 0.04 | AK91: 0.04 | AL91: 0.04 | AM91: 0.04 | AN91: 0.04 | AO91: 0.04
A93: FCF
A94: FCF | AD94: ='Cash Flow Statement'!AD22-'Cash Flow Statement'!AD25 -> 0 | AE94: ='Cash Flow Statement'!AE22-'Cash Flow Statement'!AE25 -> 4637 | AF94: ='Cash Flow Statement'!AF22-'Cash Flow Statement'!AF25 -> 5505 | AG94: ='Cash Flow Statement'!AG22-'Cash Flow Statement'!AG25 -> 6287 | AH94: ='Cash Flow Statement'!AH22-'Cash Flow Statement'!AH25 -> 6864 | AI94: ='Cash Flow Statement'!AI22-'Cash Flow Statement'!AI25 -> 7687 | AJ94: ='Cash Flow Statement'!AJ22-'Cash Flow Statement'!AJ25 -> 7179.2293 | AK94: ='Cash Flow Statement'!AK22-'Cash Flow Statement'!AK25 -> 7942.1457 | ... AO94: ='Cash Flow Statement'!AO22-'Cash Flow Statement'!AO25 -> 12123.433
A95: FCF Yield
A97: Working Capital Schedule
A98: Days | I98: 182.5 | J98: 182.5 | K98: 182.5 | L98: 182.5 | M98: 183 | N98: 183 | O98: 182.5 | P98: 182.5 | Q98: 182.5 | R98: 182.5 | S98: 182.5 | T98: 182.5 | U98: 182.5 | V98: 183 | W98: 182.5 | X98: 182.5 | Y98: 182.5 | Z98: 182.5 | AG98: 365 | AH98: 365 | AI98: 366 | AJ98: 365 | AK98: 365 | AL98: 365 | AM98: 366 | AN98: 365 | AO98: 365
A99: =A13 -> Inventories | I99: =I13 -> 3143 | J99: =J13 -> 3250 | K99: =K13 -> 4370 | L99: =L13 -> 3721 | M99: =M13 -> 3859 | N99: =AI99 -> 3644.7125 | O99: =O103*'Profit and Loss Statement '!O$5/'Balance Sheet'!O$98 -> 3760.9109 | P99: =AJ99 -> 4328.4016 | Q99: =Q103*'Profit and Loss Statement '!Q$5/'Balance Sheet'!Q$98 -> 3566.8554 | R99: =AK99 -> 4744.9048 | S99: =S103*'Profit and Loss Statement '!S$5/'Balance Sheet'!S$98 -> 3756.5143 | T99: =AL99 -> 5242.472 | U99: =U103*'Profit and Loss Statement '!U$5/'Balance Sheet'!U$98 -> 4037.7976 | V99: =AM99 -> 5815.9926 | W99: =W103*'Profit and Loss Statement '!W$5/'Balance Sheet'!W$98 -> 4413.6596 | X99: =AN99 -> 6527.9335 | Y99: =Y103*'Profit and Loss Statement '!Y$5/'Balance Sheet'!Y$98 -> 4893.1346 | Z99: =AO99 -> 7349.2831 | AG99: =AG13 -> 3250 | AH99: =AH13 -> 3721 | AI99: =AI103*'Profit and Loss Statement '!AI$5/'Balance Sheet'!AI$98 -> 3644.7125 | AJ99: =AJ103*'Profit and Loss Statement '!AJ$5/'Balance Sheet'!AJ$98 -> 4328.4016 | AK99: =AK103*'Profit and Loss Statement '!AK$5/'Balance Sheet'!AK$98 -> 4744.9048 | AL99: =AL103*'Profit and Loss Statement '!AL$5/'Balance Sheet'!AL$98 -> 5242.472 | AM99: =AM103*'Profit and Loss Statement '!AM$5/'Balance Sheet'!AM$98 -> 5815.9926 | AN99: =AN103*'Profit and Loss Statement '!AN$5/'Balance Sheet'!AN$98 -> 6527.9335 | AO99: =AO103*'Profit and Loss Statement '!AO$5/'Balance Sheet'!AO$98 -> 7349.2831
A100: =A14 -> Trade and other receivables | I100: =I14 -> 4966 | J100: =J14 -> 4531 | K100: =K14 -> 5715 | L100: =L14 -> 5019 | M100: =M14 -> 5385 | N100: =AI100 -> 4916.1011 | O100: =O104*'Profit and Loss Statement '!O$5/'Balance Sheet'!O$98 -> 5072.833 | P100: =AJ100 -> 5838.2821 | Q100: =Q104*'Profit and Loss Statement '!Q$5/'Balance Sheet'!Q$98 -> 4811.0849 | R100: =AK100 -> 6400.0746 | S100: =S104*'Profit and Loss Statement '!S$5/'Balance Sheet'!S$98 -> 5066.9028 | T100: =AL100 -> 7071.2085 | U100: =U104*'Profit and Loss Statement '!U$5/'Balance Sheet'!U$98 -> 5446.3065 | V100: =AM100 -> 7844.7908 | W100: =W104*'Profit and Loss Statement '!W$5/'Balance Sheet'!W$98 -> 5953.2806 | X100: =AN100 -> 8805.0788 | Y100: =Y104*'Profit and Loss Statement '!Y$5/'Balance Sheet'!Y$98 -> 6600.0114 | Z100: =AO100 -> 9912.9406 | AG100: =AG14 -> 4531 | AH100: =AH14 -> 5019 | AI100: =AI104*'Profit and Loss Statement '!AI$5/'Balance Sheet'!AI$98 -> 4916.1011 | AJ100: =AJ104*'Profit and Loss Statement '!AJ$5/'Balance Sheet'!AJ$98 -> 5838.2821 | AK100: =AK104*'Profit and Loss Statement '!AK$5/'Balance Sheet'!AK$98 -> 6400.0746 | AL100: =AL104*'Profit and Loss Statement '!AL$5/'Balance Sheet'!AL$98 -> 7071.2085 | AM100: =AM104*'Profit and Loss Statement '!AM$5/'Balance Sheet'!AM$98 -> 7844.7908 | AN100: =AN104*'Profit and Loss Statement '!AN$5/'Balance Sheet'!AN$98 -> 8805.0788 | AO100: =AO104*'Profit and Loss Statement '!AO$5/'Balance Sheet'!AO$98 -> 9912.9406
A101: Trade Payables | I101: =I39 -> 9091 | J101: =J39 -> 9283 | K101: =K39 -> 9744 | L101: =L39 -> 9432 | M101: =M39 -> 9401 | N101: =AI101 -> 9238.6262 | O101: =O105*'Profit and Loss Statement '!O$5/'Balance Sheet'!O$98 -> 9533.1662 | P101: =AJ101 -> 10971.643 | Q101: =Q105*'Profit and Loss Statement '!Q$5/'Balance Sheet'!Q$98 -> 9041.2738 | R101: =AK101 -> 12027.397 | S101: =S105*'Profit and Loss Statement '!S$5/'Balance Sheet'!S$98 -> 9522.0218 | T101: =AL101 -> 13288.631 | U101: =U105*'Profit and Loss Statement '!U$5/'Balance Sheet'!U$98 -> 10235.019 | V101: =AM101 -> 14742.392 | W101: =W105*'Profit and Loss Statement '!W$5/'Balance Sheet'!W$98 -> 11187.755 | X101: =AN101 -> 16547.022 | Y101: =Y105*'Profit and Loss Statement '!Y$5/'Balance Sheet'!Y$98 -> 12403.13 | Z101: =AO101 -> 18628.981 | AG101: =AG39 -> 9283 | AH101: =AH39 -> 9432 | AI101: =AI105*'Profit and Loss Statement '!AI$5/'Balance Sheet'!AI$98 -> 9238.6262 | AJ101: =AJ105*'Profit and Loss Statement '!AJ$5/'Balance Sheet'!AJ$98 -> 10971.643 | AK101: =AK105*'Profit and Loss Statement '!AK$5/'Balance Sheet'!AK$98 -> 12027.397 | AL101: =AL105*'Profit and Loss Statement '!AL$5/'Balance Sheet'!AL$98 -> 13288.631 | AM101: =AM105*'Profit and Loss Statement '!AM$5/'Balance Sheet'!AM$98 -> 14742.392 | AN101: =AN105*'Profit and Loss Statement '!AN$5/'Balance Sheet'!AN$98 -> 16547.022 | AO101: =AO105*'Profit and Loss Statement '!AO$5/'Balance Sheet'!AO$98 -> 18628.981
A103: DIO | I103: =I99/'Profit and Loss Statement '!I$5*'Balance Sheet'!I$98 -> 42.535966 | J103: =J99/'Profit and Loss Statement '!J$5*'Balance Sheet'!J$98 -> 38.934292 | K103: =K99/'Profit and Loss Statement '!K$5*'Balance Sheet'!K$98 -> 54.910837 | L103: =L99/'Profit and Loss Statement '!L$5*'Balance Sheet'!L$98 -> 42.876784 | M103: =M99/'Profit and Loss Statement '!M$5*'Balance Sheet'!M$98 -> 47.638761 | N103: =N99/'Profit and Loss Statement '!N$5*'Balance Sheet'!N$98 -> 44.474387 | O103: =N103 -> 44.474387 | P103: =P99/'Profit and Loss Statement '!P$5*'Balance Sheet'!P$98 -> 39.72442 | Q103: =P103 -> 39.72442 | R103: =R99/'Profit and Loss Statement '!R$5*'Balance Sheet'!R$98 -> 38.779423 | S103: =R103 -> 38.779423 | T103: =T99/'Profit and Loss Statement '!T$5*'Balance Sheet'!T$98 -> 38.120448 | U103: =T103 -> 38.120448 | V103: =V99/'Profit and Loss Statement '!V$5*'Balance Sheet'!V$98 -> 37.6678 | W103: =V103 -> 37.6678 | X103: =X99/'Profit and Loss Statement '!X$5*'Balance Sheet'!X$98 -> 37.368083 | Y103: =X103 -> 37.368083 | Z103: =Z99/'Profit and Loss Statement '!Z$5*'Balance Sheet'!Z$98 -> 37.184331 | AG103: =AG99/'Profit and Loss Statement '!AG$5*'Balance Sheet'!AG$98 -> 41.305408 | AH103: =AH99/'Profit and Loss Statement '!AH$5*'Balance Sheet'!AH$98 -> 44.732396 | AI103: =AH103 -> 44.732396 | AJ103: =AI103 -> 44.732396 | AK103: =AJ103 -> 44.732396 | AL103: =AK103 -> 44.732396 | AM103: =AL103 -> 44.732396 | AN103: =AM103 -> 44.732396 | AO103: =AN103 -> 44.732396
A104: DSO | I104: =I100/'Profit and Loss Statement '!I$5*'Balance Sheet'!I$98 -> 67.207638 | J104: =J100/'Profit and Loss Statement '!J$5*'Balance Sheet'!J$98 -> 54.280393 | K104: =K100/'Profit and Loss Statement '!K$5*'Balance Sheet'!K$98 -> 71.811312 | L104: =L100/'Profit and Loss Statement '!L$5*'Balance Sheet'!L$98 -> 57.833533 | M104: =M100/'Profit and Loss Statement '!M$5*'Balance Sheet'!M$98 -> 66.476997 | N104: =N100/'Profit and Loss Statement '!N$5*'Balance Sheet'!N$98 -> 59.988431 | O104: =N104 -> 59.988431 | P104: =P100/'Profit and Loss Statement '!P$5*'Balance Sheet'!P$98 -> 53.581528 | Q104: =P104 -> 53.581528 | R104: =R100/'Profit and Loss Statement '!R$5*'Balance Sheet'!R$98 -> 52.306887 | S104: =R104 -> 52.306887 | T104: =T100/'Profit and Loss Statement '!T$5*'Balance Sheet'!T$98 -> 51.418041 | U104: =T104 -> 51.418041 | V104: =V100/'Profit and Loss Statement '!V$5*'Balance Sheet'!V$98 -> 50.807495 | W104: =V104 -> 50.807495 | X104: =X100/'Profit and Loss Statement '!X$5*'Balance Sheet'!X$98 -> 50.403227 | Y104: =X104 -> 50.403227 | Z104: =Z100/'Profit and Loss Statement '!Z$5*'Balance Sheet'!Z$98 -> 50.155377 | AG104: =AG100/'Profit and Loss Statement '!AG$5*'Balance Sheet'!AG$98 -> 57.586093 | AH104: =AH100/'Profit and Loss Statement '!AH$5*'Balance Sheet'!AH$98 -> 60.33644 | AI104: =AH104 -> 60.33644 | AJ104: =AI104 -> 60.33644 | AK104: =AJ104 -> 60.33644 | AL104: =AK104 -> 60.33644 | AM104: =AL104 -> 60.33644 | AN104: =AM104 -> 60.33644 | AO104: =AN104 -> 60.33644
A105: DPO | I105: =I101/'Profit and Loss Statement '!I$5*'Balance Sheet'!I$98 -> 123.03356 | J105: =J101/'Profit and Loss Statement '!J$5*'Balance Sheet'!J$98 -> 111.20832 | K105: =K101/'Profit and Loss Statement '!K$5*'Balance Sheet'!K$98 -> 122.43735 | L105: =L101/'Profit and Loss Statement '!L$5*'Balance Sheet'!L$98 -> 108.68418 | M105: =M101/'Profit and Loss Statement '!M$5*'Balance Sheet'!M$98 -> 116.0539 | N105: =N101/'Profit and Loss Statement '!N$5*'Balance Sheet'!N$98 -> 112.73379 | O105: =N105 -> 112.73379 | P105: =P101/'Profit and Loss Statement '!P$5*'Balance Sheet'!P$98 -> 100.69356 | Q105: =P105 -> 100.69356 | R105: =R101/'Profit and Loss Statement '!R$5*'Balance Sheet'!R$98 -> 98.298178 | S105: =R105 -> 98.298178 | T105: =T101/'Profit and Loss Statement '!T$5*'Balance Sheet'!T$98 -> 96.627807 | U105: =T105 -> 96.627807 | V105: =V101/'Profit and Loss Statement '!V$5*'Balance Sheet'!V$98 -> 95.480432 | W105: =V105 -> 95.480432 | X105: =X101/'Profit and Loss Statement '!X$5*'Balance Sheet'!X$98 -> 94.72071 | Y105: =X105 -> 94.72071 | Z105: =Z101/'Profit and Loss Statement '!Z$5*'Balance Sheet'!Z$98 -> 94.254935 | AG105: =AG101/'Profit and Loss Statement '!AG$5*'Balance Sheet'!AG$98 -> 117.98095 | AH105: =AH101/'Profit and Loss Statement '!AH$5*'Balance Sheet'!AH$98 -> 113.38779 | AI105: =AH105 -> 113.38779 | AJ105: =AI105 -> 113.38779 | AK105: =AJ105 -> 113.38779 | AL105: =AK105 -> 113.38779 | AM105: =AL105 -> 113.38779 | AN105: =AM105 -> 113.38779 | AO105: =AN105 -> 113.38779
A107: Retained Earnings schedule

Sheet Cash Flow Statement
A1: ='Profit and Loss Statement '!A1 -> In millions of € | B1: ='Profit and Loss Statement '!B1 -> H1'19 | C1: ='Profit and Loss Statement '!C1 -> H2'19 | D1: ='Profit and Loss Statement '!D1 -> FY'19 | E1: ='Profit and Loss Statement '!E1 -> H1'20 | F1: ='Profit and Loss Statement '!F1 -> H2'20 | G1: ='Profit and Loss Statement '!G1 -> H1'21 | H1: ='Profit and Loss Statement '!H1 -> H2'21 | ... Z1: ='Profit and Loss Statement '!Z1 -> H2'30 | AE1: ='Profit and Loss Statement '!AE1 -> FY'20 | AF1: ='Profit and Loss Statement '!AF1 -> FY'21 | AG1: ='Profit and Loss Statement '!AG1 -> FY'22 | AH1: ='Profit and Loss Statement '!AH1 -> FY'23 | AI1: ='Profit and Loss Statement '!AI1 -> FY'24 | AJ1: ='Profit and Loss Statement '!AJ1 -> FY'25 | AK1: ='Profit and Loss Statement '!AK1 -> FY'26 | AL1: ='Profit and Loss Statement '!AL1 -> FY'27 | ... AO1: ='Profit and Loss Statement '!AO1 -> FY'30
A3: Profit/Loss | B3: 1038 | C3: =D3-B3 -> 1336 | D3: 2374 | E3: -272 | F3: =AE3-E3 -> 184 | G3: 1169 | H3: =AF3-G3 -> 2366 | I3: 1455 | J3: =AG3-I3 -> 1584 | K3: 1187 | L3: =AH3-K3 -> 1214 | M3: ='Profit and Loss Statement '!M24 -> -48 | N3: ='Profit and Loss Statement '!N24 -> 843.21882 | O3: ='Profit and Loss Statement '!O24 -> 1077.6022 | P3: ='Profit and Loss Statement '!P24 -> 885.31721 | Q3: ='Profit and Loss Statement '!Q24 -> 1181.1559 | R3: ='Profit and Loss Statement '!R24 -> 1079.8071 | S3: ='Profit and Loss Statement '!S24 -> 1340.9254 | T3: ='Profit and Loss Statement '!T24 -> 1287.5893 | ... Z3: ='Profit and Loss Statement '!Z24 -> 2050.3134 | AE3: -88 | AF3: 3535 | AG3: 3039 | AH3: 2401 | AI3: 1161 | AJ3: ='Profit and Loss Statement '!AJ24 -> 1962.9194 | AK3: ='Profit and Loss Statement '!AK24 -> 2260.963 | AL3: ='Profit and Loss Statement '!AL24 -> 2628.5147 | AM3: ='Profit and Loss Statement '!AM24 -> 3074.3026 | AN3: ='Profit and Loss Statement '!AN24 -> 3610.5413 | AO3: ='Profit and Loss Statement '!AO24 -> 4253.126
A4: Adjustments:
A5: D&A | B5: 911 | C5: =D5-B5 -> 1048 | D5: 1959 | E5: 1479 | F5: =AE5-E5 -> 1395 | G5: 870 | H5: =AF5-G5 -> 1089 | I5: 932 | J5: =AG5-I5 -> 954 | K5: 1244 | L5: =AH5-K5 -> 1852 | M5: 1367 | N5: =-'Profit and Loss Statement '!N13 -> 1238 | O5: =-'Profit and Loss Statement '!O13 -> 1692.54 | P5: =-'Profit and Loss Statement '!P13 -> 1425.72 | Q5: =-'Profit and Loss Statement '!Q13 -> 1766.7082 | R5: =-'Profit and Loss Statement '!R13 -> 1514.0154 | S5: =-'Profit and Loss Statement '!S13 -> 1848.0132 | T5: =-'Profit and Loss Statement '!T13 -> 1610.8072 | U5: =-'Profit and Loss Statement '!U13 -> 1937.8442 | ... Z5: =-'Profit and Loss Statement '!Z13 -> 1969.8787 | AE5: 2874 | AF5: 1959 | AG5: 1886 | AH5: 3096 | AI5: 2605 | AJ5: =-'Profit and Loss Statement '!AJ13 -> 3118.26 | AK5: =-'Profit and Loss Statement '!AK13 -> 3280.7236 | AL5: =-'Profit and Loss Statement '!AL13 -> 3458.8204 | AM5: =-'Profit and Loss Statement '!AM13 -> 3655.593 | AN5: =-'Profit and Loss Statement '!AN13 -> 3874.4904 | AO5: =-'Profit and Loss Statement '!AO13 -> 4119.5119
A6: Interest Expenses | B6: 227 | C6: =D6-B6 -> 227 | D6: 454 | E6: 207 | F6: =AE6-E6 -> 240 | G6: 202 | H6: =AF6-G6 -> 211 | I6: 185 | J6: =AG6-I6 -> 199 | K6: 249 | L6: =AH6-K6 -> 301 | M6: 295 | N6: =AI6-M6 -> 275 | AE6: 447 | AF6: 413 | AG6: 384 | AH6: 550 | AI6: 570
A7: Other Income | B7: -78 | C7: =D7-B7 -> -17 | D7: -95 | E7: -5 | F7: =AE7-E7 -> -51 | G7: -20 | H7: =AF7-G7 -> -1306 | I7: -31 | J7: =AG7-I7 -> -116 | K7: -103 | L7: =AH7-K7 -> -249 | M7: -5 | N7: =AI7-M7 -> -32 | AE7: -56 | AF7: -1326 | AG7: -147 | AH7: -352 | AI7: -37 | AU7: 0
A8: Profit/Loss asociates & JVs | B8: -85 | C8: =D8-B8 -> -88 | D8: -173 | E8: 32 | F8: =AE8-E8 -> -11 | G8: -75 | H8: =AF8-G8 -> -181 | I8: -85 | J8: =AG8-I8 -> -145 | K8: -107 | L8: =AH8-K8 -> -119 | M8: 751 | N8: =AI8-M8 -> -64 | AE8: 21 | AF8: -256 | AG8: -230 | AH8: -226 | AI8: 687 | AU8: 0
A9: Income tax expenses | B9: 438 | C9: =D9-B9 -> 472 | D9: 910 | E9: 51 | F9: =AE9-E9 -> 194 | G9: 440 | H9: =AF9-G9 -> 359 | I9: 547 | J9: =AG9-I9 -> 584 | K9: 89 | L9: =AH9-K9 -> 32 | M9: 387 | N9: =AI9-M9 -> 459 | AE9: 245 | AF9: 799 | AG9: 1131 | AH9: 121 | AI9: 846 | AU9: 0
A10: Other non-cash items | B10: 182 | C10: =D10-B10 -> 58 | D10: 240 | E10: 85 | F10: =AE10-E10 -> 146 | G10: -9 | H10: =AF10-G10 -> 39 | I10: 97 | J10: =AG10-I10 -> 187 | K10: 316 | L10: =AH10-K10 -> 221 | M10: 169 | N10: =AI10-M10 -> 57 | O10: ='Balance Sheet'!O38-'Balance Sheet'!N38 -> 926 | AE10: 231 | AF10: 30 | AG10: 284 | AH10: 537 | AI10: 226 | AJ10: ='Balance Sheet'!AJ38-'Balance Sheet'!AI38+'Balance Sheet'!AJ40-'Balance Sheet'!AI40+'Balance Sheet'!AJ41-'Balance Sheet'!AI41+'Balance Sheet'!AJ42-'Balance Sheet'!AI42+'Balance Sheet'!AJ43-'Balance Sheet'!AI43+'Balance Sheet'!AI15-'Balance Sheet'!AJ15+'Balance Sheet'!AI16-'Balance Sheet'!AJ16+'Balance Sheet'!AI18-'Balance Sheet'!AJ18 -> 926 | AK10: ='Balance Sheet'!AK38-'Balance Sheet'!AJ38+'Balance Sheet'!AK40-'Balance Sheet'!AJ40+'Balance Sheet'!AK41-'Balance Sheet'!AJ41+'Balance Sheet'!AK42-'Balance Sheet'!AJ42+'Balance Sheet'!AK43-'Balance Sheet'!AJ43+'Balance Sheet'!AJ15-'Balance Sheet'!AK15+'Balance Sheet'!AJ16-'Balance Sheet'!AK16+'Balance Sheet'!AJ18-'Balance Sheet'!AK18 -> 0 | AL10: ='Balance Sheet'!AL38-'Balance Sheet'!AK38+'Balance Sheet'!AL40-'Balance Sheet'!AK40+'Balance Sheet'!AL41-'Balance Sheet'!AK41+'Balance Sheet'!AL42-'Balance Sheet'!AK42+'Balance Sheet'!AL43-'Balance Sheet'!AK43+'Balance Sheet'!AK15-'Balance Sheet'!AL15+'Balance Sheet'!AK16-'Balance Sheet'!AL16+'Balance Sheet'!AK18-'Balance Sheet'!AL18 -> 0 | AM10: ='Balance Sheet'!AM38-'Balance Sheet'!AL38+'Balance Sheet'!AM40-'Balance Sheet'!AL40+'Balance Sheet'!AM41-'Balance Sheet'!AL41+'Balance Sheet'!AM42-'Balance Sheet'!AL42+'Balance Sheet'!AM43-'Balance Sheet'!AL43+'Balance Sheet'!AL15-'Balance Sheet'!AM15+'Balance Sheet'!AL16-'Balance Sheet'!AM16+'Balance Sheet'!AL18-'Balance Sheet'!AM18 -> 0 | AN10: ='Balance Sheet'!AN38-'Balance Sheet'!AM38+'Balance Sheet'!AN40-'Balance Sheet'!AM40+'Balance Sheet'!AN41-'Balance Sheet'!AM41+'Balance Sheet'!AN42-'Balance Sheet'!AM42+'Balance Sheet'!AN43-'Balance Sheet'!AM43+'Balance Sheet'!AM15-'Balance Sheet'!AN15+'Balance Sheet'!AM16-'Balance Sheet'!AN16+'Balance Sheet'!AM18-'Balance Sheet'!AN18 -> 0 | AO10: ='Balance Sheet'!AO38-'Balance Sheet'!AN38+'Balance Sheet'!AO40-'Balance Sheet'!AN40+'Balance Sheet'!AO41-'Balance Sheet'!AN41+'Balance Sheet'!AO42-'Balance Sheet'!AN42+'Balance Sheet'!AO43-'Balance Sheet'!AN43+'Balance Sheet'!AN15-'Balance Sheet'!AO15+'Balance Sheet'!AN16-'Balance Sheet'!AO16+'Balance Sheet'!AN18-'Balance Sheet'!AO18 -> 0 | AU10: 0
A11: Cash Flow before WC | B11: =B3+SUM(B5:B10) -> 2633 | C11: =C3+SUM(C5:C10) -> 3036 | D11: =D3+SUM(D5:D10) -> 5669 | E11: =E3+SUM(E5:E10) -> 1577 | F11: =F3+SUM(F5:F10) -> 2097 | G11: =G3+SUM(G5:G10) -> 2577 | H11: =H3+SUM(H5:H10) -> 2577 | I11: =I3+SUM(I5:I10) -> 3100 | ... Z11: =Z3+SUM(Z5:Z10) -> 4020.1921 | AE11: =AE3+SUM(AE5:AE10) -> 3674 | AF11: =AF3+SUM(AF5:AF10) -> 5154 | AG11: =AG3+SUM(AG5:AG10) -> 6347 | AH11: =AH3+SUM(AH5:AH10) -> 6127 | AI11: =AI3+SUM(AI5:AI10) -> 6058 | AJ11: =AJ3+SUM(AJ5:AJ10) -> 6007.1794 | AK11: =AK3+SUM(AK5:AK10) -> 5541.6866 | AL11: =AL3+SUM(AL5:AL10) -> 6087.3351 | ... AO11: =AO3+SUM(AO5:AO10) -> 8372.6379 | AU11: 0
A12: Change in inventories | B12: -332 | C12: =D12-B12 -> 75 | D12: -257 | E12: -155 | F12: =AE12-E12 -> 137 | G12: -330 | H12: =AF12-G12 -> 22 | I12: -611 | J12: =AG12-I12 -> -182 | K12: -611 | L12: =AH12-K12 -> 607 | M12: -220 | N12: =AI12-M12 -> 181 | O12: ='Balance Sheet'!N13-'Balance Sheet'!O13 -> -188.91086 | P12: =AJ12-O12 -> -567.49076 | Q12: ='Balance Sheet'!P13-'Balance Sheet'!Q13 -> 761.54626 | R12: =AK12-Q12 -> -1178.0495 | S12: ='Balance Sheet'!R13-'Balance Sheet'!S13 -> 988.39053 | T12: =AL12-S12 -> -1485.9577 | U12: ='Balance Sheet'!T13-'Balance Sheet'!U13 -> 1204.6744 | V12: =AM12-U12 -> -1778.1949 | W12: ='Balance Sheet'!V13-'Balance Sheet'!W13 -> 1402.333 | X12: =AN12-W12 -> -2114.2739 | Y12: ='Balance Sheet'!X13-'Balance Sheet'!Y13 -> 1634.7989 | Z12: =AO12-Y12 -> -2456.1485 | AE12: -18 | AF12: -308 | AG12: -793 | AH12: -4 | AI12: -39 | AJ12: ='Balance Sheet'!AI13-'Balance Sheet'!AJ13 -> -756.40163 | AK12: ='Balance Sheet'!AJ13-'Balance Sheet'!AK13 -> -416.50322 | AL12: ='Balance Sheet'!AK13-'Balance Sheet'!AL13 -> -497.56715 | AM12: ='Balance Sheet'!AL13-'Balance Sheet'!AM13 -> -573.52058 | AN12: ='Balance Sheet'!AM13-'Balance Sheet'!AN13 -> -711.94089 | AO12: ='Balance Sheet'!AN13-'Balance Sheet'!AO13 -> -821.34962
A13: Change in trade and other receivables | B13: -769 | C13: =D13-B13 -> 524 | D13: -245 | E13: 7 | F13: =AE13-E13 -> 1117 | G13: -1167 | H13: =AF13-G13 -> 470 | I13: -1150 | J13: =AG13-I13 -> 482 | K13: -869 | L13: =AH13-K13 -> 827 | M13: -469 | N13: =AI13-M13 -> 816 | O13: ='Balance Sheet'!N14-'Balance Sheet'!O14 -> -484.83301 | P13: =AJ13-O13 -> -765.44911 | Q13: ='Balance Sheet'!P14-'Balance Sheet'!Q14 -> 1027.1972 | R13: =AK13-Q13 -> -1588.9896 | S13: ='Balance Sheet'!R14-'Balance Sheet'!S14 -> 1333.1717 | T13: =AL13-S13 -> -2004.3057 | U13: ='Balance Sheet'!T14-'Balance Sheet'!U14 -> 1624.9021 | V13: =AM13-U13 -> -2398.4844 | W13: ='Balance Sheet'!V14-'Balance Sheet'!W14 -> 1891.5102 | X13: =AN13-W13 -> -2851.7981 | Y13: ='Balance Sheet'!X14-'Balance Sheet'!Y14 -> 2205.0674 | Z13: =AO13-Y13 -> -3312.9292 | AE13: 1124 | AF13: -697 | AG13: -668 | AH13: -42 | AI13: 347 | AJ13: ='Balance Sheet'!AI14-'Balance Sheet'!AJ14 -> -1250.2821 | AK13: ='Balance Sheet'!AJ14-'Balance Sheet'!AK14 -> -561.79243 | AL13: ='Balance Sheet'!AK14-'Balance Sheet'!AL14 -> -671.13398 | AM13: ='Balance Sheet'!AL14-'Balance Sheet'!AM14 -> -773.58231 | AN13: ='Balance Sheet'!AM14-'Balance Sheet'!AN14 -> -960.28792 | AO13: ='Balance Sheet'!AN14-'Balance Sheet'!AO14 -> -1107.8618
A14: Change in trade and other payables | B14: 818 | C14: =D14-B14 -> -308 | D14: 510 | E14: -548 | F14: =AE14-E14 -> -211 | G14: 1185 | H14: =AF14-G14 -> 83 | I14: 1545 | J14: =AG14-I14 -> -564 | K14: 470 | L14: =AH14-K14 -> -570 | M14: 437 | N14: =AI14-M14 -> 106 | O14: ='Balance Sheet'!O39-'Balance Sheet'!N39 -> -378.83385 | P14: =AJ14-O14 -> 1438.477 | Q14: ='Balance Sheet'!Q39-'Balance Sheet'!P39 -> -1930.3694 | R14: =AK14-Q14 -> 2986.1227 | S14: ='Balance Sheet'!S39-'Balance Sheet'!R39 -> -2505.3747 | T14: =AL14-S14 -> 3766.6092 | U14: ='Balance Sheet'!U39-'Balance Sheet'!T39 -> -3053.6115 | V14: =AM14-U14 -> 4507.3729 | W14: ='Balance Sheet'!W39-'Balance Sheet'!V39 -> -3554.6372 | X14: =AN14-W14 -> 5359.2667 | Y14: ='Balance Sheet'!Y39-'Balance Sheet'!X39 -> -4143.8923 | Z14: =AO14-Y14 -> 6225.8513 | AE14: -759 | AF14: 1268 | AG14: 981 | AH14: -100 | AI14: 543 | AJ14: ='Balance Sheet'!AJ39-'Balance Sheet'!AI39 -> 1059.6431 | AK14: ='Balance Sheet'!AK39-'Balance Sheet'!AJ39 -> 1055.7534 | AL14: ='Balance Sheet'!AL39-'Balance Sheet'!AK39 -> 1261.2344 | AM14: ='Balance Sheet'!AM39-'Balance Sheet'!AL39 -> 1453.7614 | AN14: ='Balance Sheet'!AN39-'Balance Sheet'!AM39 -> 1804.6295 | AO14: ='Balance Sheet'!AO39-'Balance Sheet'!AN39 -> 2081.9591
A15: Total change | B15: =SUM(B12:B14) -> -283 | C15: =SUM(C12:C14) -> 291 | D15: =SUM(D12:D14) -> 8 | E15: =SUM(E12:E14) -> -696 | F15: =SUM(F12:F14) -> 1043 | G15: =SUM(G12:G14) -> -312 | H15: =SUM(H12:H14) -> 575 | I15: =SUM(I12:I14) -> -216 | ... Z15: =SUM(Z12:Z14) -> 456.77365 | AE15: =SUM(AE12:AE14) -> 347 | AF15: =SUM(AF12:AF14) -> 263 | AG15: =SUM(AG12:AG14) -> -480 | AH15: =SUM(AH12:AH14) -> -146 | AI15: =SUM(AI12:AI14) -> 851 | AJ15: =SUM(AJ12:AJ14) -> -947.0406 | AK15: =SUM(AK12:AK14) -> 77.457733 | AL15: =SUM(AL12:AL14) -> 92.533316 | ... AO15: =SUM(AO12:AO14) -> 152.74763
A16: Change in provisions and post-retirement obligations | B16: -98 | C16: =D16-B16 -> -23 | D16: -121 | E16: 3 | F16: =AE16-E16 -> 208 | G16: -148 | H16: =AF16-G16 -> -142 | I16: -100 | J16: =AG16-I16 -> -107 | K16: -30 | L16: =AH16-K16 -> -2 | M16: 22 | N16: =AI16-M16 -> -28 | P16: =AJ16-O16 -> 0 | R16: =AK16-Q16 -> 0 | T16: =AL16-S16 -> 0 | V16: =AM16-U16 -> 0 | X16: =AN16-W16 -> 0 | Z16: =AO16-Y16 -> 0 | AE16: 211 | AF16: -290 | AG16: -207 | AH16: -32 | AI16: -6 | AU16: 0
A17: Cash flow from operations | B17: =B11+B15+B16 -> 2252 | C17: =C11+C15+C16 -> 3304 | D17: =D11+D15+D16 -> 5556 | E17: =E11+E15+E16 -> 884 | F17: =F11+F15+F16 -> 3348 | G17: =G11+G15+G16 -> 2117 | H17: =H11+H15+H16 -> 3010 | I17: =I11+I15+I16 -> 2784 | ... Z17: =Z11+Z15+Z16 -> 4476.9657 | AE17: =AE11+AE15+AE16 -> 4232 | AF17: =AF11+AF15+AF16 -> 5127 | AG17: =AG11+AG15+AG16 -> 5660 | AH17: =AH11+AH15+AH16 -> 5949 | AI17: =AI11+AI15+AI16 -> 6903 | AJ17: =AJ11+AJ15+AJ16 -> 5060.1388 | AK17: =AK11+AK15+AK16 -> 5619.1443 | AL17: =AL11+AL15+AL16 -> 6179.8684 | ... AO17: =AO11+AO15+AO16 -> 8525.3855 | AU17: 0
A18: Interest paid | B18: -256 | C18: =D18-B18 -> -272 | D18: -528 | E18: -244 | F18: =AE18-E18 -> -237 | G18: -271 | H18: =AF18-G18 -> -185 | I18: -236 | J18: =AG18-I18 -> -203 | K18: -298 | L18: =AH18-K18 -> -326 | M18: -349 | N18: =AI18-M18 -> -319 | P18: =AJ18-O18 -> 0 | R18: =AK18-Q18 -> 0 | T18: =AL18-S18 -> 0 | V18: =AM18-U18 -> 0 | X18: =AN18-W18 -> 0 | Z18: =AO18-Y18 -> 0 | AE18: -481 | AF18: -456 | AG18: -439 | AH18: -624 | AI18: -668 | AU18: -1898.171
A19: Interest received | B19: 31 | C19: =D19-B19 -> 21 | D19: 52 | E19: 27 | F19: =AE19-E19 -> 18 | G19: 22 | H19: =AF19-G19 -> 21 | I19: 17 | J19: =AG19-I19 -> 29 | K19: 51 | L19: =AH19-K19 -> 67 | M19: 51 | N19: =AI19-M19 -> 69 | P19: =AJ19-O19 -> 0 | R19: =AK19-Q19 -> 0 | T19: =AL19-S19 -> 0 | V19: =AM19-U19 -> 0 | X19: =AN19-W19 -> 0 | Z19: =AO19-Y19 -> 0 | AE19: 45 | AF19: 43 | AG19: 46 | AH19: 118 | AI19: 120 | AU19: 0
A20: Dividends received | B20: 111 | C20: =D20-B20 -> 70 | D20: 181 | E20: 50 | F20: =AE20-E20 -> 39 | G20: 37 | H20: =AF20-G20 -> 147 | I20: 60 | J20: =AG20-I20 -> 117 | K20: 51 | L20: =AH20-K20 -> 96 | M20: 58 | N20: =AI20-M20 -> 141 | P20: =AJ20-O20 -> 0 | R20: =AK20-Q20 -> 0 | T20: =AL20-S20 -> 0 | V20: =AM20-U20 -> 0 | X20: =AN20-W20 -> 0 | Z20: =AO20-Y20 -> 0 | AE20: 89 | AF20: 184 | AG20: 177 | AH20: 147 | AI20: 199 | AU20: 0
A21: Income taxes paid | B21: -456 | C21: =D21-B21 -> -468 | D21: -924 | E21: -382 | F21: =AE21-E21 -> -367 | G21: -324 | H21: =AF21-G21 -> -393 | I21: -456 | J21: =AG21-I21 -> -492 | K21: -607 | L21: =AH21-K21 -> -553 | M21: -503 | N21: =AI21-M21 -> -548 | P21: =AJ21-O21 -> 0 | R21: =AK21-Q21 -> 0 | T21: =AL21-S21 -> 0 | V21: =AM21-U21 -> 0 | X21: =AN21-W21 -> 0 | Z21: =AO21-Y21 -> 0 | AE21: -749 | AF21: -717 | AG21: -948 | AH21: -1160 | AI21: -1051
A22: Cash flow from (used in)/Operating Activites | B22: =SUM(B17:B21) -> 1682 | C22: =SUM(C17:C21) -> 2655 | D22: =SUM(D17:D21) -> 4337 | E22: =SUM(E17:E21) -> 335 | F22: =SUM(F17:F21) -> 2801 | G22: =SUM(G17:G21) -> 1581 | H22: =SUM(H17:H21) -> 2600 | I22: =SUM(I17:I21) -> 2169 | ... Z22: =SUM(Z17:Z21) -> 4476.9657 | AE22: =SUM(AE17:AE21) -> 3136 | AF22: =SUM(AF17:AF21) -> 4181 | AG22: =SUM(AG17:AG21) -> 4496 | AH22: =SUM(AH17:AH21) -> 4430 | AI22: =SUM(AI17:AI21) -> 5503 | AJ22: =SUM(AJ17:AJ21) -> 5060.1388 | AK22: =SUM(AK17:AK21) -> 5619.1443 | AL22: =SUM(AL17:AL21) -> 6179.8684 | ... AO22: =SUM(AO17:AO21) -> 8525.3855
A24: Sale of PP&E | B24: 23 | C24: =D24-B24 -> 154 | D24: 177 | E24: 28 | F24: =AE24-E24 -> 122 | G24: 35 | H24: =AF24-G24 -> 51 | I24: 51 | J24: =AG24-I24 -> 61 | K24: 84 | L24: =AH24-K24 -> 70 | M24: 51 | N24: =AI24-M24 -> 101 | P24: =AJ24-O24 -> 0 | R24: =AK24-Q24 -> 0 | T24: =AL24-S24 -> 0 | V24: =AM24-U24 -> 0 | X24: =AN24-W24 -> 0 | Z24: =AO24-Y24 -> 0 | AE24: 150 | AF24: 86 | AG24: 112 | AH24: 154 | AI24: 152
A25: Purchase of PP&E | B25: -1005 | C25: =D25-B25 -> -910 | D25: -1915 | E25: -1064 | F25: =AE25-E25 -> -437 | G25: -728 | H25: =AF25-G25 -> -596 | I25: -958 | J25: =AG25-I25 -> -833 | K25: -1378 | L25: =AH25-K25 -> -1056 | M25: -1221 | N25: =AI25-M25 -> -963 | O25: =-('Balance Sheet'!O54) -> -925.97057 | P25: =AJ25-O25 -> -1193.1199 | Q25: =-('Balance Sheet'!Q54) -> -983.20041 | R25: =AK25-Q25 -> -1339.8009 | S25: =-('Balance Sheet'!S54) -> -1060.7128 | T25: =AL25-S25 -> -1505.8865 | U25: =-('Balance Sheet'!U54) -> -1159.8469 | V25: =AM25-U25 -> -1695.3366 | W25: =-('Balance Sheet'!W54) -> -1283.0474 | X25: =AN25-W25 -> -1912.8857 | Y25: =-('Balance Sheet'!Y54) -> -1433.8392 | Z25: =AO25-Y25 -> -2164.2086 | AE25: -1501 | AF25: -1324 | AG25: -1791 | AH25: -2434 | AI25: -2184 | AJ25: =-('Balance Sheet'!AJ54) -> -2119.0905 | AK25: =-('Balance Sheet'!AK54+'Balance Sheet'!AK61) -> -2323.0014 | AL25: =-('Balance Sheet'!AL54+'Balance Sheet'!AL61) -> -2566.5993 | AM25: =-('Balance Sheet'!AM54+'Balance Sheet'!AM61) -> -2855.1835 | AN25: =-('Balance Sheet'!AN54+'Balance Sheet'!AN61) -> -3195.9331 | AO25: =-('Balance Sheet'!AO54+'Balance Sheet'!AO61) -> -3598.0478 | AU25: 0
A26: Purchase of intangible assets | B26: -41 | C26: =D26-B26 -> -145 | D26: -186 | E26: -62 | F26: =AE26-E26 -> -77 | G26: -181 | H26: =AF26-G26 -> -92 | I26: -68 | J26: =AG26-I26 -> -152 | K26: -90 | L26: =AH26-K26 -> -153 | M26: -81 | N26: =AI26-M26 -> -200 | O26: =-'Balance Sheet'!O64 -> -154.32843 | P26: =AJ26-O26 -> -198.85332 | Q26: =-'Balance Sheet'!Q64 -> -163.86674 | R26: =AK26-Q26 -> -223.30016 | S26: =-'Balance Sheet'!S64 -> -176.78547 | T26: =AL26-S26 -> -250.98108 | U26: =-'Balance Sheet'!U64 -> -193.30782 | V26: =AM26-U26 -> -282.55609 | W26: =-'Balance Sheet'!W64 -> -213.84123 | X26: =AN26-W26 -> -318.81428 | Y26: =-'Balance Sheet'!Y64 -> -238.97321 | Z26: =AO26-Y26 -> -360.70143 | AE26: -139 | AF26: -273 | AG26: -220 | AH26: -243 | AI26: -281 | AJ26: =-'Balance Sheet'!AJ64 -> -353.18175 | AK26: =-'Balance Sheet'!AK64 -> -387.16689 | AL26: =-'Balance Sheet'!AL64 -> -427.76655 | AM26: =-'Balance Sheet'!AM64 -> -475.86391 | AN26: =-'Balance Sheet'!AN64 -> -532.65551 | AO26: =-'Balance Sheet'!AO64 -> -599.67464 | AU26: 0
A27: Loans issued to customers and other investments | B27: -121 | C27: =D27-B27 -> -128 | D27: -249 | E27: -68 | F27: =AE27-E27 -> -109 | G27: -70 | H27: =AF27-G27 -> -126 | I27: -89 | J27: =AG27-I27 -> -130 | K27: -139 | L27: =AH27-K27 -> -105 | M27: -107 | N27: =AI27-M27 -> -114 | P27: =AJ27-O27 -> 0 | R27: =AK27-Q27 -> 0 | T27: =AL27-S27 -> 0 | V27: =AM27-U27 -> 0 | X27: =AN27-W27 -> 0 | Z27: =AO27-Y27 -> 0 | AE27: -177 | AF27: -196 | AG27: -219 | AH27: -244 | AI27: -221 | AJ27: ='Balance Sheet'!AI6-'Balance Sheet'!AJ6+'Balance Sheet'!AI7-'Balance Sheet'!AJ7+'Balance Sheet'!AI8-'Balance Sheet'!AJ8+'Balance Sheet'!AI9-'Balance Sheet'!AJ9+'Balance Sheet'!AI10-'Balance Sheet'!AJ10 -> 0 | AK27: ='Balance Sheet'!AJ6-'Balance Sheet'!AK6+'Balance Sheet'!AJ7-'Balance Sheet'!AK7+'Balance Sheet'!AJ8-'Balance Sheet'!AK8+'Balance Sheet'!AJ9-'Balance Sheet'!AK9+'Balance Sheet'!AJ10-'Balance Sheet'!AK10 -> 0 | AL27: ='Balance Sheet'!AK6-'Balance Sheet'!AL6+'Balance Sheet'!AK7-'Balance Sheet'!AL7+'Balance Sheet'!AK8-'Balance Sheet'!AL8+'Balance Sheet'!AK9-'Balance Sheet'!AL9+'Balance Sheet'!AK10-'Balance Sheet'!AL10 -> 0 | AM27: ='Balance Sheet'!AL6-'Balance Sheet'!AM6+'Balance Sheet'!AL7-'Balance Sheet'!AM7+'Balance Sheet'!AL8-'Balance Sheet'!AM8+'Balance Sheet'!AL9-'Balance Sheet'!AM9+'Balance Sheet'!AL10-'Balance Sheet'!AM10 -> 0 | AN27: ='Balance Sheet'!AM6-'Balance Sheet'!AN6+'Balance Sheet'!AM7-'Balance Sheet'!AN7+'Balance Sheet'!AM8-'Balance Sheet'!AN8+'Balance Sheet'!AM9-'Balance Sheet'!AN9+'Balance Sheet'!AM10-'Balance Sheet'!AN10 -> 0 | AO27: ='Balance Sheet'!AN6-'Balance Sheet'!AO6+'Balance Sheet'!AN7-'Balance Sheet'!AO7+'Balance Sheet'!AN8-'Balance Sheet'!AO8+'Balance Sheet'!AN9-'Balance Sheet'!AO9+'Balance Sheet'!AN10-'Balance Sheet'!AO10 -> 0 | AU27: 0
A28: Repayment on loans to customers and other investments | B28: 40 | C28: =D28-B28 -> 24 | D28: 64 | E28: 22 | F28: =AE28-E28 -> 22 | G28: 13 | H28: =AF28-G28 -> 27 | I28: 17 | J28: =AG28-I28 -> 14 | K28: 24 | L28: =AH28-K28 -> 72 | M28: 70 | N28: =AI28-M28 -> 19 | P28: =AJ28-O28 -> 0 | R28: =AK28-Q28 -> 0 | T28: =AL28-S28 -> 0 | V28: =AM28-U28 -> 0 | X28: =AN28-W28 -> 0 | Z28: =AO28-Y28 -> 0 | AE28: 44 | AF28: 40 | AG28: 31 | AH28: 96 | AI28: 89
A29: Cash flow (used in)/from operational investing activities | B29: =SUM(B24:B28) -> -1104 | C29: =SUM(C24:C28) -> -1005 | D29: =SUM(D24:D28) -> -2109 | E29: =SUM(E24:E28) -> -1144 | F29: =SUM(F24:F28) -> -479 | G29: =SUM(G24:G28) -> -931 | H29: =SUM(H24:H28) -> -736 | I29: =SUM(I24:I28) -> -1047 | ... Z29: =SUM(Z24:Z28) -> -2524.91 | AE29: =SUM(AE24:AE28) -> -1623 | AF29: =SUM(AF24:AF28) -> -1667 | AG29: =SUM(AG24:AG28) -> -2087 | AH29: =SUM(AH24:AH28) -> -2671 | AI29: =SUM(AI24:AI28) -> -2445 | AJ29: =SUM(AJ24:AJ28) -> -2472.2723 | AK29: =SUM(AK24:AK28) -> -2710.1682 | AL29: =SUM(AL24:AL28) -> -2994.3659 | ... AO29: =SUM(AO24:AO28) -> -4197.7225
A31: Acquisition of subsidiaries, net of cash acquired | B31: -169 | C31: =D31-B31 -> -14 | D31: -183 | E31: 0 | F31: =AE31-E31 -> -26 | G31: -1 | H31: =AF31-G31 -> 55 | I31: -7 | J31: =AG31-I31 -> -164 | K31: -821 | L31: =AH31-K31 -> 15 | M31: 0 | N31: =AI31-M31 -> -4 | P31: =AJ31-O31 -> 0 | R31: =AK31-Q31 -> 0 | T31: =AL31-S31 -> 0 | V31: =AM31-U31 -> 0 | X31: =AN31-W31 -> 0 | Z31: =AO31-Y31 -> 0 | AE31: -26 | AF31: 54 | AG31: -171 | AH31: -806 | AI31: -4
A32: Acquisition of/additions to associates, joint ventures and other investments | B32: -2872 | C32: =D32-B32 -> -3 | D32: -2875 | E32: -10 | F32: =AE32-E32 -> 1 | G32: -662 | H32: =AF32-G32 -> -16 | I32: -37 | J32: =AG32-I32 -> -8 | K32: -404 | L32: =AH32-K32 -> -5 | M32: -24 | N32: =AI32-M32 -> -20 | P32: =AJ32-O32 -> 0 | R32: =AK32-Q32 -> 0 | T32: =AL32-S32 -> 0 | V32: =AM32-U32 -> 0 | X32: =AN32-W32 -> 0 | Z32: =AO32-Y32 -> 0 | AE32: -9 | AF32: -678 | AG32: -45 | AH32: -409 | AI32: -44
A33: Disposal of subsidiaries, net of cash disposed of | B33: 279 | C33: =D33-B33 -> -35 | D33: 244 | E33: 0 | F33: =AE33-E33 -> -29 | G33: -4 | H33: =AF33-G33 -> 7 | I33: 0 | J33: =AG33-I33 -> 9 | K33: -1 | L33: =AH33-K33 -> 258 | M33: 15 | N33: =AI33-M33 -> -1 | P33: =AJ33-O33 -> 0 | R33: =AK33-Q33 -> 0 | T33: =AL33-S33 -> 0 | V33: =AM33-U33 -> 0 | X33: =AN33-W33 -> 0 | Z33: =AO33-Y33 -> 0 | AE33: -29 | AF33: 3 | AG33: 9 | AH33: 257 | AI33: 14 | AU33: 0
A34: Disposal of associates, joint ventures and other investments | B34: 0 | C34: =D34-B34 -> 50 | D34: 50 | E34: 65 | F34: =AE34-E34 -> 184 | G34: 8 | H34: =AF34-G34 -> 3 | I34: 0 | J34: =AG34-I34 -> 8 | K34: 46 | L34: =AH34-K34 -> 7 | M34: 32 | N34: =AI34-M34 -> 12 | P34: =AJ34-O34 -> 0 | R34: =AK34-Q34 -> 0 | T34: =AL34-S34 -> 0 | V34: =AM34-U34 -> 0 | X34: =AN34-W34 -> 0 | Z34: =AO34-Y34 -> 0 | AE34: 249 | AF34: 11 | AG34: 8 | AH34: 53 | AI34: 44 | AU34: 0
A35: Cash flow (used in)/from operational investing activities | B35: =SUM(B31:B34) -> -2762 | C35: =SUM(C31:C34) -> -2 | D35: =SUM(D31:D34) -> -2764 | E35: =SUM(E31:E34) -> 55 | F35: =SUM(F31:F34) -> 130 | G35: =SUM(G31:G34) -> -659 | H35: =SUM(H31:H34) -> 49 | I35: =SUM(I31:I34) -> -44 | ... Z35: =SUM(Z31:Z34) -> 0 | AE35: =SUM(AE31:AE34) -> 185 | AF35: =SUM(AF31:AF34) -> -610 | AG35: =SUM(AG31:AG34) -> -199 | AH35: =SUM(AH31:AH34) -> -905 | AI35: =SUM(AI31:AI34) -> 10 | AJ35: =SUM(AJ31:AJ34) -> 0 | AK35: =SUM(AK31:AK34) -> 0 | AL35: =SUM(AL31:AL34) -> 0 | ... AO35: =SUM(AO31:AO34) -> 0 | AU35: 0
A36: Cash flow (used in)/from investing activities | B36: =B29+B35 -> -3866 | C36: =C29+C35 -> -1007 | D36: =D29+D35 -> -4873 | E36: =E29+E35 -> -1089 | F36: =F29+F35 -> -349 | G36: =G29+G35 -> -1590 | H36: =H29+H35 -> -687 | I36: =I29+I35 -> -1091 | ... Z36: =Z29+Z35 -> -2524.91 | AE36: =AE29+AE35 -> -1438 | AF36: =AF29+AF35 -> -2277 | AG36: =AG29+AG35 -> -2286 | AH36: =AH29+AH35 -> -3576 | AI36: =AI29+AI35 -> -2435 | AJ36: =AJ29+AJ35 -> -2472.2723 | AK36: =AK29+AK35 -> -2710.1682 | AL36: =AL29+AL35 -> -2994.3659 | ... AO36: =AO29+AO35 -> -4197.7225 | AU36: 0
A38: Proceeds from borrowings | B38: 537 | C38: =D38-B38 -> 1751 | D38: 2288 | E38: 5872 | F38: =AE38-E38 -> 165 | G38: 721 | H38: =AF38-G38 -> 850 | I38: 301 | J38: =AG38-I38 -> 343 | K38: 5492 | L38: =AH38-K38 -> 1259 | M38: 1973 | N38: =AI38-M38 -> 1103 | O38: =-('Balance Sheet'!N31-'Balance Sheet'!O31) -> 250 | P38: =AJ38-O38 -> 250 | Q38: ='Balance Sheet'!Q82-'Balance Sheet'!P82 -> 250 | R38: =AK38-Q38 -> 250 | S38: ='Balance Sheet'!S82-'Balance Sheet'!R82 -> 250 | T38: =AL38-S38 -> 250 | U38: ='Balance Sheet'!U82-'Balance Sheet'!T82 -> 250 | V38: =AM38-U38 -> 250 | W38: ='Balance Sheet'!W82-'Balance Sheet'!V82 -> 250 | X38: =AN38-W38 -> 250 | Y38: ='Balance Sheet'!Y82-'Balance Sheet'!X82 -> 250 | Z38: =AO38-Y38 -> 250 | AE38: 6037 | AF38: 1571 | AG38: 644 | AH38: 6751 | AI38: 3076 | AJ38: ='Balance Sheet'!AJ82-'Balance Sheet'!AI82 -> 500 | AK38: ='Balance Sheet'!AK82-'Balance Sheet'!AJ82 -> 500 | AL38: ='Balance Sheet'!AL82-'Balance Sheet'!AK82 -> 500 | AM38: ='Balance Sheet'!AM82-'Balance Sheet'!AL82 -> 500 | AN38: ='Balance Sheet'!AN82-'Balance Sheet'!AM82 -> 500 | AO38: ='Balance Sheet'!AO82-'Balance Sheet'!AN82 -> 500
A39: Repayment of borrowings | B39: -881 | C39: =D39-B39 -> -1269 | D39: -2150 | E39: -1474 | F39: =AE39-E39 -> -2240 | G39: -2275 | H39: =AF39-G39 -> -1087 | I39: -986 | J39: =AG39-I39 -> -948 | K39: -2041 | L39: =AH39-K39 -> -2573 | M39: -1804 | N39: =AI39-M39 -> -2287 | P39: =AJ39-O39 -> 0 | R39: =AK39-Q39 -> 0 | T39: =AL39-S39 -> 0 | V39: =AM39-U39 -> 0 | X39: =AN39-W39 -> 0 | Z39: =AO39-Y39 -> 0 | AE39: -3714 | AF39: -3362 | AG39: -1934 | AH39: -4614 | AI39: -4091 | AU39: 0
A40: Payment of lease commitments | B40: -114 | C40: =D40-B40 -> -145 | D40: -259 | E40: -137 | F40: =AE40-E40 -> -144 | G40: -150 | H40: =AF40-G40 -> -148 | I40: -148 | J40: =AG40-I40 -> -156 | K40: -220 | L40: =AH40-K40 -> -170 | M40: -184 | N40: =AI40-M40 -> -171 | P40: =AJ40-O40 -> 0 | R40: =AK40-Q40 -> 0 | T40: =AL40-S40 -> 0 | V40: =AM40-U40 -> 0 | X40: =AN40-W40 -> 0 | Z40: =AO40-Y40 -> 0 | AE40: -281 | AF40: -298 | AG40: -304 | AH40: -390 | AI40: -355
A41: Dividends paid | B41: -724 | C41: =D41-B41 -> -499 | D41: -1223 | E41: -709 | F41: =AE41-E41 -> -102 | G41: -579 | H41: =AF41-G41 -> -217 | I41: -652 | J41: =AG41-I41 -> -447 | K41: -840 | L41: =AH41-K41 -> -495 | M41: -638 | N41: =AI41-M41 -> -561 | P41: =AJ41-O41 -> 0 | R41: =AK41-Q41 -> 0 | T41: =AL41-S41 -> 0 | V41: =AM41-U41 -> 0 | X41: =AN41-W41 -> 0 | Z41: =AO41-Y41 -> 0 | AE41: -811 | AF41: -796 | AG41: -1099 | AH41: -1335 | AI41: -1199 | AU41: 0
A42: Purchase own shares and shares issued by Heineken N.V. | B42: 418 | C42: =D42-B42 -> 10 | D42: 428 | E42: -4 | F42: =AE42-E42 -> 15 | G42: 26 | H42: =AF42-G42 -> -14 | I42: -23 | J42: =AG42-I42 -> -20 | K42: -928 | L42: =AH42-K42 -> -14 | M42: -36 | N42: =AI42-M42 -> 31 | P42: =AJ42-O42 -> 0 | R42: =AK42-Q42 -> 0 | T42: =AL42-S42 -> 0 | V42: =AM42-U42 -> 0 | X42: =AN42-W42 -> 0 | Z42: =AO42-Y42 -> 0 | AE42: 11 | AF42: 12 | AG42: -43 | AH42: -942 | AI42: -5 | AU42: 0
A43: Acquisition of non-controlling interests | B43: -103 | C43: =D43-B43 -> 0 | D43: -103 | E43: -3 | F43: =AE43-E43 -> -1 | G43: -10 | H43: =AF43-G43 -> 0 | I43: -8 | J43: =AG43-I43 -> -383 | K43: -288 | L43: =AH43-K43 -> 2 | M43: 0 | N43: =AI43-M43 -> 0 | P43: =AJ43-O43 -> 0 | R43: =AK43-Q43 -> 0 | T43: =AL43-S43 -> 0 | V43: =AM43-U43 -> 0 | X43: =AN43-W43 -> 0 | Z43: =AO43-Y43 -> 0 | AE43: -4 | AF43: -10 | AG43: -391 | AH43: -286 | AI43: 0 | AU43: 0
A44: Other | B44: 0 | C44: =D44-B44 -> 3 | D44: 3 | E44: 0 | F44: =AE44-E44 -> 0 | G44: 0 | H44: =AF44-G44 -> 0 | I44: 0 | J44: =AG44-I44 -> 0 | K44: 0 | L44: =AH44-K44 -> 0 | M44: 0 | N44: =AI44-M44 -> 0 | P44: =AJ44-O44 -> 0 | R44: =AK44-Q44 -> 0 | T44: =AL44-S44 -> 0 | V44: =AM44-U44 -> 0 | X44: =AN44-W44 -> 0 | Z44: =AO44-Y44 -> 0 | AE44: 0 | AF44: 0 | AG44: 0 | AH44: 0 | AI44: 0 | AJ44: ='Balance Sheet'!AJ32-'Balance Sheet'!AI32+'Balance Sheet'!AJ33-'Balance Sheet'!AI33+'Balance Sheet'!AJ34-'Balance Sheet'!AI34+'Balance Sheet'!AJ35-'Balance Sheet'!AI35++'Balance Sheet'!AJ26-'Balance Sheet'!AI26 -> 0 | AK44: ='Balance Sheet'!AK32-'Balance Sheet'!AJ32+'Balance Sheet'!AK33-'Balance Sheet'!AJ33+'Balance Sheet'!AK34-'Balance Sheet'!AJ34+'Balance Sheet'!AK35-'Balance Sheet'!AJ35++'Balance Sheet'!AK26-'Balance Sheet'!AJ26 -> 0 | AL44: ='Balance Sheet'!AL32-'Balance Sheet'!AK32+'Balance Sheet'!AL33-'Balance Sheet'!AK33+'Balance Sheet'!AL34-'Balance Sheet'!AK34+'Balance Sheet'!AL35-'Balance Sheet'!AK35++'Balance Sheet'!AL26-'Balance Sheet'!AK26 -> 0 | AM44: ='Balance Sheet'!AM32-'Balance Sheet'!AL32+'Balance Sheet'!AM33-'Balance Sheet'!AL33+'Balance Sheet'!AM34-'Balance Sheet'!AL34+'Balance Sheet'!AM35-'Balance Sheet'!AL35++'Balance Sheet'!AM26-'Balance Sheet'!AL26 -> 0 | AN44: ='Balance Sheet'!AN32-'Balance Sheet'!AM32+'Balance Sheet'!AN33-'Balance Sheet'!AM33+'Balance Sheet'!AN34-'Balance Sheet'!AM34+'Balance Sheet'!AN35-'Balance Sheet'!AM35++'Balance Sheet'!AN26-'Balance Sheet'!AM26 -> 0 | AO44: ='Balance Sheet'!AO32-'Balance Sheet'!AN32+'Balance Sheet'!AO33-'Balance Sheet'!AN33+'Balance Sheet'!AO34-'Balance Sheet'!AN34+'Balance Sheet'!AO35-'Balance Sheet'!AN35++'Balance Sheet'!AO26-'Balance Sheet'!AN26 -> 0 | AU44: 0
A45: Cash flow (used in)/from financing activities | B45: =SUM(B38:B44) -> -867 | C45: =SUM(C38:C44) -> -149 | D45: =SUM(D38:D44) -> -1016 | E45: =SUM(E38:E44) -> 3545 | F45: =SUM(F38:F44) -> -2307 | G45: =SUM(G38:G44) -> -2267 | H45: =SUM(H38:H44) -> -616 | I45: =SUM(I38:I44) -> -1516 | ... Z45: =SUM(Z38:Z44) -> 250 | AE45: =SUM(AE38:AE44) -> 1238 | AF45: =SUM(AF38:AF44) -> -2883 | AG45: =SUM(AG38:AG44) -> -3127 | AH45: =SUM(AH38:AH44) -> -816 | AI45: =SUM(AI38:AI44) -> -2574 | AJ45: =SUM(AJ38:AJ44) -> 500 | AK45: =SUM(AK38:AK44) -> 500 | AL45: =SUM(AL38:AL44) -> 500 | ... AO45: =SUM(AO38:AO44) -> 500 | AU45: 0
A47: Net Cash flow | B47: =+B22+B36+B45 -> -3051 | C47: =+C22+C36+C45 -> 1499 | D47: =+D22+D36+D45 -> -1552 | E47: =+E22+E36+E45 -> 2791 | F47: =+F22+F36+F45 -> 145 | G47: =+G22+G36+G45 -> -2276 | H47: =+H22+H36+H45 -> 1297 | I47: =+I22+I36+I45 -> -438 | ... Z47: =+Z22+Z36+Z45 -> 2202.0557 | AE47: =+AE22+AE36+AE45 -> 2936 | AF47: =+AF22+AF36+AF45 -> -979 | AG47: =+AG22+AG36+AG45 -> -917 | AH47: =+AH22+AH36+AH45 -> 38 | AI47: =+AI22+AI36+AI45 -> 494 | AJ47: =+AJ22+AJ36+AJ45 -> 3087.8665 | AK47: =+AK22+AK36+AK45 -> 3408.9761 | AL47: =+AL22+AL36+AL45 -> 3685.5025 | ... AO47: =+AO22+AO36+AO45 -> 4827.6631
A48: Beginning Cash | B48: 2249 | C48: =B50 -> -796 | D48: 2248 | E48: 687 | F48: =E50 -> 3493 | G48: =AE50 -> 3519 | H48: =G50 -> 1253 | I48: =AF50 -> 2556 | J48: =I50 -> 2146 | K48: 1618 | L48: =K50 -> 975 | M48: =AH50 -> 1425 | N48: ='Balance Sheet'!M17 -> 2277 | O48: =N50 -> 2339.2188 | P48: =O50 -> 4152.4843 | Q48: =P50 -> 5427.0853 | R48: =Q50 -> 7336.2563 | S48: =R50 -> 8836.0614 | T48: =S50 -> 10853.689 | U48: =T50 -> 12521.564 | V48: =U50 -> 14692.051 | ... Z48: =Y50 -> 23541.522 | AE48: =D50 -> 687 | AF48: =AE50 -> 3519 | AG48: 2556 | AH48: =AG50 -> 1618 | AI48: =AH50 -> 1425 | AJ48: ='Balance Sheet'!AI17 -> 2350 | AK48: ='Balance Sheet'!AJ17 -> 5437.8665 | AL48: ='Balance Sheet'!AK17 -> 8846.8426 | AM48: ='Balance Sheet'!AL17 -> 12532.345 | AN48: ='Balance Sheet'!AM17 -> 16537.852 | AO48: ='Balance Sheet'!AN17 -> 20926.696
A49: Fx | B49: 6 | C49: =D49-B49 -> -15 | D49: -9 | E49: 15 | F49: =AE49-E49 -> -119 | G49: 10 | H49: =AF49-G49 -> 6 | I49: 28 | J49: =AG49-I49 -> -49 | K49: -171 | L49: =AH49-K49 -> -60 | M49: -89 | N49: =AI49-M49 -> -77 | P49: =AJ49-O49 -> 0 | R49: =AK49-Q49 -> 0 | T49: =AL49-S49 -> 0 | V49: =AM49-U49 -> 0 | X49: =AN49-W49 -> 0 | Z49: =AO49-Y49 -> 0 | AE49: -104 | AF49: 16 | AG49: -21 | AH49: -231 | AI49: -166
A50: End Cash | B50: =+B47+B48+B49 -> -796 | C50: =+C47+C48+C49-1 -> 687 | D50: =+D47+D48+D49 -> 687 | E50: =+E47+E48+E49 -> 3493 | F50: =+F47+F48+F49 -> 3519 | G50: =+G47+G48+G49 -> 1253 | H50: =+H47+H48+H49 -> 2556 | I50: =+I47+I48+I49 -> 2146 | J50: =+J47+J48+J49 -> 1618 | K50: =+K47+K48+K49 -> 975 | ... Z50: =+Z47+Z48+Z49 -> 25743.578 | AE50: =+AE47+AE48+AE49 -> 3519 | AF50: =+AF47+AF48+AF49 -> 2556 | AG50: =+AG47+AG48+AG49 -> 1618 | AH50: =+AH47+AH48+AH49 -> 1425 | AI50: =+AI47+AI48+AI49 -> 1753 | AJ50: =+AJ47+AJ48+AJ49 -> 5437.8665 | AK50: =+AK47+AK48+AK49 -> 8846.8426 | AL50: =+AL47+AL48+AL49 -> 12532.345 | ... AO50: =+AO47+AO48+AO49 -> 25754.359
AJ52: =+AJ50-P50 -> 10.78118

Sheet Ratio Analysis
A1: Ratios | I1: ='Cash Flow Statement'!I1 -> H1'22 | J1: ='Cash Flow Statement'!J1 -> H2'22 | K1: ='Cash Flow Statement'!K1 -> H1'23 | L1: ='Cash Flow Statement'!L1 -> H2'23 | M1: ='Cash Flow Statement'!M1 -> H1'24 | N1: ='Cash Flow Statement'!N1 -> H2'24 | O1: ='Cash Flow Statement'!O1 -> H1'25 | P1: ='Cash Flow Statement'!P1 -> H2'25 | ... Z1: ='Cash Flow Statement'!Z1 -> H2'30 | AE1: ='Cash Flow Statement'!AE1 -> FY'20 | AF1: ='Cash Flow Statement'!AF1 -> FY'21 | AG1: ='Cash Flow Statement'!AG1 -> FY'22 | AH1: ='Cash Flow Statement'!AH1 -> FY'23 | AI1: ='Cash Flow Statement'!AI1 -> FY'24 | AJ1: ='Cash Flow Statement'!AJ1 -> FY'25 | AK1: ='Cash Flow Statement'!AK1 -> FY'26 | AL1: ='Cash Flow Statement'!AL1 -> FY'27 | ... AO1: ='Cash Flow Statement'!AO1 -> FY'30 | AQ1: Sparklines | AS1: Notes
A3: Actvity Ratios (Utilising resources)
A5: Receivables Turnover | H5: Sales/Average Receivables
A6: DSO | H6: Days/RT | I6: ='Balance Sheet'!I104 -> 67.207638 | J6: ='Balance Sheet'!J104 -> 54.280393 | K6: ='Balance Sheet'!K104 -> 71.811312 | L6: ='Balance Sheet'!L104 -> 57.833533 | M6: ='Balance Sheet'!M104 -> 66.476997 | N6: ='Balance Sheet'!N104 -> 59.988431 | O6: ='Balance Sheet'!O104 -> 59.988431 | P6: ='Balance Sheet'!P104 -> 53.581528 | ... Z6: ='Balance Sheet'!Z104 -> 50.155377 | AE6: ='Balance Sheet'!AE104 -> 0 | AF6: ='Balance Sheet'!AF104 -> 0 | AG6: ='Balance Sheet'!AG104 -> 57.586093 | AH6: ='Balance Sheet'!AH104 -> 60.33644 | AI6: ='Balance Sheet'!AI104 -> 60.33644 | AJ6: ='Balance Sheet'!AJ104 -> 60.33644 | AK6: ='Balance Sheet'!AK104 -> 60.33644 | AL6: ='Balance Sheet'!AL104 -> 60.33644 | ... AO6: ='Balance Sheet'!AO104 -> 60.33644
A7: Inventory Turnover | H7: COGS/Average Inventory
A8: DIO | H8: Days/IT | I8: ='Balance Sheet'!I103 -> 42.535966 | J8: ='Balance Sheet'!J103 -> 38.934292 | K8: ='Balance Sheet'!K103 -> 54.910837 | L8: ='Balance Sheet'!L103 -> 42.876784 | M8: ='Balance Sheet'!M103 -> 47.638761 | N8: ='Balance Sheet'!N103 -> 44.474387 | O8: ='Balance Sheet'!O103 -> 44.474387 | P8: ='Balance Sheet'!P103 -> 39.72442 | ... Z8: ='Balance Sheet'!Z103 -> 37.184331 | AE8: ='Balance Sheet'!AE103 -> 0 | AF8: ='Balance Sheet'!AF103 -> 0 | AG8: ='Balance Sheet'!AG103 -> 41.305408 | AH8: ='Balance Sheet'!AH103 -> 44.732396 | AI8: ='Balance Sheet'!AI103 -> 44.732396 | AJ8: ='Balance Sheet'!AJ103 -> 44.732396 | AK8: ='Balance Sheet'!AK103 -> 44.732396 | AL8: ='Balance Sheet'!AL103 -> 44.732396 | ... AO8: ='Balance Sheet'!AO103 -> 44.732396
A9: Payables Turnover | H9: COGS/Average Payables
A10: DPO | H10: Days/PT | I10: ='Balance Sheet'!I105 -> 123.03356 | J10: ='Balance Sheet'!J105 -> 111.20832 | K10: ='Balance Sheet'!K105 -> 122.43735 | L10: ='Balance Sheet'!L105 -> 108.68418 | M10: ='Balance Sheet'!M105 -> 116.0539 | N10: ='Balance Sheet'!N105 -> 112.73379 | O10: ='Balance Sheet'!O105 -> 112.73379 | P10: ='Balance Sheet'!P105 -> 100.69356 | ... Z10: ='Balance Sheet'!Z105 -> 94.254935 | AE10: ='Balance Sheet'!AE105 -> 0 | AF10: ='Balance Sheet'!AF105 -> 0 | AG10: ='Balance Sheet'!AG105 -> 117.98095 | AH10: ='Balance Sheet'!AH105 -> 113.38779 | AI10: ='Balance Sheet'!AI105 -> 113.38779 | AJ10: ='Balance Sheet'!AJ105 -> 113.38779 | AK10: ='Balance Sheet'!AK105 -> 113.38779 | AL10: ='Balance Sheet'!AL105 -> 113.38779 | ... AO10: ='Balance Sheet'!AO105 -> 113.38779
A11: Cash Conversion Cycle | H11: DSO+DIO-DPO | I11: =I6+I8-I10 -> -13.289952 | J11: =J6+J8-J10 -> -17.993633 | K11: =K6+K8-K10 -> 4.2848045 | L11: =L6+L8-L10 -> -7.9738603 | M11: =M6+M8-M10 -> -1.9381409 | N11: =N6+N8-N10 -> -8.2709691 | O11: =O6+O8-O10 -> -8.2709691 | P11: =P6+P8-P10 -> -7.3876105 | ... Z11: =Z6+Z8-Z10 -> -6.9152264 | AE11: =AE6+AE8-AE10 -> 0 | AF11: =AF6+AF8-AF10 -> 0 | AG11: =AG6+AG8-AG10 -> -19.089453 | AH11: =AH6+AH8-AH10 -> -8.3189513 | AI11: =AI6+AI8-AI10 -> -8.3189513 | AJ11: =AJ6+AJ8-AJ10 -> -8.3189513 | AK11: =AK6+AK8-AK10 -> -8.3189513 | AL11: =AL6+AL8-AL10 -> -8.3189513 | ... AO11: =AO6+AO8-AO10 -> -8.3189513 | AS11: Negative cash conversion cycle is good for the business, shows less reliance on own money
A12: Fixed Assets Turnover | H12: Sales/Average net fixed assets | I12: ='Profit and Loss Statement '!I5/AVERAGE('Balance Sheet'!H11:I11) -> 0.33773292 | J12: ='Profit and Loss Statement '!J5/AVERAGE('Balance Sheet'!I11:J11) -> 0.37167429 | K12: ='Profit and Loss Statement '!K5/AVERAGE('Balance Sheet'!J11:K11) -> 0.33990171 | L12: ='Profit and Loss Statement '!L5/AVERAGE('Balance Sheet'!K11:L11) -> 0.36068 | M12: ='Profit and Loss Statement '!M5/AVERAGE('Balance Sheet'!L11:M11) -> 0.34295762 | N12: ='Profit and Loss Statement '!N5/AVERAGE('Balance Sheet'!M11:N11) -> 0.35052823 | O12: ='Profit and Loss Statement '!O5/AVERAGE('Balance Sheet'!N11:O11) -> 0.36254667 | P12: ='Profit and Loss Statement '!P5/AVERAGE('Balance Sheet'!O11:P11) -> 0.47071573 | ... Z12: ='Profit and Loss Statement '!Z5/AVERAGE('Balance Sheet'!Y11:Z11) -> 0.89010984 | AE12: ='Profit and Loss Statement '!AE5/AVERAGE('Balance Sheet'!AD11:AE11) -> 0 | AF12: ='Profit and Loss Statement '!AF5/AVERAGE('Balance Sheet'!AE11:AF11) -> 0.60208002 | AG12: ='Profit and Loss Statement '!AG5/AVERAGE('Balance Sheet'!AF11:AG11) -> 0.71207369 | AH12: ='Profit and Loss Statement '!AH5/AVERAGE('Balance Sheet'!AG11:AH11) -> 0.71318339 | AI12: ='Profit and Loss Statement '!AI5/AVERAGE('Balance Sheet'!AH11:AI11) -> 0.68848409 | AJ12: ='Profit and Loss Statement '!AJ5/AVERAGE('Balance Sheet'!AI11:AJ11) -> 0.83001975 | AK12: ='Profit and Loss Statement '!AK5/AVERAGE('Balance Sheet'!AJ11:AK11) -> 0.92308453 | AL12: ='Profit and Loss Statement '!AL5/AVERAGE('Balance Sheet'!AK11:AL11) -> 1.0326233 | ... AO12: ='Profit and Loss Statement '!AO5/AVERAGE('Balance Sheet'!AN11:AO11) -> 1.4711732 | AS12: Better asset utlization
A13: Working Capital Turnover | H13: Revenue/Average working capital | I13: ='Profit and Loss Statement '!I5/('Balance Sheet'!I20-'Balance Sheet'!I45) -> -5.279953 | J13: ='Profit and Loss Statement '!J5/('Balance Sheet'!J20-'Balance Sheet'!J45) -> -4.7981102 | K13: ='Profit and Loss Statement '!K5/('Balance Sheet'!K20-'Balance Sheet'!K45) -> -3.7212401 | L13: ='Profit and Loss Statement '!L5/('Balance Sheet'!L20-'Balance Sheet'!L45) -> -4.6228838 | M13: ='Profit and Loss Statement '!M5/('Balance Sheet'!M20-'Balance Sheet'!M45) -> -4.3345029 | N13: ='Profit and Loss Statement '!N5/('Balance Sheet'!N20-'Balance Sheet'!N45) -> -4.4914645 | O13: ='Profit and Loss Statement '!O5/('Balance Sheet'!O20-'Balance Sheet'!O45) -> -11.030102 | P13: ='Profit and Loss Statement '!P5/('Balance Sheet'!P20-'Balance Sheet'!P45) -> -86.423069 | ... Z13: ='Profit and Loss Statement '!Z5/('Balance Sheet'!Z20-'Balance Sheet'!Z45) -> 1.8474202 | AE13: ='Profit and Loss Statement '!AE5/('Balance Sheet'!AE20-'Balance Sheet'!AE45) -> 0 | AF13: ='Profit and Loss Statement '!AF5/('Balance Sheet'!AF20-'Balance Sheet'!AF45) -> -8.7205882 | AG13: ='Profit and Loss Statement '!AG5/('Balance Sheet'!AG20-'Balance Sheet'!AG45) -> -9.0453543 | AH13: ='Profit and Loss Statement '!AH5/('Balance Sheet'!AH20-'Balance Sheet'!AH45) -> -8.86223 | AI13: ='Profit and Loss Statement '!AI5/('Balance Sheet'!AI20-'Balance Sheet'!AI45) -> -8.9311171 | AJ13: ='Profit and Loss Statement '!AJ5/('Balance Sheet'!AJ20-'Balance Sheet'!AJ45) -> -153.4953 | AK13: ='Profit and Loss Statement '!AK5/('Balance Sheet'!AK20-'Balance Sheet'!AK45) -> 12.483514 | AL13: ='Profit and Loss Statement '!AL5/('Balance Sheet'!AL20-'Balance Sheet'!AL45) -> 6.3899213 | ... AO13: ='Profit and Loss Statement '!AO5/('Balance Sheet'!AO20-'Balance Sheet'!AO45) -> 3.0713797 | AS13: Indicates improving efficiency
A14: Total Assets Turnover | H14: Revenue/Average total assets | I14: =+'Profit and Loss Statement '!I5/AVERAGE('Balance Sheet'!H22:I22) -> 0.26650461 | J14: =+'Profit and Loss Statement '!J5/AVERAGE('Balance Sheet'!I22:J22) -> 0.29085008 | K14: =+'Profit and Loss Statement '!K5/AVERAGE('Balance Sheet'!J22:K22) -> 0.26571776 | L14: =+'Profit and Loss Statement '!L5/AVERAGE('Balance Sheet'!K22:L22) -> 0.28265486 | M14: =+'Profit and Loss Statement '!M5/AVERAGE('Balance Sheet'!L22:M22) -> 0.27022248 | N14: =+'Profit and Loss Statement '!N5/AVERAGE('Balance Sheet'!M22:N22) -> 0.27685832 | O14: =+'Profit and Loss Statement '!O5/AVERAGE('Balance Sheet'!N22:O22) -> 0.28208252 | P14: =+'Profit and Loss Statement '!P5/AVERAGE('Balance Sheet'!O22:P22) -> 0.34926582 | ... Z14: =+'Profit and Loss Statement '!Z5/AVERAGE('Balance Sheet'!Y22:Z22) -> 0.45119677 | AE14: =+'Profit and Loss Statement '!AE5/AVERAGE('Balance Sheet'!AD22:AE22) -> 0 | AF14: =+'Profit and Loss Statement '!AF5/AVERAGE('Balance Sheet'!AE22:AF22) -> 0.47967906 | AG14: =+'Profit and Loss Statement '!AG5/AVERAGE('Balance Sheet'!AF22:AG22) -> 0.56725527 | AH14: =+'Profit and Loss Statement '!AH5/AVERAGE('Balance Sheet'!AG22:AH22) -> 0.56456456 | AI14: =+'Profit and Loss Statement '!AI5/AVERAGE('Balance Sheet'!AH22:AI22) -> 0.54754604 | AJ14: =+'Profit and Loss Statement '!AJ5/AVERAGE('Balance Sheet'!AI22:AJ22) -> 0.63071232 | AK14: =+'Profit and Loss Statement '!AK5/AVERAGE('Balance Sheet'!AJ22:AK22) -> 0.64388392 | AL14: =+'Profit and Loss Statement '!AL5/AVERAGE('Balance Sheet'!AK22:AL22) -> 0.66595914 | ... AO14: =+'Profit and Loss Statement '!AO5/AVERAGE('Balance Sheet'!AN22:AO22) -> 0.74227442 | AS14: High turnover shows better assets utilization
A15: Equity Turnover | H15: Revenue/Average Total Equity | I15: =+'Profit and Loss Statement '!I5/AVERAGE('Balance Sheet'!H29:I29) -> 0.65372309 | J15: =+'Profit and Loss Statement '!J5/AVERAGE('Balance Sheet'!I29:J29) -> 0.70080044 | K15: =+'Profit and Loss Statement '!K5/AVERAGE('Balance Sheet'!J29:K29) -> 0.66043699 | L15: =+'Profit and Loss Statement '!L5/AVERAGE('Balance Sheet'!K29:L29) -> 0.70623384 | M15: =+'Profit and Loss Statement '!M5/AVERAGE('Balance Sheet'!L29:M29) -> 0.66073856 | N15: =+'Profit and Loss Statement '!N5/AVERAGE('Balance Sheet'!M29:N29) -> 0.6742649 | O15: =+'Profit and Loss Statement '!O5/AVERAGE('Balance Sheet'!N29:O29) -> 0.67272467 | P15: =+'Profit and Loss Statement '!P5/AVERAGE('Balance Sheet'!O29:P29) -> 0.83124804 | ... Z15: =+'Profit and Loss Statement '!Z5/AVERAGE('Balance Sheet'!Y29:Z29) -> 0.92092705 | AE15: =+'Profit and Loss Statement '!AE5/AVERAGE('Balance Sheet'!AD29:AE29) -> 0 | AF15: =+'Profit and Loss Statement '!AF5/AVERAGE('Balance Sheet'!AE29:AF29) -> 1.2871641 | AG15: =+'Profit and Loss Statement '!AG5/AVERAGE('Balance Sheet'!AF29:AG29) -> 1.3800577 | AH15: =+'Profit and Loss Statement '!AH5/AVERAGE('Balance Sheet'!AG29:AH29) -> 1.3582053 | AI15: =+'Profit and Loss Statement '!AI5/AVERAGE('Balance Sheet'!AH29:AI29) -> 1.3197761 | AJ15: =+'Profit and Loss Statement '!AJ5/AVERAGE('Balance Sheet'!AI29:AJ29) -> 1.5103914 | AK15: =+'Profit and Loss Statement '!AK5/AVERAGE('Balance Sheet'!AJ29:AK29) -> 1.5185754 | AL15: =+'Profit and Loss Statement '!AL5/AVERAGE('Balance Sheet'!AK29:AL29) -> 1.5310108 | ... AO15: =+'Profit and Loss Statement '!AO5/AVERAGE('Balance Sheet'!AN29:AO29) -> 1.5753631 | AS15: High equity turnover shows the company is generating good results for stakeholders
A18: Liquidity Ratios
A20: Current Ratio | H20: CA/CL | I20: ='Balance Sheet'!I20/'Balance Sheet'!I45 -> 0.82163559 | J20: ='Balance Sheet'!J20/'Balance Sheet'!J45 -> 0.77625088 | K20: ='Balance Sheet'!K20/'Balance Sheet'!K45 -> 0.76694333 | L20: ='Balance Sheet'!L20/'Balance Sheet'!L45 -> 0.76890388 | M20: ='Balance Sheet'!M20/'Balance Sheet'!M45 -> 0.7763244 | N20: ='Balance Sheet'!N20/'Balance Sheet'!N45 -> 0.76548673 | O20: ='Balance Sheet'!O20/'Balance Sheet'!O45 -> 0.90536753 | P20: ='Balance Sheet'!P20/'Balance Sheet'!P45 -> 0.98581743 | ... Z20: ='Balance Sheet'!Z20/'Balance Sheet'!Z45 -> 1.8175795 | AE20: ='Balance Sheet'!AE20/'Balance Sheet'!AE45 -> 0.82995951 | AF20: ='Balance Sheet'!AF20/'Balance Sheet'!AF45 -> 0.79196296 | AG20: ='Balance Sheet'!AG20/'Balance Sheet'!AG45 -> 0.77625088 | AH20: ='Balance Sheet'!AH20/'Balance Sheet'!AH45 -> 0.76890388 | AI20: ='Balance Sheet'!AI20/'Balance Sheet'!AI45 -> 0.76548673 | AJ20: ='Balance Sheet'!AJ20/'Balance Sheet'!AJ45 -> 0.98581743 | AK20: ='Balance Sheet'!AK20/'Balance Sheet'!AK45 -> 1.1794869 | AL20: ='Balance Sheet'!AL20/'Balance Sheet'!AL45 -> 1.3610662 | ... AO20: ='Balance Sheet'!AO20/'Balance Sheet'!AO45 -> 1.8175795 | AS20: Below 1 (0.82 in H1'22, increasing to 1.86 by FY'30), meaning potential liquidity concerns early on but improving over time.
A21: Quick Ratio | H21: Quick Assets/CL | I21: =('Balance Sheet'!I17+'Balance Sheet'!I14)/'Balance Sheet'!I45 -> 0.54857183 | J21: =('Balance Sheet'!J17+'Balance Sheet'!J14)/'Balance Sheet'!J45 -> 0.5141649 | K21: =('Balance Sheet'!K17+'Balance Sheet'!K14)/'Balance Sheet'!K45 -> 0.47071117 | L21: =('Balance Sheet'!L17+'Balance Sheet'!L14)/'Balance Sheet'!L45 -> 0.49888702 | M21: =('Balance Sheet'!M17+'Balance Sheet'!M14)/'Balance Sheet'!M45 -> 0.50111184 | N21: =('Balance Sheet'!N17+'Balance Sheet'!N14)/'Balance Sheet'!N45 -> 0.48728754 | O21: =('Balance Sheet'!O17+'Balance Sheet'!O14)/'Balance Sheet'!O45 -> 0.62468682 | P21: =('Balance Sheet'!P17+'Balance Sheet'!P14)/'Balance Sheet'!P45 -> 0.69504417 | ... Z21: =('Balance Sheet'!Z17+'Balance Sheet'!Z14)/'Balance Sheet'!Z45 -> 1.4935441 | AE21: =('Balance Sheet'!AE17+'Balance Sheet'!AE14)/'Balance Sheet'!AE45 -> 0.62633419 | AF21: =('Balance Sheet'!AF17+'Balance Sheet'!AF14)/'Balance Sheet'!AF45 -> 0.5713577 | AG21: =('Balance Sheet'!AG17+'Balance Sheet'!AG14)/'Balance Sheet'!AG45 -> 0.5141649 | AH21: =('Balance Sheet'!AH17+'Balance Sheet'!AH14)/'Balance Sheet'!AH45 -> 0.49888702 | AI21: =('Balance Sheet'!AI17+'Balance Sheet'!AI14)/'Balance Sheet'!AI45 -> 0.48728754 | AJ21: =('Balance Sheet'!AJ17+'Balance Sheet'!AJ14)/'Balance Sheet'!AJ45 -> 0.69504417 | AK21: =('Balance Sheet'!AK17+'Balance Sheet'!AK14)/'Balance Sheet'!AK45 -> 0.88237556 | AL21: =('Balance Sheet'!AL17+'Balance Sheet'!AL14)/'Balance Sheet'!AL45 -> 1.0573294 | ... AO21: =('Balance Sheet'!AO17+'Balance Sheet'!AO14)/'Balance Sheet'!AO45 -> 1.4935441 | AS21: Good cash balance
A22: Cash ratio | H22: Cash+Marketable sec/CL | I22: ='Balance Sheet'!I17/'Balance Sheet'!I45 -> 0.2017599 | J22: ='Balance Sheet'!J17/'Balance Sheet'!J45 -> 0.19485553 | K22: ='Balance Sheet'!K17/'Balance Sheet'!K45 -> 0.12945602 | L22: ='Balance Sheet'!L17/'Balance Sheet'!L45 -> 0.16033727 | M22: ='Balance Sheet'!M17/'Balance Sheet'!M45 -> 0.14892086 | N22: ='Balance Sheet'!N17/'Balance Sheet'!N45 -> 0.16505127 | O22: ='Balance Sheet'!O17/'Balance Sheet'!O45 -> 0.28158395 | P22: ='Balance Sheet'!P17/'Balance Sheet'!P45 -> 0.33518159 | ... Z22: ='Balance Sheet'!Z17/'Balance Sheet'!Z45 -> 1.0784464 | AE22: ='Balance Sheet'!AE17/'Balance Sheet'!AE45 -> 0.368053 | AF22: ='Balance Sheet'!AF17/'Balance Sheet'!AF45 -> 0.26856292 | AG22: ='Balance Sheet'!AG17/'Balance Sheet'!AG45 -> 0.19485553 | AH22: ='Balance Sheet'!AH17/'Balance Sheet'!AH45 -> 0.16033727 | AI22: ='Balance Sheet'!AI17/'Balance Sheet'!AI45 -> 0.16505127 | AJ22: ='Balance Sheet'!AJ17/'Balance Sheet'!AJ45 -> 0.33518159 | AK22: ='Balance Sheet'!AK17/'Balance Sheet'!AK45 -> 0.51198794 | AL22: ='Balance Sheet'!AL17/'Balance Sheet'!AL45 -> 0.67593952 | ... AO22: ='Balance Sheet'!AO17/'Balance Sheet'!AO45 -> 1.0784464 | AS22: 0.20 in H1'22, reaching 1.13 in FY'30, indicating strong cash reserves.
A23: Defensive Interval | H23: Cash+Marketable sec+Receivables/Average Daily Expenditure | I23: =('Balance Sheet'!I17+'Balance Sheet'!I14)/('Profit and Loss Statement '!I14/182.5) -> 692.53019 | J23: =('Balance Sheet'!J17+'Balance Sheet'!J14)/('Profit and Loss Statement '!J14/182.5) -> 601.68098 | K23: =('Balance Sheet'!K17+'Balance Sheet'!K14)/('Profit and Loss Statement '!K14/182.5) -> 893.01521 | L23: =('Balance Sheet'!L17+'Balance Sheet'!L14)/('Profit and Loss Statement '!L14/182.5) -> 834.22126 | M23: =('Balance Sheet'!M17+'Balance Sheet'!M14)/('Profit and Loss Statement '!M14/182.5) -> 906.81907 | N23: =('Balance Sheet'!N17+'Balance Sheet'!N14)/('Profit and Loss Statement '!N14/182.5) -> 954.54007 | O23: =('Balance Sheet'!O17+'Balance Sheet'!O14)/('Profit and Loss Statement '!O14/182.5) -> 1042.078 | P23: =('Balance Sheet'!P17+'Balance Sheet'!P14)/('Profit and Loss Statement '!P14/182.5) -> 818.33462 | ... Z23: =('Balance Sheet'!Z17+'Balance Sheet'!Z14)/('Profit and Loss Statement '!Z14/182.5) -> 1248.0904 | AE23: =('Balance Sheet'!AE17+'Balance Sheet'!AE14)/('Profit and Loss Statement '!AE14/365) -> -131.20109 | AF23: =('Balance Sheet'!AF17+'Balance Sheet'!AF14)/('Profit and Loss Statement '!AF14/365) -> 562.60317 | AG23: =('Balance Sheet'!AG17+'Balance Sheet'!AG14)/('Profit and Loss Statement '!AG14/365) -> 621.76979 | AH23: =('Balance Sheet'!AH17+'Balance Sheet'!AH14)/('Profit and Loss Statement '!AH14/365) -> 836.02973 | AI23: =('Balance Sheet'!AI17+'Balance Sheet'!AI14)/('Profit and Loss Statement '!AI14/365) -> 720.03696 | AJ23: =('Balance Sheet'!AJ17+'Balance Sheet'!AJ14)/('Profit and Loss Statement '!AJ14/365) -> 996.01441 | AK23: =('Balance Sheet'!AK17+'Balance Sheet'!AK14)/('Profit and Loss Statement '!AK14/365) -> 1192.3173 | AL23: =('Balance Sheet'!AL17+'Balance Sheet'!AL14)/('Profit and Loss Statement '!AL14/365) -> 1344.2564 | ... AO23: =('Balance Sheet'!AO17+'Balance Sheet'!AO14)/('Profit and Loss Statement '!AO14/365) -> 1589.3154 | AS23: Very high (~692 days in H1'22, increasing to ~1,747 days by FY'30), meaning a strong liquidity position.
A25: Solvency Ratios
A27: Debt to Equity | H27: Total Debt/ Shareholder's equity | I27: =('Balance Sheet'!I38+'Balance Sheet'!I31)/'Balance Sheet'!I29 -> 0.76925218 | J27: =('Balance Sheet'!J38+'Balance Sheet'!J31)/'Balance Sheet'!J29 -> 0.74712591 | K27: =('Balance Sheet'!K38+'Balance Sheet'!K31)/'Balance Sheet'!K29 -> 0.9000136 | L27: =('Balance Sheet'!L38+'Balance Sheet'!L31)/'Balance Sheet'!L29 -> 0.80029839 | M27: =('Balance Sheet'!M38+'Balance Sheet'!M31)/'Balance Sheet'!M29 -> 0.83765058 | N27: =('Balance Sheet'!N38+'Balance Sheet'!N31)/'Balance Sheet'!N29 -> 0.76104812 | O27: =('Balance Sheet'!O38+'Balance Sheet'!O31)/'Balance Sheet'!O29 -> 0.77620566 | P27: =('Balance Sheet'!P38+'Balance Sheet'!P31)/'Balance Sheet'!P29 -> 0.75826231 | ... Z27: =('Balance Sheet'!Z38+'Balance Sheet'!Z31)/'Balance Sheet'!Z29 -> 0.52186526 | AE27: =('Balance Sheet'!AE38+'Balance Sheet'!AE31)/'Balance Sheet'!AE29 -> 1.2643135 | AF27: =('Balance Sheet'!AF38+'Balance Sheet'!AF31)/'Balance Sheet'!AF29 -> 0.85649746 | AG27: =('Balance Sheet'!AG38+'Balance Sheet'!AG31)/'Balance Sheet'!AG29 -> 0.74712591 | AH27: =('Balance Sheet'!AH38+'Balance Sheet'!AH31)/'Balance Sheet'!AH29 -> 0.80029839 | AI27: =('Balance Sheet'!AI38+'Balance Sheet'!AI31)/'Balance Sheet'!AI29 -> 0.76104812 | AJ27: =('Balance Sheet'!AJ38+'Balance Sheet'!AJ31)/'Balance Sheet'!AJ29 -> 0.75826231 | AK27: =('Balance Sheet'!AK38+'Balance Sheet'!AK31)/'Balance Sheet'!AK29 -> 0.71265244 | AL27: =('Balance Sheet'!AL38+'Balance Sheet'!AL31)/'Balance Sheet'!AL29 -> 0.66571189 | ... AO27: =('Balance Sheet'!AO38+'Balance Sheet'!AO31)/'Balance Sheet'!AO29 -> 0.52186526 | AS27: Reduces financial risk
A28: Debt to Capital | H28: Total Debt/ Total Debt + Shareholder's equity | I28: =('Balance Sheet'!I31+'Balance Sheet'!I38)/('Balance Sheet'!I31+'Balance Sheet'!I38+'Balance Sheet'!I29) -> 0.43478945 | J28: =('Balance Sheet'!J31+'Balance Sheet'!J38)/('Balance Sheet'!J31+'Balance Sheet'!J38+'Balance Sheet'!J29) -> 0.42763141 | K28: =('Balance Sheet'!K31+'Balance Sheet'!K38)/('Balance Sheet'!K31+'Balance Sheet'!K38+'Balance Sheet'!K29) -> 0.47368798 | L28: =('Balance Sheet'!L31+'Balance Sheet'!L38)/('Balance Sheet'!L31+'Balance Sheet'!L38+'Balance Sheet'!L29) -> 0.44453652 | M28: =('Balance Sheet'!M31+'Balance Sheet'!M38)/('Balance Sheet'!M31+'Balance Sheet'!M38+'Balance Sheet'!M29) -> 0.45582691 | N28: =('Balance Sheet'!N31+'Balance Sheet'!N38)/('Balance Sheet'!N31+'Balance Sheet'!N38+'Balance Sheet'!N29) -> 0.43215635 | O28: =('Balance Sheet'!O31+'Balance Sheet'!O38)/('Balance Sheet'!O31+'Balance Sheet'!O38+'Balance Sheet'!O29) -> 0.43700213 | P28: =('Balance Sheet'!P31+'Balance Sheet'!P38)/('Balance Sheet'!P31+'Balance Sheet'!P38+'Balance Sheet'!P29) -> 0.43125665 | ... Z28: =('Balance Sheet'!Z31+'Balance Sheet'!Z38)/('Balance Sheet'!Z31+'Balance Sheet'!Z38+'Balance Sheet'!Z29) -> 0.34291161 | AE28: =('Balance Sheet'!AE31+'Balance Sheet'!AE38)/('Balance Sheet'!AE31+'Balance Sheet'!AE38+'Balance Sheet'!AE29) -> 0.55836504 | AF28: =('Balance Sheet'!AF31+'Balance Sheet'!AF38)/('Balance Sheet'!AF31+'Balance Sheet'!AF38+'Balance Sheet'!AF29) -> 0.46135127 | AG28: =('Balance Sheet'!AG31+'Balance Sheet'!AG38)/('Balance Sheet'!AG31+'Balance Sheet'!AG38+'Balance Sheet'!AG29) -> 0.42763141 | AH28: =('Balance Sheet'!AH31+'Balance Sheet'!AH38)/('Balance Sheet'!AH31+'Balance Sheet'!AH38+'Balance Sheet'!AH29) -> 0.44453652 | AI28: =('Balance Sheet'!AI31+'Balance Sheet'!AI38)/('Balance Sheet'!AI31+'Balance Sheet'!AI38+'Balance Sheet'!AI29) -> 0.43215635 | AJ28: =('Balance Sheet'!AJ31+'Balance Sheet'!AJ38)/('Balance Sheet'!AJ31+'Balance Sheet'!AJ38+'Balance Sheet'!AJ29) -> 0.43125665 | AK28: =('Balance Sheet'!AK31+'Balance Sheet'!AK38)/('Balance Sheet'!AK31+'Balance Sheet'!AK38+'Balance Sheet'!AK29) -> 0.41611037 | AL28: =('Balance Sheet'!AL31+'Balance Sheet'!AL38)/('Balance Sheet'!AL31+'Balance Sheet'!AL38+'Balance Sheet'!AL29) -> 0.39965608 | ... AO28: =('Balance Sheet'!AO31+'Balance Sheet'!AO38)/('Balance Sheet'!AO31+'Balance Sheet'!AO38+'Balance Sheet'!AO29) -> 0.34291161 | AS28: Improving capital structure
A29: Debt to Assets | H29: Total Debt / Total Assets | I29: =('Balance Sheet'!I31+'Balance Sheet'!I38)/'Balance Sheet'!I22 -> 0.31675868 | J29: =('Balance Sheet'!J31+'Balance Sheet'!J38)/'Balance Sheet'!J22 -> 0.31250239 | K29: =('Balance Sheet'!K31+'Balance Sheet'!K38)/'Balance Sheet'!K22 -> 0.34890095 | L29: =('Balance Sheet'!L31+'Balance Sheet'!L38)/'Balance Sheet'!L22 -> 0.33068011 | M29: =('Balance Sheet'!M31+'Balance Sheet'!M38)/'Balance Sheet'!M22 -> 0.33899641 | N29: =('Balance Sheet'!N31+'Balance Sheet'!N38)/'Balance Sheet'!N22 -> 0.31705503 | O29: =('Balance Sheet'!O31+'Balance Sheet'!O38)/'Balance Sheet'!O22 -> 0.3275064 | P29: =('Balance Sheet'!P31+'Balance Sheet'!P38)/'Balance Sheet'!P22 -> 0.3173223 | ... Z29: =('Balance Sheet'!Z31+'Balance Sheet'!Z38)/'Balance Sheet'!Z22 -> 0.24909048 | AE29: =('Balance Sheet'!AE31+'Balance Sheet'!AE38)/'Balance Sheet'!AE22 -> 0.42681554 | AF29: =('Balance Sheet'!AF31+'Balance Sheet'!AF38)/'Balance Sheet'!AF22 -> 0.3454043 | AG29: =('Balance Sheet'!AG31+'Balance Sheet'!AG38)/'Balance Sheet'!AG22 -> 0.31250239 | AH29: =('Balance Sheet'!AH31+'Balance Sheet'!AH38)/'Balance Sheet'!AH22 -> 0.33068011 | AI29: =('Balance Sheet'!AI31+'Balance Sheet'!AI38)/'Balance Sheet'!AI22 -> 0.31705503 | AJ29: =('Balance Sheet'!AJ31+'Balance Sheet'!AJ38)/'Balance Sheet'!AJ22 -> 0.3173223 | AK29: =('Balance Sheet'!AK31+'Balance Sheet'!AK38)/'Balance Sheet'!AK22 -> 0.30585955 | AL29: =('Balance Sheet'!AL31+'Balance Sheet'!AL38)/'Balance Sheet'!AL22 -> 0.29317444 | ... AO29: =('Balance Sheet'!AO31+'Balance Sheet'!AO38)/'Balance Sheet'!AO22 -> 0.24909048 | AS29: Low debt to total assets
A30: Financial Leverage | H30: Average Total assets / average total equity | I30: =AVERAGE('Balance Sheet'!H22:I22)/AVERAGE('Balance Sheet'!H29:I29) -> 2.4529523 | J30: =AVERAGE('Balance Sheet'!I22:J22)/AVERAGE('Balance Sheet'!I29:J29) -> 2.4094903 | K30: =AVERAGE('Balance Sheet'!J22:K22)/AVERAGE('Balance Sheet'!J29:K29) -> 2.485483 | L30: =AVERAGE('Balance Sheet'!K22:L22)/AVERAGE('Balance Sheet'!K29:L29) -> 2.4985731 | M30: =AVERAGE('Balance Sheet'!L22:M22)/AVERAGE('Balance Sheet'!L29:M29) -> 2.445165 | N30: =AVERAGE('Balance Sheet'!M22:N22)/AVERAGE('Balance Sheet'!M29:N29) -> 2.435415 | O30: =AVERAGE('Balance Sheet'!N22:O22)/AVERAGE('Balance Sheet'!N29:O29) -> 2.3848506 | P30: =AVERAGE('Balance Sheet'!O22:P22)/AVERAGE('Balance Sheet'!O29:P29) -> 2.3799868 | ... Z30: =AVERAGE('Balance Sheet'!Y22:Z22)/AVERAGE('Balance Sheet'!Y29:Z29) -> 2.0410763 | AE30: =AVERAGE('Balance Sheet'!AD22:AE22)/AVERAGE('Balance Sheet'!AD29:AE29) -> 2.9622012 | AF30: =AVERAGE('Balance Sheet'!AE22:AF22)/AVERAGE('Balance Sheet'!AE29:AF29) -> 2.6833861 | AG30: =AVERAGE('Balance Sheet'!AF22:AG22)/AVERAGE('Balance Sheet'!AF29:AG29) -> 2.4328688 | AH30: =AVERAGE('Balance Sheet'!AG22:AH22)/AVERAGE('Balance Sheet'!AG29:AH29) -> 2.4057572 | AI30: =AVERAGE('Balance Sheet'!AH22:AI22)/AVERAGE('Balance Sheet'!AH29:AI29) -> 2.4103472 | AJ30: =AVERAGE('Balance Sheet'!AI22:AJ22)/AVERAGE('Balance Sheet'!AI29:AJ29) -> 2.3947389 | AK30: =AVERAGE('Balance Sheet'!AJ22:AK22)/AVERAGE('Balance Sheet'!AJ29:AK29) -> 2.3584615 | AL30: =AVERAGE('Balance Sheet'!AK22:AL22)/AVERAGE('Balance Sheet'!AK29:AL29) -> 2.2989561 | ... AO30: =AVERAGE('Balance Sheet'!AN22:AO22)/AVERAGE('Balance Sheet'!AN29:AO29) -> 2.122346 | AS30: Stronger equity base, low risk
A31: Interest Coverage | H31: EBIT/Interest Payments | I31: ='Profit and Loss Statement '!I14/-'Profit and Loss Statement '!I17 -> 9.6728972 | J31: ='Profit and Loss Statement '!J14/-'Profit and Loss Statement '!J17 -> 9.0696721 | K31: ='Profit and Loss Statement '!K14/-'Profit and Loss Statement '!K17 -> 5.4610169 | L31: ='Profit and Loss Statement '!L14/-'Profit and Loss Statement '!L17 -> 4.6898551 | M31: ='Profit and Loss Statement '!M14/-'Profit and Loss Statement '!M17 -> 4.5087719 | N31: ='Profit and Loss Statement '!N14/-'Profit and Loss Statement '!N17 -> 3.5185332 | O31: ='Profit and Loss Statement '!O14/-'Profit and Loss Statement '!O17 -> 4.4376565 | P31: ='Profit and Loss Statement '!P14/-'Profit and Loss Statement '!P17 -> 6.7149211 | ... Z31: ='Profit and Loss Statement '!Z14/-'Profit and Loss Statement '!Z17 -> 12.285967 | AE31: ='Profit and Loss Statement '!AE14/-'Profit and Loss Statement '!AE17 -> -38.102616 | AF31: ='Profit and Loss Statement '!AF14/-'Profit and Loss Statement '!AF17 -> 9.7034632 | AG31: ='Profit and Loss Statement '!AG14/-'Profit and Loss Statement '!AG17 -> 9.3515284 | AH31: ='Profit and Loss Statement '!AH14/-'Profit and Loss Statement '!AH17 -> 5.0453125 | AI31: ='Profit and Loss Statement '!AI14/-'Profit and Loss Statement '!AI17 -> 5.1720588 | AJ31: ='Profit and Loss Statement '!AJ14/-'Profit and Loss Statement '!AJ17 -> 5.5916966 | AK31: ='Profit and Loss Statement '!AK14/-'Profit and Loss Statement '!AK17 -> 6.149521 | AL31: ='Profit and Loss Statement '!AL14/-'Profit and Loss Statement '!AL17 -> 6.832948 | ... AO31: ='Profit and Loss Statement '!AO14/-'Profit and Loss Statement '!AO17 -> 9.7631741 | AS31: Strong ability to pay off interest
A32: Fixed Charge coverage | H32: EBIT+Lease Payments/Interest+Lease Payments
A34: Profitability Ratios
A36: EBIT Margin | H36: EBIT/Margin | I36: ='Profit and Loss Statement '!I14/'Profit and Loss Statement '!I5 -> 0.15350389 | J36: ='Profit and Loss Statement '!J14/'Profit and Loss Statement '!J5 -> 0.14526717 | K36: ='Profit and Loss Statement '!K14/'Profit and Loss Statement '!K5 -> 0.11091986 | L36: ='Profit and Loss Statement '!L14/'Profit and Loss Statement '!L5 -> 0.10215936 | M36: ='Profit and Loss Statement '!M14/'Profit and Loss Statement '!M5 -> 0.10402051 | N36: ='Profit and Loss Statement '!N14/'Profit and Loss Statement '!N5 -> 0.088450157 | O36: ='Profit and Loss Statement '!O14/'Profit and Loss Statement '!O5 -> 0.10481062 | P36: ='Profit and Loss Statement '!P14/'Profit and Loss Statement '!P5 -> 0.12646195 | ... Z36: ='Profit and Loss Statement '!Z14/'Profit and Loss Statement '!Z5 -> 0.14459031 | AF36: ='Profit and Loss Statement '!AF14/'Profit and Loss Statement '!AF5 -> 0.20432068 | AG36: ='Profit and Loss Statement '!AG14/'Profit and Loss Statement '!AG5 -> 0.14913472 | AH36: ='Profit and Loss Statement '!AH14/'Profit and Loss Statement '!AH5 -> 0.10635004 | AI36: ='Profit and Loss Statement '!AI14/'Profit and Loss Statement '!AI5 -> 0.11793702 | AJ36: ='Profit and Loss Statement '!AJ14/'Profit and Loss Statement '!AJ5 -> 0.11700105 | AK36: ='Profit and Loss Statement '!AK14/'Profit and Loss Statement '!AK5 -> 0.1205549 | AL36: ='Profit and Loss Statement '!AL14/'Profit and Loss Statement '!AL5 -> 0.12443391 | AM36: ='Profit and Loss Statement '!AM14/'Profit and Loss Statement '!AM5 -> 0.12847144 | ... AO36: ='Profit and Loss Statement '!AO14/'Profit and Loss Statement '!AO5 -> 0.13659579 | AS36: Good
A37: EBITDA Margin | H37: EBITDA/Margin | I37: ='Profit and Loss Statement '!I15/'Profit and Loss Statement '!I5 -> 0.22261772 | J37: ='Profit and Loss Statement '!J15/'Profit and Loss Statement '!J5 -> 0.20789025 | K37: ='Profit and Loss Statement '!K15/'Profit and Loss Statement '!K5 -> 0.19657119 | L37: ='Profit and Loss Statement '!L15/'Profit and Loss Statement '!L5 -> 0.21909332 | M37: ='Profit and Loss Statement '!M15/'Profit and Loss Statement '!M5 -> 0.19623583 | N37: ='Profit and Loss Statement '!N15/'Profit and Loss Statement '!N5 -> 0.171 | O37: ='Profit and Loss Statement '!O15/'Profit and Loss Statement '!O5 -> 0.21448192 | P37: ='Profit and Loss Statement '!P15/'Profit and Loss Statement '!P5 -> 0.19815902 | ... Z37: ='Profit and Loss Statement '!Z15/'Profit and Loss Statement '!Z5 -> 0.19920275 | AF37: ='Profit and Loss Statement '!AF15/'Profit and Loss Statement '!AF5 -> 0.29360558 | AG37: ='Profit and Loss Statement '!AG15/'Profit and Loss Statement '!AG5 -> 0.21480553 | AH37: ='Profit and Loss Statement '!AH15/'Profit and Loss Statement '!AH5 -> 0.20831961 | AI37: ='Profit and Loss Statement '!AI15/'Profit and Loss Statement '!AI5 -> 0.20529157 | AJ37: ='Profit and Loss Statement '!AJ15/'Profit and Loss Statement '!AJ5 -> 0.20529157 | AK37: ='Profit and Loss Statement '!AK15/'Profit and Loss Statement '!AK5 -> 0.20529157 | AL37: ='Profit and Loss Statement '!AL15/'Profit and Loss Statement '!AL5 -> 0.20529157 | AM37: ='Profit and Loss Statement '!AM15/'Profit and Loss Statement '!AM5 -> 0.20529157 | ... AO37: ='Profit and Loss Statement '!AO15/'Profit and Loss Statement '!AO5 -> 0.20529157 | AS37: Good
A38: PBT Margin | H38: PBT/Margin | I38: ='Profit and Loss Statement '!I21/'Profit and Loss Statement '!I5 -> 0.14846125 | J38: ='Profit and Loss Statement '!J21/'Profit and Loss Statement '!J5 -> 0.14231325 | K38: ='Profit and Loss Statement '!K21/'Profit and Loss Statement '!K5 -> 0.087854586 | L38: ='Profit and Loss Statement '!L21/'Profit and Loss Statement '!L5 -> 0.078671549 | M38: ='Profit and Loss Statement '!M21/'Profit and Loss Statement '!M5 -> 0.022868322 | N38: ='Profit and Loss Statement '!N21/'Profit and Loss Statement '!N5 -> 0.065378876 | O38: ='Profit and Loss Statement '!O21/'Profit and Loss Statement '!O5 -> 0.081192156 | P38: ='Profit and Loss Statement '!P21/'Profit and Loss Statement '!P5 -> 0.10762898 | ... Z38: ='Profit and Loss Statement '!Z21/'Profit and Loss Statement '!Z5 -> 0.13282157 | AF38: ='Profit and Loss Statement '!AF21/'Profit and Loss Statement '!AF5 -> 0.19752974 | AG38: ='Profit and Loss Statement '!AG21/'Profit and Loss Statement '!AG5 -> 0.14520004 | AH38: ='Profit and Loss Statement '!AH21/'Profit and Loss Statement '!AH5 -> 0.083064357 | AI38: ='Profit and Loss Statement '!AI21/'Profit and Loss Statement '!AI5 -> 0.067301566 | AJ38: ='Profit and Loss Statement '!AJ21/'Profit and Loss Statement '!AJ5 -> 0.096076984 | AK38: ='Profit and Loss Statement '!AK21/'Profit and Loss Statement '!AK5 -> 0.10095095 | AL38: ='Profit and Loss Statement '!AL21/'Profit and Loss Statement '!AL5 -> 0.10622304 | AM38: ='Profit and Loss Statement '!AM21/'Profit and Loss Statement '!AM5 -> 0.11168092 | ... AO38: ='Profit and Loss Statement '!AO21/'Profit and Loss Statement '!AO5 -> 0.12260487 | AS38: Good
A39: Net Profit Margin | H39: Net Income/Margin | I39: ='Profit and Loss Statement '!I24/'Profit and Loss Statement '!I5 -> 0.10789766 | J39: ='Profit and Loss Statement '!J24/'Profit and Loss Statement '!J5 -> 0.10397794 | K39: ='Profit and Loss Statement '!K24/'Profit and Loss Statement '!K5 -> 0.081726797 | L39: ='Profit and Loss Statement '!L24/'Profit and Loss Statement '!L5 -> 0.076651092 | M39: ='Profit and Loss Statement '!M24/'Profit and Loss Statement '!M5 -> -0.0032379924 | N39: ='Profit and Loss Statement '!N24/'Profit and Loss Statement '!N5 -> 0.056225833 | O39: ='Profit and Loss Statement '!O24/'Profit and Loss Statement '!O5 -> 0.069825254 | P39: ='Profit and Loss Statement '!P24/'Profit and Loss Statement '!P5 -> 0.044521117 | ... Z39: ='Profit and Loss Statement '!Z24/'Profit and Loss Statement '!Z5 -> 0.056842398 | AF39: ='Profit and Loss Statement '!AF24/'Profit and Loss Statement '!AF5 -> 0.1611139 | AG39: ='Profit and Loss Statement '!AG24/'Profit and Loss Statement '!AG5 -> 0.10581845 | AH39: ='Profit and Loss Statement '!AH24/'Profit and Loss Statement '!AH5 -> 0.079079112 | AI39: ='Profit and Loss Statement '!AI24/'Profit and Loss Statement '!AI5 -> 0.038932296 | AJ39: ='Profit and Loss Statement '!AJ24/'Profit and Loss Statement '!AJ5 -> 0.055578166 | AK39: ='Profit and Loss Statement '!AK24/'Profit and Loss Statement '!AK5 -> 0.058397633 | AL39: ='Profit and Loss Statement '!AL24/'Profit and Loss Statement '!AL5 -> 0.06144741 | AM39: ='Profit and Loss Statement '!AM24/'Profit and Loss Statement '!AM5 -> 0.06460466 | ... AO39: ='Profit and Loss Statement '!AO24/'Profit and Loss Statement '!AO5 -> 0.070923893 | AS39: Good
A40: ROA | H40: Net Income / Average Total Assets | I40: ='Profit and Loss Statement '!I24/(AVERAGE('Balance Sheet'!H22:I22)) -> 0.028755225 | J40: ='Profit and Loss Statement '!J24/(AVERAGE('Balance Sheet'!I22:J22)) -> 0.030241993 | K40: ='Profit and Loss Statement '!K24/(AVERAGE('Balance Sheet'!J22:K22)) -> 0.021716262 | L40: ='Profit and Loss Statement '!L24/(AVERAGE('Balance Sheet'!K22:L22)) -> 0.021665804 | M40: ='Profit and Loss Statement '!M24/(AVERAGE('Balance Sheet'!L22:M22)) -> -0.00087497835 | N40: ='Profit and Loss Statement '!N24/(AVERAGE('Balance Sheet'!M22:N22)) -> 0.01556659 | O40: ='Profit and Loss Statement '!O24/(AVERAGE('Balance Sheet'!N22:O22)) -> 0.019696484 | P40: ='Profit and Loss Statement '!P24/(AVERAGE('Balance Sheet'!O22:P22)) -> 0.015549704 | ... Z40: ='Profit and Loss Statement '!Z24/(AVERAGE('Balance Sheet'!Y22:Z22)) -> 0.025647106 | AF40: ='Profit and Loss Statement '!AF24/(AVERAGE('Balance Sheet'!AE22:AF22)) -> 0.077282963 | AG40: ='Profit and Loss Statement '!AG24/(AVERAGE('Balance Sheet'!AF22:AG22)) -> 0.060026073 | AH40: ='Profit and Loss Statement '!AH24/(AVERAGE('Balance Sheet'!AG22:AH22)) -> 0.044645264 | AI40: ='Profit and Loss Statement '!AI24/(AVERAGE('Balance Sheet'!AH22:AI22)) -> 0.021317225 | AJ40: ='Profit and Loss Statement '!AJ24/(AVERAGE('Balance Sheet'!AI22:AJ22)) -> 0.035053834 | AK40: ='Profit and Loss Statement '!AK24/(AVERAGE('Balance Sheet'!AJ22:AK22)) -> 0.037601297 | AL40: ='Profit and Loss Statement '!AL24/(AVERAGE('Balance Sheet'!AK22:AL22)) -> 0.040921464 | AM40: ='Profit and Loss Statement '!AM24/(AVERAGE('Balance Sheet'!AL22:AM22)) -> 0.044592555 | ... AO40: ='Profit and Loss Statement '!AO24/(AVERAGE('Balance Sheet'!AN22:AO22)) -> 0.052644992 | AS40: Significant decline in profitability ratios post FY'21, likely due to increased costs, economic downturns, or operational inefficiencies.
A41: RoCA | H41: EBIT / Average Total Assets | I41: ='Profit and Loss Statement '!I14/(AVERAGE('Balance Sheet'!H22:I22)) -> 0.040909495 | J41: ='Profit and Loss Statement '!J14/(AVERAGE('Balance Sheet'!I22:J22)) -> 0.042250967 | K41: ='Profit and Loss Statement '!K14/(AVERAGE('Balance Sheet'!J22:K22)) -> 0.029473376 | L41: ='Profit and Loss Statement '!L14/(AVERAGE('Balance Sheet'!K22:L22)) -> 0.028875841 | M41: ='Profit and Loss Statement '!M14/(AVERAGE('Balance Sheet'!L22:M22)) -> 0.02810868 | N41: ='Profit and Loss Statement '!N14/(AVERAGE('Balance Sheet'!M22:N22)) -> 0.024488162 | O41: ='Profit and Loss Statement '!O14/(AVERAGE('Balance Sheet'!N22:O22)) -> 0.029565243 | P41: ='Profit and Loss Statement '!P14/(AVERAGE('Balance Sheet'!O22:P22)) -> 0.044168837 | ... Z41: ='Profit and Loss Statement '!Z14/(AVERAGE('Balance Sheet'!Y22:Z22)) -> 0.06523868 | AF41: ='Profit and Loss Statement '!AF14/(AVERAGE('Balance Sheet'!AE22:AF22)) -> 0.098008351 | AG41: ='Profit and Loss Statement '!AG14/(AVERAGE('Balance Sheet'!AF22:AG22)) -> 0.084597456 | AH41: ='Profit and Loss Statement '!AH14/(AVERAGE('Balance Sheet'!AG22:AH22)) -> 0.060041466 | AI41: ='Profit and Loss Statement '!AI14/(AVERAGE('Balance Sheet'!AH22:AI22)) -> 0.064575951 | AJ41: ='Profit and Loss Statement '!AJ14/(AVERAGE('Balance Sheet'!AI22:AJ22)) -> 0.073794007 | AK41: ='Profit and Loss Statement '!AK14/(AVERAGE('Balance Sheet'!AJ22:AK22)) -> 0.077623359 | AL41: ='Profit and Loss Statement '!AL14/(AVERAGE('Balance Sheet'!AK22:AL22)) -> 0.082867899 | AM41: ='Profit and Loss Statement '!AM14/(AVERAGE('Balance Sheet'!AL22:AM22)) -> 0.088675797 | ... AO41: ='Profit and Loss Statement '!AO14/(AVERAGE('Balance Sheet'!AN22:AO22)) -> 0.10139156 | AS41: Recovery phase expected from FY'25 onwards, suggesting strategic improvements or favorable market conditions.
A42: RoE | H42: Net Income / Average Equity | I42: ='Profit and Loss Statement '!I24/AVERAGE('Balance Sheet'!H29:I29) -> 0.070535195 | J42: ='Profit and Loss Statement '!J24/AVERAGE('Balance Sheet'!I29:J29) -> 0.072867789 | K42: ='Profit and Loss Statement '!K24/AVERAGE('Balance Sheet'!J29:K29) -> 0.0539754 | L42: ='Profit and Loss Statement '!L24/AVERAGE('Balance Sheet'!K29:L29) -> 0.054133595 | M42: ='Profit and Loss Statement '!M24/AVERAGE('Balance Sheet'!L29:M29) -> -0.0021394665 | N42: ='Profit and Loss Statement '!N24/AVERAGE('Balance Sheet'!M29:N29) -> 0.037911106 | O42: ='Profit and Loss Statement '!O24/AVERAGE('Balance Sheet'!N29:O29) -> 0.046973171 | P42: ='Profit and Loss Statement '!P24/AVERAGE('Balance Sheet'!O29:P29) -> 0.037008091 | ... Z42: ='Profit and Loss Statement '!Z24/AVERAGE('Balance Sheet'!Y29:Z29) -> 0.052347701 | AF42: ='Profit and Loss Statement '!AF24/AVERAGE('Balance Sheet'!AE29:AF29) -> 0.20738003 | AG42: ='Profit and Loss Statement '!AG24/AVERAGE('Balance Sheet'!AF29:AG29) -> 0.14603556 | AH42: ='Profit and Loss Statement '!AH24/AVERAGE('Balance Sheet'!AG29:AH29) -> 0.10740567 | AI42: ='Profit and Loss Statement '!AI24/AVERAGE('Balance Sheet'!AH29:AI29) -> 0.051381912 | AJ42: ='Profit and Loss Statement '!AJ24/AVERAGE('Balance Sheet'!AI29:AJ29) -> 0.083944781 | AK42: ='Profit and Loss Statement '!AK24/AVERAGE('Balance Sheet'!AJ29:AK29) -> 0.08868121 | AL42: ='Profit and Loss Statement '!AL24/AVERAGE('Balance Sheet'!AK29:AL29) -> 0.094076648 | AM42: ='Profit and Loss Statement '!AM24/AVERAGE('Balance Sheet'!AL29:AM29) -> 0.099842417 | ... AO42: ='Profit and Loss Statement '!AO24/AVERAGE('Balance Sheet'!AN29:AO29) -> 0.11173089 | AS42: ROE still lower than historical levels, indicating the company may need to optimize equity utilization or manage debt more effectively
A44: Valuation Ratios
A46: Earnings per Share | H46: Net Income - Preferred Dividends / WASO | Z46: ='Profit and Loss Statement '!Z34 -> -1.3859124 | AE46: ='Profit and Loss Statement '!AE34 -> -0.35439703 | AF46: ='Profit and Loss Statement '!AF34 -> 5.77114 | AG46: ='Profit and Loss Statement '!AG34 -> 4.6560389 | AH46: ='Profit and Loss Statement '!AH34 -> 4.085254 | AI46: ='Profit and Loss Statement '!AI34 -> 1.7444379 | AJ46: ='Profit and Loss Statement '!AJ34 -> 2.9493463 | AK46: ='Profit and Loss Statement '!AK34 -> 3.397166 | AL46: ='Profit and Loss Statement '!AL34 -> 3.9494236 | ... AO46: ='Profit and Loss Statement '!AO34 -> 6.3904517 | AS46: Increasing
A47: PE | H47: Share Price / EPS | Z47: ='DCF '!$C$23/'Ratio Analysis'!Z46 -> -59.109077 | AE47: ='DCF '!$C$23/'Ratio Analysis'!AE46 -> -231.15318 | AF47: ='DCF '!$C$23/'Ratio Analysis'!AF46 -> 14.194769 | AG47: ='DCF '!$C$23/'Ratio Analysis'!AG46 -> 17.594355 | AH47: ='DCF '!$C$23/'Ratio Analysis'!AH46 -> 20.052609 | AI47: ='DCF '!$C$23/'Ratio Analysis'!AI46 -> 46.960684 | AJ47: ='DCF '!$C$23/'Ratio Analysis'!AJ46 -> 27.775646 | AK47: ='DCF '!$C$23/'Ratio Analysis'!AK46 -> 24.114218 | AL47: ='DCF '!$C$23/'Ratio Analysis'!AL46 -> 20.742267 | ... AO47: ='DCF '!$C$23/'Ratio Analysis'!AO46 -> 12.819125 | AS47: Decreasing
A48: TTM EPS | Z48: ='Profit and Loss Statement '!Y24/'Profit and Loss Statement '!Z38 -> 3.9291102 | AE48: ='Profit and Loss Statement '!AD24/'Profit and Loss Statement '!AE38 -> 0 | AF48: ='Profit and Loss Statement '!AE24/'Profit and Loss Statement '!AF38 -> -34.382035 | AG48: ='Profit and Loss Statement '!AF24/'Profit and Loss Statement '!AG38 -> 6.1368745 | AH48: ='Profit and Loss Statement '!AG24/'Profit and Loss Statement '!AH38 -> 5.3884926 | AI48: ='Profit and Loss Statement '!AH24/'Profit and Loss Statement '!AI38 -> 4.282613 | AJ48: ='Profit and Loss Statement '!AI24/'Profit and Loss Statement '!AJ38 -> 2.0708512 | AK48: ='Profit and Loss Statement '!AJ24/'Profit and Loss Statement '!AK38 -> 3.5012179 | AL48: ='Profit and Loss Statement '!AK24/'Profit and Loss Statement '!AL38 -> 4.032832 | ... AO48: ='Profit and Loss Statement '!AN24/'Profit and Loss Statement '!AO38 -> 6.4400463
A49: TTM P/E | Z49: ='DCF '!$C$23/'Ratio Analysis'!Z48 -> 20.849504 | AE49: ='DCF '!$C$23/'Ratio Analysis'!AE48 -> #DIV/0! | AF49: ='DCF '!$C$23/'Ratio Analysis'!AF48 -> -2.3826396 | AG49: ='DCF '!$C$23/'Ratio Analysis'!AG48 -> 13.348815 | AH49: ='DCF '!$C$23/'Ratio Analysis'!AH48 -> 15.202768 | AI49: ='DCF '!$C$23/'Ratio Analysis'!AI48 -> 19.128509 | AJ49: ='DCF '!$C$23/'Ratio Analysis'!AJ48 -> 39.558613 | AK49: ='DCF '!$C$23/'Ratio Analysis'!AK48 -> 23.397573 | AL49: ='DCF '!$C$23/'Ratio Analysis'!AL48 -> 20.313269 | ... AO49: ='DCF '!$C$23/'Ratio Analysis'!AO48 -> 12.720405
A50: Forward EPS | Z50: ='Profit and Loss Statement '!AA24/'Profit and Loss Statement '!Z38 -> 0 | AE50: ='Profit and Loss Statement '!AF24/'Profit and Loss Statement '!AE38 -> 6.1411445 | AF50: ='Profit and Loss Statement '!AG24/'Profit and Loss Statement '!AF38 -> 5.276322 | AG50: ='Profit and Loss Statement '!AH24/'Profit and Loss Statement '!AG38 -> 4.1682138 | AH50: ='Profit and Loss Statement '!AI24/'Profit and Loss Statement '!AH38 -> 2.058585 | AI50: ='Profit and Loss Statement '!AJ24/'Profit and Loss Statement '!AI38 -> 3.5012179 | AJ50: ='Profit and Loss Statement '!AK24/'Profit and Loss Statement '!AJ38 -> 4.032832 | AK50: ='Profit and Loss Statement '!AL24/'Profit and Loss Statement '!AK38 -> 4.6884262 | AL50: ='Profit and Loss Statement '!AM24/'Profit and Loss Statement '!AL38 -> 5.4835686 | ... AN50: ='Profit and Loss Statement '!AO24/'Profit and Loss Statement '!AN38 -> 7.586211
A51: Forward P/E | Z51: ='DCF '!$C$23/Z50 -> #DIV/0! | AE51: ='DCF '!$C$23/AE50 -> 13.339533 | AF51: ='DCF '!$C$23/AF50 -> 15.525967 | AG51: ='DCF '!$C$23/AG50 -> 19.653503 | AH51: ='DCF '!$C$23/AH50 -> 39.794324 | AI51: ='DCF '!$C$23/AI50 -> 23.397573 | AJ51: ='DCF '!$C$23/AJ50 -> 20.313269 | AK51: ='DCF '!$C$23/AK50 -> 17.472814 | AL51: ='DCF '!$C$23/AL50 -> 14.939177 | ... AN51: ='DCF '!$C$23/AN50 -> 10.79854
A52: Dividend Yield | H52: Dividend / Price
A53: Dividend Payout | H53: Dividend /Net Icome
A54: Retention Rate | H54: Net Income - Dividends / Net Income
A55: Sustainable Growth Rate | H55: RR*RoE
A56: BVPS | Z56: ='Balance Sheet'!Z29/'Profit and Loss Statement '!Z38 -> 71.690276 | AF56: ='Balance Sheet'!AF29/'Profit and Loss Statement '!AF38 -> 34.203206 | AG56: ='Balance Sheet'!AG29/'Profit and Loss Statement '!AG38 -> 38.05383 | AH56: ='Balance Sheet'!AH29/'Profit and Loss Statement '!AH38 -> 40.407488 | AI56: ='Balance Sheet'!AI29/'Profit and Loss Statement '!AI38 -> 39.957974 | AJ56: ='Balance Sheet'!AJ29/'Profit and Loss Statement '!AJ38 -> 43.459192 | AK56: ='Balance Sheet'!AK29/'Profit and Loss Statement '!AK38 -> 47.492024 | AL56: ='Balance Sheet'!AL29/'Profit and Loss Statement '!AL38 -> 52.18045 | AM56: ='Balance Sheet'!AM29/'Profit and Loss Statement '!AM38 -> 57.664019 | ... AO56: ='Balance Sheet'!AO29/'Profit and Loss Statement '!AO38 -> 71.690276 | AS56: Suggesting strong retained earnings, asset appreciation, or reduced liabilities.
A57: OCF/share | Z57: ='Cash Flow Statement'!Z22/'Profit and Loss Statement '!Z38 -> 7.9854693 | AF57: ='Cash Flow Statement'!AF22/'Profit and Loss Statement '!AF38 -> 7.2590663 | AG57: ='Cash Flow Statement'!AG22/'Profit and Loss Statement '!AG38 -> 7.8052016 | AH57: ='Cash Flow Statement'!AH22/'Profit and Loss Statement '!AH38 -> 7.8548938 | AI57: ='Cash Flow Statement'!AI22/'Profit and Loss Statement '!AI38 -> 9.8155849 | AJ57: ='Cash Flow Statement'!AJ22/'Profit and Loss Statement '!AJ38 -> 9.0256627 | AK57: ='Cash Flow Statement'!AK22/'Profit and Loss Statement '!AK38 -> 10.022749 | AL57: ='Cash Flow Statement'!AL22/'Profit and Loss Statement '!AL38 -> 11.022901 | AM57: ='Cash Flow Statement'!AM22/'Profit and Loss Statement '!AM38 -> 12.194217 | ... AO57: ='Cash Flow Statement'!AO22/'Profit and Loss Statement '!AO38 -> 15.20655 | AS57: suggesting improved profitability, cost efficiencies, or stronger cash collections.
A58: FCF/share | Z58: ='Balance Sheet'!Z94/'Profit and Loss Statement '!Z38 -> 0 | AF58: ='Balance Sheet'!AF94/'Profit and Loss Statement '!AF38 -> 9.5577995 | AG58: ='Balance Sheet'!AG94/'Profit and Loss Statement '!AG38 -> 10.914436 | AH58: ='Balance Sheet'!AH94/'Profit and Loss Statement '!AH38 -> 12.170653 | AI58: ='Balance Sheet'!AI94/'Profit and Loss Statement '!AI38 -> 13.71114 | AJ58: ='Balance Sheet'!AJ94/'Profit and Loss Statement '!AJ38 -> 12.80544 | AK58: ='Balance Sheet'!AK94/'Profit and Loss Statement '!AK38 -> 14.166238 | AL58: ='Balance Sheet'!AL94/'Profit and Loss Statement '!AL38 -> 15.60089 | AM58: ='Balance Sheet'!AM94/'Profit and Loss Statement '!AM38 -> 17.286948 | ... AO58: ='Balance Sheet'!AO94/'Profit and Loss Statement '!AO38 -> 21.624312 | AS58: Positive trend in both OCF and FCF per share, indicating increasing financial flexibility.
A59: Net Debt/EBITDA | AF59: =('Balance Sheet'!AF38+'Balance Sheet'!AF31)/'Profit and Loss Statement '!AF15 -> 2.6192176 | AG59: =('Balance Sheet'!AG38+'Balance Sheet'!AG31)/'Profit and Loss Statement '!AG15 -> 2.6547252 | AH59: =('Balance Sheet'!AH38+'Balance Sheet'!AH31)/'Profit and Loss Statement '!AH15 -> 2.8834783 | AI59: =('Balance Sheet'!AI38+'Balance Sheet'!AI31)/'Profit and Loss Statement '!AI15 -> 2.7848742 | AJ59: =('Balance Sheet'!AJ38+'Balance Sheet'!AJ31)/'Profit and Loss Statement '!AJ15 -> 2.5480918 | AK59: =('Balance Sheet'!AK38+'Balance Sheet'!AK31)/'Profit and Loss Statement '!AK15 -> 2.38733 | AL59: =('Balance Sheet'!AL38+'Balance Sheet'!AL31)/'Profit and Loss Statement '!AL15 -> 2.2176833 | AM59: =('Balance Sheet'!AM38+'Balance Sheet'!AM31)/'Profit and Loss Statement '!AM15 -> 2.0447155 | ... AO59: =('Balance Sheet'!AO38+'Balance Sheet'!AO31)/'Profit and Loss Statement '!AO15 -> 1.7037865 | AS59: FCF per share is higher than OCF per share, which is unusual—might indicate low CapEx or asset sales boosting FCF.
AS60: Long-term growth suggests efficient working capital management and profitability improvements.
AI61: ='Balance Sheet'!AI29+'Balance Sheet'!AI31+'Balance Sheet'!AI38-'Balance Sheet'!AI17 -> 37101 | AJ61: ='Balance Sheet'!AJ29+'Balance Sheet'!AJ31+'Balance Sheet'!AJ38-'Balance Sheet'!AJ17 -> 37402.053
AI62: =AI61/'Profit and Loss Statement '!AI15 -> 6.0602744 | AJ62: =AJ61/'Profit and Loss Statement '!AJ15 -> 5.1585312

Sheet Africa & Middle East
B1: ='Cash Flow Statement'!B1 -> H1'19 | C1: ='Cash Flow Statement'!C1 -> H2'19 | D1: ='Cash Flow Statement'!D1 -> FY'19 | E1: ='Cash Flow Statement'!E1 -> H1'20 | F1: ='Cash Flow Statement'!F1 -> H2'20 | G1: ='Cash Flow Statement'!G1 -> H1'21 | H1: ='Cash Flow Statement'!H1 -> H2'21 | I1: ='Cash Flow Statement'!I1 -> H1'22 | ... Z1: ='Cash Flow Statement'!Z1 -> H2'30 | AF1: ='Cash Flow Statement'!AE1 -> FY'20 | AG1: ='Cash Flow Statement'!AF1 -> FY'21 | AH1: ='Cash Flow Statement'!AG1 -> FY'22 | AI1: ='Cash Flow Statement'!AH1 -> FY'23 | AJ1: ='Cash Flow Statement'!AI1 -> FY'24 | AK1: ='Cash Flow Statement'!AJ1 -> FY'25 | AL1: ='Cash Flow Statement'!AK1 -> FY'26 | AM1: ='Cash Flow Statement'!AL1 -> FY'27 | ... AP1: ='Cash Flow Statement'!AO1 -> FY'30
A4: Africa and Middle East
A6: Net Revenue (beia) | I6: =G17 -> 1472 | K6: =I17 -> 1856 | M6: =K17 -> 1968 | O6: =M17 -> 1919 | Q6: =O17 -> 2061.7889 | S6: =Q17 -> 2490.3297 | U6: =S17 -> 3185.8204 | W6: =U17 -> 4148.7297 | Y6: =W17 -> 5395.7925 | AI6: =AH17 -> 4005 | AJ6: =AI17 -> 4229 | AK6: =AJ17 -> 4119.2199 | AL6: =AK17 -> 4324.7293 | AM6: =AL17 -> 4808.392 | AN6: =AM17 -> 5555.9021 | AO6: =AN17 -> 6571.3134 | AP6: =AO17 -> 7874.3937
A7: Fx | I7: 80 | K7: -223 | M7: -728 | O7: =M7*(1+O8) -> -509.6 | Q7: =O7*(1+Q8) -> -356.72 | S7: =Q7*(1+S8) -> -249.704 | U7: =S7*(1+U8) -> -174.7928 | W7: =U7*(1+W8) -> -122.35496 | Y7: =W7*(1+Y8) -> -85.648472 | AI7: -958 | AJ7: =AI7*(1+AJ8) -> -670.6 | AK7: =AJ7*(1+AK8) -> -469.42 | AL7: =AK7*(1+AL8) -> -328.594 | AM7: =AL7*(1+AM8) -> -230.0158 | AN7: =AM7*(1+AN8) -> -161.01106 | AO7: =AN7*(1+AO8) -> -112.70774 | AP7: =AO7*(1+AP8) -> -78.895419
A8: Fx (%) | F8: =F7/D17 -> #DIV/0! | G8: =G7/E17 -> #DIV/0! | H8: =H7/F17 -> #DIV/0! | I8: =I7/G17 -> 0.054347826 | J8: =J7/H17 -> #DIV/0! | K8: =K7/I17 -> -0.12015086 | L8: =L7/J17 -> #DIV/0! | M8: =M7/K17 -> -0.3699187 | O8: -0.3 | Q8: -0.3 | S8: -0.3 | U8: -0.3 | W8: -0.3 | Y8: -0.3 | AI8: =AI7/AH17 -> -0.239201 | AJ8: -0.3 | AK8: -0.3 | AL8: -0.3 | AM8: -0.3 | AN8: -0.3 | AO8: -0.3 | AP8: -0.3
A9: Scope | I9: -55 | K9: 155 | M9: 137 | O9: =M9*(1+O10) -> 137.959 | Q9: =O9*(1+Q10) -> 138.92471 | S9: =Q9*(1+S10) -> 139.89719 | U9: =S9*(1+U10) -> 140.87647 | W9: =U9*(1+W10) -> 141.8626 | Y9: =W9*(1+Y10) -> 142.85564 | AI9: 716 | AJ9: =AI9*(1+AJ10) -> 721.012 | AK9: =AJ9*(1+AK10) -> 726.05908 | AL9: =AK9*(1+AL10) -> 731.1415 | AM9: =AL9*(1+AM10) -> 736.25949 | AN9: =AM9*(1+AN10) -> 741.4133 | AO9: =AN9*(1+AO10) -> 746.6032 | AP9: =AO9*(1+AP10) -> 751.82942
A10: Scope (%) | F10: =F9/D17 -> #DIV/0! | G10: =G9/E17 -> #DIV/0! | H10: =H9/F17 -> #DIV/0! | I10: =I9/G17 -> -0.03736413 | J10: =J9/H17 -> #DIV/0! | K10: =K9/I17 -> 0.083512931 | L10: =L9/J17 -> #DIV/0! | M10: =M9/K17 -> 0.069613821 | O10: 0.007 | Q10: 0.007 | S10: 0.007 | U10: 0.007 | W10: 0.007 | Y10: 0.007 | AI10: =AI9/AH17 -> 0.17877653 | AJ10: 0.007 | AK10: 0.007 | AL10: 0.007 | AM10: 0.007 | AN10: 0.007 | AO10: 0.007 | AP10: 0.007
A11: Organic Growth | I11: 359 | K11: 180 | M11: 542 | O11: =M11*(1+O12) -> 652.38895 | Q11: =O11*(1+Q12) -> 785.26079 | S11: =Q11*(1+S12) -> 945.19462 | U11: =S11*(1+U12) -> 1137.7022 | W11: =U11*(1+W12) -> 1369.4177 | Y11: =W11*(1+Y12) -> 1648.3267 | AI11: 466 | AJ11: =AI11*(1+AJ12) -> 560.81987 | AK11: =AJ11*(1+AK12) -> 674.92939 | AL11: =AK11*(1+AL12) -> 812.25671 | AM11: =AL11*(1+AM12) -> 977.52591 | AN11: =AM11*(1+AN12) -> 1176.4223 | AO11: =AN11*(1+AO12) -> 1415.7881 | AP11: =AO11*(1+AP12) -> 1703.8575
A12: Organic Growth (%) | E12: =(1+E13)*(1+E15)-1 -> 0 | F12: =(1+F13)*(1+F15)-1 -> 0 | G12: =(1+G13)*(1+G15)-1 -> 0 | H12: =(1+H13)*(1+H15)-1 -> 0 | I12: =(1+I13)*(1+I15)-1 -> 0.240872 | J12: =(1+J13)*(1+J15)-1 -> 0 | K12: =(1+K13)*(1+K15)-1 -> 0.094646 | L12: =(1+L13)*(1+L15)-1 -> 0 | M12: =(1+M13)*(1+M15)-1 -> 0.27514 | O12: =(1+O15)*(1+O13)-1 -> 0.20366964 | Q12: =(1+Q15)*(1+Q13)-1 -> 0.20366967 | S12: =(1+S15)*(1+S13)-1 -> 0.2036697 | U12: =(1+U15)*(1+U13)-1 -> 0.20366974 | W12: =(1+W15)*(1+W13)-1 -> 0.20366977 | Y12: =(1+Y15)*(1+Y13)-1 -> 0.2036698 | AI12: =AI13+AI15 -> 0.118 | AJ12: =(1+AJ15)*(1+AJ13)-1 -> 0.20347611 | AK12: =(1+AK15)*(1+AK13)-1 -> 0.20346912 | AL12: =(1+AL15)*(1+AL13)-1 -> 0.20346915 | AM12: =(1+AM15)*(1+AM13)-1 -> 0.20346918 | AN12: =(1+AN15)*(1+AN13)-1 -> 0.20346921 | AO12: =(1+AO15)*(1+AO13)-1 -> 0.20346924 | AP12: =(1+AP15)*(1+AP13)-1 -> 0.20346928
A13: Price mix | I13: 0.192 | K13: 0.167 | M13: 0.238 | O13: 0.2 | Q13: 0.2 | S13: 0.2 | U13: 0.2 | W13: 0.2 | Y13: 0.2 | AI13: 0.174 | AJ13: 0.2 | AK13: 0.2 | AL13: 0.2 | AM13: 0.2 | AN13: 0.2 | AO13: 0.2 | AP13: 0.2
A15: Volume | I15: 0.041 | K15: -0.062 | M15: 0.03 | O15: =O58 -> 0.0030580357 | Q15: =Q58 -> 0.0030580615 | S15: =S58 -> 0.0030580874 | U15: =U58 -> 0.0030581134 | W15: =W58 -> 0.0030581395 | Y15: =Y58 -> 0.0030581656 | AI15: -0.056 | AJ15: =AJ58 -> 0.0028967611 | AK15: =AK58 -> 0.0028909345 | AL15: =AL58 -> 0.0028909599 | AM15: =AM58 -> 0.0028909855 | AN15: =AN58 -> 0.0028910111 | AO15: =AO58 -> 0.0028910368 | AP15: =AP58 -> 0.0028910625
G17: 1472 | I17: 1856 | K17: 1968 | M17: =M6+M7+M9+M11 -> 1919 | O17: =O6+O7+O11 -> 2061.7889 | Q17: =Q6+Q7+Q11 -> 2490.3297 | S17: =S6+S7+S11 -> 3185.8204 | U17: =U6+U7+U11 -> 4148.7297 | W17: =W6+W7+W11 -> 5395.7925 | Y17: =Y6+Y7+Y11 -> 6958.4707 | AH17: 4005 | AI17: =AI6+AI7+AI9+AI11 -> 4229 | AJ17: =AJ6+AJ7+AJ11 -> 4119.2199 | AK17: =AK6+AK7+AK11 -> 4324.7293 | AL17: =AL6+AL7+AL11 -> 4808.392 | AM17: =AM6+AM7+AM11 -> 5555.9021 | AN17: =AN6+AN7+AN11 -> 6571.3134 | AO17: =AO6+AO7+AO11 -> 7874.3937 | AP17: =AP6+AP7+AP11 -> 9499.3558
I18: =I17/G17-1 -> 0.26086957 | K18: =K17/I17-1 -> 0.060344828 | M18: =M17/K17-1 -> -0.024898374
A20: Net revenue per hectolitre | K20: =M20/1.24 -> 69.088422 | M20: =M17/M51 -> 85.669643
I21: 0.192 | K21: 0.165 | M21: =M20/K20-1 -> 0.24
A22: Beer Volume | G22: 19.1 | I22: =+I24+I26+I28+G22 -> 19.6 | K22: 18.6 | M22: 14.5 | O22: =M22+O24+O26+O28 -> 14.6015 | Q22: =O22+Q24+Q26+Q28 -> 14.70371 | S22: =Q22+S24+S26+S28 -> 14.806636 | U22: =S22+U24+U26+U28 -> 14.910283 | W22: =U22+W24+W26+W28 -> 15.014655 | Y22: =W22+Y24+Y26+Y28 -> 15.119757 | AH22: 39.2 | AI22: 34.8 | AJ22: =AI22+AJ24+AJ26+AJ28 -> 35.0436 | AK22: =AJ22+AK24+AK26+AK28 -> 35.288905 | AL22: =AK22+AL24+AL26+AL28 -> 35.535928 | AM22: =AL22+AM24+AM26+AM28 -> 35.784679 | AN22: =AM22+AN24+AN26+AN28 -> 36.035172 | AO22: =AN22+AO24+AO26+AO28 -> 36.287418 | AP22: =AO22+AP24+AP26+AP28 -> 36.54143
G23: =G22/E22-1 -> #DIV/0! | H23: =H22/F22-1 -> #DIV/0! | I23: =I22/G22-1 -> 0.02617801 | J23: =J22/H22-1 -> #DIV/0! | K23: =K22/I22-1 -> -0.051020408 | L23: =L22/J22-1 -> #DIV/0! | M23: =M22/K22-1 -> -0.22043011
A24: FX | I24: 0 | K24: 0 | M24: 0 | O24: =O25*M22 -> 0 | Q24: =Q25*O22 -> 0 | S24: =S25*Q22 -> 0 | U24: =U25*S22 -> 0 | W24: =W25*U22 -> 0 | Y24: =Y25*W22 -> 0 | AI24: 0 | AJ24: =AJ25*AI22 -> 0 | AK24: =AK25*AJ22 -> 0 | AL24: =AL25*AK22 -> 0 | AM24: =AM25*AL22 -> 0 | AN24: =AN25*AM22 -> 0 | AO24: =AO25*AN22 -> 0 | AP24: =AP25*AO22 -> 0
A25: Fx (%) | G25: =G24/E22 -> #DIV/0! | H25: =H24/F22 -> #DIV/0! | I25: =I24/G22 -> 0 | J25: =J24/H22 -> #DIV/0! | K25: =K24/I22 -> 0 | L25: =L24/J22 -> #DIV/0! | M25: =M24/K22 -> 0 | O25: 0 | Q25: 0 | S25: 0 | U25: 0 | W25: 0 | Y25: 0 | AI25: =AI24/AH22 -> 0 | AJ25: 0 | AK25: 0 | AL25: 0 | AM25: 0 | AN25: 0 | AO25: 0 | AP25: 0
A26: Scope | I26: -0.2 | K26: 0.2 | M26: -4.4 | O26: =O27*M22 -> 0.0725 | Q26: =Q27*O22 -> 0.0730075 | S26: =S27*Q22 -> 0.073518553 | U26: =U27*S22 -> 0.074033182 | W26: =W27*U22 -> 0.074551415 | Y26: =Y27*W22 -> 0.075073275 | AI26: -2 | AJ26: =AJ27*AI22 -> 0.174 | AK26: =AK27*AJ22 -> 0.175218 | AL26: =AL27*AK22 -> 0.17644453 | AM26: =AM27*AL22 -> 0.17767964 | AN26: =AN27*AM22 -> 0.1789234 | AO26: =AO27*AN22 -> 0.18017586 | AP26: =AP27*AO22 -> 0.18143709
A27: Scope (%) | G27: =G26/E22 -> #DIV/0! | H27: =H26/F22 -> #DIV/0! | I27: =I26/G22 -> -0.010471204 | J27: =J26/H22 -> #DIV/0! | K27: =K26/I22 -> 0.010204082 | L27: =L26/J22 -> #DIV/0! | M27: =M26/K22 -> -0.23655914 | O27: 0.005 | Q27: 0.005 | S27: 0.005 | U27: 0.005 | W27: 0.005 | Y27: 0.005 | AI27: =AI26/AH22 -> -0.051020408 | AJ27: 0.005 | AK27: 0.005 | AL27: 0.005 | AM27: 0.005 | AN27: 0.005 | AO27: 0.005 | AP27: 0.005
A28: Organic Growth | I28: 0.7 | K28: -1.3 | M28: 0.3 | O28: =O29*M22 -> 0.029 | Q28: =Q29*O22 -> 0.029203 | S28: =S29*Q22 -> 0.029407421 | U28: =U29*S22 -> 0.029613273 | W28: =W29*U22 -> 0.029820566 | Y28: =Y29*W22 -> 0.03002931 | AI28: -2.5 | AJ28: =AJ29*AI22 -> 0.0696 | AK28: =AK29*AJ22 -> 0.0700872 | AL28: =AL29*AK22 -> 0.07057781 | AM28: =AM29*AL22 -> 0.071071855 | AN28: =AN29*AM22 -> 0.071569358 | AO28: =AO29*AN22 -> 0.072070344 | AP28: =AP29*AO22 -> 0.072574836
A29: Organic Growth (%) | G29: =G28/E22 -> #DIV/0! | H29: =H28/F22 -> #DIV/0! | I29: =I28/G22 -> 0.036649215 | J29: =J28/H22 -> #DIV/0! | K29: =K28/I22 -> -0.066326531 | L29: =L28/J22 -> #DIV/0! | M29: =M28/K22 -> 0.016129032 | O29: 0.002 | Q29: 0.002 | S29: 0.002 | U29: 0.002 | W29: 0.002 | Y29: 0.002 | AI29: =AI28/AH22 -> -0.06377551 | AJ29: 0.002 | AK29: 0.002 | AL29: 0.002 | AM29: 0.002 | AN29: 0.002 | AO29: 0.002 | AP29: 0.002
A31: Non-Beer Volume | G31: 5.3 | I31: 5.6 | K31: 5.6 | M31: 7.8 | O31: =M31+O33+O35+O37 -> 7.8546 | Q31: =O31+Q33+Q35+Q37 -> 7.9095822 | S31: =Q31+S33+S35+S37 -> 7.9649493 | U31: =S31+U33+U35+U37 -> 8.0207039 | W31: =U31+W33+W35+W37 -> 8.0768488 | Y31: =W31+Y33+Y35+Y37 -> 8.1333868 | AH31: 11.5 | AI31: 14.5 | AJ31: =AI31+AJ33+AJ35+AJ37 -> 14.6015 | AK31: =AJ31+AK33+AK35+AK37 -> 14.70371 | AL31: =AK31+AL33+AL35+AL37 -> 14.806636 | AM31: =AL31+AM33+AM35+AM37 -> 14.910283 | AN31: =AM31+AN33+AN35+AN37 -> 15.014655 | AO31: =AN31+AO33+AO35+AO37 -> 15.119757 | AP31: =AO31+AP33+AP35+AP37 -> 15.225596
G32: =G31/E31-1 -> #DIV/0! | H32: =H31/F31-1 -> #DIV/0! | I32: =I31/G31-1 -> 0.056603774 | J32: =J31/H31-1 -> #DIV/0! | K32: =K31/I31-1 -> 0 | L32: =L31/J31-1 -> #DIV/0! | M32: =M31/K31-1 -> 0.39285714
A33: FX | I33: 0 | K33: 0 | M33: 0 | O33: =O34*M31 -> 0 | Q33: =Q34*O31 -> 0 | S33: =S34*Q31 -> 0 | U33: =U34*S31 -> 0 | W33: =W34*U31 -> 0 | Y33: =Y34*W31 -> 0 | AI33: 0 | AJ33: =AJ34*AI31 -> 0 | AK33: =AK34*AJ31 -> 0 | AL33: =AL34*AK31 -> 0 | AM33: =AM34*AL31 -> 0 | AN33: =AN34*AM31 -> 0 | AO33: =AO34*AN31 -> 0 | AP33: =AP34*AO31 -> 0
A34: Fx (%) | G34: =G33/E31 -> #DIV/0! | H34: =H33/F31 -> #DIV/0! | I34: =I33/G31 -> 0 | J34: =J33/H31 -> #DIV/0! | K34: =K33/I31 -> 0 | L34: =L33/J31 -> #DIV/0! | M34: =M33/K31 -> 0 | O34: 0 | Q34: 0 | S34: 0 | U34: 0 | W34: 0 | Y34: 0 | AI34: =AI33/AH31 -> 0 | AJ34: 0 | AK34: 0 | AL34: 0 | AM34: 0 | AN34: 0 | AO34: 0 | AP34: 0
A35: Scope | I35: 0 | K35: 0.3 | M35: 1.8 | O35: =O36*M31 -> 0.0156 | Q35: =Q36*O31 -> 0.0157092 | S35: =S36*Q31 -> 0.015819164 | U35: =U36*S31 -> 0.015929899 | W35: =W36*U31 -> 0.016041408 | Y35: =Y36*W31 -> 0.016153698 | AI35: 3.4 | AJ35: =AJ36*AI31 -> 0.029 | AK35: =AK36*AJ31 -> 0.029203 | AL35: =AL36*AK31 -> 0.029407421 | AM35: =AM36*AL31 -> 0.029613273 | AN35: =AN36*AM31 -> 0.029820566 | AO35: =AO36*AN31 -> 0.03002931 | AP35: =AP36*AO31 -> 0.030239515
A36: Scope (%) | G36: =G35/E31 -> #DIV/0! | H36: =H35/F31 -> #DIV/0! | I36: =I35/G31 -> 0 | J36: =J35/H31 -> #DIV/0! | K36: =K35/I31 -> 0.053571429 | L36: =L35/J31 -> #DIV/0! | M36: =M35/K31 -> 0.32142857 | O36: 0.002 | Q36: 0.002 | S36: 0.002 | U36: 0.002 | W36: 0.002 | Y36: 0.002 | AI36: =AI35/AH31 -> 0.29565217 | AJ36: 0.002 | AK36: 0.002 | AL36: 0.002 | AM36: 0.002 | AN36: 0.002 | AO36: 0.002 | AP36: 0.002
A37: Organic Growth | I37: 0.3 | K37: -0.3 | M37: 0.4 | O37: =O38*M31 -> 0.039 | Q37: =Q38*O31 -> 0.039273 | S37: =S38*Q31 -> 0.039547911 | U37: =U38*S31 -> 0.039824746 | W37: =W38*U31 -> 0.04010352 | Y37: =Y38*W31 -> 0.040384244 | AI37: -0.4 | AJ37: =AJ38*AI31 -> 0.0725 | AK37: =AK38*AJ31 -> 0.0730075 | AL37: =AL38*AK31 -> 0.073518553 | AM37: =AM38*AL31 -> 0.074033182 | AN37: =AN38*AM31 -> 0.074551415 | AO37: =AO38*AN31 -> 0.075073275 | AP37: =AP38*AO31 -> 0.075598787
A38: Organic Growth (%) | G38: =G37/E31 -> #DIV/0! | H38: =H37/F31 -> #DIV/0! | I38: =I37/G31 -> 0.056603774 | J38: =J37/H31 -> #DIV/0! | K38: =K37/I31 -> -0.053571429 | L38: =L37/J31 -> #DIV/0! | M38: =M37/K31 -> 0.071428571 | O38: 0.005 | Q38: 0.005 | S38: 0.005 | U38: 0.005 | W38: 0.005 | Y38: 0.005 | AI38: =AI37/AH31 -> -0.034782609 | AJ38: 0.005 | AK38: 0.005 | AL38: 0.005 | AM38: 0.005 | AN38: 0.005 | AO38: 0.005 | AP38: 0.005
A41: Third Party products volume | I41: 0 | K41: 0 | M41: 0.1 | O41: =M41+O43+O45+O47 -> 0.101 | Q41: =O41+Q43+Q45+Q47 -> 0.10201 | S41: =Q41+S43+S45+S47 -> 0.1030301 | U41: =S41+U43+U45+U47 -> 0.1040604 | W41: =U41+W43+W45+W47 -> 0.10510101 | Y41: =W41+Y43+Y45+Y47 -> 0.10615202 | AH41: 0.1 | AI41: 0.2 | AJ41: =AI41+AJ43+AJ45+AJ47 -> 0.202 | AK41: =AJ41+AK43+AK45+AK47 -> 0.20402 | AL41: =AK41+AL43+AL45+AL47 -> 0.2060602 | AM41: =AL41+AM43+AM45+AM47 -> 0.2081208 | AN41: =AM41+AN43+AN45+AN47 -> 0.21020201 | AO41: =AN41+AO43+AO45+AO47 -> 0.21230403 | AP41: =AO41+AP43+AP45+AP47 -> 0.21442707
G42: =IFERROR(G41/E41-1, "-") -> - | H42: =IFERROR(H41/F41-1, "-") -> - | I42: =IFERROR(I41/G41-1, "-") -> - | J42: =IFERROR(J41/H41-1, "-") -> - | K42: =IFERROR(K41/I41-1, "-") -> - | L42: =IFERROR(L41/J41-1, "-") -> - | M42: =IFERROR(M41/K41-1, "-") -> -
A43: FX | M43: 0 | O43: =O44*M41 -> 0 | Q43: =Q44*O41 -> 0 | S43: =S44*Q41 -> 0 | U43: =U44*S41 -> 0 | W43: =W44*U41 -> 0 | Y43: =Y44*W41 -> 0 | AI43: 0 | AJ43: =AJ44*AI41 -> 0 | AK43: =AK44*AJ41 -> 0 | AL43: =AL44*AK41 -> 0 | AM43: =AM44*AL41 -> 0 | AN43: =AN44*AM41 -> 0 | AO43: =AO44*AN41 -> 0 | AP43: =AP44*AO41 -> 0
A44: Fx (%) | G44: =IFERROR(G43/E41,"-") -> - | H44: =IFERROR(H43/F41,"-") -> - | I44: =IFERROR(I43/G41,"-") -> - | J44: =IFERROR(J43/H41,"-") -> - | K44: =IFERROR(K43/I41,"-") -> - | L44: =IFERROR(L43/J41,"-") -> - | M44: =IFERROR(M43/K41,"-") -> - | O44: 0 | Q44: 0 | S44: 0 | U44: 0 | W44: 0 | Y44: 0 | AI44: =AI43/AH41 -> 0 | AJ44: 0 | AK44: 0 | AL44: 0 | AM44: 0 | AN44: 0 | AO44: 0 | AP44: 0
A45: Scope | M45: 1.8 | O45: =O46*M41 -> 0.0005 | Q45: =Q46*O41 -> 0.000505 | S45: =S46*Q41 -> 0.00051005 | U45: =U46*S41 -> 0.0005151505 | W45: =W46*U41 -> 0.00052030201 | Y45: =Y46*W41 -> 0.00052550503 | AI45: 0.1 | AJ45: =AJ46*AI41 -> 0.001 | AK45: =AK46*AJ41 -> 0.00101 | AL45: =AL46*AK41 -> 0.0010201 | AM45: =AM46*AL41 -> 0.001030301 | AN45: =AN46*AM41 -> 0.001040604 | AO45: =AO46*AN41 -> 0.0010510101 | AP45: =AP46*AO41 -> 0.0010615202
A46: Scope (%) | G46: =IFERROR(G45/E41,"-") -> - | H46: =IFERROR(H45/F41,"-") -> - | I46: =IFERROR(I45/G41,"-") -> - | J46: =IFERROR(J45/H41,"-") -> - | K46: =IFERROR(K45/I41,"-") -> - | L46: =IFERROR(L45/J41,"-") -> - | M46: =IFERROR(M45/K41,"-") -> - | O46: 0.005 | Q46: 0.005 | S46: 0.005 | U46: 0.005 | W46: 0.005 | Y46: 0.005 | AI46: =AI45/AH41 -> 1 | AJ46: 0.005 | AK46: 0.005 | AL46: 0.005 | AM46: 0.005 | AN46: 0.005 | AO46: 0.005 | AP46: 0.005
A47: Organic Growth | M47: 0.4 | O47: =O48*M41 -> 0.0005 | Q47: =Q48*O41 -> 0.000505 | S47: =S48*Q41 -> 0.00051005 | U47: =U48*S41 -> 0.0005151505 | W47: =W48*U41 -> 0.00052030201 | Y47: =Y48*W41 -> 0.00052550503 | AI47: 0 | AJ47: =AJ48*AI41 -> 0.001 | AK47: =AK48*AJ41 -> 0.00101 | AL47: =AL48*AK41 -> 0.0010201 | AM47: =AM48*AL41 -> 0.001030301 | AN47: =AN48*AM41 -> 0.001040604 | AO47: =AO48*AN41 -> 0.0010510101 | AP47: =AP48*AO41 -> 0.0010615202
A48: Organic Growth (%) | G48: =IFERROR(G47/E41,"-") -> - | H48: =IFERROR(H47/F41,"-") -> - | I48: =IFERROR(I47/G41,"-") -> - | J48: =IFERROR(J47/H41,"-") -> - | K48: =IFERROR(K47/I41,"-") -> - | L48: =IFERROR(L47/J41,"-") -> - | M48: =IFERROR(M47/K41,"-") -> - | O48: 0.005 | Q48: 0.005 | S48: 0.005 | U48: 0.005 | W48: 0.005 | Y48: 0.005 | AI48: 0.624 | AJ48: 0.005 | AK48: 0.005 | AL48: 0.005 | AM48: 0.005 | AN48: 0.005 | AO48: 0.005 | AP48: 0.005
A51: Total Volume | G51: 24.5 | I51: 25.3 | K51: =K22+K31+K41 -> 24.2 | M51: =M22+M31+M41 -> 22.4 | O51: =O22+O31+O41 -> 22.5571 | Q51: =Q22+Q31+Q41 -> 22.715303 | S51: =S22+S31+S41 -> 22.874616 | U51: =U22+U31+U41 -> 23.035047 | W51: =W22+W31+W41 -> 23.196605 | Y51: =Y22+Y31+Y41 -> 23.359296 | AH51: 50.8 | AI51: 49.4 | AJ51: =AJ22+AJ31+AJ41 -> 49.8471 | AK51: =AK22+AK31+AK41 -> 50.196636 | AL51: =AL22+AL31+AL41 -> 50.548624 | AM51: =AM22+AM31+AM41 -> 50.903083 | AN51: =AN22+AN31+AN41 -> 51.260029 | AO51: =AO22+AO31+AO41 -> 51.61948 | AP51: =AP22+AP31+AP41 -> 51.981453
G52: =IFERROR(G51/E51-1, "-") -> - | H52: =IFERROR(H51/F51-1, "-") -> - | I52: =IFERROR(I51/G51-1, "-") -> 0.032653061 | J52: =IFERROR(J51/H51-1, "-") -> - | K52: =IFERROR(K51/I51-1, "-") -> -0.043478261 | L52: =IFERROR(L51/J51-1, "-") -> - | M52: =IFERROR(M51/K51-1, "-") -> -0.074380165
A53: FX | I53: 0 | K53: 0 | M53: 0 | O53: =O24+O33+O43 -> 0 | Q53: =Q24+Q33+Q43 -> 0 | S53: =S24+S33+S43 -> 0 | U53: =U24+U33+U43 -> 0 | W53: =W24+W33+W43 -> 0 | Y53: =Y24+Y33+Y43 -> 0 | AI53: 0 | AJ53: =AJ24+AJ33+AJ43 -> 0 | AK53: =AK24+AK33+AK43 -> 0 | AL53: =AL24+AL33+AL43 -> 0 | AM53: =AM24+AM33+AM43 -> 0 | AN53: =AN24+AN33+AN43 -> 0 | AO53: =AO24+AO33+AO43 -> 0 | AP53: =AP24+AP33+AP43 -> 0
A54: Fx (%) | G54: =IFERROR(G53/E51,"-") -> - | H54: =IFERROR(H53/F51,"-") -> - | I54: =IFERROR(I53/G51,"-") -> 0 | J54: =IFERROR(J53/H51,"-") -> - | K54: =IFERROR(K53/I51,"-") -> 0 | L54: =IFERROR(L53/J51,"-") -> - | M54: =IFERROR(M53/K51,"-") -> 0 | O54: =O53/M51 -> 0 | Q54: =Q53/O51 -> 0 | S54: =S53/Q51 -> 0 | U54: =U53/S51 -> 0 | W54: =W53/U51 -> 0 | Y54: =Y53/W51 -> 0 | AI54: =AI53/AH51 -> 0 | AJ54: =AJ53/AI51 -> 0 | AK54: =AK53/AJ51 -> 0 | AL54: =AL53/AK51 -> 0 | AM54: =AM53/AL51 -> 0 | AN54: =AN53/AM51 -> 0 | AO54: =AO53/AN51 -> 0 | AP54: =AP53/AO51 -> 0
A55: Scope | I55: -0.2 | K55: 0.5 | M55: -2.6 | O55: =O26+O35+O45 -> 0.0886 | Q55: =Q26+Q35+Q45 -> 0.0892217 | S55: =S26+S35+S45 -> 0.089847767 | U55: =U26+U35+U45 -> 0.090478231 | W55: =W26+W35+W45 -> 0.091113124 | Y55: =Y26+Y35+Y45 -> 0.091752477 | AI55: 1.5 | AJ55: =AJ26+AJ35+AJ45 -> 0.204 | AK55: =AK26+AK35+AK45 -> 0.205431 | AL55: =AL26+AL35+AL45 -> 0.20687205 | AM55: =AM26+AM35+AM45 -> 0.20832321 | AN55: =AN26+AN35+AN45 -> 0.20978457 | AO55: =AO26+AO35+AO45 -> 0.21125618 | AP55: =AP26+AP35+AP45 -> 0.21273813
A56: Scope (%) | G56: =IFERROR(G55/E51,"-") -> - | H56: =IFERROR(H55/F51,"-") -> - | I56: =IFERROR(I55/G51,"-") -> -0.0081632653 | J56: =IFERROR(J55/H51,"-") -> - | K56: =IFERROR(K55/I51,"-") -> 0.019762846 | L56: =IFERROR(L55/J51,"-") -> - | M56: =IFERROR(M55/K51,"-") -> -0.10743802 | O56: =O55/M51 -> 0.0039553571 | Q56: =Q55/O51 -> 0.003955371 | S56: =S55/Q51 -> 0.003955385 | U56: =U55/S51 -> 0.0039553989 | W56: =W55/U51 -> 0.003955413 | Y56: =Y55/W51 -> 0.003955427 | AI56: =AI55/AH51 -> 0.029527559 | AJ56: =AJ55/AI51 -> 0.0041295547 | AK56: =AK55/AJ51 -> 0.0041212227 | AL56: =AL55/AK51 -> 0.0041212333 | AM56: =AM55/AL51 -> 0.0041212439 | AN56: =AN55/AM51 -> 0.0041212546 | AO56: =AO55/AN51 -> 0.0041212653 | AP56: =AP55/AO51 -> 0.0041212761
A57: Organic Growth | I57: 1 | K57: -1.6 | M57: 0.7 | O57: =O28+O37+O47 -> 0.0685 | Q57: =Q28+Q37+Q47 -> 0.068981 | S57: =S28+S37+S47 -> 0.069465382 | U57: =U28+U37+U47 -> 0.06995317 | W57: =W28+W37+W47 -> 0.070444387 | Y57: =Y28+Y37+Y47 -> 0.070939059 | AI57: -2.8 | AJ57: =AJ28+AJ37+AJ47 -> 0.1431 | AK57: =AK28+AK37+AK47 -> 0.1441047 | AL57: =AL28+AL37+AL47 -> 0.14511646 | AM57: =AM28+AM37+AM47 -> 0.14613534 | AN57: =AN28+AN37+AN47 -> 0.14716138 | AO57: =AO28+AO37+AO47 -> 0.14819463 | AP57: =AP28+AP37+AP47 -> 0.14923514
A58: Organic Growth (%) | G58: =IFERROR(G57/E51,"-") -> - | H58: =IFERROR(H57/F51,"-") -> - | I58: =IFERROR(I57/G51,"-") -> 0.040816327 | J58: =IFERROR(J57/H51,"-") -> - | K58: =IFERROR(K57/I51,"-") -> -0.063241107 | L58: =IFERROR(L57/J51,"-") -> - | M58: =IFERROR(M57/K51,"-") -> 0.02892562 | O58: =O57/M51 -> 0.0030580357 | Q58: =Q57/O51 -> 0.0030580615 | S58: =S57/Q51 -> 0.0030580874 | U58: =U57/S51 -> 0.0030581134 | W58: =W57/U51 -> 0.0030581395 | Y58: =Y57/W51 -> 0.0030581656 | AI58: =AI57/AH51 -> -0.05511811 | AJ58: =AJ57/AI51 -> 0.0028967611 | AK58: =AK57/AJ51 -> 0.0028909345 | AL58: =AL57/AK51 -> 0.0028909599 | AM58: =AM57/AL51 -> 0.0028909855 | AN58: =AN57/AM51 -> 0.0028910111 | AO58: =AO57/AN51 -> 0.0028910368 | AP58: =AP57/AO51 -> 0.0028910625
A60: Licensed Beer Volume | G60: 1.1 | I60: 1.1 | K60: 1.2 | M60: 0.7 | AH60: 2.5 | AI60: 2.4
A62: Group Beer Volume | G62: 20.4 | I62: 21 | K62: 19.9 | M62: 15.4 | AH62: 42.2 | AI62: 37.7
M66: =M8+M10+M12-M18 -> -0.00026650407

Sheet Americas
B1: ='Cash Flow Statement'!B1 -> H1'19 | C1: ='Cash Flow Statement'!C1 -> H2'19 | D1: ='Cash Flow Statement'!D1 -> FY'19 | E1: ='Cash Flow Statement'!E1 -> H1'20 | F1: ='Cash Flow Statement'!F1 -> H2'20 | G1: ='Cash Flow Statement'!G1 -> H1'21 | H1: ='Cash Flow Statement'!H1 -> H2'21 | I1: ='Cash Flow Statement'!I1 -> H1'22 | ... Z1: ='Cash Flow Statement'!Z1 -> H2'30 | AE1: ='Cash Flow Statement'!AE1 -> FY'20 | AF1: ='Cash Flow Statement'!AF1 -> FY'21 | AG1: ='Cash Flow Statement'!AG1 -> FY'22 | AH1: ='Cash Flow Statement'!AH1 -> FY'23 | AI1: ='Cash Flow Statement'!AI1 -> FY'24 | AJ1: ='Cash Flow Statement'!AJ1 -> FY'25 | AK1: ='Cash Flow Statement'!AK1 -> FY'26 | AL1: ='Cash Flow Statement'!AL1 -> FY'27 | ... AO1: ='Cash Flow Statement'!AO1 -> FY'30
A4: Americas
A6: Net Revenue (beia) | I6: =G17 -> 3344 | K6: =I17 -> 4288 | M6: =K17 -> 4893 | O6: =M17 -> 5247 | Q6: =O17 -> 5594.2899 | S6: =Q17 -> 5957.0269 | U6: =S17 -> 6354.7997 | W6: =U17 -> 6806.225 | Y6: =W17 -> 7330.2318 | AH6: =AG17 -> 9421 | AI6: =AH17 -> 10469 | AJ6: =AI17 -> 11552.824 | AK6: =AJ17 -> 12732.637 | AL6: =AK17 -> 14064.913 | AM6: =AL17 -> 15606.449 | AN6: =AM17 -> 17417.761 | AO6: =AN17 -> 19566.179
A7: Fx | I7: 414 | K7: 238 | M7: 156 | O7: =M7*(1+O8) -> 109.2 | Q7: =O7*(1+Q8) -> 76.44 | S7: =Q7*(1+S8) -> 53.508 | U7: =S7*(1+U8) -> 37.4556 | W7: =U7*(1+W8) -> 26.21892 | Y7: =W7*(1+Y8) -> 18.353244 | AH7: 351 | AI7: =AH7*(1+AI8) -> 245.7 | AJ7: =AI7*(1+AJ8) -> 171.99 | AK7: =AJ7*(1+AK8) -> 120.393 | AL7: =AK7*(1+AL8) -> 84.2751 | AM7: =AL7*(1+AM8) -> 58.99257 | AN7: =AM7*(1+AN8) -> 41.294799 | AO7: =AN7*(1+AO8) -> 28.906359
A8: Fx (%) | G8: =G7/E17 -> #DIV/0! | H8: =H7/F17 -> #DIV/0! | I8: =I7/G17 -> 0.12380383 | J8: =J7/H17 -> #DIV/0! | K8: =K7/I17 -> 0.055503731 | L8: =L7/J17 -> #DIV/0! | M8: =M7/K17 -> 0.031882281 | O8: -0.3 | Q8: -0.3 | S8: -0.3 | U8: -0.3 | W8: -0.3 | Y8: -0.3 | AH8: =AH7/AG17 -> 0.037257191 | AI8: -0.3 | AJ8: -0.3 | AK8: -0.3 | AL8: -0.3 | AM8: -0.3 | AN8: -0.3 | AO8: -0.3
A9: Scope | I9: 0 | M9: 0 | O9: =M9*(1+O10) -> 0 | Q9: =O9*(1+Q10) -> 0 | S9: =Q9*(1+S10) -> 0 | U9: =S9*(1+U10) -> 0 | W9: =U9*(1+W10) -> 0 | Y9: =W9*(1+Y10) -> 0 | AH9: 0 | AI9: =AH9*(1+AI10) -> 0 | AJ9: =AI9*(1+AJ10) -> 0 | AK9: =AJ9*(1+AK10) -> 0 | AL9: =AK9*(1+AL10) -> 0 | AM9: =AL9*(1+AM10) -> 0 | AN9: =AM9*(1+AN10) -> 0 | AO9: =AN9*(1+AO10) -> 0
A10: Scope (%) | G10: =G9/E17 -> #DIV/0! | H10: =H9/F17 -> #DIV/0! | I10: =I9/G17 -> 0 | J10: =J9/H17 -> #DIV/0! | K10: =K9/I17 -> 0 | L10: =L9/J17 -> #DIV/0! | M10: =M9/K17 -> 0 | O10: 0.007 | Q10: 0.007 | S10: 0.007 | U10: 0.007 | W10: 0.007 | Y10: 0.007 | AH10: =AH9/AG17 -> 0 | AI10: 0.007 | AJ10: 0.007 | AK10: 0.007 | AL10: 0.007 | AM10: 0.007 | AN10: 0.007 | AO10: 0.007
A11: Organic Growth | I11: 529 | K11: 367 | M11: 198 | O11: =M11*(1+O12) -> 238.08991 | Q11: =O11*(1+Q12) -> 286.29701 | S11: =Q11*(1+S12) -> 344.26482 | U11: =S11*(1+U12) -> 413.96962 | W11: =U11*(1+W12) -> 497.78788 | Y11: =W11*(1+Y12) -> 598.57719 | AH11: 697 | AI11: =AH11*(1+AI12) -> 838.12369 | AJ11: =AI11*(1+AJ12) -> 1007.8234 | AK11: =AJ11*(1+AK12) -> 1211.8832 | AL11: =AK11*(1+AL12) -> 1457.2602 | AM11: =AL11*(1+AM12) -> 1752.3202 | AN11: =AM11*(1+AN12) -> 2107.1226 | AO11: =AN11*(1+AO12) -> 2533.764
A12: Organic Growth (%) | G12: =G11/E17 -> #DIV/0! | H12: =H11/F17 -> #DIV/0! | I12: =I11/G17 -> 0.15819378 | J12: =J11/H17 -> #DIV/0! | K12: =K11/I17 -> 0.085587687 | L12: =L11/J17 -> #DIV/0! | M12: =M11/K17 -> 0.040465972 | O12: =(1+O15)*(1+O13)-1 -> 0.20247431 | Q12: =(1+Q15)*(1+Q13)-1 -> 0.20247434 | S12: =(1+S15)*(1+S13)-1 -> 0.20247436 | U12: =(1+U15)*(1+U13)-1 -> 0.20247438 | W12: =(1+W15)*(1+W13)-1 -> 0.20247441 | Y12: =(1+Y15)*(1+Y13)-1 -> 0.20247443 | AH12: =AH11/AG17 -> 0.073983654 | AI12: =(1+AI15)*(1+AI13)-1 -> 0.20247301 | AJ12: =(1+AJ15)*(1+AJ13)-1 -> 0.20247576 | AK12: =(1+AK15)*(1+AK13)-1 -> 0.20247577 | AL12: =(1+AL15)*(1+AL13)-1 -> 0.20247578 | AM12: =(1+AM15)*(1+AM13)-1 -> 0.20247579 | AN12: =(1+AN15)*(1+AN13)-1 -> 0.20247581 | AO12: =(1+AO15)*(1+AO13)-1 -> 0.20247582
A13: Price mix | I13: 0.143 | K13: 0.113 | M13: 0.038 | O13: 0.2 | Q13: 0.2 | S13: 0.2 | U13: 0.2 | W13: 0.2 | Y13: 0.2 | AH13: 0.084 | AI13: 0.2 | AJ13: 0.2 | AK13: 0.2 | AL13: 0.2 | AM13: 0.2 | AN13: 0.2 | AO13: 0.2
A15: Volume | I15: 0.031 | K15: -0.017 | M15: 0.008 | O15: =O58 -> 0.0020619266 | Q15: =Q58 -> 0.0020619467 | S15: =S58 -> 0.0020619668 | U15: =U58 -> 0.002061987 | W15: =W58 -> 0.0020620073 | Y15: =Y58 -> 0.0020620276 | AH15: -0.002 | AI15: =AI58 -> 0.0020608407 | AJ15: =AJ58 -> 0.0020631326 | AK15: =AK58 -> 0.0020631423 | AL15: =AL58 -> 0.0020631521 | AM15: =AM58 -> 0.0020631619 | AN15: =AN58 -> 0.0020631717 | AO15: =AO58 -> 0.0020631815
G17: 3344 | I17: 4288 | K17: 4893 | M17: 5247 | O17: =O6+O7+O11 -> 5594.2899 | Q17: =Q6+Q7+Q11 -> 5957.0269 | S17: =S6+S7+S11 -> 6354.7997 | U17: =U6+U7+U11 -> 6806.225 | W17: =W6+W7+W11 -> 7330.2318 | Y17: =Y6+Y7+Y11 -> 7947.1622 | AG17: 9421 | AH17: =AH6+AH7+AH9+AH11 -> 10469 | AI17: =AI6+AI7+AI11 -> 11552.824 | AJ17: =AJ6+AJ7+AJ11 -> 12732.637 | AK17: =AK6+AK7+AK11 -> 14064.913 | AL17: =AL6+AL7+AL11 -> 15606.449 | AM17: =AM6+AM7+AM11 -> 17417.761 | AN17: =AN6+AN7+AN11 -> 19566.179 | AO17: =AO6+AO7+AO11 -> 22128.849
G18: =G17/E17-1 -> #DIV/0! | H18: =H17/F17-1 -> #DIV/0! | I18: =I17/G17-1 -> 0.28229665 | J18: =J17/H17-1 -> #DIV/0! | K18: =K17/I17-1 -> 0.14109142 | L18: =L17/J17-1 -> #DIV/0! | M18: =M17/K17-1 -> 0.072348253
A20: Net revenue per hl growth | K20: =M20/(1+M21) -> 116.49955 | M20: =M17/M51 -> 120.34404
I21: 0.128 | K21: 0.11 | M21: 0.033
A22: Beer Volume | G22: 40.3 | I22: 42.8 | K22: =I22+K24+K26+K28 -> 42.2 | M22: 42.7 | O22: =M22+O24+O26+O28 -> 42.9989 | Q22: =O22+Q24+Q26+Q28 -> 43.299892 | S22: =Q22+S24+S26+S28 -> 43.602992 | U22: =S22+U24+U26+U28 -> 43.908212 | W22: =U22+W24+W26+W28 -> 44.21557 | Y22: =W22+Y24+Y26+Y28 -> 44.525079 | AG22: 88.5 | AH22: 88.4 | AI22: =AH22+AI24+AI26+AI28 -> 89.0188 | AJ22: =AI22+AJ24+AJ26+AJ28 -> 89.641932 | AK22: =AJ22+AK24+AK26+AK28 -> 90.269425 | AL22: =AK22+AL24+AL26+AL28 -> 90.901311 | AM22: =AL22+AM24+AM26+AM28 -> 91.53762 | AN22: =AM22+AN24+AN26+AN28 -> 92.178384 | AO22: =AN22+AO24+AO26+AO28 -> 92.823632
G23: =G22/E22-1 -> #DIV/0! | H23: =H22/F22-1 -> #DIV/0! | I23: =I22/G22-1 -> 0.062034739 | J23: =J22/H22-1 -> #DIV/0! | K23: =K22/I22-1 -> -0.014018692 | L23: =L22/J22-1 -> #DIV/0! | M23: =M22/K22-1 -> 0.011848341
A24: FX | I24: 0 | K24: 0 | M24: 0 | O24: =O25*M22 -> 0 | Q24: =Q25*O22 -> 0 | S24: =S25*Q22 -> 0 | U24: =U25*S22 -> 0 | W24: =W25*U22 -> 0 | Y24: =Y25*W22 -> 0 | AH24: 0 | AI24: =AI25*AH22 -> 0 | AJ24: =AJ25*AI22 -> 0 | AK24: =AK25*AJ22 -> 0 | AL24: =AL25*AK22 -> 0 | AM24: =AM25*AL22 -> 0 | AN24: =AN25*AM22 -> 0 | AO24: =AO25*AN22 -> 0
A25: Fx (%) | G25: =G24/E22 -> #DIV/0! | H25: =H24/F22 -> #DIV/0! | I25: =I24/G22 -> 0 | J25: =J24/H22 -> #DIV/0! | K25: =K24/I22 -> 0 | L25: =L24/J22 -> #DIV/0! | M25: =M24/K22 -> 0 | O25: 0 | Q25: 0 | S25: 0 | U25: 0 | W25: 0 | Y25: 0 | AH25: =AH24/AG22 -> 0 | AI25: 0 | AJ25: 0 | AK25: 0 | AL25: 0 | AM25: 0 | AN25: 0 | AO25: 0
A26: Scope | I26: 0 | K26: 0 | M26: 0.1 | O26: =O27*M22 -> 0.2135 | Q26: =Q27*O22 -> 0.2149945 | S26: =S27*Q22 -> 0.21649946 | U26: =U27*S22 -> 0.21801496 | W26: =W27*U22 -> 0.21954106 | Y26: =Y27*W22 -> 0.22107785 | AH26: 0 | AI26: =AI27*AH22 -> 0.442 | AJ26: =AJ27*AI22 -> 0.445094 | AK26: =AK27*AJ22 -> 0.44820966 | AL26: =AL27*AK22 -> 0.45134713 | AM26: =AM27*AL22 -> 0.45450656 | AN26: =AN27*AM22 -> 0.4576881 | AO26: =AO27*AN22 -> 0.46089192
A27: Scope (%) | G27: =G26/E22 -> #DIV/0! | H27: =H26/F22 -> #DIV/0! | I27: =I26/G22 -> 0 | J27: =J26/H22 -> #DIV/0! | K27: =K26/I22 -> 0 | L27: =L26/J22 -> #DIV/0! | M27: =M26/K22 -> 0.0023696682 | O27: 0.005 | Q27: 0.005 | S27: 0.005 | U27: 0.005 | W27: 0.005 | Y27: 0.005 | AH27: =AH26/AG22 -> 0 | AI27: 0.005 | AJ27: 0.005 | AK27: 0.005 | AL27: 0.005 | AM27: 0.005 | AN27: 0.005 | AO27: 0.005
A28: Organic Growth | I28: 2.5 | K28: -0.6 | M28: 0.5 | O28: =O29*M22 -> 0.0854 | Q28: =Q29*O22 -> 0.0859978 | S28: =S29*Q22 -> 0.086599785 | U28: =U29*S22 -> 0.087205983 | W28: =W29*U22 -> 0.087816425 | Y28: =Y29*W22 -> 0.08843114 | AH28: -0.1 | AI28: =AI29*AH22 -> 0.1768 | AJ28: =AJ29*AI22 -> 0.1780376 | AK28: =AK29*AJ22 -> 0.17928386 | AL28: =AL29*AK22 -> 0.18053885 | AM28: =AM29*AL22 -> 0.18180262 | AN28: =AN29*AM22 -> 0.18307524 | AO28: =AO29*AN22 -> 0.18435677
A29: Organic Growth (%) | G29: =G28/E22 -> #DIV/0! | H29: =H28/F22 -> #DIV/0! | I29: =I28/G22 -> 0.062034739 | J29: =J28/H22 -> #DIV/0! | K29: =K28/I22 -> -0.014018692 | L29: =L28/J22 -> #DIV/0! | M29: =M28/K22 -> 0.011848341 | O29: 0.002 | Q29: 0.002 | S29: 0.002 | U29: 0.002 | W29: 0.002 | Y29: 0.002 | AH29: =AH28/AG22 -> -0.0011299435 | AI29: 0.002 | AJ29: 0.002 | AK29: 0.002 | AL29: 0.002 | AM29: 0.002 | AN29: 0.002 | AO29: 0.002
A31: Non-Beer Volume | G31: 2.2 | I31: 1 | K31: =I31+K33+K35+K37 -> 0.9 | M31: 0.8 | O31: =M31+O33+O35+O37 -> 0.8056 | Q31: =O31+Q33+Q35+Q37 -> 0.8112392 | S31: =Q31+S33+S35+S37 -> 0.81691787 | U31: =S31+U33+U35+U37 -> 0.8226363 | W31: =U31+W33+W35+W37 -> 0.82839475 | Y31: =W31+Y33+Y35+Y37 -> 0.83419352 | AG31: 1.9 | AH31: 1.8 | AI31: =AH31+AI33+AI35+AI37 -> 1.8126 | AJ31: =AI31+AJ33+AJ35+AJ37 -> 1.8252882 | AK31: =AJ31+AK33+AK35+AK37 -> 1.8380652 | AL31: =AK31+AL33+AL35+AL37 -> 1.8509317 | AM31: =AL31+AM33+AM35+AM37 -> 1.8638882 | AN31: =AM31+AN33+AN35+AN37 -> 1.8769354 | AO31: =AN31+AO33+AO35+AO37 -> 1.890074
G32: =G31/E31-1 -> #DIV/0! | H32: =H31/F31-1 -> #DIV/0! | I32: =I31/G31-1 -> -0.54545455 | J32: =J31/H31-1 -> #DIV/0! | K32: =K31/I31-1 -> -0.1 | L32: =L31/J31-1 -> #DIV/0! | M32: =M31/K31-1 -> -0.11111111
A33: FX | I33: 0 | K33: 0 | M33: 0 | O33: =O34*M31 -> 0 | Q33: =Q34*O31 -> 0 | S33: =S34*Q31 -> 0 | U33: =U34*S31 -> 0 | W33: =W34*U31 -> 0 | Y33: =Y34*W31 -> 0 | AH33: 0 | AI33: =AI34*AH31 -> 0 | AJ33: =AJ34*AI31 -> 0 | AK33: =AK34*AJ31 -> 0 | AL33: =AL34*AK31 -> 0 | AM33: =AM34*AL31 -> 0 | AN33: =AN34*AM31 -> 0 | AO33: =AO34*AN31 -> 0
A34: Fx (%) | G34: =G33/E31 -> #DIV/0! | H34: =H33/F31 -> #DIV/0! | I34: =I33/G31 -> 0 | J34: =J33/H31 -> #DIV/0! | K34: =K33/I31 -> 0 | L34: =L33/J31 -> #DIV/0! | M34: =M33/K31 -> 0 | O34: 0 | Q34: 0 | S34: 0 | U34: 0 | W34: 0 | Y34: 0 | AH34: =AH33/AG31 -> 0 | AI34: 0 | AJ34: 0 | AK34: 0 | AL34: 0 | AM34: 0 | AN34: 0 | AO34: 0
A35: Scope | I35: 0 | K35: 0 | M35: 0 | O35: =O36*M31 -> 0.0016 | Q35: =Q36*O31 -> 0.0016112 | S35: =S36*Q31 -> 0.0016224784 | U35: =U36*S31 -> 0.0016338357 | W35: =W36*U31 -> 0.0016452726 | Y35: =Y36*W31 -> 0.0016567895 | AH35: 0 | AI35: =AI36*AH31 -> 0.0036 | AJ35: =AJ36*AI31 -> 0.0036252 | AK35: =AK36*AJ31 -> 0.0036505764 | AL35: =AL36*AK31 -> 0.0036761304 | AM35: =AM36*AL31 -> 0.0037018633 | AN35: =AN36*AM31 -> 0.0037277764 | AO35: =AO36*AN31 -> 0.0037538708
A36: Scope (%) | G36: =G35/E31 -> #DIV/0! | H36: =H35/F31 -> #DIV/0! | I36: =I35/G31 -> 0 | J36: =J35/H31 -> #DIV/0! | K36: =K35/I31 -> 0 | L36: =L35/J31 -> #DIV/0! | M36: =M35/K31 -> 0 | O36: 0.002 | Q36: 0.002 | S36: 0.002 | U36: 0.002 | W36: 0.002 | Y36: 0.002 | AH36: =AH35/AG31 -> 0 | AI36: 0.002 | AJ36: 0.002 | AK36: 0.002 | AL36: 0.002 | AM36: 0.002 | AN36: 0.002 | AO36: 0.002
A37: Organic Growth | I37: -1.2 | K37: -0.1 | M37: -0.1 | O37: =O38*M31 -> 0.004 | Q37: =Q38*O31 -> 0.004028 | S37: =S38*Q31 -> 0.004056196 | U37: =U38*S31 -> 0.0040845894 | W37: =W38*U31 -> 0.0041131815 | Y37: =Y38*W31 -> 0.0041419738 | AH37: -0.1 | AI37: =AI38*AH31 -> 0.009 | AJ37: =AJ38*AI31 -> 0.009063 | AK37: =AK38*AJ31 -> 0.009126441 | AL37: =AL38*AK31 -> 0.0091903261 | AM37: =AM38*AL31 -> 0.0092546584 | AN37: =AN38*AM31 -> 0.009319441 | AO37: =AO38*AN31 -> 0.0093846771
A38: Organic Growth (%) | G38: =G37/E31 -> #DIV/0! | H38: =H37/F31 -> #DIV/0! | I38: =I37/G31 -> -0.54545455 | J38: =J37/H31 -> #DIV/0! | K38: =K37/I31 -> -0.1 | L38: =L37/J31 -> #DIV/0! | M38: =M37/K31 -> -0.11111111 | O38: 0.005 | Q38: 0.005 | S38: 0.005 | U38: 0.005 | W38: 0.005 | Y38: 0.005 | AH38: =AH37/AG31 -> -0.052631579 | AI38: 0.005 | AJ38: 0.005 | AK38: 0.005 | AL38: 0.005 | AM38: 0.005 | AN38: 0.005 | AO38: 0.005
A41: Third Party products volume | I41: 0.1 | K41: 0.1 | M41: 0.1 | O41: =M41+O43+O45+O47 -> 0.101 | Q41: =O41+Q43+Q45+Q47 -> 0.10201 | S41: =Q41+S43+S45+S47 -> 0.1030301 | U41: =S41+U43+U45+U47 -> 0.1040604 | W41: =U41+W43+W45+W47 -> 0.10510101 | Y41: =W41+Y43+Y45+Y47 -> 0.10615202 | AG41: 0.1 | AH41: 0.1 | AI41: =AH41+AI43+AI45+AI47 -> 0.101 | AJ41: =AI41+AJ43+AJ45+AJ47 -> 0.10201 | AK41: =AJ41+AK43+AK45+AK47 -> 0.1030301 | AL41: =AK41+AL43+AL45+AL47 -> 0.1040604 | AM41: =AL41+AM43+AM45+AM47 -> 0.10510101 | AN41: =AM41+AN43+AN45+AN47 -> 0.10615202 | AO41: =AN41+AO43+AO45+AO47 -> 0.10721354
G42: =IFERROR(G41/E41-1, "-") -> - | H42: =IFERROR(H41/F41-1, "-") -> - | I42: =IFERROR(I41/G41-1, "-") -> - | J42: =IFERROR(J41/H41-1, "-") -> - | K42: =IFERROR(K41/I41-1, "-") -> 0 | L42: =IFERROR(L41/J41-1, "-") -> - | M42: =IFERROR(M41/K41-1, "-") -> 0
A43: FX | M43: 0 | O43: =O44*M41 -> 0 | Q43: =Q44*O41 -> 0 | S43: =S44*Q41 -> 0 | U43: =U44*S41 -> 0 | W43: =W44*U41 -> 0 | Y43: =Y44*W41 -> 0 | AH43: 0 | AI43: =AI44*AH41 -> 0 | AJ43: =AJ44*AI41 -> 0 | AK43: =AK44*AJ41 -> 0 | AL43: =AL44*AK41 -> 0 | AM43: =AM44*AL41 -> 0 | AN43: =AN44*AM41 -> 0 | AO43: =AO44*AN41 -> 0
A44: Fx (%) | G44: =IFERROR(G43/E41,"-") -> - | H44: =IFERROR(H43/F41,"-") -> - | I44: =IFERROR(I43/G41,"-") -> - | J44: =IFERROR(J43/H41,"-") -> - | K44: =IFERROR(K43/I41,"-") -> 0 | L44: =IFERROR(L43/J41,"-") -> - | M44: =IFERROR(M43/K41,"-") -> 0 | O44: 0 | Q44: 0 | S44: 0 | U44: 0 | W44: 0 | Y44: 0 | AH44: =AH43/AG41 -> 0 | AI44: 0 | AJ44: 0 | AK44: 0 | AL44: 0 | AM44: 0 | AN44: 0 | AO44: 0
A45: Scope | M45: 0 | O45: =O46*M41 -> 0.0005 | Q45: =Q46*O41 -> 0.000505 | S45: =S46*Q41 -> 0.00051005 | U45: =U46*S41 -> 0.0005151505 | W45: =W46*U41 -> 0.00052030201 | Y45: =Y46*W41 -> 0.00052550503 | AH45: 0 | AI45: =AI46*AH41 -> 0.0005 | AJ45: =AJ46*AI41 -> 0.000505 | AK45: =AK46*AJ41 -> 0.00051005 | AL45: =AL46*AK41 -> 0.0005151505 | AM45: =AM46*AL41 -> 0.00052030201 | AN45: =AN46*AM41 -> 0.00052550503 | AO45: =AO46*AN41 -> 0.00053076008
A46: Scope (%) | G46: =IFERROR(G45/E41,"-") -> - | H46: =IFERROR(H45/F41,"-") -> - | I46: =IFERROR(I45/G41,"-") -> - | J46: =IFERROR(J45/H41,"-") -> - | K46: =IFERROR(K45/I41,"-") -> 0 | L46: =IFERROR(L45/J41,"-") -> - | M46: =IFERROR(M45/K41,"-") -> 0 | O46: 0.005 | Q46: 0.005 | S46: 0.005 | U46: 0.005 | W46: 0.005 | Y46: 0.005 | AH46: =AH45/AG41 -> 0 | AI46: 0.005 | AJ46: 0.005 | AK46: 0.005 | AL46: 0.005 | AM46: 0.005 | AN46: 0.005 | AO46: 0.005
A47: Organic Growth | I47: 1 | M47: 0 | O47: =O48*M41 -> 0.0005 | Q47: =Q48*O41 -> 0.000505 | S47: =S48*Q41 -> 0.00051005 | U47: =U48*S41 -> 0.0005151505 | W47: =W48*U41 -> 0.00052030201 | Y47: =Y48*W41 -> 0.00052550503 | AH47: 0 | AI47: =AI48*AH41 -> 0.0005 | AJ47: =AJ48*AI41 -> 0.000505 | AK47: =AK48*AJ41 -> 0.00051005 | AL47: =AL48*AK41 -> 0.0005151505 | AM47: =AM48*AL41 -> 0.00052030201 | AN47: =AN48*AM41 -> 0.00052550503 | AO47: =AO48*AN41 -> 0.00053076008
A48: Organic Growth (%) | I48: 0.739 | K48: -0.392 | M48: 0.568 | O48: 0.005 | Q48: 0.005 | S48: 0.005 | U48: 0.005 | W48: 0.005 | Y48: 0.005 | AH48: =AH47/AG41 -> 0 | AI48: 0.005 | AJ48: 0.005 | AK48: 0.005 | AL48: 0.005 | AM48: 0.005 | AN48: 0.005 | AO48: 0.005
A51: Total Volume | G51: 42.6 | I51: 43.9 | K51: =K22+K31+K41 -> 43.2 | M51: =M22+M31+M41 -> 43.6 | O51: =O22+O31+O41 -> 43.9055 | Q51: =Q22+Q31+Q41 -> 44.213142 | S51: =S22+S31+S41 -> 44.52294 | U51: =U22+U31+U41 -> 44.834909 | W51: =W22+W31+W41 -> 45.149066 | Y51: =Y22+Y31+Y41 -> 45.465424 | AG51: 90.6 | AH51: 90.4 | AI51: =AI22+AI31+AI41 -> 90.9324 | AJ51: =AJ22+AJ31+AJ41 -> 91.56923 | AK51: =AK22+AK31+AK41 -> 92.21052 | AL51: =AL22+AL31+AL41 -> 92.856303 | AM51: =AM22+AM31+AM41 -> 93.506609 | AN51: =AN22+AN31+AN41 -> 94.161471 | AO51: =AO22+AO31+AO41 -> 94.82092
G52: =IFERROR(G51/E51-1, "-") -> - | H52: =IFERROR(H51/F51-1, "-") -> - | I52: =IFERROR(I51/G51-1, "-") -> 0.030516432 | J52: =IFERROR(J51/H51-1, "-") -> - | K52: =IFERROR(K51/I51-1, "-") -> -0.01594533 | L52: =IFERROR(L51/J51-1, "-") -> - | M52: =IFERROR(M51/K51-1, "-") -> 0.0092592593
A53: FX | I53: 0 | K53: 0 | M53: 0 | O53: =O24+O33+O43 -> 0 | Q53: =Q24+Q33+Q43 -> 0 | S53: =S24+S33+S43 -> 0 | U53: =U24+U33+U43 -> 0 | W53: =W24+W33+W43 -> 0 | Y53: =Y24+Y33+Y43 -> 0 | AH53: 0 | AI53: =AI24+AI33+AI43 -> 0 | AJ53: =AJ24+AJ33+AJ43 -> 0 | AK53: =AK24+AK33+AK43 -> 0 | AL53: =AL24+AL33+AL43 -> 0 | AM53: =AM24+AM33+AM43 -> 0 | AN53: =AN24+AN33+AN43 -> 0 | AO53: =AO24+AO33+AO43 -> 0
A54: Fx (%) | G54: =IFERROR(G53/E51,"-") -> - | H54: =IFERROR(H53/F51,"-") -> - | I54: =IFERROR(I53/G51,"-") -> 0 | J54: =IFERROR(J53/H51,"-") -> - | K54: =IFERROR(K53/I51,"-") -> 0 | L54: =IFERROR(L53/J51,"-") -> - | M54: =IFERROR(M53/K51,"-") -> 0 | O54: =O53/M51 -> 0 | Q54: =Q53/O51 -> 0 | S54: =S53/Q51 -> 0 | U54: =U53/S51 -> 0 | W54: =W53/U51 -> 0 | Y54: =Y53/W51 -> 0 | AH54: =AH53/AG51 -> 0 | AI54: =AI53/AH51 -> 0 | AJ54: =AJ53/AI51 -> 0 | AK54: =AK53/AJ51 -> 0 | AL54: =AL53/AK51 -> 0 | AM54: =AM53/AL51 -> 0 | AN54: =AN53/AM51 -> 0 | AO54: =AO53/AN51 -> 0
A55: Scope | K55: 0 | M55: 0.1 | O55: =O26+O35+O45 -> 0.2156 | Q55: =Q26+Q35+Q45 -> 0.2171107 | S55: =S26+S35+S45 -> 0.21863199 | U55: =U26+U35+U45 -> 0.22016394 | W55: =W26+W35+W45 -> 0.22170664 | Y55: =Y26+Y35+Y45 -> 0.22326014 | AH55: 0 | AI55: =AI26+AI35+AI45 -> 0.4461 | AJ55: =AJ26+AJ35+AJ45 -> 0.4492242 | AK55: =AK26+AK35+AK45 -> 0.45237028 | AL55: =AL26+AL35+AL45 -> 0.45553841 | AM55: =AM26+AM35+AM45 -> 0.45872872 | AN55: =AN26+AN35+AN45 -> 0.46194138 | AO55: =AO26+AO35+AO45 -> 0.46517655
A56: Scope (%) | G56: =IFERROR(G55/E51,"-") -> - | H56: =IFERROR(H55/F51,"-") -> - | I56: =IFERROR(I55/G51,"-") -> 0 | J56: =IFERROR(J55/H51,"-") -> - | K56: =IFERROR(K55/I51,"-") -> 0 | L56: =IFERROR(L55/J51,"-") -> - | M56: =IFERROR(M55/K51,"-") -> 0.0023148148 | O56: =O55/M51 -> 0.0049449541 | Q56: =Q55/O51 -> 0.0049449545 | S56: =S55/Q51 -> 0.0049449549 | U56: =U55/S51 -> 0.0049449553 | W56: =W55/U51 -> 0.0049449556 | Y56: =Y55/W51 -> 0.004944956 | AH56: =AH55/AG51 -> 0 | AI56: =AI55/AH51 -> 0.0049347345 | AJ56: =AJ55/AI51 -> 0.0049401995 | AK56: =AK55/AJ51 -> 0.0049401997 | AL56: =AL55/AK51 -> 0.0049401999 | AM56: =AM55/AL51 -> 0.0049402001 | AN56: =AN55/AM51 -> 0.0049402003 | AO56: =AO55/AN51 -> 0.0049402005
A57: Organic Growth | I57: 1.3 | K57: -0.7 | M57: 0.4 | O57: =O28+O37+O47 -> 0.0899 | Q57: =Q28+Q37+Q47 -> 0.0905308 | S57: =S28+S37+S47 -> 0.091166031 | U57: =U28+U37+U47 -> 0.091805723 | W57: =W28+W37+W47 -> 0.092449908 | Y57: =Y28+Y37+Y47 -> 0.093098619 | AH57: -0.2 | AI57: =AI28+AI37+AI47 -> 0.1863 | AJ57: =AJ28+AJ37+AJ47 -> 0.1876056 | AK57: =AK28+AK37+AK47 -> 0.18892035 | AL57: =AL28+AL37+AL47 -> 0.19024433 | AM57: =AM28+AM37+AM47 -> 0.19157758 | AN57: =AN28+AN37+AN47 -> 0.19292019 | AO57: =AO28+AO37+AO47 -> 0.1942722
A58: Organic Growth (%) | G58: =IFERROR(G57/E51,"-") -> - | H58: =IFERROR(H57/F51,"-") -> - | I58: =IFERROR(I57/G51,"-") -> 0.030516432 | J58: =IFERROR(J57/H51,"-") -> - | K58: =IFERROR(K57/I51,"-") -> -0.01594533 | L58: =IFERROR(L57/J51,"-") -> - | M58: =IFERROR(M57/K51,"-") -> 0.0092592593 | O58: =O57/M51 -> 0.0020619266 | Q58: =Q57/O51 -> 0.0020619467 | S58: =S57/Q51 -> 0.0020619668 | U58: =U57/S51 -> 0.002061987 | W58: =W57/U51 -> 0.0020620073 | Y58: =Y57/W51 -> 0.0020620276 | AH58: =AH57/AG51 -> -0.0022075055 | AI58: =AI57/AH51 -> 0.0020608407 | AJ58: =AJ57/AI51 -> 0.0020631326 | AK58: =AK57/AJ51 -> 0.0020631423 | AL58: =AL57/AK51 -> 0.0020631521 | AM58: =AM57/AL51 -> 0.0020631619 | AN58: =AN57/AM51 -> 0.0020631717 | AO58: =AO57/AN51 -> 0.0020631815
A60: Licensed Beer Volume | G60: 1.4 | I60: 1.4 | K60: 1.6 | M60: 1.5 | AG60: 3.2 | AH60: 3.4
A62: Group Beer Volume | G62: 45.8 | I62: 47.9 | K62: 47.6 | M62: 47.5 | AG62: 99.6 | AH62: 99.7
M66: =M8+M10+M12-M18 -> 0

Sheet Asia Pacific
B1: ='Cash Flow Statement'!B1 -> H1'19 | C1: ='Cash Flow Statement'!C1 -> H2'19 | D1: ='Cash Flow Statement'!D1 -> FY'19 | E1: ='Cash Flow Statement'!E1 -> H1'20 | F1: ='Cash Flow Statement'!F1 -> H2'20 | G1: ='Cash Flow Statement'!G1 -> H1'21 | H1: ='Cash Flow Statement'!H1 -> H2'21 | I1: ='Cash Flow Statement'!I1 -> H1'22 | ... Z1: ='Cash Flow Statement'!Z1 -> H2'30 | AE1: ='Cash Flow Statement'!AE1 -> FY'20 | AF1: ='Cash Flow Statement'!AF1 -> FY'21 | AG1: ='Cash Flow Statement'!AG1 -> FY'22 | AH1: ='Cash Flow Statement'!AH1 -> FY'23 | AI1: ='Cash Flow Statement'!AI1 -> FY'24 | AJ1: ='Cash Flow Statement'!AJ1 -> FY'25 | AK1: ='Cash Flow Statement'!AK1 -> FY'26 | AL1: ='Cash Flow Statement'!AL1 -> FY'27 | ... AO1: ='Cash Flow Statement'!AO1 -> FY'30
A4: Africa and Middle East
A6: Net Revenue (beia) | G6: =E17 -> 0 | I6: =G17 -> 1310 | K6: =I17 -> 2232 | M6: =K17 -> 2019 | O6: =M17 -> 2100 | Q6: =O17 -> 2228.6938 | S6: =Q17 -> 2415.4501 | U6: =S17 -> 2662.422 | W6: =U17 -> 2975.0796 | Y6: =W17 -> 3362.0168 | AH6: =AG17 -> 4652 | AI6: =AH17 -> 4157 | AJ6: =AI17 -> 3644.3197 | AK6: =AJ17 -> 3119.2853 | AL6: =AK17 -> 2551.9603 | AM6: =AL17 -> 1914.5775 | AN6: =AM17 -> 1179.5087 | AO6: =AN17 -> 317.56486
A7: Fx | I7: 123 | K7: -86 | M7: -91 | O7: =M7*(1+O8) -> -63.7 | Q7: =O7*(1+Q8) -> -44.59 | S7: =Q7*(1+S8) -> -31.213 | U7: =S7*(1+U8) -> -21.8491 | W7: =U7*(1+W8) -> -15.29437 | Y7: =W7*(1+Y8) -> -10.706059 | AH7: -260 | AI7: =AH7*(1+AI8) -> -182 | AJ7: =AI7*(1+AJ8) -> -127.4 | AK7: =AJ7*(1+AK8) -> -89.18 | AL7: =AK7*(1+AL8) -> -62.426 | AM7: =AL7*(1+AM8) -> -43.6982 | AN7: =AM7*(1+AN8) -> -30.58874 | AO7: =AN7*(1+AO8) -> -21.412118
A8: Fx (%) | G8: =G7/E17 -> #DIV/0! | H8: =H7/F17 -> #DIV/0! | I8: =I7/G17 -> 0.09389313 | J8: =J7/H17 -> #DIV/0! | K8: =K7/I17 -> -0.038530466 | L8: =L7/J17 -> #DIV/0! | M8: =M7/K17 -> -0.045071818 | O8: -0.3 | Q8: -0.3 | S8: -0.3 | U8: -0.3 | W8: -0.3 | Y8: -0.3 | AH8: =AH7/AG17 -> -0.05588994 | AI8: -0.3 | AJ8: -0.3 | AK8: -0.3 | AL8: -0.3 | AM8: -0.3 | AN8: -0.3 | AO8: -0.3
