Workbook

Sheet Revenue Model
B2: In Euro millions | C2: H1'21 | D2: H2'21 | E2: FY21 | F2: H1'22 | G2: H2'22 | H2: H1'23 | I2: H2'23 | J2: H1'24 | K2: H2'24 | L2: H1'25 | M2: H2'25 | N2: H1'26 | O2: H2'26 | P2: H1'27 | Q2: H2'27 | R2: H1'28 | S2: H2'28 | T2: H1'29 | U2: H2'29 | V2: H1'30 | W2: H2'30 | AC2: FY22 | AD2: FY23 | AE2: FY24 | AF2: FY25 | AG2: FY26 | AH2: FY27 | AI2: FY28 | AJ2: FY29 | AK2: FY30
B4: Americas
B5: Organic | F5: 196 | G5: =AC5-F5 -> 123 | H5: 118 | I5: =AD5-H5 -> -56 | J5: -145 | K5: =AE5-J5 -> -14 | L5: -81 | M5: =K5*(1+M6) -> -13.86 | N5: =L5*(1+N6) -> -83.43 | O5: =M5*(1+O6) -> -14.2758 | P5: =N5*(1+P6) -> -85.9329 | Q5: =O5*(1+Q6) -> -14.704074 | R5: =P5*(1+R6) -> -88.510887 | S5: =Q5*(1+S6) -> -15.145196 | T5: =R5*(1+T6) -> -91.166214 | ... W5: =U5*(1+W6) -> -16.067539 | AC5: 319 | AD5: 62 | AE5: -159 | AF5: =L5+M5 -> -94.86 | AG5: =N5+O5 -> -97.7058 | AH5: =P5+Q5 -> -100.63697 | AI5: =R5+S5 -> -103.65608 | AJ5: =T5+U5 -> -106.76577 | AK5: =V5+W5 -> -109.96874
B6: Organic growth (%) | C6: =IFERROR(C5/#REF!-1, "-") -> - | D6: =IFERROR(D5/#REF!-1, "-") -> - | E6: =IFERROR(E5/#REF!-1, "-") -> - | F6: =F5/C11 -> 0.13980029 | G6: =G5/D11 -> 0.10040816 | H6: =H5/F11 -> 0.072039072 | I6: =I5/G11 -> -0.037458194 | J6: =J5/H11 -> -0.072319202 | K6: =K5/I11 -> -0.0094915254 | L6: =L5/J11 -> -0.043548387 | M6: -0.01 | N6: 0.03 | O6: 0.03 | P6: 0.03 | Q6: 0.03 | R6: 0.03 | S6: 0.03 | T6: 0.03 | U6: 0.03 | V6: 0.03 | W6: 0.03 | AC6: =AC5/E11 -> 0.12143129 | AD6: =AD5/AC11 -> 0.019789339 | AE6: =AE5/AD11 -> -0.04567653 | AF6: =AF5/AE5-1 -> -0.40339623 | AG6: =AG5/AF5-1 -> 0.03 | AH6: =AH5/AG5-1 -> 0.03 | AI6: =AI5/AH5-1 -> 0.03 | AJ6: =AJ5/AI5-1 -> 0.03 | AK6: =AK5/AJ5-1 -> 0.03
B7: Fx | F7: 22 | G7: =AC7-F7 -> 134 | H7: 220 | I7: =AD7-H7 -> -42 | J7: -173 | K7: =AE7-J7 -> -92 | L7: -98 | M7: =K7*(1+M8) -> -91.08 | N7: =L7*(1+N8) -> -100.94 | O7: =M7*(1+O8) -> -93.8124 | P7: =N7*(1+P8) -> -103.9682 | Q7: =O7*(1+Q8) -> -96.626772 | R7: =P7*(1+R8) -> -107.08725 | S7: =Q7*(1+S8) -> -99.525575 | T7: =R7*(1+T8) -> -110.29986 | ... W7: =U7*(1+W8) -> -105.58668 | AC7: 156 | AD7: 178 | AE7: -265 | AF7: =L7+M7 -> -189.08 | AG7: =N7+O7 -> -194.7524 | AH7: =P7+Q7 -> -200.59497 | AI7: =R7+S7 -> -206.61282 | AJ7: =T7+U7 -> -212.81121 | AK7: =V7+W7 -> -219.19554
B8: Fx growth (%) | C8: =IFERROR(C7/#REF!-1, "-") -> - | D8: =IFERROR(D7/#REF!-1, "-") -> - | E8: =IFERROR(E7/#REF!-1, "-") -> - | F8: =F7/C11 -> 0.015691869 | G8: =G7/D11 -> 0.10938776 | H8: =H7/F11 -> 0.13431013 | I8: =I7/G11 -> -0.028093645 | J8: =J7/H11 -> -0.086284289 | K8: =K7/I11 -> -0.062372881 | L8: =L7/J11 -> -0.052688172 | M8: -0.01 | N8: 0.03 | O8: 0.03 | P8: 0.03 | Q8: 0.03 | R8: 0.03 | S8: 0.03 | T8: 0.03 | U8: 0.03 | V8: 0.03 | W8: 0.03 | AC8: =AC7/E11 -> 0.059383327 | AD8: =AD7/AC11 -> 0.056814555 | AE8: =AE7/AD11 -> -0.07612755 | AF8: =AF7/AE7-1 -> -0.28649057 | AG8: =AG7/AF7-1 -> 0.03 | AH8: =AH7/AG7-1 -> 0.03 | AI8: =AI7/AH7-1 -> 0.03 | AJ8: =AJ7/AI7-1 -> 0.03 | AK8: =AK7/AJ7-1 -> 0.03
B9: Scope | F9: 17 | G9: =AC9-F9 -> 13 | H9: 30 | I9: =AD9-H9 -> 78 | J9: 173 | K9: =AE9-J9 -> 110 | L9: 57 | M9: =K9*(1+M10) -> 108.9 | N9: =L9*(1+N10) -> 58.71 | O9: =M9*(1+O10) -> 112.167 | P9: =N9*(1+P10) -> 60.4713 | Q9: =O9*(1+Q10) -> 115.53201 | R9: =P9*(1+R10) -> 62.285439 | S9: =Q9*(1+S10) -> 118.99797 | T9: =R9*(1+T10) -> 64.154002 | ... W9: =U9*(1+W10) -> 126.24495 | AC9: 30 | AD9: 108 | AE9: 283 | AF9: =L9+M9 -> 165.9 | AG9: =N9+O9 -> 170.877 | AH9: =P9+Q9 -> 176.00331 | AI9: =R9+S9 -> 181.28341 | AJ9: =T9+U9 -> 186.72191 | AK9: =V9+W9 -> 192.32357
B10: Scope growth (%) | C10: =IFERROR(C9/#REF!-1, "-") -> - | D10: =IFERROR(D9/#REF!-1, "-") -> - | E10: =IFERROR(E9/#REF!-1, "-") -> - | F10: =F9/C11 -> 0.012125535 | G10: =G9/D11 -> 0.010612245 | H10: =H9/F11 -> 0.018315018 | I10: =I9/G11 -> 0.052173913 | J10: =J9/H11 -> 0.086284289 | K10: =K9/I11 -> 0.074576271 | L10: =L9/J11 -> 0.030645161 | M10: -0.01 | N10: 0.03 | O10: 0.03 | P10: 0.03 | Q10: 0.03 | R10: 0.03 | S10: 0.03 | T10: 0.03 | U10: 0.03 | V10: 0.03 | W10: 0.03 | AC10: =AC9/E11 -> 0.011419871 | AD10: =AD9/AC11 -> 0.034471752 | AE10: =AE9/AD11 -> 0.081298477 | AF10: =IFERROR(AF9/AE9-1, "-") -> -0.41378092 | AG10: =IFERROR(AG9/AF9-1, "-") -> 0.03 | AH10: =IFERROR(AH9/AG9-1, "-") -> 0.03 | AI10: =IFERROR(AI9/AH9-1, "-") -> 0.03 | AJ10: =IFERROR(AJ9/AI9-1, "-") -> 0.03 | AK10: =IFERROR(AK9/AJ9-1, "-") -> 0.03
B11: Total Sales - Americas | C11: 1402 | D11: =E11-C11 -> 1225 | E11: 2627 | F11: =C11+F5+F7+F9+1 -> 1638 | G11: =D11+G5+G7+G9 -> 1495 | H11: =F11+H5+H7+H9-1 -> 2005 | I11: =G11+I5+I7+I9 -> 1475 | J11: =H11+J5+J7+J9 -> 1860 | K11: =I11+K5+K7+K9 -> 1479 | L11: =J11+L5+L7+L9 -> 1738 | M11: =K11+M5+M7+M9 -> 1482.96 | N11: =L11+N5+N7+N9 -> 1612.34 | O11: =M11+O5+O7+O9 -> 1487.0388 | P11: =N11+P5+P7+P9 -> 1482.9102 | ... W11: =U11+W5+W7+W9 -> 1504.6149 | AC11: =E11+AC5+AC7+AC9+1 -> 3133 | AD11: =AC11+AD5+AD7+AD9 -> 3481 | AE11: =AD11+AE5+AE7+AE9 -> 3340 | AF11: =AE11+AF5+AF7+AF9 -> 3221.96 | AG11: =AF11+AG5+AG7+AG9 -> 3100.3788 | AH11: =AG11+AH5+AH7+AH9 -> 2975.1502 | AI11: =AH11+AI5+AI7+AI9 -> 2846.1647 | AJ11: =AI11+AJ5+AJ7+AJ9 -> 2713.3096 | AK11: =AJ11+AK5+AK7+AK9 -> 2576.4689
B12: Growth (%) | C12: =IFERROR(C11/#REF!-1, "-") -> - | D12: =IFERROR(D11/#REF!-1, "-") -> - | E12: =IFERROR(E11/#REF!-1, "-") -> - | F12: =IFERROR(F11/C11-1, "-") -> 0.16833096 | G12: =IFERROR(G11/D11-1, "-") -> 0.22040816 | H12: =IFERROR(H11/F11-1, "-") -> 0.22405372 | I12: =IFERROR(I11/G11-1, "-") -> -0.013377926 | J12: =IFERROR(J11/H11-1, "-") -> -0.072319202 | K12: =IFERROR(K11/I11-1, "-") -> 0.0027118644 | L12: =IFERROR(L11/J11-1, "-") -> -0.065591398 | M12: =IFERROR(M11/K11-1, "-") -> 0.0026774848 | N12: =IFERROR(N11/L11-1, "-") -> -0.072301496 | O12: =IFERROR(O11/M11-1, "-") -> 0.0027504451 | ... W12: =IFERROR(W11/U11-1, "-") -> 0.0030604342 | AC12: =IFERROR(AC11/E11-1, "-") -> 0.19261515 | AD12: =IFERROR(AD11/AC11-1, "-") -> 0.11107565 | AE12: =IFERROR(AE11/AD11-1, "-") -> -0.040505602 | AF12: =IFERROR(AF11/AE11-1, "-") -> -0.035341317 | AG12: =IFERROR(AG11/AF11-1, "-") -> -0.037735167 | AH12: =IFERROR(AH11/AG11-1, "-") -> -0.040391399 | AI12: =IFERROR(AI11/AH11-1, "-") -> -0.043354281 | AJ12: =IFERROR(AJ11/AI11-1, "-") -> -0.046678627 | AK12: =IFERROR(AK11/AJ11-1, "-") -> -0.050433136
B14: Asia/Row
B15: Organic | F15: 338 | G15: =AC15-F15 -> 336 | H15: 460 | I15: =AD15-H15 -> 295 | J15: 16 | K15: =AE15-J15 -> 151 | L15: -156 | M15: =K15*(1+M16) -> 149.49 | N15: =L15*(1+N16) -> -160.68 | O15: =M15*(1+O16) -> 153.9747 | P15: =N15*(1+P16) -> -165.5004 | Q15: =O15*(1+Q16) -> 158.59394 | R15: =P15*(1+R16) -> -170.46541 | S15: =Q15*(1+S16) -> 163.35176 | T15: =R15*(1+T16) -> -175.57937 | ... W15: =U15*(1+W16) -> 173.29988 | AC15: 674 | AD15: 755 | AE15: 167 | AF15: =L15+M15 -> -6.51 | AG15: =N15+O15 -> -6.7053 | AH15: =P15+Q15 -> -6.906459 | AI15: =R15+S15 -> -7.1136528 | AJ15: =T15+U15 -> -7.3270624 | AK15: =V15+W15 -> -7.5468742
B16: Organic growth (%) | C16: =IFERROR(C15/#REF!-1, "-") -> - | D16: =IFERROR(D15/#REF!-1, "-") -> - | E16: =IFERROR(E15/#REF!-1, "-") -> - | F16: =F15/C21 -> 0.15890926 | G16: =G15/D21 -> 0.22207535 | H16: =H15/F21 -> 0.1822504 | I16: =I15/G21 -> 0.15412748 | J16: =J15/H21 -> 0.0051249199 | K16: =K15/I21 -> 0.072982117 | L16: =L15/J21 -> -0.054736842 | M16: -0.01 | N16: 0.03 | O16: 0.03 | P16: 0.03 | Q16: 0.03 | R16: 0.03 | S16: 0.03 | T16: 0.03 | U16: 0.03 | V16: 0.03 | W16: 0.03 | AC16: =AC15/E21 -> 0.18516484 | AD16: =AD15/AC21 -> 0.17012168 | AE16: =AE15/AD21 -> 0.032171065 | AF16: =AF15/AE15-1 -> -1.038982 | AG16: =AG15/AF15-1 -> 0.03 | AH16: =AH15/AG15-1 -> 0.03 | AI16: =AI15/AH15-1 -> 0.03 | AJ16: =AJ15/AI15-1 -> 0.03 | AK16: =AK15/AJ15-1 -> 0.03
B17: Fx | F17: 60 | G17: =AC17-F17 -> 65 | H17: 90 | I17: =AD17-H17 -> -176 | J17: -366 | K17: =AE17-J17 -> -130 | L17: -80 | M17: =K17*(1+M18) -> -128.7 | N17: =L17*(1+N18) -> -82.4 | O17: =M17*(1+O18) -> -132.561 | P17: =N17*(1+P18) -> -84.872 | Q17: =O17*(1+Q18) -> -136.53783 | R17: =P17*(1+R18) -> -87.41816 | S17: =Q17*(1+S18) -> -140.63396 | T17: =R17*(1+T18) -> -90.040705 | ... W17: =U17*(1+W18) -> -149.19857 | AC17: 125 | AD17: -86 | AE17: -496 | AF17: =L17+M17 -> -208.7 | AG17: =N17+O17 -> -214.961 | AH17: =P17+Q17 -> -221.40983 | AI17: =R17+S17 -> -228.05212 | AJ17: =T17+U17 -> -234.89369 | AK17: =V17+W17 -> -241.9405
B18: Fx growth (%) | C18: =IFERROR(C17/#REF!-1, "-") -> - | D18: =IFERROR(D17/#REF!-1, "-") -> - | E18: =IFERROR(E17/#REF!-1, "-") -> - | F18: =F17/C21 -> 0.028208745 | G18: =G17/D21 -> 0.042961005 | H18: =H17/F21 -> 0.035657686 | I18: =I17/G21 -> -0.091954023 | J18: =J17/H21 -> -0.11723254 | K18: =K17/I21 -> -0.062832286 | L18: =L17/J21 -> -0.028070175 | M18: -0.01 | N18: 0.03 | O18: 0.03 | P18: 0.03 | Q18: 0.03 | R18: 0.03 | S18: 0.03 | T18: 0.03 | U18: 0.03 | V18: 0.03 | W18: 0.03 | AC18: =AC17/E21 -> 0.034340659 | AD18: =AD17/AC21 -> -0.019378098 | AE18: =AE17/AD21 -> -0.09554999 | AF18: =AF17/AE17-1 -> -0.57923387 | AG18: =AG17/AF17-1 -> 0.03 | AH18: =AH17/AG17-1 -> 0.03 | AI18: =AI17/AH17-1 -> 0.03 | AJ18: =AJ17/AI17-1 -> 0.03 | AK18: =AK17/AJ17-1 -> 0.03
B19: Scope | F19: 0 | G19: =AC19-F19 -> 0 | H19: 48 | I19: =AD19-H19 -> 36 | J19: 79 | K19: =AE19-J19 -> 32 | L19: 5 | M19: =K19*(1+M20) -> 31.68 | N19: =L19*(1+N20) -> 5.15 | O19: =M19*(1+O20) -> 32.6304 | P19: =N19*(1+P20) -> 5.3045 | Q19: =O19*(1+Q20) -> 33.609312 | R19: =P19*(1+R20) -> 5.463635 | S19: =Q19*(1+S20) -> 34.617591 | T19: =R19*(1+T20) -> 5.6275441 | ... W19: =U19*(1+W20) -> 36.725803 | AC19: 0 | AD19: 84 | AE19: 111 | AF19: =L19+M19 -> 36.68 | AG19: =N19+O19 -> 37.7804 | AH19: =P19+Q19 -> 38.913812 | AI19: =R19+S19 -> 40.081226 | AJ19: =T19+U19 -> 41.283663 | AK19: =V19+W19 -> 42.522173
B20: Scope growth (%) | C20: =IFERROR(C19/#REF!-1, "-") -> - | D20: =IFERROR(D19/#REF!-1, "-") -> - | E20: =IFERROR(E19/#REF!-1, "-") -> - | F20: =F19/C21 -> 0 | G20: =G19/D21 -> 0 | H20: =H19/F21 -> 0.019017433 | I20: =I19/G21 -> 0.018808777 | J20: =J19/H21 -> 0.025304292 | K20: =K19/I21 -> 0.015466409 | L20: =L19/J21 -> 0.001754386 | M20: -0.01 | N20: 0.03 | O20: 0.03 | P20: 0.03 | Q20: 0.03 | R20: 0.03 | S20: 0.03 | T20: 0.03 | U20: 0.03 | V20: 0.03 | W20: 0.03 | AC20: =AC19/E21 -> 0 | AD20: =AD19/AC21 -> 0.018927445 | AE20: =AE19/AD21 -> 0.021383163 | AF20: =IFERROR(AF19/AE19-1, "-") -> -0.66954955 | AG20: =IFERROR(AG19/AF19-1, "-") -> 0.03 | AH20: =IFERROR(AH19/AG19-1, "-") -> 0.03 | AI20: =IFERROR(AI19/AH19-1, "-") -> 0.03 | AJ20: =IFERROR(AJ19/AI19-1, "-") -> 0.03 | AK20: =IFERROR(AK19/AJ19-1, "-") -> 0.03
B21: Total Sales - Asia/Row | C21: 2127 | D21: =E21-C21 -> 1513 | E21: 3640 | F21: =C21+F15+F17+F19-1 -> 2524 | G21: =D21+G15+G17+G19 -> 1914 | H21: =F21+H15+H17+H19 -> 3122 | I21: =G21+I15+I17+I19 -> 2069 | J21: =H21+J15+J17+J19-1 -> 2850 | K21: =I21+K15+K17+K19 -> 2122 | L21: =J21+L15+L17+L19 -> 2619 | M21: =K21+M15+M17+M19 -> 2174.47 | N21: =L21+N15+N17+N19 -> 2381.07 | O21: =M21+O15+O17+O19 -> 2228.5141 | P21: =N21+P15+P17+P19 -> 2136.0021 | Q21: =O21+Q15+Q17+Q19 -> 2284.1795 | R21: =P21+R15+R17+R19 -> 1883.5822 | ... W21: =U21+W15+W17+W19 -> 2461.3975 | AC21: =E21+AC15+AC17+AC19-1 -> 4438 | AD21: =AC21+AD15+AD17+AD19 -> 5191 | AE21: =AD21+AE15+AE17+AE19 -> 4973 | AF21: =AE21+AF15+AF17+AF19 -> 4794.47 | AG21: =AF21+AG15+AG17+AG19 -> 4610.5841 | AH21: =AG21+AH15+AH17+AH19 -> 4421.1816 | AI21: =AH21+AI15+AI17+AI19 -> 4226.0971 | AJ21: =AI21+AJ15+AJ17+AJ19 -> 4025.16 | AK21: =AJ21+AK15+AK17+AK19 -> 3818.1948
B22: Growth (%) | C22: =IFERROR(C21/#REF!-1, "-") -> - | D22: =IFERROR(D21/#REF!-1, "-") -> - | E22: =IFERROR(E21/#REF!-1, "-") -> - | F22: =IFERROR(F21/C21-1, "-") -> 0.18664786 | G22: =IFERROR(G21/D21-1, "-") -> 0.26503635 | H22: =IFERROR(H21/F21-1, "-") -> 0.23692552 | I22: =IFERROR(I21/G21-1, "-") -> 0.080982236 | J22: =IFERROR(J21/H21-1, "-") -> -0.087123639 | K22: =IFERROR(K21/I21-1, "-") -> 0.02561624 | L22: =IFERROR(L21/J21-1, "-") -> -0.081052632 | M22: =IFERROR(M21/K21-1, "-") -> 0.024726673 | N22: =IFERROR(N21/L21-1, "-") -> -0.090847652 | O22: =IFERROR(O21/M21-1, "-") -> 0.024853918 | ... W22: =IFERROR(W21/U21-1, "-") -> 0.025338608 | AC22: =IFERROR(AC21/E21-1, "-") -> 0.21923077 | AD22: =IFERROR(AD21/AC21-1, "-") -> 0.16967102 | AE22: =IFERROR(AE21/AD21-1, "-") -> -0.041995762 | AF22: =IFERROR(AF21/AE21-1, "-") -> -0.035899859 | AG22: =IFERROR(AG21/AF21-1, "-") -> -0.038353749 | AH22: =IFERROR(AH21/AG21-1, "-") -> -0.041079931 | AI22: =IFERROR(AI21/AH21-1, "-") -> -0.04412498 | AJ22: =IFERROR(AJ21/AI21-1, "-") -> -0.047546728 | AK22: =IFERROR(AK21/AJ21-1, "-") -> -0.051417882
B24: Europe
B25: Organic | F25: 300 | G25: =AC25-F25 -> 183 | H25: 108 | I25: =AD25-H25 -> 143 | J25: -84 | K25: =AE25-J25 -> -74 | L25: -30 | M25: =K25*(1+M26) -> -73.26 | N25: =L25*(1+N26) -> -30.9 | O25: =M25*(1+O26) -> -75.4578 | P25: =N25*(1+P26) -> -31.827 | Q25: =O25*(1+Q26) -> -77.721534 | R25: =P25*(1+R26) -> -32.78181 | S25: =Q25*(1+S26) -> -80.05318 | T25: =R25*(1+T26) -> -33.765264 | ... W25: =U25*(1+W26) -> -84.928419 | AC25: 483 | AD25: 251 | AE25: -158 | AF25: =L25+M25 -> -103.26 | AG25: =N25+O25 -> -106.3578 | AH25: =P25+Q25 -> -109.54853 | AI25: =R25+S25 -> -112.83499 | AJ25: =T25+U25 -> -116.22004 | AK25: =V25+W25 -> -119.70664
B26: Organic growth (%) | C26: =IFERROR(C25/#REF!-1, "-") -> - | D26: =IFERROR(D25/#REF!-1, "-") -> - | E26: =IFERROR(E25/#REF!-1, "-") -> - | F26: =F25/C31 -> 0.20604396 | G26: =G25/D31 -> 0.16621253 | H26: =H25/F31 -> 0.060100167 | I26: =I25/G31 -> 0.10727682 | J26: =J25/H31 -> -0.042232278 | K26: =K25/I31 -> -0.050101557 | L26: =L25/J31 -> -0.015965939 | M26: -0.01 | N26: 0.03 | O26: 0.03 | P26: 0.03 | Q26: 0.03 | R26: 0.03 | S26: 0.03 | T26: 0.03 | U26: 0.03 | V26: 0.03 | W26: 0.03 | AC26: =AC25/E31 -> 0.18889323 | AD26: =AD25/AC31 -> 0.080191693 | AE26: =AE25/AD31 -> -0.045598846 | AF26: =AF25/AE25-1 -> -0.3464557 | AG26: =AG25/AF25-1 -> 0.03 | AH26: =AH25/AG25-1 -> 0.03 | AI26: =AI25/AH25-1 -> 0.03 | AJ26: =AJ25/AI25-1 -> 0.03 | AK26: =AK25/AJ25-1 -> 0.03
B27: Fx | F27: 22 | G27: =AC27-F27 -> 13 | H27: 45 | I27: =AD27-H27 -> -18 | J27: -37 | K27: =AE27-J27 -> 14 | L27: 1 | M27: =K27*(1+M28) -> 13.86 | N27: =L27*(1+N28) -> 1.03 | O27: =M27*(1+O28) -> 14.2758 | P27: =N27*(1+P28) -> 1.0609 | Q27: =O27*(1+Q28) -> 14.704074 | R27: =P27*(1+R28) -> 1.092727 | S27: =Q27*(1+S28) -> 15.145196 | T27: =R27*(1+T28) -> 1.1255088 | ... W27: =U27*(1+W28) -> 16.067539 | AC27: 35 | AD27: 27 | AE27: -23 | AF27: =L27+M27 -> 14.86 | AG27: =N27+O27 -> 15.3058 | AH27: =P27+Q27 -> 15.764974 | AI27: =R27+S27 -> 16.237923 | AJ27: =T27+U27 -> 16.725061 | AK27: =V27+W27 -> 17.226813
B28: Fx growth (%) | C28: =IFERROR(C27/#REF!-1, "-") -> - | D28: =IFERROR(D27/#REF!-1, "-") -> - | E28: =IFERROR(E27/#REF!-1, "-") -> - | F28: =F27/C31 -> 0.01510989 | G28: =G27/D31 -> 0.011807448 | H28: =H27/F31 -> 0.025041736 | I28: =I27/G31 -> -0.013503376 | J28: =J27/H31 -> -0.018602313 | K28: =K27/I31 -> 0.009478673 | L28: =L27/J31 -> 0.00053219798 | M28: -0.01 | N28: 0.03 | O28: 0.03 | P28: 0.03 | Q28: 0.03 | R28: 0.03 | S28: 0.03 | T28: 0.03 | U28: 0.03 | V28: 0.03 | W28: 0.03 | AC28: =AC27/E31 -> 0.013687916 | AD28: =AD27/AC31 -> 0.0086261981 | AE28: =AE27/AD31 -> -0.0066378066 | AF28: =AF27/AE27-1 -> -1.646087 | AG28: =AG27/AF27-1 -> 0.03 | AH28: =AH27/AG27-1 -> 0.03 | AI28: =AI27/AH27-1 -> 0.03 | AJ28: =AJ27/AI27-1 -> 0.03 | AK28: =AK27/AJ27-1 -> 0.03
B29: Scope | F29: 19 | G29: =AC29-F29 -> 36 | H29: 38 | I29: =AD29-H29 -> 19 | J29: 12 | K29: =AE29-J29 -> -11 | L29: -33 | M29: =K29*(1+M30) -> -10.89 | N29: =L29*(1+N30) -> -33.99 | O29: =M29*(1+O30) -> -11.2167 | P29: =N29*(1+P30) -> -35.0097 | Q29: =O29*(1+Q30) -> -11.553201 | R29: =P29*(1+R30) -> -36.059991 | S29: =Q29*(1+S30) -> -11.899797 | T29: =R29*(1+T30) -> -37.141791 | ... W29: =U29*(1+W30) -> -12.624495 | AC29: 55 | AD29: 57 | AE29: 1 | AF29: =L29+M29 -> -43.89 | AG29: =N29+O29 -> -45.2067 | AH29: =P29+Q29 -> -46.562901 | AI29: =R29+S29 -> -47.959788 | AJ29: =T29+U29 -> -49.398582 | AK29: =V29+W29 -> -50.880539
B30: Scope growth (%) | C30: =IFERROR(C29/#REF!-1, "-") -> - | D30: =IFERROR(D29/#REF!-1, "-") -> - | E30: =IFERROR(E29/#REF!-1, "-") -> - | F30: =F29/C31 -> 0.013049451 | G30: =G29/D31 -> 0.032697548 | H30: =H29/F31 -> 0.021146355 | I30: =I29/G31 -> 0.014253563 | J30: =J29/H31 -> 0.0060331825 | K30: =K29/I31 -> -0.0074475288 | L30: =L29/J31 -> -0.017562533 | M30: -0.01 | N30: 0.03 | O30: 0.03 | P30: 0.03 | Q30: 0.03 | R30: 0.03 | S30: 0.03 | T30: 0.03 | U30: 0.03 | V30: 0.03 | W30: 0.03 | AC30: =AC29/E31 -> 0.021509582 | AD30: =AD29/AC31 -> 0.018210863 | AE30: =AE29/AD31 -> 0.00028860029 | AF30: =AF29/AE29-1 -> -44.89 | AG30: =AG29/AF29-1 -> 0.03 | AH30: =AH29/AG29-1 -> 0.03 | AI30: =AI29/AH29-1 -> 0.03 | AJ30: =AJ29/AI29-1 -> 0.03 | AK30: =AK29/AJ29-1 -> 0.03
B31: Total Sales - Europe | C31: 1456 | D31: =E31-C31 -> 1101 | E31: 2557 | F31: =C31+F25+F27+F29 -> 1797 | G31: =D31+G25+G27+G29 -> 1333 | H31: =F31+H25+H27+H29+1 -> 1989 | I31: =G31+I25+I27+I29 -> 1477 | J31: =H31+J25+J27+J29-1 -> 1879 | K31: =I31+K25+K27+K29 -> 1406 | L31: =J31+L25+L27+L29-1 -> 1816 | M31: =K31+M25+M27+M29 -> 1335.71 | N31: =L31+N25+N27+N29 -> 1752.14 | O31: =M31+O25+O27+O29 -> 1263.3113 | P31: =N31+P25+P27+P29 -> 1686.3642 | Q31: =O31+Q25+Q27+Q29 -> 1188.7406 | R31: =P31+R25+R27+R29 -> 1618.6151 | S31: =Q31+S25+S27+S29 -> 1111.9329 | T31: =R31+T25+T27+T29 -> 1548.8336 | ... W31: =U31+W25+W27+W29 -> 951.33547 | AC31: =E31+AC25+AC27+AC29 -> 3130 | AD31: =AC31+AD25+AD27+AD29 -> 3465 | AE31: =AD31+AE25+AE27+AE29 -> 3285 | AF31: =AE31+AF25+AF27+AF29 -> 3152.71 | AG31: =AF31+AG25+AG27+AG29 -> 3016.4513 | AH31: =AG31+AH25+AH27+AH29 -> 2876.1048 | AI31: =AH31+AI25+AI27+AI29 -> 2731.548 | AJ31: =AI31+AJ25+AJ27+AJ29 -> 2582.6544 | AK31: =AJ31+AK25+AK27+AK29 -> 2429.2941
B32: Growth (%) | C32: =IFERROR(C31/#REF!-1, "-") -> - | D32: =IFERROR(D31/#REF!-1, "-") -> - | E32: =IFERROR(E31/#REF!-1, "-") -> - | F32: =IFERROR(F31/C31-1, "-") -> 0.2342033 | G32: =IFERROR(G31/D31-1, "-") -> 0.21071753 | H32: =IFERROR(H31/F31-1, "-") -> 0.10684474 | I32: =IFERROR(I31/G31-1, "-") -> 0.10802701 | J32: =IFERROR(J31/H31-1, "-") -> -0.055304173 | K32: =IFERROR(K31/I31-1, "-") -> -0.048070413 | L32: =IFERROR(L31/J31-1, "-") -> -0.033528473 | M32: =IFERROR(M31/K31-1, "-") -> -0.049992888 | N32: =IFERROR(N31/L31-1, "-") -> -0.035165198 | O32: =IFERROR(O31/M31-1, "-") -> -0.054202409 | ... W32: =IFERROR(W31/U31-1, "-") -> -0.078895943 | AC32: =IFERROR(AC31/E31-1, "-") -> 0.22409073 | AD32: =IFERROR(AD31/AC31-1, "-") -> 0.10702875 | AE32: =IFERROR(AE31/AD31-1, "-") -> -0.051948052 | AF32: =IFERROR(AF31/AE31-1, "-") -> -0.040270928 | AG32: =IFERROR(AG31/AF31-1, "-") -> -0.043219548 | AH32: =IFERROR(AH31/AG31-1, "-") -> -0.04652701 | AI32: =IFERROR(AI31/AH31-1, "-") -> -0.05026133 | AJ32: =IFERROR(AJ31/AI31-1, "-") -> -0.054508858 | AK32: =IFERROR(AK31/AJ31-1, "-") -> -0.059380909
B34: Total
B35: Organic | F35: =F5+F15+F25 -> 834 | G35: =AC35-F35 -> 642 | H35: =H5+H15+H25 -> 686 | I35: =AD35-H35 -> 382 | J35: =J5+J15+J25 -> -213 | K35: =AE35-J35 -> 63 | L35: =L5+L15+L25 -> -267 | M35: =AF35-L35 -> 62.37 | N35: =N5+N15+N25 -> -275.01 | O35: =AG35-N35 -> 64.2411 | P35: =P5+P15+P25 -> -283.2603 | Q35: =AH35-P35 -> 66.168333 | R35: =R5+R15+R25 -> -291.75811 | S35: =AI35-R35 -> 68.153383 | T35: =T5+T15+T25 -> -300.51085 | U35: =AJ35-T35 -> 70.197984 | V35: =V5+V15+V25 -> -309.52618 | W35: =AK35-V35 -> 72.303924 | AC35: =AC5+AC15+AC25 -> 1476 | AD35: =AD5+AD15+AD25 -> 1068 | AE35: =AE5+AE15+AE25 -> -150 | AF35: =AF5+AF15+AF25 -> -204.63 | AG35: =AG5+AG15+AG25 -> -210.7689 | AH35: =AH5+AH15+AH25 -> -217.09197 | AI35: =AI5+AI15+AI25 -> -223.60473 | AJ35: =AJ5+AJ15+AJ25 -> -230.31287 | AK35: =AK5+AK15+AK25 -> -237.22225
B36: Organic growth (%) | F36: =F35/C41 -> 0.16730191 | G36: =G35/D41 -> 0.16723105 | H36: =H35/F41 -> 0.11511999 | I36: =I35/G41 -> 0.080556727 | J36: =J35/H41 -> -0.029932546 | K36: =K35/I41 -> 0.012547301 | L36: =L35/J41 -> -0.040509786 | M36: =M35/K41 -> 0.012456561 | N36: =N35/L41 -> -0.044528821 | O36: =O35/M41 -> 0.012865872 | ... W36: =W35/U41 -> 0.014655957 | AC36: =AC35/E41 -> 0.16727108 | AD36: =AD35/AC41 -> 0.099803757 | AE36: =AE35/AD41 -> -0.012358903 | AF36: =AF35/AE41 -> -0.017643559 | AG36: =AG35/AF41 -> -0.018870647 | AH36: =AH35/AG41 -> -0.02023712 | AI36: =AI35/AH41 -> -0.021767448 | AJ36: =AJ35/AI41 -> -0.023492181 | AK36: =AK35/AJ41 -> -0.025449962
B37: Fx | F37: =F7+F17+F27 -> 104 | G37: =AC37-F37 -> 212 | H37: =H7+H17+H27 -> 355 | I37: =AD37-H37 -> -236 | J37: =J7+J17+J27 -> -576 | K37: =AE37-J37 -> -208 | L37: =L7+L17+L27 -> -177 | M37: =AF37-L37 -> -205.92 | N37: =N7+N17+N27 -> -182.31 | O37: =AG37-N37 -> -212.0976 | P37: =P7+P17+P27 -> -187.7793 | Q37: =AH37-P37 -> -218.46053 | R37: =R7+R17+R27 -> -193.41268 | S37: =AI37-R37 -> -225.01434 | T37: =T7+T17+T27 -> -199.21506 | U37: =AJ37-T37 -> -231.76477 | V37: =V7+V17+V27 -> -205.19151 | W37: =AK37-V37 -> -238.71772 | AC37: =AC7+AC17+AC27 -> 316 | AD37: =AD7+AD17+AD27 -> 119 | AE37: =AE7+AE17+AE27 -> -784 | AF37: =AF7+AF17+AF27 -> -382.92 | AG37: =AG7+AG17+AG27 -> -394.4076 | AH37: =AH7+AH17+AH27 -> -406.23983 | AI37: =AI7+AI17+AI27 -> -418.42702 | AJ37: =AJ7+AJ17+AJ27 -> -430.97983 | AK37: =AK7+AK17+AK27 -> -443.90923
B38: Fx growth (%) | F38: =F37/C41 -> 0.020862588 | G38: =G37/D41 -> 0.055222714 | H38: =H37/F41 -> 0.059573754 | I38: =I37/G41 -> -0.04976803 | J38: =J37/H41 -> -0.080944351 | K38: =K37/I41 -> -0.041426011 | L38: =L37/J41 -> -0.026854802 | M38: =M37/K41 -> -0.041126423 | N38: =N37/L41 -> -0.029519106 | O38: =O37/M41 -> -0.0424778 | ... W38: =W37/U41 -> -0.048387922 | AC38: =AC37/E41 -> 0.035811423 | AD38: =AD37/AC41 -> 0.011120456 | AE38: =AE37/AD41 -> -0.064595864 | AF38: =AF37/AE41 -> -0.033016037 | AG38: =AG37/AF41 -> -0.035312262 | AH38: =AH37/AG41 -> -0.037869315 | AI38: =AI37/AH41 -> -0.040732987 | AJ38: =AJ37/AI41 -> -0.043960445 | AK38: =AK37/AJ41 -> -0.047624002
B39: Scope | F39: =F9+F19+F29 -> 36 | G39: =AC39-F39 -> 49 | H39: =H9+H19+H29 -> 116 | I39: =AD39-H39 -> 133 | J39: =J9+J19+J29 -> 264 | K39: =AE39-J39 -> 131 | L39: =L9+L19+L29 -> 29 | M39: =AF39-L39 -> 129.69 | N39: =N9+N19+N29 -> 29.87 | O39: =AG39-N39 -> 133.5807 | P39: =P9+P19+P29 -> 30.7661 | Q39: =AH39-P39 -> 137.58812 | R39: =R9+R19+R29 -> 31.689083 | S39: =AI39-R39 -> 141.71576 | T39: =T9+T19+T29 -> 32.639755 | U39: =AJ39-T39 -> 145.96724 | V39: =V9+V19+V29 -> 33.618948 | W39: =AK39-V39 -> 150.34625 | AC39: =AC9+AC19+AC29 -> 85 | AD39: =AD9+AD19+AD29 -> 249 | AE39: =AE9+AE19+AE29 -> 395 | AF39: =AF9+AF19+AF29 -> 158.69 | AG39: =AG9+AG19+AG29 -> 163.4507 | AH39: =AH9+AH19+AH29 -> 168.35422 | AI39: =AI9+AI19+AI29 -> 173.40485 | AJ39: =AJ9+AJ19+AJ29 -> 178.60699 | AK39: =AK9+AK19+AK29 -> 183.9652
B40: Scope growth (%) | F40: =F39/C41 -> 0.007221665 | G40: =G39/D41 -> 0.012763741 | H40: =H39/F41 -> 0.019466353 | I40: =I39/G41 -> 0.028047237 | J40: =J39/H41 -> 0.037099494 | K40: =K39/I41 -> 0.02609042 | L40: =L39/J41 -> 0.0043999393 | M40: =M39/K41 -> 0.025901738 | N40: =N39/L41 -> 0.0048364637 | O40: =O39/M41 -> 0.026752845 | ... W40: =W39/U41 -> 0.030475085 | AC40: =AC39/E41 -> 0.0096328196 | AD40: =AD39/AC41 -> 0.023268853 | AE40: =AE39/AD41 -> 0.03254511 | AF40: =AF39/AE41 -> 0.013682531 | AG40: =AG39/AF41 -> 0.014634135 | AH40: =AH39/AG41 -> 0.015693831 | AI40: =AI39/AH41 -> 0.016880596 | AJ40: =AJ39/AI41 -> 0.018218121 | AK40: =AK39/AJ41 -> 0.019736375
B41: Total Sales | C41: =C11+C31+C21 -> 4985 | D41: =D11+D31+D21 -> 3839 | E41: =E11+E31+E21 -> 8824 | F41: =F11+F31+F21 -> 5959 | G41: =D41+G35+G37+G39 -> 4742 | H41: =F41+H35+H37+H39 -> 7116 | I41: =I11+I31+I21 -> 5021 | J41: =H41+J35+J37+J39 -> 6591 | K41: =K11+K31+K21 -> 5007 | L41: =J41+L35+L37+L39 -> 6176 | M41: =M11+M31+M21 -> 4993.14 | N41: =L41+N35+N37+N39 -> 5748.55 | O41: =O11+O31+O21 -> 4978.8642 | P41: =N41+P35+P37+P39 -> 5308.2765 | Q41: =Q11+Q31+Q21 -> 4964.1601 | R41: =P41+R35+R37+R39 -> 4854.7948 | S41: =S11+S31+S21 -> 4949.0149 | T41: =R41+T35+T37+T39 -> 4387.7086 | U41: =U11+U31+U21 -> 4933.4154 | V41: =T41+V35+V37+V39 -> 3906.6099 | W41: =W11+W31+W21 -> 4917.3478 | AC41: =E41+AC35+AC37+AC39 -> 10701 | AD41: =AC41+AD35+AD37+AD39 -> 12137 | AE41: =AD41+AE35+AE37+AE39 -> 11598 | AF41: =AE41+AF35+AF37+AF39 -> 11169.14 | AG41: =AF41+AG35+AG37+AG39 -> 10727.414 | AH41: =AG41+AH35+AH37+AH39 -> 10272.437 | AI41: =AH41+AI35+AI37+AI39 -> 9803.8097 | AJ41: =AI41+AJ35+AJ37+AJ39 -> 9321.124 | AK41: =AJ41+AK35+AK37+AK39 -> 8823.9577
B42: Growth (%) | C42: =IFERROR(C41/#REF!-1, "-") -> - | D42: =IFERROR(D41/#REF!-1, "-") -> - | E42: =IFERROR(E41/#REF!-1, "-") -> - | F42: =IFERROR(F41/C41-1, "-") -> 0.19538616 | G42: =IFERROR(G41/D41-1, "-") -> 0.2352175 | H42: =IFERROR(H41/F41-1, "-") -> 0.19416009 | I42: =IFERROR(I41/G41-1, "-") -> 0.058835934 | J42: =IFERROR(J41/H41-1, "-") -> -0.073777403 | K42: =IFERROR(K41/I41-1, "-") -> -0.0027882892 | L42: =IFERROR(L41/J41-1, "-") -> -0.062964649 | M42: =IFERROR(M41/K41-1, "-") -> -0.0027681246 | N42: =IFERROR(N41/L41-1, "-") -> -0.069211464 | O42: =IFERROR(O41/M41-1, "-") -> -0.0028590827 | ... W42: =IFERROR(W41/U41-1, "-") -> -0.0032568794 | AC42: =IFERROR(AC41/E41-1, "-") -> 0.21271532 | AD42: =IFERROR(AD41/AC41-1, "-") -> 0.13419307 | AE42: =IFERROR(AE41/AD41-1, "-") -> -0.044409656 | AF42: =IFERROR(AF41/AE41-1, "-") -> -0.036977065 | AG42: =IFERROR(AG41/AF41-1, "-") -> -0.039548775 | AH42: =IFERROR(AH41/AG41-1, "-") -> -0.042412604 | AI42: =IFERROR(AI41/AH41-1, "-") -> -0.045619839 | AJ42: =IFERROR(AJ41/AI41-1, "-") -> -0.049234504 | AK42: =IFERROR(AK41/AJ41-1, "-") -> -0.053337589

Sheet Revenue Model-Segment
B2: In Euro millions | C2: H1'21 | D2: H2'21 | E2: FY21 | F2: H1'22 | G2: H2'22 | H2: H1'23 | I2: H2'23 | J2: H1'24 | K2: H2'24 | L2: H1'25 | M2: H2'25 | N2: H1'26 | O2: H2'26 | P2: H1'27 | Q2: H2'27 | R2: H1'28 | S2: H2'28 | T2: H1'29 | U2: H2'29 | V2: H1'30 | W2: H2'30 | AC2: FY22 | AD2: FY23 | AE2: FY24 | AF2: FY25 | AG2: FY26 | AH2: FY27 | AI2: FY28 | AJ2: FY29 | AK2: FY30
B4: Americas
B5: Organic | G5: =AC5-F5 -> 0 | I5: =AD5-H5 -> 0 | K5: =AE5-J5 -> 0 | M5: =K5*(1+M6) -> 0 | N5: =L5*(1+N6) -> 0 | O5: =M5*(1+O6) -> 0 | P5: =N5*(1+P6) -> 0 | Q5: =O5*(1+Q6) -> 0 | R5: =P5*(1+R6) -> 0 | S5: =Q5*(1+S6) -> 0 | T5: =R5*(1+T6) -> 0 | ... W5: =U5*(1+W6) -> 0 | AF5: =L5+M5 -> 0 | AG5: =N5+O5 -> 0 | AH5: =P5+Q5 -> 0 | AI5: =R5+S5 -> 0 | AJ5: =T5+U5 -> 0 | AK5: =V5+W5 -> 0
B6: Organic growth (%) | C6: =IFERROR(C5/#REF!-1, "-") -> - | D6: =IFERROR(D5/#REF!-1, "-") -> - | E6: =IFERROR(E5/#REF!-1, "-") -> - | F6: =F5/C11 -> #DIV/0! | G6: =G5/D11 -> #DIV/0! | H6: =H5/F11 -> 0 | I6: =I5/G11 -> #DIV/0! | J6: =J5/H11 -> #DIV/0! | K6: =K5/I11 -> #DIV/0! | L6: =L5/J11 -> #DIV/0! | AC6: =AC5/E11 -> #DIV/0! | AD6: =AD5/AC11 -> 0 | AE6: =AE5/AD11 -> 0 | AF6: =AF5/AE5-1 -> #DIV/0! | AG6: =AG5/AF5-1 -> #DIV/0! | AH6: =AH5/AG5-1 -> #DIV/0! | AI6: =AI5/AH5-1 -> #DIV/0! | AJ6: =AJ5/AI5-1 -> #DIV/0! | AK6: =AK5/AJ5-1 -> #DIV/0!
B7: Fx | G7: =AC7-F7 -> 0 | I7: =AD7-H7 -> 0 | K7: =AE7-J7 -> 0 | M7: =K7*(1+M8) -> 0 | N7: =L7*(1+N8) -> 0 | O7: =M7*(1+O8) -> 0 | P7: =N7*(1+P8) -> 0 | Q7: =O7*(1+Q8) -> 0 | R7: =P7*(1+R8) -> 0 | S7: =Q7*(1+S8) -> 0 | T7: =R7*(1+T8) -> 0 | ... W7: =U7*(1+W8) -> 0 | AF7: =L7+M7 -> 0 | AG7: =N7+O7 -> 0 | AH7: =P7+Q7 -> 0 | AI7: =R7+S7 -> 0 | AJ7: =T7+U7 -> 0 | AK7: =V7+W7 -> 0
B8: Fx growth (%) | C8: =IFERROR(C7/#REF!-1, "-") -> - | D8: =IFERROR(D7/#REF!-1, "-") -> - | E8: =IFERROR(E7/#REF!-1, "-") -> - | F8: =F7/C11 -> #DIV/0! | G8: =G7/D11 -> #DIV/0! | H8: =H7/F11 -> 0 | I8: =I7/G11 -> #DIV/0! | J8: =J7/H11 -> #DIV/0! | K8: =K7/I11 -> #DIV/0! | L8: =L7/J11 -> #DIV/0! | AC8: =AC7/E11 -> #DIV/0! | AD8: =AD7/AC11 -> 0 | AE8: =AE7/AD11 -> 0 | AF8: =AF7/AE7-1 -> #DIV/0! | AG8: =AG7/AF7-1 -> #DIV/0! | AH8: =AH7/AG7-1 -> #DIV/0! | AI8: =AI7/AH7-1 -> #DIV/0! | AJ8: =AJ7/AI7-1 -> #DIV/0! | AK8: =AK7/AJ7-1 -> #DIV/0!
B9: Scope | G9: =AC9-F9 -> 0 | I9: =AD9-H9 -> 0 | K9: =AE9-J9 -> 0 | M9: =K9*(1+M10) -> 0 | N9: =L9*(1+N10) -> 0 | O9: =M9*(1+O10) -> 0 | P9: =N9*(1+P10) -> 0 | Q9: =O9*(1+Q10) -> 0 | R9: =P9*(1+R10) -> 0 | S9: =Q9*(1+S10) -> 0 | T9: =R9*(1+T10) -> 0 | ... W9: =U9*(1+W10) -> 0 | AF9: =L9+M9 -> 0 | AG9: =N9+O9 -> 0 | AH9: =P9+Q9 -> 0 | AI9: =R9+S9 -> 0 | AJ9: =T9+U9 -> 0 | AK9: =V9+W9 -> 0
B10: Scope growth (%) | C10: =IFERROR(C9/#REF!-1, "-") -> - | D10: =IFERROR(D9/#REF!-1, "-") -> - | E10: =IFERROR(E9/#REF!-1, "-") -> - | F10: =F9/C11 -> #DIV/0! | G10: =G9/D11 -> #DIV/0! | H10: =H9/F11 -> 0 | I10: =I9/G11 -> #DIV/0! | J10: =J9/H11 -> #DIV/0! | K10: =K9/I11 -> #DIV/0! | L10: =L9/J11 -> #DIV/0! | AC10: =AC9/E11 -> #DIV/0! | AD10: =AD9/AC11 -> 0 | AE10: =AE9/AD11 -> 0 | AF10: =IFERROR(AF9/AE9-1, "-") -> - | AG10: =IFERROR(AG9/AF9-1, "-") -> - | AH10: =IFERROR(AH9/AG9-1, "-") -> - | AI10: =IFERROR(AI9/AH9-1, "-") -> - | AJ10: =IFERROR(AJ9/AI9-1, "-") -> - | AK10: =IFERROR(AK9/AJ9-1, "-") -> -
B11: Total Sales - Americas | D11: =E11-C11 -> 0 | F11: =C11+F5+F7+F9+1 -> 1 | G11: =D11+G5+G7+G9 -> 0 | H11: =F11+H5+H7+H9-1 -> 0 | I11: =G11+I5+I7+I9 -> 0 | J11: =H11+J5+J7+J9 -> 0 | K11: =I11+K5+K7+K9 -> 0 | L11: =J11+L5+L7+L9 -> 0 | M11: =K11+M5+M7+M9 -> 0 | N11: =L11+N5+N7+N9 -> 0 | O11: =M11+O5+O7+O9 -> 0 | P11: =N11+P5+P7+P9 -> 0 | ... W11: =U11+W5+W7+W9 -> 0 | AC11: =E11+AC5+AC7+AC9+1 -> 1 | AD11: =AC11+AD5+AD7+AD9 -> 1 | AE11: =AD11+AE5+AE7+AE9 -> 1 | AF11: =AE11+AF5+AF7+AF9 -> 1 | AG11: =AF11+AG5+AG7+AG9 -> 1 | AH11: =AG11+AH5+AH7+AH9 -> 1 | AI11: =AH11+AI5+AI7+AI9 -> 1 | AJ11: =AI11+AJ5+AJ7+AJ9 -> 1 | AK11: =AJ11+AK5+AK7+AK9 -> 1
B12: Growth (%) | C12: =IFERROR(C11/#REF!-1, "-") -> - | D12: =IFERROR(D11/#REF!-1, "-") -> - | E12: =IFERROR(E11/#REF!-1, "-") -> - | F12: =IFERROR(F11/C11-1, "-") -> - | G12: =IFERROR(G11/D11-1, "-") -> - | H12: =IFERROR(H11/F11-1, "-") -> -1 | I12: =IFERROR(I11/G11-1, "-") -> - | J12: =IFERROR(J11/H11-1, "-") -> - | K12: =IFERROR(K11/I11-1, "-") -> - | L12: =IFERROR(L11/J11-1, "-") -> - | M12: =IFERROR(M11/K11-1, "-") -> - | N12: =IFERROR(N11/L11-1, "-") -> - | O12: =IFERROR(O11/M11-1, "-") -> - | ... W12: =IFERROR(W11/U11-1, "-") -> - | AC12: =IFERROR(AC11/E11-1, "-") -> - | AD12: =IFERROR(AD11/AC11-1, "-") -> 0 | AE12: =IFERROR(AE11/AD11-1, "-") -> 0 | AF12: =IFERROR(AF11/AE11-1, "-") -> 0 | AG12: =IFERROR(AG11/AF11-1, "-") -> 0 | AH12: =IFERROR(AH11/AG11-1, "-") -> 0 | AI12: =IFERROR(AI11/AH11-1, "-") -> 0 | AJ12: =IFERROR(AJ11/AI11-1, "-") -> 0 | AK12: =IFERROR(AK11/AJ11-1, "-") -> 0
B14: Asia/Row
B15: Organic | G15: =AC15-F15 -> 0 | I15: =AD15-H15 -> 0 | K15: =AE15-J15 -> 0 | M15: =K15*(1+M16) -> 0 | N15: =L15*(1+N16) -> 0 | O15: =M15*(1+O16) -> 0 | P15: =N15*(1+P16) -> 0 | Q15: =O15*(1+Q16) -> 0 | R15: =P15*(1+R16) -> 0 | S15: =Q15*(1+S16) -> 0 | T15: =R15*(1+T16) -> 0 | ... W15: =U15*(1+W16) -> 0 | AF15: =L15+M15 -> 0 | AG15: =N15+O15 -> 0 | AH15: =P15+Q15 -> 0 | AI15: =R15+S15 -> 0 | AJ15: =T15+U15 -> 0 | AK15: =V15+W15 -> 0
B16: Organic growth (%) | C16: =IFERROR(C15/#REF!-1, "-") -> - | D16: =IFERROR(D15/#REF!-1, "-") -> - | E16: =IFERROR(E15/#REF!-1, "-") -> - | F16: =F15/C21 -> #DIV/0! | G16: =G15/D21 -> #DIV/0! | H16: =H15/F21 -> 0 | I16: =I15/G21 -> #DIV/0! | J16: =J15/H21 -> 0 | K16: =K15/I21 -> #DIV/0! | L16: =L15/J21 -> 0 | AC16: =AC15/E21 -> #DIV/0! | AD16: =AD15/AC21 -> 0 | AE16: =AE15/AD21 -> 0 | AF16: =AF15/AE15-1 -> #DIV/0! | AG16: =AG15/AF15-1 -> #DIV/0! | AH16: =AH15/AG15-1 -> #DIV/0! | AI16: =AI15/AH15-1 -> #DIV/0! | AJ16: =AJ15/AI15-1 -> #DIV/0! | AK16: =AK15/AJ15-1 -> #DIV/0!
B17: Fx | G17: =AC17-F17 -> 0 | I17: =AD17-H17 -> 0 | K17: =AE17-J17 -> 0 | M17: =K17*(1+M18) -> 0 | N17: =L17*(1+N18) -> 0 | O17: =M17*(1+O18) -> 0 | P17: =N17*(1+P18) -> 0 | Q17: =O17*(1+Q18) -> 0 | R17: =P17*(1+R18) -> 0 | S17: =Q17*(1+S18) -> 0 | T17: =R17*(1+T18) -> 0 | ... W17: =U17*(1+W18) -> 0 | AF17: =L17+M17 -> 0 | AG17: =N17+O17 -> 0 | AH17: =P17+Q17 -> 0 | AI17: =R17+S17 -> 0 | AJ17: =T17+U17 -> 0 | AK17: =V17+W17 -> 0
B18: Fx growth (%) | C18: =IFERROR(C17/#REF!-1, "-") -> - | D18: =IFERROR(D17/#REF!-1, "-") -> - | E18: =IFERROR(E17/#REF!-1, "-") -> - | F18: =F17/C21 -> #DIV/0! | G18: =G17/D21 -> #DIV/0! | H18: =H17/F21 -> 0 | I18: =I17/G21 -> #DIV/0! | J18: =J17/H21 -> 0 | K18: =K17/I21 -> #DIV/0! | L18: =L17/J21 -> 0 | AC18: =AC17/E21 -> #DIV/0! | AD18: =AD17/AC21 -> 0 | AE18: =AE17/AD21 -> 0 | AF18: =AF17/AE17-1 -> #DIV/0! | AG18: =AG17/AF17-1 -> #DIV/0! | AH18: =AH17/AG17-1 -> #DIV/0! | AI18: =AI17/AH17-1 -> #DIV/0! | AJ18: =AJ17/AI17-1 -> #DIV/0! | AK18: =AK17/AJ17-1 -> #DIV/0!
B19: Scope | G19: =AC19-F19 -> 0 | I19: =AD19-H19 -> 0 | K19: =AE19-J19 -> 0 | M19: =K19*(1+M20) -> 0 | N19: =L19*(1+N20) -> 0 | O19: =M19*(1+O20) -> 0 | P19: =N19*(1+P20) -> 0 | Q19: =O19*(1+Q20) -> 0 | R19: =P19*(1+R20) -> 0 | S19: =Q19*(1+S20) -> 0 | T19: =R19*(1+T20) -> 0 | ... W19: =U19*(1+W20) -> 0 | AF19: =L19+M19 -> 0 | AG19: =N19+O19 -> 0 | AH19: =P19+Q19 -> 0 | AI19: =R19+S19 -> 0 | AJ19: =T19+U19 -> 0 | AK19: =V19+W19 -> 0
B20: Scope growth (%) | C20: =IFERROR(C19/#REF!-1, "-") -> - | D20: =IFERROR(D19/#REF!-1, "-") -> - | E20: =IFERROR(E19/#REF!-1, "-") -> - | F20: =F19/C21 -> #DIV/0! | G20: =G19/D21 -> #DIV/0! | H20: =H19/F21 -> 0 | I20: =I19/G21 -> #DIV/0! | J20: =J19/H21 -> 0 | K20: =K19/I21 -> #DIV/0! | L20: =L19/J21 -> 0 | AC20: =AC19/E21 -> #DIV/0! | AD20: =AD19/AC21 -> 0 | AE20: =AE19/AD21 -> 0 | AF20: =IFERROR(AF19/AE19-1, "-") -> - | AG20: =IFERROR(AG19/AF19-1, "-") -> - | AH20: =IFERROR(AH19/AG19-1, "-") -> - | AI20: =IFERROR(AI19/AH19-1, "-") -> - | AJ20: =IFERROR(AJ19/AI19-1, "-") -> - | AK20: =IFERROR(AK19/AJ19-1, "-") -> -
B21: Total Sales - Asia/Row | D21: =E21-C21 -> 0 | F21: =C21+F15+F17+F19-1 -> -1 | G21: =D21+G15+G17+G19 -> 0 | H21: =F21+H15+H17+H19 -> -1 | I21: =G21+I15+I17+I19 -> 0 | J21: =H21+J15+J17+J19-1 -> -2 | K21: =I21+K15+K17+K19 -> 0 | L21: =J21+L15+L17+L19 -> -2 | M21: =K21+M15+M17+M19 -> 0 | N21: =L21+N15+N17+N19 -> -2 | O21: =M21+O15+O17+O19 -> 0 | P21: =N21+P15+P17+P19 -> -2 | Q21: =O21+Q15+Q17+Q19 -> 0 | R21: =P21+R15+R17+R19 -> -2 | ... W21: =U21+W15+W17+W19 -> 0 | AC21: =E21+AC15+AC17+AC19-1 -> -1 | AD21: =AC21+AD15+AD17+AD19 -> -1 | AE21: =AD21+AE15+AE17+AE19 -> -1 | AF21: =AE21+AF15+AF17+AF19 -> -1 | AG21: =AF21+AG15+AG17+AG19 -> -1 | AH21: =AG21+AH15+AH17+AH19 -> -1 | AI21: =AH21+AI15+AI17+AI19 -> -1 | AJ21: =AI21+AJ15+AJ17+AJ19 -> -1 | AK21: =AJ21+AK15+AK17+AK19 -> -1
B22: Growth (%) | C22: =IFERROR(C21/#REF!-1, "-") -> - | D22: =IFERROR(D21/#REF!-1, "-") -> - | E22: =IFERROR(E21/#REF!-1, "-") -> - | F22: =IFERROR(F21/C21-1, "-") -> - | G22: =IFERROR(G21/D21-1, "-") -> - | H22: =IFERROR(H21/F21-1, "-") -> 0 | I22: =IFERROR(I21/G21-1, "-") -> - | J22: =IFERROR(J21/H21-1, "-") -> 1 | K22: =IFERROR(K21/I21-1, "-") -> - | L22: =IFERROR(L21/J21-1, "-") -> 0 | M22: =IFERROR(M21/K21-1, "-") -> - | N22: =IFERROR(N21/L21-1, "-") -> 0 | O22: =IFERROR(O21/M21-1, "-") -> - | ... W22: =IFERROR(W21/U21-1, "-") -> - | AC22: =IFERROR(AC21/E21-1, "-") -> - | AD22: =IFERROR(AD21/AC21-1, "-") -> 0 | AE22: =IFERROR(AE21/AD21-1, "-") -> 0 | AF22: =IFERROR(AF21/AE21-1, "-") -> 0 | AG22: =IFERROR(AG21/AF21-1, "-") -> 0 | AH22: =IFERROR(AH21/AG21-1, "-") -> 0 | AI22: =IFERROR(AI21/AH21-1, "-") -> 0 | AJ22: =IFERROR(AJ21/AI21-1, "-") -> 0 | AK22: =IFERROR(AK21/AJ21-1, "-") -> 0
B24: Europe
B25: Organic | G25: =AC25-F25 -> 0 | I25: =AD25-H25 -> 0 | K25: =AE25-J25 -> 0 | M25: =K25*(1+M26) -> 0 | N25: =L25*(1+N26) -> 0 | O25: =M25*(1+O26) -> 0 | P25: =N25*(1+P26) -> 0 | Q25: =O25*(1+Q26) -> 0 | R25: =P25*(1+R26) -> 0 | S25: =Q25*(1+S26) -> 0 | T25: =R25*(1+T26) -> 0 | ... W25: =U25*(1+W26) -> 0 | AF25: =L25+M25 -> 0 | AG25: =N25+O25 -> 0 | AH25: =P25+Q25 -> 0 | AI25: =R25+S25 -> 0 | AJ25: =T25+U25 -> 0 | AK25: =V25+W25 -> 0
B26: Organic growth (%) | C26: =IFERROR(C25/#REF!-1, "-") -> - | D26: =IFERROR(D25/#REF!-1, "-") -> - | E26: =IFERROR(E25/#REF!-1, "-") -> - | F26: =F25/C31 -> #DIV/0! | G26: =G25/D31 -> #DIV/0! | H26: =H25/F31 -> #DIV/0! | I26: =I25/G31 -> #DIV/0! | J26: =J25/H31 -> 0 | K26: =K25/I31 -> #DIV/0! | L26: =L25/J31 -> #DIV/0! | AC26: =AC25/E31 -> #DIV/0! | AD26: =AD25/AC31 -> #DIV/0! | AE26: =AE25/AD31 -> #DIV/0! | AF26: =AF25/AE25-1 -> #DIV/0! | AG26: =AG25/AF25-1 -> #DIV/0! | AH26: =AH25/AG25-1 -> #DIV/0! | AI26: =AI25/AH25-1 -> #DIV/0! | AJ26: =AJ25/AI25-1 -> #DIV/0! | AK26: =AK25/AJ25-1 -> #DIV/0!
B27: Fx | G27: =AC27-F27 -> 0 | I27: =AD27-H27 -> 0 | K27: =AE27-J27 -> 0 | M27: =K27*(1+M28) -> 0 | N27: =L27*(1+N28) -> 0 | O27: =M27*(1+O28) -> 0 | P27: =N27*(1+P28) -> 0 | Q27: =O27*(1+Q28) -> 0 | R27: =P27*(1+R28) -> 0 | S27: =Q27*(1+S28) -> 0 | T27: =R27*(1+T28) -> 0 | ... W27: =U27*(1+W28) -> 0 | AF27: =L27+M27 -> 0 | AG27: =N27+O27 -> 0 | AH27: =P27+Q27 -> 0 | AI27: =R27+S27 -> 0 | AJ27: =T27+U27 -> 0 | AK27: =V27+W27 -> 0
B28: Fx growth (%) | C28: =IFERROR(C27/#REF!-1, "-") -> - | D28: =IFERROR(D27/#REF!-1, "-") -> - | E28: =IFERROR(E27/#REF!-1, "-") -> - | F28: =F27/C31 -> #DIV/0! | G28: =G27/D31 -> #DIV/0! | H28: =H27/F31 -> #DIV/0! | I28: =I27/G31 -> #DIV/0! | J28: =J27/H31 -> 0 | K28: =K27/I31 -> #DIV/0! | L28: =L27/J31 -> #DIV/0! | AC28: =AC27/E31 -> #DIV/0! | AD28: =AD27/AC31 -> #DIV/0! | AE28: =AE27/AD31 -> #DIV/0! | AF28: =AF27/AE27-1 -> #DIV/0! | AG28: =AG27/AF27-1 -> #DIV/0! | AH28: =AH27/AG27-1 -> #DIV/0! | AI28: =AI27/AH27-1 -> #DIV/0! | AJ28: =AJ27/AI27-1 -> #DIV/0! | AK28: =AK27/AJ27-1 -> #DIV/0!
B29: Scope | G29: =AC29-F29 -> 0 | I29: =AD29-H29 -> 0 | K29: =AE29-J29 -> 0 | M29: =K29*(1+M30) -> 0 | N29: =L29*(1+N30) -> 0 | O29: =M29*(1+O30) -> 0 | P29: =N29*(1+P30) -> 0 | Q29: =O29*(1+Q30) -> 0 | R29: =P29*(1+R30) -> 0 | S29: =Q29*(1+S30) -> 0 | T29: =R29*(1+T30) -> 0 | ... W29: =U29*(1+W30) -> 0 | AF29: =L29+M29 -> 0 | AG29: =N29+O29 -> 0 | AH29: =P29+Q29 -> 0 | AI29: =R29+S29 -> 0 | AJ29: =T29+U29 -> 0 | AK29: =V29+W29 -> 0
B30: Scope growth (%) | C30: =IFERROR(C29/#REF!-1, "-") -> - | D30: =IFERROR(D29/#REF!-1, "-") -> - | E30: =IFERROR(E29/#REF!-1, "-") -> - | F30: =F29/C31 -> #DIV/0! | G30: =G29/D31 -> #DIV/0! | H30: =H29/F31 -> #DIV/0! | I30: =I29/G31 -> #DIV/0! | J30: =J29/H31 -> 0 | K30: =K29/I31 -> #DIV/0! | L30: =L29/J31 -> #DIV/0! | AC30: =AC29/E31 -> #DIV/0! | AD30: =AD29/AC31 -> #DIV/0! | AE30: =AE29/AD31 -> #DIV/0! | AF30: =AF29/AE29-1 -> #DIV/0! | AG30: =AG29/AF29-1 -> #DIV/0! | AH30: =AH29/AG29-1 -> #DIV/0! | AI30: =AI29/AH29-1 -> #DIV/0! | AJ30: =AJ29/AI29-1 -> #DIV/0! | AK30: =AK29/AJ29-1 -> #DIV/0!
B31: Total Sales - Europe | D31: =E31-C31 -> 0 | F31: =C31+F25+F27+F29 -> 0 | G31: =D31+G25+G27+G29 -> 0 | H31: =F31+H25+H27+H29+1 -> 1 | I31: =G31+I25+I27+I29 -> 0 | J31: =H31+J25+J27+J29-1 -> 0 | K31: =I31+K25+K27+K29 -> 0 | L31: =J31+L25+L27+L29-1 -> -1 | M31: =K31+M25+M27+M29 -> 0 | N31: =L31+N25+N27+N29 -> -1 | O31: =M31+O25+O27+O29 -> 0 | P31: =N31+P25+P27+P29 -> -1 | Q31: =O31+Q25+Q27+Q29 -> 0 | R31: =P31+R25+R27+R29 -> -1 | S31: =Q31+S25+S27+S29 -> 0 | T31: =R31+T25+T27+T29 -> -1 | ... W31: =U31+W25+W27+W29 -> 0 | AC31: =E31+AC25+AC27+AC29 -> 0 | AD31: =AC31+AD25+AD27+AD29 -> 0 | AE31: =AD31+AE25+AE27+AE29 -> 0 | AF31: =AE31+AF25+AF27+AF29 -> 0 | AG31: =AF31+AG25+AG27+AG29 -> 0 | AH31: =AG31+AH25+AH27+AH29 -> 0 | AI31: =AH31+AI25+AI27+AI29 -> 0 | AJ31: =AI31+AJ25+AJ27+AJ29 -> 0 | AK31: =AJ31+AK25+AK27+AK29 -> 0
B32: Growth (%) | C32: =IFERROR(C31/#REF!-1, "-") -> - | D32: =IFERROR(D31/#REF!-1, "-") -> - | E32: =IFERROR(E31/#REF!-1, "-") -> - | F32: =IFERROR(F31/C31-1, "-") -> - | G32: =IFERROR(G31/D31-1, "-") -> - | H32: =IFERROR(H31/F31-1, "-") -> - | I32: =IFERROR(I31/G31-1, "-") -> - | J32: =IFERROR(J31/H31-1, "-") -> -1 | K32: =IFERROR(K31/I31-1, "-") -> - | L32: =IFERROR(L31/J31-1, "-") -> - | M32: =IFERROR(M31/K31-1, "-") -> - | N32: =IFERROR(N31/L31-1, "-") -> 0 | O32: =IFERROR(O31/M31-1, "-") -> - | ... W32: =IFERROR(W31/U31-1, "-") -> - | AC32: =IFERROR(AC31/E31-1, "-") -> - | AD32: =IFERROR(AD31/AC31-1, "-") -> - | AE32: =IFERROR(AE31/AD31-1, "-") -> - | AF32: =IFERROR(AF31/AE31-1, "-") -> - | AG32: =IFERROR(AG31/AF31-1, "-") -> - | AH32: =IFERROR(AH31/AG31-1, "-") -> - | AI32: =IFERROR(AI31/AH31-1, "-") -> - | AJ32: =IFERROR(AJ31/AI31-1, "-") -> - | AK32: =IFERROR(AK31/AJ31-1, "-") -> -
B34: Total
B35: Organic | F35: =F5+F15+F25 -> 0 | G35: =AC35-F35 -> 0 | H35: =H5+H15+H25 -> 0 | I35: =AD35-H35 -> 0 | J35: =J5+J15+J25 -> 0 | K35: =AE35-J35 -> 0 | L35: =L5+L15+L25 -> 0 | M35: =AF35-L35 -> 0 | N35: =N5+N15+N25 -> 0 | O35: =AG35-N35 -> 0 | P35: =P5+P15+P25 -> 0 | Q35: =AH35-P35 -> 0 | R35: =R5+R15+R25 -> 0 | S35: =AI35-R35 -> 0 | T35: =T5+T15+T25 -> 0 | U35: =AJ35-T35 -> 0 | V35: =V5+V15+V25 -> 0 | W35: =AK35-V35 -> 0 | AC35: =AC5+AC15+AC25 -> 0 | AD35: =AD5+AD15+AD25 -> 0 | AE35: =AE5+AE15+AE25 -> 0 | AF35: =AF5+AF15+AF25 -> 0 | AG35: =AG5+AG15+AG25 -> 0 | AH35: =AH5+AH15+AH25 -> 0 | AI35: =AI5+AI15+AI25 -> 0 | AJ35: =AJ5+AJ15+AJ25 -> 0 | AK35: =AK5+AK15+AK25 -> 0
B36: Organic growth (%) | F36: =F35/C41 -> #DIV/0! | G36: =G35/D41 -> #DIV/0! | H36: =H35/F41 -> #DIV/0! | I36: =I35/G41 -> #DIV/0! | J36: =J35/H41 -> #DIV/0! | K36: =K35/I41 -> #DIV/0! | L36: =L35/J41 -> #DIV/0! | M36: =M35/K41 -> #DIV/0! | N36: =N35/L41 -> #DIV/0! | O36: =O35/M41 -> #DIV/0! | ... W36: =W35/U41 -> #DIV/0! | AC36: =AC35/E41 -> #DIV/0! | AD36: =AD35/AC41 -> #DIV/0! | AE36: =AE35/AD41 -> #DIV/0! | AF36: =AF35/AE41 -> #DIV/0! | AG36: =AG35/AF41 -> #DIV/0! | AH36: =AH35/AG41 -> #DIV/0! | AI36: =AI35/AH41 -> #DIV/0! | AJ36: =AJ35/AI41 -> #DIV/0! | AK36: =AK35/AJ41 -> #DIV/0!
B37: Fx | F37: =F7+F17+F27 -> 0 | G37: =AC37-F37 -> 0 | H37: =H7+H17+H27 -> 0 | I37: =AD37-H37 -> 0 | J37: =J7+J17+J27 -> 0 | K37: =AE37-J37 -> 0 | L37: =L7+L17+L27 -> 0 | M37: =AF37-L37 -> 0 | N37: =N7+N17+N27 -> 0 | O37: =AG37-N37 -> 0 | P37: =P7+P17+P27 -> 0 | Q37: =AH37-P37 -> 0 | R37: =R7+R17+R27 -> 0 | S37: =AI37-R37 -> 0 | T37: =T7+T17+T27 -> 0 | U37: =AJ37-T37 -> 0 | V37: =V7+V17+V27 -> 0 | W37: =AK37-V37 -> 0 | AC37: =AC7+AC17+AC27 -> 0 | AD37: =AD7+AD17+AD27 -> 0 | AE37: =AE7+AE17+AE27 -> 0 | AF37: =AF7+AF17+AF27 -> 0 | AG37: =AG7+AG17+AG27 -> 0 | AH37: =AH7+AH17+AH27 -> 0 | AI37: =AI7+AI17+AI27 -> 0 | AJ37: =AJ7+AJ17+AJ27 -> 0 | AK37: =AK7+AK17+AK27 -> 0
B38: Fx growth (%) | F38: =F37/C41 -> #DIV/0! | G38: =G37/D41 -> #DIV/0! | H38: =H37/F41 -> #DIV/0! | I38: =I37/G41 -> #DIV/0! | J38: =J37/H41 -> #DIV/0! | K38: =K37/I41 -> #DIV/0! | L38: =L37/J41 -> #DIV/0! | M38: =M37/K41 -> #DIV/0! | N38: =N37/L41 -> #DIV/0! | O38: =O37/M41 -> #DIV/0! | ... W38: =W37/U41 -> #DIV/0! | AC38: =AC37/E41 -> #DIV/0! | AD38: =AD37/AC41 -> #DIV/0! | AE38: =AE37/AD41 -> #DIV/0! | AF38: =AF37/AE41 -> #DIV/0! | AG38: =AG37/AF41 -> #DIV/0! | AH38: =AH37/AG41 -> #DIV/0! | AI38: =AI37/AH41 -> #DIV/0! | AJ38: =AJ37/AI41 -> #DIV/0! | AK38: =AK37/AJ41 -> #DIV/0!
B39: Scope | F39: =F9+F19+F29 -> 0 | G39: =AC39-F39 -> 0 | H39: =H9+H19+H29 -> 0 | I39: =AD39-H39 -> 0 | J39: =J9+J19+J29 -> 0 | K39: =AE39-J39 -> 0 | L39: =L9+L19+L29 -> 0 | M39: =AF39-L39 -> 0 | N39: =N9+N19+N29 -> 0 | O39: =AG39-N39 -> 0 | P39: =P9+P19+P29 -> 0 | Q39: =AH39-P39 -> 0 | R39: =R9+R19+R29 -> 0 | S39: =AI39-R39 -> 0 | T39: =T9+T19+T29 -> 0 | U39: =AJ39-T39 -> 0 | V39: =V9+V19+V29 -> 0 | W39: =AK39-V39 -> 0 | AC39: =AC9+AC19+AC29 -> 0 | AD39: =AD9+AD19+AD29 -> 0 | AE39: =AE9+AE19+AE29 -> 0 | AF39: =AF9+AF19+AF29 -> 0 | AG39: =AG9+AG19+AG29 -> 0 | AH39: =AH9+AH19+AH29 -> 0 | AI39: =AI9+AI19+AI29 -> 0 | AJ39: =AJ9+AJ19+AJ29 -> 0 | AK39: =AK9+AK19+AK29 -> 0
B40: Scope growth (%) | F40: =F39/C41 -> #DIV/0! | G40: =G39/D41 -> #DIV/0! | H40: =H39/F41 -> #DIV/0! | I40: =I39/G41 -> #DIV/0! | J40: =J39/H41 -> #DIV/0! | K40: =K39/I41 -> #DIV/0! | L40: =L39/J41 -> #DIV/0! | M40: =M39/K41 -> #DIV/0! | N40: =N39/L41 -> #DIV/0! | O40: =O39/M41 -> #DIV/0! | ... W40: =W39/U41 -> #DIV/0! | AC40: =AC39/E41 -> #DIV/0! | AD40: =AD39/AC41 -> #DIV/0! | AE40: =AE39/AD41 -> #DIV/0! | AF40: =AF39/AE41 -> #DIV/0! | AG40: =AG39/AF41 -> #DIV/0! | AH40: =AH39/AG41 -> #DIV/0! | AI40: =AI39/AH41 -> #DIV/0! | AJ40: =AJ39/AI41 -> #DIV/0! | AK40: =AK39/AJ41 -> #DIV/0!
B41: Total Sales | C41: =C11+C31+C21 -> 0 | D41: =D11+D31+D21 -> 0 | E41: =E11+E31+E21 -> 0 | F41: =F11+F31+F21 -> 0 | G41: =D41+G35+G37+G39 -> 0 | H41: =F41+H35+H37+H39 -> 0 | I41: =I11+I31+I21 -> 0 | J41: =H41+J35+J37+J39 -> 0 | K41: =K11+K31+K21 -> 0 | L41: =J41+L35+L37+L39 -> 0 | M41: =M11+M31+M21 -> 0 | N41: =L41+N35+N37+N39 -> 0 | O41: =O11+O31+O21 -> 0 | P41: =N41+P35+P37+P39 -> 0 | Q41: =Q11+Q31+Q21 -> 0 | R41: =P41+R35+R37+R39 -> 0 | S41: =S11+S31+S21 -> 0 | T41: =R41+T35+T37+T39 -> 0 | U41: =U11+U31+U21 -> 0 | V41: =T41+V35+V37+V39 -> 0 | W41: =W11+W31+W21 -> 0 | AC41: =E41+AC35+AC37+AC39 -> 0 | AD41: =AC41+AD35+AD37+AD39 -> 0 | AE41: =AD41+AE35+AE37+AE39 -> 0 | AF41: =AE41+AF35+AF37+AF39 -> 0 | AG41: =AF41+AG35+AG37+AG39 -> 0 | AH41: =AG41+AH35+AH37+AH39 -> 0 | AI41: =AH41+AI35+AI37+AI39 -> 0 | AJ41: =AI41+AJ35+AJ37+AJ39 -> 0 | AK41: =AJ41+AK35+AK37+AK39 -> 0
B42: Growth (%) | C42: =IFERROR(C41/#REF!-1, "-") -> - | D42: =IFERROR(D41/#REF!-1, "-") -> - | E42: =IFERROR(E41/#REF!-1, "-") -> - | F42: =IFERROR(F41/C41-1, "-") -> - | G42: =IFERROR(G41/D41-1, "-") -> - | H42: =IFERROR(H41/F41-1, "-") -> - | I42: =IFERROR(I41/G41-1, "-") -> - | J42: =IFERROR(J41/H41-1, "-") -> - | K42: =IFERROR(K41/I41-1, "-") -> - | L42: =IFERROR(L41/J41-1, "-") -> - | M42: =IFERROR(M41/K41-1, "-") -> - | N42: =IFERROR(N41/L41-1, "-") -> - | O42: =IFERROR(O41/M41-1, "-") -> - | ... W42: =IFERROR(W41/U41-1, "-") -> - | AC42: =IFERROR(AC41/E41-1, "-") -> - | AD42: =IFERROR(AD41/AC41-1, "-") -> - | AE42: =IFERROR(AE41/AD41-1, "-") -> - | AF42: =IFERROR(AF41/AE41-1, "-") -> - | AG42: =IFERROR(AG41/AF41-1, "-") -> - | AH42: =IFERROR(AH41/AG41-1, "-") -> - | AI42: =IFERROR(AI41/AH41-1, "-") -> - | AJ42: =IFERROR(AJ41/AI41-1, "-") -> - | AK42: =IFERROR(AK41/AJ41-1, "-") -> -

Sheet Gross Margin
B2: In Euro millions | C2: H1'21 | D2: H2'21 | E2: FY21 | F2: H1'22 | G2: H2'22 | H2: H1'23 | I2: H2'23 | J2: H1'24 | K2: H2'24 | L2: H1'25 | M2: H2'25 | N2: H1'26 | O2: H2'26 | P2: H1'27 | Q2: H2'27 | R2: H1'28 | S2: H2'28 | T2: H1'29 | U2: H2'29 | V2: H1'30 | W2: H2'30 | AC2: FY22 | AD2: FY23 | AE2: FY24 | AF2: FY25 | AG2: FY26 | AH2: FY27 | AI2: FY28 | AJ2: FY29 | AK2: FY30
B4: Americas
B5: Organic | F5: 123 | G5: =AC5-F5 -> 56 | H5: 59 | I5: =AD5-H5 -> -49 | J5: -41 | K5: =AE5-J5 -> 8 | L5: -50 | M5: =K5*(1+M6) -> 8.32 | N5: =L5*(1+N6) -> -52 | O5: =M5*(1+O6) -> 8.6528 | P5: =N5*(1+P6) -> -54.08 | Q5: =O5*(1+Q6) -> 8.998912 | R5: =P5*(1+R6) -> -56.2432 | S5: =Q5*(1+S6) -> 9.3588685 | T5: =R5*(1+T6) -> -58.492928 | ... W5: =U5*(1+W6) -> 10.122552 | AC5: 179 | AD5: 10 | AE5: -33 | AF5: =L5+M5 -> -41.68 | AG5: =N5+O5 -> -43.3472 | AH5: =P5+Q5 -> -45.081088 | AI5: =R5+S5 -> -46.884332 | AJ5: =T5+U5 -> -48.759705 | AK5: =V5+W5 -> -50.710093
B6: Organic growth (%) | C6: =IFERROR(C5/#REF!-1, "-") -> - | D6: =IFERROR(D5/#REF!-1, "-") -> - | E6: =IFERROR(E5/#REF!-1, "-") -> - | F6: =F5/C11 -> 0.13531353 | G6: =G5/D11 -> 0.070886076 | H6: =H5/F11 -> 0.055140187 | I6: =I5/G11 -> -0.049544995 | J6: =J5/H11 -> -0.031202435 | K6: =K5/I11 -> 0.008839779 | L6: =L5/J11 -> -0.040584416 | M6: 0.04 | N6: 0.04 | O6: 0.04 | P6: 0.04 | Q6: 0.04 | R6: 0.04 | S6: 0.04 | T6: 0.04 | U6: 0.04 | V6: 0.04 | W6: 0.04 | AC6: =AC5/E11 -> 0.10535609 | AD6: =AD5/AC11 -> 0.0048567266 | AE6: =AE5/AD11 -> -0.014864865 | AF6: =AF5/AE5-1 -> 0.2630303 | AG6: =AG5/AF5-1 -> 0.04 | AH6: =AH5/AG5-1 -> 0.04 | AI6: =AI5/AH5-1 -> 0.04 | AJ6: =AJ5/AI5-1 -> 0.04 | AK6: =AK5/AJ5-1 -> 0.04
B7: Fx | F7: 27 | G7: =AC7-F7 -> 135 | H7: 168 | I7: =AD7-H7 -> -68 | J7: -127 | K7: =AE7-J7 -> -44 | L7: -48 | M7: =K7*(1+M8) -> -45.76 | N7: =L7*(1+N8) -> -49.92 | O7: =M7*(1+O8) -> -47.5904 | P7: =N7*(1+P8) -> -51.9168 | Q7: =O7*(1+Q8) -> -49.494016 | R7: =P7*(1+R8) -> -53.993472 | S7: =Q7*(1+S8) -> -51.473777 | T7: =R7*(1+T8) -> -56.153211 | ... W7: =U7*(1+W8) -> -55.674037 | AC7: 162 | AD7: 100 | AE7: -171 | AF7: =L7+M7 -> -93.76 | AG7: =N7+O7 -> -97.5104 | AH7: =P7+Q7 -> -101.41082 | AI7: =R7+S7 -> -105.46725 | AJ7: =T7+U7 -> -109.68594 | AK7: =V7+W7 -> -114.07338
B8: Fx growth (%) | C8: =IFERROR(C7/#REF!-1, "-") -> - | D8: =IFERROR(D7/#REF!-1, "-") -> - | E8: =IFERROR(E7/#REF!-1, "-") -> - | F8: =F7/C11 -> 0.02970297 | G8: =G7/D11 -> 0.17088608 | H8: =H7/F11 -> 0.15700935 | I8: =I7/G11 -> -0.06875632 | J8: =J7/H11 -> -0.096651446 | K8: =K7/I11 -> -0.048618785 | L8: =L7/J11 -> -0.038961039 | M8: 0.04 | N8: 0.04 | O8: 0.04 | P8: 0.04 | Q8: 0.04 | R8: 0.04 | S8: 0.04 | T8: 0.04 | U8: 0.04 | V8: 0.04 | W8: 0.04 | AC8: =AC7/E11 -> 0.095350206 | AD8: =AD7/AC11 -> 0.048567266 | AE8: =AE7/AD11 -> -0.077027027 | AF8: =AF7/AE7-1 -> -0.45169591 | AG8: =AG7/AF7-1 -> 0.04 | AH8: =AH7/AG7-1 -> 0.04 | AI8: =AI7/AH7-1 -> 0.04 | AJ8: =AJ7/AI7-1 -> 0.04 | AK8: =AK7/AJ7-1 -> 0.04
B9: Scope | F9: 11 | G9: =AC9-F9 -> 8 | H9: 18 | I9: =AD9-H9 -> 33 | J9: 86 | K9: =AE9-J9 -> 60 | L9: 20 | M9: =K9*(1+M10) -> 62.4 | N9: =L9*(1+N10) -> 20.8 | O9: =M9*(1+O10) -> 64.896 | P9: =N9*(1+P10) -> 21.632 | Q9: =O9*(1+Q10) -> 67.49184 | R9: =P9*(1+R10) -> 22.49728 | S9: =Q9*(1+S10) -> 70.191514 | T9: =R9*(1+T10) -> 23.397171 | ... W9: =U9*(1+W10) -> 75.919141 | AC9: 19 | AD9: 51 | AE9: 146 | AF9: =L9+M9 -> 82.4 | AG9: =N9+O9 -> 85.696 | AH9: =P9+Q9 -> 89.12384 | AI9: =R9+S9 -> 92.688794 | AJ9: =T9+U9 -> 96.396345 | AK9: =V9+W9 -> 100.2522
B10: Scope growth (%) | C10: =IFERROR(C9/#REF!-1, "-") -> - | D10: =IFERROR(D9/#REF!-1, "-") -> - | E10: =IFERROR(E9/#REF!-1, "-") -> - | F10: =F9/C11 -> 0.01210121 | G10: =G9/D11 -> 0.010126582 | H10: =H9/F11 -> 0.01682243 | I10: =I9/G11 -> 0.033367037 | J10: =J9/H11 -> 0.065449011 | K10: =K9/I11 -> 0.066298343 | L10: =L9/J11 -> 0.016233766 | M10: 0.04 | N10: 0.04 | O10: 0.04 | P10: 0.04 | Q10: 0.04 | R10: 0.04 | S10: 0.04 | T10: 0.04 | U10: 0.04 | V10: 0.04 | W10: 0.04 | AC10: =AC9/E11 -> 0.011183049 | AD10: =AD9/AC11 -> 0.024769305 | AE10: =AE9/AD11 -> 0.065765766 | AF10: =IFERROR(AF9/AE9-1, "-") -> -0.43561644 | AG10: =IFERROR(AG9/AF9-1, "-") -> 0.04 | AH10: =IFERROR(AH9/AG9-1, "-") -> 0.04 | AI10: =IFERROR(AI9/AH9-1, "-") -> 0.04 | AJ10: =IFERROR(AJ9/AI9-1, "-") -> 0.04 | AK10: =IFERROR(AK9/AJ9-1, "-") -> 0.04
B11: Total Sales - Americas | C11: 909 | D11: =E11-C11 -> 790 | E11: 1699 | F11: =C11+F5+F7+F9 -> 1070 | G11: =D11+G5+G7+G9 -> 989 | H11: =F11+H5+H7+H9-1 -> 1314 | I11: =G11+I5+I7+I9 -> 905 | J11: =H11+J5+J7+J9 -> 1232 | K11: =I11+K5+K7+K9 -> 929 | L11: =J11+L5+L7+L9 -> 1154 | M11: =K11+M5+M7+M9 -> 953.96 | N11: =L11+N5+N7+N9 -> 1072.88 | O11: =M11+O5+O7+O9 -> 979.9184 | P11: =N11+P5+P7+P9 -> 988.5152 | ... W11: =U11+W5+W7+W9 -> 1094.5591 | AC11: =E11+AC5+AC7+AC9 -> 2059 | AD11: =AC11+AD5+AD7+AD9 -> 2220 | AE11: =AD11+AE5+AE7+AE9 -> 2162 | AF11: =AE11+AF5+AF7+AF9 -> 2108.96 | AG11: =AF11+AG5+AG7+AG9 -> 2053.7984 | AH11: =AG11+AH5+AH7+AH9 -> 1996.4303 | AI11: =AH11+AI5+AI7+AI9 -> 1936.7675 | AJ11: =AI11+AJ5+AJ7+AJ9 -> 1874.7183 | AK11: =AJ11+AK5+AK7+AK9 -> 1810.187
B12: Growth (%) | C12: =IFERROR(C11/#REF!-1, "-") -> - | D12: =IFERROR(D11/#REF!-1, "-") -> - | E12: =IFERROR(E11/#REF!-1, "-") -> - | F12: =IFERROR(F11/C11-1, "-") -> 0.17711771 | G12: =IFERROR(G11/D11-1, "-") -> 0.25189873 | H12: =IFERROR(H11/F11-1, "-") -> 0.22803738 | I12: =IFERROR(I11/G11-1, "-") -> -0.084934277 | J12: =IFERROR(J11/H11-1, "-") -> -0.062404871 | K12: =IFERROR(K11/I11-1, "-") -> 0.026519337 | L12: =IFERROR(L11/J11-1, "-") -> -0.063311688 | M12: =IFERROR(M11/K11-1, "-") -> 0.0268676 | N12: =IFERROR(N11/L11-1, "-") -> -0.070294627 | O12: =IFERROR(O11/M11-1, "-") -> 0.027211204 | ... W12: =IFERROR(W11/U11-1, "-") -> 0.028535897 | AC12: =IFERROR(AC11/E11-1, "-") -> 0.21188935 | AD12: =IFERROR(AD11/AC11-1, "-") -> 0.078193298 | AE12: =IFERROR(AE11/AD11-1, "-") -> -0.026126126 | AF12: =IFERROR(AF11/AE11-1, "-") -> -0.02453284 | AG12: =IFERROR(AG11/AF11-1, "-") -> -0.02615583 | AH12: =IFERROR(AH11/AG11-1, "-") -> -0.027932666 | AI12: =IFERROR(AI11/AH11-1, "-") -> -0.029884733 | AJ12: =IFERROR(AJ11/AI11-1, "-") -> -0.032037556 | AK12: =IFERROR(AK11/AJ11-1, "-") -> -0.03442185
B14: Asia/Row
B15: Organic | F15: 198 | G15: =AC15-F15 -> 185 | H15: 285 | I15: =AD15-H15 -> 216 | J15: 62 | K15: =AE15-J15 -> 93 | L15: -98 | M15: =K15*(1+M16) -> 96.72 | N15: =L15*(1+N16) -> -101.92 | O15: =M15*(1+O16) -> 100.5888 | P15: =N15*(1+P16) -> -105.9968 | Q15: =O15*(1+Q16) -> 104.61235 | R15: =P15*(1+R16) -> -110.23667 | S15: =Q15*(1+S16) -> 108.79685 | T15: =R15*(1+T16) -> -114.64614 | ... W15: =U15*(1+W16) -> 117.67467 | AC15: 383 | AD15: 501 | AE15: 155 | AF15: =L15+M15 -> -1.28 | AG15: =N15+O15 -> -1.3312 | AH15: =P15+Q15 -> -1.384448 | AI15: =R15+S15 -> -1.4398259 | AJ15: =T15+U15 -> -1.497419 | AK15: =V15+W15 -> -1.5573157
B16: Organic growth (%) | C16: =IFERROR(C15/#REF!-1, "-") -> - | D16: =IFERROR(D15/#REF!-1, "-") -> - | E16: =IFERROR(E15/#REF!-1, "-") -> - | F16: =F15/C21 -> 0.16071429 | G16: =G15/D21 -> 0.22342995 | H16: =H15/F21 -> 0.19547325 | I16: =I15/G21 -> 0.20829315 | J16: =J15/H21 -> 0.033935413 | K16: =K15/I21 -> 0.08150745 | L16: =L15/J21 -> -0.057680989 | M16: 0.04 | N16: 0.04 | O16: 0.04 | P16: 0.04 | Q16: 0.04 | R16: 0.04 | S16: 0.04 | T16: 0.04 | U16: 0.04 | V16: 0.04 | W16: 0.04 | AC16: =AC15/E21 -> 0.18592233 | AD16: =AD15/AC21 -> 0.20072115 | AE16: =AE15/AD21 -> 0.05220613 | AF16: =AF15/AE15-1 -> -1.0082581 | AG16: =AG15/AF15-1 -> 0.04 | AH16: =AH15/AG15-1 -> 0.04 | AI16: =AI15/AH15-1 -> 0.04 | AJ16: =AJ15/AI15-1 -> 0.04 | AK16: =AK15/AJ15-1 -> 0.04
B17: Fx | F17: 29 | G17: =AC17-F17 -> 24 | H17: 36 | I17: =AD17-H17 -> -138 | J17: -279 | K17: =AE17-J17 -> -119 | L17: -83 | M17: =K17*(1+M18) -> -123.76 | N17: =L17*(1+N18) -> -86.32 | O17: =M17*(1+O18) -> -128.7104 | P17: =N17*(1+P18) -> -89.7728 | Q17: =O17*(1+Q18) -> -133.85882 | R17: =P17*(1+R18) -> -93.363712 | S17: =Q17*(1+S18) -> -139.21317 | T17: =R17*(1+T18) -> -97.09826 | ... W17: =U17*(1+W18) -> -150.57296 | AC17: 53 | AD17: -102 | AE17: -398 | AF17: =L17+M17 -> -206.76 | AG17: =N17+O17 -> -215.0304 | AH17: =P17+Q17 -> -223.63162 | AI17: =R17+S17 -> -232.57688 | AJ17: =T17+U17 -> -241.87996 | AK17: =V17+W17 -> -251.55515
B18: Fx growth (%) | C18: =IFERROR(C17/#REF!-1, "-") -> - | D18: =IFERROR(D17/#REF!-1, "-") -> - | E18: =IFERROR(E17/#REF!-1, "-") -> - | F18: =F17/C21 -> 0.023538961 | G18: =G17/D21 -> 0.028985507 | H18: =H17/F21 -> 0.024691358 | I18: =I17/G21 -> -0.13307618 | J18: =J17/H21 -> -0.15270936 | K18: =K17/I21 -> -0.10429448 | L18: =L17/J21 -> -0.048852266 | M18: 0.04 | N18: 0.04 | O18: 0.04 | P18: 0.04 | Q18: 0.04 | R18: 0.04 | S18: 0.04 | T18: 0.04 | U18: 0.04 | V18: 0.04 | W18: 0.04 | AC18: =AC17/E21 -> 0.025728155 | AD18: =AD17/AC21 -> -0.040865385 | AE18: =AE17/AD21 -> -0.13405187 | AF18: =AF17/AE17-1 -> -0.48050251 | AG18: =AG17/AF17-1 -> 0.04 | AH18: =AH17/AG17-1 -> 0.04 | AI18: =AI17/AH17-1 -> 0.04 | AJ18: =AJ17/AI17-1 -> 0.04 | AK18: =AK17/AJ17-1 -> 0.04
B19: Scope | F19: 0 | G19: =AC19-F19 -> 0 | H19: 48 | I19: =AD19-H19 -> 26 | J19: 89 | K19: =AE19-J19 -> 37 | L19: 5 | M19: =K19*(1+M20) -> 38.48 | N19: =L19*(1+N20) -> 5.2 | O19: =M19*(1+O20) -> 40.0192 | P19: =N19*(1+P20) -> 5.408 | Q19: =O19*(1+Q20) -> 41.619968 | R19: =P19*(1+R20) -> 5.62432 | S19: =Q19*(1+S20) -> 43.284767 | T19: =R19*(1+T20) -> 5.8492928 | ... W19: =U19*(1+W20) -> 46.816804 | AC19: 0 | AD19: 74 | AE19: 126 | AF19: =L19+M19 -> 43.48 | AG19: =N19+O19 -> 45.2192 | AH19: =P19+Q19 -> 47.027968 | AI19: =R19+S19 -> 48.909087 | AJ19: =T19+U19 -> 50.86545 | AK19: =V19+W19 -> 52.900068
B20: Scope growth (%) | C20: =IFERROR(C19/#REF!-1, "-") -> - | D20: =IFERROR(D19/#REF!-1, "-") -> - | E20: =IFERROR(E19/#REF!-1, "-") -> - | F20: =F19/C21 -> 0 | G20: =G19/D21 -> 0 | H20: =H19/F21 -> 0.032921811 | I20: =I19/G21 -> 0.025072324 | J20: =J19/H21 -> 0.048713738 | K20: =K19/I21 -> 0.032427695 | L20: =L19/J21 -> 0.0029429076 | M20: 0.04 | N20: 0.04 | O20: 0.04 | P20: 0.04 | Q20: 0.04 | R20: 0.04 | S20: 0.04 | T20: 0.04 | U20: 0.04 | V20: 0.04 | W20: 0.04 | AC20: =AC19/E21 -> 0 | AD20: =AD19/AC21 -> 0.029647436 | AE20: =AE19/AD21 -> 0.042438531 | AF20: =IFERROR(AF19/AE19-1, "-") -> -0.65492063 | AG20: =IFERROR(AG19/AF19-1, "-") -> 0.04 | AH20: =IFERROR(AH19/AG19-1, "-") -> 0.04 | AI20: =IFERROR(AI19/AH19-1, "-") -> 0.04 | AJ20: =IFERROR(AJ19/AI19-1, "-") -> 0.04 | AK20: =IFERROR(AK19/AJ19-1, "-") -> 0.04
B21: Total Sales - Asia/Row | C21: 1232 | D21: =E21-C21 -> 828 | E21: 2060 | F21: =C21+F15+F17+F19-1 -> 1458 | G21: =D21+G15+G17+G19 -> 1037 | H21: =F21+H15+H17+H19 -> 1827 | I21: =G21+I15+I17+I19 -> 1141 | J21: =H21+J15+J17+J19 -> 1699 | K21: =I21+K15+K17+K19 -> 1152 | L21: =J21+L15+L17+L19 -> 1523 | M21: =K21+M15+M17+M19 -> 1163.44 | N21: =L21+N15+N17+N19 -> 1339.96 | O21: =M21+O15+O17+O19 -> 1175.3376 | ... W21: =U21+W15+W17+W19 -> 1227.8812 | AC21: =E21+AC15+AC17+AC19 -> 2496 | AD21: =AC21+AD15+AD17+AD19 -> 2969 | AE21: =AD21+AE15+AE17+AE19 -> 2852 | AF21: =AE21+AF15+AF17+AF19 -> 2687.44 | AG21: =AF21+AG15+AG17+AG19 -> 2516.2976 | AH21: =AG21+AH15+AH17+AH19 -> 2338.3095 | AI21: =AH21+AI15+AI17+AI19 -> 2153.2019 | AJ21: =AI21+AJ15+AJ17+AJ19 -> 1960.69 | AK21: =AJ21+AK15+AK17+AK19 -> 1760.4776
B22: Growth (%) | C22: =IFERROR(C21/#REF!-1, "-") -> - | D22: =IFERROR(D21/#REF!-1, "-") -> - | E22: =IFERROR(E21/#REF!-1, "-") -> - | F22: =IFERROR(F21/C21-1, "-") -> 0.18344156 | G22: =IFERROR(G21/D21-1, "-") -> 0.25241546 | H22: =IFERROR(H21/F21-1, "-") -> 0.25308642 | I22: =IFERROR(I21/G21-1, "-") -> 0.1002893 | J22: =IFERROR(J21/H21-1, "-") -> -0.070060208 | K22: =IFERROR(K21/I21-1, "-") -> 0.0096406661 | L22: =IFERROR(L21/J21-1, "-") -> -0.10359035 | M22: =IFERROR(M21/K21-1, "-") -> 0.0099305556 | N22: =IFERROR(N21/L21-1, "-") -> -0.12018385 | O22: =IFERROR(O21/M21-1, "-") -> 0.010226226 | ... W22: =IFERROR(W21/U21-1, "-") -> 0.011465351 | AC22: =IFERROR(AC21/E21-1, "-") -> 0.21165049 | AD22: =IFERROR(AD21/AC21-1, "-") -> 0.18950321 | AE22: =IFERROR(AE21/AD21-1, "-") -> -0.039407208 | AF22: =IFERROR(AF21/AE21-1, "-") -> -0.05769986 | AG22: =IFERROR(AG21/AF21-1, "-") -> -0.063682315 | AH22: =IFERROR(AH21/AG21-1, "-") -> -0.07073412 | AI22: =IFERROR(AI21/AH21-1, "-") -> -0.079163011 | AJ22: =IFERROR(AJ21/AI21-1, "-") -> -0.08940728 | AK22: =IFERROR(AK21/AJ21-1, "-") -> -0.10211324
B24: Europe
B25: Organic | F25: 211 | G25: =AC25-F25 -> 131 | H25: 79 | I25: =AD25-H25 -> 56 | J25: -67 | K25: =AE25-J25 -> -17 | L25: -30 | M25: =K25*(1+M26) -> -17.68 | N25: =L25*(1+N26) -> -31.2 | O25: =M25*(1+O26) -> -18.3872 | P25: =N25*(1+P26) -> -32.448 | Q25: =O25*(1+Q26) -> -19.122688 | R25: =P25*(1+R26) -> -33.74592 | S25: =Q25*(1+S26) -> -19.887596 | T25: =R25*(1+T26) -> -35.095757 | ... W25: =U25*(1+W26) -> -21.510423 | AC25: 342 | AD25: 135 | AE25: -84 | AF25: =L25+M25 -> -47.68 | AG25: =N25+O25 -> -49.5872 | AH25: =P25+Q25 -> -51.570688 | AI25: =R25+S25 -> -53.633516 | AJ25: =T25+U25 -> -55.778856 | AK25: =V25+W25 -> -58.01001
B26: Organic growth (%) | C26: =IFERROR(C25/#REF!-1, "-") -> - | D26: =IFERROR(D25/#REF!-1, "-") -> - | E26: =IFERROR(E25/#REF!-1, "-") -> - | F26: =F25/C31 -> 0.23950057 | G26: =G25/D31 -> 0.20061256 | H26: =H25/F31 -> 0.071043165 | I26: =I25/G31 -> 0.069565217 | J26: =J25/H31 -> -0.054604727 | K26: =K25/I31 -> -0.020481928 | L26: =L25/J31 -> -0.026086957 | M26: 0.04 | N26: 0.04 | O26: 0.04 | P26: 0.04 | Q26: 0.04 | R26: 0.04 | S26: 0.04 | T26: 0.04 | U26: 0.04 | V26: 0.04 | W26: 0.04 | AC26: =AC25/E31 -> 0.22294654 | AD26: =AD25/AC31 -> 0.070385819 | AE26: =AE25/AD31 -> -0.040836169 | AF26: =AF25/AE25-1 -> -0.43238095 | AG26: =AG25/AF25-1 -> 0.04 | AH26: =AH25/AG25-1 -> 0.04 | AI26: =AI25/AH25-1 -> 0.04 | AJ26: =AJ25/AI25-1 -> 0.04 | AK26: =AK25/AJ25-1 -> 0.04
B27: Fx | F27: 14 | G27: =AC27-F27 -> 21 | H27: 23 | I27: =AD27-H27 -> -36 | J27: -10 | K27: =AE27-J27 -> 7 | L27: -11 | M27: =K27*(1+M28) -> 7.28 | N27: =L27*(1+N28) -> -11.44 | O27: =M27*(1+O28) -> 7.5712 | P27: =N27*(1+P28) -> -11.8976 | Q27: =O27*(1+Q28) -> 7.874048 | R27: =P27*(1+R28) -> -12.373504 | S27: =Q27*(1+S28) -> 8.1890099 | T27: =R27*(1+T28) -> -12.868444 | ... W27: =U27*(1+W28) -> 8.8572331 | AC27: 35 | AD27: -13 | AE27: -3 | AF27: =L27+M27 -> -3.72 | AG27: =N27+O27 -> -3.8688 | AH27: =P27+Q27 -> -4.023552 | AI27: =R27+S27 -> -4.1844941 | AJ27: =T27+U27 -> -4.3518738 | AK27: =V27+W27 -> -4.5259488
B28: Fx growth (%) | C28: =IFERROR(C27/#REF!-1, "-") -> - | D28: =IFERROR(D27/#REF!-1, "-") -> - | E28: =IFERROR(E27/#REF!-1, "-") -> - | F28: =F27/C31 -> 0.015891033 | G28: =G27/D31 -> 0.032159265 | H28: =H27/F31 -> 0.020683453 | I28: =I27/G31 -> -0.044720497 | J28: =J27/H31 -> -0.0081499593 | K28: =K27/I31 -> 0.0084337349 | L28: =L27/J31 -> -0.0095652174 | M28: 0.04 | N28: 0.04 | O28: 0.04 | P28: 0.04 | Q28: 0.04 | R28: 0.04 | S28: 0.04 | T28: 0.04 | U28: 0.04 | V28: 0.04 | W28: 0.04 | AC28: =AC27/E31 -> 0.022816167 | AD28: =AD27/AC31 -> -0.0067778936 | AE28: =AE27/AD31 -> -0.0014584346 | AF28: =AF27/AE27-1 -> 0.24 | AG28: =AG27/AF27-1 -> 0.04 | AH28: =AH27/AG27-1 -> 0.04 | AI28: =AI27/AH27-1 -> 0.04 | AJ28: =AJ27/AI27-1 -> 0.04 | AK28: =AK27/AJ27-1 -> 0.04
B29: Scope | F29: 7 | G29: =AC29-F29 -> 0 | H29: 12 | I29: =AD29-H29 -> 5 | J29: 1 | K29: =AE29-J29 -> -9 | L29: -14 | M29: =K29*(1+M30) -> -9.36 | N29: =L29*(1+N30) -> -14.56 | O29: =M29*(1+O30) -> -9.7344 | P29: =N29*(1+P30) -> -15.1424 | Q29: =O29*(1+Q30) -> -10.123776 | R29: =P29*(1+R30) -> -15.748096 | S29: =Q29*(1+S30) -> -10.528727 | T29: =R29*(1+T30) -> -16.37802 | ... W29: =U29*(1+W30) -> -11.387871 | AC29: 7 | AD29: 17 | AE29: -8 | AF29: =L29+M29 -> -23.36 | AG29: =N29+O29 -> -24.2944 | AH29: =P29+Q29 -> -25.266176 | AI29: =R29+S29 -> -26.276823 | AJ29: =T29+U29 -> -27.327896 | AK29: =V29+W29 -> -28.421012
B30: Scope growth (%) | C30: =IFERROR(C29/#REF!-1, "-") -> - | D30: =IFERROR(D29/#REF!-1, "-") -> - | E30: =IFERROR(E29/#REF!-1, "-") -> - | F30: =F29/C31 -> 0.0079455165 | G30: =G29/D31 -> 0 | H30: =H29/F31 -> 0.010791367 | I30: =I29/G31 -> 0.0062111801 | J30: =J29/H31 -> 0.00081499593 | K30: =K29/I31 -> -0.010843373 | L30: =L29/J31 -> -0.012173913 | M30: 0.04 | N30: 0.04 | O30: 0.04 | P30: 0.04 | Q30: 0.04 | R30: 0.04 | S30: 0.04 | T30: 0.04 | U30: 0.04 | V30: 0.04 | W30: 0.04 | AC30: =AC29/E31 -> 0.0045632334 | AD30: =AD29/AC31 -> 0.0088633994 | AE30: =AE29/AD31 -> -0.003889159 | AF30: =IFERROR(AF29/AE29-1, "-") -> 1.92 | AG30: =IFERROR(AG29/AF29-1, "-") -> 0.04 | AH30: =IFERROR(AH29/AG29-1, "-") -> 0.04 | AI30: =IFERROR(AI29/AH29-1, "-") -> 0.04 | AJ30: =IFERROR(AJ29/AI29-1, "-") -> 0.04 | AK30: =IFERROR(AK29/AJ29-1, "-") -> 0.04
B31: Total Sales - Europe | C31: 881 | D31: =E31-C31 -> 653 | E31: 1534 | F31: =C31+F25+F27+F29-1 -> 1112 | G31: =D31+G25+G27+G29 -> 805 | H31: =F31+H25+H27+H29+1 -> 1227 | I31: =G31+I25+I27+I29 -> 830 | J31: =H31+J25+J27+J29-1 -> 1150 | K31: =I31+K25+K27+K29 -> 811 | L31: =J31+L25+L27+L29 -> 1095 | M31: =K31+M25+M27+M29 -> 791.24 | N31: =L31+N25+N27+N29 -> 1037.8 | O31: =M31+O25+O27+O29 -> 770.6896 | P31: =N31+P25+P27+P29 -> 978.312 | Q31: =O31+Q25+Q27+Q29 -> 749.31718 | R31: =P31+R25+R27+R29 -> 916.44448 | ... W31: =U31+W25+W27+W29 -> 679.9324 | AC31: =E31+AC25+AC27+AC29 -> 1918 | AD31: =AC31+AD25+AD27+AD29 -> 2057 | AE31: =AD31+AE25+AE27+AE29 -> 1962 | AF31: =AE31+AF25+AF27+AF29 -> 1887.24 | AG31: =AF31+AG25+AG27+AG29 -> 1809.4896 | AH31: =AG31+AH25+AH27+AH29 -> 1728.6292 | AI31: =AH31+AI25+AI27+AI29 -> 1644.5344 | AJ31: =AI31+AJ25+AJ27+AJ29 -> 1557.0757 | AK31: =AJ31+AK25+AK27+AK29 -> 1466.1188
B32: Growth (%) | C32: =IFERROR(C31/#REF!-1, "-") -> - | D32: =IFERROR(D31/#REF!-1, "-") -> - | E32: =IFERROR(E31/#REF!-1, "-") -> - | F32: =IFERROR(F31/C31-1, "-") -> 0.26220204 | G32: =IFERROR(G31/D31-1, "-") -> 0.23277182 | H32: =IFERROR(H31/F31-1, "-") -> 0.10341727 | I32: =IFERROR(I31/G31-1, "-") -> 0.031055901 | J32: =IFERROR(J31/H31-1, "-") -> -0.062754686 | K32: =IFERROR(K31/I31-1, "-") -> -0.022891566 | L32: =IFERROR(L31/J31-1, "-") -> -0.047826087 | M32: =IFERROR(M31/K31-1, "-") -> -0.024364982 | N32: =IFERROR(N31/L31-1, "-") -> -0.052237443 | O32: =IFERROR(O31/M31-1, "-") -> -0.025972398 | ... W32: =IFERROR(W31/U31-1, "-") -> -0.034150522 | AC32: =IFERROR(AC31/E31-1, "-") -> 0.25032595 | AD32: =IFERROR(AD31/AC31-1, "-") -> 0.072471324 | AE32: =IFERROR(AE31/AD31-1, "-") -> -0.046183763 | AF32: =IFERROR(AF31/AE31-1, "-") -> -0.038103976 | AG32: =IFERROR(AG31/AF31-1, "-") -> -0.04119794 | AH32: =IFERROR(AH31/AG31-1, "-") -> -0.044686864 | AI32: =IFERROR(AI31/AH31-1, "-") -> -0.048648278 | AJ32: =IFERROR(AJ31/AI31-1, "-") -> -0.053181392 | AK32: =IFERROR(AK31/AJ31-1, "-") -> -0.058415252
B34: Total
B35: Organic | F35: =F5+F15+F25 -> 532 | G35: =AC35-F35 -> 372 | H35: =H5+H15+H25 -> 423 | I35: =AD35-H35 -> 223 | J35: =J5+J15+J25 -> -46 | K35: =AE35-J35 -> 84 | L35: =L5+L15+L25 -> -178 | M35: =AF35-L35 -> 87.36 | N35: =N5+N15+N25 -> -185.12 | O35: =AG35-N35 -> 90.8544 | P35: =P5+P15+P25 -> -192.5248 | Q35: =AH35-P35 -> 94.488576 | R35: =R5+R15+R25 -> -200.22579 | S35: =AI35-R35 -> 98.268119 | T35: =T5+T15+T25 -> -208.23482 | U35: =AJ35-T35 -> 102.19884 | V35: =V5+V15+V25 -> -216.56422 | W35: =AK35-V35 -> 106.2868 | AC35: =AC5+AC15+AC25 -> 904 | AD35: =AD5+AD15+AD25 -> 646 | AE35: =AE5+AE15+AE25 -> 38 | AF35: =AF5+AF15+AF25 -> -90.64 | AG35: =AG5+AG15+AG25 -> -94.2656 | AH35: =AH5+AH15+AH25 -> -98.036224 | AI35: =AI5+AI15+AI25 -> -101.95767 | AJ35: =AJ5+AJ15+AJ25 -> -106.03598 | AK35: =AK5+AK15+AK25 -> -110.27742
B36: Organic growth (%) | F36: =F35/C41 -> 0.17604236 | G36: =G35/D41 -> 0.16380449 | H36: =H35/F41 -> 0.11614498 | I36: =I35/G41 -> 0.078770752 | J36: =J35/H41 -> -0.010526316 | K36: =K35/I41 -> 0.029207232 | L36: =L35/J41 -> -0.043595396 | M36: =M35/K41 -> 0.030207469 | N36: =N35/L41 -> -0.049064405 | O36: =O35/M41 -> 0.031236042 | ... W36: =W35/U41 -> 0.035641264 | AC36: =AC35/E41 -> 0.17079161 | AD36: =AD35/AC41 -> 0.099799166 | AE36: =AE35/AD41 -> 0.0052442727 | AF36: =AF35/AE41 -> -0.012994982 | AG36: =AG35/AF41 -> -0.014106042 | AH36: =AH35/AG41 -> -0.015369587 | AI36: =AI35/AH41 -> -0.016818124 | AJ36: =AJ35/AI41 -> -0.018494098 | AK36: =AK35/AJ41 -> -0.020454001
B37: Fx | F37: =F7+F17+F27 -> 70 | G37: =AC37-F37 -> 180 | H37: =H7+H17+H27 -> 227 | I37: =AD37-H37 -> -242 | J37: =J7+J17+J27 -> -416 | K37: =AE37-J37 -> -156 | L37: =L7+L17+L27 -> -142 | M37: =AF37-L37 -> -162.24 | N37: =N7+N17+N27 -> -147.68 | O37: =AG37-N37 -> -168.7296 | P37: =P7+P17+P27 -> -153.5872 | Q37: =AH37-P37 -> -175.47878 | R37: =R7+R17+R27 -> -159.73069 | S37: =AI37-R37 -> -182.49794 | T37: =T7+T17+T27 -> -166.11992 | U37: =AJ37-T37 -> -189.79785 | V37: =V7+V17+V27 -> -172.76471 | W37: =AK37-V37 -> -197.38977 | AC37: =AC7+AC17+AC27 -> 250 | AD37: =AD7+AD17+AD27 -> -15 | AE37: =AE7+AE17+AE27 -> -572 | AF37: =AF7+AF17+AF27 -> -304.24 | AG37: =AG7+AG17+AG27 -> -316.4096 | AH37: =AH7+AH17+AH27 -> -329.06598 | AI37: =AI7+AI17+AI27 -> -342.22862 | AJ37: =AJ7+AJ17+AJ27 -> -355.91777 | AK37: =AK7+AK17+AK27 -> -370.15448
B38: Fx growth (%) | F38: =F37/C41 -> 0.023163468 | G38: =G37/D41 -> 0.079260238 | H38: =H37/F41 -> 0.062328391 | I38: =I37/G41 -> -0.085482162 | J38: =J37/H41 -> -0.095194508 | K38: =K37/I41 -> -0.054242003 | L38: =L37/J41 -> -0.034778349 | M38: =M37/K41 -> -0.056099585 | N38: =N37/L41 -> -0.039141267 | O38: =O37/M41 -> -0.058009792 | ... W38: =W37/U41 -> -0.066190919 | AC38: =AC37/E41 -> 0.047232193 | AD38: =AD37/AC41 -> -0.0023173181 | AE38: =AE37/AD41 -> -0.078940105 | AF38: =AF37/AE41 -> -0.043618638 | AG38: =AG37/AF41 -> -0.047347994 | AH38: =AH37/AG41 -> -0.051589177 | AI38: =AI37/AH41 -> -0.056451302 | AJ38: =AJ37/AI41 -> -0.062076835 | AK38: =AK37/AJ41 -> -0.068655399
B39: Scope | F39: =F9+F19+F29 -> 18 | G39: =AC39-F39 -> 8 | H39: =H9+H19+H29 -> 78 | I39: =AD39-H39 -> 64 | J39: =J9+J19+J29 -> 176 | K39: =AE39-J39 -> 88 | L39: =L9+L19+L29 -> 11 | M39: =AF39-L39 -> 91.52 | N39: =N9+N19+N29 -> 11.44 | O39: =AG39-N39 -> 95.1808 | P39: =P9+P19+P29 -> 11.8976 | Q39: =AH39-P39 -> 98.988032 | R39: =R9+R19+R29 -> 12.373504 | S39: =AI39-R39 -> 102.94755 | T39: =T9+T19+T29 -> 12.868444 | U39: =AJ39-T39 -> 107.06546 | V39: =V9+V19+V29 -> 13.383182 | W39: =AK39-V39 -> 111.34807 | AC39: =AC9+AC19+AC29 -> 26 | AD39: =AD9+AD19+AD29 -> 142 | AE39: =AE9+AE19+AE29 -> 264 | AF39: =AF9+AF19+AF29 -> 102.52 | AG39: =AG9+AG19+AG29 -> 106.6208 | AH39: =AH9+AH19+AH29 -> 110.88563 | AI39: =AI9+AI19+AI29 -> 115.32106 | AJ39: =AJ9+AJ19+AJ29 -> 119.9339 | AK39: =AK9+AK19+AK29 -> 124.73126
B40: Scope growth (%) | F40: =F39/C41 -> 0.0059563203 | G40: =G39/D41 -> 0.0035226772 | H40: =H39/F41 -> 0.021416804 | I40: =I39/G41 -> 0.022606853 | J40: =J39/H41 -> 0.0402746 | K40: =K39/I41 -> 0.030598053 | L40: =L39/J41 -> 0.0026940975 | M40: =M39/K41 -> 0.03164592 | N40: =N39/L41 -> 0.00303207 | O40: =O39/M41 -> 0.032723472 | ... W40: =W39/U41 -> 0.037338467 | AC40: =AC39/E41 -> 0.0049121481 | AD40: =AD39/AC41 -> 0.021937278 | AE40: =AE39/AD41 -> 0.036433895 | AF40: =AF39/AE41 -> 0.014698208 | AG40: =AG39/AF41 -> 0.015954892 | AH40: =AH39/AG41 -> 0.017384047 | AI40: =AI39/AH41 -> 0.019022441 | AJ40: =AJ39/AI41 -> 0.020918082 | AK40: =AK39/AJ41 -> 0.023134865
B41: Total Sales | C41: =C11+C31+C21 -> 3022 | D41: =D11+D31+D21 -> 2271 | E41: =E11+E31+E21 -> 5293 | F41: =C41+F35+F37+F39 -> 3642 | G41: =G11+G31+G21 -> 2831 | H41: =F41+H35+H37+H39 -> 4370 | I41: =I11+I31+I21 -> 2876 | J41: =H41+J35+J37+J39-1 -> 4083 | K41: =K11+K31+K21 -> 2892 | L41: =J41+L35+L37+L39-1 -> 3773 | M41: =M11+M31+M21 -> 2908.64 | N41: =L41+N35+N37+N39 -> 3451.64 | O41: =O11+O31+O21 -> 2925.9456 | P41: =N41+P35+P37+P39 -> 3117.4256 | Q41: =Q11+Q31+Q21 -> 2943.9434 | R41: =P41+R35+R37+R39 -> 2769.8426 | S41: =S11+S31+S21 -> 2962.6612 | T41: =R41+T35+T37+T39 -> 2408.3563 | U41: =U11+U31+U21 -> 2982.1276 | V41: =T41+V35+V37+V39 -> 2032.4106 | W41: =W11+W31+W21 -> 3002.3727 | AC41: =E41+AC35+AC37+AC39 -> 6473 | AD41: =AC41+AD35+AD37+AD39 -> 7246 | AE41: =AD41+AE35+AE37+AE39-1 -> 6975 | AF41: =AE41+AF35+AF37+AF39 -> 6682.64 | AG41: =AF41+AG35+AG37+AG39 -> 6378.5856 | AH41: =AG41+AH35+AH37+AH39 -> 6062.369 | AI41: =AH41+AI35+AI37+AI39 -> 5733.5038 | AJ41: =AI41+AJ35+AJ37+AJ39 -> 5391.4839 | AK41: =AJ41+AK35+AK37+AK39 -> 5035.7833
B42: Growth (%) | C42: =IFERROR(C41/#REF!-1, "-") -> - | D42: =IFERROR(D41/#REF!-1, "-") -> - | E42: =IFERROR(E41/#REF!-1, "-") -> - | F42: =IFERROR(F41/C41-1, "-") -> 0.20516214 | G42: =IFERROR(G41/D41-1, "-") -> 0.24658741 | H42: =IFERROR(H41/F41-1, "-") -> 0.19989017 | I42: =IFERROR(I41/G41-1, "-") -> 0.015895443 | J42: =IFERROR(J41/H41-1, "-") -> -0.065675057 | K42: =IFERROR(K41/I41-1, "-") -> 0.0055632823 | L42: =IFERROR(L41/J41-1, "-") -> -0.075924565 | M42: =IFERROR(M41/K41-1, "-") -> 0.0057538036 | N42: =IFERROR(N41/L41-1, "-") -> -0.085173602 | O42: =IFERROR(O41/M41-1, "-") -> 0.0059497222 | ... W42: =IFERROR(W41/U41-1, "-") -> 0.0067888122 | AC42: =IFERROR(AC41/E41-1, "-") -> 0.22293595 | AD42: =IFERROR(AD41/AC41-1, "-") -> 0.11941913 | AE42: =IFERROR(AE41/AD41-1, "-") -> -0.037399945 | AF42: =IFERROR(AF41/AE41-1, "-") -> -0.041915412 | AG42: =IFERROR(AG41/AF41-1, "-") -> -0.045499144 | AH42: =IFERROR(AH41/AG41-1, "-") -> -0.049574717 | AI42: =IFERROR(AI41/AH41-1, "-") -> -0.054246985 | AJ42: =IFERROR(AJ41/AI41-1, "-") -> -0.059652851 | AK42: =IFERROR(AK41/AJ41-1, "-") -> -0.065974534

Sheet Advertisment & promotional spen
B2: In Euro millions | C2: H1'21 | D2: H2'21 | E2: FY21 | F2: H1'22 | G2: H2'22 | H2: H1'23 | I2: H2'23 | J2: H1'24 | K2: H2'24 | L2: H1'25 | M2: H2'25 | N2: H1'26 | O2: H2'26 | P2: H1'27 | Q2: H2'27 | R2: H1'28 | S2: H2'28 | T2: H1'29 | U2: H2'29 | V2: H1'30 | W2: H2'30 | AC2: FY22 | AD2: FY23 | AE2: FY24 | AF2: FY25 | AG2: FY26 | AH2: FY27 | AI2: FY28 | AJ2: FY29 | AK2: FY30
B4: Americas
B5: Organic | F5: -7 | G5: =AC5-F5 -> -58 | H5: -45 | I5: =AD5-H5 -> -12 | J5: -13 | K5: =AE5-J5 -> 70 | L5: 46 | M5: =K5*(1+M6) -> 74.9 | N5: =L5*(1+N6) -> 49.22 | O5: =M5*(1+O6) -> 80.143 | P5: =N5*(1+P6) -> 52.6654 | Q5: =O5*(1+Q6) -> 85.75301 | R5: =P5*(1+R6) -> 56.351978 | S5: =Q5*(1+S6) -> 91.755721 | T5: =R5*(1+T6) -> 60.296616 | ... W5: =U5*(1+W6) -> 105.05112 | AC5: -65 | AD5: -57 | AE5: 57 | AF5: =L5+M5 -> 120.9 | AG5: =N5+O5 -> 129.363 | AH5: =P5+Q5 -> 138.41841 | AI5: =R5+S5 -> 148.1077 | AJ5: =T5+U5 -> 158.47524 | AK5: =V5+W5 -> 169.5685
B6: Organic growth (%) | C6: =IFERROR(C5/#REF!-1, "-") -> - | D6: =IFERROR(D5/#REF!-1, "-") -> - | E6: =IFERROR(E5/#REF!-1, "-") -> - | F6: =F5/C11 -> 0.028 | G6: =G5/D11 -> 0.26363636 | H6: =H5/F11 -> 0.17045455 | I6: =I5/G11 -> 0.039473684 | J6: =J5/H11 -> 0.037249284 | K6: =K5/I11 -> -0.20771513 | L6: =L5/J11 -> -0.12299465 | M6: 0.07 | N6: 0.07 | O6: 0.07 | P6: 0.07 | Q6: 0.07 | R6: 0.07 | S6: 0.07 | T6: 0.07 | U6: 0.07 | V6: 0.07 | W6: 0.07 | AC6: =AC5/E11 -> 0.13829787 | AD6: =AD5/AC11 -> 0.1 | AE6: =AE5/AD11 -> -0.082848837 | AF6: =AF5/AE5-1 -> 1.1210526 | AG6: =AG5/AF5-1 -> 0.07 | AH6: =AH5/AG5-1 -> 0.07 | AI6: =AI5/AH5-1 -> 0.07 | AJ6: =AJ5/AI5-1 -> 0.07 | AK6: =AK5/AJ5-1 -> 0.07
B7: Fx | F7: -5 | G7: =AC7-F7 -> -23 | H7: -37 | I7: =AD7-H7 -> -1 | J7: 23 | K7: =AE7-J7 -> 2 | L7: 10 | M7: =K7*(1+M8) -> 2.14 | N7: =L7*(1+N8) -> 10.7 | O7: =M7*(1+O8) -> 2.2898 | P7: =N7*(1+P8) -> 11.449 | Q7: =O7*(1+Q8) -> 2.450086 | R7: =P7*(1+R8) -> 12.25043 | S7: =Q7*(1+S8) -> 2.621592 | T7: =R7*(1+T8) -> 13.10796 | ... W7: =U7*(1+W8) -> 3.0014607 | AC7: -28 | AD7: -38 | AE7: 25 | AF7: =L7+M7 -> 12.14 | AG7: =N7+O7 -> 12.9898 | AH7: =P7+Q7 -> 13.899086 | AI7: =R7+S7 -> 14.872022 | AJ7: =T7+U7 -> 15.913064 | AK7: =V7+W7 -> 17.026978
B8: Fx growth (%) | C8: =IFERROR(C7/#REF!-1, "-") -> - | D8: =IFERROR(D7/#REF!-1, "-") -> - | E8: =IFERROR(E7/#REF!-1, "-") -> - | F8: =F7/C11 -> 0.02 | G8: =G7/D11 -> 0.10454545 | H8: =H7/F11 -> 0.14015152 | I8: =I7/G11 -> 0.0032894737 | J8: =J7/H11 -> -0.065902579 | K8: =K7/I11 -> -0.0059347181 | L8: =L7/J11 -> -0.026737968 | M8: 0.07 | N8: 0.07 | O8: 0.07 | P8: 0.07 | Q8: 0.07 | R8: 0.07 | S8: 0.07 | T8: 0.07 | U8: 0.07 | V8: 0.07 | W8: 0.07 | AC8: =AC7/E11 -> 0.059574468 | AD8: =AD7/AC11 -> 0.066666667 | AE8: =AE7/AD11 -> -0.036337209 | AF8: =AF7/AE7-1 -> -0.5144 | AG8: =AG7/AF7-1 -> 0.07 | AH8: =AH7/AG7-1 -> 0.07 | AI8: =AI7/AH7-1 -> 0.07 | AJ8: =AJ7/AI7-1 -> 0.07 | AK8: =AK7/AJ7-1 -> 0.07
B9: Scope | F9: -3 | G9: =AC9-F9 -> -3 | H9: -3 | I9: =AD9-H9 -> -20 | J9: -35 | K9: =AE9-J9 -> -30 | L9: -4 | M9: =K9*(1+M10) -> -32.1 | N9: =L9*(1+N10) -> -4.28 | O9: =M9*(1+O10) -> -34.347 | P9: =N9*(1+P10) -> -4.5796 | Q9: =O9*(1+Q10) -> -36.75129 | R9: =P9*(1+R10) -> -4.900172 | S9: =Q9*(1+S10) -> -39.32388 | T9: =R9*(1+T10) -> -5.243184 | ... W9: =U9*(1+W10) -> -45.021911 | AC9: -6 | AD9: -23 | AE9: -65 | AF9: =L9+M9 -> -36.1 | AG9: =N9+O9 -> -38.627 | AH9: =P9+Q9 -> -41.33089 | AI9: =R9+S9 -> -44.224052 | AJ9: =T9+U9 -> -47.319736 | AK9: =V9+W9 -> -50.632117
B10: Scope growth (%) | C10: =IFERROR(C9/#REF!-1, "-") -> - | D10: =IFERROR(D9/#REF!-1, "-") -> - | E10: =IFERROR(E9/#REF!-1, "-") -> - | F10: =F9/C11 -> 0.012 | G10: =G9/D11 -> 0.013636364 | H10: =H9/F11 -> 0.011363636 | I10: =I9/G11 -> 0.065789474 | J10: =J9/H11 -> 0.10028653 | K10: =K9/I11 -> 0.089020772 | L10: =L9/J11 -> 0.010695187 | M10: 0.07 | N10: 0.07 | O10: 0.07 | P10: 0.07 | Q10: 0.07 | R10: 0.07 | S10: 0.07 | T10: 0.07 | U10: 0.07 | V10: 0.07 | W10: 0.07 | AC10: =AC9/E11 -> 0.012765957 | AD10: =AD9/AC11 -> 0.040350877 | AE10: =AE9/AD11 -> 0.094476744 | AF10: =IFERROR(AF9/AE9-1, "-") -> -0.44461538 | AG10: =IFERROR(AG9/AF9-1, "-") -> 0.07 | AH10: =IFERROR(AH9/AG9-1, "-") -> 0.07 | AI10: =IFERROR(AI9/AH9-1, "-") -> 0.07 | AJ10: =IFERROR(AJ9/AI9-1, "-") -> 0.07 | AK10: =IFERROR(AK9/AJ9-1, "-") -> 0.07
B11: Total Sales - Americas | C11: -250 | D11: =E11-C11 -> -220 | E11: -470 | F11: =C11+F5+F7+F9+1 -> -264 | G11: =D11+G5+G7+G9 -> -304 | H11: =F11+H5+H7+H9 -> -349 | I11: =G11+I5+I7+I9 -> -337 | J11: =H11+J5+J7+J9 -> -374 | K11: =I11+K5+K7+K9 -> -295 | L11: =J11+L5+L7+L9 -> -322 | M11: =K11+M5+M7+M9 -> -250.06 | N11: =L11+N5+N7+N9 -> -266.36 | O11: =M11+O5+O7+O9 -> -201.9742 | ... W11: =U11+W5+W7+W9 -> 26.468886 | AC11: =E11+AC5+AC7+AC9-1 -> -570 | AD11: =AC11+AD5+AD7+AD9 -> -688 | AE11: =AD11+AE5+AE7+AE9+2 -> -669 | AF11: =AE11+AF5+AF7+AF9 -> -572.06 | AG11: =AF11+AG5+AG7+AG9 -> -468.3342 | AH11: =AG11+AH5+AH7+AH9 -> -357.34759 | AI11: =AH11+AI5+AI7+AI9 -> -238.59193 | AJ11: =AI11+AJ5+AJ7+AJ9 -> -111.52336 | AK11: =AJ11+AK5+AK7+AK9 -> 24.440004
B12: Growth (%) | C12: =IFERROR(C11/#REF!-1, "-") -> - | D12: =IFERROR(D11/#REF!-1, "-") -> - | E12: =IFERROR(E11/#REF!-1, "-") -> - | F12: =IFERROR(F11/C11-1, "-") -> 0.056 | G12: =IFERROR(G11/D11-1, "-") -> 0.38181818 | H12: =IFERROR(H11/F11-1, "-") -> 0.3219697 | I12: =IFERROR(I11/G11-1, "-") -> 0.10855263 | J12: =IFERROR(J11/H11-1, "-") -> 0.071633238 | K12: =IFERROR(K11/I11-1, "-") -> -0.12462908 | L12: =IFERROR(L11/J11-1, "-") -> -0.13903743 | M12: =IFERROR(M11/K11-1, "-") -> -0.15233898 | N12: =IFERROR(N11/L11-1, "-") -> -0.17279503 | O12: =IFERROR(O11/M11-1, "-") -> -0.19229705 | ... W12: =IFERROR(W11/U11-1, "-") -> -1.7239494 | AC12: =IFERROR(AC11/E11-1, "-") -> 0.21276596 | AD12: =IFERROR(AD11/AC11-1, "-") -> 0.20701754 | AE12: =IFERROR(AE11/AD11-1, "-") -> -0.027616279 | AF12: =IFERROR(AF11/AE11-1, "-") -> -0.14490284 | AG12: =IFERROR(AG11/AF11-1, "-") -> -0.18131979 | AH12: =IFERROR(AH11/AG11-1, "-") -> -0.23698164 | AI12: =IFERROR(AI11/AH11-1, "-") -> -0.33232536 | AJ12: =IFERROR(AJ11/AI11-1, "-") -> -0.53257697 | AK12: =IFERROR(AK11/AJ11-1, "-") -> -1.219147
B14: Asia/Row
B15: Organic | F15: -58 | G15: =AC15-F15 -> -9 | H15: -25 | I15: =AD15-H15 -> -86 | J15: 7 | K15: =AE15-J15 -> 6 | L15: 56 | M15: =K15*(1+M16) -> 6.42 | N15: =L15*(1+N16) -> 59.92 | O15: =M15*(1+O16) -> 6.8694 | P15: =N15*(1+P16) -> 64.1144 | Q15: =O15*(1+Q16) -> 7.350258 | R15: =P15*(1+R16) -> 68.602408 | S15: =Q15*(1+S16) -> 7.8647761 | T15: =R15*(1+T16) -> 73.404577 | ... W15: =U15*(1+W16) -> 9.0043821 | AC15: -67 | AD15: -111 | AE15: 13 | AF15: =L15+M15 -> 62.42 | AG15: =N15+O15 -> 66.7894 | AH15: =P15+Q15 -> 71.464658 | AI15: =R15+S15 -> 76.467184 | AJ15: =T15+U15 -> 81.819887 | AK15: =V15+W15 -> 87.547279
B16: Organic growth (%) | C16: =IFERROR(C15/#REF!-1, "-") -> - | D16: =IFERROR(D15/#REF!-1, "-") -> - | E16: =IFERROR(E15/#REF!-1, "-") -> - | F16: =F15/C21 -> 0.19931271 | G16: =G15/D21 -> 0.035856574 | H16: =H15/F21 -> 0.069252078 | I16: =I15/G21 -> 0.31617647 | J16: =J15/H21 -> -0.0175 | K16: =K15/I21 -> -0.017595308 | L16: =L15/J21 -> -0.15686275 | M16: 0.07 | N16: 0.07 | O16: 0.07 | P16: 0.07 | Q16: 0.07 | R16: 0.07 | S16: 0.07 | T16: 0.07 | U16: 0.07 | V16: 0.07 | W16: 0.07 | AC16: =AC15/E21 -> 0.12361624 | AD16: =AD15/AC21 -> 0.17535545 | AE16: =AE15/AD21 -> -0.017567568 | AF16: =AF15/AE15-1 -> 3.8015385 | AG16: =AG15/AF15-1 -> 0.07 | AH16: =AH15/AG15-1 -> 0.07 | AI16: =AI15/AH15-1 -> 0.07 | AJ16: =AJ15/AI15-1 -> 0.07 | AK16: =AK15/AJ15-1 -> 0.07
B17: Fx | F17: -12 | G17: =AC17-F17 -> -12 | H17: -14 | I17: =AD17-H17 -> 21 | J17: 37 | K17: =AE17-J17 -> 14 | L17: 6 | M17: =K17*(1+M18) -> 14.98 | N17: =L17*(1+N18) -> 6.42 | O17: =M17*(1+O18) -> 16.0286 | P17: =N17*(1+P18) -> 6.8694 | Q17: =O17*(1+Q18) -> 17.150602 | R17: =P17*(1+R18) -> 7.350258 | S17: =Q17*(1+S18) -> 18.351144 | T17: =R17*(1+T18) -> 7.8647761 | ... W17: =U17*(1+W18) -> 21.010225 | AC17: -24 | AD17: 7 | AE17: 51 | AF17: =L17+M17 -> 20.98 | AG17: =N17+O17 -> 22.4486 | AH17: =P17+Q17 -> 24.020002 | AI17: =R17+S17 -> 25.701402 | AJ17: =T17+U17 -> 27.5005 | AK17: =V17+W17 -> 29.425535
B18: Fx growth (%) | C18: =IFERROR(C17/#REF!-1, "-") -> - | D18: =IFERROR(D17/#REF!-1, "-") -> - | E18: =IFERROR(E17/#REF!-1, "-") -> - | F18: =F17/C21 -> 0.041237113 | G18: =G17/D21 -> 0.047808765 | H18: =H17/F21 -> 0.038781163 | I18: =I17/G21 -> -0.077205882 | J18: =J17/H21 -> -0.0925 | K18: =K17/I21 -> -0.041055718 | L18: =L17/J21 -> -0.016806723 | M18: 0.07 | N18: 0.07 | O18: 0.07 | P18: 0.07 | Q18: 0.07 | R18: 0.07 | S18: 0.07 | T18: 0.07 | U18: 0.07 | V18: 0.07 | W18: 0.07 | AC18: =AC17/E21 -> 0.044280443 | AD18: =AD17/AC21 -> -0.011058452 | AE18: =AE17/AD21 -> -0.068918919 | AF18: =AF17/AE17-1 -> -0.58862745 | AG18: =AG17/AF17-1 -> 0.07 | AH18: =AH17/AG17-1 -> 0.07 | AI18: =AI17/AH17-1 -> 0.07 | AJ18: =AJ17/AI17-1 -> 0.07 | AK18: =AK17/AJ17-1 -> 0.07
B19: Scope | F19: 0 | G19: =AC19-F19 -> 0 | H19: 0 | I19: =AD19-H19 -> -4 | J19: -2 | K19: =AE19-J19 -> -1 | L19: -2 | M19: =K19*(1+M20) -> -1.07 | N19: =L19*(1+N20) -> -2.14 | O19: =M19*(1+O20) -> -1.1449 | P19: =N19*(1+P20) -> -2.2898 | Q19: =O19*(1+Q20) -> -1.225043 | R19: =P19*(1+R20) -> -2.450086 | S19: =Q19*(1+S20) -> -1.310796 | T19: =R19*(1+T20) -> -2.621592 | ... W19: =U19*(1+W20) -> -1.5007304 | AC19: 0 | AD19: -4 | AE19: -3 | AF19: =L19+M19 -> -3.07 | AG19: =N19+O19 -> -3.2849 | AH19: =P19+Q19 -> -3.514843 | AI19: =R19+S19 -> -3.760882 | AJ19: =T19+U19 -> -4.0241438 | AK19: =V19+W19 -> -4.3058338
B20: Scope growth (%) | C20: =IFERROR(C19/#REF!-1, "-") -> - | D20: =IFERROR(D19/#REF!-1, "-") -> - | E20: =IFERROR(E19/#REF!-1, "-") -> - | F20: =F19/C21 -> 0 | G20: =G19/D21 -> 0 | H20: =H19/F21 -> 0 | I20: =I19/G21 -> 0.014705882 | J20: =J19/H21 -> 0.005 | K20: =K19/I21 -> 0.0029325513 | L20: =L19/J21 -> 0.0056022409 | M20: 0.07 | N20: 0.07 | O20: 0.07 | P20: 0.07 | Q20: 0.07 | R20: 0.07 | S20: 0.07 | T20: 0.07 | U20: 0.07 | V20: 0.07 | W20: 0.07 | AC20: =AC19/E21 -> 0 | AD20: =AD19/AC21 -> 0.0063191153 | AE20: =AE19/AD21 -> 0.0040540541 | AF20: =IFERROR(AF19/AE19-1, "-") -> 0.023333333 | AG20: =IFERROR(AG19/AF19-1, "-") -> 0.07 | AH20: =IFERROR(AH19/AG19-1, "-") -> 0.07 | AI20: =IFERROR(AI19/AH19-1, "-") -> 0.07 | AJ20: =IFERROR(AJ19/AI19-1, "-") -> 0.07 | AK20: =IFERROR(AK19/AJ19-1, "-") -> 0.07
B21: Total Sales - Asia/Row | C21: -291 | D21: =E21-C21 -> -251 | E21: -542 | F21: =C21+F15+F17+F19 -> -361 | G21: =D21+G15+G17+G19 -> -272 | H21: =F21+H15+H17+H19 -> -400 | I21: =G21+I15+I17+I19 -> -341 | J21: =H21+J15+J17+J19+1 -> -357 | K21: =I21+K15+K17+K19 -> -322 | L21: =J21+L15+L17+L19+1 -> -296 | M21: =K21+M15+M17+M19 -> -301.67 | N21: =L21+N15+N17+N19 -> -231.8 | O21: =M21+O15+O17+O19 -> -279.9169 | P21: =N21+P15+P17+P19 -> -163.106 | Q21: =O21+Q15+Q17+Q19 -> -256.64108 | R21: =P21+R15+R17+R19 -> -89.60342 | S21: =Q21+S15+S17+S19 -> -231.73596 | T21: =R21+T15+T17+T19 -> -10.955659 | ... W21: =U21+W15+W17+W19 -> -176.5736 | AC21: =E21+AC15+AC17+AC19 -> -633 | AD21: =AC21+AD15+AD17+AD19+1 -> -740 | AE21: =AD21+AE15+AE17+AE19+1 -> -678 | AF21: =AE21+AF15+AF17+AF19 -> -597.67 | AG21: =AF21+AG15+AG17+AG19 -> -511.7169 | AH21: =AG21+AH15+AH17+AH19 -> -419.74708 | AI21: =AH21+AI15+AI17+AI19 -> -321.33938 | AJ21: =AI21+AJ15+AJ17+AJ19 -> -216.04314 | AK21: =AJ21+AK15+AK17+AK19 -> -103.37615
B22: Growth (%) | C22: =IFERROR(C21/#REF!-1, "-") -> - | D22: =IFERROR(D21/#REF!-1, "-") -> - | E22: =IFERROR(E21/#REF!-1, "-") -> - | F22: =IFERROR(F21/C21-1, "-") -> 0.24054983 | G22: =IFERROR(G21/D21-1, "-") -> 0.083665339 | H22: =IFERROR(H21/F21-1, "-") -> 0.10803324 | I22: =IFERROR(I21/G21-1, "-") -> 0.25367647 | J22: =IFERROR(J21/H21-1, "-") -> -0.1075 | K22: =IFERROR(K21/I21-1, "-") -> -0.055718475 | L22: =IFERROR(L21/J21-1, "-") -> -0.17086835 | M22: =IFERROR(M21/K21-1, "-") -> -0.063136646 | N22: =IFERROR(N21/L21-1, "-") -> -0.21689189 | O22: =IFERROR(O21/M21-1, "-") -> -0.072108927 | ... W22: =IFERROR(W21/U21-1, "-") -> -0.13903275 | AC22: =IFERROR(AC21/E21-1, "-") -> 0.16789668 | AD22: =IFERROR(AD21/AC21-1, "-") -> 0.16903633 | AE22: =IFERROR(AE21/AD21-1, "-") -> -0.083783784 | AF22: =IFERROR(AF21/AE21-1, "-") -> -0.11848083 | AG22: =IFERROR(AG21/AF21-1, "-") -> -0.14381364 | AH22: =IFERROR(AH21/AG21-1, "-") -> -0.17972793 | AI22: =IFERROR(AI21/AH21-1, "-") -> -0.23444524 | AJ22: =IFERROR(AJ21/AI21-1, "-") -> -0.32767924 | AK22: =IFERROR(AK21/AJ21-1, "-") -> -0.52150225
B24: Europe
B25: Organic | F25: -46 | G25: =AC25-F25 -> -61 | H25: -27 | I25: =AD25-H25 -> 14 | J25: -1 | K25: =AE25-J25 -> -10 | L25: 10 | M25: =K25*(1+M26) -> -10.7 | N25: =L25*(1+N26) -> 10.7 | O25: =M25*(1+O26) -> -11.449 | P25: =N25*(1+P26) -> 11.449 | Q25: =O25*(1+Q26) -> -12.25043 | R25: =P25*(1+R26) -> 12.25043 | S25: =Q25*(1+S26) -> -13.10796 | T25: =R25*(1+T26) -> 13.10796 | ... W25: =U25*(1+W26) -> -15.007304 | AC25: -107 | AD25: -13 | AE25: -11 | AF25: =L25+M25 -> -0.7 | AG25: =N25+O25 -> -0.749 | AH25: =P25+Q25 -> -0.80143 | AI25: =R25+S25 -> -0.8575301 | AJ25: =T25+U25 -> -0.91755721 | AK25: =V25+W25 -> -0.98178621
B26: Organic growth (%) | C26: =IFERROR(C25/#REF!-1, "-") -> - | D26: =IFERROR(D25/#REF!-1, "-") -> - | E26: =IFERROR(E25/#REF!-1, "-") -> - | F26: =F25/C31 -> 0.2804878 | G26: =G25/D31 -> 0.28110599 | H26: =H25/F31 -> 0.12616822 | I26: =I25/G31 -> -0.049295775 | J26: =J25/H31 -> 0.0040816327 | K26: =K25/I31 -> 0.036900369 | L26: =L25/J31 -> -0.040322581 | M26: 0.07 | N26: 0.07 | O26: 0.07 | P26: 0.07 | Q26: 0.07 | R26: 0.07 | S26: 0.07 | T26: 0.07 | U26: 0.07 | V26: 0.07 | W26: 0.07 | AC26: =AC25/E31 -> 0.2808399 | AD26: =AD25/AC31 -> 0.026209677 | AE26: =AE25/AD31 -> 0.021442495 | AF26: =AF25/AE25-1 -> -0.93636364 | AG26: =AG25/AF25-1 -> 0.07 | AH26: =AH25/AG25-1 -> 0.07 | AI26: =AI25/AH25-1 -> 0.07 | AJ26: =AJ25/AI25-1 -> 0.07 | AK26: =AK25/AJ25-1 -> 0.07
B27: Fx | F27: -2 | G27: =AC27-F27 -> -4 | H27: -2 | I27: =AD27-H27 -> 2 | J27: 1 | K27: =AE27-J27 -> -1 | L27: -1 | M27: =K27*(1+M28) -> -1.07 | N27: =L27*(1+N28) -> -1.07 | O27: =M27*(1+O28) -> -1.1449 | P27: =N27*(1+P28) -> -1.1449 | Q27: =O27*(1+Q28) -> -1.225043 | R27: =P27*(1+R28) -> -1.225043 | S27: =Q27*(1+S28) -> -1.310796 | T27: =R27*(1+T28) -> -1.310796 | ... W27: =U27*(1+W28) -> -1.5007304 | AC27: -6 | AD27: 0 | AE27: 0 | AF27: =L27+M27 -> -2.07 | AG27: =N27+O27 -> -2.2149 | AH27: =P27+Q27 -> -2.369943 | AI27: =R27+S27 -> -2.535839 | AJ27: =T27+U27 -> -2.7133477 | AK27: =V27+W27 -> -2.9032821
B28: Fx growth (%) | C28: =IFERROR(C27/#REF!-1, "-") -> - | D28: =IFERROR(D27/#REF!-1, "-") -> - | E28: =IFERROR(E27/#REF!-1, "-") -> - | F28: =F27/C31 -> 0.012195122 | G28: =G27/D31 -> 0.01843318 | H28: =H27/F31 -> 0.0093457944 | I28: =I27/G31 -> -0.0070422535 | J28: =J27/H31 -> -0.0040816327 | K28: =K27/I31 -> 0.0036900369 | L28: =L27/J31 -> 0.0040322581 | M28: 0.07 | N28: 0.07 | O28: 0.07 | P28: 0.07 | Q28: 0.07 | R28: 0.07 | S28: 0.07 | T28: 0.07 | U28: 0.07 | V28: 0.07 | W28: 0.07 | AC28: =AC27/E31 -> 0.015748031 | AD28: =AD27/AC31 -> 0 | AE28: =AE27/AD31 -> 0 | AF28: =AF27/AE27-1 -> #DIV/0! | AG28: =AG27/AF27-1 -> 0.07 | AH28: =AH27/AG27-1 -> 0.07 | AI28: =AI27/AH27-1 -> 0.07 | AJ28: =AJ27/AI27-1 -> 0.07 | AK28: =AK27/AJ27-1 -> 0.07
B29: Scope | F29: -1 | G29: =AC29-F29 -> -2 | H29: -1 | I29: =AD29-H29 -> -3 | J29: -3 | K29: =AE29-J29 -> 3 | L29: 1 | M29: =K29*(1+M30) -> 3.21 | N29: =L29*(1+N30) -> 1.07 | O29: =M29*(1+O30) -> 3.4347 | P29: =N29*(1+P30) -> 1.1449 | Q29: =O29*(1+Q30) -> 3.675129 | R29: =P29*(1+R30) -> 1.225043 | S29: =Q29*(1+S30) -> 3.932388 | T29: =R29*(1+T30) -> 1.310796 | ... W29: =U29*(1+W30) -> 4.5021911 | AC29: -3 | AD29: -4 | AE29: 0 | AF29: =L29+M29 -> 4.21 | AG29: =N29+O29 -> 4.5047 | AH29: =P29+Q29 -> 4.820029 | AI29: =R29+S29 -> 5.157431 | AJ29: =T29+U29 -> 5.5184512 | AK29: =V29+W29 -> 5.9047428
B30: Scope growth (%) | C30: =IFERROR(C29/#REF!-1, "-") -> - | D30: =IFERROR(D29/#REF!-1, "-") -> - | E30: =IFERROR(E29/#REF!-1, "-") -> - | F30: =F29/C31 -> 0.006097561 | G30: =G29/D31 -> 0.0092165899 | H30: =H29/F31 -> 0.0046728972 | I30: =I29/G31 -> 0.01056338 | J30: =J29/H31 -> 0.012244898 | K30: =K29/I31 -> -0.011070111 | L30: =L29/J31 -> -0.0040322581 | M30: 0.07 | N30: 0.07 | O30: 0.07 | P30: 0.07 | Q30: 0.07 | R30: 0.07 | S30: 0.07 | T30: 0.07 | U30: 0.07 | V30: 0.07 | W30: 0.07 | AC30: =AC29/E31 -> 0.0078740157 | AD30: =AD29/AC31 -> 0.0080645161 | AE30: =AE29/AD31 -> 0 | AF30: =IFERROR(AF29/AE29-1, "-") -> - | AG30: =IFERROR(AG29/AF29-1, "-") -> 0.07 | AH30: =IFERROR(AH29/AG29-1, "-") -> 0.07 | AI30: =IFERROR(AI29/AH29-1, "-") -> 0.07 | AJ30: =IFERROR(AJ29/AI29-1, "-") -> 0.07 | AK30: =IFERROR(AK29/AJ29-1, "-") -> 0.07
B31: Total Sales - Europe | C31: -164 | D31: =E31-C31 -> -217 | E31: -381 | F31: =C31+F25+F27+F29-1 -> -214 | G31: =D31+G25+G27+G29 -> -284 | H31: =F31+H25+H27+H29-1 -> -245 | I31: =G31+I25+I27+I29 -> -271 | J31: =H31+J25+J27+J29 -> -248 | K31: =I31+K25+K27+K29 -> -279 | L31: =J31+L25+L27+L29 -> -238 | M31: =K31+M25+M27+M29 -> -287.56 | N31: =L31+N25+N27+N29 -> -227.3 | O31: =M31+O25+O27+O29 -> -296.7192 | P31: =N31+P25+P27+P29 -> -215.851 | ... W31: =U31+W25+W27+W29 -> -340.23217 | AC31: =E31+AC25+AC27+AC29+1 -> -496 | AD31: =AC31+AD25+AD27+AD29 -> -513 | AE31: =AD31+AE25+AE27+AE29-3 -> -527 | AF31: =AE31+AF25+AF27+AF29 -> -525.56 | AG31: =AF31+AG25+AG27+AG29 -> -524.0192 | AH31: =AG31+AH25+AH27+AH29 -> -522.37054 | AI31: =AH31+AI25+AI27+AI29 -> -520.60648 | AJ31: =AI31+AJ25+AJ27+AJ29 -> -518.71894 | AK31: =AJ31+AK25+AK27+AK29 -> -516.69926
B32: Growth (%) | C32: =IFERROR(C31/#REF!-1, "-") -> - | D32: =IFERROR(D31/#REF!-1, "-") -> - | E32: =IFERROR(E31/#REF!-1, "-") -> - | F32: =IFERROR(F31/C31-1, "-") -> 0.30487805 | G32: =IFERROR(G31/D31-1, "-") -> 0.30875576 | H32: =IFERROR(H31/F31-1, "-") -> 0.14485981 | I32: =IFERROR(I31/G31-1, "-") -> -0.045774648 | J32: =IFERROR(J31/H31-1, "-") -> 0.012244898 | K32: =IFERROR(K31/I31-1, "-") -> 0.029520295 | L32: =IFERROR(L31/J31-1, "-") -> -0.040322581 | M32: =IFERROR(M31/K31-1, "-") -> 0.030681004 | N32: =IFERROR(N31/L31-1, "-") -> -0.044957983 | O32: =IFERROR(O31/M31-1, "-") -> 0.03185144 | ... W32: =IFERROR(W31/U31-1, "-") -> 0.03657794 | AC32: =IFERROR(AC31/E31-1, "-") -> 0.30183727 | AD32: =IFERROR(AD31/AC31-1, "-") -> 0.034274194 | AE32: =IFERROR(AE31/AD31-1, "-") -> 0.027290448 | AF32: =IFERROR(AF31/AE31-1, "-") -> -0.0027324478 | AG32: =IFERROR(AG31/AF31-1, "-") -> -0.00293173 | AH32: =IFERROR(AH31/AG31-1, "-") -> -0.0031461748 | AI32: =IFERROR(AI31/AH31-1, "-") -> -0.0033770318 | AJ32: =IFERROR(AJ31/AI31-1, "-") -> -0.003625668 | AK32: =IFERROR(AK31/AJ31-1, "-") -> -0.0038935816
B34: Total
B35: Organic | F35: =F5+F15+F25 -> -111 | G35: =AC35-F35 -> -128 | H35: =H5+H15+H25 -> -97 | I35: =AD35-H35 -> -84 | J35: =J5+J15+J25 -> -7 | K35: =AE35-J35 -> 66 | L35: =L5+L15+L25 -> 112 | M35: =AF35-L35 -> 70.62 | N35: =N5+N15+N25 -> 119.84 | O35: =AG35-N35 -> 75.5634 | P35: =P5+P15+P25 -> 128.2288 | Q35: =AH35-P35 -> 80.852838 | R35: =R5+R15+R25 -> 137.20482 | S35: =AI35-R35 -> 86.512537 | T35: =T5+T15+T25 -> 146.80915 | U35: =AJ35-T35 -> 92.568414 | V35: =V5+V15+V25 -> 157.08579 | W35: =AK35-V35 -> 99.048203 | AC35: =AC5+AC15+AC25 -> -239 | AD35: =AD5+AD15+AD25 -> -181 | AE35: =AE5+AE15+AE25 -> 59 | AF35: =AF5+AF15+AF25 -> 182.62 | AG35: =AG5+AG15+AG25 -> 195.4034 | AH35: =AH5+AH15+AH25 -> 209.08164 | AI35: =AI5+AI15+AI25 -> 223.71735 | AJ35: =AJ5+AJ15+AJ25 -> 239.37757 | AK35: =AK5+AK15+AK25 -> 256.134
B36: Organic growth (%) | F36: =F35/C41 -> 0.15744681 | G36: =G35/D41 -> 0.18604651 | H36: =H35/F41 -> 0.11547619 | I36: =I35/G41 -> 0.097674419 | J36: =J35/H41 -> 0.0070422535 | K36: =K35/I41 -> -0.069546891 | L36: =L35/J41 -> -0.11428571 | M36: =M35/K41 -> -0.078816964 | N36: =N35/L41 -> -0.13967366 | O36: =O35/M41 -> -0.090032527 | ... W36: =W35/U41 -> -0.17380671 | AC36: =AC35/E41 -> 0.17157215 | AD36: =AD35/AC41 -> 0.10653325 | AE36: =AE35/AD41 -> -0.030428056 | AF36: =AF35/AE41 -> -0.097345416 | AG36: =AG35/AF41 -> -0.1151267 | AH36: =AH35/AG41 -> -0.13882595 | AI36: =AI35/AH41 -> -0.17189653 | AJ36: =AJ35/AI41 -> -0.22112629 | AK36: =AK35/AJ41 -> -0.30194318
B37: Fx | F37: =F7+F17+F27 -> -19 | G37: =AC37-F37 -> -39 | H37: =H7+H17+H27 -> -53 | I37: =AD37-H37 -> 22 | J37: =J7+J17+J27 -> 61 | K37: =AE37-J37 -> 15 | L37: =L7+L17+L27 -> 15 | M37: =AF37-L37 -> 16.05 | N37: =N7+N17+N27 -> 16.05 | O37: =AG37-N37 -> 17.1735 | P37: =P7+P17+P27 -> 17.1735 | Q37: =AH37-P37 -> 18.375645 | R37: =R7+R17+R27 -> 18.375645 | S37: =AI37-R37 -> 19.66194 | T37: =T7+T17+T27 -> 19.66194 | U37: =AJ37-T37 -> 21.038276 | V37: =V7+V17+V27 -> 21.038276 | W37: =AK37-V37 -> 22.510955 | AC37: =AC7+AC17+AC27 -> -58 | AD37: =AD7+AD17+AD27 -> -31 | AE37: =AE7+AE17+AE27 -> 76 | AF37: =AF7+AF17+AF27 -> 31.05 | AG37: =AG7+AG17+AG27 -> 33.2235 | AH37: =AH7+AH17+AH27 -> 35.549145 | AI37: =AI7+AI17+AI27 -> 38.037585 | AJ37: =AJ7+AJ17+AJ27 -> 40.700216 | AK37: =AK7+AK17+AK27 -> 43.549231
B38: Fx growth (%) | F38: =F37/C41 -> 0.026950355 | G38: =G37/D41 -> 0.056686047 | H38: =H37/F41 -> 0.063095238 | I38: =I37/G41 -> -0.025581395 | J38: =J37/H41 -> -0.061368209 | K38: =K37/I41 -> -0.015806112 | L38: =L37/J41 -> -0.015306122 | M38: =M37/K41 -> -0.017912946 | N38: =N37/L41 -> -0.018706294 | O38: =O37/M41 -> -0.020461938 | ... W38: =W37/U41 -> -0.039501526 | AC38: =AC37/E41 -> 0.041636755 | AD38: =AD37/AC41 -> 0.018246027 | AE38: =AE37/AD41 -> -0.039195462 | AF38: =AF37/AE41 -> -0.016551173 | AG38: =AG37/AF41 -> -0.019574439 | AH38: =AH37/AG41 -> -0.023603908 | AI38: =AI37/AH41 -> -0.02922674 | AJ38: =AJ37/AI41 -> -0.03759704 | AK38: =AK37/AJ41 -> -0.051337945
B39: Scope | F39: =F9+F19+F29 -> -4 | G39: =AC39-F39 -> -5 | H39: =H9+H19+H29 -> -4 | I39: =AD39-H39 -> -27 | J39: =J9+J19+J29 -> -40 | K39: =AE39-J39 -> -28 | L39: =L9+L19+L29 -> -5 | M39: =AF39-L39 -> -29.96 | N39: =N9+N19+N29 -> -5.35 | O39: =AG39-N39 -> -32.0572 | P39: =P9+P19+P29 -> -5.7245 | Q39: =AH39-P39 -> -34.301204 | R39: =R9+R19+R29 -> -6.125215 | S39: =AI39-R39 -> -36.702288 | T39: =T9+T19+T29 -> -6.5539801 | U39: =AJ39-T39 -> -39.271448 | V39: =V9+V19+V29 -> -7.0127587 | W39: =AK39-V39 -> -42.02045 | AC39: =AC9+AC19+AC29 -> -9 | AD39: =AD9+AD19+AD29 -> -31 | AE39: =AE9+AE19+AE29 -> -68 | AF39: =AF9+AF19+AF29 -> -34.96 | AG39: =AG9+AG19+AG29 -> -37.4072 | AH39: =AH9+AH19+AH29 -> -40.025704 | AI39: =AI9+AI19+AI29 -> -42.827503 | AJ39: =AJ9+AJ19+AJ29 -> -45.825429 | AK39: =AK9+AK19+AK29 -> -49.033209
B40: Scope growth (%) | F40: =F39/C41 -> 0.0056737589 | G40: =G39/D41 -> 0.0072674419 | H40: =H39/F41 -> 0.0047619048 | I40: =I39/G41 -> 0.031395349 | J40: =J39/H41 -> 0.040241449 | K40: =K39/I41 -> 0.029504742 | L40: =L39/J41 -> 0.0051020408 | M40: =M39/K41 -> 0.0334375 | N40: =N39/L41 -> 0.0062354312 | O40: =O39/M41 -> 0.038195618 | ... W40: =W39/U41 -> 0.073736181 | AC40: =AC39/E41 -> 0.0064608758 | AD40: =AD39/AC41 -> 0.018246027 | AE40: =AE39/AD41 -> 0.035069624 | AF40: =AF39/AE41 -> 0.018635394 | AG40: =AG39/AF41 -> 0.022039369 | AH40: =AH39/AG41 -> 0.026576252 | AI40: =AI39/AH41 -> 0.032907144 | AJ40: =AJ39/AI41 -> 0.042331482 | AK40: =AK39/AJ41 -> 0.057802724
B41: Total Sales | C41: =C11+C31+C21 -> -705 | D41: =D11+D31+D21 -> -688 | E41: =E11+E31+E21 -> -1393 | F41: =C41+F35+F37+F39-1 -> -840 | G41: =G11+G31+G21 -> -860 | H41: =F41+H35+H37+H39 -> -994 | I41: =I11+I31+I21 -> -949 | J41: =H41+J35+J37+J39 -> -980 | K41: =K11+K31+K21 -> -896 | L41: =J41+L35+L37+L39 -> -858 | M41: =M11+M31+M21 -> -839.29 | N41: =L41+N35+N37+N39 -> -727.46 | O41: =O11+O31+O21 -> -778.6103 | P41: =N41+P35+P37+P39 -> -587.7822 | Q41: =Q11+Q31+Q21 -> -713.68302 | R41: =P41+R35+R37+R39 -> -438.32695 | S41: =S11+S31+S21 -> -644.21083 | T41: =R41+T35+T37+T39 -> -278.40984 | U41: =U11+U31+U21 -> -569.87559 | V41: =T41+V35+V37+V39 -> -107.29853 | W41: =W11+W31+W21 -> -490.33688 | AC41: =E41+AC35+AC37+AC39 -> -1699 | AD41: =AC41+AD35+AD37+AD39+3 -> -1939 | AE41: =AD41+AE35+AE37+AE39-4 -> -1876 | AF41: =AE41+AF35+AF37+AF39 -> -1697.29 | AG41: =AF41+AG35+AG37+AG39 -> -1506.0703 | AH41: =AG41+AH35+AH37+AH39 -> -1301.4652 | AI41: =AH41+AI35+AI37+AI39 -> -1082.5378 | AJ41: =AI41+AJ35+AJ37+AJ39 -> -848.28543 | AK41: =AJ41+AK35+AK37+AK39 -> -597.63541
B42: Growth (%) | C42: =IFERROR(C41/#REF!-1, "-") -> - | D42: =IFERROR(D41/#REF!-1, "-") -> - | E42: =IFERROR(E41/#REF!-1, "-") -> - | F42: =IFERROR(F41/C41-1, "-") -> 0.19148936 | G42: =IFERROR(G41/D41-1, "-") -> 0.25 | H42: =IFERROR(H41/F41-1, "-") -> 0.18333333 | I42: =IFERROR(I41/G41-1, "-") -> 0.10348837 | J42: =IFERROR(J41/H41-1, "-") -> -0.014084507 | K42: =IFERROR(K41/I41-1, "-") -> -0.055848261 | L42: =IFERROR(L41/J41-1, "-") -> -0.1244898 | M42: =IFERROR(M41/K41-1, "-") -> -0.063292411 | N42: =IFERROR(N41/L41-1, "-") -> -0.15214452 | O42: =IFERROR(O41/M41-1, "-") -> -0.072298848 | ... W42: =IFERROR(W41/U41-1, "-") -> -0.13957206 | AC42: =IFERROR(AC41/E41-1, "-") -> 0.21966978 | AD42: =IFERROR(AD41/AC41-1, "-") -> 0.14125956 | AE42: =IFERROR(AE41/AD41-1, "-") -> -0.032490975 | AF42: =IFERROR(AF41/AE41-1, "-") -> -0.095261194 | AG42: =IFERROR(AG41/AF41-1, "-") -> -0.11266177 | AH42: =IFERROR(AH41/AG41-1, "-") -> -0.1358536 | AI42: =IFERROR(AI41/AH41-1, "-") -> -0.16821612 | AJ42: =IFERROR(AJ41/AI41-1, "-") -> -0.21639185 | AK42: =IFERROR(AK41/AJ41-1, "-") -> -0.2954784

Sheet Financial Statements
B1: In Euro Millions
B3: Income Statement | C3: H1'21 | D3: H2'21 | E3: FY21 | F3: H1'22 | G3: H2'22 | H3: H1'23 | I3: H2'23 | J3: H1'24 | K3: H2'24 | L3: H1'25 | M3: ='Revenue Model'!M2 -> H2'25 | N3: ='Revenue Model'!N2 -> H1'26 | O3: ='Revenue Model'!O2 -> H2'26 | P3: ='Revenue Model'!P2 -> H1'27 | Q3: ='Revenue Model'!Q2 -> H2'27 | R3: ='Revenue Model'!R2 -> H1'28 | S3: ='Revenue Model'!S2 -> H2'28 | T3: ='Revenue Model'!T2 -> H1'29 | ... W3: ='Revenue Model'!W2 -> H2'30 | AC3: FY22 | AD3: FY23 | AE3: FY24 | AF3: ='Revenue Model'!AF2 -> FY25 | AG3: ='Revenue Model'!AG2 -> FY26 | AH3: ='Revenue Model'!AH2 -> FY27 | AI3: ='Revenue Model'!AI2 -> FY28 | AJ3: ='Revenue Model'!AJ2 -> FY29 | AK3: ='Revenue Model'!AK2 -> FY30
B4: Sales | C4: 4985 | D4: =E4-C4 -> 3839 | E4: 8824 | F4: 5959 | G4: =AC4-F4 -> 4742 | H4: 7116 | I4: =AD4-H4 -> 5021 | J4: 6590 | K4: =AE4-J4 -> 5008 | L4: 6176 | M4: ='Revenue Model'!M41 -> 4993.14 | N4: ='Revenue Model'!N41 -> 5748.55 | O4: ='Revenue Model'!O41 -> 4978.8642 | P4: ='Revenue Model'!P41 -> 5308.2765 | Q4: ='Revenue Model'!Q41 -> 4964.1601 | R4: ='Revenue Model'!R41 -> 4854.7948 | S4: ='Revenue Model'!S41 -> 4949.0149 | T4: ='Revenue Model'!T41 -> 4387.7086 | ... W4: ='Revenue Model'!W41 -> 4917.3478 | AC4: 10701 | AD4: 12137 | AE4: 11598 | AF4: ='Revenue Model'!AF41 -> 11169.14 | AG4: ='Revenue Model'!AG41 -> 10727.414 | AH4: ='Revenue Model'!AH41 -> 10272.437 | AI4: ='Revenue Model'!AI41 -> 9803.8097 | AJ4: ='Revenue Model'!AJ41 -> 9321.124 | AK4: ='Revenue Model'!AK41 -> 8823.9577
B5: Cost of Sales | C5: 1964 | D5: =E5-C5 -> 1567 | E5: 3531 | F5: 2319 | G5: =AC5-F5 -> 1909 | H5: 2747 | I5: =AD5-H5 -> 2144 | J5: 2509 | K5: =AE5-J5 -> 2114 | L5: 2403 | M5: =M4-M6 -> 2084.5 | N5: =N4-N6 -> 2296.91 | O5: =O4-O6 -> 2052.9186 | P5: =P4-P6 -> 2190.8509 | Q5: =Q4-Q6 -> 2020.2167 | R5: =R4-R6 -> 2084.9522 | S5: =S4-S6 -> 1986.3538 | T5: =T4-T6 -> 1979.3523 | ... W5: =W4-W6 -> 1914.9751 | AC5: 4228 | AD5: 4891 | AE5: 4623 | AF5: =AF4-AF6 -> 4486.5 | AG5: =AG4-AG6 -> 4348.8286 | AH5: =AH4-AH6 -> 4210.0676 | AI5: =AI4-AI6 -> 4070.3059 | AJ5: =AJ4-AJ6 -> 3929.6401 | AK5: =AK4-AK6 -> 3788.1744
B6: Gross Profit | C6: =C4-C5 -> 3021 | D6: =D4-D5 -> 2272 | E6: =E4-E5 -> 5293 | F6: =F4-F5 -> 3640 | G6: =G4-G5 -> 2833 | H6: =H4-H5 -> 4369 | I6: =I4-I5 -> 2877 | J6: =J4-J5 -> 4081 | ... L6: =L4-L5 -> 3773 | M6: ='Gross Margin'!M41 -> 2908.64 | N6: ='Gross Margin'!N41 -> 3451.64 | O6: ='Gross Margin'!O41 -> 2925.9456 | P6: ='Gross Margin'!P41 -> 3117.4256 | Q6: ='Gross Margin'!Q41 -> 2943.9434 | R6: ='Gross Margin'!R41 -> 2769.8426 | S6: ='Gross Margin'!S41 -> 2962.6612 | T6: ='Gross Margin'!T41 -> 2408.3563 | ... W6: ='Gross Margin'!W41 -> 3002.3727 | AC6: =AC4-AC5 -> 6473 | AD6: =AD4-AD5 -> 7246 | AE6: =AE4-AE5 -> 6975 | AF6: ='Gross Margin'!AF41 -> 6682.64 | AG6: ='Gross Margin'!AG41 -> 6378.5856 | AH6: ='Gross Margin'!AH41 -> 6062.369 | AI6: ='Gross Margin'!AI41 -> 5733.5038 | AJ6: ='Gross Margin'!AJ41 -> 5391.4839 | AK6: ='Gross Margin'!AK41 -> 5035.7833
B7: Gross Margin (%) | C7: =C6/C4 -> 0.60601805 | D7: =D6/D4 -> 0.59182079 | E7: =E6/E4 -> 0.59984134 | F7: =F6/F4 -> 0.61084075 | G7: =G6/G4 -> 0.59742725 | H7: =H6/H4 -> 0.61396852 | I7: =I6/I4 -> 0.57299343 | J7: =J6/J4 -> 0.61927162 | ... W7: =W6/W4 -> 0.61056749 | AC7: =AC6/AC4 -> 0.60489674 | AD7: =AD6/AD4 -> 0.59701738 | AE7: =AE6/AE4 -> 0.60139679 | AF7: =AF6/AF4 -> 0.59831285 | AG7: =AG6/AG4 -> 0.59460607 | AH7: =AH6/AH4 -> 0.59015881 | AI7: =AI6/AI4 -> 0.58482406 | AJ7: =AJ6/AJ4 -> 0.57841564 | AK7: =AK6/AK4 -> 0.5706944
B8: Advertising & Promotions | C8: 706 | D8: =E8-C8 -> 687 | E8: 1393 | F8: 840 | G8: =AC8-F8 -> 858 | H8: 994 | I8: =AD8-H8 -> 945 | J8: 980 | K8: =AE8-J8 -> 892 | L8: 857 | M8: =-'Advertisment & promotional spen'!M41 -> 839.29 | N8: =-'Advertisment & promotional spen'!N41 -> 727.46 | O8: =-'Advertisment & promotional spen'!O41 -> 778.6103 | P8: =-'Advertisment & promotional spen'!P41 -> 587.7822 | Q8: =-'Advertisment & promotional spen'!Q41 -> 713.68302 | R8: =-'Advertisment & promotional spen'!R41 -> 438.32695 | S8: =-'Advertisment & promotional spen'!S41 -> 644.21083 | T8: =-'Advertisment & promotional spen'!T41 -> 278.40984 | ... W8: =-'Advertisment & promotional spen'!W41 -> 490.33688 | AC8: 1698 | AD8: 1939 | AE8: 1872 | AF8: =-'Advertisment & promotional spen'!AF41 -> 1697.29 | AG8: =-'Advertisment & promotional spen'!AG41 -> 1506.0703 | AH8: =-'Advertisment & promotional spen'!AH41 -> 1301.4652 | AI8: =-'Advertisment & promotional spen'!AI41 -> 1082.5378 | AJ8: =-'Advertisment & promotional spen'!AJ41 -> 848.28543 | AK8: =-'Advertisment & promotional spen'!AK41 -> 597.63541
B9: A&P / Sales | C9: =C8/C4 -> 0.14162487 | D9: =D8/D4 -> 0.17895285 | E9: =E8/E4 -> 0.15786491 | F9: =F8/F4 -> 0.14096325 | G9: =G8/G4 -> 0.18093631 | H9: =H8/H4 -> 0.13968522 | I9: =I8/I4 -> 0.18820952 | J9: =J8/J4 -> 0.14871017 | ... W9: =W8/W4 -> 0.09971572 | AC9: =AC8/AC4 -> 0.15867676 | AD9: =AD8/AD4 -> 0.15975941 | AE9: =AE8/AE4 -> 0.16140714 | AF9: =AF8/AF4 -> 0.15196246 | AG9: =AG8/AG4 -> 0.14039453 | AH9: =AH8/AH4 -> 0.12669489 | AI9: =AI8/AI4 -> 0.11042011 | AJ9: =AJ8/AJ4 -> 0.091006775 | AK9: =AK8/AK4 -> 0.067728726
B10: Contribution after advertising and promotion expenses | C10: =C6-C8 -> 2315 | D10: =D6-D8 -> 1585 | E10: =E6-E8 -> 3900 | F10: =F6-F8 -> 2800 | G10: =G6-G8 -> 1975 | H10: =H6-H8 -> 3375 | I10: =I6-I8 -> 1932 | J10: =J6-J8 -> 3101 | ... W10: =W6-W8 -> 2512.0358 | AC10: =AC6-AC8 -> 4775 | AD10: =AD6-AD8 -> 5307 | AE10: =AE6-AE8 -> 5103 | AF10: =AF6-AF8 -> 4985.35 | AG10: =AG6-AG8 -> 4872.5153 | AH10: =AH6-AH8 -> 4760.9038 | AI10: =AI6-AI8 -> 4650.966 | AJ10: =AJ6-AJ8 -> 4543.1985 | AK10: =AK6-AK8 -> 4438.1479
B11: Structure Costs | C11: =721-C13 -> 542 | D11: =E11-C11 -> 568 | E11: =1477-E13 -> 1110 | F11: =803-F13 -> 614 | G11: =AC11-F11 -> 746 | H11: =951-H13 -> 747 | I11: =AD11-H11 -> 745 | J11: =958-J13 -> 741 | K11: =AE11-J11 -> 311 | L11: =931-L13 -> 720 | M11: =AF11-L11 -> 955.371 | N11: =N12*N4-125 -> 737.2825 | O11: =AG11-N11 -> 621.82963 | P11: =P12*P4-125 -> 671.24147 | Q11: =AH11-P11 -> 619.62402 | R11: =R12*R4-125 -> 603.21922 | S11: =AI11-R11 -> 617.35224 | T11: =T12*T4-125 -> 533.1563 | U11: =AJ11-T11 -> 615.01231 | V11: =V12*V4-125 -> 460.99148 | W11: =AK11-V11 -> 612.60218 | AC11: =1751-AC13 -> 1360 | AD11: =1959-AD13 -> 1492 | AE11: =1987-AE13 -> 1052 | AF11: =AF12*AF4 -> 1675.371 | AG11: =AG12*AG4-250 -> 1359.1121 | AH11: =AH12*AH4-250 -> 1290.8655 | AI11: =AI12*AI4-250 -> 1220.5715 | AJ11: =AJ12*AJ4-250 -> 1148.1686 | AK11: =AK12*AK4-250 -> 1073.5937
B12: SG&A Margin (%) | C12: =C8/C4 -> 0.14162487 | D12: =D8/D4 -> 0.17895285 | E12: =E8/E4 -> 0.15786491 | F12: =F8/F4 -> 0.14096325 | G12: =G8/G4 -> 0.18093631 | H12: =H8/H4 -> 0.13968522 | I12: =I8/I4 -> 0.18820952 | J12: =J8/J4 -> 0.14871017 | ... M12: =M8/M4 -> 0.16808862 | N12: 0.15 | O12: =O8/O4 -> 0.15638312 | P12: 0.15 | Q12: =Q8/Q4 -> 0.14376712 | R12: 0.15 | S12: =S8/S4 -> 0.13016951 | T12: 0.15 | U12: =U8/U4 -> 0.1155134 | V12: 0.15 | W12: =W8/W4 -> 0.09971572 | AC12: =AC8/AC4 -> 0.15867676 | AD12: =AD8/AD4 -> 0.15975941 | AE12: =AE8/AE4 -> 0.16140714 | AF12: 0.15 | AG12: 0.15 | AH12: 0.15 | AI12: 0.15 | AJ12: 0.15 | AK12: 0.15
B13: D&A | C13: =Schedules!C9 -> 179 | D13: =E13-C13 -> 188 | E13: =Schedules!E9 -> 367 | F13: =Schedules!F9 -> 189 | G13: =AC13-F13 -> 202 | H13: =Schedules!H9 -> 204 | I13: =AD13-H13 -> 263 | J13: =Schedules!J9 -> 217 | K13: =AE13-J13 -> 718 | L13: 211 | M13: =Schedules!M9 -> 255.96 | N13: =Schedules!N9 -> 264.56947 | O13: =Schedules!O9 -> 281.46204 | P13: =Schedules!P9 -> 292.95384 | Q13: =Schedules!Q9 -> 305.63379 | R13: =Schedules!R9 -> 315.59147 | S13: =Schedules!S9 -> 324.32832 | T13: =Schedules!T9 -> 333.078 | ... W13: =Schedules!W9 -> 178.91354 | AC13: =Schedules!AC9 -> 391 | AD13: =Schedules!AD9 -> 467 | AE13: =Schedules!AE9 -> 935 | AF13: =Schedules!AF9 -> 466.96 | AG13: =Schedules!AG9 -> 546.03151 | AH13: =Schedules!AH9 -> 598.58763 | AI13: =Schedules!AI9 -> 639.91979 | AJ13: =Schedules!AJ9 -> 671.18126 | AK13: =Schedules!AK9 -> 351.88231
B14: Other operating income/expense | C14: 61 | D14: =E14-C14 -> 1 | E14: 62 | F14: 2 | G14: =AC14-F14 -> 60 | H14: -86 | I14: =AD14-H14 -> 169 | J14: -142 | K14: =AE14-J14 -> 534 | L14: 88 | AC14: 62 | AD14: 83 | AE14: 392 | AF14: =L14+M14 -> 88
B15: EBIT | C15: =C6-C8-C11-C13-C14+1 -> 1534 | D15: =D6-D8-D11-D13-D14 -> 828 | E15: =E6-E8-E11-E13-E14 -> 2361 | F15: =F6-F8-F11-F13-F14 -> 1995 | G15: =G6-G8-G11-G13-G14 -> 967 | H15: =H6-H8-H11-H13-H14-1 -> 2509 | I15: =I6-I8-I11-I13-I14 -> 755 | J15: =J6-J8-J11-J13-J14 -> 2285 | K15: =K6-K8-K11-K13-K14 -> 439 | L15: =L6-L8-L11-L13-L14 -> 1897 | M15: =M6-M8-M11-M13-M14 -> 858.019 | N15: =N6-N8-N11-N13-N14 -> 1722.328 | O15: =O6-O8-O11-O13-O14 -> 1244.0436 | P15: =P6-P8-P11-P13-P14 -> 1565.4481 | ... W15: =W6-W8-W11-W13-W14 -> 1720.5201 | AC15: =AC6-AC8-AC11-AC13-AC14 -> 2962 | AD15: =AD6-AD8-AD11-AD13-AD14 -> 3265 | AE15: =AE6-AE8-AE11-AE13-AE14 -> 2724 | AF15: =AF6-AF8-AF11-AF13-AF14 -> 2755.019 | AG15: =AG6-AG8-AG11-AG13-AG14 -> 2967.3717 | AH15: =AH6-AH8-AH11-AH13-AH14 -> 2871.4507 | AI15: =AI6-AI8-AI11-AI13-AI14 -> 2790.4748 | AJ15: =AJ6-AJ8-AJ11-AJ13-AJ14 -> 2723.8486 | AK15: =AK6-AK8-AK11-AK13-AK14 -> 3012.6719
B16: EBIT Margin (%) | C16: =C15/C4 -> 0.30772317 | D16: =D15/D4 -> 0.21568117 | E16: =E15/E4 -> 0.26756573 | F16: =F15/F4 -> 0.33478772 | G16: =G15/G4 -> 0.2039224 | H16: =H15/H4 -> 0.35258572 | I16: =I15/I4 -> 0.15036845 | J16: =J15/J4 -> 0.34673748 | ... W16: =W15/W4 -> 0.34988782 | AC16: =AC15/AC4 -> 0.27679656 | AD16: =AD15/AD4 -> 0.26901211 | AE16: =AE15/AE4 -> 0.23486808 | AF16: =AF15/AF4 -> 0.24666349 | AG16: =AG15/AG4 -> 0.27661574 | AH16: =AH15/AH4 -> 0.27952966 | AI16: =AI15/AI4 -> 0.28463167 | AJ16: =AJ15/AJ4 -> 0.29222319 | AK16: =AK15/AK4 -> 0.34141958
B17: Financial Expenses | C17: 265 | D17: =E17-C17 -> 145 | E17: 410 | F17: 154 | G17: =AC17-F17 -> 154 | H17: 163 | I17: =AD17-H17 -> 217 | J17: 249 | K17: =AE17-J17 -> 256 | L17: 287 | M17: =Schedules!M32 -> 173.56 | N17: =Schedules!N32 -> 300.35 | O17: =Schedules!O32 -> 200.21 | P17: =Schedules!P32 -> 325.35 | Q17: =Schedules!Q32 -> 215.21 | R17: =Schedules!R32 -> 350.35 | S17: =Schedules!S32 -> 230.21 | T17: =Schedules!T32 -> 375.35 | ... W17: =Schedules!W32 -> 260.21 | AC17: 308 | AD17: 380 | AE17: 505 | AF17: =Schedules!AF32 -> 460.56 | AG17: =Schedules!AG32 -> 500.56 | AH17: =Schedules!AH32 -> 540.56 | AI17: =Schedules!AI32 -> 580.56 | AJ17: =Schedules!AJ32 -> 620.56 | AK17: =Schedules!AK32 -> 660.56
B18: Financial Income | C18: 12 | D18: =E18-C18 -> 27 | E18: 39 | F18: 20 | G18: =AC18-F18 -> 28 | H18: 24 | I18: =AD18-H18 -> 29 | J18: 31 | K18: =AE18-J18 -> 37 | L18: 39 | AC18: 48 | AD18: 53 | AE18: 68 | AF18: =L18+M18 -> 39
B19: Other financial income/expenses | D19: =E19-C19 -> 0 | F19: 0 | G19: =AC19-F19 -> 0 | I19: =AD19-H19 -> 0 | K19: =AE19-J19 -> 0
B20: PBT | C20: =C15-C17+C18-C19 -> 1281 | D20: =D15-D17+D18-D19 -> 710 | E20: =E15-E17+E18-E19 -> 1990 | F20: =F15-F17+F18-F19 -> 1861 | G20: =G15-G17+G18-G19 -> 841 | H20: =H15-H17+H18-H19 -> 2370 | I20: =I15-I17+I18-I19 -> 567 | J20: =J15-J17+J18-J19 -> 2067 | ... W20: =W15-W17+W18-W19 -> 1460.3101 | AC20: =AC15-AC17+AC18-AC19 -> 2702 | AD20: =AD15-AD17+AD18-AD19 -> 2938 | AE20: =AE15-AE17+AE18-AE19 -> 2287 | AF20: =AF15-AF17+AF18-AF19 -> 2333.459 | AG20: =AG15-AG17+AG18-AG19 -> 2466.8117 | AH20: =AH15-AH17+AH18-AH19 -> 2330.8907 | AI20: =AI15-AI17+AI18-AI19 -> 2209.9148 | AJ20: =AJ15-AJ17+AJ18-AJ19 -> 2103.2886 | AK20: =AK15-AK17+AK18-AK19 -> 2352.1119
B21: PBT Margin (%) | C21: =C20/C4 -> 0.25697091 | D21: =D20/D4 -> 0.184944 | E21: =E20/E4 -> 0.22552131 | F21: =F20/F4 -> 0.31230072 | G21: =G20/G4 -> 0.17735133 | H21: =H20/H4 -> 0.33305228 | I21: =I20/I4 -> 0.11292571 | J21: =J20/J4 -> 0.31365706 | ... W21: =W20/W4 -> 0.29697108 | AC21: =AC20/AC4 -> 0.25249977 | AD21: =AD20/AD4 -> 0.2420697 | AE21: =AE20/AE4 -> 0.19718917 | AF21: =AF20/AF4 -> 0.2089202 | AG21: =AG20/AG4 -> 0.22995399 | AH21: =AH20/AH4 -> 0.22690728 | AI21: =AI20/AI4 -> 0.22541388 | AJ21: =AJ20/AJ4 -> 0.22564753 | AK21: =AK20/AK4 -> 0.26655974
B22: Income Tax | C22: 294 | D22: =E22-C22 -> 373 | E22: 667 | F22: 452 | G22: =AC22-F22 -> 224 | H22: 553 | I22: =AD22-H22 -> 98 | J22: 466 | K22: =AE22-J22 -> 300 | L22: 433 | M22: =AF22-L22 -> 103.69557 | N22: =N23*N20 -> 327.05495 | O22: =AG22-N22 -> 240.31174 | P22: =P23*P20 -> 285.22256 | Q22: =AH22-P22 -> 250.8823 | R22: =R23*R20 -> 159.35325 | S22: =AI22-R22 -> 172.13397 | T22: =T23*T20 -> 133.25433 | U22: =AJ22-T22 -> 182.23897 | V22: =V23*V20 -> 133.62027 | W22: =AK22-V22 -> 219.19652 | AC22: 676 | AD22: 651 | AE22: 766 | AF22: =AF23*AF20 -> 536.69557 | AG22: =AG23*AG20 -> 567.36668 | AH22: =AH23*AH20 -> 536.10486 | AI22: =AI23*AI20 -> 331.48721 | AJ22: =AJ23*AJ20 -> 315.4933 | AK22: =AK23*AK20 -> 352.81679
B23: Tax Rate (%) | C23: =C22/C20 -> 0.2295082 | D23: =D22/D20 -> 0.52535211 | E23: =E22/E20 -> 0.33517588 | F23: =F22/F20 -> 0.24288017 | G23: =G22/G20 -> 0.26634958 | H23: =H22/H20 -> 0.23333333 | I23: =I22/I20 -> 0.17283951 | J23: =J22/J20 -> 0.22544751 | ... M23: =M22/M20 -> 0.15150005 | N23: 0.23 | O23: =O22/O20 -> 0.23022034 | P23: 0.23 | Q23: =Q22/Q20 -> 0.23021105 | R23: 0.15 | S23: =S22/S20 -> 0.15013083 | T23: 0.15 | U23: =U22/U20 -> 0.15012357 | V23: 0.15 | W23: =W22/W20 -> 0.15010272 | AC23: =AC22/AC20 -> 0.25018505 | AD23: =AD22/AD20 -> 0.22157931 | AE23: =AE22/AE20 -> 0.3349366 | AF23: 0.23 | AG23: 0.23 | AH23: 0.23 | AI23: 0.15 | AJ23: 0.15 | AK23: 0.15
B24: Profit of associates | C24: -2 | D24: =E24-C24 -> -2 | E24: -4 | F24: 2 | G24: =AC24-F24 -> 3 | H24: -4 | I24: =AD24-H24 -> 0 | J24: -2 | K24: =AE24-J24 -> -5 | L24: -3 | AC24: 5 | AD24: -4 | AE24: -7 | AF24: =L24+M24 -> -3
B25: Net Profit before discounted | C25: =C27+C29 -> 1002 | D25: =D27+D29 -> 330 | E25: =E27+E29 -> 1331 | F25: =F27+F29 -> 1432 | G25: =G27+G29 -> 634 | H25: =H27+H29 -> 1834 | I25: =I27+I29 -> 469 | J25: =J27+J29 -> 1629 | ... W25: =W27+W29 -> 1241.1136 | AC25: =AC27+AC29 -> 2065 | AD25: =AD27+AD29 -> 2304 | AE25: =AE27+AE29 -> 1552 | AF25: =AF27+AF29 -> 1817.7634 | AG25: =AG27+AG29 -> 1899.445 | AH25: =AH27+AH29 -> 1794.7858 | AI25: =AI27+AI29 -> 1878.4275 | AJ25: =AJ27+AJ29 -> 1787.7953 | AK25: =AK27+AK29 -> 1999.2951
B26: Net profit/loss from discontinued | C26: 0 | D26: =E26-C26 -> 0 | F26: 0 | G26: =AC26-F26 -> 0 | H26: 0 | I26: =AD26-H26 -> 0 | J26: 0 | K26: =AE26-J26 -> 0 | AC26: 0 | AD26: 0 | AE26: 0
B27: Net profit/loss | C27: =C20-C22+C24-1 -> 984 | D27: =D20-D22+D24 -> 335 | E27: =E20-E22+E24-1 -> 1318 | F27: =F20-F22+F24 -> 1411 | G27: =G20-G22+G24 -> 620 | H27: =H20-H22+H24 -> 1813 | I27: =I20-I22+I24 -> 469 | J27: =J20-J22+J24 -> 1599 | K27: =K20-K22+K24 -> -85 | L27: =L20-L22+L24 -> 1213 | M27: =M20-M22+M24 -> 580.76343 | ... W27: =W20-W22+W24 -> 1241.1136 | AC27: =AC20-AC22+AC24-1 -> 2030 | AD27: =AD20-AD22+AD24 -> 2283 | AE27: =AE20-AE22+AE24 -> 1514 | AF27: =AF20-AF22+AF24 -> 1793.7634 | AG27: =AG20-AG22+AG24 -> 1899.445 | AH27: =AH20-AH22+AH24 -> 1794.7858 | AI27: =AI20-AI22+AI24 -> 1878.4275 | AJ27: =AJ20-AJ22+AJ24 -> 1787.7953 | AK27: =AK20-AK22+AK24 -> 1999.2951
B28: Net Profit Margin (%) | C28: =C27/C4 -> 0.19739218 | D28: =D27/D4 -> 0.087262308 | E28: =E27/E4 -> 0.14936537 | F28: =F27/F4 -> 0.2367847 | G28: =G27/G4 -> 0.13074652 | H28: =H27/H4 -> 0.25477797 | I28: =I27/I4 -> 0.093407688 | J28: =J27/J4 -> 0.24264036 | ... W28: =W27/W4 -> 0.25239492 | AC28: =AC27/AC4 -> 0.1897019 | AD28: =AD27/AD4 -> 0.1881025 | AE28: =AE27/AE4 -> 0.13053975 | AF28: =AF27/AF4 -> 0.16059996 | AG28: =AG27/AG4 -> 0.17706457 | AH28: =AH27/AH4 -> 0.17471861 | AI28: =AI27/AI4 -> 0.19160179 | AJ28: =AJ27/AJ4 -> 0.1918004 | AK28: =AK27/AK4 -> 0.22657578
B29: Non-controling interests | C29: 18 | D29: =E29-C29 -> -5 | E29: 13 | F29: 21 | G29: =AC29-F29 -> 14 | H29: 21 | I29: =AD29-H29 -> 0 | J29: 30 | K29: =AE29-J29 -> 8 | L29: 24 | AC29: 35 | AD29: 21 | AE29: 38 | AF29: =L29+M29 -> 24
B30: Net Profit attributable to parents | C30: =C27-C29 -> 966 | D30: =D27-D29 -> 340 | E30: =E27-E29 -> 1305 | F30: =F27-F29 -> 1390 | G30: =G27-G29 -> 606 | H30: =H27-H29 -> 1792 | I30: =I27-I29 -> 469 | J30: =J27-J29 -> 1569 | K30: =K27-K29 -> -93 | L30: =L27-L29+1 -> 1190 | M30: =M27-M29 -> 580.76343 | N30: =N27-N29 -> 1094.9231 | O30: =O27-O29 -> 803.5219 | P30: =P27-P29 -> 954.87552 | Q30: =Q27-Q29 -> 838.9103 | R30: =R27-R29 -> 903.00173 | S30: =S27-S29 -> 974.42581 | T30: =T27-T29 -> 755.10786 | ... W30: =W27-W29 -> 1241.1136 | AC30: =AC27-AC29 -> 1995 | AD30: =AD27-AD29 -> 2262 | AE30: =AE27-AE29 -> 1476 | AF30: =AF27-AF29 -> 1769.7634 | AG30: =AG27-AG29 -> 1899.445 | AH30: =AH27-AH29 -> 1794.7858 | AI30: =AI27-AI29 -> 1878.4275 | AJ30: =AJ27-AJ29 -> 1787.7953 | AK30: =AK27-AK29 -> 1999.2951
B32: EPS
B33: Basic | C33: =C30/C37*10 -> 3.7059595 | D33: =D30/D37*10 -> 1.3037006 | E33: =E30/E37*10 -> 5.0039096 | F33: =F30/F37*10 -> 5.341626 | G33: =G30/G37*10 -> 2.3394817 | H33: =H30/H37*10 -> 6.982656 | I33: =I30/I37*10 -> 1.8316858 | J33: =J30/J37*10 -> 6.2066689 | ... W33: =W30/W37*10 -> 4.9134413 | AC33: =AC30/AC37*10 -> 7.701759 | AD33: =AD30/AD37*10 -> 8.8342714 | AE33: =AE30/AE37*10 -> 5.8433325 | AF33: =AF30/AF37*10 -> 7.0063117 | AG33: =AG30/AG37*10 -> 7.5197077 | AH33: =AH30/AH37*10 -> 7.1053728 | AI33: =AI30/AI37*10 -> 7.4365018 | AJ33: =AJ30/AJ37*10 -> 7.0776982 | AK33: =AK30/AK37*10 -> 7.9150041
B34: Diluted | C34: =C30/C38*10 -> 3.6943885 | D34: =D30/D38*10 -> 1.3001221 | E34: =E30/E38*10 -> 4.9901744 | F34: =F30/F38*10 -> 5.3291566 | G34: =G30/G38*10 -> 2.333287 | H34: =H30/H38*10 -> 6.9627557 | I34: =I30/I38*10 -> 1.8257676 | J34: =J30/J38*10 -> 6.1920458 | ... W34: =W30/W38*10 -> 4.9019388 | AC34: =AC30/AC38*10 -> 7.6813657 | AD34: =AD30/AD38*10 -> 8.8057279 | AE34: =AE30/AE38*10 -> 5.8296531 | AF34: =AF30/AF38*10 -> 6.9899098 | AG34: =AG30/AG38*10 -> 7.5021039 | AH34: =AH30/AH38*10 -> 7.088739 | AI34: =AI30/AI38*10 -> 7.4190928 | AJ34: =AJ30/AJ38*10 -> 7.0611292 | AK34: =AK30/AK38*10 -> 7.896475
B36: No. of shares
B37: Basic | C37: 2606.6124 | D37: =E37 -> 2607.9608 | E37: 2607.9608 | F37: 2602.2039 | G37: =AC37 -> 2590.3173 | H37: 2566.3587 | I37: =AD37 -> 2560.4828 | J37: 2527.9261 | K37: =AE37 -> 2525.9559 | L37: 2514.7245 | M37: =L37 -> 2514.7245 | N37: =AF37 -> 2525.9559 | O37: =N37 -> 2525.9559 | P37: =AG37 -> 2525.9559 | Q37: =P37 -> 2525.9559 | R37: =AH37 -> 2525.9559 | S37: =R37 -> 2525.9559 | T37: =AI37 -> 2525.9559 | U37: =T37 -> 2525.9559 | V37: =AJ37 -> 2525.9559 | W37: =V37 -> 2525.9559 | AC37: 2590.3173 | AD37: 2560.4828 | AE37: 2525.9559 | AF37: =AE37 -> 2525.9559 | AG37: =AF37 -> 2525.9559 | AH37: =AG37 -> 2525.9559 | AI37: =AH37 -> 2525.9559 | AJ37: =AI37 -> 2525.9559 | AK37: =AJ37 -> 2525.9559
B38: Diluted | C38: 2614.7764 | D38: =E38 -> 2615.139 | E38: 2615.139 | F38: 2608.2926 | G38: =AC38 -> 2597.1944 | H38: 2573.6936 | I38: =AD38 -> 2568.7825 | J38: 2533.896 | K38: =AE38 -> 2531.8831 | L38: 2519.1773 | M38: =L38 -> 2519.1773 | N38: =AF38 -> 2531.8831 | O38: =N38 -> 2531.8831 | P38: =AG38 -> 2531.8831 | Q38: =P38 -> 2531.8831 | R38: =AH38 -> 2531.8831 | S38: =R38 -> 2531.8831 | T38: =AI38 -> 2531.8831 | U38: =T38 -> 2531.8831 | V38: =AJ38 -> 2531.8831 | W38: =V38 -> 2531.8831 | AC38: 2597.1944 | AD38: 2568.7825 | AE38: 2531.8831 | AF38: =AE38 -> 2531.8831 | AG38: =AF38 -> 2531.8831 | AH38: =AG38 -> 2531.8831 | AI38: =AH38 -> 2531.8831 | AJ38: =AI38 -> 2531.8831 | AK38: =AJ38 -> 2531.8831
B40: Dividend per share | AE40: High dividend yield but not favourable because it is due to fall in stock price
C41: 1.48 | E41: 1.33 | F41: 1.79 | H41: 2.56 | J41: 2.64 | L41: 2.35 | AC41: 1.56 | AD41: 2.06 | AE41: 2.35
B44: Balance Sheet | C44: =C3 -> H1'21 | D44: =D3 -> H2'21 | E44: =E3 -> FY21 | F44: =F3 -> H1'22 | G44: =G3 -> H2'22 | H44: =H3 -> H1'23 | I44: =I3 -> H2'23 | J44: =J3 -> H1'24 | ... L44: =L3 -> H1'25 | M44: H2'25 | N44: H1'26 | O44: H2'26 | P44: H1'27 | Q44: H2'27 | R44: H1'28 | S44: H2'28 | T44: H1'29 | U44: H2'29 | V44: H1'30 | W44: H2'30 | AC44: =AC3 -> FY22 | AD44: =AD3 -> FY23 | AE44: =AE3 -> FY24 | AF44: FY25 | AG44: FY26 | AH44: FY27 | AI44: FY28 | AJ44: FY29 | AK44: FY30
B45: Intangibles | C45: 10552 | D45: =E45 -> 10725 | E45: 10725 | F45: 11038 | G45: =AC45 -> 11512 | H45: 11313 | I45: =AD45 -> 12250 | J45: 12119 | K45: =AE45 -> 12234 | L45: 12403 | M45: =L45 -> 12403 | N45: =AF45 -> 12403 | O45: =N45 -> 12403 | P45: =AG45 -> 12403 | Q45: =P45 -> 12403 | R45: =AH45 -> 12403 | S45: =R45 -> 12403 | T45: =AI45 -> 12403 | U45: =T45 -> 12403 | V45: =AJ45 -> 12403 | W45: =V45 -> 12403 | AC45: 11512 | AD45: 12250 | AE45: 12234 | AF45: =M45 -> 12403 | AG45: =O45 -> 12403 | AH45: =Q45 -> 12403 | AI45: =S45 -> 12403 | AJ45: =U45 -> 12403 | AK45: =W45 -> 12403
B46: Goodwill | C46: 5401 | D46: =E46 -> 5505 | E46: 5505 | F46: 5819 | G46: =AC46 -> 6145 | H46: 6993 | I46: =AD46 -> 6750 | J46: 6756 | K46: =AE46 -> 6806 | L46: 6927 | M46: =L46 -> 6927 | N46: =AF46 -> 6927 | O46: =N46 -> 6927 | P46: =AG46 -> 6927 | Q46: =P46 -> 6927 | R46: =AH46 -> 6927 | S46: =R46 -> 6927 | T46: =AI46 -> 6927 | U46: =T46 -> 6927 | V46: =AJ46 -> 6927 | W46: =V46 -> 6927 | AC46: 6145 | AD46: 6750 | AE46: 6806 | AF46: =M46 -> 6927 | AG46: =O46 -> 6927 | AH46: =Q46 -> 6927 | AI46: =S46 -> 6927 | AJ46: =U46 -> 6927 | AK46: =W46 -> 6927
B47: PP&E | C47: 3051 | D47: =E47 -> 3177 | E47: 3177 | F47: 3232 | G47: =AC47 -> 3591 | H47: 3614 | I47: =AD47 -> 3901 | J47: 4065 | K47: =AE47 -> 3982 | L47: 4266 | M47: =Schedules!M11 -> 4409.4912 | N47: =Schedules!N11 -> 4691.034 | O47: =Schedules!O11 -> 4882.564 | P47: =Schedules!P11 -> 5093.8965 | Q47: =Schedules!Q11 -> 5259.8579 | R47: =Schedules!R11 -> 5405.4719 | S47: =Schedules!S11 -> 5551.3 | T47: =Schedules!T11 -> 5635.0543 | ... W47: =Schedules!W11 -> 6252.0192 | AC47: 3591 | AD47: 3901 | AE47: 3982 | AF47: =Schedules!AF11 -> 4409.4912 | AG47: =Schedules!AG11 -> 4882.564 | AH47: =Schedules!AH11 -> 5259.8579 | AI47: =Schedules!AI11 -> 5551.3 | AJ47: =Schedules!AJ11 -> 5765.6255 | AK47: =Schedules!AK11 -> 6252.0192
B48: Non-current financial Assets | C48: 695 | D48: =E48 -> 685 | E48: 685 | F48: 669 | G48: =AC48 -> 761 | H48: 757 | I48: =AD48 -> 855 | J48: 889 | K48: =AE48 -> 932 | L48: 996 | M48: =L48 -> 996 | N48: =AF48 -> 996 | O48: =N48 -> 996 | P48: =AG48 -> 996 | Q48: =P48 -> 996 | R48: =AH48 -> 996 | S48: =R48 -> 996 | T48: =AI48 -> 996 | U48: =T48 -> 996 | V48: =AJ48 -> 996 | W48: =V48 -> 996 | AC48: 761 | AD48: 855 | AE48: 932 | AF48: =M48 -> 996 | AG48: =O48 -> 996 | AH48: =Q48 -> 996 | AI48: =S48 -> 996 | AJ48: =U48 -> 996 | AK48: =W48 -> 996
B49: Investment in associates | C49: 38 | D49: =E49 -> 36 | E49: 36 | F49: 217 | G49: =AC49 -> 243 | H49: 40 | I49: =AD49 -> 37 | J49: 65 | K49: =AE49 -> 58 | L49: 73 | M49: =L49 -> 73 | N49: =AF49 -> 73 | O49: =N49 -> 73 | P49: =AG49 -> 73 | Q49: =P49 -> 73 | R49: =AH49 -> 73 | S49: =R49 -> 73 | T49: =AI49 -> 73 | U49: =T49 -> 73 | V49: =AJ49 -> 73 | W49: =V49 -> 73 | AC49: 243 | AD49: 37 | AE49: 58 | AF49: =M49 -> 73 | AG49: =O49 -> 73 | AH49: =Q49 -> 73 | AI49: =S49 -> 73 | AJ49: =U49 -> 73 | AK49: =W49 -> 73
B50: Non-current derivative instruments | C50: 83 | D50: =E50 -> 65 | E50: 65 | F50: 28 | G50: =AC50 -> 4 | H50: 5 | I50: =AD50 -> 5 | J50: 7 | K50: =AE50 -> 0 | L50: 0 | M50: =L50 -> 0 | N50: =AF50 -> 0 | O50: =N50 -> 0 | P50: =AG50 -> 0 | Q50: =P50 -> 0 | R50: =AH50 -> 0 | S50: =R50 -> 0 | T50: =AI50 -> 0 | U50: =T50 -> 0 | V50: =AJ50 -> 0 | W50: =V50 -> 0 | AC50: 4 | AD50: 5 | AE50: 0 | AF50: =M50 -> 0 | AG50: =O50 -> 0 | AH50: =Q50 -> 0 | AI50: =S50 -> 0 | AJ50: =U50 -> 0 | AK50: =W50 -> 0
B51: Deferred Tax Assets | C51: 1578 | D51: =E51 -> 1623 | E51: 1623 | F51: 1687 | G51: =AC51 -> 1844 | H51: 1767 | I51: =AD51 -> 1870 | J51: 1851 | K51: =AE51 -> 1713 | L51: 1684 | M51: =L51 -> 1684 | N51: =AF51 -> 1684 | O51: =N51 -> 1684 | P51: =AG51 -> 1684 | Q51: =P51 -> 1684 | R51: =AH51 -> 1684 | S51: =R51 -> 1684 | T51: =AI51 -> 1684 | U51: =T51 -> 1684 | V51: =AJ51 -> 1684 | W51: =V51 -> 1684 | AC51: 1844 | AD51: 1870 | AE51: 1713 | AF51: =M51 -> 1684 | AG51: =O51 -> 1684 | AH51: =Q51 -> 1684 | AI51: =S51 -> 1684 | AJ51: =U51 -> 1684 | AK51: =W51 -> 1684
B52: Non-current Assets | C52: =SUM(C45:C51) -> 21398 | D52: =SUM(D45:D51) -> 21816 | E52: =SUM(E45:E51) -> 21816 | F52: =SUM(F45:F51) -> 22690 | G52: =SUM(G45:G51) -> 24100 | H52: =SUM(H45:H51) -> 24489 | I52: =SUM(I45:I51)-1 -> 25667 | J52: =SUM(J45:J51)+2 -> 25754 | K52: =SUM(K45:K51)-1 -> 25724 | L52: =SUM(L45:L51) -> 26349 | M52: =SUM(M45:M51) -> 26492.491 | N52: =SUM(N45:N51) -> 26774.034 | O52: =SUM(O45:O51) -> 26965.564 | P52: =SUM(P45:P51) -> 27176.896 | Q52: =SUM(Q45:Q51) -> 27342.858 | R52: =SUM(R45:R51) -> 27488.472 | S52: =SUM(S45:S51) -> 27634.3 | ... W52: =SUM(W45:W51) -> 28335.019 | AC52: =SUM(AC45:AC51) -> 24100 | AD52: =SUM(AD45:AD51)-1 -> 25667 | AE52: =SUM(AE45:AE51)-1 -> 25724 | AF52: =SUM(AF45:AF51) -> 26492.491 | AG52: =SUM(AG45:AG51) -> 26965.564 | AH52: =SUM(AH45:AH51) -> 27342.858 | AI52: =SUM(AI45:AI51) -> 27634.3 | AJ52: =SUM(AJ45:AJ51) -> 27848.626 | AK52: =SUM(AK45:AK51) -> 28335.019
B54: Inventories | C54: 6139 | D54: =E54 -> 6555 | E54: 6555 | F54: 6694 | G54: =AC54 -> 7369 | H54: 7567 | I54: =AD54 -> 8104 | J54: 8252 | K54: =AE54 -> 8255 | L54: 8423 | M54: =Schedules!$K$18 -> 8255 | N54: =Schedules!$K$18 -> 8255 | O54: =Schedules!$K$18 -> 8255 | P54: =Schedules!$K$18 -> 8255 | Q54: =Schedules!$K$18 -> 8255 | R54: =Schedules!$K$18 -> 8255 | S54: =Schedules!$K$18 -> 8255 | T54: =Schedules!$K$18 -> 8255 | ... W54: =Schedules!$K$18 -> 8255 | AC54: 7369 | AD54: 8104 | AE54: 8255 | AF54: =Schedules!$K$18 -> 8255 | AG54: =Schedules!$K$18 -> 8255 | AH54: =Schedules!$K$18 -> 8255 | AI54: =Schedules!$K$18 -> 8255 | AJ54: =Schedules!$K$18 -> 8255 | AK54: =Schedules!$K$18 -> 8255
B55: Trade and other receivables | C55: 1829 | D55: =E55 -> 1126 | E55: 1126 | F55: 2233 | G55: =AC55 -> 1388 | H55: 2469 | I55: =AD55 -> 1814 | J55: 2458 | K55: =AE55 -> 1581 | L55: 2203 | M55: =Schedules!$K$19 -> 1581 | N55: =Schedules!$K$19 -> 1581 | O55: =Schedules!$K$19 -> 1581 | P55: =Schedules!$K$19 -> 1581 | Q55: =Schedules!$K$19 -> 1581 | R55: =Schedules!$K$19 -> 1581 | S55: =Schedules!$K$19 -> 1581 | T55: =Schedules!$K$19 -> 1581 | ... W55: =Schedules!$K$19 -> 1581 | AC55: 1388 | AD55: 1814 | AE55: 1581 | AF55: =Schedules!$K$19 -> 1581 | AG55: =Schedules!$K$19 -> 1581 | AH55: =Schedules!$K$19 -> 1581 | AI55: =Schedules!$K$19 -> 1581 | AJ55: =Schedules!$K$19 -> 1581 | AK55: =Schedules!$K$19 -> 1581
B56: Income tax receivables | C56: 133 | D56: =E56 -> 141 | E56: 141 | F56: 77 | G56: =AC56 -> 145 | H56: 97 | I56: =AD56 -> 31 | J56: 110 | K56: =AE56 -> 122 | L56: 97 | M56: =L56 -> 97 | N56: =AF56 -> 97 | O56: =N56 -> 97 | P56: =AG56 -> 97 | Q56: =P56 -> 97 | R56: =AH56 -> 97 | S56: =R56 -> 97 | T56: =AI56 -> 97 | U56: =T56 -> 97 | V56: =AJ56 -> 97 | W56: =V56 -> 97 | AC56: 145 | AD56: 31 | AE56: 122 | AF56: =M56 -> 97 | AG56: =O56 -> 97 | AH56: =Q56 -> 97 | AI56: =S56 -> 97 | AJ56: =U56 -> 97 | AK56: =W56 -> 97
B57: Other current assets | C57: 299 | D57: =E57 -> 413 | E57: 413 | F57: 353 | G57: =AC57 -> 435 | H57: 448 | I57: =AD57 -> 435 | J57: 456 | K57: =AE57 -> 416 | L57: 420 | M57: =L57 -> 420 | N57: =AF57 -> 420 | O57: =N57 -> 420 | P57: =AG57 -> 420 | Q57: =P57 -> 420 | R57: =AH57 -> 420 | S57: =R57 -> 420 | T57: =AI57 -> 420 | U57: =T57 -> 420 | V57: =AJ57 -> 420 | W57: =V57 -> 420 | AC57: 435 | AD57: 435 | AE57: 416 | AF57: =M57 -> 420 | AG57: =O57 -> 420 | AH57: =Q57 -> 420 | AI57: =S57 -> 420 | AJ57: =U57 -> 420 | AK57: =W57 -> 420
B58: Derivatives | C58: 9 | D58: =E58 -> 8 | E58: 8 | F58: 26 | G58: =AC58 -> 32 | H58: 10 | I58: =AD58 -> 15 | J58: 9 | K58: =AE58 -> 8 | L58: 19 | M58: =L58 -> 19 | N58: =AF58 -> 19 | O58: =N58 -> 19 | P58: =AG58 -> 19 | Q58: =P58 -> 19 | R58: =AH58 -> 19 | S58: =R58 -> 19 | T58: =AI58 -> 19 | U58: =T58 -> 19 | V58: =AJ58 -> 19 | W58: =V58 -> 19 | AC58: 32 | AD58: 15 | AE58: 8 | AF58: =M58 -> 19 | AG58: =O58 -> 19 | AH58: =Q58 -> 19 | AI58: =S58 -> 19 | AJ58: =U58 -> 19 | AK58: =W58 -> 19
B59: Cash and cash equivalents | C59: 1955 | D59: =E59 -> 2078 | E59: 2078 | F59: 1997 | G59: =AC59 -> 2527 | H59: 1796 | I59: =AD59 -> 1609 | J59: 1639 | K59: =AE59 -> 2683 | L59: 1916 | M59: =M143 -> 3846.2722 | N59: =N143 -> 5159.6525 | O59: =O143 -> 6271.6444 | P59: =P143 -> 7516.1875 | Q59: =Q143 -> 8689.1363 | R59: =R143 -> 9946.524 | S59: =S143 -> 11275.122 | T59: =T143 -> 12446.475 | ... W59: =W143 -> 16359.493 | AC59: 2527 | AD59: 1609 | AE59: 2683 | AF59: =AF143 -> 3846.2722 | AG59: =AG143 -> 6272.6444 | AH59: =AH143 -> 8689.1363 | AI59: =AI143 -> 11275.122 | AJ59: =AJ143 -> 13847.592 | AK59: =AK143 -> 16359.493
B60: Current Assets | C60: =SUM(C54:C59)-1 -> 10363 | D60: =SUM(D54:D59) -> 10321 | E60: =SUM(E54:E59) -> 10321 | F60: =SUM(F54:F59) -> 11380 | G60: =SUM(G54:G59) -> 11896 | H60: =SUM(H54:H59)-1 -> 12386 | I60: =SUM(I54:I59) -> 12008 | J60: =SUM(J54:J59)-1 -> 12923 | K60: =SUM(K54:K59) -> 13065 | L60: =SUM(L54:L59) -> 13078 | M60: =SUM(M54:M59) -> 14218.272 | N60: =SUM(N54:N59) -> 15531.653 | O60: =SUM(O54:O59) -> 16643.644 | P60: =SUM(P54:P59) -> 17888.187 | Q60: =SUM(Q54:Q59) -> 19061.136 | R60: =SUM(R54:R59) -> 20318.524 | ... W60: =SUM(W54:W59) -> 26731.493 | AC60: =SUM(AC54:AC59) -> 11896 | AD60: =SUM(AD54:AD59) -> 12008 | AE60: =SUM(AE54:AE59) -> 13065 | AF60: =SUM(AF54:AF59) -> 14218.272 | AG60: =SUM(AG54:AG59) -> 16644.644 | AH60: =SUM(AH54:AH59) -> 19061.136 | AI60: =SUM(AI54:AI59) -> 21647.122 | AJ60: =SUM(AJ54:AJ59) -> 24219.592 | AK60: =SUM(AK54:AK59) -> 26731.493
B61: Assets held for sale | C61: 11 | D61: =E61 -> 11 | E61: 11 | F61: 0 | G61: =AC61 -> 15 | H61: 1 | I61: =AD61 -> 1 | J61: 60 | K61: =AE61 -> 395 | L61: 367 | M61: =L61 -> 367 | N61: =AF61 -> 367 | O61: =N61 -> 367 | P61: =AG61 -> 367 | Q61: =P61 -> 367 | R61: =AH61 -> 367 | S61: =R61 -> 367 | T61: =AI61 -> 367 | U61: =T61 -> 367 | V61: =AJ61 -> 367 | W61: =V61 -> 367 | AC61: 15 | AD61: 1 | AE61: 395 | AF61: =M61 -> 367 | AG61: =O61 -> 367 | AH61: =Q61 -> 367 | AI61: =S61 -> 367 | AJ61: =U61 -> 367 | AK61: =W61 -> 367
B62: Total Assets | C62: =C61+C52+C60 -> 31772 | D62: =D61+D52+D60-1 -> 32147 | E62: =E61+E52+E60-1 -> 32147 | F62: =F61+F52+F60 -> 34070 | G62: =G61+G52+G60+1 -> 36012 | H62: =H61+H52+H60-1 -> 36875 | I62: =I61+I52+I60 -> 37676 | J62: =J61+J52+J60 -> 38737 | K62: =K61+K52+K60+1 -> 39185 | L62: =L61+L52+L60+1 -> 39795 | M62: =M61+M52+M60 -> 41077.763 | N62: =N61+N52+N60 -> 42672.687 | O62: =O61+O52+O60 -> 43976.208 | P62: =P61+P52+P60 -> 45432.084 | Q62: =Q61+Q52+Q60 -> 46770.994 | R62: =R61+R52+R60 -> 48173.996 | S62: =S61+S52+S60 -> 49648.422 | T62: =T61+T52+T60 -> 50903.53 | ... W62: =W61+W52+W60 -> 55433.512 | AC62: =AC61+AC52+AC60+1 -> 36012 | AD62: =AD61+AD52+AD60 -> 37676 | AE62: =AE61+AE52+AE60+1 -> 39185 | AF62: =AF61+AF52+AF60 -> 41077.763 | AG62: =AG61+AG52+AG60-1 -> 43976.208 | AH62: =AH61+AH52+AH60 -> 46770.994 | AI62: =AI61+AI52+AI60 -> 49648.422 | AJ62: =AJ61+AJ52+AJ60 -> 52435.217 | AK62: =AK61+AK52+AK60 -> 55433.512
B64: Share Capital | C64: 406 | D64: =E64 -> 406 | E64: 406 | F64: 406 | G64: =AC64 -> 400 | H64: 400 | I64: =AD64 -> 396 | J64: 396 | K64: =AE64 -> 393 | L64: 391 | M64: =L64 -> 391 | N64: =AF64 -> 391 | O64: =N64 -> 391 | P64: =AG64 -> 391 | Q64: =P64 -> 391 | R64: =AH64 -> 391 | S64: =R64 -> 391 | T64: =AI64 -> 391 | U64: =T64 -> 391 | V64: =AJ64 -> 391 | W64: =V64 -> 391 | AC64: 400 | AD64: 396 | AE64: 393 | AF64: =M64 -> 391 | AG64: =O64 -> 391 | AH64: =Q64 -> 391 | AI64: =S64 -> 391 | AJ64: =U64 -> 391 | AK64: =W64 -> 391
B65: Share Premium | C65: 3052 | D65: =E65 -> 3052 | E65: 3052 | F65: 3052 | G65: =AC65 -> 3052 | H65: 3052 | I65: =AD65 -> 3052 | J65: 3052 | K65: =AE65 -> 3052 | L65: 3052 | M65: =L65 -> 3052 | N65: =AF65 -> 3052 | O65: =N65 -> 3052 | P65: =AG65 -> 3052 | Q65: =P65 -> 3052 | R65: =AH65 -> 3052 | S65: =R65 -> 3052 | T65: =AI65 -> 3052 | U65: =T65 -> 3052 | V65: =AJ65 -> 3052 | W65: =V65 -> 3052 | AC65: 3052 | AD65: 3052 | AE65: 3052 | AF65: =M65 -> 3052 | AG65: =O65 -> 3052 | AH65: =Q65 -> 3052 | AI65: =S65 -> 3052 | AJ65: =U65 -> 3052 | AK65: =W65 -> 3052
B66: Retained Earnings | C66: 10011 | D66: =E66 -> 10066 | E66: 10066 | F66: 10909 | G66: =AC66 -> 10496 | H66: 11170 | I66: =AD66 -> 10006 | J66: 11178 | K66: =AE66 -> 10828 | L66: 11911 | M66: =L66 -> 11911 | N66: =AF66 -> 11911 | O66: =N66 -> 11911 | P66: =AG66 -> 11911 | Q66: =P66 -> 11911 | R66: =AH66 -> 11911 | S66: =R66 -> 11911 | T66: =AI66 -> 11911 | U66: =T66 -> 11911 | V66: =AJ66 -> 11911 | W66: =V66 -> 11911 | AC66: 10496 | AD66: 10006 | AE66: 10828 | AF66: =M66 -> 11911 | AG66: =O66 -> 11911 | AH66: =Q66 -> 11911 | AI66: =S66 -> 11911 | AJ66: =U66 -> 11911 | AK66: =W66 -> 11911
B67: Group share of net profit | C67: 966 | D67: =E67 -> 1305 | E67: 1305 | F67: 1390 | G67: =AC67 -> 1996 | H67: 1793 | I67: =AD67 -> 2262 | J67: 1569 | K67: =AE67 -> 1476 | L67: 1190 | M67: =L67+M30 -> 1770.7634 | N67: =AF67+N30 -> 2865.6865 | O67: =N67+O30 -> 3669.2084 | P67: =AG67+P30 -> 4624.0839 | Q67: =P67+Q30 -> 5462.9942 | R67: =AH67+R30 -> 6365.996 | S67: =R67+S30 -> 7340.4218 | T67: =AI67+T30 -> 8095.5296 | U67: =T67+U30 -> 9127.2171 | V67: =AJ67+V30 -> 9884.3986 | W67: =V67+W30 -> 11125.512 | AC67: 1996 | AD67: 2262 | AE67: 1476 | AF67: =M67 -> 1770.7634 | AG67: =O67 -> 3669.2084 | AH67: =Q67 -> 5462.9942 | AI67: =S67 -> 7340.4218 | AJ67: =U67 -> 9127.2171 | AK67: =W67 -> 11125.512
B68: Equity - parents | C68: =SUM(C64:C67) -> 14435 | D68: =SUM(D64:D67) -> 14829 | E68: =SUM(E64:E67) -> 14829 | F68: =SUM(F64:F67) -> 15757 | G68: =SUM(G64:G67) -> 15944 | H68: =SUM(H64:H67) -> 16415 | I68: =SUM(I64:I67) -> 15716 | J68: =SUM(J64:J67)-2 -> 16193 | K68: =SUM(K64:K67) -> 15749 | L68: =SUM(L64:L67) -> 16544 | M68: =SUM(M64:M67) -> 17124.763 | N68: =SUM(N64:N67) -> 18219.687 | O68: =SUM(O64:O67) -> 19023.208 | P68: =SUM(P64:P67) -> 19978.084 | Q68: =SUM(Q64:Q67) -> 20816.994 | R68: =SUM(R64:R67) -> 21719.996 | ... W68: =SUM(W64:W67) -> 26479.512 | AC68: =SUM(AC64:AC67) -> 15944 | AD68: =SUM(AD64:AD67) -> 15716 | AE68: =SUM(AE64:AE67) -> 15749 | AF68: =SUM(AF64:AF67) -> 17124.763 | AG68: =SUM(AG64:AG67) -> 19023.208 | AH68: =SUM(AH64:AH67) -> 20816.994 | AI68: =SUM(AI64:AI67) -> 22694.422 | AJ68: =SUM(AJ64:AJ67) -> 24481.217 | AK68: =SUM(AK64:AK67) -> 26479.512
B69: Non-controliing interests | C69: 244 | D69: =E69 -> 246 | E69: 246 | F69: 265 | G69: =AC69 -> 309 | H69: 343 | I69: =AD69 -> 998 | J69: 1016 | K69: =AE69 -> 1048 | L69: 1089 | M69: =L69 -> 1089 | N69: =AF69 -> 1089 | O69: =N69 -> 1089 | P69: =AG69 -> 1089 | Q69: =P69 -> 1089 | R69: =AH69 -> 1089 | S69: =R69 -> 1089 | T69: =AI69 -> 1089 | U69: =T69 -> 1089 | V69: =AJ69 -> 1089 | W69: =V69 -> 1089 | AC69: 309 | AD69: 998 | AE69: 1048 | AF69: =M69 -> 1089 | AG69: =O69 -> 1089 | AH69: =Q69 -> 1089 | AI69: =S69 -> 1089 | AJ69: =U69 -> 1089 | AK69: =W69 -> 1089
B70: Equity | C70: =C68+C69 -> 14679 | D70: =D68+D69 -> 15075 | E70: =E68+E69 -> 15075 | F70: =F68+F69 -> 16022 | G70: =G68+G69 -> 16253 | H70: =H68+H69 -> 16758 | I70: =I68+I69+1 -> 16715 | J70: =J68+J69 -> 17209 | K70: =K68+K69 -> 16797 | L70: =L68+L69-1 -> 17632 | M70: =M68+M69 -> 18213.763 | N70: =N68+N69 -> 19308.687 | O70: =O68+O69 -> 20112.208 | P70: =P68+P69 -> 21067.084 | Q70: =Q68+Q69 -> 21905.994 | R70: =R68+R69 -> 22808.996 | S70: =S68+S69 -> 23783.422 | T70: =T68+T69 -> 24538.53 | ... W70: =W68+W69 -> 27568.512 | AC70: =AC68+AC69 -> 16253 | AD70: =AD68+AD69+1 -> 16715 | AE70: =AE68+AE69 -> 16797 | AF70: =AF68+AF69 -> 18213.763 | AG70: =AG68+AG69 -> 20112.208 | AH70: =AH68+AH69 -> 21905.994 | AI70: =AI68+AI69 -> 23783.422 | AJ70: =AJ68+AJ69 -> 25570.217 | AK70: =AK68+AK69 -> 27568.512
B72: Long-term provisions | C72: 308 | D72: =E72 -> 253 | E72: 253 | F72: 266 | G72: =AC72 -> 318 | H72: 294 | I72: =AD72 -> 294 | J72: 299 | K72: =AE72 -> 313 | L72: 316 | M72: =L72 -> 316 | N72: =AF72 -> 316 | O72: =N72 -> 316 | P72: =AG72 -> 316 | Q72: =P72 -> 316 | R72: =AH72 -> 316 | S72: =R72 -> 316 | T72: =AI72 -> 316 | U72: =T72 -> 316 | V72: =AJ72 -> 316 | W72: =V72 -> 316 | AC72: 318 | AD72: 294 | AE72: 313 | AF72: =M72 -> 316 | AG72: =O72 -> 316 | AH72: =Q72 -> 316 | AI72: =S72 -> 316 | AJ72: =U72 -> 316 | AK72: =W72 -> 316
B73: Provision for employee benefits | C73: 550 | D73: =E73 -> 477 | E73: 477 | F73: 435 | G73: =AC73 -> 361 | H73: 374 | I73: =AD73 -> 349 | J73: 395 | K73: =AE73 -> 277 | L73: 261 | M73: =L73 -> 261 | N73: =AF73 -> 261 | O73: =N73 -> 261 | P73: =AG73 -> 261 | Q73: =P73 -> 261 | R73: =AH73 -> 261 | S73: =R73 -> 261 | T73: =AI73 -> 261 | U73: =T73 -> 261 | V73: =AJ73 -> 261 | W73: =V73 -> 261 | AC73: 361 | AD73: 349 | AE73: 277 | AF73: =M73 -> 261 | AG73: =O73 -> 261 | AH73: =Q73 -> 261 | AI73: =S73 -> 261 | AJ73: =U73 -> 261 | AK73: =W73 -> 261
B74: Deferred Tax liabilities | C74: 2566 | D74: =E74 -> 2825 | E74: 2825 | F74: 2949 | G74: =AC74 -> 3139 | H74: 3134 | I74: =AD74 -> 3134 | J74: 3192 | K74: =AE74 -> 3153 | L74: 3232 | M74: =L74 -> 3232 | N74: =AF74 -> 3232 | O74: =N74 -> 3232 | P74: =AG74 -> 3232 | Q74: =P74 -> 3232 | R74: =AH74 -> 3232 | S74: =R74 -> 3232 | T74: =AI74 -> 3232 | U74: =T74 -> 3232 | V74: =AJ74 -> 3232 | W74: =V74 -> 3232 | AC74: 3139 | AD74: 3134 | AE74: 3153 | AF74: =M74 -> 3232 | AG74: =O74 -> 3232 | AH74: =Q74 -> 3232 | AI74: =S74 -> 3232 | AJ74: =U74 -> 3232 | AK74: =W74 -> 3232
B75: Bonds - non-current | C75: 8680 | D75: =E75 -> 8787 | E75: 8787 | F75: 8236 | G75: =AC75 -> 9238 | H75: 9732 | I75: =AD75 -> 9678 | J75: 10318 | K75: =AE75 -> 10907 | L75: 11014 | M75: =Schedules!M31 -> 11514 | N75: =Schedules!N31 -> 12014 | O75: =Schedules!O31 -> 12514 | P75: =Schedules!P31 -> 13014 | Q75: =Schedules!Q31 -> 13514 | R75: =Schedules!R31 -> 14014 | S75: =Schedules!S31 -> 14514 | T75: =Schedules!T31 -> 15014 | ... W75: =Schedules!W31 -> 16514 | AC75: 9238 | AD75: 9678 | AE75: 10907 | AF75: =Schedules!AF31 -> 11514 | AG75: =Schedules!AG31 -> 12514 | AH75: =Schedules!AH31 -> 13514 | AI75: =Schedules!AI31 -> 14514 | AJ75: =Schedules!AJ31 -> 15514 | AK75: =Schedules!AK31 -> 16514
B76: Non-current lease liabilities | C76: 409 | D76: =E76 -> 405 | E76: 405 | F76: 402 | G76: =AC76 -> 400 | H76: 390 | I76: =AD76 -> 384 | J76: 396 | K76: =AE76 -> 352 | L76: 391 | M76: =L76 -> 391 | N76: =AF76 -> 391 | O76: =N76 -> 391 | P76: =AG76 -> 391 | Q76: =P76 -> 391 | R76: =AH76 -> 391 | S76: =R76 -> 391 | T76: =AI76 -> 391 | U76: =T76 -> 391 | V76: =AJ76 -> 391 | W76: =V76 -> 391 | AC76: 400 | AD76: 384 | AE76: 352 | AF76: =M76 -> 391 | AG76: =O76 -> 391 | AH76: =Q76 -> 391 | AI76: =S76 -> 391 | AJ76: =U76 -> 391 | AK76: =W76 -> 391
B77: Other non-current financial liabilities | C77: 82 | D77: =E77 -> 108 | E77: 108 | F77: 94 | G77: =AC77 -> 179 | H77: 207 | I77: =AD77 -> 173 | J77: 128 | K77: =AE77 -> 133 | L77: 135 | M77: =L77 -> 135 | N77: =AF77 -> 135 | O77: =N77 -> 135 | P77: =AG77 -> 135 | Q77: =P77 -> 135 | R77: =AH77 -> 135 | S77: =R77 -> 135 | T77: =AI77 -> 135 | U77: =T77 -> 135 | V77: =AJ77 -> 135 | W77: =V77 -> 135 | AC77: 179 | AD77: 173 | AE77: 133 | AF77: =M77 -> 135 | AG77: =O77 -> 135 | AH77: =Q77 -> 135 | AI77: =S77 -> 135 | AJ77: =U77 -> 135 | AK77: =W77 -> 135
B78: Non-current derivative instruments | C78: 0 | D78: =E78 -> 0 | E78: 0 | F78: 3 | G78: =AC78 -> 18 | H78: 22 | I78: =AD78 -> 14 | J78: 10 | K78: =AE78 -> 11 | L78: 8 | M78: =L78 -> 8 | N78: =AF78 -> 8 | O78: =N78 -> 8 | P78: =AG78 -> 8 | Q78: =P78 -> 8 | R78: =AH78 -> 8 | S78: =R78 -> 8 | T78: =AI78 -> 8 | U78: =T78 -> 8 | V78: =AJ78 -> 8 | W78: =V78 -> 8 | AC78: 18 | AD78: 14 | AE78: 11 | AF78: =M78 -> 8 | AG78: =O78 -> 8 | AH78: =Q78 -> 8 | AI78: =S78 -> 8 | AJ78: =U78 -> 8 | AK78: =W78 -> 8
B79: Non-Current Liabilities | C79: =SUM(C72:C78) -> 12595 | D79: =SUM(D72:D78)-1 -> 12854 | E79: =SUM(E72:E78)-1 -> 12854 | F79: =SUM(F72:F78) -> 12385 | G79: =SUM(G72:G78) -> 13653 | H79: =SUM(H72:H78) -> 14153 | I79: =SUM(I72:I78) -> 14026 | J79: =SUM(J72:J78) -> 14738 | K79: =SUM(K72:K78) -> 15146 | L79: =SUM(L72:L78)+1 -> 15358 | M79: =SUM(M72:M78) -> 15857 | N79: =SUM(N72:N78) -> 16357 | O79: =SUM(O72:O78) -> 16857 | P79: =SUM(P72:P78) -> 17357 | Q79: =SUM(Q72:Q78) -> 17857 | R79: =SUM(R72:R78) -> 18357 | S79: =SUM(S72:S78) -> 18857 | T79: =SUM(T72:T78) -> 19357 | ... W79: =SUM(W72:W78) -> 20857 | AC79: =SUM(AC72:AC78) -> 13653 | AD79: =SUM(AD72:AD78) -> 14026 | AE79: =SUM(AE72:AE78) -> 15146 | AF79: =SUM(AF72:AF78) -> 15857 | AG79: =SUM(AG72:AG78) -> 16857 | AH79: =SUM(AH72:AH78) -> 17857 | AI79: =SUM(AI72:AI78) -> 18857 | AJ79: =SUM(AJ72:AJ78) -> 19857 | AK79: =SUM(AK72:AK78) -> 20857
B81: Short-term provisions | C81: 187 | D81: =E81 -> 163 | E81: 163 | F81: 151 | G81: =AC81 -> 150 | H81: 135 | I81: =AD81 -> 164 | J81: 148 | K81: =AE81 -> 158 | L81: 149 | M81: =L81 -> 149 | N81: =AF81 -> 149 | O81: =N81 -> 149 | P81: =AG81 -> 149 | Q81: =P81 -> 149 | R81: =AH81 -> 149 | S81: =R81 -> 149 | T81: =AI81 -> 149 | U81: =T81 -> 149 | V81: =AJ81 -> 149 | W81: =V81 -> 149 | AC81: 150 | AD81: 164 | AE81: 158 | AF81: =M81 -> 149 | AG81: =O81 -> 149 | AH81: =Q81 -> 149 | AI81: =S81 -> 149 | AJ81: =U81 -> 149 | AK81: =W81 -> 149
B82: Trade and Other payables | C82: 2345 | D82: =E82 -> 2337 | E82: 2337 | F82: 2976 | G82: =AC82 -> 3019 | H82: 3222 | I82: =AD82 -> 3461 | J82: 3068 | K82: =AE82 -> 2930 | L82: 2727 | M82: =Schedules!$K$20 -> 2930 | N82: =Schedules!$K$20 -> 2930 | O82: =Schedules!$K$20 -> 2930 | P82: =Schedules!$K$20 -> 2930 | Q82: =Schedules!$K$20 -> 2930 | R82: =Schedules!$K$20 -> 2930 | S82: =Schedules!$K$20 -> 2930 | T82: =Schedules!$K$20 -> 2930 | ... W82: =Schedules!$K$20 -> 2930 | AC82: 3019 | AD82: 3461 | AE82: 2930 | AF82: =Schedules!$K$20 -> 2930 | AG82: =Schedules!$K$20 -> 2930 | AH82: =Schedules!$K$20 -> 2930 | AI82: =Schedules!$K$20 -> 2930 | AJ82: =Schedules!$K$20 -> 2930 | AK82: =Schedules!$K$20 -> 2930
B83: Income Tax payables | C83: 349 | D83: =E83 -> 282 | E83: 282 | F83: 423 | G83: =AC83 -> 263 | H83: 391 | I83: =AD83 -> 113 | J83: 320 | K83: =AE83 -> 149 | L83: 280 | M83: =L83 -> 280 | N83: =AF83 -> 280 | O83: =N83 -> 280 | P83: =AG83 -> 280 | Q83: =P83 -> 280 | R83: =AH83 -> 280 | S83: =R83 -> 280 | T83: =AI83 -> 280 | U83: =T83 -> 280 | V83: =AJ83 -> 280 | W83: =V83 -> 280 | AC83: 263 | AD83: 113 | AE83: 149 | AF83: =M83 -> 280 | AG83: =O83 -> 280 | AH83: =Q83 -> 280 | AI83: =S83 -> 280 | AJ83: =U83 -> 280 | AK83: =W83 -> 280
B84: Other current liabilities | C84: 753 | D84: =E84 -> 1134 | E84: 1134 | F84: 886 | G84: =AC84 -> 1311 | H84: 971 | I84: =AD84 -> 1556 | J84: 1041 | K84: =AE84 -> 1607 | L84: 1039 | M84: =L84 -> 1039 | N84: =AF84 -> 1039 | O84: =N84 -> 1039 | P84: =AG84 -> 1039 | Q84: =P84 -> 1039 | R84: =AH84 -> 1039 | S84: =R84 -> 1039 | T84: =AI84 -> 1039 | U84: =T84 -> 1039 | V84: =AJ84 -> 1039 | W84: =V84 -> 1039 | AC84: 1311 | AD84: 1556 | AE84: 1607 | AF84: =M84 -> 1039 | AG84: =O84 -> 1039 | AH84: =Q84 -> 1039 | AI84: =S84 -> 1039 | AJ84: =U84 -> 1039 | AK84: =W84 -> 1039
B85: Bonds - current | C85: 237 | D85: =E85 -> 70 | E85: 70 | F85: 785 | G85: =AC85 -> 842 | H85: 575 | I85: =AD85 -> 580 | J85: 739 | K85: =AE85 -> 1778 | L85: 1110 | M85: =L85 -> 1110 | N85: =AF85 -> 1110 | O85: =N85 -> 1110 | P85: =AG85 -> 1110 | Q85: =P85 -> 1110 | R85: =AH85 -> 1110 | S85: =R85 -> 1110 | T85: =AI85 -> 1110 | U85: =T85 -> 1110 | V85: =AJ85 -> 1110 | W85: =V85 -> 1110 | AC85: 842 | AD85: 580 | AE85: 1778 | AF85: =M85 -> 1110 | AG85: =O85 -> 1110 | AH85: =Q85 -> 1110 | AI85: =S85 -> 1110 | AJ85: =U85 -> 1110 | AK85: =W85 -> 1110
B86: Current lease liabilities | C86: 103 | D86: =E86 -> 103 | E86: 103 | F86: 105 | G86: =AC86 -> 107 | H86: 100 | I86: =AD86 -> 99 | J86: 97 | K86: =AE86 -> 96 | L86: 96 | M86: =L86 -> 96 | N86: =AF86 -> 96 | O86: =N86 -> 96 | P86: =AG86 -> 96 | Q86: =P86 -> 96 | R86: =AH86 -> 96 | S86: =R86 -> 96 | T86: =AI86 -> 96 | U86: =T86 -> 96 | V86: =AJ86 -> 96 | W86: =V86 -> 96 | AC86: 107 | AD86: 99 | AE86: 96 | AF86: =M86 -> 96 | AG86: =O86 -> 96 | AH86: =Q86 -> 96 | AI86: =S86 -> 96 | AJ86: =U86 -> 96 | AK86: =W86 -> 96
B87: Other current financial liabilities | C87: 507 | D87: =E87 -> 122 | E87: 122 | F87: 333 | G87: =AC87 -> 406 | H87: 558 | I87: =AD87 -> 956 | J87: 1341 | K87: =AE87 -> 352 | L87: 1188 | M87: =L87 -> 1188 | N87: =AF87 -> 1188 | O87: =N87 -> 1188 | P87: =AG87 -> 1188 | Q87: =P87 -> 1188 | R87: =AH87 -> 1188 | S87: =R87 -> 1188 | T87: =AI87 -> 1188 | U87: =T87 -> 1188 | V87: =AJ87 -> 1188 | W87: =V87 -> 1188 | AC87: 406 | AD87: 956 | AE87: 352 | AF87: =M87 -> 1188 | AG87: =O87 -> 1188 | AH87: =Q87 -> 1188 | AI87: =S87 -> 1188 | AJ87: =U87 -> 1188 | AK87: =W87 -> 1188
B88: Derivatives | C88: 16 | D88: =E88 -> 6 | E88: 6 | F88: 4 | G88: =AC88 -> 9 | H88: 11 | I88: =AD88 -> 6 | J88: 17 | K88: =AE88 -> 21 | L88: 36 | M88: =L88 -> 36 | N88: =AF88 -> 36 | O88: =N88 -> 36 | P88: =AG88 -> 36 | Q88: =P88 -> 36 | R88: =AH88 -> 36 | S88: =R88 -> 36 | T88: =AI88 -> 36 | U88: =T88 -> 36 | V88: =AJ88 -> 36 | W88: =V88 -> 36 | AC88: 9 | AD88: 6 | AE88: 21 | AF88: =M88 -> 36 | AG88: =O88 -> 36 | AH88: =Q88 -> 36 | AI88: =S88 -> 36 | AJ88: =U88 -> 36 | AK88: =W88 -> 36
B89: Current Liabilities | C89: =SUM(C81:C88) -> 4497 | D89: =SUM(D81:D88)+1 -> 4218 | E89: =SUM(E81:E88)+1 -> 4218 | F89: =SUM(F81:F88) -> 5663 | G89: =SUM(G81:G88) -> 6107 | H89: =SUM(H81:H88)+1 -> 5964 | I89: =SUM(I81:I88) -> 6935 | J89: =SUM(J81:J88)+1 -> 6772 | K89: =SUM(K81:K88) -> 7091 | L89: =SUM(L81:L88) -> 6625 | M89: =SUM(M81:M88) -> 6828 | N89: =SUM(N81:N88) -> 6828 | O89: =SUM(O81:O88) -> 6828 | P89: =SUM(P81:P88) -> 6828 | Q89: =SUM(Q81:Q88) -> 6828 | R89: =SUM(R81:R88) -> 6828 | ... W89: =SUM(W81:W88) -> 6828 | AC89: =SUM(AC81:AC88) -> 6107 | AD89: =SUM(AD81:AD88) -> 6935 | AE89: =SUM(AE81:AE88) -> 7091 | AF89: =SUM(AF81:AF88) -> 6828 | AG89: =SUM(AG81:AG88) -> 6828 | AH89: =SUM(AH81:AH88) -> 6828 | AI89: =SUM(AI81:AI88) -> 6828 | AJ89: =SUM(AJ81:AJ88) -> 6828 | AK89: =SUM(AK81:AK88) -> 6828
B90: Liabilities held for sale | C90: 0 | D90: =E90 -> 0 | E90: 0 | F90: 0 | G90: =AC90 -> 0 | H90: 0 | I90: 0 | J90: 17 | K90: =AE90 -> 151 | L90: 180 | M90: =L90 -> 180 | N90: =AF90 -> 180 | O90: =N90 -> 180 | P90: =AG90 -> 180 | Q90: =P90 -> 180 | R90: =AH90 -> 180 | S90: =R90 -> 180 | T90: =AI90 -> 180 | U90: =T90 -> 180 | V90: =AJ90 -> 180 | W90: =V90 -> 180 | AC90: 0 | AD90: 0 | AE90: 151 | AF90: =M90 -> 180 | AG90: =O90 -> 180 | AH90: =Q90 -> 180 | AI90: =S90 -> 180 | AJ90: =U90 -> 180 | AK90: =W90 -> 180
B91: Total Equity & Liabilities | C91: =C70+C79+C89+1 -> 31772 | D91: =D70+D79+D89 -> 32147 | E91: =E70+E79+E89+E90 -> 32147 | F91: =F70+F79+F89 -> 34070 | G91: =G70+G79+G89-1 -> 36012 | H91: =H70+H79+H89 -> 36875 | I91: =I70+I79+I89 -> 37676 | J91: =J70+J79+J89+J90+1 -> 38737 | K91: =K70+K79+K89+K90 -> 39185 | L91: =L70+L79+L89+L90 -> 39795 | M91: =M70+M79+M89+M90-1 -> 41077.763 | N91: =N70+N79+N89+N90-1 -> 42672.687 | O91: =O70+O79+O89+O90-1 -> 43976.208 | P91: =P70+P79+P89+P90 -> 45432.084 | Q91: =Q70+Q79+Q89+Q90 -> 46770.994 | R91: =R70+R79+R89+R90 -> 48173.996 | S91: =S70+S79+S89+S90 -> 49648.422 | T91: =T70+T79+T89+T90 -> 50903.53 | U91: =U70+U79+U89+U90 -> 52435.217 | V91: =V70+V79+V89+V90 -> 53692.399 | W91: =W70+W79+W89+W90 -> 55433.512 | AC91: =AC70+AC79+AC89-1 -> 36012 | AD91: =AD70+AD79+AD89 -> 37676 | AE91: =AE70+AE79+AE89+AE90 -> 39185 | AF91: =AF70+AF79+AF89+AF90-1 -> 41077.763 | AG91: =AG70+AG79+AG89+AG90-1 -> 43976.208 | AH91: =AH70+AH79+AH89+AH90 -> 46770.994 | AI91: =AI70+AI79+AI89+AI90 -> 49648.422 | AJ91: =AJ70+AJ79+AJ89+AJ90 -> 52435.217 | AK91: =AK70+AK79+AK89+AK90 -> 55433.512
B93: Check | C93: =IF(C62=C91,"OK",C62-C91) -> OK | D93: =IF(D62=D91,"OK",D62-D91) -> OK | E93: =IF(E62=E91,"OK",E62-E91) -> OK | F93: =IF(F62=F91,"OK",F62-F91) -> OK | G93: =IF(G62=G91,"OK",G62-G91) -> OK | H93: =IF(H62=H91,"OK",H62-H91) -> OK | I93: =IF(I62=I91,"OK",I62-I91) -> OK | J93: =IF(J62=J91,"OK",J62-J91) -> OK | ... W93: =IF(W62=W91,"OK",W62-W91) -> OK | AC93: =IF(AC62=AC91,"OK",AC62-AC91) -> OK | AD93: =IF(AD62=AD91,"OK",AD62-AD91) -> OK | AE93: =IF(AE62=AE91,"OK",AE62-AE91) -> OK | AF93: =IF(AF62=AF91,"OK",AF62-AF91) -> OK | AG93: =IF(AG62=AG91,"OK",AG62-AG91) -> OK | AH93: =IF(AH62=AH91,"OK",AH62-AH91) -> OK | AI93: =IF(AI62=AI91,"OK",AI62-AI91) -> OK | AJ93: =IF(AJ62=AJ91,"OK",AJ62-AJ91) -> OK | AK93: =IF(AK62=AK91,"OK",AK62-AK91) -> OK
B95: Cash Flow | C95: =C44 -> H1'21 | D95: =D44 -> H2'21 | E95: =E44 -> FY21 | F95: =F44 -> H1'22 | G95: =G44 -> H2'22 | H95: =H44 -> H1'23 | I95: =I44 -> H2'23 | J95: =J44 -> H1'24 | ... L95: =L44 -> H1'25 | M95: H2'25 | N95: H1'26 | O95: H2'26 | P95: H1'27 | Q95: H2'27 | R95: H1'28 | S95: H2'28 | T95: H1'29 | U95: H2'29 | V95: H1'30 | W95: H2'30 | AC95: =AC44 -> FY22 | AD95: =AD44 -> FY23 | AE95: =AE44 -> FY24 | AF95: FY25 | AG95: FY26 | AH95: FY27 | AI95: FY28 | AJ95: FY29 | AK95: FY30
B96: PAT | C96: 966 | D96: =E96-C96 -> 339 | E96: 1305 | F96: 1390 | G96: =AC96-F96 -> 606 | H96: 1792 | I96: =AD96-H96 -> 470 | J96: 1569 | K96: =AE96-J96 -> -93 | L96: 1190 | M96: =M30 -> 580.76343 | N96: =N30 -> 1094.9231 | O96: =O30 -> 803.5219 | P96: =P30 -> 954.87552 | Q96: =Q30 -> 838.9103 | R96: =R30 -> 903.00173 | S96: =S30 -> 974.42581 | T96: =T30 -> 755.10786 | ... W96: =W30 -> 1241.1136 | AC96: 1996 | AD96: 2262 | AE96: 1476 | AF96: =AF30+1 -> 1770.7634 | AG96: =AG30+1 -> 1900.445 | AH96: =AH30+1 -> 1795.7858 | AI96: =AI30+1 -> 1879.4275 | AJ96: =AJ30+1 -> 1788.7953 | AK96: =AK30+1 -> 2000.2951
B97: MI | C97: 18 | D97: =E97-C97 -> -5 | E97: 13 | F97: 21 | G97: =AC97-F97 -> 14 | H97: 21 | I97: =AD97-H97 -> 0 | J97: 30 | K97: =AE97-J97 -> 8 | L97: 24 | AC97: 35 | AD97: 21 | AE97: 38 | AF97: =L97+M97 -> 24
B98: Share of net profit/(loss) of associates, net of dividends received | C98: 2 | D98: =E98-C98 -> 2 | E98: 4 | F98: -2 | G98: =AC98-F98 -> -3 | H98: 4 | I98: =AD98-H98 -> 0 | J98: 2 | K98: =AE98-J98 -> 7 | L98: 3 | AC98: -5 | AD98: 4 | AE98: 9 | AF98: =L98+M98 -> 3
B99: Financial (income)/expenses | C99: 254 | D99: =E99-C99 -> 117 | E99: 371 | F99: 135 | G99: =AC99-F99 -> 125 | H99: 139 | I99: =AD99-H99 -> 188 | J99: 218 | K99: =AE99-J99 -> 219 | L99: 248 | AC99: 260 | AD99: 327 | AE99: 437 | AF99: =L99+M99 -> 248
B100: Tax (income)/expenses | C100: 294 | D100: =E100-C100 -> 373 | E100: 667 | F100: 452 | G100: =AC100-F100 -> 224 | H100: 553 | I100: =AD100-H100 -> 98 | J100: 466 | K100: =AE100-J100 -> 300 | L100: 433 | AC100: 676 | AD100: 651 | AE100: 766 | AF100: =L100+M100 -> 433
B101: Net profit from discontinued operations | C101: 0 | D101: =E101-C101 -> 0 | E101: 0 | F101: 0 | G101: =AC101-F101 -> 0 | H101: 0 | I101: =AD101-H101 -> 0 | K101: =AE101-J101 -> 0 | L101: 0 | AC101: 0 | AD101: 0 | AE101: 0 | AF101: =L101+M101 -> 0
B102: Depreciation of fixed assets | C102: 179 | D102: =E102-C102 -> 188 | E102: 367 | F102: 189 | G102: =AC102-F102 -> 192 | H102: 204 | I102: =AD102-H102 -> 213 | J102: 217 | K102: =AE102-J102 -> 224 | L102: 211 | M102: =M13 -> 255.96 | N102: =N13 -> 264.56947 | O102: =O13 -> 281.46204 | P102: =P13 -> 292.95384 | Q102: =Q13 -> 305.63379 | R102: =R13 -> 315.59147 | S102: =S13 -> 324.32832 | T102: =T13 -> 333.078 | ... W102: =W13 -> 178.91354 | AC102: 381 | AD102: 417 | AE102: 441 | AF102: =AF13 -> 466.96 | AG102: =AG13 -> 546.03151 | AH102: =AH13 -> 598.58763 | AI102: =AI13 -> 639.91979 | AJ102: =AJ13 -> 671.18126 | AK102: =AK13 -> 351.88231
B103: Net change in provisions | C103: -31 | D103: =E103-C103 -> -49 | E103: -80 | F103: -22 | G103: =AC103-F103 -> 29 | H103: -50 | I103: =AD103-H103 -> -24 | J103: -42 | K103: =AE103-J103 -> 5 | L103: -30 | AC103: 7 | AD103: -74 | AE103: -37 | AF103: =L103+M103 -> -30
B104: Net change in impairment of goodwill, property, plant and equipment and intangible assets | C104: 6 | D104: =E104-C104 -> 72 | E104: 78 | F104: 0 | G104: =AC104-F104 -> 10 | H104: 8 | I104: =AD104-H104 -> 44 | J104: 14 | K104: =AE104-J104 -> 481 | L104: 0 | AC104: 10 | AD104: 52 | AE104: 495 | AF104: =L104+M104 -> 0
B105: Changes in fair value of commercial derivatives | C105: -3 | D105: =E105-C105 -> 7 | E105: 4 | F105: -3 | G105: =AC105-F105 -> 5 | H105: -4 | I105: =AD105-H105 -> -3 | J105: 3 | K105: =AE105-J105 -> 2 | L105: 2 | AC105: 2 | AD105: -7 | AE105: 5 | AF105: =L105+M105 -> 2
B106: Changes in fair value of biological assets and investments | C106: -2 | D106: =E106-C106 -> -2 | E106: -4 | F106: 0 | G106: =AC106-F106 -> -4 | H106: -70 | I106: =AD106-H106 -> -10 | J106: 0 | K106: =AE106-J106 -> -5 | L106: 0 | AC106: -4 | AD106: -80 | AE106: -5 | AF106: =L106+M106 -> 0
B107: Dividends received | C107: 2 | D107: =E107-C107 -> -18 | E107: -16 | F107: -3 | G107: =AC107-F107 -> -2 | H107: -74 | I107: =AD107-H107 -> 0 | J107: -213 | K107: =AE107-J107 -> -79 | L107: -7 | AC107: -5 | AD107: -74 | AE107: -292 | AF107: =L107+M107 -> -7
B108: Share based payments | C108: 15 | D108: =E108-C108 -> 13 | E108: 28 | F108: 17 | G108: =AC108-F108 -> 23 | H108: 21 | I108: =AD108-H108 -> 23 | J108: 26 | K108: =AE108-J108 -> 19 | L108: 22 | AC108: 40 | AD108: 44 | AE108: 45 | AF108: =L108+M108 -> 22
B109: Self-financing capacity before financing interest and taxes | C109: =SUM(C96:C108)-1 -> 1699 | D109: =SUM(D96:D108)+1 -> 1038 | E109: =SUM(E96:E108)+1 -> 2738 | F109: =SUM(F96:F108)-1 -> 2173 | G109: =SUM(G96:G108)-1 -> 1218 | H109: =SUM(H96:H108) -> 2544 | I109: =SUM(I96:I108) -> 999 | J109: =SUM(J96:J108) -> 2290 | K109: =SUM(K96:K108) -> 1088 | L109: =SUM(L96:L108)-2 -> 2094 | M109: =SUM(M96:M108) -> 836.72343 | N109: =SUM(N96:N108) -> 1359.4926 | O109: =SUM(O96:O108) -> 1084.9839 | P109: =SUM(P96:P108) -> 1247.8294 | Q109: =SUM(Q96:Q108) -> 1144.5441 | R109: =SUM(R96:R108) -> 1218.5932 | S109: =SUM(S96:S108) -> 1298.7541 | T109: =SUM(T96:T108) -> 1088.1859 | ... W109: =SUM(W96:W108) -> 1420.0271 | AC109: =SUM(AC96:AC108)-1 -> 3392 | AD109: =SUM(AD96:AD108) -> 3543 | AE109: =SUM(AE96:AE108) -> 3378 | AF109: =SUM(AF96:AF108)-2 -> 2930.7234 | AG109: =SUM(AG96:AG108) -> 2446.4765 | AH109: =SUM(AH96:AH108) -> 2394.3735 | AI109: =SUM(AI96:AI108) -> 2519.3473 | AJ109: =SUM(AJ96:AJ108) -> 2459.9766 | AK109: =SUM(AK96:AK108) -> 2352.1774
B110: Changes in inventories | D110: =E110-C110 -> -305 | E110: -305 | F110: -27 | G110: =AC110-F110 -> -605 | H110: -261 | I110: =AD110-H110 -> -487 | J110: -209 | K110: =AE110-J110 -> -294 | L110: -69 | M110: =L54-M54 -> 168 | N110: =AF54-N54 -> 0 | O110: =N54-O54 -> 0 | P110: =AG54-P54 -> 0 | Q110: =P54-Q54 -> 0 | R110: =AH54-R54 -> 0 | S110: =R54-S54 -> 0 | T110: =AI54-T54 -> 0 | U110: =T54-U54 -> 0 | V110: =AJ54-V54 -> 0 | W110: =V54-W54 -> 0 | AC110: -632 | AD110: -748 | AE110: -503 | AF110: =L110+M110 -> 99 | AG110: =N54-AG54 -> 0 | AH110: =Q54-AH54 -> 0 | AI110: =S54-AI54 -> 0 | AJ110: =U54-AJ54 -> 0 | AK110: =W54-AK54 -> 0
B111: Changes in Trade Receivables | C111: -923 | D111: =E111-C111 -> 692 | E111: -231 | F111: -1047 | G111: =AC111-F111 -> 862 | H111: -1140 | I111: =AD111-H111 -> 641 | J111: -689 | K111: =AE111-J111 -> 892 | L111: -633 | M111: =L55-M55 -> 622 | N111: =AF55-N55 -> 0 | O111: =N55-O55 -> 0 | P111: =AG55-P55 -> 0 | Q111: =P55-Q55 -> 0 | R111: =AH55-R55 -> 0 | S111: =R55-S55 -> 0 | T111: =AI55-T55 -> 0 | U111: =T55-U55 -> 0 | V111: =AJ55-V55 -> 0 | W111: =V55-W55 -> 0 | AC111: -185 | AD111: -499 | AE111: 203 | AF111: =L111+M111 -> -11 | AG111: =N55-AG55 -> 0 | AH111: =Q55-AH55 -> 0 | AI111: =S55-AI55 -> 0 | AJ111: =U55-AJ55 -> 0 | AK111: =W55-AK55 -> 0
B112: Changes in Trade Payables | C112: 519 | D112: =E112-C112 -> -19 | E112: 500 | F112: 511 | G112: =AC112-F112 -> 39 | H112: 308 | I112: =AD112-H112 -> 303 | J112: -368 | K112: =AE112-J112 -> -156 | L112: -214 | M112: =M82-L82 -> 203 | N112: =N82-AF82 -> 0 | O112: =O82-N82 -> 0 | P112: =P82-AG82 -> 0 | Q112: =Q82-P82 -> 0 | R112: =R82-AH82 -> 0 | S112: =S82-R82 -> 0 | T112: =T82-AI82 -> 0 | U112: =U82-T82 -> 0 | V112: =V82-AJ82 -> 0 | W112: =W82-V82 -> 0 | AC112: 550 | AD112: 611 | AE112: -524 | AF112: =L112+M112 -> -11 | AG112: =AG82-N82 -> 0 | AH112: =AH82-Q82 -> 0 | AI112: =AI82-S82 -> 0 | AJ112: =AJ82-U82 -> 0 | AK112: =AK82-W82 -> 0
...

Sheet Schedules
B2: Schedules | C2: ='Financial Statements'!C44 -> H1'21 | D2: ='Financial Statements'!D44 -> H2'21 | E2: ='Financial Statements'!E44 -> FY21 | F2: ='Financial Statements'!F44 -> H1'22 | G2: ='Financial Statements'!G44 -> H2'22 | H2: ='Financial Statements'!H44 -> H1'23 | I2: ='Financial Statements'!I44 -> H2'23 | J2: ='Financial Statements'!J44 -> H1'24 | ... W2: ='Financial Statements'!W44 -> H2'30 | AC2: ='Financial Statements'!AC44 -> FY22 | AD2: ='Financial Statements'!AD44 -> FY23 | AE2: ='Financial Statements'!AE44 -> FY24 | AF2: ='Financial Statements'!AF44 -> FY25 | AG2: ='Financial Statements'!AG44 -> FY26 | AH2: ='Financial Statements'!AH44 -> FY27 | AI2: ='Financial Statements'!AI44 -> FY28 | AJ2: ='Financial Statements'!AJ44 -> FY29 | AK2: ='Financial Statements'!AK44 -> FY30
B3: PP&E | C3: 182.5 | D3: 182.5 | E3: =+C3+D3 -> 365 | F3: 182.5 | G3: 182.5 | H3: 182.5 | I3: 182.5 | J3: 183 | K3: 183 | L3: 182.5 | M3: 182.5 | N3: 182.5 | O3: 182.5 | P3: 182.5 | Q3: 182.5 | R3: 183 | S3: 183 | T3: 182.5 | U3: 182.5 | V3: 182.5 | W3: 182.5 | AC3: =+F3+G3 -> 365 | AD3: =+H3+I3 -> 365 | AE3: 366 | AF3: =+L3+M3 -> 365 | AG3: =+N3+O3 -> 365 | AH3: =+P3+Q3 -> 365 | AI3: =+R3+S3 -> 366 | AJ3: =+T3+U3 -> 365 | AK3: =+V3+W3 -> 365
B4: Opening Value | D4: =C11 -> 3051 | F4: =E11 -> 3177 | G4: =F11 -> 3232 | H4: =AC11 -> 3591 | I4: =H11 -> 3614 | J4: =AD11 -> 3901 | K4: =J11 -> 4065 | L4: =AE11 -> 3982 | M4: =L11 -> 4266 | N4: =AF11 -> 4409.4912 | O4: =N11 -> 4691.034 | P4: =AG11 -> 4882.564 | Q4: =P11 -> 5093.8965 | R4: =AH11 -> 5259.8579 | S4: =R11 -> 5405.4719 | T4: =AI11 -> 5551.3 | U4: =T11 -> 5635.0543 | V4: =AJ11 -> 5765.6255 | W4: =V11 -> 5963.7847 | AC4: =E11 -> 3177 | AD4: =AC11 -> 3591 | AE4: =AD11 -> 3901 | AF4: =AE11 -> 3982 | AG4: =AF11 -> 4409.4912 | AH4: =AG11 -> 4882.564 | AI4: =AH11 -> 5259.8579 | AJ4: =AI11 -> 5551.3 | AK4: =AJ11 -> 5765.6255
B5: Capex | C5: =-'Financial Statements'!C122 -> 174 | D5: =E5-C5 -> 259 | E5: =-'Financial Statements'!E122 -> 433 | F5: =-'Financial Statements'!F122 -> 177 | G5: =AC5-F5 -> 329 | H5: =-'Financial Statements'!H122 -> 268 | I5: =AD5-H5 -> 434 | J5: =-'Financial Statements'!J122 -> 393 | K5: =AE5-J5 -> 380 | L5: =-'Financial Statements'!L122 -> 370 | M5: =M6*'Financial Statements'!M4 -> 399.4512 | N5: =N6*'Financial Statements'!N4 -> 546.11225 | O5: =O6*'Financial Statements'!O4 -> 472.9921 | P5: =P6*'Financial Statements'!P4 -> 504.28627 | Q5: =Q6*'Financial Statements'!Q4 -> 471.59521 | R5: =R6*'Financial Statements'!R4 -> 461.20551 | S5: =S6*'Financial Statements'!S4 -> 470.15642 | T5: =T6*'Financial Statements'!T4 -> 416.83232 | ... W5: =W6*'Financial Statements'!W4 -> 467.14804 | AC5: =-'Financial Statements'!AC122 -> 506 | AD5: =-'Financial Statements'!AD122 -> 702 | AE5: =-'Financial Statements'!AE122 -> 773 | AF5: =SUM(L5:M5) -> 769.4512 | AG5: =SUM(N5:O5) -> 1019.1043 | AH5: =SUM(P5:Q5) -> 975.88148 | AI5: =SUM(R5:S5) -> 931.36192 | AJ5: =SUM(T5:U5) -> 885.50678 | AK5: =SUM(V5:W5) -> 838.27599
B6: Capex/sales Ratio | C6: =C5/'Financial Statements'!C4 -> 0.034904714 | D6: =D5/'Financial Statements'!D4 -> 0.067465486 | E6: =E5/'Financial Statements'!E4 -> 0.049070716 | F6: =F5/'Financial Statements'!F4 -> 0.02970297 | G6: =G5/'Financial Statements'!G4 -> 0.069380008 | H6: =H5/'Financial Statements'!H4 -> 0.037661608 | I6: =I5/'Financial Statements'!I4 -> 0.086436965 | J6: =J5/'Financial Statements'!J4 -> 0.059635812 | ... L6: =L5/'Financial Statements'!L4 -> 0.059909326 | M6: 0.08 | N6: 0.095 | O6: 0.095 | P6: 0.095 | Q6: 0.095 | R6: 0.095 | S6: 0.095 | T6: 0.095 | U6: 0.095 | V6: 0.095 | W6: 0.095 | AC6: =AC5/'Financial Statements'!AC4 -> 0.0472853 | AD6: =AD5/'Financial Statements'!AD4 -> 0.057839664 | AE6: =AE5/'Financial Statements'!AE4 -> 0.066649422 | AF6: =AF5/'Financial Statements'!AF4 -> 0.068890819 | AG6: =AG5/'Financial Statements'!AG4 -> 0.095 | AH6: =AH5/'Financial Statements'!AH4 -> 0.095 | AI6: =AI5/'Financial Statements'!AI4 -> 0.095 | AJ6: =AJ5/'Financial Statements'!AJ4 -> 0.095 | AK6: =AK5/'Financial Statements'!AK4 -> 0.095
B7: Disposals | C7: =C4+C5-C9-C11 -> -3056 | D7: =E7-C7 -> -55 | E7: =E4+E5-E9-E11 -> -3111 | F7: =F4+F5-F9-F11 -> -67 | G7: =AC7-F7 -> -232 | H7: =H4+H5-H9-H11 -> 41 | I7: =AD7-H7 -> -116 | J7: =J4+J5-J9-J11 -> 12 | K7: =AE7-J7 -> -255 | L7: =L4+L5-L9-L11 -> -125 | AC7: =AC4+AC5-AC9-AC11 -> -299 | AD7: =AD4+AD5-AD9-AD11 -> -75 | AE7: =AE4+AE5-AE9-AE11 -> -243 | AF7: =SUM(L7:M7) -> -125 | AG7: =SUM(N7:O7) -> 0 | AH7: =SUM(P7:Q7) -> 0 | AI7: =SUM(R7:S7) -> 0 | AJ7: =SUM(T7:U7) -> 0 | AK7: =SUM(V7:W7) -> 0
B8: Accumulated deprecation | D8: =E8 -> 0 | G8: =AC8 -> 0 | I8: =AD8 -> 0 | K8: =AE8 -> 0 | M8: =L8+M9 -> 255.96 | N8: =AF8+N9 -> 520.52947 | O8: =N8+O9 -> 801.99151 | P8: =AG8+P9 -> 1094.9454 | Q8: =P8+Q9 -> 1400.5791 | R8: =AH8+R9 -> 1716.1706 | S8: =R8+S9 -> 2040.4989 | T8: =AI8+T9 -> 2373.5769 | U8: =T8+U9 -> 2711.6802 | V8: =AJ8+V9 -> 2884.649 | W8: =V8+W9 -> 3063.5625 | AF8: =M8 -> 255.96 | AG8: =O8 -> 801.99151 | AH8: =Q8 -> 1400.5791 | AI8: =S8 -> 2040.4989 | AJ8: =U8 -> 2711.6802 | AK8: =W8 -> 3063.5625
B9: Depeciation charge for the year | C9: ='Financial Statements'!C102 -> 179 | D9: ='Financial Statements'!D102 -> 188 | E9: ='Financial Statements'!E102 -> 367 | F9: ='Financial Statements'!F102 -> 189 | G9: ='Financial Statements'!G102 -> 192 | H9: ='Financial Statements'!H102 -> 204 | I9: ='Financial Statements'!I102 -> 213 | J9: ='Financial Statements'!J102 -> 217 | ... L9: ='Financial Statements'!L102 -> 211 | M9: =M10*M4 -> 255.96 | N9: =N10*N4 -> 264.56947 | O9: =O10*O4 -> 281.46204 | P9: =P10*P4 -> 292.95384 | Q9: =Q10*Q4 -> 305.63379 | R9: =R10*R4 -> 315.59147 | S9: =S10*S4 -> 324.32832 | T9: =T10*T4 -> 333.078 | ... W9: =W10*W4 -> 178.91354 | AC9: 391 | AD9: 467 | AE9: 935 | AF9: =SUM(L9:M9) -> 466.96 | AG9: =SUM(N9:O9) -> 546.03151 | AH9: =SUM(P9:Q9) -> 598.58763 | AI9: =SUM(R9:S9) -> 639.91979 | AJ9: =SUM(T9:U9) -> 671.18126 | AK9: =SUM(V9:W9) -> 351.88231
B10: Depreciation rate (%) | C10: =C9/C4 -> #DIV/0! | D10: =D9/D4 -> 0.061619141 | E10: =E9/E4 -> #DIV/0! | F10: =F9/F4 -> 0.059490085 | G10: =G9/G4 -> 0.059405941 | H10: =H9/H4 -> 0.056808688 | I10: =I9/I4 -> 0.058937465 | J10: =J9/J4 -> 0.055626762 | ... L10: =L9/L4 -> 0.052988448 | M10: 0.06 | N10: 0.06 | O10: 0.06 | P10: 0.06 | Q10: 0.06 | R10: 0.06 | S10: 0.06 | T10: 0.06 | U10: 0.06 | V10: 0.03 | W10: 0.03 | AC10: =AC9/AC4 -> 0.12307208 | AD10: =AD9/AD4 -> 0.13004734 | AE10: =AE9/AE4 -> 0.23968213 | AF10: =AF9/AF4 -> 0.1172677 | AG10: =AG9/AG4 -> 0.12383096 | AH10: =AH9/AH4 -> 0.12259698 | AI10: =AI9/AI4 -> 0.12166104 | AJ10: =AJ9/AJ4 -> 0.12090524 | AK10: =AK9/AK4 -> 0.061031072
B11: Net Value | C11: ='Financial Statements'!C47 -> 3051 | D11: ='Financial Statements'!D47 -> 3177 | E11: ='Financial Statements'!E47 -> 3177 | F11: ='Financial Statements'!F47 -> 3232 | G11: ='Financial Statements'!G47 -> 3591 | H11: ='Financial Statements'!H47 -> 3614 | I11: ='Financial Statements'!I47 -> 3901 | J11: ='Financial Statements'!J47 -> 4065 | ... L11: ='Financial Statements'!L47 -> 4266 | M11: =M4+M5-M7-M9 -> 4409.4912 | N11: =N4+N5-N7-N9 -> 4691.034 | O11: =O4+O5-O7-O9 -> 4882.564 | P11: =P4+P5-P7-P9 -> 5093.8965 | Q11: =Q4+Q5-Q7-Q9 -> 5259.8579 | R11: =R4+R5-R7-R9 -> 5405.4719 | S11: =S4+S5-S7-S9 -> 5551.3 | T11: =T4+T5-T7-T9 -> 5635.0543 | ... W11: =W4+W5-W7-W9 -> 6252.0192 | AC11: ='Financial Statements'!AC47 -> 3591 | AD11: ='Financial Statements'!AD47 -> 3901 | AE11: ='Financial Statements'!AE47 -> 3982 | AF11: =AF4+AF5-AF7-AF9 -> 4409.4912 | AG11: =AG4+AG5-AG7-AG9 -> 4882.564 | AH11: =AH4+AH5-AH7-AH9 -> 5259.8579 | AI11: =AI4+AI5-AI7-AI9 -> 5551.3 | AJ11: =AJ4+AJ5-AJ7-AJ9 -> 5765.6255 | AK11: =AK4+AK5-AK7-AK9 -> 6252.0192
J12: =J4+J5-J7-J9 -> 4065 | L12: =L4+L5-L7-L9 -> 4266 | AD12: =AD4+AD5-AD7-AD9 -> 3901 | AE12: =AE4+AE5-AE7-AE9 -> 3982
B13: Working Capital
B14: No. of days | C14: 182.5 | D14: 182.5 | E14: 365 | F14: 182.5 | G14: 182.5 | H14: 182.5 | I14: 182.5 | J14: 183 | K14: 183 | L14: 182.5 | M14: 182.5 | N14: 182.5 | O14: 182.5 | P14: 182.5 | Q14: 182.5 | R14: 183 | S14: 183 | T14: 182.5 | U14: 182.5 | V14: 182.5 | W14: 182.5 | AC14: 365 | AD14: 365 | AE14: 366 | AF14: 365 | AG14: 365 | AH14: 365 | AI14: 366 | AJ14: 365 | AK14: 365
B15: Sales | C15: ='Financial Statements'!C4 -> 4985 | D15: ='Financial Statements'!D4 -> 3839 | E15: ='Financial Statements'!E4 -> 8824 | F15: ='Financial Statements'!F4 -> 5959 | G15: ='Financial Statements'!G4 -> 4742 | H15: ='Financial Statements'!H4 -> 7116 | I15: ='Financial Statements'!I4 -> 5021 | J15: ='Financial Statements'!J4 -> 6590 | ... W15: ='Financial Statements'!W4 -> 4917.3478 | AC15: ='Financial Statements'!AC4 -> 10701 | AD15: ='Financial Statements'!AD4 -> 12137 | AE15: ='Financial Statements'!AE4 -> 11598 | AF15: ='Financial Statements'!AF4 -> 11169.14 | AG15: ='Financial Statements'!AG4 -> 10727.414 | AH15: ='Financial Statements'!AH4 -> 10272.437 | AI15: ='Financial Statements'!AI4 -> 9803.8097 | AJ15: ='Financial Statements'!AJ4 -> 9321.124 | AK15: ='Financial Statements'!AK4 -> 8823.9577
B16: Cost of Sales | C16: ='Financial Statements'!C5 -> 1964 | D16: ='Financial Statements'!D5 -> 1567 | E16: ='Financial Statements'!E5 -> 3531 | F16: ='Financial Statements'!F5 -> 2319 | G16: ='Financial Statements'!G5 -> 1909 | H16: ='Financial Statements'!H5 -> 2747 | I16: ='Financial Statements'!I5 -> 2144 | J16: ='Financial Statements'!J5 -> 2509 | ... W16: ='Financial Statements'!W5 -> 1914.9751 | AC16: ='Financial Statements'!AC5 -> 4228 | AD16: ='Financial Statements'!AD5 -> 4891 | AE16: ='Financial Statements'!AE5 -> 4623 | AF16: ='Financial Statements'!AF5 -> 4486.5 | AG16: ='Financial Statements'!AG5 -> 4348.8286 | AH16: ='Financial Statements'!AH5 -> 4210.0676 | AI16: ='Financial Statements'!AI5 -> 4070.3059 | AJ16: ='Financial Statements'!AJ5 -> 3929.6401 | AK16: ='Financial Statements'!AK5 -> 3788.1744
B18: Inventories | C18: ='Financial Statements'!C54 -> 6139 | D18: ='Financial Statements'!D54 -> 6555 | E18: ='Financial Statements'!E54 -> 6555 | F18: ='Financial Statements'!F54 -> 6694 | G18: ='Financial Statements'!G54 -> 7369 | H18: ='Financial Statements'!H54 -> 7567 | I18: ='Financial Statements'!I54 -> 8104 | J18: ='Financial Statements'!J54 -> 8252 | ... L18: ='Financial Statements'!L54 -> 8423 | M18: =+AF18 -> 7375.0685 | N18: =N22*N16/N14 -> 7551.4849 | O18: =+AG18 -> 7148.7593 | P18: =P22*P16/P14 -> 7202.7975 | Q18: =+AH18 -> 6920.6591 | R18: =R22*R16/R14 -> 6835.9088 | S18: =+AI18 -> 6672.6327 | T18: =T22*T16/T14 -> 6507.4596 | U18: =+AJ18 -> 6459.6823 | V18: =V22*V16/V14 -> 6161.7512 | W18: =+AK18 -> 6227.1361 | AC18: ='Financial Statements'!AC54 -> 7369 | AD18: ='Financial Statements'!AD54 -> 8104 | AE18: ='Financial Statements'!AE54 -> 8255 | AF18: =AF22*AF16/AF14 -> 7375.0685 | AG18: =AG22*AG16/AG14 -> 7148.7593 | AH18: =AH22*AH16/AH14 -> 6920.6591 | AI18: =AI22*AI16/AI14 -> 6672.6327 | AJ18: =AJ22*AJ16/AJ14 -> 6459.6823 | AK18: =AK22*AK16/AK14 -> 6227.1361
B19: Trade Receivables | C19: ='Financial Statements'!C55 -> 1829 | D19: ='Financial Statements'!D55 -> 1126 | E19: ='Financial Statements'!E55 -> 1126 | F19: ='Financial Statements'!F55 -> 2233 | G19: ='Financial Statements'!G55 -> 1388 | H19: ='Financial Statements'!H55 -> 2469 | I19: ='Financial Statements'!I55 -> 1814 | J19: ='Financial Statements'!J55 -> 2458 | ... L19: ='Financial Statements'!L55 -> 2203 | M19: =+AF19 -> 2080.8261 | N19: =N23*N15/N14 -> 2141.9255 | O19: =+AG19 -> 1998.532 | P19: =P23*P15/P14 -> 1977.8784 | Q19: =+AH19 -> 1913.769 | R19: =R23*R15/R14 -> 1803.9675 | S19: =+AI19 -> 1821.4728 | T19: =T23*T15/T14 -> 1634.8723 | U19: =+AJ19 -> 1736.5382 | V19: =V23*V15/V14 -> 1455.6136 | W19: =+AK19 -> 1643.9154 | AC19: ='Financial Statements'!AC55 -> 1388 | AD19: ='Financial Statements'!AD55 -> 1814 | AE19: ='Financial Statements'!AE55 -> 1581 | AF19: =AF23*AF15/AF14 -> 2080.8261 | AG19: =AG23*AG15/AG14 -> 1998.532 | AH19: =AH23*AH15/AH14 -> 1913.769 | AI19: =AI23*AI15/AI14 -> 1821.4728 | AJ19: =AJ23*AJ15/AJ14 -> 1736.5382 | AK19: =AK23*AK15/AK14 -> 1643.9154
B20: Trade Payables | C20: ='Financial Statements'!C82 -> 2345 | D20: ='Financial Statements'!D82 -> 2337 | E20: ='Financial Statements'!E82 -> 2337 | F20: ='Financial Statements'!F82 -> 2976 | G20: ='Financial Statements'!G82 -> 3019 | H20: ='Financial Statements'!H82 -> 3222 | I20: ='Financial Statements'!I82 -> 3461 | J20: ='Financial Statements'!J82 -> 3068 | ... L20: ='Financial Statements'!L82 -> 2727 | M20: =+AF20 -> 2741.0671 | N20: =N24*N16/N14 -> 2806.6352 | O20: =+AG20 -> 2656.9556 | P20: =P24*P16/P14 -> 2677.0397 | Q20: =+AH20 -> 2572.1783 | R20: =R24*R16/R14 -> 2540.6794 | S20: =+AI20 -> 2479.9951 | T20: =T24*T16/T14 -> 2418.6058 | U20: =+AJ20 -> 2400.8486 | V20: =V24*V16/V14 -> 2290.1175 | W20: =+AK20 -> 2314.4189 | AC20: ='Financial Statements'!AC82 -> 3019 | AD20: ='Financial Statements'!AD82 -> 3461 | AE20: ='Financial Statements'!AE82 -> 2930 | AF20: =AF24*AF16/AF14 -> 2741.0671 | AG20: =AG24*AG16/AG14 -> 2656.9556 | AH20: =AH24*AH16/AH14 -> 2572.1783 | AI20: =AI24*AI16/AI14 -> 2479.9951 | AJ20: =AJ24*AJ16/AJ14 -> 2400.8486 | AK20: =AK24*AK16/AK14 -> 2314.4189
B22: Inventory Days | C22: =C18/C16*C14 -> 570.45188 | D22: =D18/D16*D14 -> 763.42534 | E22: =E18/E16*E14 -> 677.59133 | F22: =F18/F16*F14 -> 526.8025 | G22: =G18/G16*G14 -> 704.47486 | H22: =H18/H16*H14 -> 502.72206 | I22: =I18/I16*I14 -> 689.82276 | J22: =J18/J16*J14 -> 601.87963 | ... M22: =M18/M16*M14 -> 645.69441 | N22: 600 | O22: =O18/O16*O14 -> 635.50916 | P22: 600 | Q22: =Q18/Q16*Q14 -> 625.1905 | R22: 600 | S22: =S18/S16*S14 -> 614.74034 | T22: 600 | U22: =U18/U16*U14 -> 604.16103 | V22: 600 | W22: =W18/W16*W14 -> 593.4554 | AC22: =AC18/AC16*AC14 -> 636.16012 | AD22: =AD18/AD16*AD14 -> 604.77612 | AE22: =AE18/AE16*AE14 -> 653.54315 | AF22: 600 | AG22: 600 | AH22: 600 | AI22: 600 | AJ22: 600 | AK22: 600
B23: Days Receivables | C23: =C19/C15*C14 -> 66.959378 | D23: =D19/D15*D14 -> 53.528263 | E23: =E19/E15*E14 -> 46.576383 | F23: =F19/F15*F14 -> 68.387733 | G23: =G19/G15*G14 -> 53.418389 | H23: =H19/H15*H14 -> 63.321037 | I23: =I19/I15*I14 -> 65.934077 | J23: =J19/J15*J14 -> 68.257056 | ... M23: =M19/M15*M14 -> 76.054499 | N23: 68 | O23: =O19/O15*O14 -> 73.256082 | P23: 68 | Q23: =Q19/Q15*Q14 -> 70.356885 | R23: 68 | S23: =S19/S15*S14 -> 67.352703 | T23: 68 | U23: =U19/U15*U14 -> 64.239111 | V23: 68 | W23: =W19/W15*W14 -> 61.011458 | AC23: =AC19/AC15*AC14 -> 47.343239 | AD23: =AD19/AD15*AD14 -> 54.55302 | AE23: =AE19/AE15*AE14 -> 49.891878 | AF23: 68 | AG23: 68 | AH23: 68 | AI23: 68 | AJ23: 68 | AK23: 68
B24: Days Payables | C24: =C20/C16*C14 -> 217.90351 | D24: =D20/D16*D14 -> 272.17773 | E24: =E20/E16*E14 -> 241.57604 | F24: =F20/F16*F14 -> 234.2044 | G24: =G20/G16*G14 -> 288.61577 | H24: =H20/H16*H14 -> 214.05715 | I24: =I20/I16*I14 -> 294.60471 | J24: =J20/J16*J14 -> 223.77202 | ... M24: =M20/M16*M14 -> 239.98309 | N24: 223 | O24: =O20/O16*O14 -> 236.19757 | P24: 223 | Q24: =Q20/Q16*Q14 -> 232.36247 | R24: 223 | S24: =S20/S16*S14 -> 228.47849 | T24: 223 | U24: =U20/U16*U14 -> 224.54652 | V24: 223 | W24: =W20/W16*W14 -> 220.56759 | AC24: =AC20/AC16*AC14 -> 260.62796 | AD24: =AD20/AD16*AD14 -> 258.28358 | AE24: =AE20/AE16*AE14 -> 231.96626 | AF24: 223 | AG24: 223 | AH24: 223 | AI24: 223 | AJ24: 223 | AK24: 223
B27: Debt Schedule
B28: Opening Balance | D28: =C31 -> 8680 | E28: =D31 -> 8787 | F28: =E31 -> 8787 | G28: =F31 -> 8236 | H28: =AC31 -> 9238 | I28: =H31 -> 9732 | J28: =AD31 -> 9678 | K28: =J31 -> 10318 | L28: =AE31 -> 10907 | M28: =L31 -> 11014 | N28: =AF31 -> 11514 | O28: =N31 -> 12014 | P28: =AG31 -> 12514 | Q28: =P31 -> 13014 | R28: =AH31 -> 13514 | S28: =R31 -> 14014 | T28: =AI31 -> 14514 | U28: =T31 -> 15014 | V28: =AJ31 -> 15514 | W28: =V31 -> 16014 | AC28: =E31 -> 8787 | AD28: =AC31 -> 9238 | AE28: =AD31 -> 9678 | AF28: =AE31 -> 10907 | AG28: =AF31 -> 11514 | AH28: =AG31 -> 12514 | AI28: =AH31 -> 13514 | AJ28: =AI31 -> 14514 | AK28: =AJ31 -> 15514
B29: Repayment | D29: =D31-D28 -> 107 | E29: =E31-E28 -> 0 | F29: =F31-F28 -> -551 | G29: =G31-G28 -> 1002 | H29: =-'Financial Statements'!H132 -> 811 | I29: =AD29-H29 -> 34 | J29: =J28+J30-J31 -> 1052 | K29: =AE29-J29 -> 305 | L29: =L28+L30-L31 -> 744 | M29: 500 | N29: 500 | O29: 500 | P29: 500 | Q29: 500 | R29: 500 | S29: 500 | T29: 500 | U29: 500 | V29: 500 | W29: 500 | AC29: 493 | AD29: =-'Financial Statements'!AD132 -> 845 | AE29: =-'Financial Statements'!AE132 -> 1357 | AF29: =L29+M29 -> 1244 | AG29: =N29+O29 -> 1000 | AH29: =P29+Q29 -> 1000 | AI29: =R29+S29 -> 1000 | AJ29: =T29+U29 -> 1000 | AK29: =V29+W29 -> 1000
B30: Addition | E30: =E31-E28+E29 -> 0 | F30: =F31-F28+F29 -> -1102 | G30: =G31-G28+G29 -> 2004 | H30: ='Financial Statements'!H131 -> 1302 | I30: =I31-I28+I29 -> -20 | J30: ='Financial Statements'!J131 -> 1692 | K30: =K31-K28+K29 -> 894 | L30: ='Financial Statements'!L131 -> 851 | M30: 1000 | N30: 1000 | O30: 1000 | P30: 1000 | Q30: 1000 | R30: 1000 | S30: 1000 | T30: 1000 | U30: 1000 | V30: 1000 | W30: 1000 | AC30: =AC31-AC28+AC29 -> 944 | AD30: ='Financial Statements'!AD131 -> 1702 | AE30: ='Financial Statements'!AE131 -> 2815 | AF30: =L30+M30 -> 1851 | AG30: =N30+O30 -> 2000 | AH30: =P30+Q30 -> 2000 | AI30: =R30+S30 -> 2000 | AJ30: =T30+U30 -> 2000 | AK30: =V30+W30 -> 2000
B31: Closing Balance | C31: ='Financial Statements'!C75 -> 8680 | D31: ='Financial Statements'!D75 -> 8787 | E31: ='Financial Statements'!E75 -> 8787 | F31: ='Financial Statements'!F75 -> 8236 | G31: ='Financial Statements'!G75 -> 9238 | H31: ='Financial Statements'!H75 -> 9732 | I31: ='Financial Statements'!I75 -> 9678 | J31: ='Financial Statements'!J75 -> 10318 | ... L31: ='Financial Statements'!L75 -> 11014 | M31: =M28-M29+M30 -> 11514 | N31: =N28-N29+N30 -> 12014 | O31: =O28-O29+O30 -> 12514 | P31: =P28-P29+P30 -> 13014 | Q31: =Q28-Q29+Q30 -> 13514 | R31: =R28-R29+R30 -> 14014 | S31: =S28-S29+S30 -> 14514 | T31: =T28-T29+T30 -> 15014 | ... W31: =W28-W29+W30 -> 16514 | AC31: ='Financial Statements'!AC75 -> 9238 | AD31: ='Financial Statements'!AD75 -> 9678 | AE31: ='Financial Statements'!AE75 -> 10907 | AF31: =AF28-AF29+AF30 -> 11514 | AG31: =AG28-AG29+AG30 -> 12514 | AH31: =AH28-AH29+AH30 -> 13514 | AI31: =AI28-AI29+AI30 -> 14514 | AJ31: =AJ28-AJ29+AJ30 -> 15514 | AK31: =AK28-AK29+AK30 -> 16514
B32: Interest Expense | C32: ='Financial Statements'!C17 -> 265 | D32: ='Financial Statements'!D17 -> 145 | E32: ='Financial Statements'!E17 -> 410 | F32: ='Financial Statements'!F17 -> 154 | G32: ='Financial Statements'!G17 -> 154 | H32: ='Financial Statements'!H17 -> 163 | I32: ='Financial Statements'!I17 -> 217 | J32: ='Financial Statements'!J17 -> 249 | ... L32: ='Financial Statements'!L17 -> 287 | M32: =AF32-L32 -> 173.56 | N32: =N33*N31 -> 300.35 | O32: =AG32-N32 -> 200.21 | P32: =P33*P31 -> 325.35 | Q32: =AH32-P32 -> 215.21 | R32: =R33*R31 -> 350.35 | S32: =AI32-R32 -> 230.21 | T32: =T33*T31 -> 375.35 | U32: =AJ32-T32 -> 245.21 | V32: =V33*V31 -> 400.35 | W32: =AK32-V32 -> 260.21 | AC32: ='Financial Statements'!AC17 -> 308 | AD32: ='Financial Statements'!AD17 -> 380 | AE32: ='Financial Statements'!AE17 -> 505 | AF32: =AF33*AF31 -> 460.56 | AG32: =AG33*AG31 -> 500.56 | AH32: =AH33*AH31 -> 540.56 | AI32: =AI33*AI31 -> 580.56 | AJ32: =AJ33*AJ31 -> 620.56 | AK32: =AK33*AK31 -> 660.56
B33: % of debt | C33: =C32/C31 -> 0.030529954 | D33: =D32/D31 -> 0.01650165 | E33: =E32/E31 -> 0.046659838 | F33: =F32/F31 -> 0.018698397 | G33: =G32/G31 -> 0.016670275 | H33: =H32/H31 -> 0.01674887 | I33: =I32/I31 -> 0.022421988 | J33: =J32/J31 -> 0.024132584 | ... M33: =M32/M31 -> 0.015073823 | N33: 0.025 | O33: =O32/O31 -> 0.015998881 | P33: 0.025 | Q33: =Q32/Q31 -> 0.015924967 | R33: 0.025 | S33: =S32/S31 -> 0.015861237 | T33: 0.025 | U33: =U32/U31 -> 0.015805724 | V33: 0.025 | W33: =W32/W31 -> 0.015756934 | AC33: =AC32/AC31 -> 0.03334055 | AD33: =AD32/AD31 -> 0.039264311 | AE33: =AE32/AE31 -> 0.046300541 | AF33: 0.04 | AG33: 0.04 | AH33: 0.04 | AI33: 0.04 | AJ33: 0.04 | AK33: 0.04

Sheet DCF 
A3: Pernod Ricard
A4: Figures in Euro millions, except share data | C4: 2025E | D4: 2026E | E4: 2027E | F4: 2028E | G4: 2029E
A5: DCF | C5: 0.5 | D5: =+C5+1 -> 1.5 | E5: =+D5+1 -> 2.5 | F5: =+E5+1 -> 3.5 | G5: =+F5+1 -> 4.5
A6: Revenues | C6: ='Financial Statements'!AF4 -> 11169.14 | D6: ='Financial Statements'!AG4 -> 10727.414 | E6: ='Financial Statements'!AH4 -> 10272.437 | F6: ='Financial Statements'!AI4 -> 9803.8097 | G6: ='Financial Statements'!AJ4 -> 9321.124
A7: EBIT | C7: ='Financial Statements'!AF15 -> 2755.019 | D7: ='Financial Statements'!AG15 -> 2967.3717 | E7: ='Financial Statements'!AH15 -> 2871.4507 | F7: ='Financial Statements'!AI15 -> 2790.4748 | G7: ='Financial Statements'!AJ15 -> 2723.8486
A8: Tax | C8: ='Financial Statements'!AF23 -> 0.23 | D8: ='Financial Statements'!AG23 -> 0.23 | E8: ='Financial Statements'!AH23 -> 0.23 | F8: ='Financial Statements'!AI23 -> 0.15 | G8: ='Financial Statements'!AJ23 -> 0.15
A9: EBIT (1-t) | C9: =+C7*(1-C8) -> 2121.3646 | D9: =+D7*(1-D8) -> 2284.8762 | E9: =+E7*(1-E8) -> 2211.017 | F9: =+F7*(1-F8) -> 2371.9035 | G9: =+G7*(1-G8) -> 2315.2713
A10: D&A | C10: ='Financial Statements'!AF102 -> 466.96 | D10: ='Financial Statements'!AG102 -> 546.03151 | E10: ='Financial Statements'!AH102 -> 598.58763 | F10: ='Financial Statements'!AI102 -> 639.91979 | G10: ='Financial Statements'!AJ102 -> 671.18126
A11: NWC | C11: ='Financial Statements'!AF114 -> 157 | D11: ='Financial Statements'!AG114 -> 0 | E11: ='Financial Statements'!AH114 -> 0 | F11: ='Financial Statements'!AI114 -> 0 | G11: ='Financial Statements'!AJ114 -> 0
A12: Capital expenditures | C12: ='Financial Statements'!AF122 -> -769.4512 | D12: ='Financial Statements'!AG122 -> -1019.1043 | E12: ='Financial Statements'!AH122 -> -975.88148 | F12: ='Financial Statements'!AI122 -> -931.36192 | G12: ='Financial Statements'!AJ122 -> -885.50678
A13: Unlevered free cash flows (UFCF) | C13: =+C9+C10+C11+C12 -> 1975.8734 | D13: =+D9+D10+D11+D12 -> 1811.8033 | E13: =+E9+E10+E11+E12 -> 1833.7232 | F13: =+F9+F10+F11+F12 -> 2080.4614 | G13: =+G9+G10+G11+G12 -> 2100.9458
A14: Discounting factor | C14: =1/(1+$C$30)^C5 -> 0.99258333 | D14: =1/(1+$C$30)^D5 -> 0.97791461 | E14: =1/(1+$C$30)^E5 -> 0.96346267 | F14: =1/(1+$C$30)^F5 -> 0.94922431 | G14: =1/(1+$C$30)^G5 -> 0.93519636
A15: FCFF | C15: =+C14*C13 -> 1961.219 | D15: =+D14*D13 -> 1771.789 | E15: =+E14*E13 -> 1766.7238 | F15: =+F14*F13 -> 1974.8245 | G15: =+G14*G13 -> 1964.7969
A16: TV | G16: =+(G13*(1+C33))/(C30-C33) -> 144965.26
A17: Enterprise Value | C17: =+SUM(C15:G15)+G16 -> 154404.62
A18: Net Debt | C18: ='Financial Statements'!AF75-'Financial Statements'!AF59 -> 7667.7278
A19: Minority Interest | C19: ='Financial Statements'!AF29 -> 24
A20: Equity Value | C20: =+C17+C18+C19 -> 162096.34
A21: No. of shares | C21: ='Financial Statements'!AF38 -> 2531.8831
A22: Target Price | C22: =+C20/C21 -> 64.022049
A23: CMP | C23: 89.86
A24: Change(%) | C24: =+C22/C23-1 -> -0.28753562
A26: Assumptions | F26: Sensitivity Analysis
A27: Equity Risk Premium | C27: 0.05 | F27: =+C22 -> 64.022049 | G27: 0.008 | H27: 0.01 | I27: 0.013 | J27: 0.015 | K27: 0.018
A28: Risk Free rate | C28: 0.01 | F28: 0.005 | G28: 117.52673 | H28: 94.20356 | I28: 73.201603 | J28: 64.022049 | K28: 54.179135
A29: Beta | C29: 0.96 | F29: 0.01 | G29: 117.52673 | H29: 94.20356 | I29: 73.201603 | J29: 64.022049 | K29: 54.179135
A30: WACC | C30: 0.015 | F30: 0.015 | G30: 117.52673 | H30: 94.20356 | I30: 73.201603 | J30: 64.022049 | K30: 54.179135
A31: Cost of Equity | C31: =+C28+(C29*C27) -> 0.058 | F31: 0.02 | G31: 117.52673 | H31: 94.20356 | I31: 73.201603 | J31: 64.022049 | K31: 54.179135
A32: Cost of Debt | C32: =Schedules!AE33 -> 0.046300541 | F32: 0.025 | G32: 117.52673 | H32: 94.20356 | I32: 73.201603 | J32: 64.022049 | K32: 54.179135
A33: Growth rate (%) | C33: 0.0005
