Workbook

Sheet Company
B2: Founded | C2: 1724
B3: Business Model | C3: The Rémy Cointreau Group is one of the major operators in the global Wine & Spirits market with a portfolio of exceptional brands, which include Rémy Martin and LOUIS XIII cognacs and Cointreau liqueur. The brands are mostly distributed by a network of subsidiaries established in the Group’s various strategic markets. Rémy Cointreau is listed on Euronext Paris. The free float represents approximately 40%. The Rémy Cointreau Group is controlled by the majority shareholder, the Andromède family holding company
B4: Revenue Streams | C4: Cognac
C5: Liqueur & Spirits
C6: Partner Brands
B7: Geographies market wise
B8: Biggest SKUs
B9: Highest Priced Products
C12: Rémy Cointreau has a portfolio of exceptional spirits. Each of these brands embodies unique expertise and heritage, but all share the same culture of excellence.
B14: The House of Rémy Martin - Cognac & House of Brillet | C14: The parent company for the Group’s two brands of cognac — Rémy Martin and LOUIS XIII — Rémy Martin manages all the pooled resources that they are able to call on.
B15: Liqueur & Spirits | C15: The Liqueurs & Spirits division gathers together eight brands with very distinct personalities and brand positions: the liqueur Cointreau, the Greek spirit Metaxa, Mount Gay rum, the French brandy St-Rémy, the single malts Bruichladdich, Port Charlotte and Octomore, the American single malt Westland, the French organic single malt Domaine des Hautes Glaces, and The Botanist gin.
C16: Cointreau - Orange Liqueur- Used in Cosmopolitan
C17: Metaxa - | D17: The Original Greek Spirit
C18: Mount Gay Rum - originated in Barbados
C19: St-Remy- St-Rémy is the world’s number-one French brandy. St-Rémy is bottled in the Loire Valley and shipped around the world!
C20: Bruichladdich – Port Charlotte – Octomore - Unpeated, peated and heavily peated whiskies from Islay
C21: The Botanist - Islya Dry Gin
C22: Hautes Glaces - Whisky from French Alps
C23: Westland Distillery - American single malt
C24: Telmont - Champagne
C25: Belle de brillet - Pear liquer, pineau and cognac
B26: Partner Brands

Sheet Revenue Model
B2: In Euro millions | C2: H1'20 | D2: H2'20 | E2: FY20 | F2: H1'21 | G2: H2'21 | H2: FY21 | I2: H1'22 | J2: H2'22 | K2: FY22 | L2: H1'23 | M2: H2'23 | N2: FY23 | O2: H1'24 | P2: H2'24 | Q2: FY24 | R2: H1'25 | S2: H2'25 | T2: FY25 | U2: H1'26 | V2: H2'26 | W2: FY26 | X2: H1'27 | Y2: H2'27 | Z2: FY27 | AA2: H1'28 | AB2: H2'28 | AC2: FY28 | AD2: H1'29 | AE2: H2'29 | AF2: FY29 | AG2: H1'30 | AH2: H2'30 | AI2: FY30
B4: Cognac
B5: Organic | C5: 367.2 | D5: 349.5 | E5: 716.6 | F5: 310.9 | G5: 451.9 | H5: 762.8 | I5: 473.9 | J5: 454.3 | K5: 928.2 | L5: 568.7 | M5: 451.6 | N5: 1020.3 | O5: 445.8 | P5: 378.1 | Q5: 823.9 | R5: 343 | S5: 265 | T5: 608 | U5: 315.4 | V5: =S16*(1+V7) -> 302.736 | W5: =U5+V5 -> 618.136 | X5: =U16*(1+X7) -> 312.208 | Y5: =V16*(1+Y7) -> 314.84544 | Z5: =X5+Y5 -> 627.05344 | AA5: =X16*(1+AA7) -> 324.69632 | AB5: =Y16*(1+AB7) -> 327.43926 | AC5: =AA5+AB5 -> 652.13558 | AD5: =AA16*(1+AD7) -> 337.68417 | AE5: =AB16*(1+AE7) -> 340.53683 | AF5: =AD5+AE5 -> 678.221 | AG5: =AD16*(1+AG7) -> 351.19154 | AH5: =AE16*(1+AH7) -> 354.1583 | AI5: =AG5+AH5 -> 705.34984
U6: =U10+U8 -> -26.2955
B7: Organic growth (%) | F7: =F5/C16-1 -> -0.18097998 | G7: =G5/D16-1 -> 0.26973869 | H7: =H5/E16-1 -> 0.037258635 | I7: =I5/F16-1 -> 0.55173543 | J7: =J5/G16-1 -> 0.057495345 | K7: =K5/H16-1 -> 0.26285714 | L7: =L5/I16-1 -> 0.22406371 | M7: =M5/J16-1 -> -0.066363448 | ... U7: =U5/R16-1 -> -0.076427526 | V7: 0.12 | W7: =W5/T16-1 -> 0.010521497 | X7: 0.04 | Y7: 0.04 | Z7: =Z5/W16-1 -> 0.04 | AA7: 0.04 | AB7: 0.04 | AC7: =AC5/Z16-1 -> 0.04 | AD7: 0.04 | AE7: 0.04 | AF7: =AF5/AC16-1 -> 0.04 | AG7: 0.04 | AH7: 0.04 | AI7: =AI5/AF16-1 -> 0.04
B8: Volume | U8: =U9*R16 -> 2.3905
B9: Volume growth (%) | T9: -0.156 | U9: 0.007
B10: Price Mix | U10: =U11*R16 -> -28.686
B11: Price Mix(%) | T11: -0.063 | U11: -0.084
B12: Fx | C12: 12.4 | D12: 6.4 | E12: 18.8 | F12: -5.6 | G12: -22.5 | H12: -28.2 | I12: -9.3 | J12: 29.4 | K12: 20.1 | L12: 69.4 | M12: 10.3 | N12: 79.7 | O12: -29.7 | P12: -15.5 | Q12: -45.3 | R12: -1.6 | S12: 5.3 | T12: 3.7 | U12: -15.2 | V12: =V13*S16 -> 0 | W12: =U12+V12 -> -15.2 | X12: =X13*U16 -> 0 | Y12: =Y13*V16 -> 0 | Z12: =X12+Y12 -> 0 | AA12: =AA13*X16 -> 0 | AB12: =AB13*Y16 -> 0 | AC12: =AA12+AB12 -> 0 | AD12: =AD13*AA16 -> 0 | AE12: =AE13*AB16 -> 0 | AF12: =AD12+AE12 -> 0 | AG12: =AG13*AD16 -> 0 | AH12: =AH13*AE16 -> 0 | AI12: =AG12+AH12 -> 0
B13: Fx growth (%) | F13: =F12/C16 -> -0.014752371 | G13: =G12/D16 -> -0.063220006 | H13: =H12/E16 -> -0.038346478 | I13: =I12/F16 -> -0.030451866 | J13: =J12/G16 -> 0.068435754 | K13: =K12/H16 -> 0.027346939 | L13: =L12/I16 -> 0.14937581 | M13: =M12/J16 -> 0.021294191 | ... U13: =U12/R16 -> -0.044509517 | V13: 0 | W13: =W12/T16 -> -0.024848782 | X13: 0 | Y13: 0 | Z13: =Z12/W16 -> 0 | AA13: 0 | AB13: 0 | AC13: =AC12/Z16 -> 0 | AD13: 0 | AE13: 0 | AF13: =AF12/AC16 -> 0 | AG13: 0 | AH13: 0 | AI13: =AI12/AF16 -> 0
B14: Scope | C14: 0 | D14: 0 | E14: 0 | F14: 0.1 | G14: 0.2 | H14: 0.4 | I14: 0 | J14: 0 | K14: 0 | L14: 0 | M14: 0 | N14: 0 | O14: 0 | P14: 0 | Q14: 0 | R14: 0 | S14: 0 | T14: 0 | U14: 0 | V14: =V15*S16 -> 0 | W14: =U14+V14 -> 0 | X14: =X15*U16 -> 0 | Y14: =Y15*V16 -> 0 | Z14: =X14+Y14 -> 0 | AA14: =AA15*X16 -> 0 | AB14: =AB15*Y16 -> 0 | AC14: =AA14+AB14 -> 0 | AD14: =AD15*AA16 -> 0 | AE14: =AE15*AB16 -> 0 | AF14: =AD14+AE14 -> 0 | AG14: =AG15*AD16 -> 0 | AH14: =AH15*AE16 -> 0 | AI14: =AG14+AH14 -> 0
B15: Scope growth (%) | F15: =F14/C126 -> #DIV/0! | G15: =G14/D126 -> #DIV/0! | H15: =H14/E126 -> #DIV/0! | I15: =I14/F126 -> #DIV/0! | J15: =J14/G126 -> #DIV/0! | K15: =K14/H126 -> #DIV/0! | L15: =L14/I126 -> #DIV/0! | M15: =M14/J126 -> #DIV/0! | ... U15: =U14/R126 -> #DIV/0! | V15: 0 | W15: =W14/T126 -> #DIV/0! | X15: 0 | Y15: 0 | Z15: =Z14/W126 -> #DIV/0! | AA15: 0 | AB15: 0 | AC15: =AC14/Z126 -> #DIV/0! | AD15: 0 | AE15: 0 | AF15: =AF14/AC126 -> #DIV/0! | AG15: 0 | AH15: 0 | AI15: =AI14/AF126 -> #DIV/0!
B16: Total Sales - Cognac | C16: =C5+C12+C14 -> 379.6 | D16: =D5+D12+D14 -> 355.9 | E16: =E5+E12+E14 -> 735.4 | F16: =F5+F12+F14 -> 305.4 | G16: =G5+G12+G14 -> 429.6 | H16: =H5+H12+H14 -> 735 | I16: =I5+I12+I14 -> 464.6 | J16: =J5+J12+J14 -> 483.7 | ... Q16: =Q5+Q12+Q14 -> 778.6 | R16: =R5+R12+R14+0.1 -> 341.5 | S16: =S5+S12+S14 -> 270.3 | T16: =T5+T12+T14 -> 611.7 | U16: =U5+U12+U14 -> 300.2 | V16: =V5+V12+V14 -> 302.736 | W16: =W5+W12+W14 -> 602.936 | X16: =X5+X12+X14 -> 312.208 | Y16: =Y5+Y12+Y14 -> 314.84544 | Z16: =Z5+Z12+Z14 -> 627.05344 | ... AI16: =AI5+AI12+AI14 -> 705.34984
B17: Growth (%) | F17: =IFERROR(F16/C16-1, "-") -> -0.19546891 | G17: =IFERROR(G16/D16-1, "-") -> 0.20708064 | H17: =IFERROR(H16/E16-1, "-") -> -0.00054392168 | I17: =IFERROR(I16/F16-1, "-") -> 0.52128356 | J17: =IFERROR(J16/G16-1, "-") -> 0.1259311 | K17: =IFERROR(K16/H16-1, "-") -> 0.29020408 | L17: =IFERROR(L16/I16-1, "-") -> 0.37343952 | M17: =IFERROR(M16/J16-1, "-") -> -0.045069258 | ... AI17: =IFERROR(AI16/AF16-1, "-") -> 0.04
B19: Liquers & Spirits
B20: Organic | C20: 128 | D20: 128.5 | E20: 256.4 | F20: 113.4 | G20: 140 | H20: 253.4 | I20: 164.7 | J20: 162.5 | K20: 327.1 | L20: 198.1 | M20: 197.6 | N20: 395.7 | O20: 214.6 | P20: 185 | Q20: 399.6 | R20: 181.8 | S20: 168.8 | T20: 350.7 | U20: 189.2 | V20: =S31*(1+V22) -> 172.508 | W20: =U20+V20 -> 361.708 | X20: =U31*(1+X22) -> 190.008 | Y20: =V31*(1+Y22) -> 179.40832 | Z20: =X20+Y20 -> 369.41632 | AA20: =X31*(1+AA22) -> 197.60832 | AB20: =Y31*(1+AB22) -> 186.58465 | AC20: =AA20+AB20 -> 384.19297 | AD20: =AA31*(1+AD22) -> 205.51265 | AE20: =AB31*(1+AE22) -> 194.04804 | AF20: =AD20+AE20 -> 399.56069 | AG20: =AD31*(1+AG22) -> 221.95367 | AH20: =AE31*(1+AH22) -> 213.45284 | AI20: =AG20+AH20 -> 435.40651
U21: =U23+U25 -> 7.6314
B22: Organic growth (%) | F22: =F20/C31-1 -> -0.13567073 | G22: =G20/D31-1 -> 0.071155318 | H22: =H20/E31-1 -> -0.032085561 | I22: =I20/F31-1 -> 0.47053571 | J22: =J20/G31-1 -> 0.19222304 | K22: =K20/H31-1 -> 0.31735803 | L22: =L20/I31-1 -> 0.20719074 | M22: =M20/J31-1 -> 0.16853933 | ... U22: =U20/R31-1 -> 0.04127683 | V22: 0.01 | W22: =W20/T31-1 -> 0.02583097 | X22: 0.04 | Y22: 0.04 | Z22: =Z20/W20-1 -> 0.021310892 | AA22: 0.04 | AB22: 0.04 | AC22: =AC20/Z20-1 -> 0.04 | AD22: 0.04 | AE22: 0.04 | AF22: =AF20/AC20-1 -> 0.04 | AG22: 0.08 | AH22: 0.1 | AI22: =AI20/AF20-1 -> 0.08971307
B23: Volume | U23: =U24*R31 -> 9.4484
B24: Volume growth (%) | U24: 0.052
B25: Price Mix | U25: =U26*R31 -> -1.817
B26: Price Mix(%) | U26: -0.01
B27: Fx | C27: 3.2 | D27: 2.2 | E27: 5.4 | F27: -1.8 | G27: -6.2 | H27: -8 | I27: -2.5 | J27: 6.6 | K27: 4.1 | L27: 16.4 | M27: 6.9 | N27: 23.2 | O27: -7.9 | P27: -3.8 | Q27: -11.7 | R27: -0.1 | S27: 2 | T27: 1.9 | U27: -6.5 | V27: =V28*S31 -> 0 | W27: =U27+V27 -> -6.5 | X27: =X28*U31 -> 0 | Y27: =Y28*V31 -> 0 | Z27: =X27+Y27 -> 0 | AA27: =AA28*X31 -> 0 | AB27: =AB28*Y31 -> 0 | AC27: =AA27+AB27 -> 0 | AD27: =AD28*AA31 -> 0 | AE27: =AE28*AB31 -> 0 | AF27: =AD27+AE27 -> 0 | AG27: =AG28*AD31 -> 0 | AH27: =AH28*AE31 -> 0 | AI27: =AG27+AH27 -> 0
B28: Fx growth (%) | F28: =F27/C31 -> -0.013719512 | G28: =G27/D31 -> -0.047436878 | H28: =H27/E31 -> -0.030557678 | I28: =I27/F31 -> -0.022321429 | J28: =J27/G31 -> 0.048422597 | K28: =K27/H31 -> 0.016512284 | L28: =L27/I31 -> 0.099939062 | M28: =M27/J31 -> 0.040804258 | ... U28: =U27/R31 -> -0.035773253 | V28: 0 | W28: =W27/T31 -> -0.018434487 | X28: 0 | Y28: 0 | Z28: =Z27/W31 -> 0 | AA28: 0 | AB28: 0 | AC28: =AC27/Z31 -> 0 | AD28: 0 | AE28: 0 | AF28: =AF27/AC31 -> 0 | AG28: 0 | AH28: 0 | AI28: =AI27/AF31 -> 0
B29: Scope | C29: 0 | D29: 0 | E29: 0 | F29: 0.4 | G29: 2.5 | H29: 2.9 | I29: 1.9 | J29: 0 | K29: 0 | L29: 0 | M29: 0 | N29: 0 | O29: 0 | P29: 0 | Q29: 0 | R29: 0 | S29: 0 | T29: 0 | U29: 0 | V29: =V30*S31 -> 0 | W29: =U29+V29 -> 0 | X29: =X30*U31 -> 0 | Y29: =Y30*V31 -> 0 | Z29: =X29+Y29 -> 0 | AA29: =AA30*X31 -> 0 | AB29: =AB30*Y31 -> 0 | AC29: =AA29+AB29 -> 0 | AD29: =AD30*AA31 -> 0 | AE29: =AE30*AB31 -> 0 | AF29: =AD29+AE29 -> 0 | AG29: =AG30*AD31 -> 0 | AH29: =AH30*AE31 -> 0 | AI29: =AG29+AH29 -> 0
B30: Scope growth (%) | F30: =F29/C136 -> #DIV/0! | G30: =G29/D136 -> #DIV/0! | H30: =H29/E136 -> #DIV/0! | I30: =I29/F136 -> #DIV/0! | J30: =J29/G136 -> #DIV/0! | K30: =K29/H136 -> #DIV/0! | L30: =L29/I136 -> #DIV/0! | M30: =M29/J136 -> #DIV/0! | ... U30: =U29/R136 -> #DIV/0! | V30: 0 | W30: =W29/T136 -> #DIV/0! | X30: 0 | Y30: 0 | Z30: =Z29/W136 -> #DIV/0! | AA30: 0 | AB30: 0 | AC30: =AC29/Z136 -> #DIV/0! | AD30: 0 | AE30: 0 | AF30: =AF29/AC136 -> #DIV/0! | AG30: 0 | AH30: 0 | AI30: =AI29/AF136 -> #DIV/0!
B31: Total Sales - Liquers & Spirits | C31: =C20+C27+C29 -> 131.2 | D31: =D20+D27+D29 -> 130.7 | E31: =E20+E27+E29 -> 261.8 | F31: =F20+F27+F29 -> 112 | G31: =G20+G27+G29 -> 136.3 | H31: =H20+H27+H29 -> 248.3 | I31: =I20+I27+I29 -> 164.1 | J31: =J20+J27+J29 -> 169.1 | ... AI31: =AI20+AI27+AI29 -> 435.40651
B32: Growth (%) | F32: =IFERROR(F31/C31-1, "-") -> -0.14634146 | G32: =IFERROR(G31/D31-1, "-") -> 0.042846213 | H32: =IFERROR(H31/E31-1, "-") -> -0.051566081 | I32: =IFERROR(I31/F31-1, "-") -> 0.46517857 | J32: =IFERROR(J31/G31-1, "-") -> 0.24064563 | K32: =IFERROR(K31/H31-1, "-") -> 0.33387032 | L32: =IFERROR(L31/I31-1, "-") -> 0.3071298 | M32: =IFERROR(M31/J31-1, "-") -> 0.20934358 | ... AI32: =IFERROR(AI31/AF31-1, "-") -> 0.08971307
B34: Subtotal
B35: Cognac | C35: =C16 -> 379.6 | D35: =D16 -> 355.9 | E35: =E16 -> 735.4 | F35: =F16 -> 305.4 | G35: =G16 -> 429.6 | H35: =H16 -> 735 | I35: =I16 -> 464.6 | J35: =J16 -> 483.7 | ... S35: =S16 -> 270.3 | T35: =T16+0.1 -> 611.8 | U35: =U16 -> 300.2 | V35: =V16 -> 302.736 | W35: =W16 -> 602.936 | X35: =X16 -> 312.208 | Y35: =Y16 -> 314.84544 | Z35: =Z16 -> 627.05344 | AA35: =AA16 -> 324.69632 | AB35: =AB16 -> 327.43926 | ... AI35: =AI16 -> 705.34984
B36: Liquers & Spirits | C36: =C31 -> 131.2 | D36: =D31 -> 130.7 | E36: =E31 -> 261.8 | F36: =F31 -> 112 | G36: =G31 -> 136.3 | H36: =H31 -> 248.3 | I36: =I31 -> 164.1 | J36: =J31 -> 169.1 | ... AI36: =AI31 -> 435.40651
B37: Total Sales - Subtotal | C37: =C35+C36 -> 510.8 | D37: =D35+D36 -> 486.6 | E37: =E35+E36 -> 997.2 | F37: =F35+F36 -> 417.4 | G37: =G35+G36 -> 565.9 | H37: =H35+H36 -> 983.3 | I37: =I35+I36 -> 628.7 | J37: =J35+J36 -> 652.8 | ... AI37: =AI35+AI36 -> 1140.7563
B38: Growth (%) | F38: =IFERROR(F37/C37-1, "-") -> -0.18285043 | G38: =IFERROR(G37/D37-1, "-") -> 0.16296753 | H38: =IFERROR(H37/E37-1, "-") -> -0.013939029 | I38: =IFERROR(I37/F37-1, "-") -> 0.50622904 | J38: =IFERROR(J37/G37-1, "-") -> 0.1535607 | K38: =IFERROR(K37/H37-1, "-") -> 0.30123055 | L38: =IFERROR(L37/I37-1, "-") -> 0.3561317 | M38: =IFERROR(M37/J37-1, "-") -> 0.020833333 | ... AI38: =IFERROR(AI37/AF37-1, "-") -> 0.058429881
B40: Partner Brands
B41: Organic | C41: 13 | D41: 14.3 | E41: 27.3 | F41: 13.4 | G41: 13.7 | H41: 27.1 | I41: 16.5 | J41: 14.5 | K41: 31 | L41: 14.5 | M41: 15.2 | N41: 29.7 | O41: 14.1 | P41: 13.7 | Q41: 27.8 | R41: 10.5 | S41: 9.7 | T41: 20.1 | U41: 6.7 | V41: =S52*(1+V43) -> 10.976 | W41: =U41+V41 -> 17.676 | X41: =U52*(1+X43) -> 7.236 | Y41: =V52*(1+Y43) -> 12.0736 | Z41: =X41+Y41 -> 19.3096 | AA41: =X52*(1+AA43) -> 7.81488 | AB41: =Y52*(1+AB43) -> 13.28096 | AC41: =AA41+AB41 -> 21.09584 | AD41: =AA52*(1+AD43) -> 8.4400704 | AE41: =AB52*(1+AE43) -> 14.609056 | AF41: =AD41+AE41 -> 23.049126 | AG41: =AD52*(1+AG43) -> 9.115276 | AH41: =AE52*(1+AH43) -> 16.069962 | AI41: =AG41+AH41 -> 25.185238
B43: Organic growth (%) | F43: =F41/C52-1 -> 0.022900763 | G43: =G41/D52-1 -> -0.048611111 | H43: =H41/E52-1 -> -0.014545455 | I43: =I41/F52-1 -> 0.2406015 | J43: =J41/G52-1 -> 0.066176471 | K43: =K41/H52-1 -> 0.15241636 | L43: =L41/I52-1 -> -0.12650602 | M43: =M41/J52-1 -> 0.034013605 | ... U43: =U41/R52-1 -> -0.36190476 | V43: 0.12 | W43: =W41/T41-1 -> -0.12059701 | X43: 0.08 | Y43: 0.1 | Z43: =Z41/W41-1 -> 0.092419099 | AA43: 0.08 | AB43: 0.1 | AC43: =AC41/Z41-1 -> 0.092505282 | AD43: 0.08 | AE43: 0.1 | AF43: =AF41/AC41-1 -> 0.09259107 | AG43: 0.08 | AH43: 0.1 | AI43: =AI41/AF41-1 -> 0.092676451
B44: Volume | U44: =U45*R52 -> 0
B45: Volume growth (%) | T45: -0.156
B46: Price Mix | U46: =U47*R52 -> 0
B47: Price Mix(%) | T47: -0.063
B48: Fx | C48: 0.1 | D48: 0.1 | E48: 0.2 | F48: -0.1 | G48: -0.1 | H48: -0.2 | I48: 0.1 | J48: 0.2 | K48: 0.3 | L48: 0.1 | M48: -0.1 | N48: 0 | O48: -0.1 | P48: 0 | Q48: -0.1 | R48: 0 | S48: 0.1 | T48: 0.1 | U48: 0 | V48: =V49*S52 -> 0 | W48: =U48+V48 -> 0 | X48: =X49*U52 -> 0 | Y48: =Y49*V52 -> 0 | Z48: =X48+Y48 -> 0 | AA48: =AA49*X52 -> 0 | AB48: =AB49*Y52 -> 0 | AC48: =AA48+AB48 -> 0 | AD48: =AD49*AA52 -> 0 | AE48: =AE49*AB52 -> 0 | AF48: =AD48+AE48 -> 0 | AG48: =AG49*AD52 -> 0 | AH48: =AH49*AE52 -> 0 | AI48: =AG48+AH48 -> 0
B49: Fx growth (%) | F49: =F48/C52 -> -0.0076335878 | G49: =G48/D52 -> -0.0069444444 | H49: =H48/E52 -> -0.0072727273 | I49: =I48/F52 -> 0.007518797 | J49: =J48/G52 -> 0.014705882 | K49: =K48/H52 -> 0.011152416 | L49: =L48/I52 -> 0.0060240964 | M49: =M48/J52 -> -0.0068027211 | ... U49: =U48/R52 -> 0 | V49: 0 | W49: =W48/T52 -> 0 | X49: 0 | Y49: 0 | Z49: =Z48/W52 -> 0 | AA49: 0 | AB49: 0 | AC49: =AC48/Z52 -> 0 | AD49: 0 | AE49: 0 | AF49: =AF48/AC52 -> 0 | AG49: 0 | AH49: 0 | AI49: =AI48/AF52 -> 0
B50: Scope | C50: 0 | D50: 0 | E50: 0 | F50: 0 | G50: 0 | H50: 0 | I50: 0 | J50: 0 | K50: 0 | L50: 0 | M50: 0 | N50: 0 | O50: 0 | P50: 0 | Q50: 0 | R50: 0 | S50: 0 | T50: 0 | U50: 0 | V50: =V51*S52 -> 0 | W50: =U50+V50 -> 0 | X50: =X51*U52 -> 0 | Y50: =Y51*V52 -> 0 | Z50: =X50+Y50 -> 0 | AA50: =AA51*X52 -> 0 | AB50: =AB51*Y52 -> 0 | AC50: =AA50+AB50 -> 0 | AD50: =AD51*AA52 -> 0 | AE50: =AE51*AB52 -> 0 | AF50: =AD50+AE50 -> 0 | AG50: =AG51*AD52 -> 0 | AH50: =AH51*AE52 -> 0 | AI50: =AG50+AH50 -> 0
B51: Scope growth (%) | F51: =F50/C152 -> #DIV/0! | G51: =G50/D152 -> #DIV/0! | H51: =H50/E152 -> #DIV/0! | I51: =I50/F152 -> #DIV/0! | J51: =J50/G152 -> #DIV/0! | K51: =K50/H152 -> #DIV/0! | L51: =L50/I152 -> #DIV/0! | M51: =M50/J152 -> #DIV/0! | ... U51: =U50/R152 -> #DIV/0! | V51: 0 | W51: =W50/T152 -> #DIV/0! | X51: 0 | Y51: 0 | Z51: =Z50/W152 -> #DIV/0! | AA51: 0 | AB51: 0 | AC51: =AC50/Z152 -> #DIV/0! | AD51: 0 | AE51: 0 | AF51: =AF50/AC152 -> #DIV/0! | AG51: 0 | AH51: 0 | AI51: =AI50/AF152 -> #DIV/0!
B52: Total Sales - Partner Brands | C52: =C41+C48+C50 -> 13.1 | D52: =D41+D48+D50 -> 14.4 | E52: =E41+E48+E50 -> 27.5 | F52: =F41+F48+F50 -> 13.3 | G52: =G41+G48+G50 -> 13.6 | H52: =H41+H48+H50 -> 26.9 | I52: =I41+I48+I50 -> 16.6 | J52: =J41+J48+J50 -> 14.7 | ... S52: =S41+S48+S50 -> 9.8 | T52: =T41+T48+T50+0.1 -> 20.3 | U52: =U41+U48+U50 -> 6.7 | V52: =V41+V48+V50 -> 10.976 | W52: =W41+W48+W50 -> 17.676 | X52: =X41+X48+X50 -> 7.236 | Y52: =Y41+Y48+Y50 -> 12.0736 | Z52: =Z41+Z48+Z50 -> 19.3096 | AA52: =AA41+AA48+AA50 -> 7.81488 | AB52: =AB41+AB48+AB50 -> 13.28096 | ... AI52: =AI41+AI48+AI50 -> 25.185238
B53: Growth (%) | F53: =IFERROR(F52/C52-1, "-") -> 0.015267176 | G53: =IFERROR(G52/D52-1, "-") -> -0.055555556 | H53: =IFERROR(H52/E52-1, "-") -> -0.021818182 | I53: =IFERROR(I52/F52-1, "-") -> 0.2481203 | J53: =IFERROR(J52/G52-1, "-") -> 0.080882353 | K53: =IFERROR(K52/H52-1, "-") -> 0.16356877 | L53: =IFERROR(L52/I52-1, "-") -> -0.12048193 | M53: =IFERROR(M52/J52-1, "-") -> 0.027210884 | ... AI53: =IFERROR(AI52/AF52-1, "-") -> 0.092676451
B55: Total
B56: Group Brands | C56: =C37 -> 510.8 | D56: =D37 -> 486.6 | E56: =E37 -> 997.2 | F56: =F37 -> 417.4 | G56: =G37 -> 565.9 | H56: =H37 -> 983.3 | I56: =I37 -> 628.7 | J56: =J37 -> 652.8 | ... V56: =V37 -> 475.244 | W56: =U56+V56 -> 958.144 | X56: =X37 -> 502.216 | Y56: =Y37 -> 494.25376 | Z56: =X56+Y56 -> 996.46976 | AA56: =AA37 -> 522.30464 | AB56: =AB37 -> 514.02391 | AC56: =AA56+AB56 -> 1036.3286 | AD56: =AD37 -> 543.19683 | AE56: =AE37 -> 534.58487 | AF56: =AD56+AE56 -> 1077.7817 | AG56: =AG37 -> 573.1452 | AH56: =AH37 -> 567.61114 | AI56: =AG56+AH56 -> 1140.7563
B57: Partner Brands | C57: =C52 -> 13.1 | D57: =D52 -> 14.4 | E57: =E52 -> 27.5 | F57: =F52 -> 13.3 | G57: =G52 -> 13.6 | H57: =H52 -> 26.9 | I57: =I52 -> 16.6 | J57: =J52 -> 14.7 | ... V57: =V52 -> 10.976 | W57: =U57+V57 -> 17.676 | X57: =X52 -> 7.236 | Y57: =Y52 -> 12.0736 | Z57: =X57+Y57 -> 19.3096 | AA57: =AA52 -> 7.81488 | AB57: =AB52 -> 13.28096 | AC57: =AA57+AB57 -> 21.09584 | AD57: =AD52 -> 8.4400704 | AE57: =AE52 -> 14.609056 | AF57: =AD57+AE57 -> 23.049126 | AG57: =AG52 -> 9.115276 | AH57: =AH52 -> 16.069962 | AI57: =AG57+AH57 -> 25.185238
B58: Total Sales | C58: =C56+C57 -> 523.9 | D58: =D56+D57 -> 501 | E58: =E56+E57 -> 1024.7 | F58: =F56+F57 -> 430.7 | G58: =G56+G57 -> 579.5 | H58: =H56+H57 -> 1010.2 | I58: =I56+I57 -> 645.3 | J58: =J56+J57 -> 667.5 | ... S58: =S56+S57 -> 450.9 | T58: =T56+T57-0.1 -> 984.6 | U58: =U56+U57 -> 489.6 | V58: =V56+V57 -> 486.22 | W58: =W56+W57 -> 975.82 | X58: =X56+X57 -> 509.452 | Y58: =Y56+Y57 -> 506.32736 | Z58: =Z56+Z57 -> 1015.7794 | AA58: =AA56+AA57 -> 530.11952 | AB58: =AB56+AB57 -> 527.30487 | ... AI58: =AI56+AI57 -> 1165.9416
B59: Growth (%) | F59: =IFERROR(F58/C58-1, "-") -> -0.17789655 | G59: =IFERROR(G58/D58-1, "-") -> 0.15668663 | H59: =IFERROR(H58/E58-1, "-") -> -0.014150483 | I59: =IFERROR(I58/F58-1, "-") -> 0.49825865 | J59: =IFERROR(J58/G58-1, "-") -> 0.15185505 | K59: =IFERROR(K58/H58-1, "-") -> 0.29756484 | L59: =IFERROR(L58/I58-1, "-") -> 0.34387107 | M59: =IFERROR(M58/J58-1, "-") -> 0.020973783 | ... AI59: =IFERROR(AI58/AF58-1, "-") -> 0.059146934
Q60: =Q5+Q20+Q41 -> 1251.3 | R60: =R5+R20+R41 -> 535.3 | S60: =S5+S20+S41 -> 443.5 | T60: =T5+T20+T41 -> 978.8 | U60: =U5+U20+U41 -> 511.3
B61: Organic Growth (%) | R61: -0.159 | T61: =T60/Q58-1 -> -0.1803718 | U61: =U60/R58-1 -> -0.041971145
Q62: =Q12+Q27+Q48 -> -57.1 | R62: =R12+R27+R48 -> -1.7 | S62: =S12+S27+S48 -> 7.4 | T62: =T12+T27+T48 -> 5.7
B63: FX (%) | R63: -0.003
Q64: =Q14+Q29+Q50 -> 0 | R64: =R14+R29+R50 -> 0 | S64: 0 | T64: 0
B65: Scope (%) | R65: 0
B68: COP | C68: ='Financial Statements'!C11 -> 138.3 | D68: ='Financial Statements'!D11 -> 76.8 | E68: ='Financial Statements'!E11 -> 215.1 | F68: ='Financial Statements'!F11 -> 106.2 | G68: ='Financial Statements'!G11 -> 129.8 | H68: ='Financial Statements'!H11 -> 236 | I68: ='Financial Statements'!I11 -> 212.9 | J68: ='Financial Statements'!J11 -> 121.5 | ... AI68: ='Financial Statements'!AI11 -> 291.4854
B69: Growth (%) | F69: =IFERROR(F68/C68-1, "-") -> -0.23210412 | G69: =IFERROR(G68/D68-1, "-") -> 0.69010417 | H69: =IFERROR(H68/E68-1, "-") -> 0.09716411 | I69: =IFERROR(I68/F68-1, "-") -> 1.0047081 | J69: =IFERROR(J68/G68-1, "-") -> -0.06394453 | K69: =IFERROR(K68/H68-1, "-") -> 0.41694915 | L69: =IFERROR(L68/I68-1, "-") -> 0.49976515 | M69: =IFERROR(M68/J68-1, "-") -> -0.09218107 | ... AI69: =IFERROR(AI68/AF68-1, "-") -> 0.059146934
B70: Organic Growth (%) | R70: -0.176
B71: FX (%) | R71: 0.05
B72: Scope (%) | R72: 0

Sheet Financial Statements
B1: In Euro Millions
B3: Income Statement | C3: H1'20 | D3: H2'20 | E3: FY20 | F3: H1'21 | G3: H2'21 | H3: FY21 | I3: H1'22 | J3: H2'22 | K3: FY22 | L3: H1'23 | M3: H2'23 | N3: FY23 | O3: H1'24 | P3: H2'24 | Q3: FY24 | R3: H1'25 | S3: ='Revenue Model'!S2 -> H2'25 | T3: ='Revenue Model'!T2 -> FY25 | U3: H1'26 | V3: ='Revenue Model'!V2 -> H2'26 | W3: ='Revenue Model'!W2 -> FY26 | X3: ='Revenue Model'!X2 -> H1'27 | Y3: ='Revenue Model'!Y2 -> H2'27 | Z3: ='Revenue Model'!Z2 -> FY27 | AA3: ='Revenue Model'!AA2 -> H1'28 | AB3: ='Revenue Model'!AB2 -> H2'28 | AC3: ='Revenue Model'!AC2 -> FY28 | ... AI3: ='Revenue Model'!AI2 -> FY30
B4: Sales | C4: 523.9 | D4: =E4-C4 -> 500.9 | E4: 1024.8 | F4: 430.8 | G4: =H4-F4 -> 579.4 | H4: 1010.2 | I4: 645.3 | J4: =K4-I4 -> 667.6 | K4: 1312.9 | L4: 867.1 | M4: =N4-L4 -> 681.4 | N4: 1548.5 | O4: 636.7 | P4: =Q4-O4 -> 557.5 | Q4: ='Revenue Model'!Q58 -> 1194.2 | R4: ='Revenue Model'!R58 -> 533.7 | S4: =T4-R4 -> 450.9 | T4: ='Revenue Model'!T58 -> 984.6 | U4: ='Revenue Model'!U58 -> 489.6 | V4: ='Revenue Model'!V58 -> 486.22 | W4: ='Revenue Model'!W58 -> 975.82 | X4: ='Revenue Model'!X58 -> 509.452 | Y4: ='Revenue Model'!Y58 -> 506.32736 | Z4: ='Revenue Model'!Z58 -> 1015.7794 | AA4: ='Revenue Model'!AA58 -> 530.11952 | ... AI4: ='Revenue Model'!AI58 -> 1165.9416
B5: Cost of Sales | C5: 175.6 | D5: =E5-C5 -> 172.3 | E5: 347.9 | F5: 152.2 | G5: =H5-F5 -> 177.9 | H5: 330.1 | I5: 199.4 | J5: =K5-I5 -> 212.4 | K5: 411.8 | L5: 243.4 | M5: =N5-L5 -> 201.3 | N5: 444.7 | O5: 176.8 | P5: =Q5-O5 -> 167.2 | Q5: 344 | R5: 146.8 | S5: =T5-R5 -> 143 | T5: 289.8 | U5: 156.6 | V5: =V4-V6 -> 170.177 | W5: =U5+V5 -> 326.777 | X5: =X4-X6 -> 178.3082 | Y5: =Y4-Y6 -> 177.21458 | Z5: =X5+Y5 -> 355.52278 | AA5: =AA4-AA6 -> 185.54183 | AB5: =AB4-AB6 -> 184.5567 | AC5: =AA5+AB5 -> 370.09854 | AD5: =AD4-AD6 -> 193.07291 | AE5: =AE4-AE6 -> 192.21787 | AF5: =AD5+AE5 -> 385.29079 | AG5: =AG4-AG6 -> 203.79117 | AH5: =AH4-AH6 -> 204.28839 | AI5: =AG5+AH5 -> 408.07956
B6: Gross Profit | C6: =C4-C5 -> 348.3 | D6: =D4-D5 -> 328.6 | E6: =E4-E5 -> 676.9 | F6: =F4-F5 -> 278.6 | G6: =G4-G5 -> 401.5 | H6: =H4-H5 -> 680.1 | I6: =I4-I5 -> 445.9 | J6: =J4-J5 -> 455.2 | ... T6: =T4-T5 -> 694.8 | U6: =U4-U5+0.1 -> 333.1 | V6: =V4*V7 -> 316.043 | W6: =W4-W5 -> 649.043 | X6: =X4*X7 -> 331.1438 | Y6: =Y4*Y7 -> 329.11278 | Z6: =Z4-Z5 -> 660.25658 | AA6: =AA4*AA7 -> 344.57769 | AB6: =AB4*AB7 -> 342.74817 | AC6: =AC4-AC5 -> 687.32585 | AD6: =AD4*AD7 -> 358.56398 | AE6: =AE4*AE7 -> 356.97605 | AF6: =AF4-AF5 -> 715.54003 | AG6: =AG4*AG7 -> 378.46931 | AH6: =AH4*AH7 -> 379.39272 | AI6: =AI4-AI5 -> 757.86203
B7: Gross Margin (%) | C7: =C6/C4 -> 0.66482153 | D7: =D6/D4 -> 0.65601917 | E7: =E6/E4 -> 0.66051913 | F7: =F6/F4 -> 0.64670381 | G7: =G6/G4 -> 0.69295823 | H7: =H6/H4 -> 0.67323302 | I7: =I6/I4 -> 0.69099644 | J7: =J6/J4 -> 0.68184542 | ... U7: =U6/U4 -> 0.68035131 | V7: 0.65 | W7: =W6/W4 -> 0.66512574 | X7: 0.65 | Y7: 0.65 | Z7: =Z6/Z4 -> 0.65 | AA7: 0.65 | AB7: 0.65 | AC7: =AC6/AC4 -> 0.65 | AD7: 0.65 | AE7: 0.65 | AF7: =AF6/AF4 -> 0.65 | AG7: 0.65 | AH7: 0.65 | AI7: =AI6/AI4 -> 0.65
B8: Distribution & Administrative Expenses | C8: =159.2+50.8 -> 210 | D8: =E8-C8 -> 251.8 | E8: =355+106.8 -> 461.8 | F8: =128.6+43.8 -> 172.4 | G8: =H8-F8 -> 271.7 | H8: =341.6+102.5 -> 444.1 | I8: =172.1+60.9 -> 233 | J8: =K8-I8 -> 333.7 | K8: =566.7 -> 566.7 | L8: =230.8+73.6 -> 304.4 | M8: =N8-L8 -> 369.8 | N8: =674.2 -> 674.2 | O8: =290.8 -> 290.8 | P8: =Q8-O8 -> 255 | Q8: =545.8 -> 545.8 | R8: =239.6 -> 239.6 | S8: =T8-R8 -> 238.2 | T8: 477.8 | U8: 231.2 | V8: =V9*V4 -> 194.488 | W8: =U8+V8 -> 425.688 | X8: =X9*X4 -> 203.7808 | Y8: =Y9*Y4 -> 202.53094 | Z8: =X8+Y8 -> 406.31174 | AA8: =AA9*AA4 -> 212.04781 | AB8: =AB9*AB4 -> 210.92195 | AC8: =AA8+AB8 -> 422.96976 | AD8: =AD9*AD4 -> 220.65476 | AE8: =AE9*AE4 -> 219.67757 | AF8: =AD8+AE8 -> 440.33233 | AG8: =AG9*AG4 -> 232.90419 | AH8: =AH9*AH4 -> 233.47244 | AI8: =AG8+AH8 -> 466.37663
B9: SG&A Margin (%) | C9: =C8/C4 -> 0.40083985 | D9: =D8/D4 -> 0.50269515 | E9: =E8/E4 -> 0.45062451 | F9: =F8/F4 -> 0.4001857 | G9: =G8/G4 -> 0.46893338 | H9: =H8/H4 -> 0.43961592 | I9: =I8/I4 -> 0.36107237 | J9: =J8/J4 -> 0.49985021 | ... U9: =U8/U4 -> 0.47222222 | V9: 0.4 | W9: =W8/W4 -> 0.43623619 | X9: 0.4 | Y9: 0.4 | Z9: =Z8/Z4 -> 0.4 | AA9: 0.4 | AB9: 0.4 | AC9: =AC8/AC4 -> 0.4 | AD9: 0.4 | AE9: 0.4 | AF9: =AF8/AF4 -> 0.4 | AG9: 0.4 | AH9: 0.4 | AI9: =AI8/AI4 -> 0.4
B10: Misc. | U10: 6.9 | W10: =U10+V10 -> 6.9
B11: Current Operating Profit | C11: =C6-C8 -> 138.3 | D11: =D6-D8 -> 76.8 | E11: =E6-E8 -> 215.1 | F11: =F6-F8 -> 106.2 | G11: =G6-G8 -> 129.8 | H11: =H6-H8 -> 236 | I11: =I6-I8 -> 212.9 | J11: =J6-J8 -> 121.5 | ... T11: =T6-T8 -> 217 | U11: =U6-U8+U10-0.1 -> 108.7 | V11: =V6-V8 -> 121.555 | W11: =W6-W8+W10 -> 230.255 | X11: =X6-X8 -> 127.363 | Y11: =Y6-Y8 -> 126.58184 | Z11: =Z6-Z8 -> 253.94484 | AA11: =AA6-AA8 -> 132.52988 | AB11: =AB6-AB8 -> 131.82622 | AC11: =AC6-AC8 -> 264.3561 | AD11: =AD6-AD8 -> 137.90922 | AE11: =AE6-AE8 -> 137.29848 | ... AI11: =AI6-AI8 -> 291.4854
B12: COP Margin (%) | C12: =C11/C4 -> 0.26398168 | D12: =D11/D4 -> 0.15332402 | E12: =E11/E4 -> 0.20989461 | F12: =F11/F4 -> 0.24651811 | G12: =G11/G4 -> 0.22402485 | H12: =H11/H4 -> 0.23361711 | I12: =I11/I4 -> 0.32992407 | J12: =J11/J4 -> 0.18199521 | ... AI12: =AI11/AI4 -> 0.25
B13: Other non-current income/expense | C13: 0.6 | D13: =E13-C13 -> 19.1 | E13: 19.7 | F13: 0.2 | G13: =H13-F13 -> 0 | H13: 0.2 | I13: 13.6 | J13: =K13-I13 -> 0.5 | K13: 14.1 | L13: 4 | M13: =N13-L13 -> -0.9 | N13: 3.1 | O13: 0 | P13: =Q13-O13 -> 12.8 | Q13: 12.8 | R13: -0.2 | S13: =T13-R13 -> 6.2 | T13: 6 | U13: -0.7 | V13: 0 | W13: =U13+V13 -> -0.7 | X13: 0 | Y13: 0 | Z13: =X13+Y13 -> 0 | AA13: 0 | AB13: 0 | AC13: =AA13+AB13 -> 0 | AD13: 0 | AE13: 0 | AF13: =AD13+AE13 -> 0 | AG13: 0 | AH13: 0 | AI13: =AG13+AH13 -> 0
B14: EBIT | C14: =C11-C13 -> 137.7 | D14: =D11-D13 -> 57.7 | E14: =E11-E13 -> 195.4 | F14: =F11-F13 -> 106 | G14: =G11-G13 -> 129.8 | H14: =H11-H13 -> 235.8 | I14: =I11-I13 -> 199.3 | J14: =J11-J13 -> 121 | ... U14: =U11-U13 -> 109.4 | V14: =V6-V8-V13 -> 121.555 | W14: =W6-W8-W13 -> 224.055 | X14: =X6-X8-X13 -> 127.363 | Y14: =Y6-Y8-Y13 -> 126.58184 | Z14: =Z6-Z8-Z13 -> 253.94484 | AA14: =AA6-AA8-AA13 -> 132.52988 | AB14: =AB6-AB8-AB13 -> 131.82622 | AC14: =AC6-AC8-AC13 -> 264.3561 | ... AI14: =AI6-AI8-AI13 -> 291.4854
B15: EBIT Margin (%) | C15: =C14/C4 -> 0.26283642 | D15: =D14/D4 -> 0.11519265 | E15: =E14/E4 -> 0.19067135 | F15: =F14/F4 -> 0.24605385 | G15: =G14/G4 -> 0.22402485 | H15: =H14/H4 -> 0.23341912 | I15: =I14/I4 -> 0.3088486 | J15: =J14/J4 -> 0.18124626 | ... AI15: =AI14/AI4 -> 0.25
B16: D&A | C16: 15.4 | D16: =E16-C16 -> 18 | E16: 33.4 | F16: 16.4 | G16: =H16-F16 -> 17.6 | H16: 34 | I16: 18 | J16: =K16-I16 -> 22 | K16: 40 | L16: 19.1 | M16: =N16-L16 -> 21.1 | N16: 40.2 | O16: 21.6 | P16: =Q16-O16 -> 23.5 | Q16: 45.1 | R16: 22.9 | S16: =T16-R16 -> 23.9 | T16: 46.8 | U16: 23.2 | V16: =Schedules!V11+Schedules!V25+Schedules!V39 -> 16.038 | W16: =U16+V16 -> 39.238 | X16: =Schedules!X11+Schedules!X25+Schedules!X39 -> 16.52422 | Y16: =Schedules!Y11+Schedules!Y25+Schedules!Y39 -> 17.033672 | Z16: =Schedules!Z11+Schedules!Z25+Schedules!Z39 -> 33.557892 | AA16: =Schedules!AA11+Schedules!AA25+Schedules!AA39 -> 17.539999 | AB16: =Schedules!AB11+Schedules!AB25+Schedules!AB39 -> 18.070119 | AC16: =Schedules!AC11+Schedules!AC25+Schedules!AC39 -> 35.610118 | AD16: =Schedules!AD11+Schedules!AD25+Schedules!AD39 -> 18.597424 | AE16: =Schedules!AE11+Schedules!AE25+Schedules!AE39 -> 19.149061 | ... AI16: =Schedules!AI11+Schedules!AI25+Schedules!AI39 -> 39.97877
B17: SBP | Q17: 6.2 | R17: 4.1 | S17: =T17-R17 -> 0 | T17: 4.1 | U17: 0.8 | W17: =U17+V17 -> 0.8
B18: Dividends received from associates | Q18: 0.6 | S18: =T18-R18 -> 0 | T18: 0 | U18: 0.5 | W18: =U18+V18 -> 0.5
B19: EBITDA | C19: =C14+C16 -> 153.1 | D19: =D14+D16 -> 75.7 | E19: =E14+E16 -> 228.8 | F19: =F14+F16 -> 122.4 | G19: =G14+G16 -> 147.4 | H19: =H14+H16 -> 269.8 | I19: =I14+I16 -> 217.3 | J19: =J14+J16 -> 143 | ... P19: =P14+P16 -> 146 | Q19: =Q11+Q16+Q17+Q18 -> 356.3 | R19: =R11+R16+R17+R18 -> 174.3 | S19: =S11+S16+S17+S18 -> 93.6 | T19: =T11+T16+T17+T18-0.1 -> 267.8 | U19: =U11+U16+U17+U18 -> 133.2 | V19: =V6-V8 -> 121.555 | W19: =W6-W8 -> 223.355 | X19: =X6-X8 -> 127.363 | Y19: =Y6-Y8 -> 126.58184 | Z19: =Z6-Z8 -> 253.94484 | AA19: =AA6-AA8 -> 132.52988 | AB19: =AB6-AB8 -> 131.82622 | AC19: =AC6-AC8 -> 264.3561 | ... AI19: =AI6-AI8 -> 291.4854 | AL19: Higher EBITDA Margins
B20: EBITDA Margin (%) | C20: =C19/C4 -> 0.29223134 | D20: =D19/D4 -> 0.15112797 | E20: =E19/E4 -> 0.22326308 | F20: =F19/F4 -> 0.28412256 | G20: =G19/G4 -> 0.2544011 | H20: =H19/H4 -> 0.26707583 | I20: =I19/I4 -> 0.3367426 | J20: =J19/J4 -> 0.21420012 | ... AI20: =AI19/AI4 -> 0.25
B21: Net borrowing cost | C21: 6.3 | D21: =E21-C21 -> 6.4 | E21: 12.7 | F21: 6.1 | G21: =H21-F21 -> 5.9 | H21: 12 | I21: 5.5 | J21: =K21-I21 -> 4.9 | K21: 10.4 | L21: 4.5 | M21: =N21-L21 -> 7.2 | N21: 11.7 | O21: 11.7 | P21: =Q21-O21 -> 20 | Q21: 31.7 | R21: 16.7 | S21: =T21-R21 -> 17 | T21: 33.7 | U21: 16 | V21: =Schedules!V71 -> 17.319 | W21: =U21+V21 -> 33.319 | X21: =Schedules!X71 -> 16.719 | Y21: =Schedules!Y71 -> 16.419 | Z21: =X21+Y21 -> 33.138 | AA21: =Schedules!AA71 -> 15.819 | AB21: =Schedules!AB71 -> 15.519 | AC21: =AA21+AB21 -> 31.338 | AD21: =Schedules!AD71 -> 14.919 | AE21: =Schedules!AE71 -> 14.619 | AF21: =AD21+AE21 -> 29.538 | AG21: =Schedules!AG71 -> 14.019 | AH21: =Schedules!AH71 -> 13.719 | AI21: =AG21+AH21 -> 27.738
B22: Other financial income/expenses | C22: 8 | D22: =E22-C22 -> 7.3 | E22: 15.3 | F22: 1.9 | G22: =H22-F22 -> 0.7 | H22: 2.6 | I22: 1.9 | J22: =K22-I22 -> 0.9 | K22: 2.8 | L22: 0.7 | M22: =N22-L22 -> 5.2 | N22: 5.9 | O22: 4 | P22: =Q22-O22 -> 2.8 | Q22: 6.8 | R22: 4.4 | S22: =T22-R22 -> 4.5 | T22: 8.9 | U22: 6 | V22: 0 | W22: =U22+V22 -> 6 | X22: 0 | Y22: 0 | Z22: =X22+Y22 -> 0 | AA22: 0 | AB22: 0 | AC22: =AA22+AB22 -> 0 | AD22: 0 | AE22: 0 | AF22: =AD22+AE22 -> 0 | AG22: 0 | AH22: 0 | AI22: =AG22+AH22 -> 0
B23: PBT | C23: =C14-C21-C22 -> 123.4 | D23: =D14-D21-D22 -> 44 | E23: =E14-E21-E22 -> 167.4 | F23: =F14-F21-F22 -> 98 | G23: =G14-G21-G22 -> 123.2 | H23: =H14-H21-H22 -> 221.2 | I23: =I14-I21-I22 -> 191.9 | J23: =J14-J21-J22 -> 115.2 | ... AI23: =AI14-AI21-AI22 -> 263.7474
B24: PBT Margin (%) | C24: =C23/C4 -> 0.23554113 | D24: =D23/D4 -> 0.087841885 | E24: =E23/E4 -> 0.16334895 | F24: =F23/F4 -> 0.22748375 | G24: =G23/G4 -> 0.21263376 | H24: =H23/H4 -> 0.21896654 | I24: =I23/I4 -> 0.29738106 | J24: =J23/J4 -> 0.17255842 | ... AI24: =AI23/AI4 -> 0.22620979
B25: Income Tax | C25: 39.1 | D25: =E25-C25 -> 21.8 | E25: 60.9 | F25: 33.1 | G25: =H25-F25 -> 44.5 | H25: 77.6 | I25: 58.1 | J25: =K25-I25 -> 37.5 | K25: 95.6 | L25: 86.9 | M25: =N25-L25 -> 29.4 | N25: 116.3 | O25: 40.8 | P25: =Q25-O25 -> 28.6 | Q25: 69.4 | R25: 34.8 | S25: =T25-R25 -> 13.4 | T25: 48.2 | U25: 24.5 | V25: =V26*V23 -> 27.10136 | W25: =U25+V25 -> 51.60136 | X25: =X26*X23 -> 28.76744 | Y25: =Y26*Y23 -> 28.642338 | Z25: =X25+Y25 -> 57.409778 | AA25: =AA26*AA23 -> 30.344829 | AB25: =AB26*AB23 -> 30.239877 | AC25: =AA25+AB25 -> 60.584705 | AD25: =AD26*AD23 -> 31.977458 | AE25: =AE26*AE23 -> 31.896665 | AF25: =AD25+AE25 -> 63.874123 | AG25: =AG26*AG23 -> 34.201991 | AH25: =AH26*AH23 -> 34.372332 | AI25: =AG25+AH25 -> 68.574323
B26: Tax Rate (%) | C26: =C25/C23 -> 0.31685575 | D26: =D25/D23 -> 0.49545455 | E26: =E25/E23 -> 0.36379928 | F26: =F25/F23 -> 0.3377551 | G26: =G25/G23 -> 0.3612013 | H26: =H25/H23 -> 0.35081374 | I26: =I25/I23 -> 0.30276186 | J26: =J25/J23 -> 0.32552083 | ... U26: =U25/U23 -> 0.28032037 | V26: 0.26 | W26: =W25/W23 -> 0.27932487 | X26: 0.26 | Y26: 0.26 | Z26: =Z25/Z23 -> 0.26 | AA26: 0.26 | AB26: 0.26 | AC26: =AC25/AC23 -> 0.26 | AD26: 0.26 | AE26: 0.26 | AF26: =AF25/AF23 -> 0.26 | AG26: 0.26 | AH26: 0.26 | AI26: =AI25/AI23 -> 0.26
B27: Profit of associates | C27: 0 | D27: =E27-C27 -> 0.3 | E27: 0.3 | F27: 0 | G27: =H27-F27 -> 0.6 | H27: 0.6 | I27: 0.2 | J27: =K27-I27 -> 0.6 | K27: 0.8 | L27: 0.3 | M27: =N27-L27 -> 0.6 | N27: 0.9 | O27: 0.2 | P27: =Q27-O27 -> 0.4 | Q27: 0.6 | R27: 0.1 | S27: =T27-R27 -> 0.4 | T27: 0.5 | U27: 0.1 | V27: =U27 -> 0.1 | W27: =U27+V27 -> 0.2 | Y27: =X27 -> 0 | Z27: =X27+Y27 -> 0 | AB27: =AA27 -> 0 | AC27: =AA27+AB27 -> 0 | AE27: =AD27 -> 0 | AF27: =AD27+AE27 -> 0 | AH27: =AG27 -> 0 | AI27: =AG27+AH27 -> 0
B28: Net profit/loss | C28: =C23-C25+C27 -> 84.3 | D28: =D23-D25+D27 -> 22.5 | E28: =E23-E25+E27 -> 106.8 | F28: =F23-F25+F27 -> 64.9 | G28: =G23-G25+G27 -> 79.3 | H28: =H23-H25+H27 -> 144.2 | I28: =I23-I25+I27 -> 134 | J28: =J23-J25+J27 -> 78.3 | ... T28: =T23-T25+T27 -> 120.7 | U28: =U23-U25+U27+0.1 -> 63.1 | V28: =V23-V25+V27 -> 77.23464 | W28: =W23-W25+W27 -> 133.33464 | X28: =X23-X25+X27 -> 81.87656 | Y28: =Y23-Y25+Y27 -> 81.520502 | Z28: =Z23-Z25+Z27 -> 163.39706 | AA28: =AA23-AA25+AA27 -> 86.366051 | AB28: =AB23-AB25+AB27 -> 86.067341 | AC28: =AC23-AC25+AC27 -> 172.43339 | ... AI28: =AI23-AI25+AI27 -> 195.17307
B29: Net Profit Margin (%) | C29: =C28/C4 -> 0.16090857 | D29: =D28/D4 -> 0.044919146 | E29: =E28/E4 -> 0.10421546 | F29: =F28/F4 -> 0.15064995 | G29: =G28/G4 -> 0.13686572 | H29: =H28/H4 -> 0.14274401 | I29: =I28/I4 -> 0.20765535 | J29: =J28/J4 -> 0.1172858 | ... AI29: =AI28/AI4 -> 0.16739524
B30: Non-controling interests | C30: 0 | D30: =E30-C30 -> 0.1 | E30: 0.1 | F30: 0.1 | G30: =H30-F30 -> -0.1 | H30: 0 | I30: 0 | J30: =K30-I30 -> 0.2 | K30: 0.2 | L30: 0.1 | M30: =N30-L30 -> 0.2 | N30: 0.3 | O30: 0.2 | P30: =Q30-O30 -> 0.2 | Q30: 0.4 | R30: 0.2 | S30: =T30-R30 -> 0.3 | T30: 0.5 | W30: =U30+V30 -> 0 | Z30: =X30+Y30 -> 0 | AC30: =AA30+AB30 -> 0 | AF30: =AD30+AE30 -> 0 | AI30: =AG30+AH30 -> 0
B31: Net Profit before discounted | C31: =C28+C30 -> 84.3 | D31: =D28+D30 -> 22.6 | E31: =E28+E30 -> 106.9 | F31: =F28+F30 -> 65 | G31: =G28+G30 -> 79.2 | H31: =H28+H30 -> 144.2 | I31: =I28+I30 -> 134 | J31: =J28+J30 -> 78.5 | ... AI31: =AI28+AI30 -> 195.17307
B32: Net profit/loss from discontinued | C32: 6.3 | D32: =E32-C32 -> 0.1 | E32: 6.4 | F32: 0 | G32: =H32-F32 -> 0 | H32: 0 | I32: 0 | J32: =K32-I32 -> 0 | K32: 0 | L32: 0 | M32: =N32-L32 -> 0 | N32: 0 | O32: 0 | P32: =Q32-O32 -> 0 | Q32: 0 | R32: 0 | S32: =T32-R32 -> 0 | T32: 0 | U32: -0.1 | W32: =U32+V32 -> -0.1 | Z32: =X32+Y32 -> 0 | AC32: =AA32+AB32 -> 0 | AF32: =AD32+AE32 -> 0 | AI32: =AG32+AH32 -> 0
B33: Net Profit attributable to parents | C33: =C28+C32 -> 90.6 | D33: =D28+D32 -> 22.6 | E33: =E28+E32 -> 113.2 | F33: =F28+F32 -> 64.9 | G33: =G28+G32 -> 79.3 | H33: =H28+H32 -> 144.2 | I33: =I28+I32 -> 134 | J33: =J28+J32 -> 78.3 | ... AI33: =AI28+AI32 -> 195.17307
B35: EPS - continuing operations
B36: Basic | C36: =C33/C44*1000 -> 1.8191565 | D36: =D33/D44*1000 -> 0.4537541 | E36: =E33/E44*1000 -> 2.272786 | F36: =F33/F44*1000 -> 1.3007355 | G36: =G33/G44*1000 -> 1.583767 | H36: =H33/H44*1000 -> 2.8799395 | I36: =I33/I44*1000 -> 2.669389 | J36: =J33/J44*1000 -> 1.5523699 | ... AI36: =AI33/AI44*1000 -> 3.7960128
B37: Diluted | C37: =C33/C45*1000 -> 1.7266072 | D37: =D33/D45*1000 -> 0.43128959 | E37: =E33/E45*1000 -> 2.1602647 | F37: =F33/F45*1000 -> 1.2364702 | G37: =G33/G45*1000 -> 1.5062831 | H37: =H33/H45*1000 -> 2.7390419 | I37: =I33/I45*1000 -> 2.5977944 | J37: =J33/J45*1000 -> 1.5137133 | ... AI37: =AI33/AI45*1000 -> 3.7675913
B39: EPS
B40: Basic | C40: =C31/C44*1000 -> 1.6926589 | D40: =D31/D44*1000 -> 0.4537541 | E40: =E33/E44*1000 -> 2.272786 | F40: =F31/F44*1000 -> 1.3027397 | G40: =G31/G44*1000 -> 1.5817698 | H40: =H31/H44*1000 -> 2.8799395 | I40: =I31/I44*1000 -> 2.669389 | J40: =J31/J44*1000 -> 1.5563351 | K40: =K31/K44*1000 -> 4.2130089 | L40: =L31/L44*1000 -> 4.3932397 | M40: =M31/M44*1000 -> 1.3840602 | ... AI40: =AI31/AI44*1000 -> 3.7960128
B41: Diluted | C41: =C31/C45*1000 -> 1.6065451 | D41: =D31/D45*1000 -> 0.43128959 | E41: =E33/E45*1000 -> 2.1602647 | F41: =F31/F45*1000 -> 1.2383754 | G41: =G31/G45*1000 -> 1.5043836 | H41: =H31/H45*1000 -> 2.7390419 | I41: =I31/I45*1000 -> 2.5977944 | J41: =J31/J45*1000 -> 1.5175798 | K41: =K31/K45*1000 -> 4.1080981 | L41: =L31/L45*1000 -> 4.3151737 | M41: =M31/M45*1000 -> 1.3604365 | ... AI41: =AI31/AI45*1000 -> 3.7675913
B43: No. of shares
B44: Basic | C44: 49803.302 | D44: =E44 -> 49806.712 | E44: 49806.712 | F44: 49894.848 | G44: =H44 -> 50070.497 | H44: 50070.497 | I44: 50198.754 | J44: =K44 -> 50439.01 | K44: 50439.01 | L44: 50896.381 | M44: =N44 -> 50720.336 | N44: 50720.336 | O44: 50508.715 | P44: =Q44 -> 50719.758 | Q44: 50719.758 | R44: 50967.846 | S44: =T44 -> 51415.283 | T44: 51415.283 | U44: 51902.383 | V44: =S44 -> 51415.283 | W44: =T44 -> 51415.283 | X44: =U44 -> 51902.383 | Y44: =V44 -> 51415.283 | Z44: =W44 -> 51415.283 | AA44: =X44 -> 51902.383 | AB44: =Y44 -> 51415.283 | AC44: =Z44 -> 51415.283 | ... AI44: =AF44 -> 51415.283
B45: Diluted | C45: 52472.851 | D45: =E45 -> 52400.986 | E45: 52400.986 | F45: 52488.122 | G45: =H45 -> 52646.147 | H45: 52646.147 | I45: 51582.219 | J45: =K45 -> 51727.1 | K45: 51727.1 | L45: 51817.149 | M45: =N45 -> 51601.087 | N45: 51601.087 | O45: 50964.523 | P45: =Q45 -> 51119.23 | Q45: 51119.23 | R45: 51421.339 | S45: =T45 -> 51803.143 | T45: 51803.143 | U45: 52303.99 | V45: =S45 -> 51803.143 | W45: =T45 -> 51803.143 | X45: =U45 -> 52303.99 | Y45: =V45 -> 51803.143 | Z45: =W45 -> 51803.143 | AA45: =X45 -> 52303.99 | AB45: =Y45 -> 51803.143 | AC45: =Z45 -> 51803.143 | ... AI45: =AF45 -> 51803.143
B47: Balance Sheet | C47: =C3 -> H1'20 | D47: =D3 -> H2'20 | E47: =E3 -> FY20 | F47: =F3 -> H1'21 | G47: =G3 -> H2'21 | H47: =H3 -> FY21 | I47: =I3 -> H1'22 | J47: =J3 -> H2'22 | ... AI47: =AI3 -> FY30
B48: Goodwill | C48: 515.9 | D48: =E48 -> 498.2 | E48: 498.2 | F48: 500.1 | G48: =H48 -> 508.1 | H48: 508.1 | I48: 507 | J48: =K48 -> 511.9 | K48: 511.9 | L48: 512.9 | M48: =N48 -> 506.4 | N48: 506.4 | O48: 505.7 | P48: =Q48 -> 504.8 | Q48: 504.8 | R48: 503.8 | S48: =T48 -> 503.5 | T48: 503.5 | U48: 499 | V48: =U48 -> 499 | W48: =V48 -> 499 | X48: =W48 -> 499 | Y48: =X48 -> 499 | Z48: =Y48 -> 499 | AA48: =Z48 -> 499 | AB48: =AA48 -> 499 | AC48: =AB48 -> 499 | ... AI48: =AH48 -> 499
B49: Intangibles | D49: =E49 -> 0 | G49: =H49 -> 0 | J49: =K49 -> 0 | M49: =N49 -> 0 | P49: =Q49 -> 0 | S49: =T49 -> 0 | T49: 0
B50: Right-of-use assets | C50: 22.2 | D50: =E50 -> 20.8 | E50: 20.8 | F50: 16.7 | G50: =H50 -> 17.4 | H50: 17.4 | I50: 13.7 | J50: =K50 -> 23.4 | K50: 23.4 | L50: 20 | M50: =N50 -> 36.6 | N50: 36.6 | O50: 33.2 | P50: =Q50 -> 36.4 | Q50: 36.4 | R50: 31.6 | S50: =T50 -> 32.3 | T50: 32.3 | U50: 26.6 | V50: =U50 -> 26.6 | W50: =V50 -> 26.6 | X50: =W50 -> 26.6 | Y50: =X50 -> 26.6 | Z50: =W50 -> 26.6 | AA50: =Z50 -> 26.6 | AB50: =AA50 -> 26.6 | AC50: =Z50 -> 26.6 | AD50: =AC50 -> 26.6 | AE50: =AD50 -> 26.6 | AF50: =AC50 -> 26.6 | AG50: =AF50 -> 26.6 | AH50: =AG50 -> 26.6 | AI50: =AF50 -> 26.6
B51: PP&E | C51: 276.7 | D51: =E51 -> 310.1 | E51: 310.1 | F51: 309.3 | G51: =H51 -> 336.6 | H51: 336.6 | I51: 340.3 | J51: =K51 -> 368.9 | K51: 368.9 | L51: 381.7 | M51: =N51 -> 412.5 | N51: 412.5 | O51: 430.2 | P51: =Q51 -> 450.6 | Q51: 450.6 | R51: 450.4 | S51: =T51 -> 464.4 | T51: 464.4 | U51: 450.2 | V51: =Schedules!V15 -> 458.473 | W51: =Schedules!W15 -> 458.473 | X51: =Schedules!X15 -> 467.42138 | Y51: =Schedules!Y15 -> 475.70408 | Z51: =Schedules!Z15 -> 475.70408 | AA51: =Schedules!AA15 -> 484.67005 | AB51: =Schedules!AB15 -> 492.96518 | AC51: =Schedules!AC15 -> 492.96518 | ... AI51: =Schedules!AI15 -> 528.57854
B52: Investment in associates | C52: 1 | D52: =E52 -> 0.9 | E52: 0.9 | F52: 1.1 | G52: =H52 -> 1.7 | H52: 1.7 | I52: 1.8 | J52: =K52 -> 1.7 | K52: 1.7 | L52: 2 | M52: =N52 -> 1.5 | N52: 1.5 | O52: 1.7 | P52: =Q52 -> 1.5 | Q52: 1.5 | R52: 2.1 | S52: =T52 -> 1.9 | T52: 1.9 | U52: 1.4 | V52: =U52 -> 1.4 | W52: =V52 -> 1.4 | X52: =W52 -> 1.4 | Y52: =X52 -> 1.4 | Z52: =Y52 -> 1.4 | AA52: =Z52 -> 1.4 | AB52: =AA52 -> 1.4 | AC52: =AB52 -> 1.4 | ... AI52: =AH52 -> 1.4
B53: Other financial assets | C53: 96 | D53: =E53 -> 87.3 | E53: 87.3 | F53: 18.4 | G53: =H53 -> 26.6 | H53: 26.6 | I53: 37.1 | J53: =K53 -> 36.1 | K53: 36.1 | L53: 38.5 | M53: =N53 -> 16.3 | N53: 16.3 | O53: 16.2 | P53: =Q53 -> 18.3 | Q53: 18.3 | R53: 19.1 | S53: =T53 -> 16.8 | T53: 16.8 | U53: 19.3 | V53: =U53 -> 19.3 | W53: =V53 -> 19.3 | X53: =W53 -> 19.3 | Y53: =X53 -> 19.3 | Z53: =Y53 -> 19.3 | AA53: =Z53 -> 19.3 | AB53: =AA53 -> 19.3 | AC53: =AB53 -> 19.3 | ... AI53: =AH53 -> 19.3
B54: Deferred Taxation | C54: 20.5 | D54: =E54 -> 23.2 | E54: 23.2 | F54: 18.8 | G54: =H54 -> 29.5 | H54: 29.5 | I54: 29.5 | J54: =K54 -> 40.4 | K54: 40.4 | L54: 41.4 | M54: =N54 -> 31.2 | N54: 31.2 | O54: 36.4 | P54: =Q54 -> 25.6 | Q54: 25.6 | R54: 21.9 | S54: =T54 -> 21.3 | T54: 21.3 | U54: 18.8 | V54: =U54 -> 18.8 | W54: =V54 -> 18.8 | X54: =W54 -> 18.8 | Y54: =X54 -> 18.8 | Z54: =Y54 -> 18.8 | AA54: =Z54 -> 18.8 | AB54: =AA54 -> 18.8 | AC54: =AB54 -> 18.8 | ... AI54: =AH54 -> 18.8
B55: Non-current Assets | C55: =SUM(C48:C54) -> 932.3 | D55: =SUM(D48:D54)+0.1 -> 940.6 | E55: =SUM(E48:E54)+0.1 -> 940.6 | F55: =SUM(F48:F54) -> 864.4 | G55: =SUM(G48:G54) -> 919.9 | H55: =SUM(H48:H54) -> 919.9 | I55: =SUM(I48:I54)-0.1 -> 929.3 | J55: =SUM(J48:J54) -> 982.4 | K55: =SUM(K48:K54)+0.1 -> 982.5 | L55: =SUM(L48:L54)-0.1 -> 996.4 | M55: =SUM(M48:M54) -> 1004.5 | N55: =SUM(N48:N54) -> 1004.5 | O55: =SUM(O48:O54) -> 1023.4 | P55: =SUM(P48:P54) -> 1037.2 | Q55: =SUM(Q48:Q54) -> 1037.2 | R55: =SUM(R48:R54)+0.1 -> 1029 | S55: =SUM(S48:S54) -> 1040.2 | T55: =SUM(T48:T54) -> 1040.2 | U55: =SUM(U48:U54)+0.1 -> 1015.4 | V55: =SUM(V48:V54) -> 1023.573 | W55: =SUM(W48:W54) -> 1023.573 | X55: =SUM(X48:X54) -> 1032.5214 | Y55: =SUM(Y48:Y54) -> 1040.8041 | Z55: =SUM(Z48:Z54) -> 1040.8041 | AA55: =SUM(AA48:AA54) -> 1049.7701 | AB55: =SUM(AB48:AB54) -> 1058.0652 | AC55: =SUM(AC48:AC54) -> 1058.0652 | ... AI55: =SUM(AI48:AI54) -> 1093.6785
B57: Inventories | C57: 1269 | D57: =E57 -> 1363.9 | E57: 1363.9 | F57: 1378.6 | G57: =H57 -> 1492.5 | H57: 1492.5 | I57: 1512.6 | J57: =K57 -> 1615.5 | K57: 1615.5 | L57: 1647.6 | M57: =N57 -> 1815.8 | N57: 1815.8 | O57: 1839.3 | P57: =Q57 -> 1962.8 | Q57: 1962.8 | R57: 1973 | S57: =T57 -> 2105.6 | T57: 2105.6 | U57: 2102.2 | V57: =Schedules!V56 -> 2238.1986 | W57: =Schedules!W56 -> 2238.1986 | X57: =Schedules!X56 -> 2442.5781 | Y57: =Schedules!Y56 -> 2483.7893 | Z57: =Schedules!Z56 -> 2483.7893 | AA57: =Schedules!AA56 -> 2636.1135 | AB57: =Schedules!AB56 -> 2629.1153 | AC57: =Schedules!AC56 -> 2629.1153 | ... AI57: =Schedules!AI56 -> 2906.8681 | AL57: Working capital is tied up in aging inventory but it’s a good sign since prices are jcked up as invemory matures
B58: Trade and other receivables | C58: 249.6 | D58: =E58 -> 199.4 | E58: 199.4 | F58: 270.5 | G58: =H58 -> 158.1 | H58: 158.1 | I58: 286.4 | J58: =K58 -> 253.6 | K58: 253.6 | L58: 389.2 | M58: =N58 -> 268.7 | N58: 268.7 | O58: 364.2 | P58: =Q58 -> 238.2 | Q58: 238.2 | R58: 307.8 | S58: =T58 -> 187.5 | T58: 187.5 | U58: 254.6 | V58: =Schedules!V57 -> 334.18493 | W58: =Schedules!W57 -> 334.18493 | X58: =Schedules!X57 -> 348.93973 | Y58: =Schedules!Y57 -> 347.86964 | Z58: =Schedules!Z57 -> 347.86964 | AA58: =Schedules!AA57 -> 362.1035 | AB58: =Schedules!AB57 -> 361.14221 | AC58: =Schedules!AC57 -> 361.14221 | ... AI58: =Schedules!AI57 -> 399.29506
B59: Income tax receivables | C59: 1.5 | D59: =E59 -> 10.4 | E59: 10.4 | F59: 3.8 | G59: =H59 -> 4.9 | H59: 4.9 | I59: 3.5 | J59: =K59 -> 6.9 | K59: 6.9 | L59: 7.6 | M59: =N59 -> 5.3 | N59: 5.3 | O59: 16.5 | P59: =Q59 -> 29.8 | Q59: 29.8 | R59: 7.8 | S59: =T59 -> 2.7 | T59: 2.7 | U59: 4.7 | V59: =U59 -> 4.7 | W59: =V59 -> 4.7 | X59: =W59 -> 4.7 | Y59: =X59 -> 4.7 | Z59: =Y59 -> 4.7 | AA59: =Z59 -> 4.7 | AB59: =AA59 -> 4.7 | AC59: =AB59 -> 4.7 | ... AI59: =AH59 -> 4.7
B60: Derivatives | C60: 2.7 | D60: =E60 -> 5.1 | E60: 5.1 | F60: 9.5 | G60: =H60 -> 4.7 | H60: 4.7 | I60: 3.5 | J60: =K60 -> 3.8 | K60: 3.8 | L60: 9.6 | M60: =N60 -> 19 | N60: 19 | O60: 22.7 | P60: =Q60 -> 9.6 | Q60: 9.6 | R60: 7.3 | S60: =T60 -> 5.2 | T60: 5.2 | U60: 13.4 | V60: =U60 -> 13.4 | W60: =V60 -> 13.4 | X60: =W60 -> 13.4 | Y60: =X60 -> 13.4 | Z60: =Y60 -> 13.4 | AA60: =Z60 -> 13.4 | AB60: =AA60 -> 13.4 | AC60: =AB60 -> 13.4 | ... AI60: =AH60 -> 13.4
B61: Cash and cash equivalents | C61: 126 | D61: =E61 -> 269.4 | E61: 269.4 | F61: 89.6 | G61: =H61 -> 201 | H61: 201 | I61: 99.2 | J61: =K61 -> 116.3 | K61: 116.3 | L61: 95 | M61: =N61 -> 73.7 | N61: 73.7 | O61: 277.6 | P61: =Q61 -> 93 | Q61: 93 | R61: 48.6 | S61: =T61 -> 83.1 | T61: 83.1 | U61: 70.5 | V61: =V128 -> -142.74307 | W61: =W128 -> -142.64307 | X61: =X128 -> -256.528 | Y61: =Y128 -> -235.34887 | Z61: =Z128 -> -235.34887 | AA61: =AA128 -> -329.13869 | AB61: =AB128 -> -255.10272 | AC61: =AC128 -> -255.10272 | ... AI61: =AI128 -> -250.30208
B62: Current Assets | C62: =SUM(C57:C61) -> 1648.8 | D62: =SUM(D57:D61) -> 1848.2 | E62: =SUM(E57:E61) -> 1848.2 | F62: =SUM(F57:F61)-0.1 -> 1751.9 | G62: =SUM(G57:G61) -> 1861.2 | H62: =SUM(H57:H61) -> 1861.2 | I62: =SUM(I57:I61) -> 1905.2 | J62: =SUM(J57:J61) -> 1996.1 | K62: =SUM(K57:K61) -> 1996.1 | L62: =SUM(L57:L61) -> 2149 | M62: =SUM(M57:M61) -> 2182.5 | N62: =SUM(N57:N61) -> 2182.5 | ... S62: =SUM(S57:S61) -> 2384.1 | T62: =SUM(T57:T61)-0.1 -> 2384 | U62: =SUM(U57:U61) -> 2445.4 | V62: =SUM(V57:V61) -> 2447.7405 | W62: =SUM(W57:W61) -> 2447.8405 | X62: =SUM(X57:X61) -> 2553.0898 | Y62: =SUM(Y57:Y61) -> 2614.41 | Z62: =SUM(Z57:Z61) -> 2614.41 | AA62: =SUM(AA57:AA61) -> 2687.1783 | AB62: =SUM(AB57:AB61) -> 2753.2548 | ... AI62: =SUM(AI57:AI61) -> 3073.961
B63: Total Assets | C63: =C55+C62+0.1 -> 2581.2 | D63: =D55+D62 -> 2788.8 | E63: =E55+E62-0.1 -> 2788.7 | F63: =F55+F62 -> 2616.3 | G63: =G55+G62 -> 2781.1 | H63: =H55+H62 -> 2781.1 | I63: =I55+I62-0.1 -> 2834.4 | J63: =J55+J62 -> 2978.5 | K63: =K55+K62 -> 2978.6 | L63: =L55+L62 -> 3145.4 | M63: =M55+M62 -> 3187 | N63: =N55+N62 -> 3187 | O63: =O55+O62 -> 3543.7 | P63: =P55+P62+0.1 -> 3370.7 | Q63: =Q55+Q62+0.1 -> 3370.7 | R63: =R55+R62 -> 3373.5 | S63: =S55+S62-0.1 -> 3424.2 | T63: =T55+T62 -> 3424.2 | U63: =U55+U62-0.1 -> 3460.7 | V63: =V55+V62+0.1 -> 3471.4135 | W63: =W55+W62 -> 3471.4135 | X63: =X55+X62 -> 3585.6112 | Y63: =Y55+Y62 -> 3655.2141 | Z63: =Z55+Z62 -> 3655.2141 | AA63: =AA55+AA62 -> 3736.9483 | AB63: =AB55+AB62 -> 3811.32 | AC63: =AC55+AC62 -> 3811.32 | AD63: =AD55+AD62 -> 3901.1968 | ... AI63: =AI55+AI62 -> 4167.6396
B65: Share Capital | C65: 80.2 | D65: =E65 -> 80.2 | E65: 80.2 | F65: 80.8 | G65: =H65 -> 80.8 | H65: 80.8 | I65: 83 | J65: =K65 -> 81.8 | K65: 81.8 | L65: 82.8 | M65: =N65 -> 81.3 | N65: 81.3 | O65: 82 | P65: =Q65 -> 82 | Q65: 82 | R65: 83.5 | S65: =T65 -> 83.5 | T65: 83.5 | U65: 84.1 | V65: =U65 -> 84.1 | W65: =V65 -> 84.1 | X65: =W65 -> 84.1 | Y65: =X65 -> 84.1 | Z65: =Y65 -> 84.1 | AA65: =Z65 -> 84.1 | AB65: =AA65 -> 84.1 | AC65: =AB65 -> 84.1 | ... AI65: =AH65 -> 84.1
B66: Share Premium | C66: 795.1 | D66: =E66 -> 795.1 | E66: 795.1 | F66: 834.8 | G66: =H66 -> 834.8 | H66: 834.8 | I66: 981 | J66: =K66 -> 857.4 | K66: 857.4 | L66: 934.7 | M66: =N66 -> 773.6 | N66: 773.6 | O66: 823.6 | P66: =Q66 -> 823.6 | Q66: 823.6 | R66: 883.1 | S66: =T66 -> 883.1 | T66: 883.1 | U66: 901.5 | V66: =U66 -> 901.5 | W66: =V66 -> 901.5 | X66: =W66 -> 901.5 | Y66: =X66 -> 901.5 | Z66: =Y66 -> 901.5 | AA66: =Z66 -> 901.5 | AB66: =AA66 -> 901.5 | AC66: =AB66 -> 901.5 | ... AI66: =AH66 -> 901.5
B67: Treasury Shares | C67: -35 | D67: =E67 -> -30 | E67: -30 | F67: -27.5 | G67: =H67 -> -25.1 | H67: -25.1 | I67: -172.4 | J67: =K67 -> -58.7 | K67: -58.7 | L67: -120.2 | M67: =N67 -> -50.9 | N67: -50.9 | O67: -50.9 | P67: =Q67 -> -47 | Q67: -47 | R67: -47 | S67: =T67 -> -43.4 | T67: -43.4 | U67: -40.5 | V67: =U67 -> -40.5 | W67: =V67 -> -40.5 | X67: =W67 -> -40.5 | Y67: =X67 -> -40.5 | Z67: =Y67 -> -40.5 | AA67: =Z67 -> -40.5 | AB67: =AA67 -> -40.5 | AC67: =AB67 -> -40.5 | ... AI67: =AH67 -> -40.5
B68: Retained Earnings | C68: 519 | D68: =E68 -> 534.4 | E68: 534.4 | F68: 558.9 | G68: =H68 -> 635.3 | H68: 635.3 | I68: 666.9 | J68: =K68 -> 748.4 | K68: 748.4 | L68: 800 | M68: =N68 -> 920.7 | N68: 920.7 | O68: 889.7 | P68: =Q68 -> 954 | Q68: 954 | R68: 950.3 | S68: =T68 -> 972.1 | T68: 972.1 | U68: 957.8 | V68: =Schedules!V49 -> 1035.0346 | W68: =Schedules!W49 -> 1035.0346 | X68: =Schedules!X49 -> 1116.9112 | Y68: =Schedules!Y49 -> 1198.4317 | Z68: =Schedules!Z49 -> 1198.4317 | AA68: =Schedules!AA49 -> 1284.7978 | AB68: =Schedules!AB49 -> 1370.8651 | AC68: =Schedules!AC49 -> 1370.8651 | ... AI68: =Schedules!AI49 -> 1747.8337
B69: Translation differences | C69: 23 | D69: =E69 -> 22.7 | E69: 22.7 | F69: 17.8 | G69: =H69 -> 22.6 | H69: 22.6 | I69: 26.3 | J69: =K69 -> 31.8 | K69: 31.8 | L69: 41.9 | M69: =N69 -> 29.8 | N69: 29.8 | O69: 33.3 | P69: =Q69 -> 32.7 | Q69: 32.7 | R69: 29.9 | S69: =T69 -> 34.4 | T69: 34.4 | U69: 20.7 | V69: =U69 -> 20.7 | W69: =V69 -> 20.7 | X69: =W69 -> 20.7 | Y69: =X69 -> 20.7 | Z69: =Y69 -> 20.7 | AA69: =Z69 -> 20.7 | AB69: =AA69 -> 20.7 | AC69: =AB69 -> 20.7 | ... AI69: =AH69 -> 20.7
B70: Equity - parents | C70: =SUM(C65:C69)+0.1 -> 1382.4 | D70: =SUM(D65:D69) -> 1402.4 | E70: =SUM(E65:E69) -> 1402.4 | F70: =SUM(F65:F69)+0.1 -> 1464.9 | G70: =SUM(G65:G69) -> 1548.4 | H70: =SUM(H65:H69) -> 1548.4 | I70: =SUM(I65:I69) -> 1584.8 | J70: =SUM(J65:J69) -> 1660.7 | K70: =SUM(K65:K69) -> 1660.7 | L70: =SUM(L65:L69) -> 1739.2 | M70: =SUM(M65:M69) -> 1754.5 | N70: =SUM(N65:N69)-0.1 -> 1754.4 | O70: =SUM(O65:O69) -> 1777.7 | P70: =SUM(P65:P69) -> 1845.3 | Q70: =SUM(Q65:Q69)-0.1 -> 1845.2 | R70: =SUM(R65:R69) -> 1899.8 | S70: =SUM(S65:S69) -> 1929.7 | T70: =SUM(T65:T69) -> 1929.7 | U70: =SUM(U65:U69) -> 1923.6 | V70: =SUM(V65:V69) -> 2000.8346 | W70: =SUM(W65:W69) -> 2000.8346 | X70: =SUM(X65:X69) -> 2082.7112 | Y70: =SUM(Y65:Y69) -> 2164.2317 | ... AI70: =SUM(AI65:AI69) -> 2713.6337
B71: Non-controliing interests | C71: 1 | D71: =E71 -> 0.9 | E71: 0.9 | F71: 0.8 | G71: =H71 -> 0.8 | H71: 0.8 | I71: 0.8 | J71: =K71 -> 1 | K71: 1 | L71: 1 | M71: =N71 -> 0.7 | N71: 0.7 | O71: 0.5 | P71: =Q71 -> 0.3 | Q71: 0.3 | R71: 0 | S71: =T71 -> -0.4 | T71: -0.4 | U71: 0.9 | V71: =U71 -> 0.9 | W71: =V71 -> 0.9 | X71: =W71 -> 0.9 | Y71: =X71 -> 0.9 | Z71: =Y71 -> 0.9 | AA71: =Z71 -> 0.9 | AB71: =AA71 -> 0.9 | AC71: =AB71 -> 0.9 | ... AI71: =AH71 -> 0.9
B72: Equity | C72: =C70+C71 -> 1383.4 | D72: =D70+D71 -> 1403.3 | E72: =E70+E71 -> 1403.3 | F72: =F70+F71 -> 1465.7 | G72: =G70+G71 -> 1549.2 | H72: =H70+H71 -> 1549.2 | I72: =I70+I71-0.1 -> 1585.5 | J72: =J70+J71 -> 1661.7 | K72: =K70+K71 -> 1661.7 | L72: =L70+L71 -> 1740.2 | M72: =M70+M71 -> 1755.2 | N72: =N70+N71 -> 1755.1 | O72: =O70+O71 -> 1778.2 | P72: =P70+P71 -> 1845.6 | Q72: =Q70+Q71 -> 1845.5 | ... AI72: =AI70+AI71 -> 2714.5337
B74: Long-term financial debt | C74: 521.6 | D74: =E74 -> 452 | E74: 452 | F74: 449.7 | G74: =H74 -> 423.8 | H74: 423.8 | I74: 334.7 | J74: =K74 -> 363.9 | K74: 363.9 | L74: 319.3 | M74: =N74 -> 325.1 | N74: 325.1 | O74: 691.5 | P74: =Q74 -> 514.9 | Q74: 514.9 | R74: 511.4 | S74: =T74 -> 562.5 | T74: 562.5 | U74: 587.3 | V74: =Schedules!V70 -> 577.3 | W74: =Schedules!W70 -> 577.3 | X74: =Schedules!X70 -> 557.3 | Y74: =Schedules!Y70 -> 547.3 | Z74: =Schedules!Z70 -> 547.3 | AA74: =Schedules!AA70 -> 527.3 | AB74: =Schedules!AB70 -> 517.3 | AC74: =Schedules!AC70 -> 517.3 | ... AI74: =Schedules!AI70 -> 457.3
B75: Provision for employee benefits | C75: 32.7 | D75: =E75 -> 30.3 | E75: 30.3 | F75: 29.8 | G75: =H75 -> 29.1 | H75: 29.1 | I75: 29.4 | J75: =K75 -> 26.4 | K75: 26.4 | L75: 24.6 | M75: =N75 -> 19 | N75: 19 | O75: 19.4 | P75: =Q75 -> 20.2 | Q75: 20.2 | R75: 20.5 | S75: =T75 -> 18 | T75: 18 | U75: 18 | V75: =U75 -> 18 | W75: =V75 -> 18 | X75: =W75 -> 18 | Y75: =X75 -> 18 | Z75: =Y75 -> 18 | AA75: =Z75 -> 18 | AB75: =AA75 -> 18 | AC75: =AB75 -> 18 | ... AI75: =AH75 -> 18
B76: Long-term provisions | C76: 2 | D76: =E76 -> 2.2 | E76: 2.2 | F76: 1.9 | G76: =H76 -> 2.1 | H76: 2.1 | I76: 3.4 | J76: =K76 -> 3.3 | K76: 3.3 | L76: 3.1 | M76: =N76 -> 1.1 | N76: 1.1 | O76: 0.8 | P76: =Q76 -> 0.7 | Q76: 0.7 | R76: 0.8 | S76: =T76 -> 0.7 | T76: 0.7 | U76: 0.6 | V76: =U76 -> 0.6 | W76: =V76 -> 0.6 | X76: =W76 -> 0.6 | Y76: =X76 -> 0.6 | Z76: =Y76 -> 0.6 | AA76: =Z76 -> 0.6 | AB76: =AA76 -> 0.6 | AC76: =AB76 -> 0.6 | ... AI76: =AH76 -> 0.6
B77: Deferred Taxation | C77: 47.3 | D77: =E77 -> 59.4 | E77: 59.4 | F77: 44.4 | G77: =H77 -> 57.1 | H77: 57.1 | I77: 41.1 | J77: =K77 -> 56 | K77: 56 | L77: 42.2 | M77: =N77 -> 51.3 | N77: 51.3 | O77: 46.8 | P77: =Q77 -> 54.5 | Q77: 54.5 | R77: 52.7 | S77: =T77 -> 48.7 | T77: 48.7 | U77: 54 | V77: =U77 -> 54 | W77: =V77 -> 54 | X77: =W77 -> 54 | Y77: =X77 -> 54 | Z77: =Y77 -> 54 | AA77: =Z77 -> 54 | AB77: =AA77 -> 54 | AC77: =AB77 -> 54 | ... AI77: =AH77 -> 54
B78: Non-Current Liabilities | C78: =SUM(C74:C77) -> 603.6 | D78: =SUM(D74:D77) -> 543.9 | E78: =SUM(E74:E77) -> 543.9 | F78: =SUM(F74:F77)-0.1 -> 525.7 | G78: =SUM(G74:G77) -> 512.1 | H78: =SUM(H74:H77) -> 512.1 | I78: =SUM(I74:I77)+0.1 -> 408.7 | J78: =SUM(J74:J77) -> 449.6 | K78: =SUM(K74:K77) -> 449.6 | L78: =SUM(L74:L77)+0.1 -> 389.3 | M78: =SUM(M74:M77) -> 396.5 | N78: =SUM(N74:N77) -> 396.5 | O78: =SUM(O74:O77) -> 758.5 | P78: =SUM(P74:P77) -> 590.3 | Q78: =SUM(Q74:Q77) -> 590.3 | R78: =SUM(R74:R77) -> 585.4 | S78: =SUM(S74:S77) -> 629.9 | T78: =SUM(T74:T77) -> 629.9 | ... AI78: =SUM(AI74:AI77) -> 529.9
B80: Short-term debt | C80: 63.3 | D80: =E80 -> 268.3 | E80: 268.3 | F80: 67.2 | G80: =H80 -> 91.5 | H80: 91.5 | I80: 64.1 | J80: =K80 -> 105.7 | K80: 105.7 | L80: 123.9 | M80: =N80 -> 285.3 | N80: 285.3 | O80: 176.6 | P80: =Q80 -> 227.8 | Q80: 227.8 | R80: 181.5 | S80: =T80 -> 196.1 | T80: 196.1 | U80: 170 | V80: =U80 -> 170 | W80: =V80 -> 170 | X80: =W80 -> 170 | Y80: =X80 -> 170 | Z80: =Y80 -> 170 | AA80: =Z80 -> 170 | AB80: =AA80 -> 170 | AC80: =AB80 -> 170 | ... AI80: =AH80 -> 170
B81: Trade and Oher payables | C81: 474.7 | D81: =E81 -> 534.4 | E81: 534.4 | F81: 498.7 | G81: =H81 -> 586.1 | H81: 586.1 | I81: 600.9 | J81: =K81 -> 683.3 | K81: 683.3 | L81: 647.9 | M81: =N81 -> 717.5 | N81: 717.5 | O81: 647.1 | P81: =Q81 -> 676.3 | Q81: 676.3 | R81: 634.1 | S81: =T81 -> 639.1 | T81: 639.1 | U81: 629.5 | V81: =Schedules!V58 -> 572.97885 | W81: =Schedules!W58 -> 572.97885 | X81: =Schedules!X58 -> 625.29999 | Y81: =Schedules!Y58 -> 623.3824 | Z81: =Schedules!Z58 -> 623.3824 | AA81: =Schedules!AA58 -> 638.75057 | AB81: =Schedules!AB58 -> 637.05486 | AC81: =Schedules!AC58 -> 637.05486 | ... AI81: =Schedules!AI58 -> 676.40584
B82: Dividend Payable | C82: 0 | D82: =E82 -> 0 | E82: 0 | F82: 9.6 | G82: =H82 -> 0 | H82: 0 | I82: 93.7 | J82: =K82 -> 0 | K82: 0 | L82: 111 | M82: =N82 -> 0 | N82: 0 | O82: 152.7 | P82: =Q82 -> 0 | Q82: 0 | R82: 41 | S82: =T82 -> 0 | T82: 0 | U82: 58.8 | V82: =U82 -> 58.8 | W82: =V82 -> 58.8 | X82: =W82 -> 58.8 | Y82: =X82 -> 58.8 | Z82: =Y82 -> 58.8 | AA82: =Z82 -> 58.8 | AB82: =AA82 -> 58.8 | AC82: =AB82 -> 58.8 | ... AI82: =AH82 -> 58.8
B83: Income Tax payables | C83: 39 | D83: =E83 -> 18.7 | E83: 18.7 | F83: 37.9 | G83: =H83 -> 27.4 | H83: 27.4 | I83: 50.4 | J83: =K83 -> 46.6 | K83: 46.6 | L83: 61.8 | M83: =N83 -> 23 | N83: 23 | O83: 24.3 | P83: =Q83 -> 19.3 | Q83: 19.3 | R83: 28.5 | S83: =T83 -> 22.2 | T83: 22.2 | U83: 15.5 | V83: =U83 -> 15.5 | W83: =V83 -> 15.5 | X83: =W83 -> 15.5 | Y83: =X83 -> 15.5 | Z83: =Y83 -> 15.5 | AA83: =Z83 -> 15.5 | AB83: =AA83 -> 15.5 | AC83: =AB83 -> 15.5 | ... AI83: =AH83 -> 15.5
B84: Short-term provisions | C84: 1 | D84: =E84 -> 11.5 | E84: 11.5 | F84: 9.8 | G84: =H84 -> 7.7 | H84: 7.7 | I84: 20.3 | J84: =K84 -> 17.9 | K84: 17.9 | L84: 18.7 | M84: =N84 -> 4 | N84: 4 | O84: 1.7 | P84: =Q84 -> 9.8 | Q84: 9.8 | R84: 2.6 | S84: =T84 -> 6.7 | T84: 6.7 | U84: 2 | V84: =U84 -> 2 | W84: =V84 -> 2 | X84: =W84 -> 2 | Y84: =X84 -> 2 | Z84: =Y84 -> 2 | AA84: =Z84 -> 2 | AB84: =AA84 -> 2 | AC84: =AB84 -> 2 | ... AI84: =AH84 -> 2
B85: Derivatives | C85: 16.2 | D85: =E85 -> 8.7 | E85: 8.7 | F85: 1.8 | G85: =H85 -> 7.1 | H85: 7.1 | I85: 10.8 | J85: =K85 -> 13.7 | K85: 13.7 | L85: 52.6 | M85: =N85 -> 5.5 | N85: 5.5 | O85: 4.5 | P85: =Q85 -> 1.7 | Q85: 1.7 | R85: 0.7 | S85: =T85 -> 0.9 | T85: 0.9 | U85: 0.5 | V85: =U85 -> 0.5 | W85: =V85 -> 0.5 | X85: =W85 -> 0.5 | Y85: =X85 -> 0.5 | Z85: =Y85 -> 0.5 | AA85: =Z85 -> 0.5 | AB85: =AA85 -> 0.5 | AC85: =AB85 -> 0.5 | ... AI85: =AH85 -> 0.5
B86: Current Liabilities | C86: =SUM(C80:C85) -> 594.2 | D86: =SUM(D80:D85) -> 841.6 | E86: =SUM(E80:E85)-0.1 -> 841.5 | F86: =SUM(F80:F85) -> 625 | G86: =SUM(G80:G85) -> 719.8 | H86: =SUM(H80:H85) -> 719.8 | I86: =SUM(I80:I85) -> 840.2 | J86: =SUM(J80:J85) -> 867.2 | K86: =SUM(K80:K85) -> 867.2 | L86: =SUM(L80:L85) -> 1015.9 | M86: =SUM(M80:M85) -> 1035.3 | ... AI86: =SUM(AI80:AI85) -> 923.20584
B87: Total Equity & Liabilities | C87: =C72+C78+C86 -> 2581.2 | D87: =D72+D78+D86 -> 2788.8 | E87: =E72+E78+E86 -> 2788.7 | F87: =F72+F78+F86-0.1 -> 2616.3 | G87: =G72+G78+G86 -> 2781.1 | H87: =H72+H78+H86 -> 2781.1 | I87: =I72+I78+I86 -> 2834.4 | J87: =J72+J78+J86 -> 2978.5 | K87: =K72+K78+K86+0.1 -> 2978.6 | L87: =L72+L78+L86 -> 3145.4 | M87: =M72+M78+M86 -> 3187 | N87: =N72+N78+N86+0.1 -> 3187 | O87: =O72+O78+O86+0.1 -> 3543.7 | P87: =P72+P78+P86-0.1 -> 3370.7 | Q87: =Q72+Q78+Q86 -> 3370.7 | R87: =R72+R78+R86-0.1 -> 3373.5 | S87: =S72+S78+S86 -> 3424.2 | T87: =T72+T78+T86 -> 3424.2 | U87: =U72+U78+U86 -> 3460.7 | V87: =V72+V78+V86 -> 3471.4135 | W87: =W72+W78+W86 -> 3471.4135 | X87: =X72+X78+X86 -> 3585.6112 | Y87: =Y72+Y78+Y86 -> 3655.2141 | Z87: =Z72+Z78+Z86 -> 3655.2141 | ... AI87: =AI72+AI78+AI86 -> 4167.6396
B89: Check | C89: =IF(C63=C87,"OK",C63-C87) -> OK | D89: =IF(D63=D87,"OK",D63-D87) -> OK | E89: =IF(E63=E87,"OK",E63-E87) -> OK | F89: =IF(F63=F87,"OK",F63-F87) -> OK | G89: =IF(G63=G87,"OK",G63-G87) -> OK | H89: =IF(H63=H87,"OK",H63-H87) -> OK | I89: =IF(I63=I87,"OK",I63-I87) -> OK | J89: =IF(J63=J87,"OK",J63-J87) -> OK | ... AI89: =IF(AI63=AI87,"OK",AI63-AI87) -> OK
B91: Cash Flow | C91: =C47 -> H1'20 | D91: =D47 -> H2'20 | E91: =E47 -> FY20 | F91: =F47 -> H1'21 | G91: =G47 -> H2'21 | H91: =H47 -> FY21 | I91: =I47 -> H1'22 | J91: =J47 -> H2'22 | ... AI91: =AI47 -> FY30
B92: Current Operating Profit | C92: 138.3 | D92: =E92-C92 -> 76.8 | E92: 215.1 | F92: 106.2 | G92: =H92-F92 -> 129.9 | H92: 236.1 | I92: 212.9 | J92: =K92-I92 -> 121.5 | K92: 334.4 | L92: 319.3 | M92: =N92-L92 -> 110.3 | N92: 429.6 | O92: 169.1 | P92: =Q92-O92 -> 135.3 | Q92: 304.4 | R92: =R11 -> 147.3 | S92: =T92-R92 -> 69.7 | T92: 217 | U92: =U11 -> 108.7 | V92: =V11 -> 121.555 | W92: =W11 -> 230.255 | X92: =X11 -> 127.363 | Y92: =Y11 -> 126.58184 | Z92: =Z11 -> 253.94484 | AA92: =AA11 -> 132.52988 | AB92: =AB11 -> 131.82622 | ... AI92: =AI11 -> 291.4854
B93: D&A | C93: 15.8 | D93: =E93-C93 -> 17.6 | E93: 33.4 | F93: 17 | G93: =H93-F93 -> 17 | H93: 34 | I93: 18 | J93: =K93-I93 -> 22 | K93: 40 | L93: 19.1 | M93: =N93-L93 -> 21.9 | N93: 41 | O93: 21.6 | P93: =Q93-O93 -> 23.5 | Q93: 45.1 | R93: 22.9 | S93: =T93-R93 -> 23.9 | T93: 46.8 | U93: 23.2 | V93: =V16 -> 16.038 | W93: =W16 -> 39.238 | X93: =X16 -> 16.52422 | Y93: =Y16 -> 17.033672 | Z93: =Z16 -> 33.557892 | AA93: =AA16 -> 17.539999 | AB93: =AB16 -> 18.070119 | AC93: =AC16 -> 35.610118 | ... AI93: =AI16 -> 39.97877
B94: Share based payments | C94: 1.7 | D94: =E94-C94 -> 1.9 | E94: 3.6 | F94: 0.7 | G94: =H94-F94 -> 1.4 | H94: 2.1 | I94: 4.5 | J94: =K94-I94 -> 3.8 | K94: 8.3 | L94: 5.4 | M94: =N94-L94 -> 4.7 | N94: 10.1 | O94: 4.7 | P94: =Q94-O94 -> 1.5 | Q94: 6.2 | R94: 4.1 | S94: =T94-R94 -> 0 | T94: 4.1 | U94: 0.8 | W94: =U94+V94 -> 0.8 | Z94: =X94+Y94 -> 0 | AC94: =AA94+AB94 -> 0 | AF94: =AD94+AE94 -> 0 | AI94: =AG94+AH94 -> 0
B95: Dividends received | C95: 0 | D95: =E95-C95 -> 0.3 | E95: 0.3 | F95: 0 | G95: =H95-F95 -> 0.3 | H95: 0.3 | I95: 0 | J95: =K95-I95 -> 0.7 | K95: 0.7 | L95: 0 | M95: =N95-L95 -> 0.9 | N95: 0.9 | O95: 0 | P95: =Q95-O95 -> 0.6 | Q95: 0.6 | R95: 0 | S95: =T95-R95 -> 0 | T95: 0 | U95: 0.5 | W95: =U95+V95 -> 0.5 | Z95: =X95+Y95 -> 0 | AC95: =AA95+AB95 -> 0 | AF95: =AD95+AE95 -> 0 | AI95: =AG95+AH95 -> 0
B96: EBITDA | C96: =SUM(C92:C95) -> 155.8 | D96: =SUM(D92:D95) -> 96.6 | E96: =SUM(E92:E95) -> 252.4 | F96: =SUM(F92:F95)-0.1 -> 123.8 | G96: =SUM(G92:G95) -> 148.6 | H96: =SUM(H92:H95) -> 272.5 | I96: =SUM(I92:I95) -> 235.4 | J96: =SUM(J92:J95) -> 148 | K96: =SUM(K92:K95) -> 383.4 | L96: =SUM(L92:L95) -> 343.8 | M96: =SUM(M92:M95) -> 137.8 | N96: =SUM(N92:N95) -> 481.6 | ... P96: =SUM(P92:P95) -> 160.9 | Q96: =SUM(Q92:Q95)+0.1 -> 356.4 | R96: =SUM(R92:R95) -> 174.3 | S96: =SUM(S92:S95) -> 93.6 | T96: =SUM(T92:T95)-0.1 -> 267.8 | U96: =SUM(U92:U95) -> 133.2 | V96: =SUM(V92:V95) -> 137.593 | W96: =SUM(W92:W95) -> 270.793 | X96: =SUM(X92:X95) -> 143.88722 | Y96: =SUM(Y92:Y95) -> 143.61551 | Z96: =SUM(Z92:Z95) -> 287.50273 | AA96: =SUM(AA92:AA95) -> 150.06988 | AB96: =SUM(AB92:AB95) -> 149.89634 | ... AI96: =SUM(AI92:AI95) -> 331.46417
B97: Changes in inventories | C97: -32.6 | D97: =E97-C97 -> -96.1 | E97: -128.7 | F97: -9.6 | G97: =H97-F97 -> -90.7 | H97: -100.3 | I97: -15.4 | J97: =K97-I97 -> -102.6 | K97: -118 | L97: -25.3 | M97: =N97-L97 -> -177.5 | N97: -202.8 | O97: -22.8 | P97: =Q97-O97 -> -126.3 | Q97: -149.1 | R97: -13.7 | S97: =T97-R97 -> -122.7 | T97: -136.4 | U97: -7.9 | V97: =U57-V57 -> -135.99863 | W97: =U97+V97 -> -143.89863 | X97: =W57-X57 -> -204.37945 | Y97: =X57-Y57 -> -41.211175 | Z97: =X97+Y97 -> -245.59063 | AA97: =Z57-AA57 -> -152.3242 | AB97: =AA57-AB57 -> 6.9981725 | AC97: =AA97+AB97 -> -145.32603 | AD97: =AC57-AD57 -> -121.51252 | AE97: =AD57-AE57 -> 6.0907003 | AF97: =AD97+AE97 -> -115.42182 | AG97: =AF57-AG57 -> -158.78912 | AH97: =AG57-AH57 -> -3.5418313 | AI97: =AG97+AH97 -> -162.33095
B98: Changes in Trade receivables | C98: 5.1 | D98: =E98-C98 -> 68.9 | E98: 74 | F98: -31.3 | G98: =H98-F98 -> 40.6 | H98: 9.3 | I98: -100.8 | J98: =K98-I98 -> 62.3 | K98: -38.5 | L98: -107.5 | M98: =N98-L98 -> 90.8 | N98: -16.7 | O98: -90.5 | P98: =Q98-O98 -> 95.4 | Q98: 4.9 | R98: -54.5 | S98: =T98-R98 -> 85 | T98: 30.5 | U98: -59.6 | V98: =U58-V58 -> -79.584932 | W98: =U98+V98 -> -139.18493 | X98: =W58-X58 -> -14.754795 | Y98: =X58-Y58 -> 1.0700822 | Z98: =X98+Y98 -> -13.684712 | AA98: =Z58-AA58 -> -14.233853 | AB98: =AA58-AB58 -> 0.96128743 | AC98: =AA98+AB98 -> -13.272566 | AD98: =AC58-AD58 -> -16.691281 | AE98: =AD58-AE58 -> 0.83663465 | AF98: =AD98+AE98 -> -15.854646 | AG98: =AF58-AG58 -> -21.811693 | AH98: =AG58-AH58 -> -0.48651529 | AI98: =AG98+AH98 -> -22.298208
B99: Changes in Trade Payables | C99: -18 | D99: =E99-C99 -> 13.5 | E99: -4.5 | F99: 13.3 | G99: =H99-F99 -> 66.4 | H99: 79.7 | I99: 29 | J99: =K99-I99 -> 32.6 | K99: 61.6 | L99: -23.1 | M99: =N99-L99 -> 60.4 | N99: 37.3 | O99: -23.7 | P99: =Q99-O99 -> 15.4 | Q99: -8.3 | R99: -30.9 | S99: =T99-R99 -> -5.9 | T99: -36.8 | U99: 13.8 | V99: =V81-U81 -> -56.521151 | W99: =U99+V99 -> -42.721151 | X99: =X81-W81 -> 52.32114 | Y99: =Y81-X81 -> -1.9175873 | Z99: =X99+Y99 -> 50.403552 | AA99: =AA81-Z81 -> 15.368167 | AB99: =AB81-AA81 -> -1.695711 | AC99: =AA99+AB99 -> 13.672456 | AD99: =AD81-AC81 -> 18.864081 | AE99: =AE81-AD81 -> -1.4523978 | AF99: =AD99+AE99 -> 17.411683 | AG99: =AG81-AF81 -> 21.11514 | AH99: =AH81-AG81 -> 0.82415691 | AI99: =AG99+AH99 -> 21.939296
B100: Changes in other receivables ad payables | C100: -29 | D100: =E100-C100 -> 15.9 | E100: -13.1 | F100: -13.6 | G100: =H100-F100 -> 12 | H100: -1.6 | I100: -41.1 | J100: =K100-I100 -> -4.3 | K100: -45.4 | L100: -54.9 | M100: =N100-L100 -> 42.4 | N100: -12.5 | O100: -35.9 | P100: =Q100-O100 -> 44.2 | Q100: 8.3 | R100: -19.6 | S100: =T100-R100 -> 30.6 | T100: 11 | U100: -16.2 | W100: =U100+V100 -> -16.2 | Z100: =X100+Y100 -> 0 | AC100: =AA100+AB100 -> 0 | AF100: =AD100+AE100 -> 0 | AI100: =AG100+AH100 -> 0
B101: Change in W.C.R | C101: =SUM(C97:C100)-0.1 -> -74.6 | D101: =SUM(D97:D100) -> 2.2 | E101: =SUM(E97:E100) -> -72.3 | F101: =SUM(F97:F100)+0.1 -> -41.1 | G101: =SUM(G97:G100) -> 28.3 | H101: =SUM(H97:H100) -> -12.9 | I101: =SUM(I97:I100) -> -128.3 | J101: =SUM(J97:J100) -> -12 | K101: =SUM(K97:K100)-0.1 -> -140.4 | L101: =SUM(L97:L100) -> -210.8 | M101: =SUM(M97:M100) -> 16.1 | N101: =SUM(N97:N100)+0.1 -> -194.6 | O101: =SUM(O97:O100) -> -172.9 | P101: =SUM(P97:P100) -> 28.7 | Q101: =SUM(Q97:Q100)+0.1 -> -144.1 | R101: =SUM(R97:R100) -> -118.7 | S101: =SUM(S97:S100) -> -13 | T101: =SUM(T97:T100) -> -131.7 | U101: =SUM(U97:U100)-0.1 -> -70 | V101: =SUM(V97:V100) -> -272.10471 | W101: =SUM(W97:W100) -> -342.00471 | X101: =SUM(X97:X100) -> -166.81311 | Y101: =SUM(Y97:Y100) -> -42.05868 | Z101: =SUM(Z97:Z100) -> -208.87179 | AA101: =SUM(AA97:AA100) -> -151.18989 | AB101: =SUM(AB97:AB100) -> 6.2637489 | AC101: =SUM(AC97:AC100) -> -144.92614 | ... AI101: =SUM(AI97:AI100) -> -162.68987
B102: Net cash fo from operations | C102: =C96+C101 -> 81.2 | D102: =D96+D101 -> 98.8 | E102: =E96+E101+0.1 -> 180.2 | F102: =F96+F101+0.1 -> 82.8 | G102: =G96+G101 -> 176.9 | H102: =H96+H101 -> 259.6 | I102: =I96+I101 -> 107.1 | J102: =J96+J101 -> 136 | K102: =K96+K101 -> 243 | L102: =L96+L101 -> 133 | M102: =M96+M101 -> 153.9 | N102: =N96+N101 -> 287 | ... AI102: =AI96+AI101 -> 168.7743
B103: Net cash flow in relation to other non-current income/(expenses) | C103: 0 | D103: =E103-C103 -> -0.7 | E103: -0.7 | F103: 0 | G103: =H103-F103 -> 0 | H103: 0 | I103: 0 | J103: =K103-I103 -> 0 | K103: 0 | L103: -2.9 | M103: =N103-L103 -> -6.3 | N103: -9.2 | O103: 0 | P103: =Q103-O103 -> -4.5 | Q103: -4.5 | R103: -6.2 | S103: =T103-R103 -> -2.2 | T103: -8.4 | U103: -3.8 | W103: =U103+V103 -> -3.8 | Z103: =X103+Y103 -> 0 | AC103: =AA103+AB103 -> 0 | AF103: =AD103+AE103 -> 0 | AI103: =AG103+AH103 -> 0
B104: Net cash flow in relation to financial income/(expenses) | C104: -8.5 | D104: =E104-C104 -> -4.6 | E104: -13.1 | F104: -7.3 | G104: =H104-F104 -> -2.7 | H104: -10 | I104: -6.5 | J104: =K104-I104 -> -2.2 | K104: -8.7 | L104: -4.7 | M104: =N104-L104 -> -8.6 | N104: -13.3 | O104: -13.9 | P104: =Q104-O104 -> -10.8 | Q104: -24.7 | R104: -28.8 | S104: =T104-R104 -> -8.6 | T104: -37.4 | U104: -28.8 | V104: =-V21 -> -17.319 | W104: =U104+V104 -> -46.119 | X104: =-X21 -> -16.719 | Y104: =-Y21 -> -16.419 | Z104: =X104+Y104 -> -33.138 | AA104: =-AA21 -> -15.819 | AB104: =-AB21 -> -15.519 | AC104: =AA104+AB104 -> -31.338 | AD104: =-AD21 -> -14.919 | AE104: =-AE21 -> -14.619 | AF104: =AD104+AE104 -> -29.538 | AG104: =-AG21 -> -14.019 | AH104: =-AH21 -> -13.719 | AI104: =AG104+AH104 -> -27.738
B105: Net cash flow in relation to income ta | C105: -41.6 | D105: =E105-C105 -> -44.2 | E105: -85.8 | F105: -22.4 | G105: =H105-F105 -> -50.1 | H105: -72.5 | I105: -47.3 | J105: =K105-I105 -> -42.3 | K105: -89.6 | L105: -77.2 | M105: =N105-L105 -> -63.2 | N105: -140.4 | O105: -61.8 | P105: =Q105-O105 -> -26.6 | Q105: -88.4 | R105: -1.4 | S105: =T105-R105 -> -18.5 | T105: -19.9 | U105: -27.5 | V105: =-V25 -> -27.10136 | W105: =U105+V105 -> -54.60136 | X105: =-X25 -> -28.76744 | Y105: =-Y25 -> -28.642338 | Z105: =X105+Y105 -> -57.409778 | AA105: =-AA25 -> -30.344829 | AB105: =-AB25 -> -30.239877 | AC105: =AA105+AB105 -> -60.584705 | AD105: =-AD25 -> -31.977458 | AE105: =-AE25 -> -31.896665 | AF105: =AD105+AE105 -> -63.874123 | AG105: =-AG25 -> -34.201991 | AH105: =-AH25 -> -34.372332 | AI105: =AG105+AH105 -> -68.574323
B106: Other operating cash flows | C106: =SUM(C103:C105) -> -50.1 | D106: =SUM(D103:D105) -> -49.5 | E106: =SUM(E103:E105)-0.1 -> -99.7 | F106: =SUM(F103:F105) -> -29.7 | G106: =SUM(G103:G105) -> -52.8 | H106: =SUM(H103:H105) -> -82.5 | I106: =SUM(I103:I105) -> -53.8 | J106: =SUM(J103:J105) -> -44.5 | K106: =SUM(K103:K105) -> -98.3 | L106: =SUM(L103:L105) -> -84.8 | M106: =SUM(M103:M105) -> -78.1 | N106: =SUM(N103:N105)+0.1 -> -162.8 | O106: =SUM(O103:O105) -> -75.7 | P106: =SUM(P103:P105) -> -41.9 | Q106: =SUM(Q103:Q105)+0.1 -> -117.5 | R106: =SUM(R103:R105) -> -36.4 | S106: =SUM(S103:S105) -> -29.3 | T106: =SUM(T103:T105) -> -65.7 | U106: =SUM(U103:U105) -> -60.1 | V106: =SUM(V103:V105) -> -44.42036 | W106: =SUM(W103:W105) -> -104.52036 | X106: =SUM(X103:X105) -> -45.48644 | Y106: =SUM(Y103:Y105) -> -45.061338 | ... AI106: =SUM(AI103:AI105) -> -96.312323
B107: Net cash flow from operatng activities | C107: =C102+C106 -> 31.1 | D107: =D102+D106 -> 49.3 | E107: =E102+E106 -> 80.5 | F107: =F102+F106 -> 53.1 | G107: =G102+G106 -> 124.1 | H107: =H102+H106 -> 177.1 | I107: =I102+I106-0.1 -> 53.2 | J107: =J102+J106 -> 91.5 | K107: =K102+K106+0.1 -> 144.8 | L107: =L102+L106+0.1 -> 48.3 | M107: =M102+M106 -> 75.8 | N107: =N102+N106-0.1 -> 124.1 | O107: =O102+O106 -> -53.2 | P107: =P102+P106 -> 147.7 | Q107: =Q102+Q106-0.1 -> 94.7 | R107: =R102+R106-0.1 -> 19.1 | S107: =S102+S106 -> 51.3 | T107: =T102+T106 -> 70.4 | U107: =U102+U106 -> 3.1 | V107: =V102+V106 -> -178.93207 | W107: =W102+W106 -> -175.73207 | X107: =X102+X106 -> -68.412327 | Y107: =Y102+Y106 -> 56.495494 | Z107: =Z102+Z106 -> -11.916833 | ... AI107: =AI102+AI106 -> 72.461977
B109: Purchase of operating investments | C109: -26.1 | D109: =E109-C109 -> -38.7 | E109: -64.8 | F109: -20.5 | G109: =H109-F109 -> -33.5 | H109: -54 | I109: -23.7 | J109: =K109-I109 -> -30.8 | K109: -54.5 | L109: -31.7 | M109: =N109-L109 -> -43.9 | N109: -75.6 | O109: -45.8 | P109: =Q109-O109 -> -35.1 | Q109: -80.9 | R109: -18.5 | S109: =T109-R109 -> -32.7 | T109: -51.2 | U109: -19.6 | V109: =-Schedules!V5-Schedules!V19-Schedules!V33 -> -24.311 | W109: =U109+V109 -> -43.911 | X109: =-Schedules!X5 -> -25.4726 | Y109: =-Schedules!Y5 -> -25.316368 | Z109: =-Schedules!Z5-Schedules!Z19-Schedules!Z33 -> -50.788968 | AA109: =-Schedules!AA5 -> -26.505976 | AB109: =-Schedules!AB5 -> -26.365244 | AC109: =-Schedules!AC5-Schedules!AC19-Schedules!AC33 -> -52.87122 | AD109: =-Schedules!AD5 -> -27.581845 | AE109: =-Schedules!AE5 -> -27.459696 | AF109: =-Schedules!AF5-Schedules!AF19-Schedules!AF33 -> -55.041541 | AG109: =-Schedules!AG5 -> -29.113024 | AH109: =-Schedules!AH5 -> -29.184055 | AI109: =-Schedules!AI5-Schedules!AI19-Schedules!AI33 -> -58.297079
B110: Purchase of shares | C110: 0 | D110: =E110-C110 -> 0 | E110: 0 | F110: -9.5 | G110: =H110-F110 -> 2.8 | H110: -6.7 | I110: 0 | J110: =K110-I110 -> 0 | K110: 0 | L110: 0 | M110: =N110-L110 -> 0 | N110: 0 | O110: 0 | P110: =Q110-O110 -> 0 | Q110: 0 | R110: 0 | S110: =T110-R110 -> 0 | U110: -4 | W110: =U110+V110 -> -4 | Z110: =X110+Y110 -> 0 | AC110: =AA110+AB110 -> 0 | AF110: =AD110+AE110 -> 0 | AI110: =AG110+AH110 -> 0 | AL110: Capex light
B111: Disposals of non-current assets | C111: 0.7 | D111: =E111-C111 -> 0.3 | E111: 1 | F111: 0.2 | G111: =H111-F111 -> 1.2 | H111: 1.4 | I111: 0 | J111: =K111-I111 -> 0 | K111: 0 | L111: 0 | M111: =N111-L111 -> 0 | N111: 0 | O111: 0 | P111: =Q111-O111 -> 0 | Q111: 0 | R111: 0 | S111: =T111-R111 -> 0 | V111: =Schedules!V7 -> 0 | W111: =U111+V111 -> 0 | X111: =Schedules!X7 -> 0 | Y111: =Schedules!Y7 -> 0 | Z111: =X111+Y111 -> 0 | AA111: =Schedules!AA7 -> 0 | AB111: =Schedules!AB7 -> 0 | AC111: =AA111+AB111 -> 0 | AD111: =Schedules!AD7 -> 0 | AE111: =Schedules!AE7 -> 0 | AF111: =AD111+AE111 -> 0 | AG111: =Schedules!AG7 -> 0 | AH111: =Schedules!AH7 -> 0 | AI111: =AG111+AH111 -> 0
B112: Proceeds for sale of non-current assets | C112: 0 | D112: =E112-C112 -> 9.1 | E112: 9.1 | F112: 0 | G112: =H112-F112 -> 71.3 | H112: 71.3 | I112: 0 | J112: =K112-I112 -> 0 | K112: 0 | L112: 0.2 | M112: =N112-L112 -> -0.2 | N112: 0 | O112: 0.4 | P112: =Q112-O112 -> -0.4 | Q112: 0 | R112: -8.3 | S112: =T112-R112 -> 8.3 | U112: 0.1 | W112: =U112+V112 -> 0.1 | Z112: =X112+Y112 -> 0 | AC112: =AA112+AB112 -> 0 | AF112: =AD112+AE112 -> 0 | AI112: =AG112+AH112 -> 0
...

Sheet Schedules
B2: Schedules | C2: ='Financial Statements'!C47 -> H1'20 | D2: ='Financial Statements'!D47 -> H2'20 | E2: ='Financial Statements'!E47 -> FY20 | F2: ='Financial Statements'!F47 -> H1'21 | G2: ='Financial Statements'!G47 -> H2'21 | H2: ='Financial Statements'!H47 -> FY21 | I2: ='Financial Statements'!I47 -> H1'22 | J2: ='Financial Statements'!J47 -> H2'22 | ... R2: ='Financial Statements'!R47 -> H1'25 | S2: H2'25 | T2: FY25 | U2: ='Financial Statements'!U47 -> H1'26 | V2: ='Financial Statements'!V47 -> H2'26 | W2: ='Financial Statements'!W47 -> FY26 | X2: ='Financial Statements'!X47 -> H1'27 | Y2: ='Financial Statements'!Y47 -> H2'27 | Z2: ='Financial Statements'!Z47 -> FY27 | AA2: ='Financial Statements'!AA47 -> H1'28 | AB2: ='Financial Statements'!AB47 -> H2'28 | ... AI2: ='Financial Statements'!AI47 -> FY30
B3: PP&E
B4: Opening Value | P4: =O9 -> 735.1 | Q4: =P4 -> 735.1 | R4: =Q9 -> 764.9 | S4: =R9 -> 778.8 | T4: =S4 -> 778.8 | U4: =T9 -> 807.2 | V4: =U9 -> 801.9 | W4: =T9 -> 807.2 | X4: =W9 -> 826.211 | Y4: =X9 -> 851.6836 | Z4: =W9 -> 826.211 | AA4: =Z9 -> 876.99997 | AB4: =AA9 -> 903.50594 | AC4: =Z9 -> 876.99997 | AD4: =AC9 -> 929.87119 | AE4: =AD9 -> 957.45303 | AF4: =AC9 -> 929.87119 | AG4: =AF9 -> 984.91273 | AH4: =AG9 -> 1014.0258 | AI4: =AF9 -> 984.91273
B5: Acquisitions | O5: =-'Financial Statements'!O109 -> 45.8 | R5: 16.6 | U5: 11.4 | V5: =V6*'Financial Statements'!V4 -> 24.311 | W5: =SUM(U5:V5) -> 35.711 | X5: =X6*'Financial Statements'!X4 -> 25.4726 | Y5: =Y6*'Financial Statements'!Y4 -> 25.316368 | Z5: =SUM(X5:Y5) -> 50.788968 | AA5: =AA6*'Financial Statements'!AA4 -> 26.505976 | AB5: =AB6*'Financial Statements'!AB4 -> 26.365244 | AC5: =SUM(AA5:AB5) -> 52.87122 | AD5: =AD6*'Financial Statements'!AD4 -> 27.581845 | AE5: =AE6*'Financial Statements'!AE4 -> 27.459696 | AF5: =SUM(AD5:AE5) -> 55.041541 | AG5: =AG6*'Financial Statements'!AG4 -> 29.113024 | AH5: =AH6*'Financial Statements'!AH4 -> 29.184055 | AI5: =SUM(AG5:AH5) -> 58.297079
B6: Capex/sales Ratio | O6: =O5/'Financial Statements'!O4 -> 0.071933407 | P6: =P5/'Financial Statements'!P4 -> 0 | Q6: =Q5/'Financial Statements'!Q4 -> 0 | R6: =R5/'Financial Statements'!R4 -> 0.031103616 | S6: =S5/'Financial Statements'!S4 -> 0 | T6: =T5/'Financial Statements'!T4 -> 0 | U6: =U5/'Financial Statements'!U4 -> 0.023284314 | V6: 0.05 | W6: =W5/'Financial Statements'!W4 -> 0.036595889 | X6: 0.05 | Y6: 0.05 | Z6: =Z5/'Financial Statements'!Z4 -> 0.05 | AA6: 0.05 | AB6: 0.05 | AC6: =AC5/'Financial Statements'!AC4 -> 0.05 | AD6: 0.05 | AE6: 0.05 | AF6: =AF5/'Financial Statements'!AF4 -> 0.05 | AG6: 0.05 | AH6: 0.05 | AI6: =AI5/'Financial Statements'!AI4 -> 0.05 | AK6: =+S5-S11 -> 0
B7: Disposals | O7: =O4+O5-O11-O15 -> -406 | R7: -0.2 | U7: -2.1 | W7: =SUM(U7:V7) -> -2.1 | Z7: =SUM(X7:Y7) -> 0 | AC7: =SUM(AA7:AB7) -> 0 | AF7: =SUM(AD7:AE7) -> 0 | AI7: =SUM(AG7:AH7) -> 0
B8: Other adjustments | R8: =0.1-2.6 -> -2.5 | U8: =-0.1-14.4 -> -14.5 | W8: =SUM(U8:V8) -> -14.5
B9: Gross Value | O9: 735.1 | P9: 764.9 | Q9: =P9 -> 764.9 | R9: =R4+R5+R7+R8 -> 778.8 | S9: 807.2 | T9: =S9 -> 807.2 | U9: =U4+U5+U7+U8-0.1 -> 801.9 | V9: =V4+V5+V7+V8 -> 826.211 | W9: =W4+W5+W7+W8-0.1 -> 826.211 | X9: =X4+X5+X7+X8 -> 851.6836 | Y9: =Y4+Y5+Y7+Y8 -> 876.99997 | Z9: =Z4+Z5+Z7+Z8 -> 876.99997 | AA9: =AA4+AA5+AA7+AA8 -> 903.50594 | AB9: =AB4+AB5+AB7+AB8 -> 929.87119 | AC9: =AC4+AC5+AC7+AC8 -> 929.87119 | AD9: =AD4+AD5+AD7+AD8 -> 957.45303 | AE9: =AE4+AE5+AE7+AE8 -> 984.91273 | ... AI9: =AI4+AI5+AI7+AI8 -> 1043.2098
B10: Accumulated depreciation - Opening | P10: 304.9 | Q10: =P10 -> 304.9 | R10: =Q14 -> 314.3 | S10: 304.9 | T10: =S10 -> 304.9 | U10: =T14 -> 342.8 | V10: =U14 -> 351.7 | W10: =T14 -> 342.8 | X10: =W14 -> 367.738 | Y10: =X14 -> 384.26222 | Z10: =W14 -> 367.738 | AA10: =Z14 -> 401.29589 | AB10: =AA14 -> 418.83589 | AC10: =Z14 -> 401.29589 | AD10: =AC14 -> 436.90601 | AE10: =AD14 -> 455.50343 | AF10: =AC14 -> 436.90601 | AG10: =AF14 -> 474.65249 | AH10: =AG14 -> 494.35075 | AI10: =AF14 -> 474.65249
B11: Depeciation charge for the year | O11: ='Financial Statements'!O16 -> 21.6 | Q11: ='Financial Statements'!Q16 -> 45.1 | R11: 15.4 | T11: ='Financial Statements'!T16 -> 46.8 | U11: 16.2 | V11: =V12*V4 -> 16.038 | W11: =SUM(U11:V11) -> 32.238 | X11: =X12*X4 -> 16.52422 | Y11: =Y12*Y4 -> 17.033672 | Z11: =SUM(X11:Y11) -> 33.557892 | AA11: =AA12*AA4 -> 17.539999 | AB11: =AB12*AB4 -> 18.070119 | AC11: =SUM(AA11:AB11) -> 35.610118 | AD11: =AD12*AD4 -> 18.597424 | AE11: =AE12*AE4 -> 19.149061 | AF11: =SUM(AD11:AE11) -> 37.746484 | AG11: =AG12*AG4 -> 19.698255 | AH11: =AH12*AH4 -> 20.280515 | AI11: =SUM(AG11:AH11) -> 39.97877
B12: Depreciation rate (%) | O12: =O11/O4 -> #DIV/0! | P12: =P11/P4 -> 0 | Q12: =Q11/Q4 -> 0.061352197 | R12: =R11/R4 -> 0.020133351 | S12: =S11/S4 -> 0 | T12: =T11/T4 -> 0.06009245 | U12: =U11/U4 -> 0.020069376 | V12: 0.02 | W12: =W11/W4 -> 0.039938057 | X12: 0.02 | Y12: 0.02 | Z12: =Z11/Z4 -> 0.040616612 | AA12: 0.02 | AB12: 0.02 | AC12: =AC11/AC4 -> 0.040604469 | AD12: 0.02 | AE12: 0.02 | AF12: =AF11/AF4 -> 0.04059324 | AG12: 0.02 | AH12: 0.02 | AI12: =AI11/AI4 -> 0.04059118
B13: Other adjustments | R13: =-1.1+0-0.2 -> -1.3 | U13: -7.3 | W13: =SUM(U13:V13) -> -7.3
B14: Accumulated depreciation and impairments | O14: 304.9 | P14: 314.3 | Q14: =P14 -> 314.3 | R14: =R10+R11+R13 -> 328.4 | S14: 342.8 | T14: =S14 -> 342.8 | U14: =U10+U11+U13 -> 351.7 | V14: =V10+V11+V13 -> 367.738 | W14: =W10+W11+W13 -> 367.738 | X14: =X10+X11+X13 -> 384.26222 | Y14: =Y10+Y11+Y13 -> 401.29589 | Z14: =Z10+Z11+Z13 -> 401.29589 | AA14: =AA10+AA11+AA13 -> 418.83589 | AB14: =AB10+AB11+AB13 -> 436.90601 | ... AI14: =AI10+AI11+AI13 -> 514.63126
B15: Net Value | O15: =O9-O14 -> 430.2 | P15: ='Financial Statements'!P51 -> 450.6 | Q15: =Q9-Q14 -> 450.6 | R15: =R9-R14 -> 450.4 | S15: ='Financial Statements'!S51 -> 464.4 | T15: 464.4 | U15: =U9-U14 -> 450.2 | V15: =V9-V14 -> 458.473 | W15: =W9-W14 -> 458.473 | X15: =X9-X14 -> 467.42138 | Y15: =Y9-Y14 -> 475.70408 | Z15: =Z9-Z14 -> 475.70408 | AA15: =AA9-AA14 -> 484.67005 | AB15: =AB9-AB14 -> 492.96518 | ... AI15: =AI9-AI14 -> 528.57854
B17: Goodwill
B18: Opening Value | P18: =O23 -> 647.4 | Q18: =P18 -> 647.4 | R18: =Q23 -> 648.7 | S18: =R23 -> 648.8 | T18: =S18 -> 648.8 | U18: =T23 -> 648.7 | V18: =U23 -> 647.3 | W18: =T23 -> 648.7 | X18: =W23 -> 647.3 | Y18: =X23 -> 647.3 | Z18: =W23 -> 647.3 | AA18: =Z23 -> 647.3 | AB18: =AA23 -> 647.3 | AC18: =Z23 -> 647.3 | AD18: =AC23 -> 647.3 | AE18: =AD23 -> 647.3 | AF18: =AC23 -> 647.3 | AG18: =AF23 -> 647.3 | AH18: =AG23 -> 647.3 | AI18: =AF23 -> 647.3
B19: Acquisitions | O19: =-'Financial Statements'!O123 -> -306.7 | R19: 1.7 | V19: =V20*'Financial Statements'!V21 -> 0 | W19: =SUM(U19:V19) -> 0 | X19: =X20*'Financial Statements'!X21 -> 0 | Y19: =Y20*'Financial Statements'!Y21 -> 0 | Z19: =SUM(X19:Y19) -> 0 | AA19: =AA20*'Financial Statements'!AA21 -> 0 | AB19: =AB20*'Financial Statements'!AB21 -> 0 | AC19: =SUM(AA19:AB19) -> 0 | AD19: =AD20*'Financial Statements'!AD21 -> 0 | AE19: =AE20*'Financial Statements'!AE21 -> 0 | AF19: =SUM(AD19:AE19) -> 0 | AG19: =AG20*'Financial Statements'!AG21 -> 0 | AH19: =AH20*'Financial Statements'!AH21 -> 0 | AI19: =SUM(AG19:AH19) -> 0
B20: Capex/sales Ratio | O20: =O19/'Financial Statements'!O21 -> -26.213675 | P20: =P19/'Financial Statements'!P21 -> 0 | Q20: =Q19/'Financial Statements'!Q21 -> 0 | R20: =R19/'Financial Statements'!R21 -> 0.10179641 | S20: =S19/'Financial Statements'!S21 -> 0 | T20: =T19/'Financial Statements'!T21 -> 0 | U20: =U19/'Financial Statements'!U21 -> 0 | W20: =W19/'Financial Statements'!W21 -> 0 | Z20: =Z19/'Financial Statements'!Z21 -> 0 | AC20: =AC19/'Financial Statements'!AC21 -> 0 | AF20: =AF19/'Financial Statements'!AF21 -> 0 | AI20: =AI19/'Financial Statements'!AI21 -> 0
B21: Disposals | O21: =O18+O19-O25-O29 -> -812.4 | R21: 0 | W21: =SUM(U21:V21) -> 0 | Z21: =SUM(X21:Y21) -> 0 | AC21: =SUM(AA21:AB21) -> 0 | AF21: =SUM(AD21:AE21) -> 0 | AI21: =SUM(AG21:AH21) -> 0
B22: Other adjustments | R22: =-0.1-1.4 -> -1.5 | U22: =-0.1-1.4 -> -1.5 | W22: =SUM(U22:V22) -> -1.5
B23: Gross Value | O23: 647.4 | P23: 648.7 | Q23: =P23 -> 648.7 | R23: =R18+R19+R21+R22-0.1 -> 648.8 | S23: 648.7 | T23: =S23 -> 648.7 | U23: =U18+U19+U21+U22+0.1 -> 647.3 | V23: =V18+V19+V21+V22 -> 647.3 | W23: =W18+W19+W21+W22+0.1 -> 647.3 | X23: =X18+X19+X21+X22 -> 647.3 | Y23: =Y18+Y19+Y21+Y22 -> 647.3 | Z23: =Z18+Z19+Z21+Z22 -> 647.3 | AA23: =AA18+AA19+AA21+AA22 -> 647.3 | AB23: =AB18+AB19+AB21+AB22 -> 647.3 | AC23: =AC18+AC19+AC21+AC22 -> 647.3 | AD23: =AD18+AD19+AD21+AD22 -> 647.3 | AE23: =AE18+AE19+AE21+AE22 -> 647.3 | ... AI23: =AI18+AI19+AI21+AI22 -> 647.3
B24: Accumulated amortization - Opening | P24: =O28 -> 141.7 | Q24: =P24 -> 141.7 | R24: =Q28 -> 143.9 | S24: =R28 -> 145.1 | T24: =S24 -> 145.1 | U24: 149.5 | V24: =U28 -> 148.2 | W24: 149.5 | X24: =W24+X25 -> 149.5 | Y24: =X24+Y25 -> 149.5 | Z24: =Y24 -> 149.5 | AA24: =Z24+AA25 -> 149.5 | AB24: =AA24+AB25 -> 149.5 | AC24: =AB24 -> 149.5 | AD24: =AC24+AD25 -> 149.5 | AE24: =AD24+AE25 -> 149.5 | AF24: =AE24 -> 149.5 | AG24: =AF24+AG25 -> 149.5 | AH24: =AG24+AH25 -> 149.5 | AI24: =AH24 -> 149.5
B25: Depeciation charge for the year | O25: ='Financial Statements'!O32 -> 0 | Q25: ='Financial Statements'!Q32 -> 0 | R25: 3.1 | T25: ='Financial Statements'!T32 -> 0 | U25: -1.3 | V25: =V26*V18 -> 0 | W25: =SUM(U25:V25) -> -1.3 | X25: =X26*X18 -> 0 | Y25: =Y26*Y18 -> 0 | Z25: =SUM(X25:Y25) -> 0 | AA25: =AA26*AA18 -> 0 | AB25: =AB26*AB18 -> 0 | AC25: =SUM(AA25:AB25) -> 0 | AD25: =AD26*AD18 -> 0 | AE25: =AE26*AE18 -> 0 | AF25: =SUM(AD25:AE25) -> 0 | AG25: =AG26*AG18 -> 0 | AH25: =AH26*AH18 -> 0 | AI25: =SUM(AG25:AH25) -> 0
B26: Depreciation rate (%) | O26: =O25/O18 -> #DIV/0! | P26: =P25/P18 -> 0 | Q26: =Q25/Q18 -> 0 | R26: =R25/R18 -> 0.0047787883 | S26: =S25/S18 -> 0 | T26: =T25/T18 -> 0 | U26: =U25/U18 -> -0.002004008 | W26: =W25/W18 -> -0.002004008 | Z26: =Z25/Z18 -> 0 | AC26: =AC25/AC18 -> 0 | AF26: =AF25/AF18 -> 0 | AI26: =AI25/AI18 -> 0
B27: Other adjustments | R27: -1.9
B28: Accumulated amortization | O28: 141.7 | P28: 143.9 | Q28: =P28 -> 143.9 | R28: =R24+R25+R27 -> 145.1 | S28: 143.9 | T28: =S28 -> 143.9 | U28: =U24+U25+U27 -> 148.2 | V28: =U28 -> 148.2 | W28: =W24+W25 -> 148.2 | X28: =W28 -> 148.2 | Y28: =X28 -> 148.2 | Z28: =W28 -> 148.2 | AA28: =Z28 -> 148.2 | AB28: =AA28 -> 148.2 | AC28: =Z28 -> 148.2 | AD28: =AC28 -> 148.2 | AE28: =AD28 -> 148.2 | AF28: =AC28 -> 148.2 | AG28: =AF28 -> 148.2 | AH28: =AG28 -> 148.2 | AI28: =AF28 -> 148.2
B29: Net Value | O29: =O23-O28 -> 505.7 | P29: =P23-P28 -> 504.8 | Q29: =Q23-Q28 -> 504.8 | R29: =R23-R28 -> 503.7 | S29: 503.5 | T29: =T23-T28 -> 504.8 | U29: =U23-U28-0.1 -> 499 | V29: =V23-V28 -> 499.1 | W29: =W23-W28 -> 499.1 | X29: =X23-X28+0.1 -> 499.2 | Y29: =Y23-Y28+0.1 -> 499.2 | Z29: =Z23-Z28+0.1 -> 499.2 | AA29: =AA23-AA28+0.1 -> 499.2 | AB29: =AB23-AB28+0.1 -> 499.2 | AC29: =AC23-AC28+0.1 -> 499.2 | AD29: =AD23-AD28+0.1 -> 499.2 | AE29: =AE23-AE28+0.1 -> 499.2 | ... AI29: =AI23-AI28+0.1 -> 499.2
B31: Right-of-use assets – IFRS 16
B32: Opening Value | P32: =O37 -> 64 | Q32: =P32 -> 64 | R32: =Q37 -> 58.1 | S32: =R37 -> 52.9 | T32: =S32 -> 52.9 | U32: 58.8 | V32: =U37 -> 52.4 | W32: 58.8 | X32: =W37 -> 52.4 | Y32: =X37 -> 52.4 | Z32: =W37 -> 52.4 | AA32: =Z37 -> 52.4 | AB32: =AA37 -> 52.4 | AC32: =Z37 -> 52.4 | AD32: =AC37 -> 52.4 | AE32: =AD37 -> 52.4 | AF32: =AC37 -> 52.4 | AG32: =AF37 -> 52.4 | AH32: =AG37 -> 52.4 | AI32: =AF37 -> 52.4
B33: Acquisitions | O33: =-'Financial Statements'!O137 -> 0 | R33: 0.2 | V33: =V34*'Financial Statements'!V35 -> 0 | W33: =SUM(U33:V33) -> 0 | X33: =X34*'Financial Statements'!X35 -> 0 | Y33: =Y34*'Financial Statements'!Y35 -> 0 | Z33: =SUM(X33:Y33) -> 0 | AA33: =AA34*'Financial Statements'!AA35 -> 0 | AB33: =AB34*'Financial Statements'!AB35 -> 0 | AC33: =SUM(AA33:AB33) -> 0 | AD33: =AD34*'Financial Statements'!AD35 -> 0 | AE33: =AE34*'Financial Statements'!AE35 -> 0 | AF33: =SUM(AD33:AE33) -> 0 | AG33: =AG34*'Financial Statements'!AG35 -> 0 | AH33: =AH34*'Financial Statements'!AH35 -> 0 | AI33: =SUM(AG33:AH33) -> 0
B34: Capex/sales Ratio | O34: =O33/'Financial Statements'!O35 -> #DIV/0! | P34: =P33/'Financial Statements'!P35 -> #DIV/0! | Q34: =Q33/'Financial Statements'!Q35 -> #DIV/0! | R34: =R33/'Financial Statements'!R35 -> #DIV/0! | S34: =S33/'Financial Statements'!S35 -> #DIV/0! | T34: =T33/'Financial Statements'!T35 -> #DIV/0! | U34: =U33/'Financial Statements'!U35 -> #DIV/0! | W34: =W33/'Financial Statements'!W35 -> #DIV/0! | Z34: =Z33/'Financial Statements'!Z35 -> #DIV/0! | AC34: =AC33/'Financial Statements'!AC35 -> #DIV/0! | AF34: =AF33/'Financial Statements'!AF35 -> #DIV/0! | AI34: =AI33/'Financial Statements'!AI35 -> #DIV/0!
B35: Disposals | R35: 0 | W35: =SUM(U35:V35) -> 0 | Z35: =SUM(X35:Y35) -> 0 | AC35: =SUM(AA35:AB35) -> 0 | AF35: =SUM(AD35:AE35) -> 0 | AI35: =SUM(AG35:AH35) -> 0
B36: Other adjustments | R36: =-4.6-0.7 -> -5.3 | U36: =-3.6-2.8 -> -6.4 | W36: =SUM(U36:V36) -> -6.4
B37: Gross Value | O37: 64 | P37: 58.1 | Q37: =P37 -> 58.1 | R37: =R32+R33+R35+R36-0.1 -> 52.9 | S37: 58.1 | T37: =S37 -> 58.1 | U37: =U32+U33+U35+U36 -> 52.4 | V37: =V32+V33+V35+V36 -> 52.4 | W37: =W32+W33+W35+W36 -> 52.4 | X37: =X32+X33+X35+X36 -> 52.4 | Y37: =Y32+Y33+Y35+Y36 -> 52.4 | Z37: =Z32+Z33+Z35+Z36 -> 52.4 | AA37: =AA32+AA33+AA35+AA36 -> 52.4 | AB37: =AB32+AB33+AB35+AB36 -> 52.4 | ... AI37: =AI32+AI33+AI35+AI36 -> 52.4
B38: Accumulated amortization - Opening | Q38: =P38 -> 0 | R38: =Q42 -> 21.7 | T38: =S38 -> 0 | U38: 26.5 | V38: =U42 -> 25.7 | W38: =U38 -> 26.5 | X38: =W42 -> 25.7 | Y38: =X42 -> 25.7 | Z38: =X38 -> 25.7 | AA38: =Z42 -> 25.7 | AB38: =AA42 -> 25.7 | AC38: =AA38 -> 25.7 | AD38: =AC42 -> 25.7 | AE38: =AD42 -> 25.7 | AF38: =AD38 -> 25.7 | AG38: =AF42 -> 25.7 | AH38: =AG42 -> 25.7 | AI38: =AG38 -> 25.7
B39: Depeciation charge for the year | O39: ='Financial Statements'!O46 -> 0 | Q39: ='Financial Statements'!Q46 -> 0 | R39: 4.4 | T39: ='Financial Statements'!T46 -> 0 | U39: 4 | V39: =V40*V32 -> 0 | W39: =SUM(U39:V39) -> 4 | X39: =X40*X32 -> 0 | Y39: =Y40*Y32 -> 0 | Z39: =SUM(X39:Y39) -> 0 | AA39: =AA40*AA32 -> 0 | AB39: =AB40*AB32 -> 0 | AC39: =SUM(AA39:AB39) -> 0 | AD39: =AD40*AD32 -> 0 | AE39: =AE40*AE32 -> 0 | AF39: =SUM(AD39:AE39) -> 0 | AG39: =AG40*AG32 -> 0 | AH39: =AH40*AH32 -> 0 | AI39: =SUM(AG39:AH39) -> 0
B40: Depreciation rate (%) | O40: =O39/O32 -> #DIV/0! | P40: =P39/P32 -> 0 | Q40: =Q39/Q32 -> 0 | R40: =R39/R32 -> 0.075731497 | S40: =S39/S32 -> 0 | T40: =T39/T32 -> 0 | U40: =U39/U32 -> 0.068027211 | V40: 0 | W40: =W39/W32 -> 0.068027211 | X40: 0 | Y40: 0 | Z40: =Z39/Z32 -> 0 | AA40: 0 | AB40: 0 | AC40: =AC39/AC32 -> 0 | AD40: 0 | AE40: 0 | AF40: =AF39/AF32 -> 0 | AG40: 0 | AH40: 0 | AI40: =AI39/AI32 -> 0
B41: Other adjustments | R41: 4.8 | U41: -4.8 | W41: =SUM(U41:V41) -> -4.8
B42: Accumulated amortization | O42: 30.8 | P42: 21.7 | Q42: =P42 -> 21.7 | R42: =R38-R41+R39 -> 21.3 | S42: 21.7 | T42: =S42 -> 21.7 | U42: =U38+U41+U39 -> 25.7 | V42: =V38+V41+V39 -> 25.7 | W42: =W38+W41+W39 -> 25.7 | X42: =X38+X39 -> 25.7 | Y42: =Y38+Y39 -> 25.7 | Z42: =Z38+Z39 -> 25.7 | AA42: =AA38+AA39 -> 25.7 | AB42: =AB38+AB39 -> 25.7 | AC42: =AC38+AC39 -> 25.7 | AD42: =AD38+AD39 -> 25.7 | AE42: =AE38+AE39 -> 25.7 | ... AI42: =AI38+AI39 -> 25.7
B43: Net Value | O43: =O37-O42 -> 33.2 | P43: =P37-P42 -> 36.4 | Q43: =Q37-Q42 -> 36.4 | R43: =R37-R42 -> 31.6 | S43: =S37-S42 -> 36.4 | T43: =T37-T42 -> 36.4 | U43: =U37-U42-0.1 -> 26.6 | V43: =V37-V42 -> 26.7 | W43: =W37-W42 -> 26.7 | X43: =X37-X42 -> 26.7 | Y43: =Y37-Y42 -> 26.7 | Z43: =Z37-Z42 -> 26.7 | AA43: =AA37-AA42 -> 26.7 | AB43: =AB37-AB42 -> 26.7 | AC43: =AC37-AC42 -> 26.7 | ... AI43: =AI37-AI42 -> 26.7
B45: Opening Balance | F45: =E49 -> 534.4 | G45: =F49 -> 558.9 | H45: =E49 -> 534.4 | I45: =H49 -> 635.3 | J45: =I49 -> 666.9 | K45: =H49 -> 635.3 | L45: =K49 -> 748.4 | M45: =L49 -> 800 | N45: =K49 -> 748.4 | O45: =N49 -> 920.7 | P45: =O49 -> 889.7 | Q45: =N49 -> 920.7 | R45: =Q49 -> 954 | S45: =R49 -> 950.3 | T45: =Q49 -> 954 | U45: =T49 -> 972.1 | V45: =U49 -> 957.8 | W45: =T49 -> 972.1 | X45: =W49 -> 1035.0346 | Y45: =X49 -> 1116.9112 | Z45: =W49 -> 1035.0346 | AA45: =Z49 -> 1198.4317 | AB45: =AA49 -> 1284.7978 | AC45: =Z49 -> 1198.4317 | AD45: =AC49 -> 1370.8651 | AE45: =AD49 -> 1461.8779 | AF45: =AC49 -> 1370.8651 | AG45: =AF49 -> 1552.6607 | AH45: =AG49 -> 1650.0048 | AI45: =AF49 -> 1552.6607
B46: Net Income | F46: ='Financial Statements'!F28 -> 64.9 | G46: ='Financial Statements'!G28 -> 79.3 | H46: ='Financial Statements'!H28 -> 144.2 | I46: ='Financial Statements'!I28 -> 134 | J46: ='Financial Statements'!J28 -> 78.3 | K46: ='Financial Statements'!K28 -> 212.3 | L46: ='Financial Statements'!L28 -> 223.5 | M46: ='Financial Statements'!M28 -> 70 | ... V46: ='Financial Statements'!V28 -> 77.23464 | W46: =U46+V46 -> 140.33464 | X46: ='Financial Statements'!X28 -> 81.87656 | Y46: ='Financial Statements'!Y28 -> 81.520502 | Z46: =X46+Y46 -> 163.39706 | AA46: ='Financial Statements'!AA28 -> 86.366051 | AB46: ='Financial Statements'!AB28 -> 86.067341 | AC46: =AA46+AB46 -> 172.43339 | AD46: ='Financial Statements'!AD28 -> 91.012766 | AE46: ='Financial Statements'!AE28 -> 90.782816 | AF46: =AD46+AE46 -> 181.79558 | AG46: ='Financial Statements'!AG28 -> 97.344129 | AH46: ='Financial Statements'!AH28 -> 97.828945 | AI46: =AG46+AH46 -> 195.17307
B47: Dividends | F47: ='Financial Statements'!F121 -> 0 | G47: ='Financial Statements'!G121 -> -9.6 | H47: ='Financial Statements'!H121 -> -9.6 | I47: ='Financial Statements'!I121 -> 0 | J47: ='Financial Statements'!J121 -> -93.7 | K47: ='Financial Statements'!K121 -> -93.7 | L47: ='Financial Statements'!L121 -> 0 | M47: =N47-L47 -> -111 | N47: ='Financial Statements'!N121 -> -111 | O47: ='Financial Statements'!O121 -> 0 | P47: =Q47-O47 -> -152.7 | Q47: ='Financial Statements'!Q121 -> -152.7 | R47: ='Financial Statements'!R121 -> 0 | S47: =T47-R47 -> -41 | T47: ='Financial Statements'!T121 -> -41 | U47: ='Financial Statements'!U121 -> 0 | W47: =SUM(U47:V47) -> 0 | Z47: =SUM(X47:Y47) -> 0 | AC47: =SUM(AA47:AB47) -> 0 | AF47: =SUM(AD47:AE47) -> 0 | AI47: =SUM(AG47:AH47) -> 0
B48: Adjustments | N48: =N49-(N45+N46+N47) -> -10.2 | O48: =O49-(O45+O46+O47) -> -143.8 | Q48: =Q49-(Q45+Q46+Q47) -> 1.7 | R48: =R49-(R45+R46+R47) -> -95.4 | T48: =T49-(T45+T46+T47) -> -61.6 | U48: =U49-(U45+U46+U47) -> -77.4 | W48: =SUM(U48:V48) -> -77.4
B49: Closing Balance | C49: ='Financial Statements'!C68 -> 519 | D49: ='Financial Statements'!D68 -> 534.4 | E49: ='Financial Statements'!E68 -> 534.4 | F49: ='Financial Statements'!F68 -> 558.9 | G49: ='Financial Statements'!G68 -> 635.3 | H49: ='Financial Statements'!H68 -> 635.3 | I49: ='Financial Statements'!I68 -> 666.9 | J49: ='Financial Statements'!J68 -> 748.4 | ... U49: ='Financial Statements'!U68 -> 957.8 | V49: =V45+V46+V47+V48 -> 1035.0346 | W49: =W45+W46+W47+W48 -> 1035.0346 | X49: =X45+X46+X47+X48 -> 1116.9112 | Y49: =Y45+Y46+Y47+Y48 -> 1198.4317 | Z49: =Z45+Z46+Z47+Z48 -> 1198.4317 | AA49: =AA45+AA46+AA47+AA48 -> 1284.7978 | AB49: =AB45+AB46+AB47+AB48 -> 1370.8651 | AC49: =AC45+AC46+AC47+AC48 -> 1370.8651 | ... AI49: =AI45+AI46+AI47+AI48 -> 1747.8337
B51: Working Capital | C51: H1'20 | D51: H2'20 | E51: FY20 | F51: H1'21 | G51: H2'21 | H51: FY21 | I51: H1'22 | J51: H2'22 | K51: FY22 | L51: H1'23 | M51: H2'23 | N51: FY23 | O51: H1'24 | P51: H2'24 | Q51: FY24 | R51: =R2 -> H1'25 | S51: H2'25 | T51: FY25 | U51: =U2 -> H1'26 | V51: =V2 -> H2'26 | W51: =W2 -> FY26 | X51: =X2 -> H1'27 | Y51: =Y2 -> H2'27 | Z51: =Z2 -> FY27 | AA51: =AA2 -> H1'28 | AB51: =AB2 -> H2'28 | ... AI51: =AI2 -> FY30
B52: No. of days | C52: 183 | D52: 183 | E52: 366 | F52: 182.5 | G52: 182.5 | H52: 365 | I52: 182.5 | J52: 182.5 | K52: 365 | L52: 182.5 | M52: 182.5 | N52: 365 | O52: 183 | P52: 183 | Q52: 366 | R52: 182.5 | S52: 183 | T52: 366 | U52: 182.5 | V52: 182.5 | W52: 365 | X52: 182.5 | Y52: 182.5 | Z52: 365 | AA52: 183 | AB52: 183 | AC52: 366 | AD52: 182.5 | AE52: 182.5 | AF52: 365 | AG52: 182.5 | AH52: 182.5 | AI52: 365
B53: Sales | C53: ='Financial Statements'!C4 -> 523.9 | D53: ='Financial Statements'!D4 -> 500.9 | E53: ='Financial Statements'!E4 -> 1024.8 | F53: ='Financial Statements'!F4 -> 430.8 | G53: ='Financial Statements'!G4 -> 579.4 | H53: ='Financial Statements'!H4 -> 1010.2 | I53: ='Financial Statements'!I4 -> 645.3 | J53: ='Financial Statements'!J4 -> 667.6 | ... AI53: ='Financial Statements'!AI4 -> 1165.9416
B54: Cost of Sales | C54: ='Financial Statements'!C5 -> 175.6 | D54: ='Financial Statements'!D5 -> 172.3 | E54: ='Financial Statements'!E5 -> 347.9 | F54: ='Financial Statements'!F5 -> 152.2 | G54: ='Financial Statements'!G5 -> 177.9 | H54: ='Financial Statements'!H5 -> 330.1 | I54: ='Financial Statements'!I5 -> 199.4 | J54: ='Financial Statements'!J5 -> 212.4 | ... AI54: ='Financial Statements'!AI5 -> 408.07956
B56: Inventories | C56: ='Financial Statements'!C57 -> 1269 | D56: ='Financial Statements'!D57 -> 1363.9 | E56: ='Financial Statements'!E57 -> 1363.9 | F56: ='Financial Statements'!F57 -> 1378.6 | G56: ='Financial Statements'!G57 -> 1492.5 | H56: ='Financial Statements'!H57 -> 1492.5 | I56: ='Financial Statements'!I57 -> 1512.6 | J56: ='Financial Statements'!J57 -> 1615.5 | ... U56: ='Financial Statements'!U57 -> 2102.2 | V56: =+W56 -> 2238.1986 | W56: =(W60/W52)*W54 -> 2238.1986 | X56: =X60*X54/X52 -> 2442.5781 | Y56: =+Z56 -> 2483.7893 | Z56: =Z60*Z54/Z52 -> 2483.7893 | AA56: =AA60*AA54/AA52 -> 2636.1135 | AB56: =+AC56 -> 2629.1153 | AC56: =AC60*AC54/AC52 -> 2629.1153 | AD56: =AD60*AD54/AD52 -> 2750.6278 | AE56: =+AF56 -> 2744.5371 | AF56: =AF60*AF54/AF52 -> 2744.5371 | AG56: =AG60*AG54/AG52 -> 2903.3262 | AH56: =+AI56 -> 2906.8681 | AI56: =AI60*AI54/AI52 -> 2906.8681
B57: Trade Receivables | C57: ='Financial Statements'!C58 -> 249.6 | D57: ='Financial Statements'!D58 -> 199.4 | E57: ='Financial Statements'!E58 -> 199.4 | F57: ='Financial Statements'!F58 -> 270.5 | G57: ='Financial Statements'!G58 -> 158.1 | H57: ='Financial Statements'!H58 -> 158.1 | I57: ='Financial Statements'!I58 -> 286.4 | J57: ='Financial Statements'!J58 -> 253.6 | ... U57: ='Financial Statements'!U58 -> 254.6 | V57: =+W57 -> 334.18493 | W57: =W61*W53/W52 -> 334.18493 | X57: =X61*X53/X52 -> 348.93973 | Y57: =+Z57 -> 347.86964 | Z57: =Z61*Z53/Z52 -> 347.86964 | AA57: =AA61*AA53/AA52 -> 362.1035 | AB57: =+AC57 -> 361.14221 | AC57: =AC61*AC53/AC52 -> 361.14221 | AD57: =AD61*AD53/AD52 -> 377.83349 | AE57: =+AF57 -> 376.99686 | AF57: =AF61*AF53/AF52 -> 376.99686 | AG57: =AG61*AG53/AG52 -> 398.80855 | AH57: =+AI57 -> 399.29506 | AI57: =AI61*AI53/AI52 -> 399.29506
B58: Trade Payables | C58: ='Financial Statements'!C81 -> 474.7 | D58: ='Financial Statements'!D81 -> 534.4 | E58: ='Financial Statements'!E81 -> 534.4 | F58: ='Financial Statements'!F81 -> 498.7 | G58: ='Financial Statements'!G81 -> 586.1 | H58: ='Financial Statements'!H81 -> 586.1 | I58: ='Financial Statements'!I81 -> 600.9 | J58: ='Financial Statements'!J81 -> 683.3 | ... U58: ='Financial Statements'!U81 -> 629.5 | V58: =+W58 -> 572.97885 | W58: =W62*W54/W52 -> 572.97885 | X58: =X62*X54/X52 -> 625.29999 | Y58: =+Z58 -> 623.3824 | Z58: =Z62*Z54/Z52 -> 623.3824 | AA58: =AA62*AA54/AA52 -> 638.75057 | AB58: =+AC58 -> 637.05486 | AC58: =AC62*AC54/AC52 -> 637.05486 | AD58: =AD62*AD54/AD52 -> 655.91894 | AE58: =+AF58 -> 654.46654 | AF58: =AF62*AF54/AF52 -> 654.46654 | AG58: =AG62*AG54/AG52 -> 675.58168 | AH58: =+AI58 -> 676.40584 | AI58: =AI62*AI54/AI52 -> 676.40584
B60: Inventory Days | C60: =C56/C54*C52 -> 1322.4772 | D60: =D56/D54*D52 -> 1448.5995 | E60: =E56/E54*E52 -> 1434.8589 | F60: =F56/F54*F52 -> 1653.0519 | G60: =G56/G54*G52 -> 1531.0919 | H60: =H56/H54*H52 -> 1650.2954 | I60: =I56/I54*I52 -> 1384.4007 | J60: =J56/J54*J52 -> 1388.0826 | ... V60: =V56/V54*V52 -> 2400.273 | W60: 2500 | X60: 2500 | Y60: =Y56/Y54*Y52 -> 2557.8683 | Z60: 2550 | AA60: 2600 | AB60: =AB56/AB54*AB52 -> 2606.9391 | AC60: 2600 | AD60: 2600 | AE60: =AE56/AE54*AE52 -> 2605.7828 | AF60: 2600 | AG60: 2600 | AH60: =AH56/AH54*AH52 -> 2596.8359 | AI60: 2600
B61: Days Receivables | C61: =C57/C53*C52 -> 87.186104 | D61: =D57/D53*D52 -> 72.849271 | E61: =E57/E53*E52 -> 71.214286 | F61: =F57/F53*F52 -> 114.59204 | G61: =G57/G53*G52 -> 49.798498 | H61: =H57/H53*H52 -> 57.123837 | I61: =I57/I53*I52 -> 80.997985 | J61: =J57/J53*J52 -> 69.325944 | ... V61: =V57/V53*V52 -> 125.43447 | W61: 125 | X61: 125 | Y61: =Y57/Y53*Y52 -> 125.3857 | Z61: 125 | AA61: 125 | AB61: =AB57/AB53*AB52 -> 125.33361 | AC61: 125 | AD61: 125 | AE61: =AE57/AE53*AE52 -> 125.27802 | AF61: 125 | AG61: 125 | AH61: =AH57/AH53*AH52 -> 124.84788 | AI61: 125
B62: Days Payables | C62: =C58/C54*C52 -> 494.70444 | D62: =D58/D54*D52 -> 567.58677 | E62: =E58/E54*E52 -> 562.20293 | F62: =F58/F54*F52 -> 597.98127 | G62: =G58/G54*G52 -> 601.25492 | H62: =H58/H54*H52 -> 648.06574 | I62: =I58/I54*I52 -> 549.97116 | J62: =J58/J54*J52 -> 587.1104 | ... V62: =V58/V54*V52 -> 614.46988 | W62: 640 | X62: 640 | Y62: =Y58/Y54*Y52 -> 641.97478 | Z62: 640 | AA62: 630 | AB62: =AB58/AB54*AB52 -> 631.68141 | AC62: 630 | AD62: 620 | AE62: =AE58/AE54*AE52 -> 621.37897 | AF62: 620 | AG62: 605 | AH62: =AH58/AH54*AH52 -> 604.26374 | AI62: 605
B65: Debt Schedule | C65: H1'20 | D65: H2'20 | E65: FY20 | F65: H1'21 | G65: H2'21 | H65: FY21 | I65: H1'22 | J65: H2'22 | K65: FY22 | L65: H1'23 | M65: H2'23 | N65: FY23 | O65: H1'24 | P65: H2'24 | Q65: FY24 | R65: =R51 -> H1'25 | S65: H2'25 | T65: FY25 | U65: =U51 -> H1'26 | V65: =V51 -> H2'26 | W65: =W51 -> FY26 | X65: =X51 -> H1'27 | Y65: =Y51 -> H2'27 | Z65: =Z51 -> FY27 | AA65: =AA51 -> H1'28 | AB65: =AB51 -> H2'28 | ... AI65: =AI51 -> FY30
B66: Long-term | O66: ='Financial Statements'!N74 -> 325.1 | P66: ='Financial Statements'!O74 -> 691.5 | Q66: =O66 -> 325.1 | R66: ='Financial Statements'!Q74 -> 514.9 | S66: ='Financial Statements'!R74 -> 511.4 | T66: =R66 -> 514.9 | U66: ='Financial Statements'!T74 -> 562.5 | V66: =U70 -> 587.3 | W66: =T70 -> 562.5 | X66: ='Financial Statements'!W74 -> 577.3 | Y66: =X70 -> 557.3 | Z66: =W70 -> 577.3 | AA66: ='Financial Statements'!Z74 -> 547.3 | AB66: =AA70 -> 527.3 | AC66: =Z70 -> 547.3 | AD66: ='Financial Statements'!AC74 -> 517.3 | AE66: =AD70 -> 497.3 | AF66: =AC70 -> 517.3 | AG66: ='Financial Statements'!AF74 -> 487.3 | AH66: =AG70 -> 467.3 | AI66: =AF70 -> 487.3
B67: Repayment | O67: ='Financial Statements'!O120 -> -124.4 | P67: ='Financial Statements'!P120 -> -106 | Q67: ='Financial Statements'!Q120 -> -230.4 | R67: ='Financial Statements'!R120 -> -58.4 | S67: ='Financial Statements'!S120 -> -47.2 | T67: ='Financial Statements'!T120 -> -105.6 | U67: ='Financial Statements'!U120 -> -58.8 | V67: -20 | W67: =U67+V67 -> -78.8 | X67: -30 | Y67: -20 | Z67: =X67+Y67 -> -50 | AA67: -30 | AB67: -20 | AC67: =AA67+AB67 -> -50 | AD67: -30 | AE67: -20 | AF67: =AD67+AE67 -> -50 | AG67: -30 | AH67: -20 | AI67: =AG67+AH67 -> -50
B68: Drawdowns | O68: ='Financial Statements'!O119 -> 431.1 | P68: ='Financial Statements'!P119 -> -40.9 | Q68: ='Financial Statements'!Q119 -> 390.2 | R68: ='Financial Statements'!R119 -> 18.8 | S68: ='Financial Statements'!S119 -> 95.9 | T68: ='Financial Statements'!T119 -> 114.7 | U68: ='Financial Statements'!U119 -> 71.4 | V68: 10 | W68: =U68+V68 -> 81.4 | X68: 10 | Y68: 10 | Z68: =X68+Y68 -> 20 | AA68: 10 | AB68: 10 | AC68: =AA68+AB68 -> 20 | AD68: 10 | AE68: 10 | AF68: =AD68+AE68 -> 20 | AG68: 10 | AH68: 10 | AI68: =AG68+AH68 -> 20
O69: =-(O66+O67+O68-'Financial Statements'!O74) -> 59.7 | P69: =-(P66+P67+P68-'Financial Statements'!P74) -> -29.7 | Q69: =-(Q66+Q67+Q68-'Financial Statements'!Q74) -> 30 | R69: =-(R66+R67+R68-'Financial Statements'!R74) -> 36.1 | S69: =-(S66+S67+S68-'Financial Statements'!S74) -> 2.4 | T69: =-(T66+T67+T68-'Financial Statements'!T74) -> 38.5 | U69: =-(U66+U67+U68-'Financial Statements'!U74) -> 12.2 | W69: =SUM(U69:V69) -> 12.2
B70: Closing Balance | C70: ='Financial Statements'!C74 -> 521.6 | D70: ='Financial Statements'!D74 -> 452 | O70: =O66+O68+O67+O69 -> 691.5 | P70: =P66+P68+P67+P69 -> 514.9 | Q70: =Q66+Q68+Q67+Q69 -> 514.9 | R70: =R66+R68+R67+R69 -> 511.4 | S70: =S66+S68+S67+S69 -> 562.5 | T70: =T66+T68+T67+T69 -> 562.5 | U70: =U66+U68+U67+U69 -> 587.3 | V70: =V66+V68+V67+V69 -> 577.3 | ... AI70: =AI66+AI68+AI67+AI69 -> 457.3
B71: Interest Expense | C71: ='Financial Statements'!C21 -> 6.3 | D71: ='Financial Statements'!D21 -> 6.4 | O71: ='Financial Statements'!O21 -> 11.7 | P71: ='Financial Statements'!P21 -> 20 | Q71: ='Financial Statements'!Q21 -> 31.7 | R71: ='Financial Statements'!R21 -> 16.7 | S71: ='Financial Statements'!S21 -> 17 | T71: ='Financial Statements'!T21 -> 33.7 | U71: ='Financial Statements'!U21 -> 16 | V71: =V72*V70 -> 17.319 | W71: =U71+V71 -> 33.319 | X71: =X72*X70 -> 16.719 | Y71: =Y72*Y70 -> 16.419 | Z71: =X71+Y71 -> 33.138 | AA71: =AA72*AA70 -> 15.819 | AB71: =AB72*AB70 -> 15.519 | AC71: =AA71+AB71 -> 31.338 | AD71: =AD72*AD70 -> 14.919 | AE71: =AE72*AE70 -> 14.619 | AF71: =AD71+AE71 -> 29.538 | AG71: =AG72*AG70 -> 14.019 | AH71: =AH72*AH70 -> 13.719 | AI71: =AG71+AH71 -> 27.738
B72: % of debt | C72: =C71/C70 -> 0.012078221 | D72: =D71/D70 -> 0.014159292 | O72: =O71/O70 -> 0.01691974 | P72: =P71/P70 -> 0.038842494 | Q72: =Q71/Q70 -> 0.061565352 | R72: =R71/R70 -> 0.032655456 | S72: =S71/S70 -> 0.030222222 | T72: =T71/T70 -> 0.059911111 | U72: =U71/U70 -> 0.027243317 | V72: 0.03 | W72: =W71/W70 -> 0.057715226 | X72: 0.03 | Y72: 0.03 | Z72: =Z71/Z70 -> 0.060548145 | AA72: 0.03 | AB72: 0.03 | AC72: =AC71/AC70 -> 0.060579934 | AD72: 0.03 | AE72: 0.03 | AF72: =AF71/AF70 -> 0.060615637 | AG72: 0.03 | AH72: 0.03 | AI72: =AI71/AI70 -> 0.060656024

Sheet Ratio Analysis
B2: Income Statement | C2: ='Financial Statements'!C3 -> H1'20 | D2: ='Financial Statements'!D3 -> H2'20 | E2: ='Financial Statements'!E3 -> FY20 | F2: ='Financial Statements'!F3 -> H1'21 | G2: ='Financial Statements'!G3 -> H2'21 | H2: ='Financial Statements'!H3 -> FY21 | I2: ='Financial Statements'!I3 -> H1'22 | J2: ='Financial Statements'!J3 -> H2'22 | ... AI2: ='Financial Statements'!AI3 -> FY30
B4: Actvity Ratios (Utilising resources)
B6: DIO | C6: =Schedules!C60 -> 1322.4772 | D6: =Schedules!D60 -> 1448.5995 | E6: =Schedules!E60 -> 1434.8589 | F6: =Schedules!F60 -> 1653.0519 | G6: =Schedules!G60 -> 1531.0919 | H6: =Schedules!H60 -> 1650.2954 | I6: =Schedules!I60 -> 1384.4007 | J6: =Schedules!J60 -> 1388.0826 | ... AI6: =Schedules!AI60 -> 2600
B7: DSO | C7: =Schedules!C61 -> 87.186104 | D7: =Schedules!D61 -> 72.849271 | E7: =Schedules!E61 -> 71.214286 | F7: =Schedules!F61 -> 114.59204 | G7: =Schedules!G61 -> 49.798498 | H7: =Schedules!H61 -> 57.123837 | I7: =Schedules!I61 -> 80.997985 | J7: =Schedules!J61 -> 69.325944 | ... AI7: =Schedules!AI61 -> 125
B8: DPO | C8: =Schedules!C62 -> 494.70444 | D8: =Schedules!D62 -> 567.58677 | E8: =Schedules!E62 -> 562.20293 | F8: =Schedules!F62 -> 597.98127 | G8: =Schedules!G62 -> 601.25492 | H8: =Schedules!H62 -> 648.06574 | I8: =Schedules!I62 -> 549.97116 | J8: =Schedules!J62 -> 587.1104 | ... AI8: =Schedules!AI62 -> 605
B9: Cash Conversion Cycle | C9: =C6+C7-C8 -> 914.95888 | D9: =D6+D7-D8 -> 953.86204 | E9: =E6+E7-E8 -> 943.87022 | F9: =F6+F7-F8 -> 1169.6627 | G9: =G6+G7-G8 -> 979.63549 | H9: =H6+H7-H8 -> 1059.3535 | I9: =I6+I7-I8 -> 915.42752 | J9: =J6+J7-J8 -> 870.29817 | ... AI9: =AI6+AI7-AI8 -> 2120
B10: Fixed Assets Turnover | C10: ='Financial Statements'!C4/('Financial Statements'!C50+'Financial Statements'!C51) -> 1.7527601 | D10: ='Financial Statements'!D4/('Financial Statements'!D50+'Financial Statements'!D51) -> 1.5137504 | E10: ='Financial Statements'!E4/('Financial Statements'!E50+'Financial Statements'!E51) -> 3.0970082 | F10: ='Financial Statements'!F4/('Financial Statements'!F50+'Financial Statements'!F51) -> 1.3214724 | G10: ='Financial Statements'!G4/('Financial Statements'!G50+'Financial Statements'!G51) -> 1.6367232 | H10: ='Financial Statements'!H4/('Financial Statements'!H50+'Financial Statements'!H51) -> 2.8536723 | I10: ='Financial Statements'!I4/('Financial Statements'!I50+'Financial Statements'!I51) -> 1.8228814 | J10: ='Financial Statements'!J4/('Financial Statements'!J50+'Financial Statements'!J51) -> 1.7017589 | ... AI10: ='Financial Statements'!AI4/('Financial Statements'!AI50+'Financial Statements'!AI51) -> 2.10012
B11: Working Capital Turnover | C11: ='Financial Statements'!C4/('Financial Statements'!C62-'Financial Statements'!C86) -> 0.49677603 | D11: ='Financial Statements'!D4/('Financial Statements'!D62-'Financial Statements'!D86) -> 0.49761574 | E11: ='Financial Statements'!E4/('Financial Statements'!E62-'Financial Statements'!E86) -> 1.0179795 | F11: ='Financial Statements'!F4/('Financial Statements'!F62-'Financial Statements'!F86) -> 0.38228769 | G11: ='Financial Statements'!G4/('Financial Statements'!G62-'Financial Statements'!G86) -> 0.50762222 | H11: ='Financial Statements'!H4/('Financial Statements'!H62-'Financial Statements'!H86) -> 0.88505344 | I11: ='Financial Statements'!I4/('Financial Statements'!I62-'Financial Statements'!I86) -> 0.60591549 | J11: ='Financial Statements'!J4/('Financial Statements'!J62-'Financial Statements'!J86) -> 0.59137213 | ... AI11: ='Financial Statements'!AI4/('Financial Statements'!AI62-'Financial Statements'!AI86) -> 0.54210799
B12: Total Assets Turnover | C12: ='Financial Statements'!C4/'Financial Statements'!C63 -> 0.20296761 | D12: ='Financial Statements'!D4/'Financial Statements'!D63 -> 0.1796113 | E12: ='Financial Statements'!E4/'Financial Statements'!E63 -> 0.36748306 | F12: ='Financial Statements'!F4/'Financial Statements'!F63 -> 0.16466002 | G12: ='Financial Statements'!G4/'Financial Statements'!G63 -> 0.20833483 | H12: ='Financial Statements'!H4/'Financial Statements'!H63 -> 0.36323757 | I12: ='Financial Statements'!I4/'Financial Statements'!I63 -> 0.22766723 | J12: ='Financial Statements'!J4/'Financial Statements'!J63 -> 0.22413967 | ... AI12: ='Financial Statements'!AI4/'Financial Statements'!AI63 -> 0.27976066
B13: Equity Turnover | C13: ='Financial Statements'!C4/'Financial Statements'!C72 -> 0.37870464 | D13: ='Financial Statements'!D4/'Financial Statements'!D72 -> 0.35694435 | E13: ='Financial Statements'!E4/'Financial Statements'!E72 -> 0.73027863 | F13: ='Financial Statements'!F4/'Financial Statements'!F72 -> 0.29392099 | G13: ='Financial Statements'!G4/'Financial Statements'!G72 -> 0.37399948 | H13: ='Financial Statements'!H4/'Financial Statements'!H72 -> 0.65207849 | I13: ='Financial Statements'!I4/'Financial Statements'!I72 -> 0.40700095 | J13: ='Financial Statements'!J4/'Financial Statements'!J72 -> 0.40175724 | ... AI13: ='Financial Statements'!AI4/'Financial Statements'!AI72 -> 0.42951818
T14: ='Financial Statements'!T57/'Financial Statements'!T4 -> 2.1385334
B16: Liquidity Ratios
B18: Current Ratio | C18: ='Financial Statements'!C62/'Financial Statements'!C86 -> 2.7748233 | D18: ='Financial Statements'!D62/'Financial Statements'!D86 -> 2.1960551 | E18: ='Financial Statements'!E62/'Financial Statements'!E86 -> 2.1963161 | F18: ='Financial Statements'!F62/'Financial Statements'!F86 -> 2.80304 | G18: ='Financial Statements'!G62/'Financial Statements'!G86 -> 2.5857183 | H18: ='Financial Statements'!H62/'Financial Statements'!H86 -> 2.5857183 | I18: ='Financial Statements'!I62/'Financial Statements'!I86 -> 2.2675553 | J18: ='Financial Statements'!J62/'Financial Statements'!J86 -> 2.3017758 | ... AI18: ='Financial Statements'!AI62/'Financial Statements'!AI86 -> 3.3296595
B19: Quick Ratio | C19: =('Financial Statements'!C62-'Financial Statements'!C61)/'Financial Statements'!C86 -> 2.5627735 | D19: =('Financial Statements'!D62-'Financial Statements'!D61)/'Financial Statements'!D86 -> 1.8759506 | E19: =('Financial Statements'!E62-'Financial Statements'!E61)/'Financial Statements'!E86 -> 1.8761735 | F19: =('Financial Statements'!F62-'Financial Statements'!F61)/'Financial Statements'!F86 -> 2.65968 | G19: =('Financial Statements'!G62-'Financial Statements'!G61)/'Financial Statements'!G86 -> 2.306474 | H19: =('Financial Statements'!H62-'Financial Statements'!H61)/'Financial Statements'!H86 -> 2.306474 | I19: =('Financial Statements'!I62-'Financial Statements'!I61)/'Financial Statements'!I86 -> 2.1494882 | J19: =('Financial Statements'!J62-'Financial Statements'!J61)/'Financial Statements'!J86 -> 2.1676661 | ... AI19: =('Financial Statements'!AI62-'Financial Statements'!AI61)/'Financial Statements'!AI86 -> 3.6007822
B20: Cash ratio | C20: ='Financial Statements'!C61/'Financial Statements'!C86 -> 0.21204981 | D20: ='Financial Statements'!D61/'Financial Statements'!D86 -> 0.32010456 | E20: ='Financial Statements'!E61/'Financial Statements'!E86 -> 0.3201426 | F20: ='Financial Statements'!F61/'Financial Statements'!F86 -> 0.14336 | G20: ='Financial Statements'!G61/'Financial Statements'!G86 -> 0.27924423 | H20: ='Financial Statements'!H61/'Financial Statements'!H86 -> 0.27924423 | I20: ='Financial Statements'!I61/'Financial Statements'!I86 -> 0.11806713 | J20: ='Financial Statements'!J61/'Financial Statements'!J86 -> 0.13410978 | ... AI20: ='Financial Statements'!AI61/'Financial Statements'!AI86 -> -0.27112273
B21: Defensive Interval | C21: =('Financial Statements'!C61+'Financial Statements'!C58)/('Financial Statements'!C8/182.5) -> 326.41429 | D21: =('Financial Statements'!D61+'Financial Statements'!D58)/('Financial Statements'!D8/182.5) -> 339.7776 | E21: =('Financial Statements'!E61+'Financial Statements'!E58)/('Financial Statements'!E8/365) -> 370.5327 | F21: =('Financial Statements'!F61+'Financial Statements'!F58)/('Financial Statements'!F8/182.5) -> 381.19635 | G21: =('Financial Statements'!G61+'Financial Statements'!G58)/('Financial Statements'!G8/182.5) -> 241.20629 | H21: =('Financial Statements'!H61+'Financial Statements'!H58)/('Financial Statements'!H8/365) -> 295.13961 | I21: =('Financial Statements'!I61+'Financial Statements'!I58)/('Financial Statements'!I8/182.5) -> 302.02575 | J21: =('Financial Statements'!J61+'Financial Statements'!J58)/('Financial Statements'!J8/182.5) -> 202.29772 | K21: =('Financial Statements'!K61+'Financial Statements'!K58)/('Financial Statements'!K8/365) -> 238.2451 | L21: =('Financial Statements'!L61+'Financial Statements'!L58)/('Financial Statements'!L8/182.5) -> 290.29731 | M21: =('Financial Statements'!M61+'Financial Statements'!M58)/('Financial Statements'!M8/182.5) -> 168.97783 | N21: =('Financial Statements'!N61+'Financial Statements'!N58)/('Financial Statements'!N8/365) -> 185.36933 | O21: =('Financial Statements'!O61+'Financial Statements'!O58)/('Financial Statements'!O8/182.5) -> 402.78026 | P21: =('Financial Statements'!P61+'Financial Statements'!P58)/('Financial Statements'!P8/182.5) -> 237.03529 | Q21: =('Financial Statements'!Q61+'Financial Statements'!Q58)/('Financial Statements'!Q8/365) -> 221.48772 | R21: =('Financial Statements'!R61+'Financial Statements'!R58)/('Financial Statements'!R8/182.5) -> 271.46494 | S21: =('Financial Statements'!S61+'Financial Statements'!S58)/('Financial Statements'!S8/182.5) -> 207.32368 | T21: =('Financial Statements'!T61+'Financial Statements'!T58)/('Financial Statements'!T8/365) -> 206.7162 | U21: =('Financial Statements'!U61+'Financial Statements'!U58)/('Financial Statements'!U8/182.5) -> 256.62089 | V21: =('Financial Statements'!V61+'Financial Statements'!V58)/('Financial Statements'!V8/182.5) -> 179.64162 | W21: =('Financial Statements'!W61+'Financial Statements'!W58)/('Financial Statements'!W8/365) -> 164.23479 | X21: =('Financial Statements'!X61+'Financial Statements'!X58)/('Financial Statements'!X8/182.5) -> 82.761183 | Y21: =('Financial Statements'!Y61+'Financial Statements'!Y58)/('Financial Statements'!Y8/182.5) -> 101.39211 | Z21: =('Financial Statements'!Z61+'Financial Statements'!Z58)/('Financial Statements'!Z8/365) -> 101.08022 | AA21: =('Financial Statements'!AA61+'Financial Statements'!AA58)/('Financial Statements'!AA8/182.5) -> 28.371327 | AB21: =('Financial Statements'!AB61+'Financial Statements'!AB58)/('Financial Statements'!AB8/182.5) -> 91.750558 | AC21: =('Financial Statements'!AC61+'Financial Statements'!AC58)/('Financial Statements'!AC8/365) -> 91.506336 | AD21: =('Financial Statements'!AD61+'Financial Statements'!AD58)/('Financial Statements'!AD8/182.5) -> 54.107325 | AE21: =('Financial Statements'!AE61+'Financial Statements'!AE58)/('Financial Statements'!AE8/182.5) -> 118.40855 | AF21: =('Financial Statements'!AF61+'Financial Statements'!AF58)/('Financial Statements'!AF8/365) -> 118.14577 | AG21: =('Financial Statements'!AG61+'Financial Statements'!AG58)/('Financial Statements'!AG8/182.5) -> 57.033357 | AH21: =('Financial Statements'!AH61+'Financial Statements'!AH58)/('Financial Statements'!AH8/182.5) -> 116.46436 | AI21: =('Financial Statements'!AI61+'Financial Statements'!AI58)/('Financial Statements'!AI8/365) -> 116.60626
B23: Solvency Ratios
B25: Debt to Equity | C25: =('Financial Statements'!C74+'Financial Statements'!C80)/'Financial Statements'!C72 -> 0.4227989 | D25: =('Financial Statements'!D74+'Financial Statements'!D80)/'Financial Statements'!D72 -> 0.5132901 | E25: =('Financial Statements'!E74+'Financial Statements'!E80)/'Financial Statements'!E72 -> 0.5132901 | F25: =('Financial Statements'!F74+'Financial Statements'!F80)/'Financial Statements'!F72 -> 0.35266426 | G25: =('Financial Statements'!G74+'Financial Statements'!G80)/'Financial Statements'!G72 -> 0.33262329 | H25: =('Financial Statements'!H74+'Financial Statements'!H80)/'Financial Statements'!H72 -> 0.33262329 | I25: =('Financial Statements'!I74+'Financial Statements'!I80)/'Financial Statements'!I72 -> 0.25152949 | J25: =('Financial Statements'!J74+'Financial Statements'!J80)/'Financial Statements'!J72 -> 0.28260215 | ... AI25: =('Financial Statements'!AI74+'Financial Statements'!AI80)/'Financial Statements'!AI72 -> 0.23108941
B26: Debt to Capital | C26: =+('Financial Statements'!C74+'Financial Statements'!C80)/('Financial Statements'!C72+'Financial Statements'!C74+'Financial Statements'!C80) -> 0.29715999 | D26: =+('Financial Statements'!D74+'Financial Statements'!D80)/('Financial Statements'!D72+'Financial Statements'!D74+'Financial Statements'!D80) -> 0.33918817 | E26: =+('Financial Statements'!E74+'Financial Statements'!E80)/('Financial Statements'!E72+'Financial Statements'!E74+'Financial Statements'!E80) -> 0.33918817 | F26: =+('Financial Statements'!F74+'Financial Statements'!F80)/('Financial Statements'!F72+'Financial Statements'!F74+'Financial Statements'!F80) -> 0.26071825 | G26: =+('Financial Statements'!G74+'Financial Statements'!G80)/('Financial Statements'!G72+'Financial Statements'!G74+'Financial Statements'!G80) -> 0.24960039 | H26: =+('Financial Statements'!H74+'Financial Statements'!H80)/('Financial Statements'!H72+'Financial Statements'!H74+'Financial Statements'!H80) -> 0.24960039 | I26: =+('Financial Statements'!I74+'Financial Statements'!I80)/('Financial Statements'!I72+'Financial Statements'!I74+'Financial Statements'!I80) -> 0.20097767 | J26: =+('Financial Statements'!J74+'Financial Statements'!J80)/('Financial Statements'!J72+'Financial Statements'!J74+'Financial Statements'!J80) -> 0.22033501 | ... AI26: =+('Financial Statements'!AI74+'Financial Statements'!AI80)/('Financial Statements'!AI72+'Financial Statements'!AI74+'Financial Statements'!AI80) -> 0.18771131
B27: Debt to Assets | C27: =('Financial Statements'!C74+'Financial Statements'!C80)/'Financial Statements'!C63 -> 0.22660003 | D27: =('Financial Statements'!D74+'Financial Statements'!D80)/'Financial Statements'!D63 -> 0.25828313 | E27: =('Financial Statements'!E74+'Financial Statements'!E80)/'Financial Statements'!E63 -> 0.25829239 | F27: =('Financial Statements'!F74+'Financial Statements'!F80)/'Financial Statements'!F63 -> 0.19756909 | G27: =('Financial Statements'!G74+'Financial Statements'!G80)/'Financial Statements'!G63 -> 0.1852864 | H27: =('Financial Statements'!H74+'Financial Statements'!H80)/'Financial Statements'!H63 -> 0.1852864 | I27: =('Financial Statements'!I74+'Financial Statements'!I80)/'Financial Statements'!I63 -> 0.14069997 | J27: =('Financial Statements'!J74+'Financial Statements'!J80)/'Financial Statements'!J63 -> 0.15766325 | ... AI27: =('Financial Statements'!AI74+'Financial Statements'!AI80)/'Financial Statements'!AI63 -> 0.15051685
B28: Financial Leverage | C28: ='Financial Statements'!C63/'Financial Statements'!C72 -> 1.8658378 | D28: ='Financial Statements'!D63/'Financial Statements'!D72 -> 1.9873156 | E28: ='Financial Statements'!E63/'Financial Statements'!E72 -> 1.9872444 | F28: ='Financial Statements'!F63/'Financial Statements'!F72 -> 1.7850174 | G28: ='Financial Statements'!G63/'Financial Statements'!G72 -> 1.7951846 | H28: ='Financial Statements'!H63/'Financial Statements'!H72 -> 1.7951846 | I28: ='Financial Statements'!I63/'Financial Statements'!I72 -> 1.787701 | J28: ='Financial Statements'!J63/'Financial Statements'!J72 -> 1.7924415 | ... AI28: ='Financial Statements'!AI63/'Financial Statements'!AI72 -> 1.5353059
B29: Interest Coverage | R29: ='Financial Statements'!R14/'Financial Statements'!R21 -> 8.8323353 | U29: ='Financial Statements'!U14/'Financial Statements'!U21 -> 6.8375
B30: Fixed Charge coverage
B32: Profitability Ratios
B33: Gross Margin | C33: ='Financial Statements'!C7 -> 0.66482153 | D33: ='Financial Statements'!D7 -> 0.65601917 | E33: ='Financial Statements'!E7 -> 0.66051913 | F33: ='Financial Statements'!F7 -> 0.64670381 | G33: ='Financial Statements'!G7 -> 0.69295823 | H33: ='Financial Statements'!H7 -> 0.67323302 | I33: ='Financial Statements'!I7 -> 0.69099644 | J33: ='Financial Statements'!J7 -> 0.68184542 | ... AI33: ='Financial Statements'!AI7 -> 0.65
B34: COP Margin | C34: ='Financial Statements'!C12 -> 0.26398168 | D34: ='Financial Statements'!D12 -> 0.15332402 | E34: ='Financial Statements'!E12 -> 0.20989461 | F34: ='Financial Statements'!F12 -> 0.24651811 | G34: ='Financial Statements'!G12 -> 0.22402485 | H34: ='Financial Statements'!H12 -> 0.23361711 | I34: ='Financial Statements'!I12 -> 0.32992407 | J34: ='Financial Statements'!J12 -> 0.18199521 | ... AI34: ='Financial Statements'!AI12 -> 0.25
B35: EBITDA Margin | C35: ='Financial Statements'!C20 -> 0.29223134 | D35: ='Financial Statements'!D20 -> 0.15112797 | E35: ='Financial Statements'!E20 -> 0.22326308 | F35: ='Financial Statements'!F20 -> 0.28412256 | G35: ='Financial Statements'!G20 -> 0.2544011 | H35: ='Financial Statements'!H20 -> 0.26707583 | I35: ='Financial Statements'!I20 -> 0.3367426 | J35: ='Financial Statements'!J20 -> 0.21420012 | ... AI35: ='Financial Statements'!AI20 -> 0.25
B36: PBT Margin | C36: ='Financial Statements'!C24 -> 0.23554113 | D36: ='Financial Statements'!D24 -> 0.087841885 | E36: ='Financial Statements'!E24 -> 0.16334895 | F36: ='Financial Statements'!F24 -> 0.22748375 | G36: ='Financial Statements'!G24 -> 0.21263376 | H36: ='Financial Statements'!H24 -> 0.21896654 | I36: ='Financial Statements'!I24 -> 0.29738106 | J36: ='Financial Statements'!J24 -> 0.17255842 | ... AI36: ='Financial Statements'!AI24 -> 0.22620979
B37: Net Profit Margin | C37: ='Financial Statements'!C29 -> 0.16090857 | D37: ='Financial Statements'!D29 -> 0.044919146 | E37: ='Financial Statements'!E29 -> 0.10421546 | F37: ='Financial Statements'!F29 -> 0.15064995 | G37: ='Financial Statements'!G29 -> 0.13686572 | H37: ='Financial Statements'!H29 -> 0.14274401 | I37: ='Financial Statements'!I29 -> 0.20765535 | J37: ='Financial Statements'!J29 -> 0.1172858 | ... AI37: ='Financial Statements'!AI29 -> 0.16739524
B38: ROA | C38: ='Financial Statements'!C33/'Financial Statements'!C63 -> 0.035099954 | D38: ='Financial Statements'!D33/'Financial Statements'!D63 -> 0.0081038439 | E38: ='Financial Statements'!E33/'Financial Statements'!E63 -> 0.040592391 | F38: ='Financial Statements'!F33/'Financial Statements'!F63 -> 0.024806024 | G38: ='Financial Statements'!G33/'Financial Statements'!G63 -> 0.028513897 | H38: ='Financial Statements'!H33/'Financial Statements'!H63 -> 0.051849987 | I38: ='Financial Statements'!I33/'Financial Statements'!I63 -> 0.04727632 | J38: ='Financial Statements'!J33/'Financial Statements'!J63 -> 0.0262884 | ... AI38: ='Financial Statements'!AI33/'Financial Statements'!AI63 -> 0.046830603 | AL38: Reasonable
B39: RoCA | C39: ='Financial Statements'!C11/('Financial Statements'!C63-'Financial Statements'!C86) -> 0.069602416 | D39: ='Financial Statements'!D11/('Financial Statements'!D63-'Financial Statements'!D86) -> 0.039441249 | E39: ='Financial Statements'!E11/('Financial Statements'!E63-'Financial Statements'!E86) -> 0.11046631 | F39: ='Financial Statements'!F11/('Financial Statements'!F63-'Financial Statements'!F86) -> 0.053331994 | G39: ='Financial Statements'!G11/('Financial Statements'!G63-'Financial Statements'!G86) -> 0.06296997 | H39: ='Financial Statements'!H11/('Financial Statements'!H63-'Financial Statements'!H86) -> 0.11449086 | I39: ='Financial Statements'!I11/('Financial Statements'!I63-'Financial Statements'!I86) -> 0.1067596 | J39: ='Financial Statements'!J11/('Financial Statements'!J63-'Financial Statements'!J86) -> 0.057547483 | ... AI39: ='Financial Statements'!AI11/('Financial Statements'!AI63-'Financial Statements'!AI86) -> 0.089841686 | AL39: Strong return on long term capital
B40: RoE | C40: ='Financial Statements'!C33/'Financial Statements'!C72 -> 0.06549082 | D40: ='Financial Statements'!D33/'Financial Statements'!D72 -> 0.016104896 | E40: ='Financial Statements'!E33/'Financial Statements'!E72 -> 0.080666999 | F40: ='Financial Statements'!F33/'Financial Statements'!F72 -> 0.044279184 | G40: ='Financial Statements'!G33/'Financial Statements'!G72 -> 0.05118771 | H40: ='Financial Statements'!H33/'Financial Statements'!H72 -> 0.0930803 | I40: ='Financial Statements'!I33/'Financial Statements'!I72 -> 0.084515926 | J40: ='Financial Statements'!J33/'Financial Statements'!J72 -> 0.047120419 | ... AI40: ='Financial Statements'!AI33/'Financial Statements'!AI72 -> 0.071899299 | AL40: Good return with low leverage
B42: Valuation Ratios
B44: Earnings per Share | C44: ='Financial Statements'!C41 -> 1.6065451
B45: PE | C45: ='DCF '!C23/'Financial Statements'!C33 -> 0.40640177
B46: TTM EPS
B47: TTM P/E
B48: Forward EPS
B49: Forward P/E
B50: Dividend Yield
B51: Dividend Payout
B52: Retention Rate
B53: Sustainable Growth Rate
B54: BVPS
B55: OCF/share
B56: FCF/share | C56: =('Financial Statements'!C107+'Financial Statements'!C109+'Financial Statements'!C112)/('Financial Statements'!C45/1000) -> 0.095287371 | D56: =('Financial Statements'!D107+'Financial Statements'!D109+'Financial Statements'!D112)/('Financial Statements'!D45/1000) -> 0.37594712 | E56: =('Financial Statements'!E107+'Financial Statements'!E109+'Financial Statements'!E112)/('Financial Statements'!E45/1000) -> 0.47327354 | F56: =('Financial Statements'!F107+'Financial Statements'!F109+'Financial Statements'!F112)/('Financial Statements'!F45/1000) -> 0.6210929 | G56: =('Financial Statements'!G107+'Financial Statements'!G109+'Financial Statements'!G112)/('Financial Statements'!G45/1000) -> 3.0752488 | H56: =('Financial Statements'!H107+'Financial Statements'!H109+'Financial Statements'!H112)/('Financial Statements'!H45/1000) -> 3.6925779 | I56: =('Financial Statements'!I107+'Financial Statements'!I109+'Financial Statements'!I112)/('Financial Statements'!I45/1000) -> 0.5719025 | J56: =('Financial Statements'!J107+'Financial Statements'!J109+'Financial Statements'!J112)/('Financial Statements'!J45/1000) -> 1.1734661 | ... R56: =('Financial Statements'!R107+'Financial Statements'!R109+'Financial Statements'!R112)/('Financial Statements'!R45/1000) -> -0.14974328 | U56: =('Financial Statements'!U107+'Financial Statements'!U109+'Financial Statements'!U112)/('Financial Statements'!U45/1000) -> -0.3135516
B57: Net Debt/EBITDA | C57: =('Financial Statements'!C74+'Financial Statements'!C80-'Financial Statements'!C61)/'Financial Statements'!C19 -> 2.9973873 | D57: =('Financial Statements'!D74+'Financial Statements'!D80-'Financial Statements'!D61)/'Financial Statements'!D19 -> 5.9564069 | E57: =('Financial Statements'!E74+'Financial Statements'!E80-'Financial Statements'!E61)/'Financial Statements'!E19 -> 1.9707168 | F57: =('Financial Statements'!F74+'Financial Statements'!F80-'Financial Statements'!F61)/'Financial Statements'!F19 -> 3.4910131 | G57: =('Financial Statements'!G74+'Financial Statements'!G80-'Financial Statements'!G61)/'Financial Statements'!G19 -> 2.1322931 | H57: =('Financial Statements'!H74+'Financial Statements'!H80-'Financial Statements'!H61)/'Financial Statements'!H19 -> 1.164937 | I57: =('Financial Statements'!I74+'Financial Statements'!I80-'Financial Statements'!I61)/'Financial Statements'!I19 -> 1.3787391 | J57: =('Financial Statements'!J74+'Financial Statements'!J80-'Financial Statements'!J61)/'Financial Statements'!J19 -> 2.4706294 | ... U57: =('Financial Statements'!U74+'Financial Statements'!U80-'Financial Statements'!U61)/'Financial Statements'!U19 -> 5.1561562
B58: EV/EBITDA | C58: ='DCF '!$C$17/'Financial Statements'!C19 -> 8.7015622 | D58: ='DCF '!$C$17/'Financial Statements'!D19 -> 17.598536 | E58: ='DCF '!$C$17/'Financial Statements'!E19 -> 5.8225925 | F58: ='DCF '!$C$17/'Financial Statements'!F19 -> 10.884062 | G58: ='DCF '!$C$17/'Financial Statements'!G19 -> 9.0380541 | H58: ='DCF '!$C$17/'Financial Statements'!H19 -> 4.9377656 | I58: ='DCF '!$C$17/'Financial Statements'!I19 -> 6.1307371 | J58: ='DCF '!$C$17/'Financial Statements'!J19 -> 9.316148 | ... R58: ='DCF '!$C$17/'Financial Statements'!R19 -> 7.6431966 | U58: ='DCF '!$C$17/'Financial Statements'!U19 -> 10.00157
B59: FCF | C59: ='Financial Statements'!C107+'Financial Statements'!C109+'Financial Statements'!C112 -> 5 | D59: ='Financial Statements'!D107+'Financial Statements'!D109+'Financial Statements'!D112 -> 19.7 | E59: ='Financial Statements'!E107+'Financial Statements'!E109+'Financial Statements'!E112 -> 24.8 | F59: ='Financial Statements'!F107+'Financial Statements'!F109+'Financial Statements'!F112 -> 32.6 | G59: ='Financial Statements'!G107+'Financial Statements'!G109+'Financial Statements'!G112 -> 161.9 | H59: ='Financial Statements'!H107+'Financial Statements'!H109+'Financial Statements'!H112 -> 194.4 | I59: ='Financial Statements'!I107+'Financial Statements'!I109+'Financial Statements'!I112 -> 29.5 | J59: ='Financial Statements'!J107+'Financial Statements'!J109+'Financial Statements'!J112 -> 60.7 | ... U59: ='Financial Statements'!U107+'Financial Statements'!U109+'Financial Statements'!U112 -> -16.4
B60: EV/FCF | C60: ='DCF '!$C$17/'Ratio Analysis'!C59 -> 266.44183 | D60: ='DCF '!$C$17/'Ratio Analysis'!D59 -> 67.624831 | E60: ='DCF '!$C$17/'Ratio Analysis'!E59 -> 53.718112 | F60: ='DCF '!$C$17/'Ratio Analysis'!F59 -> 40.865312 | G60: ='DCF '!$C$17/'Ratio Analysis'!G59 -> 8.2285928 | H60: ='DCF '!$C$17/'Ratio Analysis'!H59 -> 6.8529278 | I60: ='DCF '!$C$17/'Ratio Analysis'!I59 -> 45.159633 | J60: ='DCF '!$C$17/'Ratio Analysis'!J59 -> 21.947433 | ... R60: ='DCF '!$C$17/'Ratio Analysis'!R59 -> -173.01418 | U60: ='DCF '!$C$17/'Ratio Analysis'!U59 -> -81.232267
B61: Net Debt | Q61: =+('Financial Statements'!Q74+'Financial Statements'!Q80-'Financial Statements'!Q61) -> 649.7 | R61: =+('Financial Statements'!R74+'Financial Statements'!R80-'Financial Statements'!R61) -> 644.3 | S61: =+('Financial Statements'!S74+'Financial Statements'!S80-'Financial Statements'!S61) -> 675.5 | T61: =+('Financial Statements'!T74+'Financial Statements'!T80-'Financial Statements'!T61) -> 675.5 | U61: =+('Financial Statements'!U74+'Financial Statements'!U80-'Financial Statements'!U61) -> 686.8 | V61: =+('Financial Statements'!V74+'Financial Statements'!V80-'Financial Statements'!V61) -> 890.04307 | W61: =+('Financial Statements'!W74+'Financial Statements'!W80-'Financial Statements'!W61) -> 889.94307
B62: Net Debt/EBITDA | Q62: =Q61/'Financial Statements'!Q19 -> 1.8234634 | R62: =R61/('Financial Statements'!R19*2) -> 1.8482501 | T62: =T61/'Financial Statements'!T19 -> 2.5224048 | U62: =U61/('Financial Statements'!U19*2) -> 2.5780781
C63: Margin Type | D63: Value | E63: Industry Benchmark | F63: Interpretation
C64: COP Margin | D64: 0.276 | E64: ~20–25% | F64: Excellent – strong pricing power & brand premium
C65: EBITDA Margin | D65: 0.313 | E65: ~25–30% | F65: Excellent – strong operating leverage
C66: PBT Margin | D66: 0.245 | E66: ~15–20% | F66: Very good – low financing costs help
C67: Net Profit Margin | D67: 0.142 | E67: ~10–12% | F67: Strong – solid bottom-line efficiency

Sheet DCF 
A3: Remy Cointreau
A4: Figures in Euro millions, except share data | C4: 2026E | D4: 2027E | E4: 2028E | F4: 2029E | G4: 2030E
A5: DCF | C5: 0.5 | D5: =+C5+1 -> 1.5 | E5: =+D5+1 -> 2.5 | F5: =+E5+1 -> 3.5 | G5: =+F5+1 -> 4.5
A6: Revenues | C6: ='Financial Statements'!W4 -> 975.82 | D6: ='Financial Statements'!Z4 -> 1015.7794 | E6: ='Financial Statements'!AC4 -> 1057.4244 | F6: ='Financial Statements'!AF4 -> 1100.8308 | G6: ='Financial Statements'!AI4 -> 1165.9416 | L6: 994.608 | M6: 1090.3315 | N6: 1195.5706 | O6: 1311.3013 | P6: 1438.6028
A7: EBIT | C7: ='Financial Statements'!W14 -> 224.055 | D7: ='Financial Statements'!Z14 -> 253.94484 | E7: ='Financial Statements'!AC14 -> 264.3561 | F7: ='Financial Statements'!AF14 -> 275.2077 | G7: ='Financial Statements'!AI14 -> 291.4854 | L7: 228.752 | M7: 272.58288 | N7: 298.89265 | O7: 327.82533 | P7: 359.6507
A8: Tax | C8: 0.25 | D8: 0.25 | E8: 0.25 | F8: 0.25 | G8: 0.25 | I8: Need to check this | L8: 0.25 | M8: 0.25 | N8: 0.25 | O8: 0.25 | P8: 0.25
A9: EBIT (1-t) | C9: =+C7*(1-C8) -> 168.04125 | D9: =+D7*(1-D8) -> 190.45863 | E9: =+E7*(1-E8) -> 198.26707 | F9: =+F7*(1-F8) -> 206.40578 | G9: =+G7*(1-G8) -> 218.61405 | L9: 171.564 | M9: 204.43716 | N9: 224.16949 | O9: 245.869 | P9: 269.73802
A10: D&A | C10: ='Financial Statements'!W93 -> 39.238 | D10: ='Financial Statements'!Z93 -> 33.557892 | E10: ='Financial Statements'!AC93 -> 35.610118 | F10: ='Financial Statements'!AF93 -> 37.746484 | G10: ='Financial Statements'!AI93 -> 39.97877 | L10: 39.238 | M10: 33.008774 | N10: 35.231739 | O10: 37.668566 | P10: 40.340509
A11: NWC changes | C11: ='Financial Statements'!W101 -> -342.00471 | D11: ='Financial Statements'!Z101 -> -208.87179 | E11: ='Financial Statements'!AC101 -> -144.92614 | F11: ='Financial Statements'!AF101 -> -113.86478 | G11: ='Financial Statements'!AI101 -> -162.68987 | L11: -226.98696 | M11: 2.4448833 | N11: -176.00732 | O11: -205.3926 | P11: -219.72584
A12: Capital expenditures | C12: ='Financial Statements'!W109 -> -43.911 | D12: ='Financial Statements'!Z109 -> -50.788968 | E12: ='Financial Statements'!AC109 -> -52.87122 | F12: ='Financial Statements'!AF109 -> -55.041541 | G12: ='Financial Statements'!AI109 -> -58.297079 | L12: -29.70016 | M12: -54.516576 | N12: -59.77853 | O12: -65.565066 | P12: -71.930139
A13: Unlevered free cash flows (UFCF) | C13: =+C9+C10+C11+C12 -> -178.63646 | D13: =+D9+D10+D11+D12 -> -35.644233 | E13: =+E9+E10+E11+E12 -> 36.079832 | F13: =+F9+F10+F11+F12 -> 75.245937 | G13: =+G9+G10+G11+G12 -> 37.605872 | L13: -45.885119 | M13: 185.37424 | N13: 23.615381 | O13: 12.579899 | P13: 18.422555
A14: Discounting factor | C14: =1/(1+$C$30)^C5 -> 0.96783896 | D14: =1/(1+$C$30)^D5 -> 0.90658662 | E14: =1/(1+$C$30)^E5 -> 0.8492108 | F14: =1/(1+$C$30)^F5 -> 0.79546616 | G14: =1/(1+$C$30)^G5 -> 0.7451229 | L14: 0.96783896 | M14: 0.90658662 | N14: 0.8492108 | O14: 0.79546616 | P14: 0.7451229
A15: FCFF | C15: =+C14*C13 -> -172.89133 | D15: =+D14*D13 -> -32.314584 | E15: =+E14*E13 -> 30.639383 | F15: =+F14*F13 -> 59.855597 | G15: =+G14*G13 -> 28.020996 | L15: -44.409406 | M15: 168.05781 | N15: 20.054437 | O15: 10.006884 | P15: 13.727068
A16: TV | G16: =+(G13*(1+C33))/(C30-C33) -> 1418.8991 | P16: 1546.9805
A17: Enterprise Value | C17: =+SUM(C15:G15)+G16 -> 1332.2092
A18: Net Debt | C18: ='Financial Statements'!Q74-'Financial Statements'!Q61 -> 421.9
A19: Minority Interest | C19: ='Financial Statements'!Q30 -> 0.4 | E19: Notes - we need to fix the MI for better valuation
A20: Equity Value | C20: =+C17+C18+C19 -> 1754.5092
A21: No. of shares | C21: ='Financial Statements'!Q45/1000 -> 51.11923
A22: Target Price | C22: =+C20/C21 -> 34.321901
A23: CMP | C23: 36.82
A24: Change(%) | C24: =+C22/C23-1 -> -0.067846242
A26: Assumptions | F26: Sensitivity Analysis
A27: Equity Risk Premium | C27: 0.06 | F27: =+C22 -> 34.321901 | G27: 0.035 | H27: 0.045 | I27: 0.055 | J27: 0.065 | K27: 0.075
A28: Risk Free rate | C28: 0.0318 | F28: 0.048 | G28: 0.048 | H28: 0.048 | I28: 0.048 | J28: 0.048 | K28: 0.048
A29: Beta | C29: 0.7 | F29: 0.058 | G29: 0.058 | H29: 0.058 | I29: 0.058 | J29: 0.058 | K29: 0.058
A30: WACC | C30: =C31*('Financial Statements'!S72/('Financial Statements'!S72+'Financial Statements'!S74))+(C32*(1-'DCF '!C8))*('Financial Statements'!S74)/('Financial Statements'!S72+'Financial Statements'!S74) -> 0.067563698 | F30: 0.068 | G30: 0.068 | H30: 0.068 | I30: 0.068 | J30: 0.068 | K30: 0.068
A31: Cost of Equity | C31: =+C28+(C29*C27) -> 0.0738 | F31: 0.078 | G31: 0.078 | H31: 0.078 | I31: 0.078 | J31: 0.078 | K31: 0.078
A32: Cost of Debt | C32: =Schedules!Q72 -> 0.061565352 | F32: 0.088 | G32: 0.088 | H32: 0.088 | I32: 0.088 | J32: 0.088 | K32: 0.088
A33: Growth rate (%) | C33: 0.04

Sheet Relative
C2: Company | D2: EV/EBITDA (x) | E2: EV/EBIT(x) | F2: P/E(x) | G2: FCF Yield(%)
C3: LVMH (Hennessy) | D3: 13.8 | E3: 19.9 | F3: 29.1 | G3: 3.27
C4: Pernod Ricard | D4: 9.68 | E4: 11.2 | F4: 12.4 | G4: 4.26
C5: Diageo | D5: 10.9 | E5: 12.3 | F5: 13.4 | G5: 4.54
C6: Campari | D6: 12.2 | E6: 14.9 | F6: 19.7 | G6: 2.6
C7: Brown-Forman | D7: 13.8 | E7: 14.9 | F7: 18.9 | G7: 4.56
C8: Peer Median | D8: 12.2 | E8: 14.9 | F8: 18.9 | G8: 4.26
C9: Rémy Cointreau | D9: 12.3 | E9: 15.8 | F9: 21.5 | G9: 3.16
C14: Implied EV/EBITDA | D14: =D8 -> 12.2
C15: EBITDA FY26E | D15: ='Financial Statements'!W19 -> 223.355
C16: EV | D16: =D14*D15 -> 2724.931
C17: Market Cap | D17: =D16-'Ratio Analysis'!U61 -> 2038.131
C18: TP | D18: =D17/'Financial Statements'!U45*1000 -> 38.967027
C19: CMP | D19: 36.94
C20: Upside | D20: =D18/D19-1 -> 0.054873502

Sheet Football Field
A1: Method | B1: Low | C1: Range
A2: DCF – Bear | B2: 32 | C2: 4
A3: DCF – Base | B3: 36 | C3: 2
A4: EV/EBITDA Multiple | B4: 37 | C4: 4
A5: EV/EBIT Multiple | B5: 35 | C5: 5
A6: P/E Multiple | B6: 34 | C6: 5
A7: Current Price (CMP) | B7: 37 | C7: 0.1
